Workbook

Sheet P&G-SL
D1: 202601 | E1: 202602 | F1: 202603 | G1: 202604 | H1: 202605 | I1: 202606 | J1: 202607 | K1: 202608 | L1: 202609 | M1: 202610 | N1: 202611 | O1: 202612 | P1: TOTAL
A2: P&G SL 2026 | D2: Enero | E2: Febrero | F2: Marzo | G2: Abril | H2: Mayo | I2: Junio | J2: Julio | K2: Agosto | L2: Septiembre | M2: Octubre | N2: Noviembre | O2: Diciembre | P2: Total
A3: Shopify daily average | Actualizado: 31/07/2026 12:25 h | D3: =IFERROR(IF(DATE(VALUE(LEFT(D$1,4)),VALUE(RIGHT(D$1,2)),1)>TODAY(),"",IF(EOMONTH(DATE(VALUE(LEFT(D$1,4)),VALUE(RIGHT(D$1,2)),1),0)<TODAY(),D6/DAY(EOMONTH(DATE(VALUE(LEFT(D$1,4)),VALUE(RIGHT(D$1,2)),1),0)),D6/MAX(NOW()-DATE(VALUE(LEFT(D$1,4)),VALUE(RIGHT(D$1,2)),1),1/24))),"") | E3: =IFERROR(IF(DATE(VALUE(LEFT(E$1,4)),VALUE(RIGHT(E$1,2)),1)>TODAY(),"",IF(EOMONTH(DATE(VALUE(LEFT(E$1,4)),VALUE(RIGHT(E$1,2)),1),0)<TODAY(),E6/DAY(EOMONTH(DATE(VALUE(LEFT(E$1,4)),VALUE(RIGHT(E$1,2)),1),0)),E6/MAX(NOW()-DATE(VALUE(LEFT(E$1,4)),VALUE(RIGHT(E$1,2)),1),1/24))),"") | F3: =IFERROR(IF(DATE(VALUE(LEFT(F$1,4)),VALUE(RIGHT(F$1,2)),1)>TODAY(),"",IF(EOMONTH(DATE(VALUE(LEFT(F$1,4)),VALUE(RIGHT(F$1,2)),1),0)<TODAY(),F6/DAY(EOMONTH(DATE(VALUE(LEFT(F$1,4)),VALUE(RIGHT(F$1,2)),1),0)),F6/MAX(NOW()-DATE(VALUE(LEFT(F$1,4)),VALUE(RIGHT(F$1,2)),1),1/24))),"") | G3: =IFERROR(IF(DATE(VALUE(LEFT(G$1,4)),VALUE(RIGHT(G$1,2)),1)>TODAY(),"",IF(EOMONTH(DATE(VALUE(LEFT(G$1,4)),VALUE(RIGHT(G$1,2)),1),0)<TODAY(),G6/DAY(EOMONTH(DATE(VALUE(LEFT(G$1,4)),VALUE(RIGHT(G$1,2)),1),0)),G6/MAX(NOW()-DATE(VALUE(LEFT(G$1,4)),VALUE(RIGHT(G$1,2)),1),1/24))),"") | H3: =IFERROR(IF(DATE(VALUE(LEFT(H$1,4)),VALUE(RIGHT(H$1,2)),1)>TODAY(),"",IF(EOMONTH(DATE(VALUE(LEFT(H$1,4)),VALUE(RIGHT(H$1,2)),1),0)<TODAY(),H6/DAY(EOMONTH(DATE(VALUE(LEFT(H$1,4)),VALUE(RIGHT(H$1,2)),1),0)),H6/MAX(NOW()-DATE(VALUE(LEFT(H$1,4)),VALUE(RIGHT(H$1,2)),1),1/24))),"") | I3: =IFERROR(IF(DATE(VALUE(LEFT(I$1,4)),VALUE(RIGHT(I$1,2)),1)>TODAY(),"",IF(EOMONTH(DATE(VALUE(LEFT(I$1,4)),VALUE(RIGHT(I$1,2)),1),0)<TODAY(),I6/DAY(EOMONTH(DATE(VALUE(LEFT(I$1,4)),VALUE(RIGHT(I$1,2)),1),0)),I6/MAX(NOW()-DATE(VALUE(LEFT(I$1,4)),VALUE(RIGHT(I$1,2)),1),1/24))),"") | J3: =IFERROR(IF(DATE(VALUE(LEFT(J$1,4)),VALUE(RIGHT(J$1,2)),1)>TODAY(),"",IF(EOMONTH(DATE(VALUE(LEFT(J$1,4)),VALUE(RIGHT(J$1,2)),1),0)<TODAY(),J6/DAY(EOMONTH(DATE(VALUE(LEFT(J$1,4)),VALUE(RIGHT(J$1,2)),1),0)),J6/MAX(NOW()-DATE(VALUE(LEFT(J$1,4)),VALUE(RIGHT(J$1,2)),1),1/24))),"") | K3: =IFERROR(IF(DATE(VALUE(LEFT(K$1,4)),VALUE(RIGHT(K$1,2)),1)>TODAY(),"",IF(EOMONTH(DATE(VALUE(LEFT(K$1,4)),VALUE(RIGHT(K$1,2)),1),0)<TODAY(),K6/DAY(EOMONTH(DATE(VALUE(LEFT(K$1,4)),VALUE(RIGHT(K$1,2)),1),0)),K6/MAX(NOW()-DATE(VALUE(LEFT(K$1,4)),VALUE(RIGHT(K$1,2)),1),1/24))),"") | ... O3: =IFERROR(IF(DATE(VALUE(LEFT(O$1,4)),VALUE(RIGHT(O$1,2)),1)>TODAY(),"",IF(EOMONTH(DATE(VALUE(LEFT(O$1,4)),VALUE(RIGHT(O$1,2)),1),0)<TODAY(),O6/DAY(EOMONTH(DATE(VALUE(LEFT(O$1,4)),VALUE(RIGHT(O$1,2)),1),0)),O6/MAX(NOW()-DATE(VALUE(LEFT(O$1,4)),VALUE(RIGHT(O$1,2)),1),1/24))),"")
A4: Turnover | D4: =D5+D45+D50 | E4: =E5+E45+E50 | F4: =F5+F45+F50 | G4: =G5+G45+G50 | H4: =H5+H45+H50 | I4: =I5+I45+I50 | J4: =J5+J45+J50 | K4: =K5+K45+K50 | ... O4: =O5+O45+O50 | P4: =SUM(D4:O4)
A5: Product sales | B5: Product sales | D5: =D6+D35+D40+D42 | E5: =E6+E35+E40+E42 | F5: =F6+F35+F40+F42 | G5: =G6+G35+G40+G42 | H5: =H6+H35+H40+H42 | I5: =I6+I35+I40+I42 | J5: =J6+J35+J40+J42 | K5: =K6+K35+K40+K42 | ... O5: =O6+O35+O40+O42 | P5: =SUM(D5:O5)
A6: Shopify | C6: Shopify | D6: =D7+D9+D11+D13+D15+D17+D19+D21+D23+D25+D27+D29+D31+D33 | E6: =E7+E9+E11+E13+E15+E17+E19+E21+E23+E25+E27+E29+E31+E33 | F6: =F7+F9+F11+F13+F15+F17+F19+F21+F23+F25+F27+F29+F31+F33 | G6: =G7+G9+G11+G13+G15+G17+G19+G21+G23+G25+G27+G29+G31+G33 | H6: =H7+H9+H11+H13+H15+H17+H19+H21+H23+H25+H27+H29+H31+H33 | I6: =I7+I9+I11+I13+I15+I17+I19+I21+I23+I25+I27+I29+I31+I33 | J6: =J7+J9+J11+J13+J15+J17+J19+J21+J23+J25+J27+J29+J31+J33 | K6: =K7+K9+K11+K13+K15+K17+K19+K21+K23+K25+K27+K29+K31+K33 | ... O6: =O7+O9+O11+O13+O15+O17+O19+O21+O23+O25+O27+O29+O31+O33 | P6: =SUM(D6:O6) | Q6: ->
A7: ES | C7: ES | D7: =SUMIFS('i-shopify-sl'!$I:$I,'i-shopify-sl'!$A:$A,D$1,'i-shopify-sl'!$C:$C,$C7) | E7: =SUMIFS('i-shopify-sl'!$I:$I,'i-shopify-sl'!$A:$A,E$1,'i-shopify-sl'!$C:$C,$C7) | F7: =SUMIFS('i-shopify-sl'!$I:$I,'i-shopify-sl'!$A:$A,F$1,'i-shopify-sl'!$C:$C,$C7) | G7: =SUMIFS('i-shopify-sl'!$I:$I,'i-shopify-sl'!$A:$A,G$1,'i-shopify-sl'!$C:$C,$C7) | H7: =SUMIFS('i-shopify-sl'!$I:$I,'i-shopify-sl'!$A:$A,H$1,'i-shopify-sl'!$C:$C,$C7) | I7: =SUMIFS('i-shopify-sl'!$I:$I,'i-shopify-sl'!$A:$A,I$1,'i-shopify-sl'!$C:$C,$C7) | J7: =SUMIFS('i-shopify-sl'!$I:$I,'i-shopify-sl'!$A:$A,J$1,'i-shopify-sl'!$C:$C,$C7) | K7: =SUMIFS('i-shopify-sl'!$I:$I,'i-shopify-sl'!$A:$A,K$1,'i-shopify-sl'!$C:$C,$C7) | ... O7: =SUMIFS('i-shopify-sl'!$I:$I,'i-shopify-sl'!$A:$A,O$1,'i-shopify-sl'!$C:$C,$C7) | P7: =SUM(D7:O7) | Q7: ->
A8: avg/day | C8: avg/day | D8: =IFERROR(IF(DATE(VALUE(LEFT(D$1,4)),VALUE(RIGHT(D$1,2)),1)>TODAY(),"",IF(EOMONTH(DATE(VALUE(LEFT(D$1,4)),VALUE(RIGHT(D$1,2)),1),0)<TODAY(),D7/DAY(EOMONTH(DATE(VALUE(LEFT(D$1,4)),VALUE(RIGHT(D$1,2)),1),0)),D7/MAX(NOW()-DATE(VALUE(LEFT(D$1,4)),VALUE(RIGHT(D$1,2)),1),1/24))),"") | E8: =IFERROR(IF(DATE(VALUE(LEFT(E$1,4)),VALUE(RIGHT(E$1,2)),1)>TODAY(),"",IF(EOMONTH(DATE(VALUE(LEFT(E$1,4)),VALUE(RIGHT(E$1,2)),1),0)<TODAY(),E7/DAY(EOMONTH(DATE(VALUE(LEFT(E$1,4)),VALUE(RIGHT(E$1,2)),1),0)),E7/MAX(NOW()-DATE(VALUE(LEFT(E$1,4)),VALUE(RIGHT(E$1,2)),1),1/24))),"") | F8: =IFERROR(IF(DATE(VALUE(LEFT(F$1,4)),VALUE(RIGHT(F$1,2)),1)>TODAY(),"",IF(EOMONTH(DATE(VALUE(LEFT(F$1,4)),VALUE(RIGHT(F$1,2)),1),0)<TODAY(),F7/DAY(EOMONTH(DATE(VALUE(LEFT(F$1,4)),VALUE(RIGHT(F$1,2)),1),0)),F7/MAX(NOW()-DATE(VALUE(LEFT(F$1,4)),VALUE(RIGHT(F$1,2)),1),1/24))),"") | G8: =IFERROR(IF(DATE(VALUE(LEFT(G$1,4)),VALUE(RIGHT(G$1,2)),1)>TODAY(),"",IF(EOMONTH(DATE(VALUE(LEFT(G$1,4)),VALUE(RIGHT(G$1,2)),1),0)<TODAY(),G7/DAY(EOMONTH(DATE(VALUE(LEFT(G$1,4)),VALUE(RIGHT(G$1,2)),1),0)),G7/MAX(NOW()-DATE(VALUE(LEFT(G$1,4)),VALUE(RIGHT(G$1,2)),1),1/24))),"") | H8: =IFERROR(IF(DATE(VALUE(LEFT(H$1,4)),VALUE(RIGHT(H$1,2)),1)>TODAY(),"",IF(EOMONTH(DATE(VALUE(LEFT(H$1,4)),VALUE(RIGHT(H$1,2)),1),0)<TODAY(),H7/DAY(EOMONTH(DATE(VALUE(LEFT(H$1,4)),VALUE(RIGHT(H$1,2)),1),0)),H7/MAX(NOW()-DATE(VALUE(LEFT(H$1,4)),VALUE(RIGHT(H$1,2)),1),1/24))),"") | I8: =IFERROR(IF(DATE(VALUE(LEFT(I$1,4)),VALUE(RIGHT(I$1,2)),1)>TODAY(),"",IF(EOMONTH(DATE(VALUE(LEFT(I$1,4)),VALUE(RIGHT(I$1,2)),1),0)<TODAY(),I7/DAY(EOMONTH(DATE(VALUE(LEFT(I$1,4)),VALUE(RIGHT(I$1,2)),1),0)),I7/MAX(NOW()-DATE(VALUE(LEFT(I$1,4)),VALUE(RIGHT(I$1,2)),1),1/24))),"") | J8: =IFERROR(IF(DATE(VALUE(LEFT(J$1,4)),VALUE(RIGHT(J$1,2)),1)>TODAY(),"",IF(EOMONTH(DATE(VALUE(LEFT(J$1,4)),VALUE(RIGHT(J$1,2)),1),0)<TODAY(),J7/DAY(EOMONTH(DATE(VALUE(LEFT(J$1,4)),VALUE(RIGHT(J$1,2)),1),0)),J7/MAX(NOW()-DATE(VALUE(LEFT(J$1,4)),VALUE(RIGHT(J$1,2)),1),1/24))),"") | K8: =IFERROR(IF(DATE(VALUE(LEFT(K$1,4)),VALUE(RIGHT(K$1,2)),1)>TODAY(),"",IF(EOMONTH(DATE(VALUE(LEFT(K$1,4)),VALUE(RIGHT(K$1,2)),1),0)<TODAY(),K7/DAY(EOMONTH(DATE(VALUE(LEFT(K$1,4)),VALUE(RIGHT(K$1,2)),1),0)),K7/MAX(NOW()-DATE(VALUE(LEFT(K$1,4)),VALUE(RIGHT(K$1,2)),1),1/24))),"") | ... O8: =IFERROR(IF(DATE(VALUE(LEFT(O$1,4)),VALUE(RIGHT(O$1,2)),1)>TODAY(),"",IF(EOMONTH(DATE(VALUE(LEFT(O$1,4)),VALUE(RIGHT(O$1,2)),1),0)<TODAY(),O7/DAY(EOMONTH(DATE(VALUE(LEFT(O$1,4)),VALUE(RIGHT(O$1,2)),1),0)),O7/MAX(NOW()-DATE(VALUE(LEFT(O$1,4)),VALUE(RIGHT(O$1,2)),1),1/24))),"") | P8: =SUM(D8:O8)
A9: FR | C9: FR | D9: =SUMIFS('i-shopify-sl'!$I:$I,'i-shopify-sl'!$A:$A,D$1,'i-shopify-sl'!$C:$C,$C9) | E9: =SUMIFS('i-shopify-sl'!$I:$I,'i-shopify-sl'!$A:$A,E$1,'i-shopify-sl'!$C:$C,$C9) | F9: =SUMIFS('i-shopify-sl'!$I:$I,'i-shopify-sl'!$A:$A,F$1,'i-shopify-sl'!$C:$C,$C9) | G9: =SUMIFS('i-shopify-sl'!$I:$I,'i-shopify-sl'!$A:$A,G$1,'i-shopify-sl'!$C:$C,$C9) | H9: =SUMIFS('i-shopify-sl'!$I:$I,'i-shopify-sl'!$A:$A,H$1,'i-shopify-sl'!$C:$C,$C9) | I9: =SUMIFS('i-shopify-sl'!$I:$I,'i-shopify-sl'!$A:$A,I$1,'i-shopify-sl'!$C:$C,$C9) | J9: =SUMIFS('i-shopify-sl'!$I:$I,'i-shopify-sl'!$A:$A,J$1,'i-shopify-sl'!$C:$C,$C9) | K9: =SUMIFS('i-shopify-sl'!$I:$I,'i-shopify-sl'!$A:$A,K$1,'i-shopify-sl'!$C:$C,$C9) | ... O9: =SUMIFS('i-shopify-sl'!$I:$I,'i-shopify-sl'!$A:$A,O$1,'i-shopify-sl'!$C:$C,$C9) | P9: =SUM(D9:O9) | Q9: ->
A10: avg/day | C10: avg/day | D10: =IFERROR(IF(DATE(VALUE(LEFT(D$1,4)),VALUE(RIGHT(D$1,2)),1)>TODAY(),"",IF(EOMONTH(DATE(VALUE(LEFT(D$1,4)),VALUE(RIGHT(D$1,2)),1),0)<TODAY(),D9/DAY(EOMONTH(DATE(VALUE(LEFT(D$1,4)),VALUE(RIGHT(D$1,2)),1),0)),D9/MAX(NOW()-DATE(VALUE(LEFT(D$1,4)),VALUE(RIGHT(D$1,2)),1),1/24))),"") | E10: =IFERROR(IF(DATE(VALUE(LEFT(E$1,4)),VALUE(RIGHT(E$1,2)),1)>TODAY(),"",IF(EOMONTH(DATE(VALUE(LEFT(E$1,4)),VALUE(RIGHT(E$1,2)),1),0)<TODAY(),E9/DAY(EOMONTH(DATE(VALUE(LEFT(E$1,4)),VALUE(RIGHT(E$1,2)),1),0)),E9/MAX(NOW()-DATE(VALUE(LEFT(E$1,4)),VALUE(RIGHT(E$1,2)),1),1/24))),"") | F10: =IFERROR(IF(DATE(VALUE(LEFT(F$1,4)),VALUE(RIGHT(F$1,2)),1)>TODAY(),"",IF(EOMONTH(DATE(VALUE(LEFT(F$1,4)),VALUE(RIGHT(F$1,2)),1),0)<TODAY(),F9/DAY(EOMONTH(DATE(VALUE(LEFT(F$1,4)),VALUE(RIGHT(F$1,2)),1),0)),F9/MAX(NOW()-DATE(VALUE(LEFT(F$1,4)),VALUE(RIGHT(F$1,2)),1),1/24))),"") | G10: =IFERROR(IF(DATE(VALUE(LEFT(G$1,4)),VALUE(RIGHT(G$1,2)),1)>TODAY(),"",IF(EOMONTH(DATE(VALUE(LEFT(G$1,4)),VALUE(RIGHT(G$1,2)),1),0)<TODAY(),G9/DAY(EOMONTH(DATE(VALUE(LEFT(G$1,4)),VALUE(RIGHT(G$1,2)),1),0)),G9/MAX(NOW()-DATE(VALUE(LEFT(G$1,4)),VALUE(RIGHT(G$1,2)),1),1/24))),"") | H10: =IFERROR(IF(DATE(VALUE(LEFT(H$1,4)),VALUE(RIGHT(H$1,2)),1)>TODAY(),"",IF(EOMONTH(DATE(VALUE(LEFT(H$1,4)),VALUE(RIGHT(H$1,2)),1),0)<TODAY(),H9/DAY(EOMONTH(DATE(VALUE(LEFT(H$1,4)),VALUE(RIGHT(H$1,2)),1),0)),H9/MAX(NOW()-DATE(VALUE(LEFT(H$1,4)),VALUE(RIGHT(H$1,2)),1),1/24))),"") | I10: =IFERROR(IF(DATE(VALUE(LEFT(I$1,4)),VALUE(RIGHT(I$1,2)),1)>TODAY(),"",IF(EOMONTH(DATE(VALUE(LEFT(I$1,4)),VALUE(RIGHT(I$1,2)),1),0)<TODAY(),I9/DAY(EOMONTH(DATE(VALUE(LEFT(I$1,4)),VALUE(RIGHT(I$1,2)),1),0)),I9/MAX(NOW()-DATE(VALUE(LEFT(I$1,4)),VALUE(RIGHT(I$1,2)),1),1/24))),"") | J10: =IFERROR(IF(DATE(VALUE(LEFT(J$1,4)),VALUE(RIGHT(J$1,2)),1)>TODAY(),"",IF(EOMONTH(DATE(VALUE(LEFT(J$1,4)),VALUE(RIGHT(J$1,2)),1),0)<TODAY(),J9/DAY(EOMONTH(DATE(VALUE(LEFT(J$1,4)),VALUE(RIGHT(J$1,2)),1),0)),J9/MAX(NOW()-DATE(VALUE(LEFT(J$1,4)),VALUE(RIGHT(J$1,2)),1),1/24))),"") | K10: =IFERROR(IF(DATE(VALUE(LEFT(K$1,4)),VALUE(RIGHT(K$1,2)),1)>TODAY(),"",IF(EOMONTH(DATE(VALUE(LEFT(K$1,4)),VALUE(RIGHT(K$1,2)),1),0)<TODAY(),K9/DAY(EOMONTH(DATE(VALUE(LEFT(K$1,4)),VALUE(RIGHT(K$1,2)),1),0)),K9/MAX(NOW()-DATE(VALUE(LEFT(K$1,4)),VALUE(RIGHT(K$1,2)),1),1/24))),"") | ... O10: =IFERROR(IF(DATE(VALUE(LEFT(O$1,4)),VALUE(RIGHT(O$1,2)),1)>TODAY(),"",IF(EOMONTH(DATE(VALUE(LEFT(O$1,4)),VALUE(RIGHT(O$1,2)),1),0)<TODAY(),O9/DAY(EOMONTH(DATE(VALUE(LEFT(O$1,4)),VALUE(RIGHT(O$1,2)),1),0)),O9/MAX(NOW()-DATE(VALUE(LEFT(O$1,4)),VALUE(RIGHT(O$1,2)),1),1/24))),"") | P10: =SUM(D10:O10)
A11: DE | C11: DE | D11: =SUMIFS('i-shopify-sl'!$I:$I,'i-shopify-sl'!$A:$A,D$1,'i-shopify-sl'!$C:$C,$C11) | E11: =SUMIFS('i-shopify-sl'!$I:$I,'i-shopify-sl'!$A:$A,E$1,'i-shopify-sl'!$C:$C,$C11) | F11: =SUMIFS('i-shopify-sl'!$I:$I,'i-shopify-sl'!$A:$A,F$1,'i-shopify-sl'!$C:$C,$C11) | G11: =SUMIFS('i-shopify-sl'!$I:$I,'i-shopify-sl'!$A:$A,G$1,'i-shopify-sl'!$C:$C,$C11) | H11: =SUMIFS('i-shopify-sl'!$I:$I,'i-shopify-sl'!$A:$A,H$1,'i-shopify-sl'!$C:$C,$C11) | I11: =SUMIFS('i-shopify-sl'!$I:$I,'i-shopify-sl'!$A:$A,I$1,'i-shopify-sl'!$C:$C,$C11) | J11: =SUMIFS('i-shopify-sl'!$I:$I,'i-shopify-sl'!$A:$A,J$1,'i-shopify-sl'!$C:$C,$C11) | K11: =SUMIFS('i-shopify-sl'!$I:$I,'i-shopify-sl'!$A:$A,K$1,'i-shopify-sl'!$C:$C,$C11) | ... O11: =SUMIFS('i-shopify-sl'!$I:$I,'i-shopify-sl'!$A:$A,O$1,'i-shopify-sl'!$C:$C,$C11) | P11: =SUM(D11:O11) | Q11: ->
A12: avg/day | C12: avg/day | D12: =IFERROR(IF(DATE(VALUE(LEFT(D$1,4)),VALUE(RIGHT(D$1,2)),1)>TODAY(),"",IF(EOMONTH(DATE(VALUE(LEFT(D$1,4)),VALUE(RIGHT(D$1,2)),1),0)<TODAY(),D11/DAY(EOMONTH(DATE(VALUE(LEFT(D$1,4)),VALUE(RIGHT(D$1,2)),1),0)),D11/MAX(NOW()-DATE(VALUE(LEFT(D$1,4)),VALUE(RIGHT(D$1,2)),1),1/24))),"") | E12: =IFERROR(IF(DATE(VALUE(LEFT(E$1,4)),VALUE(RIGHT(E$1,2)),1)>TODAY(),"",IF(EOMONTH(DATE(VALUE(LEFT(E$1,4)),VALUE(RIGHT(E$1,2)),1),0)<TODAY(),E11/DAY(EOMONTH(DATE(VALUE(LEFT(E$1,4)),VALUE(RIGHT(E$1,2)),1),0)),E11/MAX(NOW()-DATE(VALUE(LEFT(E$1,4)),VALUE(RIGHT(E$1,2)),1),1/24))),"") | F12: =IFERROR(IF(DATE(VALUE(LEFT(F$1,4)),VALUE(RIGHT(F$1,2)),1)>TODAY(),"",IF(EOMONTH(DATE(VALUE(LEFT(F$1,4)),VALUE(RIGHT(F$1,2)),1),0)<TODAY(),F11/DAY(EOMONTH(DATE(VALUE(LEFT(F$1,4)),VALUE(RIGHT(F$1,2)),1),0)),F11/MAX(NOW()-DATE(VALUE(LEFT(F$1,4)),VALUE(RIGHT(F$1,2)),1),1/24))),"") | G12: =IFERROR(IF(DATE(VALUE(LEFT(G$1,4)),VALUE(RIGHT(G$1,2)),1)>TODAY(),"",IF(EOMONTH(DATE(VALUE(LEFT(G$1,4)),VALUE(RIGHT(G$1,2)),1),0)<TODAY(),G11/DAY(EOMONTH(DATE(VALUE(LEFT(G$1,4)),VALUE(RIGHT(G$1,2)),1),0)),G11/MAX(NOW()-DATE(VALUE(LEFT(G$1,4)),VALUE(RIGHT(G$1,2)),1),1/24))),"") | H12: =IFERROR(IF(DATE(VALUE(LEFT(H$1,4)),VALUE(RIGHT(H$1,2)),1)>TODAY(),"",IF(EOMONTH(DATE(VALUE(LEFT(H$1,4)),VALUE(RIGHT(H$1,2)),1),0)<TODAY(),H11/DAY(EOMONTH(DATE(VALUE(LEFT(H$1,4)),VALUE(RIGHT(H$1,2)),1),0)),H11/MAX(NOW()-DATE(VALUE(LEFT(H$1,4)),VALUE(RIGHT(H$1,2)),1),1/24))),"") | I12: =IFERROR(IF(DATE(VALUE(LEFT(I$1,4)),VALUE(RIGHT(I$1,2)),1)>TODAY(),"",IF(EOMONTH(DATE(VALUE(LEFT(I$1,4)),VALUE(RIGHT(I$1,2)),1),0)<TODAY(),I11/DAY(EOMONTH(DATE(VALUE(LEFT(I$1,4)),VALUE(RIGHT(I$1,2)),1),0)),I11/MAX(NOW()-DATE(VALUE(LEFT(I$1,4)),VALUE(RIGHT(I$1,2)),1),1/24))),"") | J12: =IFERROR(IF(DATE(VALUE(LEFT(J$1,4)),VALUE(RIGHT(J$1,2)),1)>TODAY(),"",IF(EOMONTH(DATE(VALUE(LEFT(J$1,4)),VALUE(RIGHT(J$1,2)),1),0)<TODAY(),J11/DAY(EOMONTH(DATE(VALUE(LEFT(J$1,4)),VALUE(RIGHT(J$1,2)),1),0)),J11/MAX(NOW()-DATE(VALUE(LEFT(J$1,4)),VALUE(RIGHT(J$1,2)),1),1/24))),"") | K12: =IFERROR(IF(DATE(VALUE(LEFT(K$1,4)),VALUE(RIGHT(K$1,2)),1)>TODAY(),"",IF(EOMONTH(DATE(VALUE(LEFT(K$1,4)),VALUE(RIGHT(K$1,2)),1),0)<TODAY(),K11/DAY(EOMONTH(DATE(VALUE(LEFT(K$1,4)),VALUE(RIGHT(K$1,2)),1),0)),K11/MAX(NOW()-DATE(VALUE(LEFT(K$1,4)),VALUE(RIGHT(K$1,2)),1),1/24))),"") | ... O12: =IFERROR(IF(DATE(VALUE(LEFT(O$1,4)),VALUE(RIGHT(O$1,2)),1)>TODAY(),"",IF(EOMONTH(DATE(VALUE(LEFT(O$1,4)),VALUE(RIGHT(O$1,2)),1),0)<TODAY(),O11/DAY(EOMONTH(DATE(VALUE(LEFT(O$1,4)),VALUE(RIGHT(O$1,2)),1),0)),O11/MAX(NOW()-DATE(VALUE(LEFT(O$1,4)),VALUE(RIGHT(O$1,2)),1),1/24))),"") | P12: =SUM(D12:O12)
A13: IT | C13: IT | D13: =SUMIFS('i-shopify-sl'!$I:$I,'i-shopify-sl'!$A:$A,D$1,'i-shopify-sl'!$C:$C,$C13) | E13: =SUMIFS('i-shopify-sl'!$I:$I,'i-shopify-sl'!$A:$A,E$1,'i-shopify-sl'!$C:$C,$C13) | F13: =SUMIFS('i-shopify-sl'!$I:$I,'i-shopify-sl'!$A:$A,F$1,'i-shopify-sl'!$C:$C,$C13) | G13: =SUMIFS('i-shopify-sl'!$I:$I,'i-shopify-sl'!$A:$A,G$1,'i-shopify-sl'!$C:$C,$C13) | H13: =SUMIFS('i-shopify-sl'!$I:$I,'i-shopify-sl'!$A:$A,H$1,'i-shopify-sl'!$C:$C,$C13) | I13: =SUMIFS('i-shopify-sl'!$I:$I,'i-shopify-sl'!$A:$A,I$1,'i-shopify-sl'!$C:$C,$C13) | J13: =SUMIFS('i-shopify-sl'!$I:$I,'i-shopify-sl'!$A:$A,J$1,'i-shopify-sl'!$C:$C,$C13) | K13: =SUMIFS('i-shopify-sl'!$I:$I,'i-shopify-sl'!$A:$A,K$1,'i-shopify-sl'!$C:$C,$C13) | ... O13: =SUMIFS('i-shopify-sl'!$I:$I,'i-shopify-sl'!$A:$A,O$1,'i-shopify-sl'!$C:$C,$C13) | P13: =SUM(D13:O13) | Q13: ->
A14: avg/day | C14: avg/day | D14: =IFERROR(IF(DATE(VALUE(LEFT(D$1,4)),VALUE(RIGHT(D$1,2)),1)>TODAY(),"",IF(EOMONTH(DATE(VALUE(LEFT(D$1,4)),VALUE(RIGHT(D$1,2)),1),0)<TODAY(),D13/DAY(EOMONTH(DATE(VALUE(LEFT(D$1,4)),VALUE(RIGHT(D$1,2)),1),0)),D13/MAX(NOW()-DATE(VALUE(LEFT(D$1,4)),VALUE(RIGHT(D$1,2)),1),1/24))),"") | E14: =IFERROR(IF(DATE(VALUE(LEFT(E$1,4)),VALUE(RIGHT(E$1,2)),1)>TODAY(),"",IF(EOMONTH(DATE(VALUE(LEFT(E$1,4)),VALUE(RIGHT(E$1,2)),1),0)<TODAY(),E13/DAY(EOMONTH(DATE(VALUE(LEFT(E$1,4)),VALUE(RIGHT(E$1,2)),1),0)),E13/MAX(NOW()-DATE(VALUE(LEFT(E$1,4)),VALUE(RIGHT(E$1,2)),1),1/24))),"") | F14: =IFERROR(IF(DATE(VALUE(LEFT(F$1,4)),VALUE(RIGHT(F$1,2)),1)>TODAY(),"",IF(EOMONTH(DATE(VALUE(LEFT(F$1,4)),VALUE(RIGHT(F$1,2)),1),0)<TODAY(),F13/DAY(EOMONTH(DATE(VALUE(LEFT(F$1,4)),VALUE(RIGHT(F$1,2)),1),0)),F13/MAX(NOW()-DATE(VALUE(LEFT(F$1,4)),VALUE(RIGHT(F$1,2)),1),1/24))),"") | G14: =IFERROR(IF(DATE(VALUE(LEFT(G$1,4)),VALUE(RIGHT(G$1,2)),1)>TODAY(),"",IF(EOMONTH(DATE(VALUE(LEFT(G$1,4)),VALUE(RIGHT(G$1,2)),1),0)<TODAY(),G13/DAY(EOMONTH(DATE(VALUE(LEFT(G$1,4)),VALUE(RIGHT(G$1,2)),1),0)),G13/MAX(NOW()-DATE(VALUE(LEFT(G$1,4)),VALUE(RIGHT(G$1,2)),1),1/24))),"") | H14: =IFERROR(IF(DATE(VALUE(LEFT(H$1,4)),VALUE(RIGHT(H$1,2)),1)>TODAY(),"",IF(EOMONTH(DATE(VALUE(LEFT(H$1,4)),VALUE(RIGHT(H$1,2)),1),0)<TODAY(),H13/DAY(EOMONTH(DATE(VALUE(LEFT(H$1,4)),VALUE(RIGHT(H$1,2)),1),0)),H13/MAX(NOW()-DATE(VALUE(LEFT(H$1,4)),VALUE(RIGHT(H$1,2)),1),1/24))),"") | I14: =IFERROR(IF(DATE(VALUE(LEFT(I$1,4)),VALUE(RIGHT(I$1,2)),1)>TODAY(),"",IF(EOMONTH(DATE(VALUE(LEFT(I$1,4)),VALUE(RIGHT(I$1,2)),1),0)<TODAY(),I13/DAY(EOMONTH(DATE(VALUE(LEFT(I$1,4)),VALUE(RIGHT(I$1,2)),1),0)),I13/MAX(NOW()-DATE(VALUE(LEFT(I$1,4)),VALUE(RIGHT(I$1,2)),1),1/24))),"") | J14: =IFERROR(IF(DATE(VALUE(LEFT(J$1,4)),VALUE(RIGHT(J$1,2)),1)>TODAY(),"",IF(EOMONTH(DATE(VALUE(LEFT(J$1,4)),VALUE(RIGHT(J$1,2)),1),0)<TODAY(),J13/DAY(EOMONTH(DATE(VALUE(LEFT(J$1,4)),VALUE(RIGHT(J$1,2)),1),0)),J13/MAX(NOW()-DATE(VALUE(LEFT(J$1,4)),VALUE(RIGHT(J$1,2)),1),1/24))),"") | K14: =IFERROR(IF(DATE(VALUE(LEFT(K$1,4)),VALUE(RIGHT(K$1,2)),1)>TODAY(),"",IF(EOMONTH(DATE(VALUE(LEFT(K$1,4)),VALUE(RIGHT(K$1,2)),1),0)<TODAY(),K13/DAY(EOMONTH(DATE(VALUE(LEFT(K$1,4)),VALUE(RIGHT(K$1,2)),1),0)),K13/MAX(NOW()-DATE(VALUE(LEFT(K$1,4)),VALUE(RIGHT(K$1,2)),1),1/24))),"") | ... O14: =IFERROR(IF(DATE(VALUE(LEFT(O$1,4)),VALUE(RIGHT(O$1,2)),1)>TODAY(),"",IF(EOMONTH(DATE(VALUE(LEFT(O$1,4)),VALUE(RIGHT(O$1,2)),1),0)<TODAY(),O13/DAY(EOMONTH(DATE(VALUE(LEFT(O$1,4)),VALUE(RIGHT(O$1,2)),1),0)),O13/MAX(NOW()-DATE(VALUE(LEFT(O$1,4)),VALUE(RIGHT(O$1,2)),1),1/24))),"") | P14: =SUM(D14:O14)
A15: AT | C15: AT | D15: =SUMIFS('i-shopify-sl'!$I:$I,'i-shopify-sl'!$A:$A,D$1,'i-shopify-sl'!$C:$C,$C15) | E15: =SUMIFS('i-shopify-sl'!$I:$I,'i-shopify-sl'!$A:$A,E$1,'i-shopify-sl'!$C:$C,$C15) | F15: =SUMIFS('i-shopify-sl'!$I:$I,'i-shopify-sl'!$A:$A,F$1,'i-shopify-sl'!$C:$C,$C15) | G15: =SUMIFS('i-shopify-sl'!$I:$I,'i-shopify-sl'!$A:$A,G$1,'i-shopify-sl'!$C:$C,$C15) | H15: =SUMIFS('i-shopify-sl'!$I:$I,'i-shopify-sl'!$A:$A,H$1,'i-shopify-sl'!$C:$C,$C15) | I15: =SUMIFS('i-shopify-sl'!$I:$I,'i-shopify-sl'!$A:$A,I$1,'i-shopify-sl'!$C:$C,$C15) | J15: =SUMIFS('i-shopify-sl'!$I:$I,'i-shopify-sl'!$A:$A,J$1,'i-shopify-sl'!$C:$C,$C15) | K15: =SUMIFS('i-shopify-sl'!$I:$I,'i-shopify-sl'!$A:$A,K$1,'i-shopify-sl'!$C:$C,$C15) | ... O15: =SUMIFS('i-shopify-sl'!$I:$I,'i-shopify-sl'!$A:$A,O$1,'i-shopify-sl'!$C:$C,$C15) | P15: =SUM(D15:O15) | Q15: ->
A16: avg/day | C16: avg/day | D16: =IFERROR(IF(DATE(VALUE(LEFT(D$1,4)),VALUE(RIGHT(D$1,2)),1)>TODAY(),"",IF(EOMONTH(DATE(VALUE(LEFT(D$1,4)),VALUE(RIGHT(D$1,2)),1),0)<TODAY(),D15/DAY(EOMONTH(DATE(VALUE(LEFT(D$1,4)),VALUE(RIGHT(D$1,2)),1),0)),D15/MAX(NOW()-DATE(VALUE(LEFT(D$1,4)),VALUE(RIGHT(D$1,2)),1),1/24))),"") | E16: =IFERROR(IF(DATE(VALUE(LEFT(E$1,4)),VALUE(RIGHT(E$1,2)),1)>TODAY(),"",IF(EOMONTH(DATE(VALUE(LEFT(E$1,4)),VALUE(RIGHT(E$1,2)),1),0)<TODAY(),E15/DAY(EOMONTH(DATE(VALUE(LEFT(E$1,4)),VALUE(RIGHT(E$1,2)),1),0)),E15/MAX(NOW()-DATE(VALUE(LEFT(E$1,4)),VALUE(RIGHT(E$1,2)),1),1/24))),"") | F16: =IFERROR(IF(DATE(VALUE(LEFT(F$1,4)),VALUE(RIGHT(F$1,2)),1)>TODAY(),"",IF(EOMONTH(DATE(VALUE(LEFT(F$1,4)),VALUE(RIGHT(F$1,2)),1),0)<TODAY(),F15/DAY(EOMONTH(DATE(VALUE(LEFT(F$1,4)),VALUE(RIGHT(F$1,2)),1),0)),F15/MAX(NOW()-DATE(VALUE(LEFT(F$1,4)),VALUE(RIGHT(F$1,2)),1),1/24))),"") | G16: =IFERROR(IF(DATE(VALUE(LEFT(G$1,4)),VALUE(RIGHT(G$1,2)),1)>TODAY(),"",IF(EOMONTH(DATE(VALUE(LEFT(G$1,4)),VALUE(RIGHT(G$1,2)),1),0)<TODAY(),G15/DAY(EOMONTH(DATE(VALUE(LEFT(G$1,4)),VALUE(RIGHT(G$1,2)),1),0)),G15/MAX(NOW()-DATE(VALUE(LEFT(G$1,4)),VALUE(RIGHT(G$1,2)),1),1/24))),"") | H16: =IFERROR(IF(DATE(VALUE(LEFT(H$1,4)),VALUE(RIGHT(H$1,2)),1)>TODAY(),"",IF(EOMONTH(DATE(VALUE(LEFT(H$1,4)),VALUE(RIGHT(H$1,2)),1),0)<TODAY(),H15/DAY(EOMONTH(DATE(VALUE(LEFT(H$1,4)),VALUE(RIGHT(H$1,2)),1),0)),H15/MAX(NOW()-DATE(VALUE(LEFT(H$1,4)),VALUE(RIGHT(H$1,2)),1),1/24))),"") | I16: =IFERROR(IF(DATE(VALUE(LEFT(I$1,4)),VALUE(RIGHT(I$1,2)),1)>TODAY(),"",IF(EOMONTH(DATE(VALUE(LEFT(I$1,4)),VALUE(RIGHT(I$1,2)),1),0)<TODAY(),I15/DAY(EOMONTH(DATE(VALUE(LEFT(I$1,4)),VALUE(RIGHT(I$1,2)),1),0)),I15/MAX(NOW()-DATE(VALUE(LEFT(I$1,4)),VALUE(RIGHT(I$1,2)),1),1/24))),"") | J16: =IFERROR(IF(DATE(VALUE(LEFT(J$1,4)),VALUE(RIGHT(J$1,2)),1)>TODAY(),"",IF(EOMONTH(DATE(VALUE(LEFT(J$1,4)),VALUE(RIGHT(J$1,2)),1),0)<TODAY(),J15/DAY(EOMONTH(DATE(VALUE(LEFT(J$1,4)),VALUE(RIGHT(J$1,2)),1),0)),J15/MAX(NOW()-DATE(VALUE(LEFT(J$1,4)),VALUE(RIGHT(J$1,2)),1),1/24))),"") | K16: =IFERROR(IF(DATE(VALUE(LEFT(K$1,4)),VALUE(RIGHT(K$1,2)),1)>TODAY(),"",IF(EOMONTH(DATE(VALUE(LEFT(K$1,4)),VALUE(RIGHT(K$1,2)),1),0)<TODAY(),K15/DAY(EOMONTH(DATE(VALUE(LEFT(K$1,4)),VALUE(RIGHT(K$1,2)),1),0)),K15/MAX(NOW()-DATE(VALUE(LEFT(K$1,4)),VALUE(RIGHT(K$1,2)),1),1/24))),"") | ... O16: =IFERROR(IF(DATE(VALUE(LEFT(O$1,4)),VALUE(RIGHT(O$1,2)),1)>TODAY(),"",IF(EOMONTH(DATE(VALUE(LEFT(O$1,4)),VALUE(RIGHT(O$1,2)),1),0)<TODAY(),O15/DAY(EOMONTH(DATE(VALUE(LEFT(O$1,4)),VALUE(RIGHT(O$1,2)),1),0)),O15/MAX(NOW()-DATE(VALUE(LEFT(O$1,4)),VALUE(RIGHT(O$1,2)),1),1/24))),"") | P16: =SUM(D16:O16)
A17: BE | C17: BE | D17: =SUMIFS('i-shopify-sl'!$I:$I,'i-shopify-sl'!$A:$A,D$1,'i-shopify-sl'!$C:$C,$C17) | E17: =SUMIFS('i-shopify-sl'!$I:$I,'i-shopify-sl'!$A:$A,E$1,'i-shopify-sl'!$C:$C,$C17) | F17: =SUMIFS('i-shopify-sl'!$I:$I,'i-shopify-sl'!$A:$A,F$1,'i-shopify-sl'!$C:$C,$C17) | G17: =SUMIFS('i-shopify-sl'!$I:$I,'i-shopify-sl'!$A:$A,G$1,'i-shopify-sl'!$C:$C,$C17) | H17: =SUMIFS('i-shopify-sl'!$I:$I,'i-shopify-sl'!$A:$A,H$1,'i-shopify-sl'!$C:$C,$C17) | I17: =SUMIFS('i-shopify-sl'!$I:$I,'i-shopify-sl'!$A:$A,I$1,'i-shopify-sl'!$C:$C,$C17) | J17: =SUMIFS('i-shopify-sl'!$I:$I,'i-shopify-sl'!$A:$A,J$1,'i-shopify-sl'!$C:$C,$C17) | K17: =SUMIFS('i-shopify-sl'!$I:$I,'i-shopify-sl'!$A:$A,K$1,'i-shopify-sl'!$C:$C,$C17) | ... O17: =SUMIFS('i-shopify-sl'!$I:$I,'i-shopify-sl'!$A:$A,O$1,'i-shopify-sl'!$C:$C,$C17) | P17: =SUM(D17:O17) | Q17: ->
A18: avg/day | C18: avg/day | D18: =IFERROR(IF(DATE(VALUE(LEFT(D$1,4)),VALUE(RIGHT(D$1,2)),1)>TODAY(),"",IF(EOMONTH(DATE(VALUE(LEFT(D$1,4)),VALUE(RIGHT(D$1,2)),1),0)<TODAY(),D17/DAY(EOMONTH(DATE(VALUE(LEFT(D$1,4)),VALUE(RIGHT(D$1,2)),1),0)),D17/MAX(NOW()-DATE(VALUE(LEFT(D$1,4)),VALUE(RIGHT(D$1,2)),1),1/24))),"") | E18: =IFERROR(IF(DATE(VALUE(LEFT(E$1,4)),VALUE(RIGHT(E$1,2)),1)>TODAY(),"",IF(EOMONTH(DATE(VALUE(LEFT(E$1,4)),VALUE(RIGHT(E$1,2)),1),0)<TODAY(),E17/DAY(EOMONTH(DATE(VALUE(LEFT(E$1,4)),VALUE(RIGHT(E$1,2)),1),0)),E17/MAX(NOW()-DATE(VALUE(LEFT(E$1,4)),VALUE(RIGHT(E$1,2)),1),1/24))),"") | F18: =IFERROR(IF(DATE(VALUE(LEFT(F$1,4)),VALUE(RIGHT(F$1,2)),1)>TODAY(),"",IF(EOMONTH(DATE(VALUE(LEFT(F$1,4)),VALUE(RIGHT(F$1,2)),1),0)<TODAY(),F17/DAY(EOMONTH(DATE(VALUE(LEFT(F$1,4)),VALUE(RIGHT(F$1,2)),1),0)),F17/MAX(NOW()-DATE(VALUE(LEFT(F$1,4)),VALUE(RIGHT(F$1,2)),1),1/24))),"") | G18: =IFERROR(IF(DATE(VALUE(LEFT(G$1,4)),VALUE(RIGHT(G$1,2)),1)>TODAY(),"",IF(EOMONTH(DATE(VALUE(LEFT(G$1,4)),VALUE(RIGHT(G$1,2)),1),0)<TODAY(),G17/DAY(EOMONTH(DATE(VALUE(LEFT(G$1,4)),VALUE(RIGHT(G$1,2)),1),0)),G17/MAX(NOW()-DATE(VALUE(LEFT(G$1,4)),VALUE(RIGHT(G$1,2)),1),1/24))),"") | H18: =IFERROR(IF(DATE(VALUE(LEFT(H$1,4)),VALUE(RIGHT(H$1,2)),1)>TODAY(),"",IF(EOMONTH(DATE(VALUE(LEFT(H$1,4)),VALUE(RIGHT(H$1,2)),1),0)<TODAY(),H17/DAY(EOMONTH(DATE(VALUE(LEFT(H$1,4)),VALUE(RIGHT(H$1,2)),1),0)),H17/MAX(NOW()-DATE(VALUE(LEFT(H$1,4)),VALUE(RIGHT(H$1,2)),1),1/24))),"") | I18: =IFERROR(IF(DATE(VALUE(LEFT(I$1,4)),VALUE(RIGHT(I$1,2)),1)>TODAY(),"",IF(EOMONTH(DATE(VALUE(LEFT(I$1,4)),VALUE(RIGHT(I$1,2)),1),0)<TODAY(),I17/DAY(EOMONTH(DATE(VALUE(LEFT(I$1,4)),VALUE(RIGHT(I$1,2)),1),0)),I17/MAX(NOW()-DATE(VALUE(LEFT(I$1,4)),VALUE(RIGHT(I$1,2)),1),1/24))),"") | J18: =IFERROR(IF(DATE(VALUE(LEFT(J$1,4)),VALUE(RIGHT(J$1,2)),1)>TODAY(),"",IF(EOMONTH(DATE(VALUE(LEFT(J$1,4)),VALUE(RIGHT(J$1,2)),1),0)<TODAY(),J17/DAY(EOMONTH(DATE(VALUE(LEFT(J$1,4)),VALUE(RIGHT(J$1,2)),1),0)),J17/MAX(NOW()-DATE(VALUE(LEFT(J$1,4)),VALUE(RIGHT(J$1,2)),1),1/24))),"") | K18: =IFERROR(IF(DATE(VALUE(LEFT(K$1,4)),VALUE(RIGHT(K$1,2)),1)>TODAY(),"",IF(EOMONTH(DATE(VALUE(LEFT(K$1,4)),VALUE(RIGHT(K$1,2)),1),0)<TODAY(),K17/DAY(EOMONTH(DATE(VALUE(LEFT(K$1,4)),VALUE(RIGHT(K$1,2)),1),0)),K17/MAX(NOW()-DATE(VALUE(LEFT(K$1,4)),VALUE(RIGHT(K$1,2)),1),1/24))),"") | ... O18: =IFERROR(IF(DATE(VALUE(LEFT(O$1,4)),VALUE(RIGHT(O$1,2)),1)>TODAY(),"",IF(EOMONTH(DATE(VALUE(LEFT(O$1,4)),VALUE(RIGHT(O$1,2)),1),0)<TODAY(),O17/DAY(EOMONTH(DATE(VALUE(LEFT(O$1,4)),VALUE(RIGHT(O$1,2)),1),0)),O17/MAX(NOW()-DATE(VALUE(LEFT(O$1,4)),VALUE(RIGHT(O$1,2)),1),1/24))),"") | P18: =SUM(D18:O18)
A19: NL | C19: NL | D19: =SUMIFS('i-shopify-sl'!$I:$I,'i-shopify-sl'!$A:$A,D$1,'i-shopify-sl'!$C:$C,$C19) | E19: =SUMIFS('i-shopify-sl'!$I:$I,'i-shopify-sl'!$A:$A,E$1,'i-shopify-sl'!$C:$C,$C19) | F19: =SUMIFS('i-shopify-sl'!$I:$I,'i-shopify-sl'!$A:$A,F$1,'i-shopify-sl'!$C:$C,$C19) | G19: =SUMIFS('i-shopify-sl'!$I:$I,'i-shopify-sl'!$A:$A,G$1,'i-shopify-sl'!$C:$C,$C19) | H19: =SUMIFS('i-shopify-sl'!$I:$I,'i-shopify-sl'!$A:$A,H$1,'i-shopify-sl'!$C:$C,$C19) | I19: =SUMIFS('i-shopify-sl'!$I:$I,'i-shopify-sl'!$A:$A,I$1,'i-shopify-sl'!$C:$C,$C19) | J19: =SUMIFS('i-shopify-sl'!$I:$I,'i-shopify-sl'!$A:$A,J$1,'i-shopify-sl'!$C:$C,$C19) | K19: =SUMIFS('i-shopify-sl'!$I:$I,'i-shopify-sl'!$A:$A,K$1,'i-shopify-sl'!$C:$C,$C19) | ... O19: =SUMIFS('i-shopify-sl'!$I:$I,'i-shopify-sl'!$A:$A,O$1,'i-shopify-sl'!$C:$C,$C19) | P19: =SUM(D19:O19) | Q19: ->
A20: avg/day | C20: avg/day | D20: =IFERROR(IF(DATE(VALUE(LEFT(D$1,4)),VALUE(RIGHT(D$1,2)),1)>TODAY(),"",IF(EOMONTH(DATE(VALUE(LEFT(D$1,4)),VALUE(RIGHT(D$1,2)),1),0)<TODAY(),D19/DAY(EOMONTH(DATE(VALUE(LEFT(D$1,4)),VALUE(RIGHT(D$1,2)),1),0)),D19/MAX(NOW()-DATE(VALUE(LEFT(D$1,4)),VALUE(RIGHT(D$1,2)),1),1/24))),"") | E20: =IFERROR(IF(DATE(VALUE(LEFT(E$1,4)),VALUE(RIGHT(E$1,2)),1)>TODAY(),"",IF(EOMONTH(DATE(VALUE(LEFT(E$1,4)),VALUE(RIGHT(E$1,2)),1),0)<TODAY(),E19/DAY(EOMONTH(DATE(VALUE(LEFT(E$1,4)),VALUE(RIGHT(E$1,2)),1),0)),E19/MAX(NOW()-DATE(VALUE(LEFT(E$1,4)),VALUE(RIGHT(E$1,2)),1),1/24))),"") | F20: =IFERROR(IF(DATE(VALUE(LEFT(F$1,4)),VALUE(RIGHT(F$1,2)),1)>TODAY(),"",IF(EOMONTH(DATE(VALUE(LEFT(F$1,4)),VALUE(RIGHT(F$1,2)),1),0)<TODAY(),F19/DAY(EOMONTH(DATE(VALUE(LEFT(F$1,4)),VALUE(RIGHT(F$1,2)),1),0)),F19/MAX(NOW()-DATE(VALUE(LEFT(F$1,4)),VALUE(RIGHT(F$1,2)),1),1/24))),"") | G20: =IFERROR(IF(DATE(VALUE(LEFT(G$1,4)),VALUE(RIGHT(G$1,2)),1)>TODAY(),"",IF(EOMONTH(DATE(VALUE(LEFT(G$1,4)),VALUE(RIGHT(G$1,2)),1),0)<TODAY(),G19/DAY(EOMONTH(DATE(VALUE(LEFT(G$1,4)),VALUE(RIGHT(G$1,2)),1),0)),G19/MAX(NOW()-DATE(VALUE(LEFT(G$1,4)),VALUE(RIGHT(G$1,2)),1),1/24))),"") | H20: =IFERROR(IF(DATE(VALUE(LEFT(H$1,4)),VALUE(RIGHT(H$1,2)),1)>TODAY(),"",IF(EOMONTH(DATE(VALUE(LEFT(H$1,4)),VALUE(RIGHT(H$1,2)),1),0)<TODAY(),H19/DAY(EOMONTH(DATE(VALUE(LEFT(H$1,4)),VALUE(RIGHT(H$1,2)),1),0)),H19/MAX(NOW()-DATE(VALUE(LEFT(H$1,4)),VALUE(RIGHT(H$1,2)),1),1/24))),"") | I20: =IFERROR(IF(DATE(VALUE(LEFT(I$1,4)),VALUE(RIGHT(I$1,2)),1)>TODAY(),"",IF(EOMONTH(DATE(VALUE(LEFT(I$1,4)),VALUE(RIGHT(I$1,2)),1),0)<TODAY(),I19/DAY(EOMONTH(DATE(VALUE(LEFT(I$1,4)),VALUE(RIGHT(I$1,2)),1),0)),I19/MAX(NOW()-DATE(VALUE(LEFT(I$1,4)),VALUE(RIGHT(I$1,2)),1),1/24))),"") | J20: =IFERROR(IF(DATE(VALUE(LEFT(J$1,4)),VALUE(RIGHT(J$1,2)),1)>TODAY(),"",IF(EOMONTH(DATE(VALUE(LEFT(J$1,4)),VALUE(RIGHT(J$1,2)),1),0)<TODAY(),J19/DAY(EOMONTH(DATE(VALUE(LEFT(J$1,4)),VALUE(RIGHT(J$1,2)),1),0)),J19/MAX(NOW()-DATE(VALUE(LEFT(J$1,4)),VALUE(RIGHT(J$1,2)),1),1/24))),"") | K20: =IFERROR(IF(DATE(VALUE(LEFT(K$1,4)),VALUE(RIGHT(K$1,2)),1)>TODAY(),"",IF(EOMONTH(DATE(VALUE(LEFT(K$1,4)),VALUE(RIGHT(K$1,2)),1),0)<TODAY(),K19/DAY(EOMONTH(DATE(VALUE(LEFT(K$1,4)),VALUE(RIGHT(K$1,2)),1),0)),K19/MAX(NOW()-DATE(VALUE(LEFT(K$1,4)),VALUE(RIGHT(K$1,2)),1),1/24))),"") | ... O20: =IFERROR(IF(DATE(VALUE(LEFT(O$1,4)),VALUE(RIGHT(O$1,2)),1)>TODAY(),"",IF(EOMONTH(DATE(VALUE(LEFT(O$1,4)),VALUE(RIGHT(O$1,2)),1),0)<TODAY(),O19/DAY(EOMONTH(DATE(VALUE(LEFT(O$1,4)),VALUE(RIGHT(O$1,2)),1),0)),O19/MAX(NOW()-DATE(VALUE(LEFT(O$1,4)),VALUE(RIGHT(O$1,2)),1),1/24))),"") | P20: =SUM(D20:O20)
A21: PT | C21: PT | D21: =SUMIFS('i-shopify-sl'!$I:$I,'i-shopify-sl'!$A:$A,D$1,'i-shopify-sl'!$C:$C,$C21) | E21: =SUMIFS('i-shopify-sl'!$I:$I,'i-shopify-sl'!$A:$A,E$1,'i-shopify-sl'!$C:$C,$C21) | F21: =SUMIFS('i-shopify-sl'!$I:$I,'i-shopify-sl'!$A:$A,F$1,'i-shopify-sl'!$C:$C,$C21) | G21: =SUMIFS('i-shopify-sl'!$I:$I,'i-shopify-sl'!$A:$A,G$1,'i-shopify-sl'!$C:$C,$C21) | H21: =SUMIFS('i-shopify-sl'!$I:$I,'i-shopify-sl'!$A:$A,H$1,'i-shopify-sl'!$C:$C,$C21) | I21: =SUMIFS('i-shopify-sl'!$I:$I,'i-shopify-sl'!$A:$A,I$1,'i-shopify-sl'!$C:$C,$C21) | J21: =SUMIFS('i-shopify-sl'!$I:$I,'i-shopify-sl'!$A:$A,J$1,'i-shopify-sl'!$C:$C,$C21) | K21: =SUMIFS('i-shopify-sl'!$I:$I,'i-shopify-sl'!$A:$A,K$1,'i-shopify-sl'!$C:$C,$C21) | ... O21: =SUMIFS('i-shopify-sl'!$I:$I,'i-shopify-sl'!$A:$A,O$1,'i-shopify-sl'!$C:$C,$C21) | P21: =SUM(D21:O21) | Q21: ->
A22: avg/day | C22: avg/day | D22: =IFERROR(IF(DATE(VALUE(LEFT(D$1,4)),VALUE(RIGHT(D$1,2)),1)>TODAY(),"",IF(EOMONTH(DATE(VALUE(LEFT(D$1,4)),VALUE(RIGHT(D$1,2)),1),0)<TODAY(),D21/DAY(EOMONTH(DATE(VALUE(LEFT(D$1,4)),VALUE(RIGHT(D$1,2)),1),0)),D21/MAX(NOW()-DATE(VALUE(LEFT(D$1,4)),VALUE(RIGHT(D$1,2)),1),1/24))),"") | E22: =IFERROR(IF(DATE(VALUE(LEFT(E$1,4)),VALUE(RIGHT(E$1,2)),1)>TODAY(),"",IF(EOMONTH(DATE(VALUE(LEFT(E$1,4)),VALUE(RIGHT(E$1,2)),1),0)<TODAY(),E21/DAY(EOMONTH(DATE(VALUE(LEFT(E$1,4)),VALUE(RIGHT(E$1,2)),1),0)),E21/MAX(NOW()-DATE(VALUE(LEFT(E$1,4)),VALUE(RIGHT(E$1,2)),1),1/24))),"") | F22: =IFERROR(IF(DATE(VALUE(LEFT(F$1,4)),VALUE(RIGHT(F$1,2)),1)>TODAY(),"",IF(EOMONTH(DATE(VALUE(LEFT(F$1,4)),VALUE(RIGHT(F$1,2)),1),0)<TODAY(),F21/DAY(EOMONTH(DATE(VALUE(LEFT(F$1,4)),VALUE(RIGHT(F$1,2)),1),0)),F21/MAX(NOW()-DATE(VALUE(LEFT(F$1,4)),VALUE(RIGHT(F$1,2)),1),1/24))),"") | G22: =IFERROR(IF(DATE(VALUE(LEFT(G$1,4)),VALUE(RIGHT(G$1,2)),1)>TODAY(),"",IF(EOMONTH(DATE(VALUE(LEFT(G$1,4)),VALUE(RIGHT(G$1,2)),1),0)<TODAY(),G21/DAY(EOMONTH(DATE(VALUE(LEFT(G$1,4)),VALUE(RIGHT(G$1,2)),1),0)),G21/MAX(NOW()-DATE(VALUE(LEFT(G$1,4)),VALUE(RIGHT(G$1,2)),1),1/24))),"") | H22: =IFERROR(IF(DATE(VALUE(LEFT(H$1,4)),VALUE(RIGHT(H$1,2)),1)>TODAY(),"",IF(EOMONTH(DATE(VALUE(LEFT(H$1,4)),VALUE(RIGHT(H$1,2)),1),0)<TODAY(),H21/DAY(EOMONTH(DATE(VALUE(LEFT(H$1,4)),VALUE(RIGHT(H$1,2)),1),0)),H21/MAX(NOW()-DATE(VALUE(LEFT(H$1,4)),VALUE(RIGHT(H$1,2)),1),1/24))),"") | I22: =IFERROR(IF(DATE(VALUE(LEFT(I$1,4)),VALUE(RIGHT(I$1,2)),1)>TODAY(),"",IF(EOMONTH(DATE(VALUE(LEFT(I$1,4)),VALUE(RIGHT(I$1,2)),1),0)<TODAY(),I21/DAY(EOMONTH(DATE(VALUE(LEFT(I$1,4)),VALUE(RIGHT(I$1,2)),1),0)),I21/MAX(NOW()-DATE(VALUE(LEFT(I$1,4)),VALUE(RIGHT(I$1,2)),1),1/24))),"") | J22: =IFERROR(IF(DATE(VALUE(LEFT(J$1,4)),VALUE(RIGHT(J$1,2)),1)>TODAY(),"",IF(EOMONTH(DATE(VALUE(LEFT(J$1,4)),VALUE(RIGHT(J$1,2)),1),0)<TODAY(),J21/DAY(EOMONTH(DATE(VALUE(LEFT(J$1,4)),VALUE(RIGHT(J$1,2)),1),0)),J21/MAX(NOW()-DATE(VALUE(LEFT(J$1,4)),VALUE(RIGHT(J$1,2)),1),1/24))),"") | K22: =IFERROR(IF(DATE(VALUE(LEFT(K$1,4)),VALUE(RIGHT(K$1,2)),1)>TODAY(),"",IF(EOMONTH(DATE(VALUE(LEFT(K$1,4)),VALUE(RIGHT(K$1,2)),1),0)<TODAY(),K21/DAY(EOMONTH(DATE(VALUE(LEFT(K$1,4)),VALUE(RIGHT(K$1,2)),1),0)),K21/MAX(NOW()-DATE(VALUE(LEFT(K$1,4)),VALUE(RIGHT(K$1,2)),1),1/24))),"") | ... O22: =IFERROR(IF(DATE(VALUE(LEFT(O$1,4)),VALUE(RIGHT(O$1,2)),1)>TODAY(),"",IF(EOMONTH(DATE(VALUE(LEFT(O$1,4)),VALUE(RIGHT(O$1,2)),1),0)<TODAY(),O21/DAY(EOMONTH(DATE(VALUE(LEFT(O$1,4)),VALUE(RIGHT(O$1,2)),1),0)),O21/MAX(NOW()-DATE(VALUE(LEFT(O$1,4)),VALUE(RIGHT(O$1,2)),1),1/24))),"") | P22: =SUM(D22:O22)
A23: CZ | C23: CZ | D23: =SUMIFS('i-shopify-sl'!$I:$I,'i-shopify-sl'!$A:$A,D$1,'i-shopify-sl'!$C:$C,$C23) | E23: =SUMIFS('i-shopify-sl'!$I:$I,'i-shopify-sl'!$A:$A,E$1,'i-shopify-sl'!$C:$C,$C23) | F23: =SUMIFS('i-shopify-sl'!$I:$I,'i-shopify-sl'!$A:$A,F$1,'i-shopify-sl'!$C:$C,$C23) | G23: =SUMIFS('i-shopify-sl'!$I:$I,'i-shopify-sl'!$A:$A,G$1,'i-shopify-sl'!$C:$C,$C23) | H23: =SUMIFS('i-shopify-sl'!$I:$I,'i-shopify-sl'!$A:$A,H$1,'i-shopify-sl'!$C:$C,$C23) | I23: =SUMIFS('i-shopify-sl'!$I:$I,'i-shopify-sl'!$A:$A,I$1,'i-shopify-sl'!$C:$C,$C23) | J23: =SUMIFS('i-shopify-sl'!$I:$I,'i-shopify-sl'!$A:$A,J$1,'i-shopify-sl'!$C:$C,$C23) | K23: =SUMIFS('i-shopify-sl'!$I:$I,'i-shopify-sl'!$A:$A,K$1,'i-shopify-sl'!$C:$C,$C23) | ... O23: =SUMIFS('i-shopify-sl'!$I:$I,'i-shopify-sl'!$A:$A,O$1,'i-shopify-sl'!$C:$C,$C23) | P23: =SUM(D23:O23) | Q23: ->
A24: avg/day | C24: avg/day | D24: =IFERROR(IF(DATE(VALUE(LEFT(D$1,4)),VALUE(RIGHT(D$1,2)),1)>TODAY(),"",IF(EOMONTH(DATE(VALUE(LEFT(D$1,4)),VALUE(RIGHT(D$1,2)),1),0)<TODAY(),D23/DAY(EOMONTH(DATE(VALUE(LEFT(D$1,4)),VALUE(RIGHT(D$1,2)),1),0)),D23/MAX(NOW()-DATE(VALUE(LEFT(D$1,4)),VALUE(RIGHT(D$1,2)),1),1/24))),"") | E24: =IFERROR(IF(DATE(VALUE(LEFT(E$1,4)),VALUE(RIGHT(E$1,2)),1)>TODAY(),"",IF(EOMONTH(DATE(VALUE(LEFT(E$1,4)),VALUE(RIGHT(E$1,2)),1),0)<TODAY(),E23/DAY(EOMONTH(DATE(VALUE(LEFT(E$1,4)),VALUE(RIGHT(E$1,2)),1),0)),E23/MAX(NOW()-DATE(VALUE(LEFT(E$1,4)),VALUE(RIGHT(E$1,2)),1),1/24))),"") | F24: =IFERROR(IF(DATE(VALUE(LEFT(F$1,4)),VALUE(RIGHT(F$1,2)),1)>TODAY(),"",IF(EOMONTH(DATE(VALUE(LEFT(F$1,4)),VALUE(RIGHT(F$1,2)),1),0)<TODAY(),F23/DAY(EOMONTH(DATE(VALUE(LEFT(F$1,4)),VALUE(RIGHT(F$1,2)),1),0)),F23/MAX(NOW()-DATE(VALUE(LEFT(F$1,4)),VALUE(RIGHT(F$1,2)),1),1/24))),"") | G24: =IFERROR(IF(DATE(VALUE(LEFT(G$1,4)),VALUE(RIGHT(G$1,2)),1)>TODAY(),"",IF(EOMONTH(DATE(VALUE(LEFT(G$1,4)),VALUE(RIGHT(G$1,2)),1),0)<TODAY(),G23/DAY(EOMONTH(DATE(VALUE(LEFT(G$1,4)),VALUE(RIGHT(G$1,2)),1),0)),G23/MAX(NOW()-DATE(VALUE(LEFT(G$1,4)),VALUE(RIGHT(G$1,2)),1),1/24))),"") | H24: =IFERROR(IF(DATE(VALUE(LEFT(H$1,4)),VALUE(RIGHT(H$1,2)),1)>TODAY(),"",IF(EOMONTH(DATE(VALUE(LEFT(H$1,4)),VALUE(RIGHT(H$1,2)),1),0)<TODAY(),H23/DAY(EOMONTH(DATE(VALUE(LEFT(H$1,4)),VALUE(RIGHT(H$1,2)),1),0)),H23/MAX(NOW()-DATE(VALUE(LEFT(H$1,4)),VALUE(RIGHT(H$1,2)),1),1/24))),"") | I24: =IFERROR(IF(DATE(VALUE(LEFT(I$1,4)),VALUE(RIGHT(I$1,2)),1)>TODAY(),"",IF(EOMONTH(DATE(VALUE(LEFT(I$1,4)),VALUE(RIGHT(I$1,2)),1),0)<TODAY(),I23/DAY(EOMONTH(DATE(VALUE(LEFT(I$1,4)),VALUE(RIGHT(I$1,2)),1),0)),I23/MAX(NOW()-DATE(VALUE(LEFT(I$1,4)),VALUE(RIGHT(I$1,2)),1),1/24))),"") | J24: =IFERROR(IF(DATE(VALUE(LEFT(J$1,4)),VALUE(RIGHT(J$1,2)),1)>TODAY(),"",IF(EOMONTH(DATE(VALUE(LEFT(J$1,4)),VALUE(RIGHT(J$1,2)),1),0)<TODAY(),J23/DAY(EOMONTH(DATE(VALUE(LEFT(J$1,4)),VALUE(RIGHT(J$1,2)),1),0)),J23/MAX(NOW()-DATE(VALUE(LEFT(J$1,4)),VALUE(RIGHT(J$1,2)),1),1/24))),"") | K24: =IFERROR(IF(DATE(VALUE(LEFT(K$1,4)),VALUE(RIGHT(K$1,2)),1)>TODAY(),"",IF(EOMONTH(DATE(VALUE(LEFT(K$1,4)),VALUE(RIGHT(K$1,2)),1),0)<TODAY(),K23/DAY(EOMONTH(DATE(VALUE(LEFT(K$1,4)),VALUE(RIGHT(K$1,2)),1),0)),K23/MAX(NOW()-DATE(VALUE(LEFT(K$1,4)),VALUE(RIGHT(K$1,2)),1),1/24))),"") | ... O24: =IFERROR(IF(DATE(VALUE(LEFT(O$1,4)),VALUE(RIGHT(O$1,2)),1)>TODAY(),"",IF(EOMONTH(DATE(VALUE(LEFT(O$1,4)),VALUE(RIGHT(O$1,2)),1),0)<TODAY(),O23/DAY(EOMONTH(DATE(VALUE(LEFT(O$1,4)),VALUE(RIGHT(O$1,2)),1),0)),O23/MAX(NOW()-DATE(VALUE(LEFT(O$1,4)),VALUE(RIGHT(O$1,2)),1),1/24))),"") | P24: =SUM(D24:O24)
A25: DK | C25: DK | D25: =SUMIFS('i-shopify-sl'!$I:$I,'i-shopify-sl'!$A:$A,D$1,'i-shopify-sl'!$C:$C,$C25) | E25: =SUMIFS('i-shopify-sl'!$I:$I,'i-shopify-sl'!$A:$A,E$1,'i-shopify-sl'!$C:$C,$C25) | F25: =SUMIFS('i-shopify-sl'!$I:$I,'i-shopify-sl'!$A:$A,F$1,'i-shopify-sl'!$C:$C,$C25) | G25: =SUMIFS('i-shopify-sl'!$I:$I,'i-shopify-sl'!$A:$A,G$1,'i-shopify-sl'!$C:$C,$C25) | H25: =SUMIFS('i-shopify-sl'!$I:$I,'i-shopify-sl'!$A:$A,H$1,'i-shopify-sl'!$C:$C,$C25) | I25: =SUMIFS('i-shopify-sl'!$I:$I,'i-shopify-sl'!$A:$A,I$1,'i-shopify-sl'!$C:$C,$C25) | J25: =SUMIFS('i-shopify-sl'!$I:$I,'i-shopify-sl'!$A:$A,J$1,'i-shopify-sl'!$C:$C,$C25) | K25: =SUMIFS('i-shopify-sl'!$I:$I,'i-shopify-sl'!$A:$A,K$1,'i-shopify-sl'!$C:$C,$C25) | ... O25: =SUMIFS('i-shopify-sl'!$I:$I,'i-shopify-sl'!$A:$A,O$1,'i-shopify-sl'!$C:$C,$C25) | P25: =SUM(D25:O25) | Q25: ->
A26: avg/day | C26: avg/day | D26: =IFERROR(IF(DATE(VALUE(LEFT(D$1,4)),VALUE(RIGHT(D$1,2)),1)>TODAY(),"",IF(EOMONTH(DATE(VALUE(LEFT(D$1,4)),VALUE(RIGHT(D$1,2)),1),0)<TODAY(),D25/DAY(EOMONTH(DATE(VALUE(LEFT(D$1,4)),VALUE(RIGHT(D$1,2)),1),0)),D25/MAX(NOW()-DATE(VALUE(LEFT(D$1,4)),VALUE(RIGHT(D$1,2)),1),1/24))),"") | E26: =IFERROR(IF(DATE(VALUE(LEFT(E$1,4)),VALUE(RIGHT(E$1,2)),1)>TODAY(),"",IF(EOMONTH(DATE(VALUE(LEFT(E$1,4)),VALUE(RIGHT(E$1,2)),1),0)<TODAY(),E25/DAY(EOMONTH(DATE(VALUE(LEFT(E$1,4)),VALUE(RIGHT(E$1,2)),1),0)),E25/MAX(NOW()-DATE(VALUE(LEFT(E$1,4)),VALUE(RIGHT(E$1,2)),1),1/24))),"") | F26: =IFERROR(IF(DATE(VALUE(LEFT(F$1,4)),VALUE(RIGHT(F$1,2)),1)>TODAY(),"",IF(EOMONTH(DATE(VALUE(LEFT(F$1,4)),VALUE(RIGHT(F$1,2)),1),0)<TODAY(),F25/DAY(EOMONTH(DATE(VALUE(LEFT(F$1,4)),VALUE(RIGHT(F$1,2)),1),0)),F25/MAX(NOW()-DATE(VALUE(LEFT(F$1,4)),VALUE(RIGHT(F$1,2)),1),1/24))),"") | G26: =IFERROR(IF(DATE(VALUE(LEFT(G$1,4)),VALUE(RIGHT(G$1,2)),1)>TODAY(),"",IF(EOMONTH(DATE(VALUE(LEFT(G$1,4)),VALUE(RIGHT(G$1,2)),1),0)<TODAY(),G25/DAY(EOMONTH(DATE(VALUE(LEFT(G$1,4)),VALUE(RIGHT(G$1,2)),1),0)),G25/MAX(NOW()-DATE(VALUE(LEFT(G$1,4)),VALUE(RIGHT(G$1,2)),1),1/24))),"") | H26: =IFERROR(IF(DATE(VALUE(LEFT(H$1,4)),VALUE(RIGHT(H$1,2)),1)>TODAY(),"",IF(EOMONTH(DATE(VALUE(LEFT(H$1,4)),VALUE(RIGHT(H$1,2)),1),0)<TODAY(),H25/DAY(EOMONTH(DATE(VALUE(LEFT(H$1,4)),VALUE(RIGHT(H$1,2)),1),0)),H25/MAX(NOW()-DATE(VALUE(LEFT(H$1,4)),VALUE(RIGHT(H$1,2)),1),1/24))),"") | I26: =IFERROR(IF(DATE(VALUE(LEFT(I$1,4)),VALUE(RIGHT(I$1,2)),1)>TODAY(),"",IF(EOMONTH(DATE(VALUE(LEFT(I$1,4)),VALUE(RIGHT(I$1,2)),1),0)<TODAY(),I25/DAY(EOMONTH(DATE(VALUE(LEFT(I$1,4)),VALUE(RIGHT(I$1,2)),1),0)),I25/MAX(NOW()-DATE(VALUE(LEFT(I$1,4)),VALUE(RIGHT(I$1,2)),1),1/24))),"") | J26: =IFERROR(IF(DATE(VALUE(LEFT(J$1,4)),VALUE(RIGHT(J$1,2)),1)>TODAY(),"",IF(EOMONTH(DATE(VALUE(LEFT(J$1,4)),VALUE(RIGHT(J$1,2)),1),0)<TODAY(),J25/DAY(EOMONTH(DATE(VALUE(LEFT(J$1,4)),VALUE(RIGHT(J$1,2)),1),0)),J25/MAX(NOW()-DATE(VALUE(LEFT(J$1,4)),VALUE(RIGHT(J$1,2)),1),1/24))),"") | K26: =IFERROR(IF(DATE(VALUE(LEFT(K$1,4)),VALUE(RIGHT(K$1,2)),1)>TODAY(),"",IF(EOMONTH(DATE(VALUE(LEFT(K$1,4)),VALUE(RIGHT(K$1,2)),1),0)<TODAY(),K25/DAY(EOMONTH(DATE(VALUE(LEFT(K$1,4)),VALUE(RIGHT(K$1,2)),1),0)),K25/MAX(NOW()-DATE(VALUE(LEFT(K$1,4)),VALUE(RIGHT(K$1,2)),1),1/24))),"") | ... O26: =IFERROR(IF(DATE(VALUE(LEFT(O$1,4)),VALUE(RIGHT(O$1,2)),1)>TODAY(),"",IF(EOMONTH(DATE(VALUE(LEFT(O$1,4)),VALUE(RIGHT(O$1,2)),1),0)<TODAY(),O25/DAY(EOMONTH(DATE(VALUE(LEFT(O$1,4)),VALUE(RIGHT(O$1,2)),1),0)),O25/MAX(NOW()-DATE(VALUE(LEFT(O$1,4)),VALUE(RIGHT(O$1,2)),1),1/24))),"") | P26: =SUM(D26:O26)
A27: IE | C27: IE | D27: =SUMIFS('i-shopify-sl'!$I:$I,'i-shopify-sl'!$A:$A,D$1,'i-shopify-sl'!$C:$C,$C27) | E27: =SUMIFS('i-shopify-sl'!$I:$I,'i-shopify-sl'!$A:$A,E$1,'i-shopify-sl'!$C:$C,$C27) | F27: =SUMIFS('i-shopify-sl'!$I:$I,'i-shopify-sl'!$A:$A,F$1,'i-shopify-sl'!$C:$C,$C27) | G27: =SUMIFS('i-shopify-sl'!$I:$I,'i-shopify-sl'!$A:$A,G$1,'i-shopify-sl'!$C:$C,$C27) | H27: =SUMIFS('i-shopify-sl'!$I:$I,'i-shopify-sl'!$A:$A,H$1,'i-shopify-sl'!$C:$C,$C27) | I27: =SUMIFS('i-shopify-sl'!$I:$I,'i-shopify-sl'!$A:$A,I$1,'i-shopify-sl'!$C:$C,$C27) | J27: =SUMIFS('i-shopify-sl'!$I:$I,'i-shopify-sl'!$A:$A,J$1,'i-shopify-sl'!$C:$C,$C27) | K27: =SUMIFS('i-shopify-sl'!$I:$I,'i-shopify-sl'!$A:$A,K$1,'i-shopify-sl'!$C:$C,$C27) | ... O27: =SUMIFS('i-shopify-sl'!$I:$I,'i-shopify-sl'!$A:$A,O$1,'i-shopify-sl'!$C:$C,$C27) | P27: =SUM(D27:O27) | Q27: ->
A28: avg/day | C28: avg/day | D28: =IFERROR(IF(DATE(VALUE(LEFT(D$1,4)),VALUE(RIGHT(D$1,2)),1)>TODAY(),"",IF(EOMONTH(DATE(VALUE(LEFT(D$1,4)),VALUE(RIGHT(D$1,2)),1),0)<TODAY(),D27/DAY(EOMONTH(DATE(VALUE(LEFT(D$1,4)),VALUE(RIGHT(D$1,2)),1),0)),D27/MAX(NOW()-DATE(VALUE(LEFT(D$1,4)),VALUE(RIGHT(D$1,2)),1),1/24))),"") | E28: =IFERROR(IF(DATE(VALUE(LEFT(E$1,4)),VALUE(RIGHT(E$1,2)),1)>TODAY(),"",IF(EOMONTH(DATE(VALUE(LEFT(E$1,4)),VALUE(RIGHT(E$1,2)),1),0)<TODAY(),E27/DAY(EOMONTH(DATE(VALUE(LEFT(E$1,4)),VALUE(RIGHT(E$1,2)),1),0)),E27/MAX(NOW()-DATE(VALUE(LEFT(E$1,4)),VALUE(RIGHT(E$1,2)),1),1/24))),"") | F28: =IFERROR(IF(DATE(VALUE(LEFT(F$1,4)),VALUE(RIGHT(F$1,2)),1)>TODAY(),"",IF(EOMONTH(DATE(VALUE(LEFT(F$1,4)),VALUE(RIGHT(F$1,2)),1),0)<TODAY(),F27/DAY(EOMONTH(DATE(VALUE(LEFT(F$1,4)),VALUE(RIGHT(F$1,2)),1),0)),F27/MAX(NOW()-DATE(VALUE(LEFT(F$1,4)),VALUE(RIGHT(F$1,2)),1),1/24))),"") | G28: =IFERROR(IF(DATE(VALUE(LEFT(G$1,4)),VALUE(RIGHT(G$1,2)),1)>TODAY(),"",IF(EOMONTH(DATE(VALUE(LEFT(G$1,4)),VALUE(RIGHT(G$1,2)),1),0)<TODAY(),G27/DAY(EOMONTH(DATE(VALUE(LEFT(G$1,4)),VALUE(RIGHT(G$1,2)),1),0)),G27/MAX(NOW()-DATE(VALUE(LEFT(G$1,4)),VALUE(RIGHT(G$1,2)),1),1/24))),"") | H28: =IFERROR(IF(DATE(VALUE(LEFT(H$1,4)),VALUE(RIGHT(H$1,2)),1)>TODAY(),"",IF(EOMONTH(DATE(VALUE(LEFT(H$1,4)),VALUE(RIGHT(H$1,2)),1),0)<TODAY(),H27/DAY(EOMONTH(DATE(VALUE(LEFT(H$1,4)),VALUE(RIGHT(H$1,2)),1),0)),H27/MAX(NOW()-DATE(VALUE(LEFT(H$1,4)),VALUE(RIGHT(H$1,2)),1),1/24))),"") | I28: =IFERROR(IF(DATE(VALUE(LEFT(I$1,4)),VALUE(RIGHT(I$1,2)),1)>TODAY(),"",IF(EOMONTH(DATE(VALUE(LEFT(I$1,4)),VALUE(RIGHT(I$1,2)),1),0)<TODAY(),I27/DAY(EOMONTH(DATE(VALUE(LEFT(I$1,4)),VALUE(RIGHT(I$1,2)),1),0)),I27/MAX(NOW()-DATE(VALUE(LEFT(I$1,4)),VALUE(RIGHT(I$1,2)),1),1/24))),"") | J28: =IFERROR(IF(DATE(VALUE(LEFT(J$1,4)),VALUE(RIGHT(J$1,2)),1)>TODAY(),"",IF(EOMONTH(DATE(VALUE(LEFT(J$1,4)),VALUE(RIGHT(J$1,2)),1),0)<TODAY(),J27/DAY(EOMONTH(DATE(VALUE(LEFT(J$1,4)),VALUE(RIGHT(J$1,2)),1),0)),J27/MAX(NOW()-DATE(VALUE(LEFT(J$1,4)),VALUE(RIGHT(J$1,2)),1),1/24))),"") | K28: =IFERROR(IF(DATE(VALUE(LEFT(K$1,4)),VALUE(RIGHT(K$1,2)),1)>TODAY(),"",IF(EOMONTH(DATE(VALUE(LEFT(K$1,4)),VALUE(RIGHT(K$1,2)),1),0)<TODAY(),K27/DAY(EOMONTH(DATE(VALUE(LEFT(K$1,4)),VALUE(RIGHT(K$1,2)),1),0)),K27/MAX(NOW()-DATE(VALUE(LEFT(K$1,4)),VALUE(RIGHT(K$1,2)),1),1/24))),"") | ... O28: =IFERROR(IF(DATE(VALUE(LEFT(O$1,4)),VALUE(RIGHT(O$1,2)),1)>TODAY(),"",IF(EOMONTH(DATE(VALUE(LEFT(O$1,4)),VALUE(RIGHT(O$1,2)),1),0)<TODAY(),O27/DAY(EOMONTH(DATE(VALUE(LEFT(O$1,4)),VALUE(RIGHT(O$1,2)),1),0)),O27/MAX(NOW()-DATE(VALUE(LEFT(O$1,4)),VALUE(RIGHT(O$1,2)),1),1/24))),"") | P28: =SUM(D28:O28)
A29: LU | C29: LU | D29: =SUMIFS('i-shopify-sl'!$I:$I,'i-shopify-sl'!$A:$A,D$1,'i-shopify-sl'!$C:$C,$C29) | E29: =SUMIFS('i-shopify-sl'!$I:$I,'i-shopify-sl'!$A:$A,E$1,'i-shopify-sl'!$C:$C,$C29) | F29: =SUMIFS('i-shopify-sl'!$I:$I,'i-shopify-sl'!$A:$A,F$1,'i-shopify-sl'!$C:$C,$C29) | G29: =SUMIFS('i-shopify-sl'!$I:$I,'i-shopify-sl'!$A:$A,G$1,'i-shopify-sl'!$C:$C,$C29) | H29: =SUMIFS('i-shopify-sl'!$I:$I,'i-shopify-sl'!$A:$A,H$1,'i-shopify-sl'!$C:$C,$C29) | I29: =SUMIFS('i-shopify-sl'!$I:$I,'i-shopify-sl'!$A:$A,I$1,'i-shopify-sl'!$C:$C,$C29) | J29: =SUMIFS('i-shopify-sl'!$I:$I,'i-shopify-sl'!$A:$A,J$1,'i-shopify-sl'!$C:$C,$C29) | K29: =SUMIFS('i-shopify-sl'!$I:$I,'i-shopify-sl'!$A:$A,K$1,'i-shopify-sl'!$C:$C,$C29) | ... O29: =SUMIFS('i-shopify-sl'!$I:$I,'i-shopify-sl'!$A:$A,O$1,'i-shopify-sl'!$C:$C,$C29) | P29: =SUM(D29:O29) | Q29: ->
A30: avg/day | C30: avg/day | D30: =IFERROR(IF(DATE(VALUE(LEFT(D$1,4)),VALUE(RIGHT(D$1,2)),1)>TODAY(),"",IF(EOMONTH(DATE(VALUE(LEFT(D$1,4)),VALUE(RIGHT(D$1,2)),1),0)<TODAY(),D29/DAY(EOMONTH(DATE(VALUE(LEFT(D$1,4)),VALUE(RIGHT(D$1,2)),1),0)),D29/MAX(NOW()-DATE(VALUE(LEFT(D$1,4)),VALUE(RIGHT(D$1,2)),1),1/24))),"") | E30: =IFERROR(IF(DATE(VALUE(LEFT(E$1,4)),VALUE(RIGHT(E$1,2)),1)>TODAY(),"",IF(EOMONTH(DATE(VALUE(LEFT(E$1,4)),VALUE(RIGHT(E$1,2)),1),0)<TODAY(),E29/DAY(EOMONTH(DATE(VALUE(LEFT(E$1,4)),VALUE(RIGHT(E$1,2)),1),0)),E29/MAX(NOW()-DATE(VALUE(LEFT(E$1,4)),VALUE(RIGHT(E$1,2)),1),1/24))),"") | F30: =IFERROR(IF(DATE(VALUE(LEFT(F$1,4)),VALUE(RIGHT(F$1,2)),1)>TODAY(),"",IF(EOMONTH(DATE(VALUE(LEFT(F$1,4)),VALUE(RIGHT(F$1,2)),1),0)<TODAY(),F29/DAY(EOMONTH(DATE(VALUE(LEFT(F$1,4)),VALUE(RIGHT(F$1,2)),1),0)),F29/MAX(NOW()-DATE(VALUE(LEFT(F$1,4)),VALUE(RIGHT(F$1,2)),1),1/24))),"") | G30: =IFERROR(IF(DATE(VALUE(LEFT(G$1,4)),VALUE(RIGHT(G$1,2)),1)>TODAY(),"",IF(EOMONTH(DATE(VALUE(LEFT(G$1,4)),VALUE(RIGHT(G$1,2)),1),0)<TODAY(),G29/DAY(EOMONTH(DATE(VALUE(LEFT(G$1,4)),VALUE(RIGHT(G$1,2)),1),0)),G29/MAX(NOW()-DATE(VALUE(LEFT(G$1,4)),VALUE(RIGHT(G$1,2)),1),1/24))),"") | H30: =IFERROR(IF(DATE(VALUE(LEFT(H$1,4)),VALUE(RIGHT(H$1,2)),1)>TODAY(),"",IF(EOMONTH(DATE(VALUE(LEFT(H$1,4)),VALUE(RIGHT(H$1,2)),1),0)<TODAY(),H29/DAY(EOMONTH(DATE(VALUE(LEFT(H$1,4)),VALUE(RIGHT(H$1,2)),1),0)),H29/MAX(NOW()-DATE(VALUE(LEFT(H$1,4)),VALUE(RIGHT(H$1,2)),1),1/24))),"") | I30: =IFERROR(IF(DATE(VALUE(LEFT(I$1,4)),VALUE(RIGHT(I$1,2)),1)>TODAY(),"",IF(EOMONTH(DATE(VALUE(LEFT(I$1,4)),VALUE(RIGHT(I$1,2)),1),0)<TODAY(),I29/DAY(EOMONTH(DATE(VALUE(LEFT(I$1,4)),VALUE(RIGHT(I$1,2)),1),0)),I29/MAX(NOW()-DATE(VALUE(LEFT(I$1,4)),VALUE(RIGHT(I$1,2)),1),1/24))),"") | J30: =IFERROR(IF(DATE(VALUE(LEFT(J$1,4)),VALUE(RIGHT(J$1,2)),1)>TODAY(),"",IF(EOMONTH(DATE(VALUE(LEFT(J$1,4)),VALUE(RIGHT(J$1,2)),1),0)<TODAY(),J29/DAY(EOMONTH(DATE(VALUE(LEFT(J$1,4)),VALUE(RIGHT(J$1,2)),1),0)),J29/MAX(NOW()-DATE(VALUE(LEFT(J$1,4)),VALUE(RIGHT(J$1,2)),1),1/24))),"") | K30: =IFERROR(IF(DATE(VALUE(LEFT(K$1,4)),VALUE(RIGHT(K$1,2)),1)>TODAY(),"",IF(EOMONTH(DATE(VALUE(LEFT(K$1,4)),VALUE(RIGHT(K$1,2)),1),0)<TODAY(),K29/DAY(EOMONTH(DATE(VALUE(LEFT(K$1,4)),VALUE(RIGHT(K$1,2)),1),0)),K29/MAX(NOW()-DATE(VALUE(LEFT(K$1,4)),VALUE(RIGHT(K$1,2)),1),1/24))),"") | ... O30: =IFERROR(IF(DATE(VALUE(LEFT(O$1,4)),VALUE(RIGHT(O$1,2)),1)>TODAY(),"",IF(EOMONTH(DATE(VALUE(LEFT(O$1,4)),VALUE(RIGHT(O$1,2)),1),0)<TODAY(),O29/DAY(EOMONTH(DATE(VALUE(LEFT(O$1,4)),VALUE(RIGHT(O$1,2)),1),0)),O29/MAX(NOW()-DATE(VALUE(LEFT(O$1,4)),VALUE(RIGHT(O$1,2)),1),1/24))),"") | P30: =SUM(D30:O30)
A31: PL | C31: PL | D31: =SUMIFS('i-shopify-sl'!$I:$I,'i-shopify-sl'!$A:$A,D$1,'i-shopify-sl'!$C:$C,$C31) | E31: =SUMIFS('i-shopify-sl'!$I:$I,'i-shopify-sl'!$A:$A,E$1,'i-shopify-sl'!$C:$C,$C31) | F31: =SUMIFS('i-shopify-sl'!$I:$I,'i-shopify-sl'!$A:$A,F$1,'i-shopify-sl'!$C:$C,$C31) | G31: =SUMIFS('i-shopify-sl'!$I:$I,'i-shopify-sl'!$A:$A,G$1,'i-shopify-sl'!$C:$C,$C31) | H31: =SUMIFS('i-shopify-sl'!$I:$I,'i-shopify-sl'!$A:$A,H$1,'i-shopify-sl'!$C:$C,$C31) | I31: =SUMIFS('i-shopify-sl'!$I:$I,'i-shopify-sl'!$A:$A,I$1,'i-shopify-sl'!$C:$C,$C31) | J31: =SUMIFS('i-shopify-sl'!$I:$I,'i-shopify-sl'!$A:$A,J$1,'i-shopify-sl'!$C:$C,$C31) | K31: =SUMIFS('i-shopify-sl'!$I:$I,'i-shopify-sl'!$A:$A,K$1,'i-shopify-sl'!$C:$C,$C31) | ... O31: =SUMIFS('i-shopify-sl'!$I:$I,'i-shopify-sl'!$A:$A,O$1,'i-shopify-sl'!$C:$C,$C31) | P31: =SUM(D31:O31) | Q31: ->
A32: avg/day | C32: avg/day | D32: =IFERROR(IF(DATE(VALUE(LEFT(D$1,4)),VALUE(RIGHT(D$1,2)),1)>TODAY(),"",IF(EOMONTH(DATE(VALUE(LEFT(D$1,4)),VALUE(RIGHT(D$1,2)),1),0)<TODAY(),D31/DAY(EOMONTH(DATE(VALUE(LEFT(D$1,4)),VALUE(RIGHT(D$1,2)),1),0)),D31/MAX(NOW()-DATE(VALUE(LEFT(D$1,4)),VALUE(RIGHT(D$1,2)),1),1/24))),"") | E32: =IFERROR(IF(DATE(VALUE(LEFT(E$1,4)),VALUE(RIGHT(E$1,2)),1)>TODAY(),"",IF(EOMONTH(DATE(VALUE(LEFT(E$1,4)),VALUE(RIGHT(E$1,2)),1),0)<TODAY(),E31/DAY(EOMONTH(DATE(VALUE(LEFT(E$1,4)),VALUE(RIGHT(E$1,2)),1),0)),E31/MAX(NOW()-DATE(VALUE(LEFT(E$1,4)),VALUE(RIGHT(E$1,2)),1),1/24))),"") | F32: =IFERROR(IF(DATE(VALUE(LEFT(F$1,4)),VALUE(RIGHT(F$1,2)),1)>TODAY(),"",IF(EOMONTH(DATE(VALUE(LEFT(F$1,4)),VALUE(RIGHT(F$1,2)),1),0)<TODAY(),F31/DAY(EOMONTH(DATE(VALUE(LEFT(F$1,4)),VALUE(RIGHT(F$1,2)),1),0)),F31/MAX(NOW()-DATE(VALUE(LEFT(F$1,4)),VALUE(RIGHT(F$1,2)),1),1/24))),"") | G32: =IFERROR(IF(DATE(VALUE(LEFT(G$1,4)),VALUE(RIGHT(G$1,2)),1)>TODAY(),"",IF(EOMONTH(DATE(VALUE(LEFT(G$1,4)),VALUE(RIGHT(G$1,2)),1),0)<TODAY(),G31/DAY(EOMONTH(DATE(VALUE(LEFT(G$1,4)),VALUE(RIGHT(G$1,2)),1),0)),G31/MAX(NOW()-DATE(VALUE(LEFT(G$1,4)),VALUE(RIGHT(G$1,2)),1),1/24))),"") | H32: =IFERROR(IF(DATE(VALUE(LEFT(H$1,4)),VALUE(RIGHT(H$1,2)),1)>TODAY(),"",IF(EOMONTH(DATE(VALUE(LEFT(H$1,4)),VALUE(RIGHT(H$1,2)),1),0)<TODAY(),H31/DAY(EOMONTH(DATE(VALUE(LEFT(H$1,4)),VALUE(RIGHT(H$1,2)),1),0)),H31/MAX(NOW()-DATE(VALUE(LEFT(H$1,4)),VALUE(RIGHT(H$1,2)),1),1/24))),"") | I32: =IFERROR(IF(DATE(VALUE(LEFT(I$1,4)),VALUE(RIGHT(I$1,2)),1)>TODAY(),"",IF(EOMONTH(DATE(VALUE(LEFT(I$1,4)),VALUE(RIGHT(I$1,2)),1),0)<TODAY(),I31/DAY(EOMONTH(DATE(VALUE(LEFT(I$1,4)),VALUE(RIGHT(I$1,2)),1),0)),I31/MAX(NOW()-DATE(VALUE(LEFT(I$1,4)),VALUE(RIGHT(I$1,2)),1),1/24))),"") | J32: =IFERROR(IF(DATE(VALUE(LEFT(J$1,4)),VALUE(RIGHT(J$1,2)),1)>TODAY(),"",IF(EOMONTH(DATE(VALUE(LEFT(J$1,4)),VALUE(RIGHT(J$1,2)),1),0)<TODAY(),J31/DAY(EOMONTH(DATE(VALUE(LEFT(J$1,4)),VALUE(RIGHT(J$1,2)),1),0)),J31/MAX(NOW()-DATE(VALUE(LEFT(J$1,4)),VALUE(RIGHT(J$1,2)),1),1/24))),"") | K32: =IFERROR(IF(DATE(VALUE(LEFT(K$1,4)),VALUE(RIGHT(K$1,2)),1)>TODAY(),"",IF(EOMONTH(DATE(VALUE(LEFT(K$1,4)),VALUE(RIGHT(K$1,2)),1),0)<TODAY(),K31/DAY(EOMONTH(DATE(VALUE(LEFT(K$1,4)),VALUE(RIGHT(K$1,2)),1),0)),K31/MAX(NOW()-DATE(VALUE(LEFT(K$1,4)),VALUE(RIGHT(K$1,2)),1),1/24))),"") | ... O32: =IFERROR(IF(DATE(VALUE(LEFT(O$1,4)),VALUE(RIGHT(O$1,2)),1)>TODAY(),"",IF(EOMONTH(DATE(VALUE(LEFT(O$1,4)),VALUE(RIGHT(O$1,2)),1),0)<TODAY(),O31/DAY(EOMONTH(DATE(VALUE(LEFT(O$1,4)),VALUE(RIGHT(O$1,2)),1),0)),O31/MAX(NOW()-DATE(VALUE(LEFT(O$1,4)),VALUE(RIGHT(O$1,2)),1),1/24))),"") | P32: =SUM(D32:O32)
A33: SE | C33: SE | D33: =SUMIFS('i-shopify-sl'!$I:$I,'i-shopify-sl'!$A:$A,D$1,'i-shopify-sl'!$C:$C,$C33) | E33: =SUMIFS('i-shopify-sl'!$I:$I,'i-shopify-sl'!$A:$A,E$1,'i-shopify-sl'!$C:$C,$C33) | F33: =SUMIFS('i-shopify-sl'!$I:$I,'i-shopify-sl'!$A:$A,F$1,'i-shopify-sl'!$C:$C,$C33) | G33: =SUMIFS('i-shopify-sl'!$I:$I,'i-shopify-sl'!$A:$A,G$1,'i-shopify-sl'!$C:$C,$C33) | H33: =SUMIFS('i-shopify-sl'!$I:$I,'i-shopify-sl'!$A:$A,H$1,'i-shopify-sl'!$C:$C,$C33) | I33: =SUMIFS('i-shopify-sl'!$I:$I,'i-shopify-sl'!$A:$A,I$1,'i-shopify-sl'!$C:$C,$C33) | J33: =SUMIFS('i-shopify-sl'!$I:$I,'i-shopify-sl'!$A:$A,J$1,'i-shopify-sl'!$C:$C,$C33) | K33: =SUMIFS('i-shopify-sl'!$I:$I,'i-shopify-sl'!$A:$A,K$1,'i-shopify-sl'!$C:$C,$C33) | ... O33: =SUMIFS('i-shopify-sl'!$I:$I,'i-shopify-sl'!$A:$A,O$1,'i-shopify-sl'!$C:$C,$C33) | P33: =SUM(D33:O33) | Q33: ->
A34: avg/day | C34: avg/day | D34: =IFERROR(IF(DATE(VALUE(LEFT(D$1,4)),VALUE(RIGHT(D$1,2)),1)>TODAY(),"",IF(EOMONTH(DATE(VALUE(LEFT(D$1,4)),VALUE(RIGHT(D$1,2)),1),0)<TODAY(),D33/DAY(EOMONTH(DATE(VALUE(LEFT(D$1,4)),VALUE(RIGHT(D$1,2)),1),0)),D33/MAX(NOW()-DATE(VALUE(LEFT(D$1,4)),VALUE(RIGHT(D$1,2)),1),1/24))),"") | E34: =IFERROR(IF(DATE(VALUE(LEFT(E$1,4)),VALUE(RIGHT(E$1,2)),1)>TODAY(),"",IF(EOMONTH(DATE(VALUE(LEFT(E$1,4)),VALUE(RIGHT(E$1,2)),1),0)<TODAY(),E33/DAY(EOMONTH(DATE(VALUE(LEFT(E$1,4)),VALUE(RIGHT(E$1,2)),1),0)),E33/MAX(NOW()-DATE(VALUE(LEFT(E$1,4)),VALUE(RIGHT(E$1,2)),1),1/24))),"") | F34: =IFERROR(IF(DATE(VALUE(LEFT(F$1,4)),VALUE(RIGHT(F$1,2)),1)>TODAY(),"",IF(EOMONTH(DATE(VALUE(LEFT(F$1,4)),VALUE(RIGHT(F$1,2)),1),0)<TODAY(),F33/DAY(EOMONTH(DATE(VALUE(LEFT(F$1,4)),VALUE(RIGHT(F$1,2)),1),0)),F33/MAX(NOW()-DATE(VALUE(LEFT(F$1,4)),VALUE(RIGHT(F$1,2)),1),1/24))),"") | G34: =IFERROR(IF(DATE(VALUE(LEFT(G$1,4)),VALUE(RIGHT(G$1,2)),1)>TODAY(),"",IF(EOMONTH(DATE(VALUE(LEFT(G$1,4)),VALUE(RIGHT(G$1,2)),1),0)<TODAY(),G33/DAY(EOMONTH(DATE(VALUE(LEFT(G$1,4)),VALUE(RIGHT(G$1,2)),1),0)),G33/MAX(NOW()-DATE(VALUE(LEFT(G$1,4)),VALUE(RIGHT(G$1,2)),1),1/24))),"") | H34: =IFERROR(IF(DATE(VALUE(LEFT(H$1,4)),VALUE(RIGHT(H$1,2)),1)>TODAY(),"",IF(EOMONTH(DATE(VALUE(LEFT(H$1,4)),VALUE(RIGHT(H$1,2)),1),0)<TODAY(),H33/DAY(EOMONTH(DATE(VALUE(LEFT(H$1,4)),VALUE(RIGHT(H$1,2)),1),0)),H33/MAX(NOW()-DATE(VALUE(LEFT(H$1,4)),VALUE(RIGHT(H$1,2)),1),1/24))),"") | I34: =IFERROR(IF(DATE(VALUE(LEFT(I$1,4)),VALUE(RIGHT(I$1,2)),1)>TODAY(),"",IF(EOMONTH(DATE(VALUE(LEFT(I$1,4)),VALUE(RIGHT(I$1,2)),1),0)<TODAY(),I33/DAY(EOMONTH(DATE(VALUE(LEFT(I$1,4)),VALUE(RIGHT(I$1,2)),1),0)),I33/MAX(NOW()-DATE(VALUE(LEFT(I$1,4)),VALUE(RIGHT(I$1,2)),1),1/24))),"") | J34: =IFERROR(IF(DATE(VALUE(LEFT(J$1,4)),VALUE(RIGHT(J$1,2)),1)>TODAY(),"",IF(EOMONTH(DATE(VALUE(LEFT(J$1,4)),VALUE(RIGHT(J$1,2)),1),0)<TODAY(),J33/DAY(EOMONTH(DATE(VALUE(LEFT(J$1,4)),VALUE(RIGHT(J$1,2)),1),0)),J33/MAX(NOW()-DATE(VALUE(LEFT(J$1,4)),VALUE(RIGHT(J$1,2)),1),1/24))),"") | K34: =IFERROR(IF(DATE(VALUE(LEFT(K$1,4)),VALUE(RIGHT(K$1,2)),1)>TODAY(),"",IF(EOMONTH(DATE(VALUE(LEFT(K$1,4)),VALUE(RIGHT(K$1,2)),1),0)<TODAY(),K33/DAY(EOMONTH(DATE(VALUE(LEFT(K$1,4)),VALUE(RIGHT(K$1,2)),1),0)),K33/MAX(NOW()-DATE(VALUE(LEFT(K$1,4)),VALUE(RIGHT(K$1,2)),1),1/24))),"") | ... O34: =IFERROR(IF(DATE(VALUE(LEFT(O$1,4)),VALUE(RIGHT(O$1,2)),1)>TODAY(),"",IF(EOMONTH(DATE(VALUE(LEFT(O$1,4)),VALUE(RIGHT(O$1,2)),1),0)<TODAY(),O33/DAY(EOMONTH(DATE(VALUE(LEFT(O$1,4)),VALUE(RIGHT(O$1,2)),1),0)),O33/MAX(NOW()-DATE(VALUE(LEFT(O$1,4)),VALUE(RIGHT(O$1,2)),1),1/24))),"") | P34: =SUM(D34:O34)
A35: Marketplaces | C35: Marketplaces | D35: =SUM(D36:D39) | E35: =SUM(E36:E39) | F35: =SUM(F36:F39) | G35: =SUM(G36:G39) | H35: =SUM(H36:H39) | I35: =SUM(I36:I39) | J35: =SUM(J36:J39) | K35: =SUM(K36:K39) | ... O35: =SUM(O36:O39) | P35: =SUM(D35:O35) | Q35: ->
A36: HANNUN | C36: HANNUN | D36: =SUMIFS('i-marketplaces-sl'!$I:$I,'i-marketplaces-sl'!$A:$A,D$1,'i-marketplaces-sl'!$C:$C,"HANNUN") | E36: =SUMIFS('i-marketplaces-sl'!$I:$I,'i-marketplaces-sl'!$A:$A,E$1,'i-marketplaces-sl'!$C:$C,"HANNUN") | F36: =SUMIFS('i-marketplaces-sl'!$I:$I,'i-marketplaces-sl'!$A:$A,F$1,'i-marketplaces-sl'!$C:$C,"HANNUN") | G36: =SUMIFS('i-marketplaces-sl'!$I:$I,'i-marketplaces-sl'!$A:$A,G$1,'i-marketplaces-sl'!$C:$C,"HANNUN") | H36: =SUMIFS('i-marketplaces-sl'!$I:$I,'i-marketplaces-sl'!$A:$A,H$1,'i-marketplaces-sl'!$C:$C,"HANNUN") | I36: =SUMIFS('i-marketplaces-sl'!$I:$I,'i-marketplaces-sl'!$A:$A,I$1,'i-marketplaces-sl'!$C:$C,"HANNUN") | J36: =SUMIFS('i-marketplaces-sl'!$I:$I,'i-marketplaces-sl'!$A:$A,J$1,'i-marketplaces-sl'!$C:$C,"HANNUN") | K36: =SUMIFS('i-marketplaces-sl'!$I:$I,'i-marketplaces-sl'!$A:$A,K$1,'i-marketplaces-sl'!$C:$C,"HANNUN") | ... O36: =SUMIFS('i-marketplaces-sl'!$I:$I,'i-marketplaces-sl'!$A:$A,O$1,'i-marketplaces-sl'!$C:$C,"HANNUN") | P36: =SUM(D36:O36) | Q36: ->
A37: TOASTY | C37: TOASTY | D37: =SUMIFS('i-marketplaces-sl'!$I:$I,'i-marketplaces-sl'!$A:$A,D$1,'i-marketplaces-sl'!$C:$C,"TOASTY") | E37: =SUMIFS('i-marketplaces-sl'!$I:$I,'i-marketplaces-sl'!$A:$A,E$1,'i-marketplaces-sl'!$C:$C,"TOASTY") | F37: =SUMIFS('i-marketplaces-sl'!$I:$I,'i-marketplaces-sl'!$A:$A,F$1,'i-marketplaces-sl'!$C:$C,"TOASTY") | G37: =SUMIFS('i-marketplaces-sl'!$I:$I,'i-marketplaces-sl'!$A:$A,G$1,'i-marketplaces-sl'!$C:$C,"TOASTY") | H37: =SUMIFS('i-marketplaces-sl'!$I:$I,'i-marketplaces-sl'!$A:$A,H$1,'i-marketplaces-sl'!$C:$C,"TOASTY") | I37: =SUMIFS('i-marketplaces-sl'!$I:$I,'i-marketplaces-sl'!$A:$A,I$1,'i-marketplaces-sl'!$C:$C,"TOASTY") | J37: =SUMIFS('i-marketplaces-sl'!$I:$I,'i-marketplaces-sl'!$A:$A,J$1,'i-marketplaces-sl'!$C:$C,"TOASTY") | K37: =SUMIFS('i-marketplaces-sl'!$I:$I,'i-marketplaces-sl'!$A:$A,K$1,'i-marketplaces-sl'!$C:$C,"TOASTY") | ... O37: =SUMIFS('i-marketplaces-sl'!$I:$I,'i-marketplaces-sl'!$A:$A,O$1,'i-marketplaces-sl'!$C:$C,"TOASTY") | P37: =SUM(D37:O37) | Q37: ->
A38: CHOOSE | C38: CHOOSE | D38: =SUMIFS('i-marketplaces-sl'!$I:$I,'i-marketplaces-sl'!$A:$A,D$1,'i-marketplaces-sl'!$C:$C,"CHOOSE") | E38: =SUMIFS('i-marketplaces-sl'!$I:$I,'i-marketplaces-sl'!$A:$A,E$1,'i-marketplaces-sl'!$C:$C,"CHOOSE") | F38: =SUMIFS('i-marketplaces-sl'!$I:$I,'i-marketplaces-sl'!$A:$A,F$1,'i-marketplaces-sl'!$C:$C,"CHOOSE") | G38: =SUMIFS('i-marketplaces-sl'!$I:$I,'i-marketplaces-sl'!$A:$A,G$1,'i-marketplaces-sl'!$C:$C,"CHOOSE") | H38: =SUMIFS('i-marketplaces-sl'!$I:$I,'i-marketplaces-sl'!$A:$A,H$1,'i-marketplaces-sl'!$C:$C,"CHOOSE") | I38: =SUMIFS('i-marketplaces-sl'!$I:$I,'i-marketplaces-sl'!$A:$A,I$1,'i-marketplaces-sl'!$C:$C,"CHOOSE") | J38: =SUMIFS('i-marketplaces-sl'!$I:$I,'i-marketplaces-sl'!$A:$A,J$1,'i-marketplaces-sl'!$C:$C,"CHOOSE") | K38: =SUMIFS('i-marketplaces-sl'!$I:$I,'i-marketplaces-sl'!$A:$A,K$1,'i-marketplaces-sl'!$C:$C,"CHOOSE") | ... O38: =SUMIFS('i-marketplaces-sl'!$I:$I,'i-marketplaces-sl'!$A:$A,O$1,'i-marketplaces-sl'!$C:$C,"CHOOSE") | P38: =SUM(D38:O38) | Q38: ->
A39: MAISONSDUMONDE | C39: MAISONSDUMONDE | D39: =SUMIFS('i-marketplaces-sl'!$I:$I,'i-marketplaces-sl'!$A:$A,D$1,'i-marketplaces-sl'!$C:$C,"MAISONS") | E39: =SUMIFS('i-marketplaces-sl'!$I:$I,'i-marketplaces-sl'!$A:$A,E$1,'i-marketplaces-sl'!$C:$C,"MAISONS") | F39: =SUMIFS('i-marketplaces-sl'!$I:$I,'i-marketplaces-sl'!$A:$A,F$1,'i-marketplaces-sl'!$C:$C,"MAISONS") | G39: =SUMIFS('i-marketplaces-sl'!$I:$I,'i-marketplaces-sl'!$A:$A,G$1,'i-marketplaces-sl'!$C:$C,"MAISONS") | H39: =SUMIFS('i-marketplaces-sl'!$I:$I,'i-marketplaces-sl'!$A:$A,H$1,'i-marketplaces-sl'!$C:$C,"MAISONS") | I39: =SUMIFS('i-marketplaces-sl'!$I:$I,'i-marketplaces-sl'!$A:$A,I$1,'i-marketplaces-sl'!$C:$C,"MAISONS") | J39: =SUMIFS('i-marketplaces-sl'!$I:$I,'i-marketplaces-sl'!$A:$A,J$1,'i-marketplaces-sl'!$C:$C,"MAISONS") | K39: =SUMIFS('i-marketplaces-sl'!$I:$I,'i-marketplaces-sl'!$A:$A,K$1,'i-marketplaces-sl'!$C:$C,"MAISONS") | ... O39: =SUMIFS('i-marketplaces-sl'!$I:$I,'i-marketplaces-sl'!$A:$A,O$1,'i-marketplaces-sl'!$C:$C,"MAISONS") | P39: =SUM(D39:O39) | Q39: ->
A40: Rappels | C40: Rappels | D40: =D41 | E40: =E41 | F40: =F41 | G40: =G41 | H40: =H41 | I40: =I41 | J40: =J41 | K40: =K41 | ... O40: =O41 | P40: =SUM(D40:O40) | Q40: ->
A41: LIVITUM | C41: LIVITUM | D41: =SUMIFS('i-rappels-sl'!$I:$I,'i-rappels-sl'!$A:$A,D$1,'i-rappels-sl'!$C:$C,$C41) | E41: =SUMIFS('i-rappels-sl'!$I:$I,'i-rappels-sl'!$A:$A,E$1,'i-rappels-sl'!$C:$C,$C41) | F41: =SUMIFS('i-rappels-sl'!$I:$I,'i-rappels-sl'!$A:$A,F$1,'i-rappels-sl'!$C:$C,$C41) | G41: =SUMIFS('i-rappels-sl'!$I:$I,'i-rappels-sl'!$A:$A,G$1,'i-rappels-sl'!$C:$C,$C41) | H41: =SUMIFS('i-rappels-sl'!$I:$I,'i-rappels-sl'!$A:$A,H$1,'i-rappels-sl'!$C:$C,$C41) | I41: =SUMIFS('i-rappels-sl'!$I:$I,'i-rappels-sl'!$A:$A,I$1,'i-rappels-sl'!$C:$C,$C41) | J41: =SUMIFS('i-rappels-sl'!$I:$I,'i-rappels-sl'!$A:$A,J$1,'i-rappels-sl'!$C:$C,$C41) | K41: =SUMIFS('i-rappels-sl'!$I:$I,'i-rappels-sl'!$A:$A,K$1,'i-rappels-sl'!$C:$C,$C41) | ... O41: =SUMIFS('i-rappels-sl'!$I:$I,'i-rappels-sl'!$A:$A,O$1,'i-rappels-sl'!$C:$C,$C41) | P41: =SUM(D41:O41) | Q41: ->
A42: Supplies | C42: Supplies | D42: =D43 | E42: =E43 | F42: =F43 | G42: =G43 | H42: =H43 | I42: =I43 | J42: =J43 | K42: =K43 | ... O42: =O43 | P42: =SUM(D42:O42) | Q42: ->
A43: REVER | C43: REVER | D43: =SUMIFS('i-supplies-sl'!$I:$I,'i-supplies-sl'!$A:$A,D$1,'i-supplies-sl'!$C:$C,$C43) | E43: =SUMIFS('i-supplies-sl'!$I:$I,'i-supplies-sl'!$A:$A,E$1,'i-supplies-sl'!$C:$C,$C43) | F43: =SUMIFS('i-supplies-sl'!$I:$I,'i-supplies-sl'!$A:$A,F$1,'i-supplies-sl'!$C:$C,$C43) | G43: =SUMIFS('i-supplies-sl'!$I:$I,'i-supplies-sl'!$A:$A,G$1,'i-supplies-sl'!$C:$C,$C43) | H43: =SUMIFS('i-supplies-sl'!$I:$I,'i-supplies-sl'!$A:$A,H$1,'i-supplies-sl'!$C:$C,$C43) | I43: =SUMIFS('i-supplies-sl'!$I:$I,'i-supplies-sl'!$A:$A,I$1,'i-supplies-sl'!$C:$C,$C43) | J43: =SUMIFS('i-supplies-sl'!$I:$I,'i-supplies-sl'!$A:$A,J$1,'i-supplies-sl'!$C:$C,$C43) | K43: =SUMIFS('i-supplies-sl'!$I:$I,'i-supplies-sl'!$A:$A,K$1,'i-supplies-sl'!$C:$C,$C43) | ... O43: =SUMIFS('i-supplies-sl'!$I:$I,'i-supplies-sl'!$A:$A,O$1,'i-supplies-sl'!$C:$C,$C43) | P43: =SUM(D43:O43) | Q43: ->
P44: =SUM(D44:O44)
A45: Services | B45: Services | D45: =SUM(D46:D49) | E45: =SUM(E46:E49) | F45: =SUM(F46:F49) | G45: =SUM(G46:G49) | H45: =SUM(H46:H49) | I45: =SUM(I46:I49) | J45: =SUM(J46:J49) | K45: =SUM(K46:K49) | ... O45: =SUM(O46:O49) | P45: =SUM(D45:O45) | Q45: ->
A46: HANNUN | C46: HANNUN | D46: =SUMIFS('i-services-sl'!$I:$I,'i-services-sl'!$A:$A,D$1,'i-services-sl'!$C:$C,$C46) | E46: =SUMIFS('i-services-sl'!$I:$I,'i-services-sl'!$A:$A,E$1,'i-services-sl'!$C:$C,$C46) | F46: =SUMIFS('i-services-sl'!$I:$I,'i-services-sl'!$A:$A,F$1,'i-services-sl'!$C:$C,$C46) | G46: =SUMIFS('i-services-sl'!$I:$I,'i-services-sl'!$A:$A,G$1,'i-services-sl'!$C:$C,$C46) | H46: =SUMIFS('i-services-sl'!$I:$I,'i-services-sl'!$A:$A,H$1,'i-services-sl'!$C:$C,$C46) | I46: =SUMIFS('i-services-sl'!$I:$I,'i-services-sl'!$A:$A,I$1,'i-services-sl'!$C:$C,$C46) | J46: =SUMIFS('i-services-sl'!$I:$I,'i-services-sl'!$A:$A,J$1,'i-services-sl'!$C:$C,$C46) | K46: =SUMIFS('i-services-sl'!$I:$I,'i-services-sl'!$A:$A,K$1,'i-services-sl'!$C:$C,$C46) | ... O46: =SUMIFS('i-services-sl'!$I:$I,'i-services-sl'!$A:$A,O$1,'i-services-sl'!$C:$C,$C46) | P46: =SUM(D46:O46) | Q46: ->
A47: QHANDS | C47: QHANDS | D47: =SUMIFS('i-services-sl'!$I:$I,'i-services-sl'!$A:$A,D$1,'i-services-sl'!$C:$C,$C47) | E47: =SUMIFS('i-services-sl'!$I:$I,'i-services-sl'!$A:$A,E$1,'i-services-sl'!$C:$C,$C47) | F47: =SUMIFS('i-services-sl'!$I:$I,'i-services-sl'!$A:$A,F$1,'i-services-sl'!$C:$C,$C47) | G47: =SUMIFS('i-services-sl'!$I:$I,'i-services-sl'!$A:$A,G$1,'i-services-sl'!$C:$C,$C47) | H47: =SUMIFS('i-services-sl'!$I:$I,'i-services-sl'!$A:$A,H$1,'i-services-sl'!$C:$C,$C47) | I47: =SUMIFS('i-services-sl'!$I:$I,'i-services-sl'!$A:$A,I$1,'i-services-sl'!$C:$C,$C47) | J47: =SUMIFS('i-services-sl'!$I:$I,'i-services-sl'!$A:$A,J$1,'i-services-sl'!$C:$C,$C47) | K47: =SUMIFS('i-services-sl'!$I:$I,'i-services-sl'!$A:$A,K$1,'i-services-sl'!$C:$C,$C47) | ... O47: =SUMIFS('i-services-sl'!$I:$I,'i-services-sl'!$A:$A,O$1,'i-services-sl'!$C:$C,$C47) | P47: =SUM(D47:O47) | Q47: ->
A48: Ltd | C48: Ltd | D48: =SUMIFS('i-services-sl'!$I:$I,'i-services-sl'!$A:$A,D$1,'i-services-sl'!$C:$C,$C48) | E48: =SUMIFS('i-services-sl'!$I:$I,'i-services-sl'!$A:$A,E$1,'i-services-sl'!$C:$C,$C48) | F48: =SUMIFS('i-services-sl'!$I:$I,'i-services-sl'!$A:$A,F$1,'i-services-sl'!$C:$C,$C48) | G48: =SUMIFS('i-services-sl'!$I:$I,'i-services-sl'!$A:$A,G$1,'i-services-sl'!$C:$C,$C48) | H48: =SUMIFS('i-services-sl'!$I:$I,'i-services-sl'!$A:$A,H$1,'i-services-sl'!$C:$C,$C48) | I48: =SUMIFS('i-services-sl'!$I:$I,'i-services-sl'!$A:$A,I$1,'i-services-sl'!$C:$C,$C48) | J48: =SUMIFS('i-services-sl'!$I:$I,'i-services-sl'!$A:$A,J$1,'i-services-sl'!$C:$C,$C48) | K48: =SUMIFS('i-services-sl'!$I:$I,'i-services-sl'!$A:$A,K$1,'i-services-sl'!$C:$C,$C48) | ... O48: =SUMIFS('i-services-sl'!$I:$I,'i-services-sl'!$A:$A,O$1,'i-services-sl'!$C:$C,$C48) | P48: =SUM(D48:O48) | Q48: ->
A49: Inc | C49: Inc | D49: =SUMIFS('i-services-sl'!$I:$I,'i-services-sl'!$A:$A,D$1,'i-services-sl'!$C:$C,$C49) | E49: =SUMIFS('i-services-sl'!$I:$I,'i-services-sl'!$A:$A,E$1,'i-services-sl'!$C:$C,$C49) | F49: =SUMIFS('i-services-sl'!$I:$I,'i-services-sl'!$A:$A,F$1,'i-services-sl'!$C:$C,$C49) | G49: =SUMIFS('i-services-sl'!$I:$I,'i-services-sl'!$A:$A,G$1,'i-services-sl'!$C:$C,$C49) | H49: =SUMIFS('i-services-sl'!$I:$I,'i-services-sl'!$A:$A,H$1,'i-services-sl'!$C:$C,$C49) | I49: =SUMIFS('i-services-sl'!$I:$I,'i-services-sl'!$A:$A,I$1,'i-services-sl'!$C:$C,$C49) | J49: =SUMIFS('i-services-sl'!$I:$I,'i-services-sl'!$A:$A,J$1,'i-services-sl'!$C:$C,$C49) | K49: =SUMIFS('i-services-sl'!$I:$I,'i-services-sl'!$A:$A,K$1,'i-services-sl'!$C:$C,$C49) | ... O49: =SUMIFS('i-services-sl'!$I:$I,'i-services-sl'!$A:$A,O$1,'i-services-sl'!$C:$C,$C49) | P49: =SUM(D49:O49) | Q49: ->
A50: Uncategorized income | B50: Uncategorized income | D50: 3586.77 | G50: 67.1 | I50: 0.01 | P50: =SUM(D50:O50)
P51: =SUM(D51:O51)
A52: Expenses | D52: =D53+D84 | E52: =E53+E84 | F52: =F53+F84 | G52: =G53+G84 | H52: =H53+H84 | I52: =I53+I84 | J52: =J53+J84 | K52: =K53+K84 | ... O52: =O53+O84 | P52: =SUM(D52:O52)
A53: COGS | B53: COGS | D53: =D54+D61+D68+D74 | E53: =E54+E61+E68+E74 | F53: =F54+F61+F68+F74 | G53: =G54+G61+G68+G74 | H53: =H54+H61+H68+H74 | I53: =I54+I61+I68+I74 | J53: =J54+J61+J68+J74 | K53: =K54+K61+K68+K74 | ... O53: =O54+O61+O68+O74 | P53: =SUM(D53:O53)
A54: Manufacturing (% sales) | C54: Manufacturing (% sales) | D54: =SUM(D55:D59) | E54: =SUM(E55:E59) | F54: =SUM(F55:F59) | G54: =SUM(G55:G59) | H54: =SUM(H55:H59) | I54: =SUM(I55:I59) | J54: =SUM(J55:J59) | K54: =SUM(K55:K59) | ... O54: =SUM(O55:O59) | P54: =SUM(D54:O54) | Q54: ->
A55: APPHOTOCAN | C55: APPHOTOCAN | D55: =SUMIFS('g-expenses-sl'!$K:$K,'g-expenses-sl'!$A:$A,D$1,'g-expenses-sl'!$D:$D,"manufacturing",'g-expenses-sl'!$E:$E,$C55) | E55: =SUMIFS('g-expenses-sl'!$K:$K,'g-expenses-sl'!$A:$A,E$1,'g-expenses-sl'!$D:$D,"manufacturing",'g-expenses-sl'!$E:$E,$C55) | F55: =SUMIFS('g-expenses-sl'!$K:$K,'g-expenses-sl'!$A:$A,F$1,'g-expenses-sl'!$D:$D,"manufacturing",'g-expenses-sl'!$E:$E,$C55) | G55: =SUMIFS('g-expenses-sl'!$K:$K,'g-expenses-sl'!$A:$A,G$1,'g-expenses-sl'!$D:$D,"manufacturing",'g-expenses-sl'!$E:$E,$C55) | H55: =SUMIFS('g-expenses-sl'!$K:$K,'g-expenses-sl'!$A:$A,H$1,'g-expenses-sl'!$D:$D,"manufacturing",'g-expenses-sl'!$E:$E,$C55) | I55: =SUMIFS('g-expenses-sl'!$K:$K,'g-expenses-sl'!$A:$A,I$1,'g-expenses-sl'!$D:$D,"manufacturing",'g-expenses-sl'!$E:$E,$C55) | J55: =SUMIFS('g-expenses-sl'!$K:$K,'g-expenses-sl'!$A:$A,J$1,'g-expenses-sl'!$D:$D,"manufacturing",'g-expenses-sl'!$E:$E,$C55) | K55: =SUMIFS('g-expenses-sl'!$K:$K,'g-expenses-sl'!$A:$A,K$1,'g-expenses-sl'!$D:$D,"manufacturing",'g-expenses-sl'!$E:$E,$C55) | ... O55: =SUMIFS('g-expenses-sl'!$K:$K,'g-expenses-sl'!$A:$A,O$1,'g-expenses-sl'!$D:$D,"manufacturing",'g-expenses-sl'!$E:$E,$C55) | P55: =SUM(D55:O55) | Q55: ->
A56: APPHOTOES | C56: APPHOTOES | D56: =SUMIFS('g-expenses-sl'!$K:$K,'g-expenses-sl'!$A:$A,D$1,'g-expenses-sl'!$D:$D,"manufacturing",'g-expenses-sl'!$E:$E,$C56) | E56: =SUMIFS('g-expenses-sl'!$K:$K,'g-expenses-sl'!$A:$A,E$1,'g-expenses-sl'!$D:$D,"manufacturing",'g-expenses-sl'!$E:$E,$C56) | F56: =SUMIFS('g-expenses-sl'!$K:$K,'g-expenses-sl'!$A:$A,F$1,'g-expenses-sl'!$D:$D,"manufacturing",'g-expenses-sl'!$E:$E,$C56) | G56: =SUMIFS('g-expenses-sl'!$K:$K,'g-expenses-sl'!$A:$A,G$1,'g-expenses-sl'!$D:$D,"manufacturing",'g-expenses-sl'!$E:$E,$C56) | H56: =SUMIFS('g-expenses-sl'!$K:$K,'g-expenses-sl'!$A:$A,H$1,'g-expenses-sl'!$D:$D,"manufacturing",'g-expenses-sl'!$E:$E,$C56) | I56: =SUMIFS('g-expenses-sl'!$K:$K,'g-expenses-sl'!$A:$A,I$1,'g-expenses-sl'!$D:$D,"manufacturing",'g-expenses-sl'!$E:$E,$C56) | J56: =SUMIFS('g-expenses-sl'!$K:$K,'g-expenses-sl'!$A:$A,J$1,'g-expenses-sl'!$D:$D,"manufacturing",'g-expenses-sl'!$E:$E,$C56) | K56: =SUMIFS('g-expenses-sl'!$K:$K,'g-expenses-sl'!$A:$A,K$1,'g-expenses-sl'!$D:$D,"manufacturing",'g-expenses-sl'!$E:$E,$C56) | ... O56: =SUMIFS('g-expenses-sl'!$K:$K,'g-expenses-sl'!$A:$A,O$1,'g-expenses-sl'!$D:$D,"manufacturing",'g-expenses-sl'!$E:$E,$C56) | P56: =SUM(D56:O56) | Q56: ->
A57: ARTLINK | C57: ARTLINK | D57: =SUMIFS('g-expenses-sl'!$K:$K,'g-expenses-sl'!$A:$A,D$1,'g-expenses-sl'!$D:$D,"manufacturing",'g-expenses-sl'!$E:$E,$C57) | E57: =SUMIFS('g-expenses-sl'!$K:$K,'g-expenses-sl'!$A:$A,E$1,'g-expenses-sl'!$D:$D,"manufacturing",'g-expenses-sl'!$E:$E,$C57) | F57: =SUMIFS('g-expenses-sl'!$K:$K,'g-expenses-sl'!$A:$A,F$1,'g-expenses-sl'!$D:$D,"manufacturing",'g-expenses-sl'!$E:$E,$C57) | G57: =SUMIFS('g-expenses-sl'!$K:$K,'g-expenses-sl'!$A:$A,G$1,'g-expenses-sl'!$D:$D,"manufacturing",'g-expenses-sl'!$E:$E,$C57) | H57: =SUMIFS('g-expenses-sl'!$K:$K,'g-expenses-sl'!$A:$A,H$1,'g-expenses-sl'!$D:$D,"manufacturing",'g-expenses-sl'!$E:$E,$C57) | I57: =SUMIFS('g-expenses-sl'!$K:$K,'g-expenses-sl'!$A:$A,I$1,'g-expenses-sl'!$D:$D,"manufacturing",'g-expenses-sl'!$E:$E,$C57) | J57: =SUMIFS('g-expenses-sl'!$K:$K,'g-expenses-sl'!$A:$A,J$1,'g-expenses-sl'!$D:$D,"manufacturing",'g-expenses-sl'!$E:$E,$C57) | K57: =SUMIFS('g-expenses-sl'!$K:$K,'g-expenses-sl'!$A:$A,K$1,'g-expenses-sl'!$D:$D,"manufacturing",'g-expenses-sl'!$E:$E,$C57) | ... O57: =SUMIFS('g-expenses-sl'!$K:$K,'g-expenses-sl'!$A:$A,O$1,'g-expenses-sl'!$D:$D,"manufacturing",'g-expenses-sl'!$E:$E,$C57) | P57: =SUM(D57:O57) | Q57: ->
A58: DCT | C58: DCT | D58: =SUMIFS('g-expenses-sl'!$K:$K,'g-expenses-sl'!$A:$A,D$1,'g-expenses-sl'!$D:$D,"manufacturing",'g-expenses-sl'!$E:$E,$C58) | E58: =SUMIFS('g-expenses-sl'!$K:$K,'g-expenses-sl'!$A:$A,E$1,'g-expenses-sl'!$D:$D,"manufacturing",'g-expenses-sl'!$E:$E,$C58) | F58: =SUMIFS('g-expenses-sl'!$K:$K,'g-expenses-sl'!$A:$A,F$1,'g-expenses-sl'!$D:$D,"manufacturing",'g-expenses-sl'!$E:$E,$C58) | G58: =SUMIFS('g-expenses-sl'!$K:$K,'g-expenses-sl'!$A:$A,G$1,'g-expenses-sl'!$D:$D,"manufacturing",'g-expenses-sl'!$E:$E,$C58) | H58: =SUMIFS('g-expenses-sl'!$K:$K,'g-expenses-sl'!$A:$A,H$1,'g-expenses-sl'!$D:$D,"manufacturing",'g-expenses-sl'!$E:$E,$C58) | I58: =SUMIFS('g-expenses-sl'!$K:$K,'g-expenses-sl'!$A:$A,I$1,'g-expenses-sl'!$D:$D,"manufacturing",'g-expenses-sl'!$E:$E,$C58) | J58: =SUMIFS('g-expenses-sl'!$K:$K,'g-expenses-sl'!$A:$A,J$1,'g-expenses-sl'!$D:$D,"manufacturing",'g-expenses-sl'!$E:$E,$C58) | K58: =SUMIFS('g-expenses-sl'!$K:$K,'g-expenses-sl'!$A:$A,K$1,'g-expenses-sl'!$D:$D,"manufacturing",'g-expenses-sl'!$E:$E,$C58) | ... O58: =SUMIFS('g-expenses-sl'!$K:$K,'g-expenses-sl'!$A:$A,O$1,'g-expenses-sl'!$D:$D,"manufacturing",'g-expenses-sl'!$E:$E,$C58) | P58: =SUM(D58:O58) | Q58: ->
A59: PRESSING | C59: PRESSING | D59: =SUMIFS('g-expenses-sl'!$K:$K,'g-expenses-sl'!$A:$A,D$1,'g-expenses-sl'!$D:$D,"manufacturing",'g-expenses-sl'!$E:$E,$C59) | E59: =SUMIFS('g-expenses-sl'!$K:$K,'g-expenses-sl'!$A:$A,E$1,'g-expenses-sl'!$D:$D,"manufacturing",'g-expenses-sl'!$E:$E,$C59) | F59: =SUMIFS('g-expenses-sl'!$K:$K,'g-expenses-sl'!$A:$A,F$1,'g-expenses-sl'!$D:$D,"manufacturing",'g-expenses-sl'!$E:$E,$C59) | G59: =SUMIFS('g-expenses-sl'!$K:$K,'g-expenses-sl'!$A:$A,G$1,'g-expenses-sl'!$D:$D,"manufacturing",'g-expenses-sl'!$E:$E,$C59) | H59: =SUMIFS('g-expenses-sl'!$K:$K,'g-expenses-sl'!$A:$A,H$1,'g-expenses-sl'!$D:$D,"manufacturing",'g-expenses-sl'!$E:$E,$C59) | I59: =SUMIFS('g-expenses-sl'!$K:$K,'g-expenses-sl'!$A:$A,I$1,'g-expenses-sl'!$D:$D,"manufacturing",'g-expenses-sl'!$E:$E,$C59) | J59: =SUMIFS('g-expenses-sl'!$K:$K,'g-expenses-sl'!$A:$A,J$1,'g-expenses-sl'!$D:$D,"manufacturing",'g-expenses-sl'!$E:$E,$C59) | K59: =SUMIFS('g-expenses-sl'!$K:$K,'g-expenses-sl'!$A:$A,K$1,'g-expenses-sl'!$D:$D,"manufacturing",'g-expenses-sl'!$E:$E,$C59) | ... O59: =SUMIFS('g-expenses-sl'!$K:$K,'g-expenses-sl'!$A:$A,O$1,'g-expenses-sl'!$D:$D,"manufacturing",'g-expenses-sl'!$E:$E,$C59) | P59: =SUM(D59:O59) | Q59: ->
A60: % Manufacturing / sales | C60: % Manufacturing / sales | D60: =IFERROR(D54/D5,0) | E60: =IFERROR(E54/E5,0) | F60: =IFERROR(F54/F5,0) | G60: =IFERROR(G54/G5,0) | H60: =IFERROR(H54/H5,0) | I60: =IFERROR(I54/I5,0) | J60: =IFERROR(J54/J5,0) | K60: =IFERROR(K54/K5,0) | ... P60: =IFERROR(P54/P5,0)
A61: Logistics (% sales) | C61: Logistics (% sales) | D61: =SUM(D62:D66) | E61: =SUM(E62:E66) | F61: =SUM(F62:F66) | G61: =SUM(G62:G66) | H61: =SUM(H62:H66) | I61: =SUM(I62:I66) | J61: =SUM(J62:J66) | K61: =SUM(K62:K66) | ... O61: =SUM(O62:O66) | P61: =SUM(D61:O61) | Q61: ->
A62: CORREOS | C62: CORREOS | D62: =SUMIFS('g-expenses-sl'!$K:$K,'g-expenses-sl'!$A:$A,D$1,'g-expenses-sl'!$D:$D,"logistics",'g-expenses-sl'!$E:$E,$C62) | E62: =SUMIFS('g-expenses-sl'!$K:$K,'g-expenses-sl'!$A:$A,E$1,'g-expenses-sl'!$D:$D,"logistics",'g-expenses-sl'!$E:$E,$C62) | F62: =SUMIFS('g-expenses-sl'!$K:$K,'g-expenses-sl'!$A:$A,F$1,'g-expenses-sl'!$D:$D,"logistics",'g-expenses-sl'!$E:$E,$C62) | G62: =SUMIFS('g-expenses-sl'!$K:$K,'g-expenses-sl'!$A:$A,G$1,'g-expenses-sl'!$D:$D,"logistics",'g-expenses-sl'!$E:$E,$C62) | H62: =SUMIFS('g-expenses-sl'!$K:$K,'g-expenses-sl'!$A:$A,H$1,'g-expenses-sl'!$D:$D,"logistics",'g-expenses-sl'!$E:$E,$C62) | I62: =SUMIFS('g-expenses-sl'!$K:$K,'g-expenses-sl'!$A:$A,I$1,'g-expenses-sl'!$D:$D,"logistics",'g-expenses-sl'!$E:$E,$C62) | J62: =SUMIFS('g-expenses-sl'!$K:$K,'g-expenses-sl'!$A:$A,J$1,'g-expenses-sl'!$D:$D,"logistics",'g-expenses-sl'!$E:$E,$C62) | K62: =SUMIFS('g-expenses-sl'!$K:$K,'g-expenses-sl'!$A:$A,K$1,'g-expenses-sl'!$D:$D,"logistics",'g-expenses-sl'!$E:$E,$C62) | ... O62: =SUMIFS('g-expenses-sl'!$K:$K,'g-expenses-sl'!$A:$A,O$1,'g-expenses-sl'!$D:$D,"logistics",'g-expenses-sl'!$E:$E,$C62) | P62: =SUM(D62:O62) | Q62: ->
A63: CORREOSCAN | C63: CORREOSCAN | D63: =SUMIFS('g-expenses-sl'!$K:$K,'g-expenses-sl'!$A:$A,D$1,'g-expenses-sl'!$D:$D,"logistics",'g-expenses-sl'!$E:$E,$C63) | E63: =SUMIFS('g-expenses-sl'!$K:$K,'g-expenses-sl'!$A:$A,E$1,'g-expenses-sl'!$D:$D,"logistics",'g-expenses-sl'!$E:$E,$C63) | F63: =SUMIFS('g-expenses-sl'!$K:$K,'g-expenses-sl'!$A:$A,F$1,'g-expenses-sl'!$D:$D,"logistics",'g-expenses-sl'!$E:$E,$C63) | G63: =SUMIFS('g-expenses-sl'!$K:$K,'g-expenses-sl'!$A:$A,G$1,'g-expenses-sl'!$D:$D,"logistics",'g-expenses-sl'!$E:$E,$C63) | H63: =SUMIFS('g-expenses-sl'!$K:$K,'g-expenses-sl'!$A:$A,H$1,'g-expenses-sl'!$D:$D,"logistics",'g-expenses-sl'!$E:$E,$C63) | I63: =SUMIFS('g-expenses-sl'!$K:$K,'g-expenses-sl'!$A:$A,I$1,'g-expenses-sl'!$D:$D,"logistics",'g-expenses-sl'!$E:$E,$C63) | J63: =SUMIFS('g-expenses-sl'!$K:$K,'g-expenses-sl'!$A:$A,J$1,'g-expenses-sl'!$D:$D,"logistics",'g-expenses-sl'!$E:$E,$C63) | K63: =SUMIFS('g-expenses-sl'!$K:$K,'g-expenses-sl'!$A:$A,K$1,'g-expenses-sl'!$D:$D,"logistics",'g-expenses-sl'!$E:$E,$C63) | ... O63: =SUMIFS('g-expenses-sl'!$K:$K,'g-expenses-sl'!$A:$A,O$1,'g-expenses-sl'!$D:$D,"logistics",'g-expenses-sl'!$E:$E,$C63) | P63: =SUM(D63:O63) | Q63: ->
A64: GLS | C64: GLS | D64: =SUMIFS('g-expenses-sl'!$K:$K,'g-expenses-sl'!$A:$A,D$1,'g-expenses-sl'!$D:$D,"logistics",'g-expenses-sl'!$E:$E,$C64) | E64: =SUMIFS('g-expenses-sl'!$K:$K,'g-expenses-sl'!$A:$A,E$1,'g-expenses-sl'!$D:$D,"logistics",'g-expenses-sl'!$E:$E,$C64) | F64: =SUMIFS('g-expenses-sl'!$K:$K,'g-expenses-sl'!$A:$A,F$1,'g-expenses-sl'!$D:$D,"logistics",'g-expenses-sl'!$E:$E,$C64) | G64: =SUMIFS('g-expenses-sl'!$K:$K,'g-expenses-sl'!$A:$A,G$1,'g-expenses-sl'!$D:$D,"logistics",'g-expenses-sl'!$E:$E,$C64) | H64: =SUMIFS('g-expenses-sl'!$K:$K,'g-expenses-sl'!$A:$A,H$1,'g-expenses-sl'!$D:$D,"logistics",'g-expenses-sl'!$E:$E,$C64) | I64: =SUMIFS('g-expenses-sl'!$K:$K,'g-expenses-sl'!$A:$A,I$1,'g-expenses-sl'!$D:$D,"logistics",'g-expenses-sl'!$E:$E,$C64) | J64: =SUMIFS('g-expenses-sl'!$K:$K,'g-expenses-sl'!$A:$A,J$1,'g-expenses-sl'!$D:$D,"logistics",'g-expenses-sl'!$E:$E,$C64) | K64: =SUMIFS('g-expenses-sl'!$K:$K,'g-expenses-sl'!$A:$A,K$1,'g-expenses-sl'!$D:$D,"logistics",'g-expenses-sl'!$E:$E,$C64) | ... O64: =SUMIFS('g-expenses-sl'!$K:$K,'g-expenses-sl'!$A:$A,O$1,'g-expenses-sl'!$D:$D,"logistics",'g-expenses-sl'!$E:$E,$C64) | P64: =SUM(D64:O64) | Q64: ->
A65: SPRINGGDS | C65: SPRINGGDS | D65: =SUMIFS('g-expenses-sl'!$K:$K,'g-expenses-sl'!$A:$A,D$1,'g-expenses-sl'!$D:$D,"logistics",'g-expenses-sl'!$E:$E,$C65) | E65: =SUMIFS('g-expenses-sl'!$K:$K,'g-expenses-sl'!$A:$A,E$1,'g-expenses-sl'!$D:$D,"logistics",'g-expenses-sl'!$E:$E,$C65) | F65: =SUMIFS('g-expenses-sl'!$K:$K,'g-expenses-sl'!$A:$A,F$1,'g-expenses-sl'!$D:$D,"logistics",'g-expenses-sl'!$E:$E,$C65) | G65: =SUMIFS('g-expenses-sl'!$K:$K,'g-expenses-sl'!$A:$A,G$1,'g-expenses-sl'!$D:$D,"logistics",'g-expenses-sl'!$E:$E,$C65) | H65: =SUMIFS('g-expenses-sl'!$K:$K,'g-expenses-sl'!$A:$A,H$1,'g-expenses-sl'!$D:$D,"logistics",'g-expenses-sl'!$E:$E,$C65) | I65: =SUMIFS('g-expenses-sl'!$K:$K,'g-expenses-sl'!$A:$A,I$1,'g-expenses-sl'!$D:$D,"logistics",'g-expenses-sl'!$E:$E,$C65) | J65: =SUMIFS('g-expenses-sl'!$K:$K,'g-expenses-sl'!$A:$A,J$1,'g-expenses-sl'!$D:$D,"logistics",'g-expenses-sl'!$E:$E,$C65) | K65: =SUMIFS('g-expenses-sl'!$K:$K,'g-expenses-sl'!$A:$A,K$1,'g-expenses-sl'!$D:$D,"logistics",'g-expenses-sl'!$E:$E,$C65) | ... O65: =SUMIFS('g-expenses-sl'!$K:$K,'g-expenses-sl'!$A:$A,O$1,'g-expenses-sl'!$D:$D,"logistics",'g-expenses-sl'!$E:$E,$C65) | P65: =SUM(D65:O65) | Q65: ->
A66: UPS | C66: UPS | D66: =SUMIFS('g-expenses-sl'!$K:$K,'g-expenses-sl'!$A:$A,D$1,'g-expenses-sl'!$D:$D,"logistics",'g-expenses-sl'!$E:$E,$C66) | E66: =SUMIFS('g-expenses-sl'!$K:$K,'g-expenses-sl'!$A:$A,E$1,'g-expenses-sl'!$D:$D,"logistics",'g-expenses-sl'!$E:$E,$C66) | F66: =SUMIFS('g-expenses-sl'!$K:$K,'g-expenses-sl'!$A:$A,F$1,'g-expenses-sl'!$D:$D,"logistics",'g-expenses-sl'!$E:$E,$C66) | G66: =SUMIFS('g-expenses-sl'!$K:$K,'g-expenses-sl'!$A:$A,G$1,'g-expenses-sl'!$D:$D,"logistics",'g-expenses-sl'!$E:$E,$C66) | H66: =SUMIFS('g-expenses-sl'!$K:$K,'g-expenses-sl'!$A:$A,H$1,'g-expenses-sl'!$D:$D,"logistics",'g-expenses-sl'!$E:$E,$C66) | I66: =SUMIFS('g-expenses-sl'!$K:$K,'g-expenses-sl'!$A:$A,I$1,'g-expenses-sl'!$D:$D,"logistics",'g-expenses-sl'!$E:$E,$C66) | J66: =SUMIFS('g-expenses-sl'!$K:$K,'g-expenses-sl'!$A:$A,J$1,'g-expenses-sl'!$D:$D,"logistics",'g-expenses-sl'!$E:$E,$C66) | K66: =SUMIFS('g-expenses-sl'!$K:$K,'g-expenses-sl'!$A:$A,K$1,'g-expenses-sl'!$D:$D,"logistics",'g-expenses-sl'!$E:$E,$C66) | ... O66: =SUMIFS('g-expenses-sl'!$K:$K,'g-expenses-sl'!$A:$A,O$1,'g-expenses-sl'!$D:$D,"logistics",'g-expenses-sl'!$E:$E,$C66) | P66: =SUM(D66:O66) | Q66: ->
A67: % Logistics / sales | C67: % Logistics / sales | D67: =IFERROR(D61/D5,0) | E67: =IFERROR(E61/E5,0) | F67: =IFERROR(F61/F5,0) | G67: =IFERROR(G61/G5,0) | H67: =IFERROR(H61/H5,0) | I67: =IFERROR(I61/I5,0) | J67: =IFERROR(J61/J5,0) | K67: =IFERROR(K61/K5,0) | ... P67: =IFERROR(P61/P5,0)
A68: Royalties (% sales) | C68: Royalties (% sales) | D68: =D69 | E68: =E69 | F68: =F69 | G68: =G69 | H68: =H69 | I68: =I69 | J68: =J69 | K68: =K69 | ... O68: =O69 | P68: =SUM(D68:O68) | Q68: ->
A69: ROYALTIES | C69: ROYALTIES | D69: =SUMIFS('g-expenses-sl'!$K:$K,'g-expenses-sl'!$A:$A,D$1,'g-expenses-sl'!$D:$D,"royalties",'g-expenses-sl'!$E:$E,$C69) | E69: =SUMIFS('g-expenses-sl'!$K:$K,'g-expenses-sl'!$A:$A,E$1,'g-expenses-sl'!$D:$D,"royalties",'g-expenses-sl'!$E:$E,$C69) | F69: =SUMIFS('g-expenses-sl'!$K:$K,'g-expenses-sl'!$A:$A,F$1,'g-expenses-sl'!$D:$D,"royalties",'g-expenses-sl'!$E:$E,$C69) | G69: =SUMIFS('g-expenses-sl'!$K:$K,'g-expenses-sl'!$A:$A,G$1,'g-expenses-sl'!$D:$D,"royalties",'g-expenses-sl'!$E:$E,$C69) | H69: =SUMIFS('g-expenses-sl'!$K:$K,'g-expenses-sl'!$A:$A,H$1,'g-expenses-sl'!$D:$D,"royalties",'g-expenses-sl'!$E:$E,$C69) | I69: =SUMIFS('g-expenses-sl'!$K:$K,'g-expenses-sl'!$A:$A,I$1,'g-expenses-sl'!$D:$D,"royalties",'g-expenses-sl'!$E:$E,$C69) | J69: =SUMIFS('g-expenses-sl'!$K:$K,'g-expenses-sl'!$A:$A,J$1,'g-expenses-sl'!$D:$D,"royalties",'g-expenses-sl'!$E:$E,$C69) | K69: =SUMIFS('g-expenses-sl'!$K:$K,'g-expenses-sl'!$A:$A,K$1,'g-expenses-sl'!$D:$D,"royalties",'g-expenses-sl'!$E:$E,$C69) | ... O69: =SUMIFS('g-expenses-sl'!$K:$K,'g-expenses-sl'!$A:$A,O$1,'g-expenses-sl'!$D:$D,"royalties",'g-expenses-sl'!$E:$E,$C69) | P69: =SUM(D69:O69) | Q69: ->
A70: eu | C70: eu | D70: =SUMIFS('i-royalties-scope-sl'!$C:$C,'i-royalties-scope-sl'!$A:$A,D$1,'i-royalties-scope-sl'!$B:$B,"eu") | E70: =SUMIFS('i-royalties-scope-sl'!$C:$C,'i-royalties-scope-sl'!$A:$A,E$1,'i-royalties-scope-sl'!$B:$B,"eu") | F70: =SUMIFS('i-royalties-scope-sl'!$C:$C,'i-royalties-scope-sl'!$A:$A,F$1,'i-royalties-scope-sl'!$B:$B,"eu") | G70: =SUMIFS('i-royalties-scope-sl'!$C:$C,'i-royalties-scope-sl'!$A:$A,G$1,'i-royalties-scope-sl'!$B:$B,"eu") | H70: =SUMIFS('i-royalties-scope-sl'!$C:$C,'i-royalties-scope-sl'!$A:$A,H$1,'i-royalties-scope-sl'!$B:$B,"eu") | I70: =SUMIFS('i-royalties-scope-sl'!$C:$C,'i-royalties-scope-sl'!$A:$A,I$1,'i-royalties-scope-sl'!$B:$B,"eu") | J70: =SUMIFS('i-royalties-scope-sl'!$C:$C,'i-royalties-scope-sl'!$A:$A,J$1,'i-royalties-scope-sl'!$B:$B,"eu") | K70: =SUMIFS('i-royalties-scope-sl'!$C:$C,'i-royalties-scope-sl'!$A:$A,K$1,'i-royalties-scope-sl'!$B:$B,"eu") | ... O70: =SUMIFS('i-royalties-scope-sl'!$C:$C,'i-royalties-scope-sl'!$A:$A,O$1,'i-royalties-scope-sl'!$B:$B,"eu") | P70: =SUM(D70:O70)
A71: uk | C71: uk | D71: =SUMIFS('i-royalties-scope-sl'!$C:$C,'i-royalties-scope-sl'!$A:$A,D$1,'i-royalties-scope-sl'!$B:$B,"uk") | E71: =SUMIFS('i-royalties-scope-sl'!$C:$C,'i-royalties-scope-sl'!$A:$A,E$1,'i-royalties-scope-sl'!$B:$B,"uk") | F71: =SUMIFS('i-royalties-scope-sl'!$C:$C,'i-royalties-scope-sl'!$A:$A,F$1,'i-royalties-scope-sl'!$B:$B,"uk") | G71: =SUMIFS('i-royalties-scope-sl'!$C:$C,'i-royalties-scope-sl'!$A:$A,G$1,'i-royalties-scope-sl'!$B:$B,"uk") | H71: =SUMIFS('i-royalties-scope-sl'!$C:$C,'i-royalties-scope-sl'!$A:$A,H$1,'i-royalties-scope-sl'!$B:$B,"uk") | I71: =SUMIFS('i-royalties-scope-sl'!$C:$C,'i-royalties-scope-sl'!$A:$A,I$1,'i-royalties-scope-sl'!$B:$B,"uk") | J71: =SUMIFS('i-royalties-scope-sl'!$C:$C,'i-royalties-scope-sl'!$A:$A,J$1,'i-royalties-scope-sl'!$B:$B,"uk") | K71: =SUMIFS('i-royalties-scope-sl'!$C:$C,'i-royalties-scope-sl'!$A:$A,K$1,'i-royalties-scope-sl'!$B:$B,"uk") | ... O71: =SUMIFS('i-royalties-scope-sl'!$C:$C,'i-royalties-scope-sl'!$A:$A,O$1,'i-royalties-scope-sl'!$B:$B,"uk") | P71: =SUM(D71:O71)
A72: us | C72: us | D72: =SUMIFS('i-royalties-scope-sl'!$C:$C,'i-royalties-scope-sl'!$A:$A,D$1,'i-royalties-scope-sl'!$B:$B,"us") | E72: =SUMIFS('i-royalties-scope-sl'!$C:$C,'i-royalties-scope-sl'!$A:$A,E$1,'i-royalties-scope-sl'!$B:$B,"us") | F72: =SUMIFS('i-royalties-scope-sl'!$C:$C,'i-royalties-scope-sl'!$A:$A,F$1,'i-royalties-scope-sl'!$B:$B,"us") | G72: =SUMIFS('i-royalties-scope-sl'!$C:$C,'i-royalties-scope-sl'!$A:$A,G$1,'i-royalties-scope-sl'!$B:$B,"us") | H72: =SUMIFS('i-royalties-scope-sl'!$C:$C,'i-royalties-scope-sl'!$A:$A,H$1,'i-royalties-scope-sl'!$B:$B,"us") | I72: =SUMIFS('i-royalties-scope-sl'!$C:$C,'i-royalties-scope-sl'!$A:$A,I$1,'i-royalties-scope-sl'!$B:$B,"us") | J72: =SUMIFS('i-royalties-scope-sl'!$C:$C,'i-royalties-scope-sl'!$A:$A,J$1,'i-royalties-scope-sl'!$B:$B,"us") | K72: =SUMIFS('i-royalties-scope-sl'!$C:$C,'i-royalties-scope-sl'!$A:$A,K$1,'i-royalties-scope-sl'!$B:$B,"us") | ... O72: =SUMIFS('i-royalties-scope-sl'!$C:$C,'i-royalties-scope-sl'!$A:$A,O$1,'i-royalties-scope-sl'!$B:$B,"us") | P72: =SUM(D72:O72)
A73: % Royalties / sales | C73: % Royalties / sales | D73: =IFERROR(D68/D5,0) | E73: =IFERROR(E68/E5,0) | F73: =IFERROR(F68/F5,0) | G73: =IFERROR(G68/G5,0) | H73: =IFERROR(H68/H5,0) | I73: =IFERROR(I68/I5,0) | J73: =IFERROR(J68/J5,0) | K73: =IFERROR(K68/K5,0) | ... P73: =IFERROR(P68/P5,0)
A74: Payment fees (% sales) | C74: Payment fees (% sales) | D74: =SUM(D75:D76) | E74: =SUM(E75:E76) | F74: =SUM(F75:F76) | G74: =SUM(G75:G76) | H74: =SUM(H75:H76) | I74: =SUM(I75:I76) | J74: =SUM(J75:J76) | K74: =SUM(K75:K76) | ... O74: =SUM(O75:O76) | P74: =SUM(D74:O74) | Q74: ->
A75: SHOPIFY | C75: SHOPIFY | D75: =SUMIFS('g-payment-fees-sl'!$H:$H,'g-payment-fees-sl'!$A:$A,D$1,'g-payment-fees-sl'!$C:$C,$C75) | E75: =SUMIFS('g-payment-fees-sl'!$H:$H,'g-payment-fees-sl'!$A:$A,E$1,'g-payment-fees-sl'!$C:$C,$C75) | F75: =SUMIFS('g-payment-fees-sl'!$H:$H,'g-payment-fees-sl'!$A:$A,F$1,'g-payment-fees-sl'!$C:$C,$C75) | G75: =SUMIFS('g-payment-fees-sl'!$H:$H,'g-payment-fees-sl'!$A:$A,G$1,'g-payment-fees-sl'!$C:$C,$C75) | H75: =SUMIFS('g-payment-fees-sl'!$H:$H,'g-payment-fees-sl'!$A:$A,H$1,'g-payment-fees-sl'!$C:$C,$C75) | I75: =SUMIFS('g-payment-fees-sl'!$H:$H,'g-payment-fees-sl'!$A:$A,I$1,'g-payment-fees-sl'!$C:$C,$C75) | J75: =SUMIFS('g-payment-fees-sl'!$H:$H,'g-payment-fees-sl'!$A:$A,J$1,'g-payment-fees-sl'!$C:$C,$C75) | K75: =SUMIFS('g-payment-fees-sl'!$H:$H,'g-payment-fees-sl'!$A:$A,K$1,'g-payment-fees-sl'!$C:$C,$C75) | ... O75: =SUMIFS('g-payment-fees-sl'!$H:$H,'g-payment-fees-sl'!$A:$A,O$1,'g-payment-fees-sl'!$C:$C,$C75) | P75: =SUM(D75:O75) | Q75: ->
A76: PAYPAL | C76: PAYPAL | D76: =SUMIFS('g-payment-fees-sl'!$H:$H,'g-payment-fees-sl'!$A:$A,D$1,'g-payment-fees-sl'!$C:$C,$C76) | E76: =SUMIFS('g-payment-fees-sl'!$H:$H,'g-payment-fees-sl'!$A:$A,E$1,'g-payment-fees-sl'!$C:$C,$C76) | F76: =SUMIFS('g-payment-fees-sl'!$H:$H,'g-payment-fees-sl'!$A:$A,F$1,'g-payment-fees-sl'!$C:$C,$C76) | G76: =SUMIFS('g-payment-fees-sl'!$H:$H,'g-payment-fees-sl'!$A:$A,G$1,'g-payment-fees-sl'!$C:$C,$C76) | H76: =SUMIFS('g-payment-fees-sl'!$H:$H,'g-payment-fees-sl'!$A:$A,H$1,'g-payment-fees-sl'!$C:$C,$C76) | I76: =SUMIFS('g-payment-fees-sl'!$H:$H,'g-payment-fees-sl'!$A:$A,I$1,'g-payment-fees-sl'!$C:$C,$C76) | J76: =SUMIFS('g-payment-fees-sl'!$H:$H,'g-payment-fees-sl'!$A:$A,J$1,'g-payment-fees-sl'!$C:$C,$C76) | K76: =SUMIFS('g-payment-fees-sl'!$H:$H,'g-payment-fees-sl'!$A:$A,K$1,'g-payment-fees-sl'!$C:$C,$C76) | ... O76: =SUMIFS('g-payment-fees-sl'!$H:$H,'g-payment-fees-sl'!$A:$A,O$1,'g-payment-fees-sl'!$C:$C,$C76) | P76: =SUM(D76:O76) | Q76: ->
A77: % Payment fees / sales | C77: % Payment fees / sales | D77: =IFERROR(D74/D5,0) | E77: =IFERROR(E74/E5,0) | F77: =IFERROR(F74/F5,0) | G77: =IFERROR(G74/G5,0) | H77: =IFERROR(H74/H5,0) | I77: =IFERROR(I74/I5,0) | J77: =IFERROR(J74/J5,0) | K77: =IFERROR(K74/K5,0) | ... P77: =IFERROR(P74/P5,0)
P78: =SUM(D78:O78)
A79: GROSS MARGIN (SALES-MANUFACTURING) | D79: =D5-D54 | E79: =E5-E54 | F79: =F5-F54 | G79: =G5-G54 | H79: =H5-H54 | I79: =I5-I54 | J79: =J5-J54 | K79: =K5-K54 | ... O79: =O5-O54 | P79: =SUM(D79:O79)
A80: % gross margin | D80: =IFERROR(D79/D5,0) | E80: =IFERROR(E79/E5,0) | F80: =IFERROR(F79/F5,0) | G80: =IFERROR(G79/G5,0) | H80: =IFERROR(H79/H5,0) | I80: =IFERROR(I79/I5,0) | J80: =IFERROR(J79/J5,0) | K80: =IFERROR(K79/K5,0) | ... P80: =IFERROR(P79/P5,0)
A81: Contributive margin (product sales-COGS) | D81: =D5-D54-D61-D70-D74 | E81: =E5-E54-E61-E70-E74 | F81: =F5-F54-F61-F70-F74 | G81: =G5-G54-G61-G70-G74 | H81: =H5-H54-H61-H70-H74 | I81: =I5-I54-I61-I70-I74 | J81: =J5-J54-J61-J70-J74 | K81: =K5-K54-K61-K70-K74 | ... O81: =O5-O54-O61-O70-O74 | P81: =SUM(D81:O81)
A82: % contributive margin | D82: =IFERROR(D81/D5,0) | E82: =IFERROR(E81/E5,0) | F82: =IFERROR(F81/F5,0) | G82: =IFERROR(G81/G5,0) | H82: =IFERROR(H81/H5,0) | I82: =IFERROR(I81/I5,0) | J82: =IFERROR(J81/J5,0) | K82: =IFERROR(K81/K5,0) | ... P82: =IFERROR(P81/P5,0)
P83: =SUM(D83:O83)
A84: Opex | B84: Opex | D84: =D85+D95+D98+D114+D132 | E84: =E85+E95+E98+E114+E132 | F84: =F85+F95+F98+F114+F132 | G84: =G85+G95+G98+G114+G132 | H84: =H85+H95+H98+H114+H132 | I84: =I85+I95+I98+I114+I132 | J84: =J85+J95+J98+J114+J132 | K84: =K85+K95+K98+K114+K132 | ... O84: =O85+O95+O98+O114+O132 | P84: =SUM(D84:O84)
A85: Marketing | C85: Marketing | D85: =D86+D90 | E85: =E86+E90 | F85: =F86+F90 | G85: =G86+G90 | H85: =H86+H90 | I85: =I86+I90 | J85: =J86+J90 | K85: =K86+K90 | ... O85: =O86+O90 | P85: =SUM(D85:O85) | Q85: ->
A86: METAADS | C86: METAADS | D86: =SUM(D87:D89) | E86: =SUM(E87:E89) | F86: =SUM(F87:F89) | G86: =SUM(G87:G89) | H86: =SUM(H87:H89) | I86: =SUM(I87:I89) | J86: =SUM(J87:J89) | K86: =SUM(K87:K89) | ... O86: =SUM(O87:O89) | P86: =SUM(D86:O86) | Q86: ->
A87: EU | C87: EU | D87: =SUMIFS('g-expenses-sl'!$K:$K,'g-expenses-sl'!$A:$A,D$1,'g-expenses-sl'!$D:$D,"marketing",'g-expenses-sl'!$E:$E,"METAADS",'g-expenses-sl'!$F:$F,$C87) | E87: =SUMIFS('g-expenses-sl'!$K:$K,'g-expenses-sl'!$A:$A,E$1,'g-expenses-sl'!$D:$D,"marketing",'g-expenses-sl'!$E:$E,"METAADS",'g-expenses-sl'!$F:$F,$C87) | F87: =SUMIFS('g-expenses-sl'!$K:$K,'g-expenses-sl'!$A:$A,F$1,'g-expenses-sl'!$D:$D,"marketing",'g-expenses-sl'!$E:$E,"METAADS",'g-expenses-sl'!$F:$F,$C87) | G87: =SUMIFS('g-expenses-sl'!$K:$K,'g-expenses-sl'!$A:$A,G$1,'g-expenses-sl'!$D:$D,"marketing",'g-expenses-sl'!$E:$E,"METAADS",'g-expenses-sl'!$F:$F,$C87) | H87: =SUMIFS('g-expenses-sl'!$K:$K,'g-expenses-sl'!$A:$A,H$1,'g-expenses-sl'!$D:$D,"marketing",'g-expenses-sl'!$E:$E,"METAADS",'g-expenses-sl'!$F:$F,$C87) | I87: =SUMIFS('g-expenses-sl'!$K:$K,'g-expenses-sl'!$A:$A,I$1,'g-expenses-sl'!$D:$D,"marketing",'g-expenses-sl'!$E:$E,"METAADS",'g-expenses-sl'!$F:$F,$C87) | J87: =SUMIFS('g-expenses-sl'!$K:$K,'g-expenses-sl'!$A:$A,J$1,'g-expenses-sl'!$D:$D,"marketing",'g-expenses-sl'!$E:$E,"METAADS",'g-expenses-sl'!$F:$F,$C87) | K87: =SUMIFS('g-expenses-sl'!$K:$K,'g-expenses-sl'!$A:$A,K$1,'g-expenses-sl'!$D:$D,"marketing",'g-expenses-sl'!$E:$E,"METAADS",'g-expenses-sl'!$F:$F,$C87) | ... O87: =SUMIFS('g-expenses-sl'!$K:$K,'g-expenses-sl'!$A:$A,O$1,'g-expenses-sl'!$D:$D,"marketing",'g-expenses-sl'!$E:$E,"METAADS",'g-expenses-sl'!$F:$F,$C87) | P87: =SUM(D87:O87) | Q87: ->
A88: UK | C88: UK | D88: =SUMIFS('g-expenses-sl'!$K:$K,'g-expenses-sl'!$A:$A,D$1,'g-expenses-sl'!$D:$D,"marketing",'g-expenses-sl'!$E:$E,"METAADS",'g-expenses-sl'!$F:$F,$C88) | E88: =SUMIFS('g-expenses-sl'!$K:$K,'g-expenses-sl'!$A:$A,E$1,'g-expenses-sl'!$D:$D,"marketing",'g-expenses-sl'!$E:$E,"METAADS",'g-expenses-sl'!$F:$F,$C88) | F88: =SUMIFS('g-expenses-sl'!$K:$K,'g-expenses-sl'!$A:$A,F$1,'g-expenses-sl'!$D:$D,"marketing",'g-expenses-sl'!$E:$E,"METAADS",'g-expenses-sl'!$F:$F,$C88) | G88: =SUMIFS('g-expenses-sl'!$K:$K,'g-expenses-sl'!$A:$A,G$1,'g-expenses-sl'!$D:$D,"marketing",'g-expenses-sl'!$E:$E,"METAADS",'g-expenses-sl'!$F:$F,$C88) | H88: =SUMIFS('g-expenses-sl'!$K:$K,'g-expenses-sl'!$A:$A,H$1,'g-expenses-sl'!$D:$D,"marketing",'g-expenses-sl'!$E:$E,"METAADS",'g-expenses-sl'!$F:$F,$C88) | I88: =SUMIFS('g-expenses-sl'!$K:$K,'g-expenses-sl'!$A:$A,I$1,'g-expenses-sl'!$D:$D,"marketing",'g-expenses-sl'!$E:$E,"METAADS",'g-expenses-sl'!$F:$F,$C88) | J88: =SUMIFS('g-expenses-sl'!$K:$K,'g-expenses-sl'!$A:$A,J$1,'g-expenses-sl'!$D:$D,"marketing",'g-expenses-sl'!$E:$E,"METAADS",'g-expenses-sl'!$F:$F,$C88) | K88: =SUMIFS('g-expenses-sl'!$K:$K,'g-expenses-sl'!$A:$A,K$1,'g-expenses-sl'!$D:$D,"marketing",'g-expenses-sl'!$E:$E,"METAADS",'g-expenses-sl'!$F:$F,$C88) | ... O88: =SUMIFS('g-expenses-sl'!$K:$K,'g-expenses-sl'!$A:$A,O$1,'g-expenses-sl'!$D:$D,"marketing",'g-expenses-sl'!$E:$E,"METAADS",'g-expenses-sl'!$F:$F,$C88) | P88: =SUM(D88:O88) | Q88: ->
A89: US | C89: US | D89: =SUMIFS('g-expenses-sl'!$K:$K,'g-expenses-sl'!$A:$A,D$1,'g-expenses-sl'!$D:$D,"marketing",'g-expenses-sl'!$E:$E,"METAADS",'g-expenses-sl'!$F:$F,$C89) | E89: =SUMIFS('g-expenses-sl'!$K:$K,'g-expenses-sl'!$A:$A,E$1,'g-expenses-sl'!$D:$D,"marketing",'g-expenses-sl'!$E:$E,"METAADS",'g-expenses-sl'!$F:$F,$C89) | F89: =SUMIFS('g-expenses-sl'!$K:$K,'g-expenses-sl'!$A:$A,F$1,'g-expenses-sl'!$D:$D,"marketing",'g-expenses-sl'!$E:$E,"METAADS",'g-expenses-sl'!$F:$F,$C89) | G89: =SUMIFS('g-expenses-sl'!$K:$K,'g-expenses-sl'!$A:$A,G$1,'g-expenses-sl'!$D:$D,"marketing",'g-expenses-sl'!$E:$E,"METAADS",'g-expenses-sl'!$F:$F,$C89) | H89: =SUMIFS('g-expenses-sl'!$K:$K,'g-expenses-sl'!$A:$A,H$1,'g-expenses-sl'!$D:$D,"marketing",'g-expenses-sl'!$E:$E,"METAADS",'g-expenses-sl'!$F:$F,$C89) | I89: =SUMIFS('g-expenses-sl'!$K:$K,'g-expenses-sl'!$A:$A,I$1,'g-expenses-sl'!$D:$D,"marketing",'g-expenses-sl'!$E:$E,"METAADS",'g-expenses-sl'!$F:$F,$C89) | J89: =SUMIFS('g-expenses-sl'!$K:$K,'g-expenses-sl'!$A:$A,J$1,'g-expenses-sl'!$D:$D,"marketing",'g-expenses-sl'!$E:$E,"METAADS",'g-expenses-sl'!$F:$F,$C89) | K89: =SUMIFS('g-expenses-sl'!$K:$K,'g-expenses-sl'!$A:$A,K$1,'g-expenses-sl'!$D:$D,"marketing",'g-expenses-sl'!$E:$E,"METAADS",'g-expenses-sl'!$F:$F,$C89) | ... O89: =SUMIFS('g-expenses-sl'!$K:$K,'g-expenses-sl'!$A:$A,O$1,'g-expenses-sl'!$D:$D,"marketing",'g-expenses-sl'!$E:$E,"METAADS",'g-expenses-sl'!$F:$F,$C89) | P89: =SUM(D89:O89) | Q89: ->
A90: GOOGLEADS | C90: GOOGLEADS | D90: =SUM(D91:D93) | E90: =SUM(E91:E93) | F90: =SUM(F91:F93) | G90: =SUM(G91:G93) | H90: =SUM(H91:H93) | I90: =SUM(I91:I93) | J90: =SUM(J91:J93) | K90: =SUM(K91:K93) | ... O90: =SUM(O91:O93) | P90: =SUM(D90:O90) | Q90: ->
A91: EU | C91: EU | D91: =SUMIFS('g-expenses-sl'!$K:$K,'g-expenses-sl'!$A:$A,D$1,'g-expenses-sl'!$D:$D,"marketing",'g-expenses-sl'!$E:$E,"GOOGLEADS",'g-expenses-sl'!$F:$F,$C91) | E91: =SUMIFS('g-expenses-sl'!$K:$K,'g-expenses-sl'!$A:$A,E$1,'g-expenses-sl'!$D:$D,"marketing",'g-expenses-sl'!$E:$E,"GOOGLEADS",'g-expenses-sl'!$F:$F,$C91) | F91: =SUMIFS('g-expenses-sl'!$K:$K,'g-expenses-sl'!$A:$A,F$1,'g-expenses-sl'!$D:$D,"marketing",'g-expenses-sl'!$E:$E,"GOOGLEADS",'g-expenses-sl'!$F:$F,$C91) | G91: =SUMIFS('g-expenses-sl'!$K:$K,'g-expenses-sl'!$A:$A,G$1,'g-expenses-sl'!$D:$D,"marketing",'g-expenses-sl'!$E:$E,"GOOGLEADS",'g-expenses-sl'!$F:$F,$C91) | H91: =SUMIFS('g-expenses-sl'!$K:$K,'g-expenses-sl'!$A:$A,H$1,'g-expenses-sl'!$D:$D,"marketing",'g-expenses-sl'!$E:$E,"GOOGLEADS",'g-expenses-sl'!$F:$F,$C91) | I91: =SUMIFS('g-expenses-sl'!$K:$K,'g-expenses-sl'!$A:$A,I$1,'g-expenses-sl'!$D:$D,"marketing",'g-expenses-sl'!$E:$E,"GOOGLEADS",'g-expenses-sl'!$F:$F,$C91) | J91: =SUMIFS('g-expenses-sl'!$K:$K,'g-expenses-sl'!$A:$A,J$1,'g-expenses-sl'!$D:$D,"marketing",'g-expenses-sl'!$E:$E,"GOOGLEADS",'g-expenses-sl'!$F:$F,$C91) | K91: =SUMIFS('g-expenses-sl'!$K:$K,'g-expenses-sl'!$A:$A,K$1,'g-expenses-sl'!$D:$D,"marketing",'g-expenses-sl'!$E:$E,"GOOGLEADS",'g-expenses-sl'!$F:$F,$C91) | ... O91: =SUMIFS('g-expenses-sl'!$K:$K,'g-expenses-sl'!$A:$A,O$1,'g-expenses-sl'!$D:$D,"marketing",'g-expenses-sl'!$E:$E,"GOOGLEADS",'g-expenses-sl'!$F:$F,$C91) | P91: =SUM(D91:O91) | Q91: ->
A92: UK | C92: UK | D92: =SUMIFS('g-expenses-sl'!$K:$K,'g-expenses-sl'!$A:$A,D$1,'g-expenses-sl'!$D:$D,"marketing",'g-expenses-sl'!$E:$E,"GOOGLEADS",'g-expenses-sl'!$F:$F,$C92) | E92: =SUMIFS('g-expenses-sl'!$K:$K,'g-expenses-sl'!$A:$A,E$1,'g-expenses-sl'!$D:$D,"marketing",'g-expenses-sl'!$E:$E,"GOOGLEADS",'g-expenses-sl'!$F:$F,$C92) | F92: =SUMIFS('g-expenses-sl'!$K:$K,'g-expenses-sl'!$A:$A,F$1,'g-expenses-sl'!$D:$D,"marketing",'g-expenses-sl'!$E:$E,"GOOGLEADS",'g-expenses-sl'!$F:$F,$C92) | G92: =SUMIFS('g-expenses-sl'!$K:$K,'g-expenses-sl'!$A:$A,G$1,'g-expenses-sl'!$D:$D,"marketing",'g-expenses-sl'!$E:$E,"GOOGLEADS",'g-expenses-sl'!$F:$F,$C92) | H92: =SUMIFS('g-expenses-sl'!$K:$K,'g-expenses-sl'!$A:$A,H$1,'g-expenses-sl'!$D:$D,"marketing",'g-expenses-sl'!$E:$E,"GOOGLEADS",'g-expenses-sl'!$F:$F,$C92) | I92: =SUMIFS('g-expenses-sl'!$K:$K,'g-expenses-sl'!$A:$A,I$1,'g-expenses-sl'!$D:$D,"marketing",'g-expenses-sl'!$E:$E,"GOOGLEADS",'g-expenses-sl'!$F:$F,$C92) | J92: =SUMIFS('g-expenses-sl'!$K:$K,'g-expenses-sl'!$A:$A,J$1,'g-expenses-sl'!$D:$D,"marketing",'g-expenses-sl'!$E:$E,"GOOGLEADS",'g-expenses-sl'!$F:$F,$C92) | K92: =SUMIFS('g-expenses-sl'!$K:$K,'g-expenses-sl'!$A:$A,K$1,'g-expenses-sl'!$D:$D,"marketing",'g-expenses-sl'!$E:$E,"GOOGLEADS",'g-expenses-sl'!$F:$F,$C92) | ... O92: =SUMIFS('g-expenses-sl'!$K:$K,'g-expenses-sl'!$A:$A,O$1,'g-expenses-sl'!$D:$D,"marketing",'g-expenses-sl'!$E:$E,"GOOGLEADS",'g-expenses-sl'!$F:$F,$C92) | P92: =SUM(D92:O92) | Q92: ->
A93: US | C93: US | D93: =SUMIFS('g-expenses-sl'!$K:$K,'g-expenses-sl'!$A:$A,D$1,'g-expenses-sl'!$D:$D,"marketing",'g-expenses-sl'!$E:$E,"GOOGLEADS",'g-expenses-sl'!$F:$F,$C93) | E93: =SUMIFS('g-expenses-sl'!$K:$K,'g-expenses-sl'!$A:$A,E$1,'g-expenses-sl'!$D:$D,"marketing",'g-expenses-sl'!$E:$E,"GOOGLEADS",'g-expenses-sl'!$F:$F,$C93) | F93: =SUMIFS('g-expenses-sl'!$K:$K,'g-expenses-sl'!$A:$A,F$1,'g-expenses-sl'!$D:$D,"marketing",'g-expenses-sl'!$E:$E,"GOOGLEADS",'g-expenses-sl'!$F:$F,$C93) | G93: =SUMIFS('g-expenses-sl'!$K:$K,'g-expenses-sl'!$A:$A,G$1,'g-expenses-sl'!$D:$D,"marketing",'g-expenses-sl'!$E:$E,"GOOGLEADS",'g-expenses-sl'!$F:$F,$C93) | H93: =SUMIFS('g-expenses-sl'!$K:$K,'g-expenses-sl'!$A:$A,H$1,'g-expenses-sl'!$D:$D,"marketing",'g-expenses-sl'!$E:$E,"GOOGLEADS",'g-expenses-sl'!$F:$F,$C93) | I93: =SUMIFS('g-expenses-sl'!$K:$K,'g-expenses-sl'!$A:$A,I$1,'g-expenses-sl'!$D:$D,"marketing",'g-expenses-sl'!$E:$E,"GOOGLEADS",'g-expenses-sl'!$F:$F,$C93) | J93: =SUMIFS('g-expenses-sl'!$K:$K,'g-expenses-sl'!$A:$A,J$1,'g-expenses-sl'!$D:$D,"marketing",'g-expenses-sl'!$E:$E,"GOOGLEADS",'g-expenses-sl'!$F:$F,$C93) | K93: =SUMIFS('g-expenses-sl'!$K:$K,'g-expenses-sl'!$A:$A,K$1,'g-expenses-sl'!$D:$D,"marketing",'g-expenses-sl'!$E:$E,"GOOGLEADS",'g-expenses-sl'!$F:$F,$C93) | ... O93: =SUMIFS('g-expenses-sl'!$K:$K,'g-expenses-sl'!$A:$A,O$1,'g-expenses-sl'!$D:$D,"marketing",'g-expenses-sl'!$E:$E,"GOOGLEADS",'g-expenses-sl'!$F:$F,$C93) | P93: =SUM(D93:O93) | Q93: ->
A94: Sales / mkt EU | C94: Sales / mkt EU | D94: =IFERROR((D7+D9+D11+D13+D15+D17+D19+D21+D23+D25+D27+D29+D31+D33)/(D87+D91),0) | E94: =IFERROR((E7+E9+E11+E13+E15+E17+E19+E21+E23+E25+E27+E29+E31+E33)/(E87+E91),0) | F94: =IFERROR((F7+F9+F11+F13+F15+F17+F19+F21+F23+F25+F27+F29+F31+F33)/(F87+F91),0) | G94: =IFERROR((G7+G9+G11+G13+G15+G17+G19+G21+G23+G25+G27+G29+G31+G33)/(G87+G91),0) | H94: =IFERROR((H7+H9+H11+H13+H15+H17+H19+H21+H23+H25+H27+H29+H31+H33)/(H87+H91),0) | I94: =IFERROR((I7+I9+I11+I13+I15+I17+I19+I21+I23+I25+I27+I29+I31+I33)/(I87+I91),0) | J94: =IFERROR((J7+J9+J11+J13+J15+J17+J19+J21+J23+J25+J27+J29+J31+J33)/(J87+J91),0) | K94: =IFERROR((K7+K9+K11+K13+K15+K17+K19+K21+K23+K25+K27+K29+K31+K33)/(K87+K91),0) | ... P94: =IFERROR((P7+P9+P11+P13+P15+P17+P19+P21+P23+P25+P27+P29+P31+P33)/(P87+P91),0)
A95: Staff | C95: Staff | D95: =SUM(D96:D97) | E95: =SUM(E96:E97) | F95: =SUM(F96:F97) | G95: =SUM(G96:G97) | H95: =SUM(H96:H97) | I95: =SUM(I96:I97) | J95: =SUM(J96:J97) | K95: =SUM(K96:K97) | ... O95: =SUM(O96:O97) | P95: =SUM(D95:O95) | Q95: ->
A96: PAYROLL | C96: PAYROLL | D96: =SUMIFS('g-expenses-sl'!$K:$K,'g-expenses-sl'!$A:$A,D$1,'g-expenses-sl'!$D:$D,"staff",'g-expenses-sl'!$E:$E,$C96) | E96: =SUMIFS('g-expenses-sl'!$K:$K,'g-expenses-sl'!$A:$A,E$1,'g-expenses-sl'!$D:$D,"staff",'g-expenses-sl'!$E:$E,$C96) | F96: =SUMIFS('g-expenses-sl'!$K:$K,'g-expenses-sl'!$A:$A,F$1,'g-expenses-sl'!$D:$D,"staff",'g-expenses-sl'!$E:$E,$C96) | G96: =SUMIFS('g-expenses-sl'!$K:$K,'g-expenses-sl'!$A:$A,G$1,'g-expenses-sl'!$D:$D,"staff",'g-expenses-sl'!$E:$E,$C96) | H96: =SUMIFS('g-expenses-sl'!$K:$K,'g-expenses-sl'!$A:$A,H$1,'g-expenses-sl'!$D:$D,"staff",'g-expenses-sl'!$E:$E,$C96) | I96: =SUMIFS('g-expenses-sl'!$K:$K,'g-expenses-sl'!$A:$A,I$1,'g-expenses-sl'!$D:$D,"staff",'g-expenses-sl'!$E:$E,$C96) | J96: =SUMIFS('g-expenses-sl'!$K:$K,'g-expenses-sl'!$A:$A,J$1,'g-expenses-sl'!$D:$D,"staff",'g-expenses-sl'!$E:$E,$C96) | K96: =SUMIFS('g-expenses-sl'!$K:$K,'g-expenses-sl'!$A:$A,K$1,'g-expenses-sl'!$D:$D,"staff",'g-expenses-sl'!$E:$E,$C96) | ... O96: =SUMIFS('g-expenses-sl'!$K:$K,'g-expenses-sl'!$A:$A,O$1,'g-expenses-sl'!$D:$D,"staff",'g-expenses-sl'!$E:$E,$C96) | P96: =SUM(D96:O96) | Q96: ->
A97: DOSCONSULTING | C97: DOSCONSULTING | D97: =SUMIFS('g-expenses-sl'!$K:$K,'g-expenses-sl'!$A:$A,D$1,'g-expenses-sl'!$D:$D,"staff",'g-expenses-sl'!$E:$E,$C97) | E97: =SUMIFS('g-expenses-sl'!$K:$K,'g-expenses-sl'!$A:$A,E$1,'g-expenses-sl'!$D:$D,"staff",'g-expenses-sl'!$E:$E,$C97) | F97: =SUMIFS('g-expenses-sl'!$K:$K,'g-expenses-sl'!$A:$A,F$1,'g-expenses-sl'!$D:$D,"staff",'g-expenses-sl'!$E:$E,$C97) | G97: =SUMIFS('g-expenses-sl'!$K:$K,'g-expenses-sl'!$A:$A,G$1,'g-expenses-sl'!$D:$D,"staff",'g-expenses-sl'!$E:$E,$C97) | H97: =SUMIFS('g-expenses-sl'!$K:$K,'g-expenses-sl'!$A:$A,H$1,'g-expenses-sl'!$D:$D,"staff",'g-expenses-sl'!$E:$E,$C97) | I97: =SUMIFS('g-expenses-sl'!$K:$K,'g-expenses-sl'!$A:$A,I$1,'g-expenses-sl'!$D:$D,"staff",'g-expenses-sl'!$E:$E,$C97) | J97: =SUMIFS('g-expenses-sl'!$K:$K,'g-expenses-sl'!$A:$A,J$1,'g-expenses-sl'!$D:$D,"staff",'g-expenses-sl'!$E:$E,$C97) | K97: =SUMIFS('g-expenses-sl'!$K:$K,'g-expenses-sl'!$A:$A,K$1,'g-expenses-sl'!$D:$D,"staff",'g-expenses-sl'!$E:$E,$C97) | ... O97: =SUMIFS('g-expenses-sl'!$K:$K,'g-expenses-sl'!$A:$A,O$1,'g-expenses-sl'!$D:$D,"staff",'g-expenses-sl'!$E:$E,$C97) | P97: =SUM(D97:O97) | Q97: ->
A98: Administration | C98: Administration | D98: =D99+D100+D101+D102+D103+D107+D108+D109+D110+D111+D112+D113 | E98: =E99+E100+E101+E102+E103+E107+E108+E109+E110+E111+E112+E113 | F98: =F99+F100+F101+F102+F103+F107+F108+F109+F110+F111+F112+F113 | G98: =G99+G100+G101+G102+G103+G107+G108+G109+G110+G111+G112+G113 | H98: =H99+H100+H101+H102+H103+H107+H108+H109+H110+H111+H112+H113 | I98: =I99+I100+I101+I102+I103+I107+I108+I109+I110+I111+I112+I113 | J98: =J99+J100+J101+J102+J103+J107+J108+J109+J110+J111+J112+J113 | K98: =K99+K100+K101+K102+K103+K107+K108+K109+K110+K111+K112+K113 | ... O98: =O99+O100+O101+O102+O103+O107+O108+O109+O110+O111+O112+O113 | P98: =SUM(D98:O98) | Q98: ->
A99: ADEPLUS | C99: ADEPLUS | D99: =SUMIFS('g-expenses-sl'!$K:$K,'g-expenses-sl'!$A:$A,D$1,'g-expenses-sl'!$D:$D,"administration",'g-expenses-sl'!$E:$E,$C99) | E99: =SUMIFS('g-expenses-sl'!$K:$K,'g-expenses-sl'!$A:$A,E$1,'g-expenses-sl'!$D:$D,"administration",'g-expenses-sl'!$E:$E,$C99) | F99: =SUMIFS('g-expenses-sl'!$K:$K,'g-expenses-sl'!$A:$A,F$1,'g-expenses-sl'!$D:$D,"administration",'g-expenses-sl'!$E:$E,$C99) | G99: =SUMIFS('g-expenses-sl'!$K:$K,'g-expenses-sl'!$A:$A,G$1,'g-expenses-sl'!$D:$D,"administration",'g-expenses-sl'!$E:$E,$C99) | H99: =SUMIFS('g-expenses-sl'!$K:$K,'g-expenses-sl'!$A:$A,H$1,'g-expenses-sl'!$D:$D,"administration",'g-expenses-sl'!$E:$E,$C99) | I99: =SUMIFS('g-expenses-sl'!$K:$K,'g-expenses-sl'!$A:$A,I$1,'g-expenses-sl'!$D:$D,"administration",'g-expenses-sl'!$E:$E,$C99) | J99: =SUMIFS('g-expenses-sl'!$K:$K,'g-expenses-sl'!$A:$A,J$1,'g-expenses-sl'!$D:$D,"administration",'g-expenses-sl'!$E:$E,$C99) | K99: =SUMIFS('g-expenses-sl'!$K:$K,'g-expenses-sl'!$A:$A,K$1,'g-expenses-sl'!$D:$D,"administration",'g-expenses-sl'!$E:$E,$C99) | ... O99: =SUMIFS('g-expenses-sl'!$K:$K,'g-expenses-sl'!$A:$A,O$1,'g-expenses-sl'!$D:$D,"administration",'g-expenses-sl'!$E:$E,$C99) | P99: =SUM(D99:O99) | Q99: ->
A100: BBVACNC | C100: BBVACNC | D100: =SUMIFS('g-expenses-sl'!$K:$K,'g-expenses-sl'!$A:$A,D$1,'g-expenses-sl'!$D:$D,"administration",'g-expenses-sl'!$E:$E,$C100) | E100: =SUMIFS('g-expenses-sl'!$K:$K,'g-expenses-sl'!$A:$A,E$1,'g-expenses-sl'!$D:$D,"administration",'g-expenses-sl'!$E:$E,$C100) | F100: =SUMIFS('g-expenses-sl'!$K:$K,'g-expenses-sl'!$A:$A,F$1,'g-expenses-sl'!$D:$D,"administration",'g-expenses-sl'!$E:$E,$C100) | G100: =SUMIFS('g-expenses-sl'!$K:$K,'g-expenses-sl'!$A:$A,G$1,'g-expenses-sl'!$D:$D,"administration",'g-expenses-sl'!$E:$E,$C100) | H100: =SUMIFS('g-expenses-sl'!$K:$K,'g-expenses-sl'!$A:$A,H$1,'g-expenses-sl'!$D:$D,"administration",'g-expenses-sl'!$E:$E,$C100) | I100: =SUMIFS('g-expenses-sl'!$K:$K,'g-expenses-sl'!$A:$A,I$1,'g-expenses-sl'!$D:$D,"administration",'g-expenses-sl'!$E:$E,$C100) | J100: =SUMIFS('g-expenses-sl'!$K:$K,'g-expenses-sl'!$A:$A,J$1,'g-expenses-sl'!$D:$D,"administration",'g-expenses-sl'!$E:$E,$C100) | K100: =SUMIFS('g-expenses-sl'!$K:$K,'g-expenses-sl'!$A:$A,K$1,'g-expenses-sl'!$D:$D,"administration",'g-expenses-sl'!$E:$E,$C100) | ... O100: =SUMIFS('g-expenses-sl'!$K:$K,'g-expenses-sl'!$A:$A,O$1,'g-expenses-sl'!$D:$D,"administration",'g-expenses-sl'!$E:$E,$C100) | P100: =SUM(D100:O100) | Q100: ->
...

Sheet params
A1: <- Volver a P&G-SL
A2: key | B2: value
A3: entity | B3: SL
A4: year | B4: 2026
A5: generated_at_utc | B5: 2026-07-31T10:25:14Z
A6: pct_staff_uk | B6: 0.15
A7: pct_staff_us | B7: 0.1
A8: pct_admin_uk | B8: 0.15
A9: pct_admin_us | B9: 0.1

Sheet i-shopify-sl
A1: <- Volver a P&G-SL
A2: yyyymm | B2: entity | C2: line_item | D2: detail | E2: amount_original | F2: currency_original | G2: reporting_currency | H2: fx_rate | I2: amount_reporting | J2: source | K2: invoice_number | L2: drive_url
A3: 202601 | B3: SL | C3: AT | D3: AT | E3: 5472.24 | F3: EUR | G3: EUR | H3: 1 | I3: 5472.24 | J3: finance.informe_vat_gestorias_detalle
A4: 202601 | B4: SL | C4: BE | D4: BE | E4: 422.71 | F4: EUR | G4: EUR | H4: 1 | I4: 422.71 | J4: finance.informe_vat_gestorias_detalle
A5: 202601 | B5: SL | C5: CZ | D5: CZ | E5: 66.82 | F5: EUR | G5: EUR | H5: 1 | I5: 66.82 | J5: finance.informe_vat_gestorias_detalle
A6: 202601 | B6: SL | C6: DE | D6: DE | E6: 20230.26 | F6: EUR | G6: EUR | H6: 1 | I6: 20230.26 | J6: finance.informe_vat_gestorias_detalle
A7: 202601 | B7: SL | C7: ES | D7: ES | E7: 61194.44 | F7: EUR | G7: EUR | H7: 1 | I7: 61194.44 | J7: finance.informe_vat_gestorias_detalle
A8: 202601 | B8: SL | C8: FR | D8: FR | E8: 25562.13 | F8: EUR | G8: EUR | H8: 1 | I8: 25562.13 | J8: finance.informe_vat_gestorias_detalle
A9: 202601 | B9: SL | C9: IT | D9: IT | E9: 18488.36 | F9: EUR | G9: EUR | H9: 1 | I9: 18488.36 | J9: finance.informe_vat_gestorias_detalle
A10: 202601 | B10: SL | C10: LU | D10: LU | E10: 361.91 | F10: EUR | G10: EUR | H10: 1 | I10: 361.91 | J10: finance.informe_vat_gestorias_detalle
A11: 202601 | B11: SL | C11: NL | D11: NL | E11: 115.58 | F11: EUR | G11: EUR | H11: 1 | I11: 115.58 | J11: finance.informe_vat_gestorias_detalle
A12: 202601 | B12: SL | C12: PT | D12: PT | E12: 729.31 | F12: EUR | G12: EUR | H12: 1 | I12: 729.31 | J12: finance.informe_vat_gestorias_detalle
A13: 202601 | B13: SL | C13: SE | D13: SE | E13: 262.46 | F13: EUR | G13: EUR | H13: 1 | I13: 262.46 | J13: finance.informe_vat_gestorias_detalle
A14: 202602 | B14: SL | C14: AT | D14: AT | E14: 6064.69 | F14: EUR | G14: EUR | H14: 1 | I14: 6064.69 | J14: finance.informe_vat_gestorias_detalle
... A79: 202607 | B79: SL | C79: SE | D79: SE | E79: 2401.98 | F79: EUR | G79: EUR | H79: 1 | I79: 2401.98 | J79: finance.informe_vat_gestorias_detalle

Sheet i-marketplaces-sl
A1: <- Volver a P&G-SL
A2: yyyymm | B2: entity | C2: line_item | D2: detail | E2: amount_original | F2: currency_original | G2: reporting_currency | H2: fx_rate | I2: amount_reporting | J2: source | K2: invoice_number | L2: drive_url
A3: 202601 | B3: SL | C3: HANNUN | D3: orders | E3: 1419.7 | F3: EUR | G3: EUR | H3: 1 | I3: 1419.7 | J3: documents | K3: 2026-0008 | L3: https://drive.google.com/file/d/1SRHb07OiC_DmTMCjAnZJpaif5amIl7Fl/view?usp=drivesdk
A4: 202602 | B4: SL | C4: HANNUN | D4: orders | E4: 1128.42 | F4: EUR | G4: EUR | H4: 1 | I4: 1128.42 | J4: documents | K4: 2026-0013 | L4: https://drive.google.com/file/d/1CmAISLBvUVe78NnGfNvevigmLiHzSEsg/view?usp=drivesdk
A5: 202602 | B5: SL | C5: TOASTY | D5: b2b_partner | E5: 1746.6 | F5: EUR | G5: EUR | H5: 1 | I5: 1746.6 | J5: documents | K5: AS-99158 | L5: https://drive.google.com/file/d/1Caf6SbLhjNsliYTmwyaOj9tn_dQke6Ff/view?usp=drivesdk
A6: 202603 | B6: SL | C6: CHOOSE | D6: campaign | E6: 15609.96 | F6: EUR | G6: EUR | H6: 1 | I6: 15609.96 | J6: documents | K6: AS-101940 | L6: https://drive.google.com/file/d/18nd9g2717srK8fdaeAjNuV-HtW9zUU3A/view?usp=drivesdk
A7: 202603 | B7: SL | C7: HANNUN | D7: orders | E7: 1277.93 | F7: EUR | G7: EUR | H7: 1 | I7: 1277.93 | J7: documents | K7: 2026-0018 | L7: https://drive.google.com/file/d/1sizgdxMBUT_B7ZP3pPW8o5AjPDT-reZn/view?usp=drivesdk
A8: 202604 | B8: SL | C8: HANNUN | D8: orders | E8: 1683.63 | F8: EUR | G8: EUR | H8: 1 | I8: 1683.63 | J8: documents | K8: 2026-0022 | L8: https://drive.google.com/file/d/1OOCVQ9WtdMm6CCyphgf3SSGTF_CcdoPR/view?usp=drivesdk
A9: 202605 | B9: SL | C9: HANNUN | D9: orders | E9: 537.25 | F9: EUR | G9: EUR | H9: 1 | I9: 537.25 | J9: documents | K9: 2026-0026 | L9: https://drive.google.com/file/d/1EnDjHW6oQDDuhBGcQU4zAyLzl-V3lLpl/view?usp=drivesdk
A10: 202605 | B10: SL | C10: MAISONS | D10: marketplace | E10: -579.74 | F10: EUR | G10: EUR | H10: 1 | I10: -579.74 | J10: documents | K10: 000000323475 | L10: https://drive.google.com/file/d/1Nw1dW-Ij9HiS9A5ea4qV5llrtmiOADvG/view?usp=drivesdk
A11: 202606 | B11: SL | C11: CHOOSE | D11: campaign | E11: 6777.88 | F11: EUR | G11: EUR | H11: 1 | I11: 6777.88 | J11: documents | K11: AS-110388 | L11: https://drive.google.com/file/d/1oigOHZTknCPf32pVarZVN5E6ByEE0fen/view?usp=drivesdk
A12: 202606 | B12: SL | C12: HANNUN | D12: orders | E12: 1056 | F12: EUR | G12: EUR | H12: 1 | I12: 1056 | J12: documents | K12: 2026-0033 | L12: https://drive.google.com/file/d/191qw_M7Gw5UX6cagHrAxI52mcUiATx1H/view?usp=drivesdk
A13: 202606 | B13: SL | C13: TOASTY | D13: b2b_partner | E13: 856.76 | F13: EUR | G13: EUR | H13: 1 | I13: 856.76 | J13: documents | K13: AS-108593 | L13: https://drive.google.com/file/d/15hAZDxJMyLbK0z7-VgO0jT8Y0YTuQsmI/view?usp=drivesdk

Sheet i-rappels-sl
A1: <- Volver a P&G-SL
A2: yyyymm | B2: entity | C2: line_item | D2: detail | E2: amount_original | F2: currency_original | G2: reporting_currency | H2: fx_rate | I2: amount_reporting | J2: source | K2: invoice_number | L2: drive_url
A3: 202601 | B3: SL | C3: LIVITUM | D3: rappels | E3: -1118.95 | F3: EUR | G3: EUR | H3: 1 | I3: -1118.95 | J3: documents | K3: A_2026-0006 | L3: https://drive.google.com/file/d/1TatcT909r9lQss48nnCsBt5kjo76SoJK/view?usp=drivesdk

Sheet i-supplies-sl
A1: <- Volver a P&G-SL
A2: yyyymm | B2: entity | C2: line_item | D2: detail | E2: amount_original | F2: currency_original | G2: reporting_currency | H2: fx_rate | I2: amount_reporting | J2: source | K2: invoice_number | L2: drive_url
A3: 202601 | B3: SL | C3: REVER | D3: suplidos | E3: -1753.49 | F3: EUR | G3: EUR | H3: 1 | I3: -1753.49 | J3: documents | K3: SUPPLIED-202512 | L3: https://drive.google.com/file/d/1fcDMocaa4cpTPjITHzeqYj2_zqO3NWYG/view?usp=drivesdk
A4: 202601 | B4: SL | C4: REVER | D4: suplidos | E4: -422.97 | F4: EUR | G4: EUR | H4: 1 | I4: -422.97 | J4: documents | K4: SUPPLIED-202601 | L4: https://drive.google.com/file/d/1JrhdQBAxThJrJre0y6m_O_546LXVrueL/view?usp=drivesdk
A5: 202602 | B5: SL | C5: REVER | D5: suplidos | E5: -522.54 | F5: EUR | G5: EUR | H5: 1 | I5: -522.54 | J5: documents | K5: SUPPLIED-202602 | L5: https://drive.google.com/file/d/1P7U8R2vW7HJBpC4dFcTfQ6Fl5v7lZf-T/view?usp=drivesdk
A6: 202603 | B6: SL | C6: REVER | D6: suplidos | E6: -585.21 | F6: EUR | G6: EUR | H6: 1 | I6: -585.21 | J6: documents | K6: RVR-19100 | L6: https://drive.google.com/file/d/1baSEebJ4fJMCcK7mR48Bv7AvqlKFFcLB/view?usp=drivesdk
A7: 202604 | B7: SL | C7: REVER | D7: suplidos | E7: -540.81 | F7: EUR | G7: EUR | H7: 1 | I7: -540.81 | J7: documents | K7: SUPPLIED-202604 | L7: https://drive.google.com/file/d/10xgyYXbSD9m2Lrut8Cs1i9h4d85XaV--/view?usp=drivesdk
A8: 202606 | B8: SL | C8: REVER | D8: suplidos | E8: -801.46 | F8: EUR | G8: EUR | H8: 1 | I8: -801.46 | J8: documents | K8: SUPPLIED-202606 | L8: https://drive.google.com/file/d/12bNvnpTWHdXv_buIxf7ian_Nji5hfgM2/view?usp=drivesdk

Sheet i-services-sl
A1: <- Volver a P&G-SL
A2: yyyymm | B2: entity | C2: line_item | D2: detail | E2: amount_original | F2: currency_original | G2: reporting_currency | H2: fx_rate | I2: amount_reporting | J2: source | K2: invoice_number | L2: drive_url
A3: 202601 | B3: SL | C3: HANNUN | D3: staff | E3: 1191.18 | F3: EUR | G3: EUR | H3: 1 | I3: 1191.18 | J3: documents | K3: 2026-0007 | L3: https://drive.google.com/file/d/1NSgOhocDqu_GBFUbkAHX1ly92CIuLykN/view?usp=drivesdk
A4: 202601 | B4: SL | C4: Inc | D4: shared_services | E4: 7334.44 | F4: EUR | G4: EUR | H4: 1 | I4: 7334.44 | J4: documents:shared_services | K4: 2026-0009 | L4: https://drive.google.com/file/d/1f0y-ak8qjEua6xrzfcweFpWZqOtA8h9C/view?usp=drivesdk
A5: 202601 | B5: SL | C5: Ltd | D5: shared_services | E5: 10732.87 | F5: EUR | G5: EUR | H5: 1 | I5: 10732.87 | J5: documents:shared_services | K5: 2026-0010 | L5: https://drive.google.com/file/d/1DVbcrKI34TY_XRmPCWYxFfktOzy1Bqmr/view?usp=drivesdk
A6: 202602 | B6: SL | C6: HANNUN | D6: staff | E6: 1191.18 | F6: EUR | G6: EUR | H6: 1 | I6: 1191.18 | J6: documents | K6: 2026-0011 | L6: https://drive.google.com/file/d/1il-dTsdyMbUZFKcN_lnqoNWLpAFjKN7A/view?usp=drivesdk
A7: 202602 | B7: SL | C7: Inc | D7: shared_services | E7: 8462.36 | F7: EUR | G7: EUR | H7: 1 | I7: 8462.36 | J7: documents:shared_services | K7: 2026-0014 | L7: https://drive.google.com/file/d/1rlqcAuJUaWxt0Udjbpq3E6fP_lfRq58_/view?usp=drivesdk
A8: 202602 | B8: SL | C8: Ltd | D8: shared_services | E8: 13068.98 | F8: EUR | G8: EUR | H8: 1 | I8: 13068.98 | J8: documents:shared_services | K8: 2026-0015 | L8: https://drive.google.com/file/d/1pNRISEZAlDdg2kXsh98mNhDndQFk42mV/view?usp=drivesdk
A9: 202602 | B9: SL | C9: QHANDS | D9: renting_cnc | E9: 1661.16 | F9: EUR | G9: EUR | H9: 1 | I9: 1661.16 | J9: documents | K9: 2026-0006 | L9: https://drive.google.com/file/d/1ZNEswgq6fNRQmQBRT6GcjgdY_sepQuvN/view?usp=drivesdk
A10: 202602 | B10: SL | C10: QHANDS | D10: renting_cnc | E10: 1661.16 | F10: EUR | G10: EUR | H10: 1 | I10: 1661.16 | J10: documents | K10: 2026-0012 | L10: https://drive.google.com/file/d/1m_ONfUFq-mhxCI2SVs0iWw4Ss3ohvEPU/view?usp=drivesdk
A11: 202603 | B11: SL | C11: HANNUN | D11: staff | E11: 595.59 | F11: EUR | G11: EUR | H11: 1 | I11: 595.59 | J11: documents | K11: 2026-0019 | L11: https://drive.google.com/file/d/1HxjVp-Wv6lXooijCdy9-Z79LhGmFJwc2/view?usp=drivesdk
A12: 202603 | B12: SL | C12: Inc | D12: shared_services | E12: 7586.05 | F12: EUR | G12: EUR | H12: 1 | I12: 7586.05 | J12: documents:shared_services | K12: 2026-0017 | L12: https://drive.google.com/file/d/1ixVdpnGpB3KUF2QQIt94W1I4J6yD6ybZ/view?usp=drivesdk
A13: 202603 | B13: SL | C13: Ltd | D13: shared_services | E13: 14144.1 | F13: EUR | G13: EUR | H13: 1 | I13: 14144.1 | J13: documents:shared_services | K13: 2026-0016 | L13: https://drive.google.com/file/d/1KdK-Ik0l5-TAvrDmyV47ighudMtGRrKE/view?usp=drivesdk
A14: 202603 | B14: SL | C14: QHANDS | D14: renting_cnc | E14: 1800 | F14: EUR | G14: EUR | H14: 1 | I14: 1800 | J14: documents | K14: 2026-0020 | L14: https://drive.google.com/file/d/1cecAxU56GNtGgMfgA6Ftf1gfGiXJDd3S/view?usp=drivesdk
... A24: 202606 | B24: SL | C24: QHANDS | D24: renting_cnc | E24: 2089.49 | F24: EUR | G24: EUR | H24: 1 | I24: 2089.49 | J24: documents | K24: 2026-0031 | L24: https://drive.google.com/file/d/1GTB7C_m8wqI5ZcLtddZ9CbMD79Quoac-/view?usp=drivesdk

Sheet i-shared-services-sl
A1: <- Volver a P&G-SL
A2: yyyymm | B2: entity | C2: line_item | D2: detail | E2: amount_original | F2: currency_original | G2: reporting_currency | H2: fx_rate | I2: amount_reporting | J2: source | K2: invoice_number | L2: drive_url
A3: 202601 | B3: SL | C3: Inc | D3: shared_services | E3: 7334.44 | F3: EUR | G3: EUR | H3: 1 | I3: 7334.44 | J3: documents:shared_services | K3: 2026-0009 | L3: https://drive.google.com/file/d/1f0y-ak8qjEua6xrzfcweFpWZqOtA8h9C/view?usp=drivesdk
A4: 202601 | B4: SL | C4: Ltd | D4: shared_services | E4: 10732.87 | F4: EUR | G4: EUR | H4: 1 | I4: 10732.87 | J4: documents:shared_services | K4: 2026-0010 | L4: https://drive.google.com/file/d/1DVbcrKI34TY_XRmPCWYxFfktOzy1Bqmr/view?usp=drivesdk
A5: 202602 | B5: SL | C5: Inc | D5: shared_services | E5: 8462.36 | F5: EUR | G5: EUR | H5: 1 | I5: 8462.36 | J5: documents:shared_services | K5: 2026-0014 | L5: https://drive.google.com/file/d/1rlqcAuJUaWxt0Udjbpq3E6fP_lfRq58_/view?usp=drivesdk
A6: 202602 | B6: SL | C6: Ltd | D6: shared_services | E6: 13068.98 | F6: EUR | G6: EUR | H6: 1 | I6: 13068.98 | J6: documents:shared_services | K6: 2026-0015 | L6: https://drive.google.com/file/d/1pNRISEZAlDdg2kXsh98mNhDndQFk42mV/view?usp=drivesdk
A7: 202603 | B7: SL | C7: Inc | D7: shared_services | E7: 7586.05 | F7: EUR | G7: EUR | H7: 1 | I7: 7586.05 | J7: documents:shared_services | K7: 2026-0017 | L7: https://drive.google.com/file/d/1ixVdpnGpB3KUF2QQIt94W1I4J6yD6ybZ/view?usp=drivesdk
A8: 202603 | B8: SL | C8: Ltd | D8: shared_services | E8: 14144.1 | F8: EUR | G8: EUR | H8: 1 | I8: 14144.1 | J8: documents:shared_services | K8: 2026-0016 | L8: https://drive.google.com/file/d/1KdK-Ik0l5-TAvrDmyV47ighudMtGRrKE/view?usp=drivesdk
A9: 202604 | B9: SL | C9: Inc | D9: shared_services | E9: 6102.34 | F9: EUR | G9: EUR | H9: 1 | I9: 6102.34 | J9: documents:shared_services | K9: 2026-0024 | L9: https://drive.google.com/file/d/1nA8pTTvpT0O76zFAg7QOq9o2784L7_T5/view?usp=drivesdk
A10: 202604 | B10: SL | C10: Ltd | D10: shared_services | E10: 12924.89 | F10: EUR | G10: EUR | H10: 1 | I10: 12924.89 | J10: documents:shared_services | K10: 2026-0023 | L10: https://drive.google.com/file/d/1kG4iTL7rVDpQrcSDFJA0JzVE0hNuiLKc/view?usp=drivesdk
A11: 202605 | B11: SL | C11: Inc | D11: shared_services | E11: 5381.74 | F11: EUR | G11: EUR | H11: 1 | I11: 5381.74 | J11: documents:shared_services | K11: 2026-0028 | L11: https://drive.google.com/file/d/1ndoIxnRCHpafl83Lsyq-PVVCI1_lzXKu/view?usp=drivesdk
A12: 202605 | B12: SL | C12: Ltd | D12: shared_services | E12: 12909.18 | F12: EUR | G12: EUR | H12: 1 | I12: 12909.18 | J12: documents:shared_services | K12: 2026-0027 | L12: https://drive.google.com/file/d/13vcEBkqDKaSJerk401zu6MdDFpeCSKic/view?usp=drivesdk
A13: 202606 | B13: SL | C13: Inc | D13: shared_services | E13: 4876.31 | F13: EUR | G13: EUR | H13: 1 | I13: 4876.31 | J13: documents:shared_services | K13: 2026-0030 | L13: https://drive.google.com/file/d/12EthxatXwUiNej1AC0mO-nrxJnB0sWHC/view?usp=drivesdk
A14: 202606 | B14: SL | C14: Ltd | D14: shared_services | E14: 12520.32 | F14: EUR | G14: EUR | H14: 1 | I14: 12520.32 | J14: documents:shared_services | K14: 2026-0029 | L14: https://drive.google.com/file/d/1NTTQ0GfYXGRLMjb9JzaVQUreuF5aARGp/view?usp=drivesdk

Sheet g-expenses-sl
A1: <- Volver a P&G-SL
A2: yyyymm | B2: entity | C2: category | D2: subcategory | E2: supplier_code | F2: detail | G2: amount_original | H2: currency_original | I2: reporting_currency | J2: fx_rate | K2: amount_reporting | L2: source | M2: invoice_number | N2: drive_url
A3: 202601 | B3: SL | C3: opex | D3: technology | E3: RAILWAY | G3: 20 | H3: USD | I3: EUR | J3: 0.83899656 | K3: 16.78 | L3: documents | M3: 1602C2F5-0015 | N3: https://drive.google.com/file/d/1ih8AMHNM7ZQvhfJOhpZ3dpM0Bv3oyAA-/view?usp=drivesdk
A4: 202602 | B4: SL | C4: opex | D4: technology | E4: RAILWAY | G4: 20 | H4: USD | I4: EUR | J4: 0.84709869 | K4: 16.94 | L4: documents | M4: 1602C2F5-0016 | N4: https://drive.google.com/file/d/1nql7QpcMxbeNk-s_Ku_8yFOrf0x8QVss/view?usp=drivesdk
A5: 202601 | B5: SL | C5: opex | D5: technology | E5: ADOBE | G5: 33.49 | H5: EUR | I5: EUR | J5: 1 | K5: 33.49 | L5: documents | M5: IEE2026001813920 | N5: https://drive.google.com/file/d/1bfLhUT5wi1Zga5-YKV-y_tFqtaYvhqG_/view?usp=drivesdk
A6: 202601 | B6: SL | C6: cogs | D6: manufacturing | E6: APPHOTOCAN | G6: 29.22 | H6: EUR | I6: EUR | J6: 1 | K6: 29.22 | L6: documents | M6: 26-1-147 | N6: https://drive.google.com/file/d/1R3F1S4DkkMdWjQCije5h6JcXrv2oanjz/view?usp=drivesdk
A7: 202601 | B7: SL | C7: cogs | D7: manufacturing | E7: APPHOTOES | G7: 4472.74 | H7: EUR | I7: EUR | J7: 1 | K7: 4472.74 | L7: documents | M7: 1-1115 | N7: https://drive.google.com/file/d/1WUqPHPgca1EQI6FEQ45b4g1OBJLlBFy7/view?usp=drivesdk
A8: 202601 | B8: SL | C8: cogs | D8: manufacturing | E8: APPHOTOES | G8: 2583.61 | H8: EUR | I8: EUR | J8: 1 | K8: 2583.61 | L8: documents | M8: 1-412 | N8: https://drive.google.com/file/d/1HSHnKuD3wT5VaYKRyqQtc1Kn3jvbtI5z/view?usp=drivesdk
A9: 202601 | B9: SL | C9: cogs | D9: manufacturing | E9: APPHOTOES | G9: 1083.14 | H9: EUR | I9: EUR | J9: 1 | K9: 1083.14 | L9: documents | M9: 1-527 | N9: https://drive.google.com/file/d/1QiOFa-Pu55ImYk1EgtLQ-1AJeKteGKKN/view?usp=drivesdk
A10: 202601 | B10: SL | C10: cogs | D10: manufacturing | E10: APPHOTOES | G10: 9758.59 | H10: EUR | I10: EUR | J10: 1 | K10: 9758.59 | L10: documents | M10: 1-841 | N10: https://drive.google.com/file/d/1Nv_kf16K0jbiVtLvDOdsF2s81ubDK86-/view?usp=drivesdk
A11: 202601 | B11: SL | C11: opex | D11: administration | E11: BBVACNC | G11: 1644.62 | H11: EUR | I11: EUR | J11: 1 | K11: 1644.62 | L11: documents | M11: 260992A00006870 | N11: https://drive.google.com/file/d/1BgsncVPJONNOSwGkAe2eb6HAzwGUvo6M/view?usp=drivesdk
A12: 202601 | B12: SL | C12: opex | D12: technology | E12: CANVA | G12: 9.91 | H12: EUR | I12: EUR | J12: 1 | K12: 9.91 | L12: documents | M12: 04765-19148572 | N12: https://drive.google.com/file/d/1F1T1ZbmwTiAvZymdmK5UN5ILkYzAcyjE/view?usp=drivesdk
A13: 202601 | B13: SL | C13: opex | D13: administration | E13: CLARIS | G13: 808.08 | H13: EUR | I13: EUR | J13: 1 | K13: 808.08 | L13: documents | M13: F00036/26 | N13: https://drive.google.com/file/d/1sZGtXApoakTTNvLB9pud8pMEBdr3FgDZ/view?usp=drivesdk
A14: 202601 | B14: SL | C14: cogs | D14: logistics | E14: CORREOS | G14: 155.8 | H14: EUR | I14: EUR | J14: 1 | K14: 155.8 | L14: documents | M14: 4004550727 | N14: https://drive.google.com/file/d/13rt7yQ8sQuRvlpYE9WCitcMHEZMp3m_O/view?usp=drivesdk
... A22: 202601 | B22: SL | C22: opex | D22: technology | E22: GODADDY | G22: 17.24 | H22: EUR | I22: EUR | J22: 1 | K22: 17.24 | L22: documents | M22: 3994794936 | N22: https://drive.google.com/file/d/1wr9Nejy--4BUDpyg8riD4WzBFOQ_RYAA/view?usp=drivesdk
A23: 202601 | B23: SL | C23: opex | D23: marketing | E23: GOOGLEADS | F23: eu | G23: 24746.34 | H23: EUR | I23: EUR | J23: 1 | K23: 24746.34 | L23: documents | M23: 5489506571 | N23: https://drive.google.com/file/d/18pxQbj0cm3VVE381utczsaBPUOMg2_rE/view?usp=drivesdk
A24: 202601 | B24: SL | C24: opex | D24: marketing | E24: GOOGLEADS | F24: uk | G24: 2298.67 | H24: EUR | I24: EUR | J24: 1 | K24: 2298.67 | L24: documents | M24: 5489506571 | N24: https://drive.google.com/file/d/18pxQbj0cm3VVE381utczsaBPUOMg2_rE/view?usp=drivesdk
A25: 202601 | B25: SL | C25: opex | D25: marketing | E25: GOOGLEADS | F25: us | G25: 2119.05 | H25: EUR | I25: EUR | J25: 1 | K25: 2119.05 | L25: documents | M25: 5489506571 | N25: https://drive.google.com/file/d/18pxQbj0cm3VVE381utczsaBPUOMg2_rE/view?usp=drivesdk
A26: 202601 | B26: SL | C26: opex | D26: technology | E26: GOOGLEWORKSPACE | G26: 194.4 | H26: EUR | I26: EUR | J26: 1 | K26: 194.4 | L26: documents | M26: 5472439457 | N26: https://drive.google.com/file/d/1iux2hxJTx8pApkdRTQ8TxrWAycKskSLW/view?usp=drivesdk
A27: 202601 | B27: SL | C27: opex | D27: technology | E27: GORGIAS | G27: 201.2 | H27: USD | I27: EUR | J27: 0.83899656 | K27: 168.81 | L27: documents | M27: INC-01-2026-35934 | N27: https://drive.google.com/file/d/1cCVWMZjXH5GZ4KJ7Owu69neJD3Mu8nhQ/view?usp=drivesdk
A28: 202601 | B28: SL | C28: opex | D28: technology | E28: HETZNER | G28: 10.9 | H28: EUR | I28: EUR | J28: 1 | K28: 10.9 | L28: documents | M28: 084000638408 | N28: https://drive.google.com/file/d/17Q0iOe_5QA4ZC2x9xXn2aAcx-KGeRBqP/view?usp=drivesdk
A29: 202601 | B29: SL | C29: opex | D29: technology | E29: KONVOAI | G29: 114.89 | H29: EUR | I29: EUR | J29: 1 | K29: 114.89 | L29: documents | M29: B5F7DF3C-6721 | N29: https://drive.google.com/file/d/1FvjQkV9yZwLwYyh31yDEv4r6Ws9x-Gee/view?usp=drivesdk
A30: 202601 | B30: SL | C30: opex | D30: technology | E30: KONVOAI | G30: 339 | H30: EUR | I30: EUR | J30: 1 | K30: 339 | L30: documents | M30: B5F7DF3C-6940 | N30: https://drive.google.com/file/d/1saa91nUMC9fiC166aUrnROE5ZHw8d_r6/view?usp=drivesdk
A31: 202601 | B31: SL | C31: opex | D31: technology | E31: MASMOVIL | G31: 5 | H31: EUR | I31: EUR | J31: 1 | K31: 5 | L31: documents | M31: MC260001070524 | N31: https://drive.google.com/file/d/1Dqpxqnn8K6M513jJX6b-_iaNJoHc9CRf/view?usp=drivesdk
A32: 202601 | B32: SL | C32: opex | D32: marketing | E32: METAADS | F32: eu | G32: 20319.32 | H32: EUR | I32: EUR | J32: 1 | K32: 20319.32 | L32: documents | M32: 250807809 | N32: https://drive.google.com/file/d/18umjaalA1qWOFkhllNu22AbrnmcOGohV/view?usp=drivesdk
A33: 202601 | B33: SL | C33: opex | D33: marketing | E33: METAADS | F33: uk | G33: 3385.46 | H33: EUR | I33: EUR | J33: 1 | K33: 3385.46 | L33: documents | M33: 250807809 | N33: https://drive.google.com/file/d/18umjaalA1qWOFkhllNu22AbrnmcOGohV/view?usp=drivesdk
A34: 202601 | B34: SL | C34: opex | D34: marketing | E34: METAADS | F34: us | G34: 1779.68 | H34: EUR | I34: EUR | J34: 1 | K34: 1779.68 | L34: documents | M34: 250807809 | N34: https://drive.google.com/file/d/18umjaalA1qWOFkhllNu22AbrnmcOGohV/view?usp=drivesdk
A35: 202601 | B35: SL | C35: opex | D35: technology | E35: MICROSOFT | G35: 30.87 | H35: EUR | I35: EUR | J35: 1 | K35: 30.87 | L35: documents | M35: G135222851 | N35: https://drive.google.com/file/d/1YkkVd0CygsXrJ-x-3pub1Sw9g6ZsG1la/view?usp=drivesdk
A36: 202601 | B36: SL | C36: opex | D36: technology | E36: MICROSOFT | G36: 37.6 | H36: EUR | I36: EUR | J36: 1 | K36: 37.6 | L36: documents | M36: G135908417 | N36: https://drive.google.com/file/d/1X74XWbQ0nVaWgQCopQ2tDJAD55vrgHJF/view?usp=drivesdk
A37: 202601 | B37: SL | C37: opex | D37: administration | E37: NODA | G37: 170 | H37: EUR | I37: EUR | J37: 1 | K37: 170 | L37: documents | M37: 020/26 | N37: https://drive.google.com/file/d/1qPyUu5142bBXkD-iF2rUjI1dWjKrbRUf/view?usp=drivesdk
A38: 202601 | B38: SL | C38: opex | D38: technology | E38: OPENAI | F38: api_usage | G38: 10 | H38: USD | I38: EUR | J38: 0.83899656 | K38: 8.39 | L38: documents | M38: BZHJNTUB0001 | N38: https://drive.google.com/file/d/1c_a7u0uC_WNkVQzPENEHHzZf2GoRgYzp/view?usp=drivesdk
A39: 202601 | B39: SL | C39: opex | D39: technology | E39: OPENAI | F39: chatgpt_plus | G39: 19.01 | H39: EUR | I39: EUR | J39: 1 | K39: 19.01 | L39: documents | M39: 7BSDV5AM0001 | N39: https://drive.google.com/file/d/1Z8crn0ZC5tm2cibuFjiaNGAUQ32eDz4H/view?usp=drivesdk
A40: 202601 | B40: SL | C40: cogs | D40: manufacturing | E40: PRESSING | G40: 28979.31 | H40: EUR | I40: EUR | J40: 1 | K40: 28979.31 | L40: documents | M40: FAC/2026/26100000691 | N40: https://drive.google.com/file/d/1OUc0Fa83_INuKCsZQC_juJA8WSWOmU7e/view?usp=drivesdk
A41: 202601 | B41: SL | C41: opex | D41: technology | E41: PRODUCTHERO | G41: 134 | H41: EUR | I41: EUR | J41: 1 | K41: 134 | L41: documents | M41: 205588 | N41: https://drive.google.com/file/d/14DyM0O39wOTD_wOQwkZ2nqk44A4Xr0Pd/view?usp=drivesdk
A42: 202601 | B42: SL | C42: opex | D42: technology | E42: REVER | G42: 434.8 | H42: EUR | I42: EUR | J42: 1 | K42: 434.8 | L42: documents | M42: RVR-16471 | N42: https://drive.google.com/file/d/1MOlMl6uaY6n-XUO8ZDVih0oyxqYCdtvw/view?usp=drivesdk
A43: 202601 | B43: SL | C43: opex | D43: technology | E43: REVER | G43: 79 | H43: EUR | I43: EUR | J43: 1 | K43: 79 | L43: documents | M43: RVR-16823 | N43: https://drive.google.com/file/d/15PYo6Nf9Rs0V66jula2uxmSQ1q_sREm9/view?usp=drivesdk
A44: 202601 | B44: SL | C44: opex | D44: technology | E44: SHOPIFY | G44: 2674.4 | H44: USD | I44: EUR | J44: 0.83899656 | K44: 2243.81 | L44: documents | M44: 479105361 | N44: https://drive.google.com/file/d/1xcXRJuhK0s-9Giwr-lbqS68FlhkSzTWB/view?usp=drivesdk
A45: 202601 | B45: SL | C45: cogs | D45: logistics | E45: SPRINGGDS | G45: 3.3 | H45: EUR | I45: EUR | J45: 1 | K45: 3.3 | L45: documents | M45: E2600764 | N45: https://drive.google.com/file/d/1VbeIR7bk7enIlMQGnI8ZlR-KDaMoHDKn/view?usp=drivesdk
A46: 202601 | B46: SL | C46: opex | D46: administration | E46: TORRAS | G46: 15 | H46: EUR | I46: EUR | J46: 1 | K46: 15 | L46: documents | M46: 7/186 | N46: https://drive.google.com/file/d/1PKaZMRQ1ZsO4JALcKcucZLVdRyUxpOON/view?usp=drivesdk
A47: 202601 | B47: SL | C47: cogs | D47: logistics | E47: UPS | G47: 204.42 | H47: EUR | I47: EUR | J47: 1 | K47: 204.42 | L47: documents | M47: 326821409 | N47: https://drive.google.com/file/d/1j2ya4FHybtMpbOwe_dwCTFuK0BuXysGa/view?usp=drivesdk
A48: 202601 | B48: SL | C48: cogs | D48: logistics | E48: UPS | G48: 440.99 | H48: EUR | I48: EUR | J48: 1 | K48: 440.99 | L48: documents | M48: 326838548 | N48: https://drive.google.com/file/d/1zXVkELtv1Sfm3Hs-3PVSAH4pEWbvWaOX/view?usp=drivesdk
A49: 202601 | B49: SL | C49: cogs | D49: logistics | E49: UPS | G49: 2253.28 | H49: EUR | I49: EUR | J49: 1 | K49: 2253.28 | L49: documents | M49: 326867966 | N49: https://drive.google.com/file/d/1icRXW3dXluuRK-dzvuDcN-maR8sKfRW3/view?usp=drivesdk
A50: 202601 | B50: SL | C50: cogs | D50: logistics | E50: UPS | G50: 602.88 | H50: EUR | I50: EUR | J50: 1 | K50: 602.88 | L50: documents | M50: 326899416 | N50: https://drive.google.com/file/d/148ysN83vJtMLS2_lbKu7r5cH1NMHbVNL/view?usp=drivesdk
A51: 202601 | B51: SL | C51: cogs | D51: logistics | E51: UPS | G51: 604.6 | H51: EUR | I51: EUR | J51: 1 | K51: 604.6 | L51: documents | M51: 326966374 | N51: https://drive.google.com/file/d/1P3C1c_Df7dkPtnnAevEEMApNVP550O_O/view?usp=drivesdk
... A77: 202602 | B77: SL | C77: cogs | D77: logistics | E77: GLS | G77: 15947.02 | H77: EUR | I77: EUR | J77: 1 | K77: 15947.02 | L77: documents | M77: 20260082 | N77: https://drive.google.com/file/d/1KY46ho8xsJpWU6Q3w32ZWRQ8btywV8Ax/view?usp=drivesdk
A78: 202602 | B78: SL | C78: opex | D78: marketing | E78: GOOGLEADS | F78: eu | G78: 19199.14 | H78: EUR | I78: EUR | J78: 1 | K78: 19199.14 | L78: documents | M78: 5509802536 | N78: https://drive.google.com/file/d/192ghVBMKOyFtFrKk5lPoccixcsZlK4GH/view?usp=drivesdk
A79: 202602 | B79: SL | C79: opex | D79: marketing | E79: GOOGLEADS | F79: uk | G79: 5006.17 | H79: EUR | I79: EUR | J79: 1 | K79: 5006.17 | L79: documents | M79: 5509802536 | N79: https://drive.google.com/file/d/192ghVBMKOyFtFrKk5lPoccixcsZlK4GH/view?usp=drivesdk
A80: 202602 | B80: SL | C80: opex | D80: marketing | E80: GOOGLEADS | F80: us | G80: 3345.8 | H80: EUR | I80: EUR | J80: 1 | K80: 3345.8 | L80: documents | M80: 5509802536 | N80: https://drive.google.com/file/d/192ghVBMKOyFtFrKk5lPoccixcsZlK4GH/view?usp=drivesdk
A81: 202602 | B81: SL | C81: opex | D81: technology | E81: GOOGLEWORKSPACE | G81: 201.91 | H81: EUR | I81: EUR | J81: 1 | K81: 201.91 | L81: documents | M81: 5505030303 | N81: https://drive.google.com/file/d/1_odcqxdXxEYZNzgQx5UzslhIG3hh5krH/view?usp=drivesdk
A82: 202602 | B82: SL | C82: opex | D82: technology | E82: GORGIAS | G82: 120 | H82: USD | I82: EUR | J82: 0.84709869 | K82: 101.65 | L82: documents | M82: INC-02-2026-50341 | N82: https://drive.google.com/file/d/1tAciOjLJ3-E_udDrY3cL0A7b-CfOvIlm/view?usp=drivesdk
A83: 202601 | B83: SL | C83: opex | D83: administration | E83: HANNUN | F83: office | G83: 175 | H83: EUR | I83: EUR | J83: 1 | K83: 175 | L83: documents | M83: VTA/26-010327 | N83: https://drive.google.com/file/d/1E8JfN7YXvjRIfPjaLKj_8zJSQJ-990YT/view?usp=drivesdk
A84: 202602 | B84: SL | C84: opex | D84: administration | E84: HANNUN | F84: office | G84: 175 | H84: EUR | I84: EUR | J84: 1 | K84: 175 | L84: documents | M84: VTA/26-010329 | N84: https://drive.google.com/file/d/1r2Hw0N7VZ6vvloF4IqY4SxfuvX_2VozE/view?usp=drivesdk
A85: 202601 | B85: SL | C85: opex | D85: administration | E85: HANNUN | F85: services | G85: 1504.92 | H85: EUR | I85: EUR | J85: 1 | K85: 1504.92 | L85: documents | M85: VTA/26-010328 | N85: https://drive.google.com/file/d/1PRJ__aaxThVGTbIcvHAJI7pgUFchpvsa/view?usp=drivesdk
A86: 202602 | B86: SL | C86: opex | D86: administration | E86: HANNUN | F86: services | G86: 1504.92 | H86: EUR | I86: EUR | J86: 1 | K86: 1504.92 | L86: documents | M86: VTA/26-010330 | N86: https://drive.google.com/file/d/1HgIvIqgrCSyQY0-INtfhp-GPqb5Et1eA/view?usp=drivesdk
A87: 202602 | B87: SL | C87: opex | D87: technology | E87: HETZNER | G87: 10.9 | H87: EUR | I87: EUR | J87: 1 | K87: 10.9 | L87: documents | M87: 084000695806 | N87: https://drive.google.com/file/d/1mtjFeFve-rSAPTA0bq7zwh6FvresB1tx/view?usp=drivesdk
A88: 202602 | B88: SL | C88: opex | D88: technology | E88: KONVOAI | G88: 136.96 | H88: EUR | I88: EUR | J88: 1 | K88: 136.96 | L88: documents | M88: B5F7DF3C-7132 | N88: https://drive.google.com/file/d/1n2bq_tMI3rNE2XsFpxvWnwo1ZZV6_K21/view?usp=drivesdk
A89: 202602 | B89: SL | C89: opex | D89: technology | E89: KONVOAI | G89: 339 | H89: EUR | I89: EUR | J89: 1 | K89: 339 | L89: documents | M89: B5F7DF3C-7296 | N89: https://drive.google.com/file/d/1Mbfxr1V40xsgbj8F0soExM05QND6zjoa/view?usp=drivesdk
A90: 202602 | B90: SL | C90: opex | D90: technology | E90: MASMOVIL | G90: 5 | H90: EUR | I90: EUR | J90: 1 | K90: 5 | L90: documents | M90: MC260002345804 | N90: https://drive.google.com/file/d/1WOvzAAmEygTW3UfGCE2EpvFGcNYl4yVq/view?usp=drivesdk
A91: 202602 | B91: SL | C91: opex | D91: marketing | E91: METAADS | F91: eu | G91: 15883.55 | H91: EUR | I91: EUR | J91: 1 | K91: 15883.55 | L91: documents | M91: 251380763 | N91: https://drive.google.com/file/d/1fDDyyoah7JlWMHXzqFDIqm2howZDBJMq/view?usp=drivesdk
A92: 202602 | B92: SL | C92: opex | D92: marketing | E92: METAADS | F92: uk | G92: 2794.04 | H92: EUR | I92: EUR | J92: 1 | K92: 2794.04 | L92: documents | M92: 251380763 | N92: https://drive.google.com/file/d/1fDDyyoah7JlWMHXzqFDIqm2howZDBJMq/view?usp=drivesdk
A93: 202602 | B93: SL | C93: opex | D93: marketing | E93: METAADS | F93: us | G93: 1397.4 | H93: EUR | I93: EUR | J93: 1 | K93: 1397.4 | L93: documents | M93: 251380763 | N93: https://drive.google.com/file/d/1fDDyyoah7JlWMHXzqFDIqm2howZDBJMq/view?usp=drivesdk
A94: 202602 | B94: SL | C94: opex | D94: technology | E94: MICROSOFT | G94: 30.87 | H94: EUR | I94: EUR | J94: 1 | K94: 30.87 | L94: documents | M94: G140910268 | N94: https://drive.google.com/file/d/1IS2fSxolw6pxcI9vC65EJRYlFK7zyUTY/view?usp=drivesdk
A95: 202602 | B95: SL | C95: opex | D95: technology | E95: MICROSOFT | G95: 47 | H95: EUR | I95: EUR | J95: 1 | K95: 47 | L95: documents | M95: G141681724 | N95: https://drive.google.com/file/d/1najlnApOGpucn5h6ZtquKVucfInGLQ0V/view?usp=drivesdk
A96: 202602 | B96: SL | C96: opex | D96: technology | E96: OPENAI | F96: api_usage | G96: 10.03 | H96: USD | I96: EUR | J96: 0.84709869 | K96: 8.5 | L96: documents | M96: BZHJNTUB0002 | N96: https://drive.google.com/file/d/1Ia49BWDccoiY0_floiPgZIOoH73-LIUQ/view?usp=drivesdk
A97: 202602 | B97: SL | C97: opex | D97: technology | E97: OPENAI | F97: api_usage | G97: 10.12 | H97: USD | I97: EUR | J97: 0.84709869 | K97: 8.57 | L97: documents | M97: BZHJNTUB0003 | N97: https://drive.google.com/file/d/1bbYR8-vHGj7nUKVcEnARnepPzYzNIFVw/view?usp=drivesdk
A98: 202602 | B98: SL | C98: opex | D98: technology | E98: OPENAI | F98: api_usage | G98: 10.13 | H98: USD | I98: EUR | J98: 0.84709869 | K98: 8.58 | L98: documents | M98: BZHJNTUB0004 | N98: https://drive.google.com/file/d/1M7IINaxBWNqY7qOSMGrLDwYHI3VnAyM4/view?usp=drivesdk
A99: 202602 | B99: SL | C99: opex | D99: technology | E99: OPENAI | F99: api_usage | G99: 10.19 | H99: USD | I99: EUR | J99: 0.84709869 | K99: 8.63 | L99: documents | M99: BZHJNTUB0005 | N99: https://drive.google.com/file/d/1s-Ni6ccpvcuZUGwwhFepiSbUNzPwXVDG/view?usp=drivesdk
A100: 202602 | B100: SL | C100: opex | D100: technology | E100: OPENAI | F100: api_usage | G100: 30 | H100: USD | I100: EUR | J100: 0.84709869 | K100: 25.41 | L100: documents | M100: BZHJNTUB0006 | N100: https://drive.google.com/file/d/1j0GTnf9iA8T0YG7zocdvmE1v-yFf-dmk/view?usp=drivesdk
A101: 202602 | B101: SL | C101: opex | D101: technology | E101: OPENAI | F101: api_usage | G101: 10.41 | H101: USD | I101: EUR | J101: 0.84709869 | K101: 8.82 | L101: documents | M101: BZHJNTUB0007 | N101: https://drive.google.com/file/d/1kgfYW187O8CHpqvovwje1T5Vb0O1df6d/view?usp=drivesdk
A102: 202602 | B102: SL | C102: cogs | D102: manufacturing | E102: PRESSING | G102: 33510.62 | H102: EUR | I102: EUR | J102: 1 | K102: 33510.62 | L102: documents | M102: FAC/2026/26100001651 | N102: https://drive.google.com/file/d/1Ht3FP9y_KBG3F1Wui0f7dj36Nz4gORY9/view?usp=drivesdk
A103: 202602 | B103: SL | C103: opex | D103: technology | E103: PRODUCTHERO | G103: 134 | H103: EUR | I103: EUR | J103: 1 | K103: 134 | L103: documents | M103: 211723 | N103: https://drive.google.com/file/d/1axe5iqNHDnZKEyTVyAhJ5hBtI1BR5ejL/view?usp=drivesdk
A104: 202602 | B104: SL | C104: opex | D104: technology | E104: REVER | G104: 79 | H104: EUR | I104: EUR | J104: 1 | K104: 79 | L104: documents | M104: RVR-17688 | N104: https://drive.google.com/file/d/1D3oOwMbnoMx_ZwdzSUQ07lRdDelVCXX6/view?usp=drivesdk
A105: 202602 | B105: SL | C105: opex | D105: technology | E105: SHOPIFY | G105: 2812.25 | H105: USD | I105: EUR | J105: 0.84709869 | K105: 2382.25 | L105: documents | M105: 493806587 | N105: https://drive.google.com/file/d/1FNZalAzXj8a7ZNUt2CefEIFu_sLZ6iOY/view?usp=drivesdk
A106: 202602 | B106: SL | C106: opex | D106: technology | E106: SYNCWITH | G106: 24.99 | H106: USD | I106: EUR | J106: 0.84709869 | K106: 21.17 | L106: documents | M106: TADGCDFS-0001 | N106: https://drive.google.com/file/d/1PjQXXRgJWle6bvVGYUn8W3Swp9IqcBqL/view?usp=drivesdk
A107: 202602 | B107: SL | C107: opex | D107: administration | E107: TORRAS | G107: 15 | H107: EUR | I107: EUR | J107: 1 | K107: 15 | L107: documents | M107: 7/517 | N107: https://drive.google.com/file/d/1ryYPmeaeN0WBdXxhk4O9pmdF4BlNsACt/view?usp=drivesdk
A108: 202602 | B108: SL | C108: cogs | D108: logistics | E108: UPS | G108: 643.82 | H108: EUR | I108: EUR | J108: 1 | K108: 643.82 | L108: documents | M108: 326997856 | N108: https://drive.google.com/file/d/1FyBHZEA9qWMwRhMfdTuL7ySwcplaqQc2/view?usp=drivesdk
A109: 202602 | B109: SL | C109: cogs | D109: logistics | E109: UPS | G109: 629.73 | H109: EUR | I109: EUR | J109: 1 | K109: 629.73 | L109: documents | M109: 327030108 | N109: https://drive.google.com/file/d/1iPkhcnUQ6IlOI2t9Y4lt6fcN9NoE8559/view?usp=drivesdk
A110: 202602 | B110: SL | C110: cogs | D110: logistics | E110: UPS | G110: 512.62 | H110: EUR | I110: EUR | J110: 1 | K110: 512.62 | L110: documents | M110: 327061645 | N110: https://drive.google.com/file/d/1nrrH_8TfwdiHGNLlFgfu6hEx8mBDTA67/view?usp=drivesdk
A111: 202602 | B111: SL | C111: cogs | D111: logistics | E111: UPS | G111: 40.32 | H111: EUR | I111: EUR | J111: 1 | K111: 40.32 | L111: documents | M111: 838088024 | N111: https://drive.google.com/file/d/1Lq08NNbxsMBp7B7MMjUiEknDIr3kxPc0/view?usp=drivesdk
A112: 202602 | B112: SL | C112: opex | D112: technology | E112: YUMAAI | G112: 440 | H112: EUR | I112: EUR | J112: 1 | K112: 440 | L112: documents | M112: OQXBYXMP-0005 | N112: https://drive.google.com/file/d/1y53mv0-BjFCp7Z4Tp9mguo1WuS7RRlVK/view?usp=drivesdk
A113: 202603 | B113: SL | C113: opex | D113: technology | E113: ADOBE | G113: 33.49 | H113: EUR | I113: EUR | J113: 1 | K113: 33.49 | L113: documents | M113: IEE2026005856850 | N113: https://drive.google.com/file/d/1_QV16SfnrecVZCv19siScEIbSVNhcwQY/view?usp=drivesdk
... A123: 202603 | B123: SL | C123: cogs | D123: manufacturing | E123: APPHOTOES | G123: 5825.41 | H123: EUR | I123: EUR | J123: 1 | K123: 5825.41 | L123: documents | M123: 1-3959 | N123: https://drive.google.com/file/d/1qmdVuUyZKvATz7DKzN55oORVw6pAX9mO/view?usp=drivesdk
A124: 202603 | B124: SL | C124: cogs | D124: manufacturing | E124: ARTLINK | F124: manufacturing | G124: 570 | H124: EUR | I124: EUR | J124: 1 | K124: 570 | L124: documents | M124: 000203570 | N124: https://drive.google.com/file/d/1cfzsuLvXSAtRD2pLnRBZ59veQeIWQKjQ/view?usp=drivesdk
A125: 202603 | B125: SL | C125: opex | D125: administration | E125: BBVACNC | G125: 1644.62 | H125: EUR | I125: EUR | J125: 1 | K125: 1644.62 | L125: documents | M125: 260992A00111734 | N125: https://drive.google.com/file/d/1fSgw1oO1UaL0OokALxdVmk9Gs9s5_Vdz/view?usp=drivesdk
A126: 202603 | B126: SL | C126: opex | D126: technology | E126: CANVA | G126: 9.91 | H126: EUR | I126: EUR | J126: 1 | K126: 9.91 | L126: documents | M126: 04824-31033212 | N126: https://drive.google.com/file/d/1Bt_uYId0Ke_7yyUlyt95NlsppeCL3W_F/view?usp=drivesdk
A127: 202603 | B127: SL | C127: opex | D127: administration | E127: CLARIS | G127: 808.08 | H127: EUR | I127: EUR | J127: 1 | K127: 808.08 | L127: documents | M127: F00658/26 | N127: https://drive.google.com/file/d/194sPXt7bz4RYudtr1LLnRSTHRD3IRfX_/view?usp=drivesdk
A128: 202603 | B128: SL | C128: opex | D128: administration | E128: CONTASIMPLE | G128: 191.4 | H128: EUR | I128: EUR | J128: 1 | K128: 191.4 | L128: documents | M128: ES-2026-11348 | N128: https://drive.google.com/file/d/1Kf3zLbAifsK47hwsfDtdiya2nTjoZhbc/view?usp=drivesdk
A129: 202603 | B129: SL | C129: cogs | D129: logistics | E129: CORREOS | G129: 193.8 | H129: EUR | I129: EUR | J129: 1 | K129: 193.8 | L129: documents | M129: 4004641446 | N129: https://drive.google.com/file/d/19BOJcU-tZOdXNewpB9MmZXKbUeYoLmQW/view?usp=drivesdk
A130: 202603 | B130: SL | C130: cogs | D130: logistics | E130: CORREOSCAN | G130: 23.66 | H130: EUR | I130: EUR | J130: 1 | K130: 23.66 | L130: documents | M130: 4004641447 | N130: https://drive.google.com/file/d/1OSsPTK_eKr03kWPWfsduaZWbO-PcRSKN/view?usp=drivesdk
A131: 202603 | B131: SL | C131: cogs | D131: manufacturing | E131: DCT | G131: 2646.66 | H131: EUR | I131: EUR | J131: 1 | K131: 2646.66 | L131: documents | M131: 26-0463 | N131: https://drive.google.com/file/d/1d9bGOdNerfRkG8hm-9tNwNLOClNoUKV1/view?usp=drivesdk
A132: 202603 | B132: SL | C132: cogs | D132: manufacturing | E132: DCT | G132: 2854.58 | H132: EUR | I132: EUR | J132: 1 | K132: 2854.58 | L132: documents | M132: 26-0548 | N132: https://drive.google.com/file/d/1RN40IgZT0khKxDgZ1TciqcREU1AzC6iG/view?usp=drivesdk
A133: 202603 | B133: SL | C133: cogs | D133: logistics | E133: GLS | G133: 14170.85 | H133: EUR | I133: EUR | J133: 1 | K133: 14170.85 | L133: documents | M133: 20260150 | N133: https://drive.google.com/file/d/1Fys_Ke3o0S3pZkqtEQkaOmeaEm-sTj0X/view?usp=drivesdk
A134: 202603 | B134: SL | C134: opex | D134: technology | E134: GODADDY | G134: 13.11 | H134: EUR | I134: EUR | J134: 1 | K134: 13.11 | L134: documents | M134: 4046950709 | N134: https://drive.google.com/file/d/1mhP1xnzmk8CIu8lzS9UTKi1YVgQ0j5vD/view?usp=drivesdk
A135: 202603 | B135: SL | C135: opex | D135: technology | E135: GODADDY | G135: 21.99 | H135: EUR | I135: EUR | J135: 1 | K135: 21.99 | L135: documents | M135: 4048729358 | N135: https://drive.google.com/file/d/1EeQh_f0ge3L2vpmoZhGqULVvQDnFYlXt/view?usp=drivesdk
A136: 202603 | B136: SL | C136: opex | D136: marketing | E136: GOOGLEADS | F136: eu | G136: 24360.27 | H136: EUR | I136: EUR | J136: 1 | K136: 24360.27 | L136: documents | M136: 5538547928 | N136: https://drive.google.com/file/d/1s7eUjqGV_ux0WxJrpYLtGKjjOS3f9F_q/view?usp=drivesdk
A137: 202603 | B137: SL | C137: opex | D137: marketing | E137: GOOGLEADS | F137: uk | G137: 5956.59 | H137: EUR | I137: EUR | J137: 1 | K137: 5956.59 | L137: documents | M137: 5538547928 | N137: https://drive.google.com/file/d/1s7eUjqGV_ux0WxJrpYLtGKjjOS3f9F_q/view?usp=drivesdk
A138: 202603 | B138: SL | C138: opex | D138: marketing | E138: GOOGLEADS | F138: us | G138: 3341.56 | H138: EUR | I138: EUR | J138: 1 | K138: 3341.56 | L138: documents | M138: 5538547928 | N138: https://drive.google.com/file/d/1s7eUjqGV_ux0WxJrpYLtGKjjOS3f9F_q/view?usp=drivesdk
A139: 202603 | B139: SL | C139: opex | D139: technology | E139: GOOGLEWORKSPACE | G139: 210.6 | H139: EUR | I139: EUR | J139: 1 | K139: 210.6 | L139: documents | M139: 5528949048 | N139: https://drive.google.com/file/d/1l-tObm8vyP3XyPss2x7ZU0ypwypzolZi/view?usp=drivesdk
A140: 202603 | B140: SL | C140: opex | D140: technology | E140: GORGIAS | G140: 126.4 | H140: USD | I140: EUR | J140: 0.86971647 | K140: 109.93 | L140: documents | M140: INC-03-2026-64889 | N140: https://drive.google.com/file/d/1r5NeAkt6BuK7stM77wMD2GmwfOkmyuaE/view?usp=drivesdk
A141: 202603 | B141: SL | C141: opex | D141: administration | E141: HANNUN | F141: administration | G141: 30 | H141: EUR | I141: EUR | J141: 1 | K141: 30 | L141: documents | M141: VTA/26-010337 | N141: https://drive.google.com/file/d/1jBhJD7kS5_SPwJKWbOaHjrF8mX4mpiT8/view?usp=drivesdk
...

Sheet g-payment-fees-sl
A1: <- Volver a P&G-SL
A2: yyyymm | B2: entity | C2: supplier_code | D2: amount_original | E2: currency_original | F2: reporting_currency | G2: fx_rate | H2: amount_reporting | I2: source
A3: 202601 | B3: SL | C3: PAYPAL | D3: 1382.84 | E3: EUR | F3: EUR | G3: 1 | H3: 1382.84 | I3: payment_fee_monthly_summary
A4: 202601 | B4: SL | C4: SHOPIFY | D4: 2623.76 | E4: EUR | F4: EUR | G4: 1 | H4: 2623.76 | I4: payment_fee_monthly_summary
A5: 202602 | B5: SL | C5: PAYPAL | D5: 1172.84 | E5: EUR | F5: EUR | G5: 1 | H5: 1172.84 | I5: payment_fee_monthly_summary
A6: 202602 | B6: SL | C6: SHOPIFY | D6: 2661.9 | E6: EUR | F6: EUR | G6: 1 | H6: 2661.9 | I6: payment_fee_monthly_summary
A7: 202603 | B7: SL | C7: PAYPAL | D7: 1432.27 | E7: EUR | F7: EUR | G7: 1 | H7: 1432.27 | I7: payment_fee_monthly_summary
A8: 202603 | B8: SL | C8: SHOPIFY | D8: 2910.29 | E8: EUR | F8: EUR | G8: 1 | H8: 2910.29 | I8: payment_fee_monthly_summary
A9: 202604 | B9: SL | C9: PAYPAL | D9: 1264.93 | E9: EUR | F9: EUR | G9: 1 | H9: 1264.93 | I9: payment_fee_monthly_summary
A10: 202604 | B10: SL | C10: SHOPIFY | D10: 2532.09 | E10: EUR | F10: EUR | G10: 1 | H10: 2532.09 | I10: payment_fee_monthly_summary
A11: 202605 | B11: SL | C11: PAYPAL | D11: 1146.27 | E11: EUR | F11: EUR | G11: 1 | H11: 1146.27 | I11: payment_fee_monthly_summary
A12: 202605 | B12: SL | C12: SHOPIFY | D12: 2606.84 | E12: EUR | F12: EUR | G12: 1 | H12: 2606.84 | I12: payment_fee_monthly_summary
A13: 202606 | B13: SL | C13: PAYPAL | D13: 28.24 | E13: CZK | F13: EUR | G13: 0.04122691 | H13: 1.16 | I13: payment_fee_monthly_summary
A14: 202606 | B14: SL | C14: PAYPAL | D14: 1003 | E14: EUR | F14: EUR | G14: 1 | H14: 1003 | I14: payment_fee_monthly_summary
... A17: 202607 | B17: SL | C17: SHOPIFY | D17: 3052.63 | E17: EUR | F17: EUR | G17: 1 | H17: 3052.63 | I17: payment_fee_monthly_summary

Sheet fx-rates
A1: <- Volver a P&G-SL
A2: yyyymm | B2: rate_date | C2: currency_original | D2: reporting_currency | E2: reference_rate | F2: fx_rate | G2: source
A3: 202601 | B3: 2026-01-01 | C3: EUR | D3: EUR | E3: 1 | F3: 1 | G3: identity
A4: 202601 | B4: 2026-01-30 | C4: GBP | D4: EUR | E4: 0.8662 | F4: 1.1544678 | G4: https://www.ecb.europa.eu/stats/eurofxref/eurofxref-hist.xml
A5: 202601 | B5: 2026-01-30 | C5: USD | D5: EUR | E5: 1.1919 | F5: 0.83899656 | G5: https://www.ecb.europa.eu/stats/eurofxref/eurofxref-hist.xml
A6: 202602 | B6: 2026-02-01 | C6: EUR | D6: EUR | E6: 1 | F6: 1 | G6: identity
A7: 202602 | B7: 2026-02-27 | C7: GBP | D7: EUR | E7: 0.8763 | F7: 1.1411617 | G7: https://www.ecb.europa.eu/stats/eurofxref/eurofxref-hist.xml
A8: 202602 | B8: 2026-02-27 | C8: USD | D8: EUR | E8: 1.1805 | F8: 0.84709869 | G8: https://www.ecb.europa.eu/stats/eurofxref/eurofxref-hist.xml
A9: 202603 | B9: 2026-03-01 | C9: EUR | D9: EUR | E9: 1 | F9: 1 | G9: identity
A10: 202603 | B10: 2026-03-31 | C10: GBP | D10: EUR | E10: 0.86833 | F10: 1.1516359 | G10: https://www.ecb.europa.eu/stats/eurofxref/eurofxref-hist.xml
A11: 202603 | B11: 2026-03-31 | C11: USD | D11: EUR | E11: 1.1498 | F11: 0.86971647 | G11: https://www.ecb.europa.eu/stats/eurofxref/eurofxref-hist.xml
A12: 202604 | B12: 2026-04-01 | C12: EUR | D12: EUR | E12: 1 | F12: 1 | G12: identity
A13: 202604 | B13: 2026-04-30 | C13: GBP | D13: EUR | E13: 0.86625 | F13: 1.1544011 | G13: https://www.ecb.europa.eu/stats/eurofxref/eurofxref-hist.xml
A14: 202604 | B14: 2026-04-30 | C14: USD | D14: EUR | E14: 1.1702 | F14: 0.85455478 | G14: https://www.ecb.europa.eu/stats/eurofxref/eurofxref-hist.xml
... A34: 202612 | B34: 2026-07-30 | C34: USD | D34: EUR | E34: 1.1476 | F34: 0.87138376 | G34: https://www.ecb.europa.eu/stats/eurofxref/eurofxref-hist.xml (latest available, no ECB data for 202612)

Sheet catalog-sl
A1: <- Volver a P&G-SL
A2: supplier_code | B2: supplier_name | C2: current_folder | D2: destination_path | E2: notes
A3: CORREOS | B3: CORREOS | C3: Correos | D3: expenses/cogs/logistics | E3: Peninsula/Baleares 21% IVA
A4: CORREOSCAN | B4: CORREOSCAN | C4: Correos | D4: expenses/cogs/logistics | E4: Canarias 7% IGIC
A5: GLS | B5: GLS | C5: GLS | D5: expenses/cogs/logistics | E5: OCR-based GLS parser via scanned PDF
A6: SPRINGGDS | B6: SPRINGGDS | C6: SPRING | D6: expenses/cogs/logistics | E6: Spring operating brand
A7: UPS | B7: UPS | C7: UPS | D7: expenses/cogs/logistics
A8: APPHOTOCAN | B8: APPHOTOCAN | C8: AP Photo | D8: expenses/cogs/manufacturing | E8: IGIC 7%
A9: APPHOTOES | B9: APPHOTOES | C9: AP Photo | D9: expenses/cogs/manufacturing
A10: ARTLINK | B10: ARTLINK | C10: Artlink | D10: expenses/cogs/manufacturing | E10: Frame purchases and related freight are treated as manufacturing
A11: DCT | B11: DCT | C11: DCT | D11: expenses/cogs/manufacturing
A12: PRESSING | B12: PRESSING | C12: Pressing | D12: expenses/cogs/manufacturing
A13: ROYALTIES | B13: ROYALTIES | C13: Artistas | D13: expenses/cogs/royalties | E13: Artist royalties received and issued by Artesta
A14: ADEPLUS | B14: ADEPLUS | C14: Adeplus | D14: expenses/opex/administration | E14: Data protection services
A15: BBVACNC | B15: BANCO BILBAO VIZCAYA ARGENTARIA, S.A. | C15: CNC | D15: expenses/opex/administration
A16: CLARIS | B16: CLARIS | C16: CLARIS | D16: expenses/opex/administration
A17: CONTASIMPLE | B17: CONTASIMPLE | C17: Contasimple | D17: expenses/opex/administration | E17: Accounting software subscription
A18: HANNUN | B18: HANNUN | C18: HANNUN | D18: expenses/opex/administration | E18: Bidirectional HANNUN relationship; incoming expense invoices and outgoing customer invoices
A19: LINKEDIN | B19: LINKEDIN | C19: LinkedIn | D19: expenses/opex/administration | E19: LinkedIn hiring and recruiting invoices
A20: LIZENZERO | B20: LIZENZERO | C20: Lizenzero | D20: expenses/opex/administration | E20: Packaging license
A21: NODA | B21: NODA | C21: NODA Asesores | D21: expenses/opex/administration
A22: NOTARIOSMONTESQUINZA | B22: NOTARIOSMONTESQUINZA | C22: Notarios Monte Esquinza | D22: expenses/opex/administration | E22: Notary and registry invoices
A23: REGUS | B23: REGUS | C23: regus | D23: expenses/opex/administration
A24: TORRAS | B24: TORRAS | C24: TORRAS | D24: expenses/opex/administration
A25: VITALY | B25: VITALY | C25: Vitaly | D25: expenses/opex/administration | E25: Annual prevention and occupational health service
A26: GOOGLEADS | B26: GOOGLEADS | C26: Google | D26: expenses/opex/marketing
A27: METAADS | B27: METAADS | C27: Meta | D27: expenses/opex/marketing
A28: DOSCONSULTING | B28: DOSCONSULTING | C28: Nóminas | D28: expenses/opex/staff | E28: Monthly payroll management for SL
A29: ADOBE | B29: ADOBE | C29: ADOBE | D29: expenses/opex/technology
A30: CANVA | B30: CANVA | C30: canva | D30: expenses/opex/technology
A31: GODADDY | B31: GODADDY | C31: godaddy | D31: expenses/opex/technology
A32: GOOGLEWORKSPACE | B32: GOOGLEWORKSPACE | C32: Google | D32: expenses/opex/technology
A33: GORGIAS | B33: GORGIAS | C33: Gorgias | D33: expenses/opex/technology
A34: HETZNER | B34: HETZNER | C34: HETZNER | D34: expenses/opex/technology
A35: KONVOAI | B35: KONVOAI | C35: konvo | D35: expenses/opex/technology
A36: MASMOVIL | B36: MASMOVIL | C36: mas movil | D36: expenses/opex/technology
A37: MICROSOFT | B37: MICROSOFT | C37: MICROSOFT | D37: expenses/opex/technology
A38: OPENAI | B38: OPENAI | C38: chatgpt | D38: expenses/opex/technology | E38: Groups ChatGPT and API
A39: PRODUCTHERO | B39: PRODUCTHERO | C39: ProductHERO | D39: expenses/opex/technology
A40: RAILWAY | B40: RAILWAY | C40: RAILWAY | D40: expenses/opex/technology
A41: REVER | B41: REVER | C41: REVER | D41: expenses/opex/technology
A42: SHOPIFY | B42: SHOPIFY | C42: Shopify | D42: expenses/opex/technology
A43: SIMPLYCOM | B43: SIMPLYCOM | C43: SimplyCom | D43: expenses/opex/technology | E43: Domain and DNS services
A44: SYNCWITH | B44: SYNCWITH | C44: SyncWith | D44: expenses/opex/technology | E44: Monthly subscription invoiced one month in arrears
A45: YUMAAI | B45: YUMAAI | C45: YUMA | D45: expenses/opex/technology
A46: LIVITUM | B46: LIVITUM | C46: 709. Rappels | D46: income/other_income/rappels | E46: Rappel issued to Livitum
A47: CHOOSE | B47: CHOOSE | C47: CHOOSE | D47: income/sales/marketplaces | E47: Outgoing partner invoice
A48: MAISONS | B48: MAISONS | C48: Maisons du Monde | D48: income/sales/marketplaces | E48: Marketplace commissions and subscription invoices shown as negative marketplace revenue
A49: TOASTY | B49: TOASTY | C49: TOASTY | D49: income/sales/marketplaces | E49: Outgoing partner invoice
A50: QHANDS | B50: QHANDS | C50: QHANDS | D50: income/shared-services | E50: Outgoing CNC rental invoice

Sheet i-royalties-scope-sl
A1: <- Volver a P&G-SL
A2: yyyymm | B2: scope | C2: gross_amount
A3: 202601 | B3: eu | C3: 11994
A4: 202602 | B4: eu | C4: 14322
A5: 202603 | B5: eu | C5: 11865
A6: 202604 | B6: eu | C6: 11421
A7: 202605 | B7: eu | C7: 11598
A8: 202606 | B8: eu | C8: 9252
A9: 202601 | B9: uk | C9: 1272
A10: 202602 | B10: uk | C10: 1596
A11: 202603 | B11: uk | C11: 1938
A12: 202604 | B12: uk | C12: 1617
A13: 202605 | B13: uk | C13: 1629
A14: 202606 | B14: uk | C14: 1767
... A20: 202606 | B20: us | C20: 543

Sheet Nº Facturas-SL
D1: 202601 | E1: 202602 | F1: 202603 | G1: 202604 | H1: 202605 | I1: 202606 | J1: 202607 | K1: 202608 | L1: 202609 | M1: 202610 | N1: 202611 | O1: 202612 | P1: TOTAL
A2: Nº Facturas SL 2026 | D2: Enero | E2: Febrero | F2: Marzo | G2: Abril | H2: Mayo | I2: Junio | J2: Julio | K2: Agosto | L2: Septiembre | M2: Octubre | N2: Noviembre | O2: Diciembre | P2: Total
A4: Turnover | D4: 19 | E4: 19 | F4: 16 | G4: 16 | H4: 16 | I4: 20 | J4: 14 | K4: 0 | L4: 0 | M4: 0 | N4: 0 | O4: 0 | P4: 120
B5: Product sales | D5: 15 | E5: 14 | F5: 12 | G5: 12 | H5: 13 | I5: 15 | J5: 14 | K5: 0 | L5: 0 | M5: 0 | N5: 0 | O5: 0 | P5: 95
C6: Shopify | D6: 11 | E6: 11 | F6: 9 | G6: 10 | H6: 11 | I6: 11 | J6: 14 | K6: 0 | L6: 0 | M6: 0 | N6: 0 | O6: 0 | P6: 77
C7: ES | D7: 1 | E7: 1 | F7: 1 | G7: 1 | H7: 1 | I7: 1 | J7: 1 | K7: 0 | L7: 0 | M7: 0 | N7: 0 | O7: 0 | P7: 7
C8: FR | D8: 1 | E8: 1 | F8: 1 | G8: 1 | H8: 1 | I8: 1 | J8: 1 | K8: 0 | L8: 0 | M8: 0 | N8: 0 | O8: 0 | P8: 7
C9: DE | D9: 1 | E9: 1 | F9: 1 | G9: 1 | H9: 1 | I9: 1 | J9: 1 | K9: 0 | L9: 0 | M9: 0 | N9: 0 | O9: 0 | P9: 7
C10: IT | D10: 1 | E10: 1 | F10: 1 | G10: 1 | H10: 1 | I10: 1 | J10: 1 | K10: 0 | L10: 0 | M10: 0 | N10: 0 | O10: 0 | P10: 7
C11: AT | D11: 1 | E11: 1 | F11: 1 | G11: 1 | H11: 1 | I11: 1 | J11: 1 | K11: 0 | L11: 0 | M11: 0 | N11: 0 | O11: 0 | P11: 7
C12: BE | D12: 1 | E12: 1 | F12: 1 | G12: 1 | H12: 1 | I12: 1 | J12: 1 | K12: 0 | L12: 0 | M12: 0 | N12: 0 | O12: 0 | P12: 7
C13: NL | D13: 1 | E13: 1 | F13: 1 | G13: 0 | H13: 1 | I13: 1 | J13: 1 | K13: 0 | L13: 0 | M13: 0 | N13: 0 | O13: 0 | P13: 6
C14: PT | D14: 1 | E14: 1 | F14: 0 | G14: 1 | H14: 1 | I14: 1 | J14: 1 | K14: 0 | L14: 0 | M14: 0 | N14: 0 | O14: 0 | P14: 6
C15: CZ | D15: 1 | E15: 0 | F15: 0 | G15: 0 | H15: 0 | I15: 1 | J15: 1 | K15: 0 | L15: 0 | M15: 0 | N15: 0 | O15: 0 | P15: 3
C16: DK | D16: 0 | E16: 1 | F16: 0 | G16: 1 | H16: 1 | I16: 0 | J16: 1 | K16: 0 | L16: 0 | M16: 0 | N16: 0 | O16: 0 | P16: 4
C17: IE | D17: 0 | E17: 1 | F17: 1 | G17: 1 | H17: 1 | I17: 1 | J17: 1 | K17: 0 | L17: 0 | M17: 0 | N17: 0 | O17: 0 | P17: 6
... C29: REVER | D29: 2 | E29: 1 | F29: 1 | G29: 1 | H29: 0 | I29: 1 | J29: 0 | K29: 0 | L29: 0 | M29: 0 | N29: 0 | O29: 0 | P29: 6
B31: Services | D31: 3 | E31: 5 | F31: 4 | G31: 3 | H31: 3 | I31: 4 | J31: 0 | K31: 0 | L31: 0 | M31: 0 | N31: 0 | O31: 0 | P31: 22
C32: HANNUN | D32: 1 | E32: 1 | F32: 1 | G32: 0 | H32: 0 | I32: 1 | J32: 0 | K32: 0 | L32: 0 | M32: 0 | N32: 0 | O32: 0 | P32: 4
C33: QHANDS | D33: 0 | E33: 2 | F33: 1 | G33: 1 | H33: 1 | I33: 1 | J33: 0 | K33: 0 | L33: 0 | M33: 0 | N33: 0 | O33: 0 | P33: 6
C34: Ltd | D34: 1 | E34: 1 | F34: 1 | G34: 1 | H34: 1 | I34: 1 | J34: 0 | K34: 0 | L34: 0 | M34: 0 | N34: 0 | O34: 0 | P34: 6
C35: Inc | D35: 1 | E35: 1 | F35: 1 | G35: 1 | H35: 1 | I35: 1 | J35: 0 | K35: 0 | L35: 0 | M35: 0 | N35: 0 | O35: 0 | P35: 6
B36: Uncategorized income | D36: 1 | E36: 0 | F36: 0 | G36: 1 | H36: 0 | I36: 1 | J36: 0 | K36: 0 | L36: 0 | M36: 0 | N36: 0 | O36: 0 | P36: 3
A38: Expenses | D38: 52 | E38: 48 | F38: 55 | G38: 48 | H38: 43 | I38: 56 | J38: 34 | K38: 0 | L38: 0 | M38: 0 | N38: 0 | O38: 0 | P38: 336
B39: COGS | D39: 28 | E39: 22 | F39: 29 | G39: 24 | H39: 19 | I39: 25 | J39: 16 | K39: 0 | L39: 0 | M39: 0 | N39: 0 | O39: 0 | P39: 163
C40: Manufacturing | D40: 9 | E40: 12 | F40: 15 | G40: 9 | H40: 8 | I40: 10 | J40: 7 | K40: 0 | L40: 0 | M40: 0 | N40: 0 | O40: 0 | P40: 70
C41: APPHOTOCAN | D41: 1 | E41: 1 | F41: 1 | G41: 1 | H41: 1 | I41: 1 | J41: 1 | K41: 0 | L41: 0 | M41: 0 | N41: 0 | O41: 0 | P41: 7
C42: APPHOTOES | D42: 4 | E42: 7 | F42: 9 | G42: 5 | H42: 4 | I42: 4 | J42: 4 | K42: 0 | L42: 0 | M42: 0 | N42: 0 | O42: 0 | P42: 37
C43: ARTLINK | D43: 0 | E43: 0 | F43: 1 | G43: 0 | H43: 0 | I43: 1 | J43: 0 | K43: 0 | L43: 0 | M43: 0 | N43: 0 | O43: 0 | P43: 2
C44: DCT | D44: 3 | E44: 3 | F44: 2 | G44: 2 | H44: 2 | I44: 3 | J44: 1 | K44: 0 | L44: 0 | M44: 0 | N44: 0 | O44: 0 | P44: 16
C45: PRESSING | D45: 1 | E45: 1 | F45: 2 | G45: 1 | H45: 1 | I45: 1 | J45: 1 | K45: 0 | L45: 0 | M45: 0 | N45: 0 | O45: 0 | P45: 8
C46: Logistics | D46: 16 | E46: 7 | F46: 11 | G46: 12 | H46: 8 | I46: 11 | J46: 7 | K46: 0 | L46: 0 | M46: 0 | N46: 0 | O46: 0 | P46: 72
C47: CORREOS | D47: 2 | E47: 1 | F47: 1 | G47: 1 | H47: 1 | I47: 1 | J47: 0 | K47: 0 | L47: 0 | M47: 0 | N47: 0 | O47: 0 | P47: 7
C48: CORREOSCAN | D48: 1 | E48: 1 | F48: 1 | G48: 1 | H48: 1 | I48: 1 | J48: 0 | K48: 0 | L48: 0 | M48: 0 | N48: 0 | O48: 0 | P48: 6
C49: GLS | D49: 1 | E49: 1 | F49: 1 | G49: 1 | H49: 1 | I49: 1 | J49: 0 | K49: 0 | L49: 0 | M49: 0 | N49: 0 | O49: 0 | P49: 6
C50: SPRINGGDS | D50: 1 | E50: 0 | F50: 0 | G50: 0 | H50: 0 | I50: 0 | J50: 0 | K50: 0 | L50: 0 | M50: 0 | N50: 0 | O50: 0 | P50: 1
C51: UPS | D51: 11 | E51: 4 | F51: 8 | G51: 9 | H51: 5 | I51: 8 | J51: 7 | K51: 0 | L51: 0 | M51: 0 | N51: 0 | O51: 0 | P51: 52
... C59: PAYPAL | D59: 1 | E59: 1 | F59: 1 | G59: 1 | H59: 1 | I59: 2 | J59: 1 | K59: 0 | L59: 0 | M59: 0 | N59: 0 | O59: 0 | P59: 8
B62: Opex | D62: 24 | E62: 26 | F62: 26 | G62: 24 | H62: 24 | I62: 31 | J62: 18 | K62: 0 | L62: 0 | M62: 0 | N62: 0 | O62: 0 | P62: 173
C63: Marketing | D63: 0 | E63: 0 | F63: 0 | G63: 0 | H63: 0 | I63: 0 | J63: 0 | K63: 0 | L63: 0 | M63: 0 | N63: 0 | O63: 0 | P63: 0
C64: METAADS | D64: 0 | E64: 0 | F64: 0 | G64: 0 | H64: 0 | I64: 0 | J64: 0 | K64: 0 | L64: 0 | M64: 0 | N64: 0 | O64: 0 | P64: 0
C65: EU | D65: 0 | E65: 0 | F65: 0 | G65: 0 | H65: 0 | I65: 0 | J65: 0 | K65: 0 | L65: 0 | M65: 0 | N65: 0 | O65: 0 | P65: 0
C66: UK | D66: 0 | E66: 0 | F66: 0 | G66: 0 | H66: 0 | I66: 0 | J66: 0 | K66: 0 | L66: 0 | M66: 0 | N66: 0 | O66: 0 | P66: 0
C67: US | D67: 0 | E67: 0 | F67: 0 | G67: 0 | H67: 0 | I67: 0 | J67: 0 | K67: 0 | L67: 0 | M67: 0 | N67: 0 | O67: 0 | P67: 0
C68: GOOGLEADS | D68: 0 | E68: 0 | F68: 0 | G68: 0 | H68: 0 | I68: 0 | J68: 0 | K68: 0 | L68: 0 | M68: 0 | N68: 0 | O68: 0 | P68: 0
C69: EU | D69: 0 | E69: 0 | F69: 0 | G69: 0 | H69: 0 | I69: 0 | J69: 0 | K69: 0 | L69: 0 | M69: 0 | N69: 0 | O69: 0 | P69: 0
C70: UK | D70: 0 | E70: 0 | F70: 0 | G70: 0 | H70: 0 | I70: 0 | J70: 0 | K70: 0 | L70: 0 | M70: 0 | N70: 0 | O70: 0 | P70: 0
C71: US | D71: 0 | E71: 0 | F71: 0 | G71: 0 | H71: 0 | I71: 0 | J71: 0 | K71: 0 | L71: 0 | M71: 0 | N71: 0 | O71: 0 | P71: 0
C72: Staff | D72: 1 | E72: 1 | F72: 1 | G72: 1 | H72: 1 | I72: 1 | J72: 1 | K72: 0 | L72: 0 | M72: 0 | N72: 0 | O72: 0 | P72: 7
C73: PAYROLL | D73: 1 | E73: 1 | F73: 1 | G73: 1 | H73: 1 | I73: 1 | J73: 1 | K73: 0 | L73: 0 | M73: 0 | N73: 0 | O73: 0 | P73: 7
C74: DOSCONSULTING | D74: 0 | E74: 0 | F74: 0 | G74: 0 | H74: 0 | I74: 0 | J74: 0 | K74: 0 | L74: 0 | M74: 0 | N74: 0 | O74: 0 | P74: 0
... C109: Uncategorized Expenses | D109: 1 | E109: 1 | F109: 0 | G109: 1 | H109: 0 | I109: 1 | J109: 0 | K109: 0 | L109: 0 | M109: 0 | N109: 0 | O109: 0 | P109: 4
B110: Currency Adjustment | D110: 1 | E110: 1 | F110: 0 | G110: 1 | H110: 0 | I110: 1 | J110: 0 | K110: 0 | L110: 0 | M110: 0 | N110: 0 | O110: 0 | P110: 4

Sheet shared-services
A1: <- Volver a P&G-SL
D2: 202601 | E2: 202602 | F2: 202603 | G2: 202604 | H2: 202605 | I2: 202606 | J2: 202607 | K2: 202608 | L2: 202609 | M2: 202610 | N2: 202611 | O2: 202612 | P2: TOTAL
A3: Shared Services SL → LTD / INC 2026 | D3: Enero | E3: Febrero | F3: Marzo | G3: Abril | H3: Mayo | I3: Junio | J3: Julio | K3: Agosto | L3: Septiembre | M3: Octubre | N3: Noviembre | O3: Diciembre | P3: Total
A4: LTD (UK) | B4: ver facturas
A5: Marketing | D5: 6005.65 | E5: 7802.34 | F5: 8926.77 | G5: 7735.83 | H5: 7698.53 | I5: 7194.7 | J5: =SUMIFS('g-expenses-sl'!$K:$K,'g-expenses-sl'!$A:$A,J$2,'g-expenses-sl'!$D:$D,"marketing",'g-expenses-sl'!$F:$F,"uk") | K5: =SUMIFS('g-expenses-sl'!$K:$K,'g-expenses-sl'!$A:$A,K$2,'g-expenses-sl'!$D:$D,"marketing",'g-expenses-sl'!$F:$F,"uk") | L5: =SUMIFS('g-expenses-sl'!$K:$K,'g-expenses-sl'!$A:$A,L$2,'g-expenses-sl'!$D:$D,"marketing",'g-expenses-sl'!$F:$F,"uk") | M5: =SUMIFS('g-expenses-sl'!$K:$K,'g-expenses-sl'!$A:$A,M$2,'g-expenses-sl'!$D:$D,"marketing",'g-expenses-sl'!$F:$F,"uk") | N5: =SUMIFS('g-expenses-sl'!$K:$K,'g-expenses-sl'!$A:$A,N$2,'g-expenses-sl'!$D:$D,"marketing",'g-expenses-sl'!$F:$F,"uk") | O5: =SUMIFS('g-expenses-sl'!$K:$K,'g-expenses-sl'!$A:$A,O$2,'g-expenses-sl'!$D:$D,"marketing",'g-expenses-sl'!$F:$F,"uk") | P5: =SUM(D5:O5)
A6: Royalties | D6: 1232.79 | E6: 1596 | F6: 1938 | G6: 1617 | H6: 1629 | I6: 1767 | J6: =SUMIFS('i-royalties-scope-sl'!$C:$C,'i-royalties-scope-sl'!$A:$A,J$2,'i-royalties-scope-sl'!$B:$B,"uk") | K6: =SUMIFS('i-royalties-scope-sl'!$C:$C,'i-royalties-scope-sl'!$A:$A,K$2,'i-royalties-scope-sl'!$B:$B,"uk") | L6: =SUMIFS('i-royalties-scope-sl'!$C:$C,'i-royalties-scope-sl'!$A:$A,L$2,'i-royalties-scope-sl'!$B:$B,"uk") | M6: =SUMIFS('i-royalties-scope-sl'!$C:$C,'i-royalties-scope-sl'!$A:$A,M$2,'i-royalties-scope-sl'!$B:$B,"uk") | N6: =SUMIFS('i-royalties-scope-sl'!$C:$C,'i-royalties-scope-sl'!$A:$A,N$2,'i-royalties-scope-sl'!$B:$B,"uk") | O6: =SUMIFS('i-royalties-scope-sl'!$C:$C,'i-royalties-scope-sl'!$A:$A,O$2,'i-royalties-scope-sl'!$B:$B,"uk") | P6: =SUM(D6:O6)
A7: Staff | D7: 2946.37 | E7: 2946.37 | F7: 2302.41 | G7: 2327.27 | H7: 2327.27 | I7: 2313.27 | J7: ='P&G-SL'!J95*VLOOKUP("pct_staff_uk",params!$A:$B,2,0) | K7: ='P&G-SL'!K95*VLOOKUP("pct_staff_uk",params!$A:$B,2,0) | L7: ='P&G-SL'!L95*VLOOKUP("pct_staff_uk",params!$A:$B,2,0) | M7: ='P&G-SL'!M95*VLOOKUP("pct_staff_uk",params!$A:$B,2,0) | N7: ='P&G-SL'!N95*VLOOKUP("pct_staff_uk",params!$A:$B,2,0) | O7: ='P&G-SL'!O95*VLOOKUP("pct_staff_uk",params!$A:$B,2,0) | P7: =SUM(D7:O7)
A8: Administrativos | D8: 548.06 | E8: 724.27 | F8: 976.92 | G8: 1244.79 | H8: 1254.38 | I8: 1245.35 | J8: =('P&G-SL'!J98+'P&G-SL'!J114)*VLOOKUP("pct_admin_uk",params!$A:$B,2,0) | K8: =('P&G-SL'!K98+'P&G-SL'!K114)*VLOOKUP("pct_admin_uk",params!$A:$B,2,0) | L8: =('P&G-SL'!L98+'P&G-SL'!L114)*VLOOKUP("pct_admin_uk",params!$A:$B,2,0) | M8: =('P&G-SL'!M98+'P&G-SL'!M114)*VLOOKUP("pct_admin_uk",params!$A:$B,2,0) | N8: =('P&G-SL'!N98+'P&G-SL'!N114)*VLOOKUP("pct_admin_uk",params!$A:$B,2,0) | O8: =('P&G-SL'!O98+'P&G-SL'!O114)*VLOOKUP("pct_admin_uk",params!$A:$B,2,0) | P8: =SUM(D8:O8)
A9: TOTAL EUR | D9: =SUM(D5:D8) | E9: =SUM(E5:E8) | F9: =SUM(F5:F8) | G9: =SUM(G5:G8) | H9: =SUM(H5:H8) | I9: =SUM(I5:I8) | J9: =SUM(J5:J8) | K9: =SUM(K5:K8) | ... O9: =SUM(O5:O8) | P9: =SUM(D9:O9)
A10: TOTAL GBP | D10: =IFERROR(D9/AVERAGEIFS('fx-rates'!$F:$F,'fx-rates'!$A:$A,D$2,'fx-rates'!$C:$C,"GBP",'fx-rates'!$D:$D,"EUR"),D9) | E10: =IFERROR(E9/AVERAGEIFS('fx-rates'!$F:$F,'fx-rates'!$A:$A,E$2,'fx-rates'!$C:$C,"GBP",'fx-rates'!$D:$D,"EUR"),E9) | F10: =IFERROR(F9/AVERAGEIFS('fx-rates'!$F:$F,'fx-rates'!$A:$A,F$2,'fx-rates'!$C:$C,"GBP",'fx-rates'!$D:$D,"EUR"),F9) | G10: =IFERROR(G9/AVERAGEIFS('fx-rates'!$F:$F,'fx-rates'!$A:$A,G$2,'fx-rates'!$C:$C,"GBP",'fx-rates'!$D:$D,"EUR"),G9) | H10: =IFERROR(H9/AVERAGEIFS('fx-rates'!$F:$F,'fx-rates'!$A:$A,H$2,'fx-rates'!$C:$C,"GBP",'fx-rates'!$D:$D,"EUR"),H9) | I10: =IFERROR(I9/AVERAGEIFS('fx-rates'!$F:$F,'fx-rates'!$A:$A,I$2,'fx-rates'!$C:$C,"GBP",'fx-rates'!$D:$D,"EUR"),I9) | J10: =IFERROR(J9/AVERAGEIFS('fx-rates'!$F:$F,'fx-rates'!$A:$A,J$2,'fx-rates'!$C:$C,"GBP",'fx-rates'!$D:$D,"EUR"),J9) | K10: =IFERROR(K9/AVERAGEIFS('fx-rates'!$F:$F,'fx-rates'!$A:$A,K$2,'fx-rates'!$C:$C,"GBP",'fx-rates'!$D:$D,"EUR"),K9) | ... O10: =IFERROR(O9/AVERAGEIFS('fx-rates'!$F:$F,'fx-rates'!$A:$A,O$2,'fx-rates'!$C:$C,"GBP",'fx-rates'!$D:$D,"EUR"),O9) | P10: =SUM(D10:O10)
A12: INC (US) | B12: ver facturas
A13: Marketing | D13: 3899.81 | E13: 4744.08 | F13: 4658.83 | G13: 3153.97 | H13: 2522.98 | I13: 1960.9 | J13: =SUMIFS('g-expenses-sl'!$K:$K,'g-expenses-sl'!$A:$A,J$2,'g-expenses-sl'!$D:$D,"marketing",'g-expenses-sl'!$F:$F,"us") | K13: =SUMIFS('g-expenses-sl'!$K:$K,'g-expenses-sl'!$A:$A,K$2,'g-expenses-sl'!$D:$D,"marketing",'g-expenses-sl'!$F:$F,"us") | L13: =SUMIFS('g-expenses-sl'!$K:$K,'g-expenses-sl'!$A:$A,L$2,'g-expenses-sl'!$D:$D,"marketing",'g-expenses-sl'!$F:$F,"us") | M13: =SUMIFS('g-expenses-sl'!$K:$K,'g-expenses-sl'!$A:$A,M$2,'g-expenses-sl'!$D:$D,"marketing",'g-expenses-sl'!$F:$F,"us") | N13: =SUMIFS('g-expenses-sl'!$K:$K,'g-expenses-sl'!$A:$A,N$2,'g-expenses-sl'!$D:$D,"marketing",'g-expenses-sl'!$F:$F,"us") | O13: =SUMIFS('g-expenses-sl'!$K:$K,'g-expenses-sl'!$A:$A,O$2,'g-expenses-sl'!$D:$D,"marketing",'g-expenses-sl'!$F:$F,"us") | P13: =SUM(D13:O13)
A14: Royalties | D14: 460.59 | E14: 744 | F14: 741 | G14: 567 | H14: 471 | I14: 543 | J14: =SUMIFS('i-royalties-scope-sl'!$C:$C,'i-royalties-scope-sl'!$A:$A,J$2,'i-royalties-scope-sl'!$B:$B,"us") | K14: =SUMIFS('i-royalties-scope-sl'!$C:$C,'i-royalties-scope-sl'!$A:$A,K$2,'i-royalties-scope-sl'!$B:$B,"us") | L14: =SUMIFS('i-royalties-scope-sl'!$C:$C,'i-royalties-scope-sl'!$A:$A,L$2,'i-royalties-scope-sl'!$B:$B,"us") | M14: =SUMIFS('i-royalties-scope-sl'!$C:$C,'i-royalties-scope-sl'!$A:$A,M$2,'i-royalties-scope-sl'!$B:$B,"us") | N14: =SUMIFS('i-royalties-scope-sl'!$C:$C,'i-royalties-scope-sl'!$A:$A,N$2,'i-royalties-scope-sl'!$B:$B,"us") | O14: =SUMIFS('i-royalties-scope-sl'!$C:$C,'i-royalties-scope-sl'!$A:$A,O$2,'i-royalties-scope-sl'!$B:$B,"us") | P14: =SUM(D14:O14)
A15: Staff | D15: 2946.37 | E15: 2946.37 | F15: 1534.94 | G15: 1551.51 | H15: 1551.51 | I15: 1542.18 | J15: ='P&G-SL'!J95*VLOOKUP("pct_staff_us",params!$A:$B,2,0) | K15: ='P&G-SL'!K95*VLOOKUP("pct_staff_us",params!$A:$B,2,0) | L15: ='P&G-SL'!L95*VLOOKUP("pct_staff_us",params!$A:$B,2,0) | M15: ='P&G-SL'!M95*VLOOKUP("pct_staff_us",params!$A:$B,2,0) | N15: ='P&G-SL'!N95*VLOOKUP("pct_staff_us",params!$A:$B,2,0) | O15: ='P&G-SL'!O95*VLOOKUP("pct_staff_us",params!$A:$B,2,0) | P15: =SUM(D15:O15)
A16: Administrativos | D16: 27.67 | E16: 27.91 | F16: 651.28 | G16: 829.86 | H16: 836.25 | I16: 830.23 | J16: =('P&G-SL'!J98+'P&G-SL'!J114)*VLOOKUP("pct_admin_us",params!$A:$B,2,0) | K16: =('P&G-SL'!K98+'P&G-SL'!K114)*VLOOKUP("pct_admin_us",params!$A:$B,2,0) | L16: =('P&G-SL'!L98+'P&G-SL'!L114)*VLOOKUP("pct_admin_us",params!$A:$B,2,0) | M16: =('P&G-SL'!M98+'P&G-SL'!M114)*VLOOKUP("pct_admin_us",params!$A:$B,2,0) | N16: =('P&G-SL'!N98+'P&G-SL'!N114)*VLOOKUP("pct_admin_us",params!$A:$B,2,0) | O16: =('P&G-SL'!O98+'P&G-SL'!O114)*VLOOKUP("pct_admin_us",params!$A:$B,2,0) | P16: =SUM(D16:O16)
A17: TOTAL EUR | D17: =SUM(D13:D16) | E17: =SUM(E13:E16) | F17: =SUM(F13:F16) | G17: =SUM(G13:G16) | H17: =SUM(H13:H16) | I17: =SUM(I13:I16) | J17: =SUM(J13:J16) | K17: =SUM(K13:K16) | ... O17: =SUM(O13:O16) | P17: =SUM(D17:O17)
A18: TOTAL USD | D18: =IFERROR(D17/AVERAGEIFS('fx-rates'!$F:$F,'fx-rates'!$A:$A,D$2,'fx-rates'!$C:$C,"USD",'fx-rates'!$D:$D,"EUR"),D17) | E18: =IFERROR(E17/AVERAGEIFS('fx-rates'!$F:$F,'fx-rates'!$A:$A,E$2,'fx-rates'!$C:$C,"USD",'fx-rates'!$D:$D,"EUR"),E17) | F18: =IFERROR(F17/AVERAGEIFS('fx-rates'!$F:$F,'fx-rates'!$A:$A,F$2,'fx-rates'!$C:$C,"USD",'fx-rates'!$D:$D,"EUR"),F17) | G18: =IFERROR(G17/AVERAGEIFS('fx-rates'!$F:$F,'fx-rates'!$A:$A,G$2,'fx-rates'!$C:$C,"USD",'fx-rates'!$D:$D,"EUR"),G17) | H18: =IFERROR(H17/AVERAGEIFS('fx-rates'!$F:$F,'fx-rates'!$A:$A,H$2,'fx-rates'!$C:$C,"USD",'fx-rates'!$D:$D,"EUR"),H17) | I18: =IFERROR(I17/AVERAGEIFS('fx-rates'!$F:$F,'fx-rates'!$A:$A,I$2,'fx-rates'!$C:$C,"USD",'fx-rates'!$D:$D,"EUR"),I17) | J18: =IFERROR(J17/AVERAGEIFS('fx-rates'!$F:$F,'fx-rates'!$A:$A,J$2,'fx-rates'!$C:$C,"USD",'fx-rates'!$D:$D,"EUR"),J17) | K18: =IFERROR(K17/AVERAGEIFS('fx-rates'!$F:$F,'fx-rates'!$A:$A,K$2,'fx-rates'!$C:$C,"USD",'fx-rates'!$D:$D,"EUR"),K17) | ... O18: =IFERROR(O17/AVERAGEIFS('fx-rates'!$F:$F,'fx-rates'!$A:$A,O$2,'fx-rates'!$C:$C,"USD",'fx-rates'!$D:$D,"EUR"),O17) | P18: =SUM(D18:O18)
A20: TOTAL SHARED SERVICES EUR | D20: =D9+D17 | E20: =E9+E17 | F20: =F9+F17 | G20: =G9+G17 | H20: =H9+H17 | I20: =I9+I17 | J20: =J9+J17 | K20: =K9+K17 | ... O20: =O9+O17 | P20: =SUM(D20:O20)
