Workbook

Sheet P&G-CONSOLIDADO
D1: 202601 | E1: 202602 | F1: 202603 | G1: 202604 | H1: 202605 | I1: 202606 | J1: 202607 | K1: 202608 | L1: 202609 | M1: 202610 | N1: 202611 | O1: 202612 | P1: TOTAL
A2: P&G CONSOLIDADO 2026 (EUR) | D2: Enero | E2: Febrero | F2: Marzo | G2: Abril | H2: Mayo | I2: Junio | J2: Julio | K2: Agosto | L2: Septiembre | M2: Octubre | N2: Noviembre | O2: Diciembre | P2: Total
A3: Shopify daily average | Actualizado: 04/09/2026 10:00 h | D3: =IFERROR(IF(DATE(VALUE(LEFT(D$1,4)),VALUE(RIGHT(D$1,2)),1)>TODAY(),"",IF(EOMONTH(DATE(VALUE(LEFT(D$1,4)),VALUE(RIGHT(D$1,2)),1),0)<TODAY(),D6/DAY(EOMONTH(DATE(VALUE(LEFT(D$1,4)),VALUE(RIGHT(D$1,2)),1),0)),D6/MAX(NOW()-DATE(VALUE(LEFT(D$1,4)),VALUE(RIGHT(D$1,2)),1),1/24))),"") | E3: =IFERROR(IF(DATE(VALUE(LEFT(E$1,4)),VALUE(RIGHT(E$1,2)),1)>TODAY(),"",IF(EOMONTH(DATE(VALUE(LEFT(E$1,4)),VALUE(RIGHT(E$1,2)),1),0)<TODAY(),E6/DAY(EOMONTH(DATE(VALUE(LEFT(E$1,4)),VALUE(RIGHT(E$1,2)),1),0)),E6/MAX(NOW()-DATE(VALUE(LEFT(E$1,4)),VALUE(RIGHT(E$1,2)),1),1/24))),"") | F3: =IFERROR(IF(DATE(VALUE(LEFT(F$1,4)),VALUE(RIGHT(F$1,2)),1)>TODAY(),"",IF(EOMONTH(DATE(VALUE(LEFT(F$1,4)),VALUE(RIGHT(F$1,2)),1),0)<TODAY(),F6/DAY(EOMONTH(DATE(VALUE(LEFT(F$1,4)),VALUE(RIGHT(F$1,2)),1),0)),F6/MAX(NOW()-DATE(VALUE(LEFT(F$1,4)),VALUE(RIGHT(F$1,2)),1),1/24))),"") | G3: =IFERROR(IF(DATE(VALUE(LEFT(G$1,4)),VALUE(RIGHT(G$1,2)),1)>TODAY(),"",IF(EOMONTH(DATE(VALUE(LEFT(G$1,4)),VALUE(RIGHT(G$1,2)),1),0)<TODAY(),G6/DAY(EOMONTH(DATE(VALUE(LEFT(G$1,4)),VALUE(RIGHT(G$1,2)),1),0)),G6/MAX(NOW()-DATE(VALUE(LEFT(G$1,4)),VALUE(RIGHT(G$1,2)),1),1/24))),"") | H3: =IFERROR(IF(DATE(VALUE(LEFT(H$1,4)),VALUE(RIGHT(H$1,2)),1)>TODAY(),"",IF(EOMONTH(DATE(VALUE(LEFT(H$1,4)),VALUE(RIGHT(H$1,2)),1),0)<TODAY(),H6/DAY(EOMONTH(DATE(VALUE(LEFT(H$1,4)),VALUE(RIGHT(H$1,2)),1),0)),H6/MAX(NOW()-DATE(VALUE(LEFT(H$1,4)),VALUE(RIGHT(H$1,2)),1),1/24))),"") | I3: =IFERROR(IF(DATE(VALUE(LEFT(I$1,4)),VALUE(RIGHT(I$1,2)),1)>TODAY(),"",IF(EOMONTH(DATE(VALUE(LEFT(I$1,4)),VALUE(RIGHT(I$1,2)),1),0)<TODAY(),I6/DAY(EOMONTH(DATE(VALUE(LEFT(I$1,4)),VALUE(RIGHT(I$1,2)),1),0)),I6/MAX(NOW()-DATE(VALUE(LEFT(I$1,4)),VALUE(RIGHT(I$1,2)),1),1/24))),"") | J3: =IFERROR(IF(DATE(VALUE(LEFT(J$1,4)),VALUE(RIGHT(J$1,2)),1)>TODAY(),"",IF(EOMONTH(DATE(VALUE(LEFT(J$1,4)),VALUE(RIGHT(J$1,2)),1),0)<TODAY(),J6/DAY(EOMONTH(DATE(VALUE(LEFT(J$1,4)),VALUE(RIGHT(J$1,2)),1),0)),J6/MAX(NOW()-DATE(VALUE(LEFT(J$1,4)),VALUE(RIGHT(J$1,2)),1),1/24))),"") | K3: =IFERROR(IF(DATE(VALUE(LEFT(K$1,4)),VALUE(RIGHT(K$1,2)),1)>TODAY(),"",IF(EOMONTH(DATE(VALUE(LEFT(K$1,4)),VALUE(RIGHT(K$1,2)),1),0)<TODAY(),K6/DAY(EOMONTH(DATE(VALUE(LEFT(K$1,4)),VALUE(RIGHT(K$1,2)),1),0)),K6/MAX(NOW()-DATE(VALUE(LEFT(K$1,4)),VALUE(RIGHT(K$1,2)),1),1/24))),"") | ... O3: =IFERROR(IF(DATE(VALUE(LEFT(O$1,4)),VALUE(RIGHT(O$1,2)),1)>TODAY(),"",IF(EOMONTH(DATE(VALUE(LEFT(O$1,4)),VALUE(RIGHT(O$1,2)),1),0)<TODAY(),O6/DAY(EOMONTH(DATE(VALUE(LEFT(O$1,4)),VALUE(RIGHT(O$1,2)),1),0)),O6/MAX(NOW()-DATE(VALUE(LEFT(O$1,4)),VALUE(RIGHT(O$1,2)),1),1/24))),"")
A4: TURNOVER | D4: =D5+D17+D18 | E4: =E5+E17+E18 | F4: =F5+F17+F18 | G4: =G5+G17+G18 | H4: =H5+H17+H18 | I4: =I5+I17+I18 | J4: =J5+J17+J18 | K4: =K5+K17+K18 | ... O4: =O5+O17+O18 | P4: =SUM(D4:O4)
A5: Product sales | D5: =D6+D14+D15+D16 | E5: =E6+E14+E15+E16 | F5: =F6+F14+F15+F16 | G5: =G6+G14+G15+G16 | H5: =H6+H14+H15+H16 | I5: =I6+I14+I15+I16 | J5: =J6+J14+J15+J16 | K5: =K6+K14+K15+K16 | ... O5: =O6+O14+O15+O16 | P5: =SUM(D5:O5)
A6: Shopify | D6: =D7+D9+D11 | E6: =E7+E9+E11 | F6: =F7+F9+F11 | G6: =G7+G9+G11 | H6: =H7+H9+H11 | I6: =I7+I9+I11 | J6: =J7+J9+J11 | K6: =K7+K9+K11 | ... O6: =O7+O9+O11 | P6: =SUM(D6:O6)
A7: SL | D7: =SUMIFS('i-sl'!$C:$C,'i-sl'!$A:$A,D$1,'i-sl'!$B:$B,"shopify") | E7: =SUMIFS('i-sl'!$C:$C,'i-sl'!$A:$A,E$1,'i-sl'!$B:$B,"shopify") | F7: =SUMIFS('i-sl'!$C:$C,'i-sl'!$A:$A,F$1,'i-sl'!$B:$B,"shopify") | G7: =SUMIFS('i-sl'!$C:$C,'i-sl'!$A:$A,G$1,'i-sl'!$B:$B,"shopify") | H7: =SUMIFS('i-sl'!$C:$C,'i-sl'!$A:$A,H$1,'i-sl'!$B:$B,"shopify") | I7: =SUMIFS('i-sl'!$C:$C,'i-sl'!$A:$A,I$1,'i-sl'!$B:$B,"shopify") | J7: =SUMIFS('i-sl'!$C:$C,'i-sl'!$A:$A,J$1,'i-sl'!$B:$B,"shopify") | K7: =SUMIFS('i-sl'!$C:$C,'i-sl'!$A:$A,K$1,'i-sl'!$B:$B,"shopify") | ... O7: =SUMIFS('i-sl'!$C:$C,'i-sl'!$A:$A,O$1,'i-sl'!$B:$B,"shopify") | P7: =SUM(D7:O7)
A8: avg/day | D8: =IFERROR(IF(DATE(VALUE(LEFT(D$1,4)),VALUE(RIGHT(D$1,2)),1)>TODAY(),"",IF(EOMONTH(DATE(VALUE(LEFT(D$1,4)),VALUE(RIGHT(D$1,2)),1),0)<TODAY(),D7/DAY(EOMONTH(DATE(VALUE(LEFT(D$1,4)),VALUE(RIGHT(D$1,2)),1),0)),D7/MAX(NOW()-DATE(VALUE(LEFT(D$1,4)),VALUE(RIGHT(D$1,2)),1),1/24))),"") | E8: =IFERROR(IF(DATE(VALUE(LEFT(E$1,4)),VALUE(RIGHT(E$1,2)),1)>TODAY(),"",IF(EOMONTH(DATE(VALUE(LEFT(E$1,4)),VALUE(RIGHT(E$1,2)),1),0)<TODAY(),E7/DAY(EOMONTH(DATE(VALUE(LEFT(E$1,4)),VALUE(RIGHT(E$1,2)),1),0)),E7/MAX(NOW()-DATE(VALUE(LEFT(E$1,4)),VALUE(RIGHT(E$1,2)),1),1/24))),"") | F8: =IFERROR(IF(DATE(VALUE(LEFT(F$1,4)),VALUE(RIGHT(F$1,2)),1)>TODAY(),"",IF(EOMONTH(DATE(VALUE(LEFT(F$1,4)),VALUE(RIGHT(F$1,2)),1),0)<TODAY(),F7/DAY(EOMONTH(DATE(VALUE(LEFT(F$1,4)),VALUE(RIGHT(F$1,2)),1),0)),F7/MAX(NOW()-DATE(VALUE(LEFT(F$1,4)),VALUE(RIGHT(F$1,2)),1),1/24))),"") | G8: =IFERROR(IF(DATE(VALUE(LEFT(G$1,4)),VALUE(RIGHT(G$1,2)),1)>TODAY(),"",IF(EOMONTH(DATE(VALUE(LEFT(G$1,4)),VALUE(RIGHT(G$1,2)),1),0)<TODAY(),G7/DAY(EOMONTH(DATE(VALUE(LEFT(G$1,4)),VALUE(RIGHT(G$1,2)),1),0)),G7/MAX(NOW()-DATE(VALUE(LEFT(G$1,4)),VALUE(RIGHT(G$1,2)),1),1/24))),"") | H8: =IFERROR(IF(DATE(VALUE(LEFT(H$1,4)),VALUE(RIGHT(H$1,2)),1)>TODAY(),"",IF(EOMONTH(DATE(VALUE(LEFT(H$1,4)),VALUE(RIGHT(H$1,2)),1),0)<TODAY(),H7/DAY(EOMONTH(DATE(VALUE(LEFT(H$1,4)),VALUE(RIGHT(H$1,2)),1),0)),H7/MAX(NOW()-DATE(VALUE(LEFT(H$1,4)),VALUE(RIGHT(H$1,2)),1),1/24))),"") | I8: =IFERROR(IF(DATE(VALUE(LEFT(I$1,4)),VALUE(RIGHT(I$1,2)),1)>TODAY(),"",IF(EOMONTH(DATE(VALUE(LEFT(I$1,4)),VALUE(RIGHT(I$1,2)),1),0)<TODAY(),I7/DAY(EOMONTH(DATE(VALUE(LEFT(I$1,4)),VALUE(RIGHT(I$1,2)),1),0)),I7/MAX(NOW()-DATE(VALUE(LEFT(I$1,4)),VALUE(RIGHT(I$1,2)),1),1/24))),"") | J8: =IFERROR(IF(DATE(VALUE(LEFT(J$1,4)),VALUE(RIGHT(J$1,2)),1)>TODAY(),"",IF(EOMONTH(DATE(VALUE(LEFT(J$1,4)),VALUE(RIGHT(J$1,2)),1),0)<TODAY(),J7/DAY(EOMONTH(DATE(VALUE(LEFT(J$1,4)),VALUE(RIGHT(J$1,2)),1),0)),J7/MAX(NOW()-DATE(VALUE(LEFT(J$1,4)),VALUE(RIGHT(J$1,2)),1),1/24))),"") | K8: =IFERROR(IF(DATE(VALUE(LEFT(K$1,4)),VALUE(RIGHT(K$1,2)),1)>TODAY(),"",IF(EOMONTH(DATE(VALUE(LEFT(K$1,4)),VALUE(RIGHT(K$1,2)),1),0)<TODAY(),K7/DAY(EOMONTH(DATE(VALUE(LEFT(K$1,4)),VALUE(RIGHT(K$1,2)),1),0)),K7/MAX(NOW()-DATE(VALUE(LEFT(K$1,4)),VALUE(RIGHT(K$1,2)),1),1/24))),"") | ... O8: =IFERROR(IF(DATE(VALUE(LEFT(O$1,4)),VALUE(RIGHT(O$1,2)),1)>TODAY(),"",IF(EOMONTH(DATE(VALUE(LEFT(O$1,4)),VALUE(RIGHT(O$1,2)),1),0)<TODAY(),O7/DAY(EOMONTH(DATE(VALUE(LEFT(O$1,4)),VALUE(RIGHT(O$1,2)),1),0)),O7/MAX(NOW()-DATE(VALUE(LEFT(O$1,4)),VALUE(RIGHT(O$1,2)),1),1/24))),"") | P8: =SUM(D8:O8)
A9: LTD | D9: =IFERROR(SUMIFS('i-ltd'!$C:$C,'i-ltd'!$A:$A,D$1,'i-ltd'!$B:$B,"product_sales")/AVERAGEIFS('fx-rates'!$C:$C,'fx-rates'!$A:$A,D$1,'fx-rates'!$B:$B,"GBP"),0) | E9: =IFERROR(SUMIFS('i-ltd'!$C:$C,'i-ltd'!$A:$A,E$1,'i-ltd'!$B:$B,"product_sales")/AVERAGEIFS('fx-rates'!$C:$C,'fx-rates'!$A:$A,E$1,'fx-rates'!$B:$B,"GBP"),0) | F9: =IFERROR(SUMIFS('i-ltd'!$C:$C,'i-ltd'!$A:$A,F$1,'i-ltd'!$B:$B,"product_sales")/AVERAGEIFS('fx-rates'!$C:$C,'fx-rates'!$A:$A,F$1,'fx-rates'!$B:$B,"GBP"),0) | G9: =IFERROR(SUMIFS('i-ltd'!$C:$C,'i-ltd'!$A:$A,G$1,'i-ltd'!$B:$B,"product_sales")/AVERAGEIFS('fx-rates'!$C:$C,'fx-rates'!$A:$A,G$1,'fx-rates'!$B:$B,"GBP"),0) | H9: =IFERROR(SUMIFS('i-ltd'!$C:$C,'i-ltd'!$A:$A,H$1,'i-ltd'!$B:$B,"product_sales")/AVERAGEIFS('fx-rates'!$C:$C,'fx-rates'!$A:$A,H$1,'fx-rates'!$B:$B,"GBP"),0) | I9: =IFERROR(SUMIFS('i-ltd'!$C:$C,'i-ltd'!$A:$A,I$1,'i-ltd'!$B:$B,"product_sales")/AVERAGEIFS('fx-rates'!$C:$C,'fx-rates'!$A:$A,I$1,'fx-rates'!$B:$B,"GBP"),0) | J9: =IFERROR(SUMIFS('i-ltd'!$C:$C,'i-ltd'!$A:$A,J$1,'i-ltd'!$B:$B,"product_sales")/AVERAGEIFS('fx-rates'!$C:$C,'fx-rates'!$A:$A,J$1,'fx-rates'!$B:$B,"GBP"),0) | K9: =IFERROR(SUMIFS('i-ltd'!$C:$C,'i-ltd'!$A:$A,K$1,'i-ltd'!$B:$B,"product_sales")/AVERAGEIFS('fx-rates'!$C:$C,'fx-rates'!$A:$A,K$1,'fx-rates'!$B:$B,"GBP"),0) | ... O9: =IFERROR(SUMIFS('i-ltd'!$C:$C,'i-ltd'!$A:$A,O$1,'i-ltd'!$B:$B,"product_sales")/AVERAGEIFS('fx-rates'!$C:$C,'fx-rates'!$A:$A,O$1,'fx-rates'!$B:$B,"GBP"),0) | P9: =SUM(D9:O9)
A10: avg/day | D10: =IFERROR(IF(DATE(VALUE(LEFT(D$1,4)),VALUE(RIGHT(D$1,2)),1)>TODAY(),"",IF(EOMONTH(DATE(VALUE(LEFT(D$1,4)),VALUE(RIGHT(D$1,2)),1),0)<TODAY(),D9/DAY(EOMONTH(DATE(VALUE(LEFT(D$1,4)),VALUE(RIGHT(D$1,2)),1),0)),D9/MAX(NOW()-DATE(VALUE(LEFT(D$1,4)),VALUE(RIGHT(D$1,2)),1),1/24))),"") | E10: =IFERROR(IF(DATE(VALUE(LEFT(E$1,4)),VALUE(RIGHT(E$1,2)),1)>TODAY(),"",IF(EOMONTH(DATE(VALUE(LEFT(E$1,4)),VALUE(RIGHT(E$1,2)),1),0)<TODAY(),E9/DAY(EOMONTH(DATE(VALUE(LEFT(E$1,4)),VALUE(RIGHT(E$1,2)),1),0)),E9/MAX(NOW()-DATE(VALUE(LEFT(E$1,4)),VALUE(RIGHT(E$1,2)),1),1/24))),"") | F10: =IFERROR(IF(DATE(VALUE(LEFT(F$1,4)),VALUE(RIGHT(F$1,2)),1)>TODAY(),"",IF(EOMONTH(DATE(VALUE(LEFT(F$1,4)),VALUE(RIGHT(F$1,2)),1),0)<TODAY(),F9/DAY(EOMONTH(DATE(VALUE(LEFT(F$1,4)),VALUE(RIGHT(F$1,2)),1),0)),F9/MAX(NOW()-DATE(VALUE(LEFT(F$1,4)),VALUE(RIGHT(F$1,2)),1),1/24))),"") | G10: =IFERROR(IF(DATE(VALUE(LEFT(G$1,4)),VALUE(RIGHT(G$1,2)),1)>TODAY(),"",IF(EOMONTH(DATE(VALUE(LEFT(G$1,4)),VALUE(RIGHT(G$1,2)),1),0)<TODAY(),G9/DAY(EOMONTH(DATE(VALUE(LEFT(G$1,4)),VALUE(RIGHT(G$1,2)),1),0)),G9/MAX(NOW()-DATE(VALUE(LEFT(G$1,4)),VALUE(RIGHT(G$1,2)),1),1/24))),"") | H10: =IFERROR(IF(DATE(VALUE(LEFT(H$1,4)),VALUE(RIGHT(H$1,2)),1)>TODAY(),"",IF(EOMONTH(DATE(VALUE(LEFT(H$1,4)),VALUE(RIGHT(H$1,2)),1),0)<TODAY(),H9/DAY(EOMONTH(DATE(VALUE(LEFT(H$1,4)),VALUE(RIGHT(H$1,2)),1),0)),H9/MAX(NOW()-DATE(VALUE(LEFT(H$1,4)),VALUE(RIGHT(H$1,2)),1),1/24))),"") | I10: =IFERROR(IF(DATE(VALUE(LEFT(I$1,4)),VALUE(RIGHT(I$1,2)),1)>TODAY(),"",IF(EOMONTH(DATE(VALUE(LEFT(I$1,4)),VALUE(RIGHT(I$1,2)),1),0)<TODAY(),I9/DAY(EOMONTH(DATE(VALUE(LEFT(I$1,4)),VALUE(RIGHT(I$1,2)),1),0)),I9/MAX(NOW()-DATE(VALUE(LEFT(I$1,4)),VALUE(RIGHT(I$1,2)),1),1/24))),"") | J10: =IFERROR(IF(DATE(VALUE(LEFT(J$1,4)),VALUE(RIGHT(J$1,2)),1)>TODAY(),"",IF(EOMONTH(DATE(VALUE(LEFT(J$1,4)),VALUE(RIGHT(J$1,2)),1),0)<TODAY(),J9/DAY(EOMONTH(DATE(VALUE(LEFT(J$1,4)),VALUE(RIGHT(J$1,2)),1),0)),J9/MAX(NOW()-DATE(VALUE(LEFT(J$1,4)),VALUE(RIGHT(J$1,2)),1),1/24))),"") | K10: =IFERROR(IF(DATE(VALUE(LEFT(K$1,4)),VALUE(RIGHT(K$1,2)),1)>TODAY(),"",IF(EOMONTH(DATE(VALUE(LEFT(K$1,4)),VALUE(RIGHT(K$1,2)),1),0)<TODAY(),K9/DAY(EOMONTH(DATE(VALUE(LEFT(K$1,4)),VALUE(RIGHT(K$1,2)),1),0)),K9/MAX(NOW()-DATE(VALUE(LEFT(K$1,4)),VALUE(RIGHT(K$1,2)),1),1/24))),"") | ... O10: =IFERROR(IF(DATE(VALUE(LEFT(O$1,4)),VALUE(RIGHT(O$1,2)),1)>TODAY(),"",IF(EOMONTH(DATE(VALUE(LEFT(O$1,4)),VALUE(RIGHT(O$1,2)),1),0)<TODAY(),O9/DAY(EOMONTH(DATE(VALUE(LEFT(O$1,4)),VALUE(RIGHT(O$1,2)),1),0)),O9/MAX(NOW()-DATE(VALUE(LEFT(O$1,4)),VALUE(RIGHT(O$1,2)),1),1/24))),"") | P10: =SUM(D10:O10)
A11: INC | D11: =IFERROR(SUMIFS('i-inc'!$C:$C,'i-inc'!$A:$A,D$1,'i-inc'!$B:$B,"product_sales")/AVERAGEIFS('fx-rates'!$C:$C,'fx-rates'!$A:$A,D$1,'fx-rates'!$B:$B,"USD"),0) | E11: =IFERROR(SUMIFS('i-inc'!$C:$C,'i-inc'!$A:$A,E$1,'i-inc'!$B:$B,"product_sales")/AVERAGEIFS('fx-rates'!$C:$C,'fx-rates'!$A:$A,E$1,'fx-rates'!$B:$B,"USD"),0) | F11: =IFERROR(SUMIFS('i-inc'!$C:$C,'i-inc'!$A:$A,F$1,'i-inc'!$B:$B,"product_sales")/AVERAGEIFS('fx-rates'!$C:$C,'fx-rates'!$A:$A,F$1,'fx-rates'!$B:$B,"USD"),0) | G11: =IFERROR(SUMIFS('i-inc'!$C:$C,'i-inc'!$A:$A,G$1,'i-inc'!$B:$B,"product_sales")/AVERAGEIFS('fx-rates'!$C:$C,'fx-rates'!$A:$A,G$1,'fx-rates'!$B:$B,"USD"),0) | H11: =IFERROR(SUMIFS('i-inc'!$C:$C,'i-inc'!$A:$A,H$1,'i-inc'!$B:$B,"product_sales")/AVERAGEIFS('fx-rates'!$C:$C,'fx-rates'!$A:$A,H$1,'fx-rates'!$B:$B,"USD"),0) | I11: =IFERROR(SUMIFS('i-inc'!$C:$C,'i-inc'!$A:$A,I$1,'i-inc'!$B:$B,"product_sales")/AVERAGEIFS('fx-rates'!$C:$C,'fx-rates'!$A:$A,I$1,'fx-rates'!$B:$B,"USD"),0) | J11: =IFERROR(SUMIFS('i-inc'!$C:$C,'i-inc'!$A:$A,J$1,'i-inc'!$B:$B,"product_sales")/AVERAGEIFS('fx-rates'!$C:$C,'fx-rates'!$A:$A,J$1,'fx-rates'!$B:$B,"USD"),0) | K11: =IFERROR(SUMIFS('i-inc'!$C:$C,'i-inc'!$A:$A,K$1,'i-inc'!$B:$B,"product_sales")/AVERAGEIFS('fx-rates'!$C:$C,'fx-rates'!$A:$A,K$1,'fx-rates'!$B:$B,"USD"),0) | ... O11: =IFERROR(SUMIFS('i-inc'!$C:$C,'i-inc'!$A:$A,O$1,'i-inc'!$B:$B,"product_sales")/AVERAGEIFS('fx-rates'!$C:$C,'fx-rates'!$A:$A,O$1,'fx-rates'!$B:$B,"USD"),0) | P11: =SUM(D11:O11)
A12: avg/day | D12: =IFERROR(IF(DATE(VALUE(LEFT(D$1,4)),VALUE(RIGHT(D$1,2)),1)>TODAY(),"",IF(EOMONTH(DATE(VALUE(LEFT(D$1,4)),VALUE(RIGHT(D$1,2)),1),0)<TODAY(),D11/DAY(EOMONTH(DATE(VALUE(LEFT(D$1,4)),VALUE(RIGHT(D$1,2)),1),0)),D11/MAX(NOW()-DATE(VALUE(LEFT(D$1,4)),VALUE(RIGHT(D$1,2)),1),1/24))),"") | E12: =IFERROR(IF(DATE(VALUE(LEFT(E$1,4)),VALUE(RIGHT(E$1,2)),1)>TODAY(),"",IF(EOMONTH(DATE(VALUE(LEFT(E$1,4)),VALUE(RIGHT(E$1,2)),1),0)<TODAY(),E11/DAY(EOMONTH(DATE(VALUE(LEFT(E$1,4)),VALUE(RIGHT(E$1,2)),1),0)),E11/MAX(NOW()-DATE(VALUE(LEFT(E$1,4)),VALUE(RIGHT(E$1,2)),1),1/24))),"") | F12: =IFERROR(IF(DATE(VALUE(LEFT(F$1,4)),VALUE(RIGHT(F$1,2)),1)>TODAY(),"",IF(EOMONTH(DATE(VALUE(LEFT(F$1,4)),VALUE(RIGHT(F$1,2)),1),0)<TODAY(),F11/DAY(EOMONTH(DATE(VALUE(LEFT(F$1,4)),VALUE(RIGHT(F$1,2)),1),0)),F11/MAX(NOW()-DATE(VALUE(LEFT(F$1,4)),VALUE(RIGHT(F$1,2)),1),1/24))),"") | G12: =IFERROR(IF(DATE(VALUE(LEFT(G$1,4)),VALUE(RIGHT(G$1,2)),1)>TODAY(),"",IF(EOMONTH(DATE(VALUE(LEFT(G$1,4)),VALUE(RIGHT(G$1,2)),1),0)<TODAY(),G11/DAY(EOMONTH(DATE(VALUE(LEFT(G$1,4)),VALUE(RIGHT(G$1,2)),1),0)),G11/MAX(NOW()-DATE(VALUE(LEFT(G$1,4)),VALUE(RIGHT(G$1,2)),1),1/24))),"") | H12: =IFERROR(IF(DATE(VALUE(LEFT(H$1,4)),VALUE(RIGHT(H$1,2)),1)>TODAY(),"",IF(EOMONTH(DATE(VALUE(LEFT(H$1,4)),VALUE(RIGHT(H$1,2)),1),0)<TODAY(),H11/DAY(EOMONTH(DATE(VALUE(LEFT(H$1,4)),VALUE(RIGHT(H$1,2)),1),0)),H11/MAX(NOW()-DATE(VALUE(LEFT(H$1,4)),VALUE(RIGHT(H$1,2)),1),1/24))),"") | I12: =IFERROR(IF(DATE(VALUE(LEFT(I$1,4)),VALUE(RIGHT(I$1,2)),1)>TODAY(),"",IF(EOMONTH(DATE(VALUE(LEFT(I$1,4)),VALUE(RIGHT(I$1,2)),1),0)<TODAY(),I11/DAY(EOMONTH(DATE(VALUE(LEFT(I$1,4)),VALUE(RIGHT(I$1,2)),1),0)),I11/MAX(NOW()-DATE(VALUE(LEFT(I$1,4)),VALUE(RIGHT(I$1,2)),1),1/24))),"") | J12: =IFERROR(IF(DATE(VALUE(LEFT(J$1,4)),VALUE(RIGHT(J$1,2)),1)>TODAY(),"",IF(EOMONTH(DATE(VALUE(LEFT(J$1,4)),VALUE(RIGHT(J$1,2)),1),0)<TODAY(),J11/DAY(EOMONTH(DATE(VALUE(LEFT(J$1,4)),VALUE(RIGHT(J$1,2)),1),0)),J11/MAX(NOW()-DATE(VALUE(LEFT(J$1,4)),VALUE(RIGHT(J$1,2)),1),1/24))),"") | K12: =IFERROR(IF(DATE(VALUE(LEFT(K$1,4)),VALUE(RIGHT(K$1,2)),1)>TODAY(),"",IF(EOMONTH(DATE(VALUE(LEFT(K$1,4)),VALUE(RIGHT(K$1,2)),1),0)<TODAY(),K11/DAY(EOMONTH(DATE(VALUE(LEFT(K$1,4)),VALUE(RIGHT(K$1,2)),1),0)),K11/MAX(NOW()-DATE(VALUE(LEFT(K$1,4)),VALUE(RIGHT(K$1,2)),1),1/24))),"") | ... O12: =IFERROR(IF(DATE(VALUE(LEFT(O$1,4)),VALUE(RIGHT(O$1,2)),1)>TODAY(),"",IF(EOMONTH(DATE(VALUE(LEFT(O$1,4)),VALUE(RIGHT(O$1,2)),1),0)<TODAY(),O11/DAY(EOMONTH(DATE(VALUE(LEFT(O$1,4)),VALUE(RIGHT(O$1,2)),1),0)),O11/MAX(NOW()-DATE(VALUE(LEFT(O$1,4)),VALUE(RIGHT(O$1,2)),1),1/24))),"") | P12: =SUM(D12:O12)
A13: Shopify daily average | P13: =SUM(D13:O13)
A14: Marketplaces | D14: =SUMIFS('i-sl'!$C:$C,'i-sl'!$A:$A,D$1,'i-sl'!$B:$B,"marketplaces") | E14: =SUMIFS('i-sl'!$C:$C,'i-sl'!$A:$A,E$1,'i-sl'!$B:$B,"marketplaces") | F14: =SUMIFS('i-sl'!$C:$C,'i-sl'!$A:$A,F$1,'i-sl'!$B:$B,"marketplaces") | G14: =SUMIFS('i-sl'!$C:$C,'i-sl'!$A:$A,G$1,'i-sl'!$B:$B,"marketplaces") | H14: =SUMIFS('i-sl'!$C:$C,'i-sl'!$A:$A,H$1,'i-sl'!$B:$B,"marketplaces") | I14: =SUMIFS('i-sl'!$C:$C,'i-sl'!$A:$A,I$1,'i-sl'!$B:$B,"marketplaces") | J14: =SUMIFS('i-sl'!$C:$C,'i-sl'!$A:$A,J$1,'i-sl'!$B:$B,"marketplaces") | K14: =SUMIFS('i-sl'!$C:$C,'i-sl'!$A:$A,K$1,'i-sl'!$B:$B,"marketplaces") | ... O14: =SUMIFS('i-sl'!$C:$C,'i-sl'!$A:$A,O$1,'i-sl'!$B:$B,"marketplaces") | P14: =SUM(D14:O14)
A15: Rappels | D15: =SUMIFS('i-sl'!$C:$C,'i-sl'!$A:$A,D$1,'i-sl'!$B:$B,"rappels") | E15: =SUMIFS('i-sl'!$C:$C,'i-sl'!$A:$A,E$1,'i-sl'!$B:$B,"rappels") | F15: =SUMIFS('i-sl'!$C:$C,'i-sl'!$A:$A,F$1,'i-sl'!$B:$B,"rappels") | G15: =SUMIFS('i-sl'!$C:$C,'i-sl'!$A:$A,G$1,'i-sl'!$B:$B,"rappels") | H15: =SUMIFS('i-sl'!$C:$C,'i-sl'!$A:$A,H$1,'i-sl'!$B:$B,"rappels") | I15: =SUMIFS('i-sl'!$C:$C,'i-sl'!$A:$A,I$1,'i-sl'!$B:$B,"rappels") | J15: =SUMIFS('i-sl'!$C:$C,'i-sl'!$A:$A,J$1,'i-sl'!$B:$B,"rappels") | K15: =SUMIFS('i-sl'!$C:$C,'i-sl'!$A:$A,K$1,'i-sl'!$B:$B,"rappels") | ... O15: =SUMIFS('i-sl'!$C:$C,'i-sl'!$A:$A,O$1,'i-sl'!$B:$B,"rappels") | P15: =SUM(D15:O15)
A16: Supplies | D16: =SUMIFS('i-sl'!$C:$C,'i-sl'!$A:$A,D$1,'i-sl'!$B:$B,"supplies") | E16: =SUMIFS('i-sl'!$C:$C,'i-sl'!$A:$A,E$1,'i-sl'!$B:$B,"supplies") | F16: =SUMIFS('i-sl'!$C:$C,'i-sl'!$A:$A,F$1,'i-sl'!$B:$B,"supplies") | G16: =SUMIFS('i-sl'!$C:$C,'i-sl'!$A:$A,G$1,'i-sl'!$B:$B,"supplies") | H16: =SUMIFS('i-sl'!$C:$C,'i-sl'!$A:$A,H$1,'i-sl'!$B:$B,"supplies") | I16: =SUMIFS('i-sl'!$C:$C,'i-sl'!$A:$A,I$1,'i-sl'!$B:$B,"supplies") | J16: =SUMIFS('i-sl'!$C:$C,'i-sl'!$A:$A,J$1,'i-sl'!$B:$B,"supplies") | K16: =SUMIFS('i-sl'!$C:$C,'i-sl'!$A:$A,K$1,'i-sl'!$B:$B,"supplies") | ... O16: =SUMIFS('i-sl'!$C:$C,'i-sl'!$A:$A,O$1,'i-sl'!$B:$B,"supplies") | P16: =SUM(D16:O16)
A17: Services | D17: =SUMIFS('i-sl'!$C:$C,'i-sl'!$A:$A,D$1,'i-sl'!$B:$B,"services_ext") | E17: =SUMIFS('i-sl'!$C:$C,'i-sl'!$A:$A,E$1,'i-sl'!$B:$B,"services_ext") | F17: =SUMIFS('i-sl'!$C:$C,'i-sl'!$A:$A,F$1,'i-sl'!$B:$B,"services_ext") | G17: =SUMIFS('i-sl'!$C:$C,'i-sl'!$A:$A,G$1,'i-sl'!$B:$B,"services_ext") | H17: =SUMIFS('i-sl'!$C:$C,'i-sl'!$A:$A,H$1,'i-sl'!$B:$B,"services_ext") | I17: =SUMIFS('i-sl'!$C:$C,'i-sl'!$A:$A,I$1,'i-sl'!$B:$B,"services_ext") | J17: =SUMIFS('i-sl'!$C:$C,'i-sl'!$A:$A,J$1,'i-sl'!$B:$B,"services_ext") | K17: =SUMIFS('i-sl'!$C:$C,'i-sl'!$A:$A,K$1,'i-sl'!$B:$B,"services_ext") | ... O17: =SUMIFS('i-sl'!$C:$C,'i-sl'!$A:$A,O$1,'i-sl'!$B:$B,"services_ext") | P17: =SUM(D17:O17)
A18: Uncategorized income | D18: =SUMIFS('i-sl'!$C:$C,'i-sl'!$A:$A,D$1,'i-sl'!$B:$B,"otros_ingresos")+IFERROR(SUMIFS('i-ltd'!$C:$C,'i-ltd'!$A:$A,D$1,'i-ltd'!$B:$B,"otros_ingresos")/AVERAGEIFS('fx-rates'!$C:$C,'fx-rates'!$A:$A,D$1,'fx-rates'!$B:$B,"GBP"),0)+IFERROR(SUMIFS('i-inc'!$C:$C,'i-inc'!$A:$A,D$1,'i-inc'!$B:$B,"otros_ingresos")/AVERAGEIFS('fx-rates'!$C:$C,'fx-rates'!$A:$A,D$1,'fx-rates'!$B:$B,"USD"),0) | E18: =SUMIFS('i-sl'!$C:$C,'i-sl'!$A:$A,E$1,'i-sl'!$B:$B,"otros_ingresos")+IFERROR(SUMIFS('i-ltd'!$C:$C,'i-ltd'!$A:$A,E$1,'i-ltd'!$B:$B,"otros_ingresos")/AVERAGEIFS('fx-rates'!$C:$C,'fx-rates'!$A:$A,E$1,'fx-rates'!$B:$B,"GBP"),0)+IFERROR(SUMIFS('i-inc'!$C:$C,'i-inc'!$A:$A,E$1,'i-inc'!$B:$B,"otros_ingresos")/AVERAGEIFS('fx-rates'!$C:$C,'fx-rates'!$A:$A,E$1,'fx-rates'!$B:$B,"USD"),0) | F18: =SUMIFS('i-sl'!$C:$C,'i-sl'!$A:$A,F$1,'i-sl'!$B:$B,"otros_ingresos")+IFERROR(SUMIFS('i-ltd'!$C:$C,'i-ltd'!$A:$A,F$1,'i-ltd'!$B:$B,"otros_ingresos")/AVERAGEIFS('fx-rates'!$C:$C,'fx-rates'!$A:$A,F$1,'fx-rates'!$B:$B,"GBP"),0)+IFERROR(SUMIFS('i-inc'!$C:$C,'i-inc'!$A:$A,F$1,'i-inc'!$B:$B,"otros_ingresos")/AVERAGEIFS('fx-rates'!$C:$C,'fx-rates'!$A:$A,F$1,'fx-rates'!$B:$B,"USD"),0) | G18: =SUMIFS('i-sl'!$C:$C,'i-sl'!$A:$A,G$1,'i-sl'!$B:$B,"otros_ingresos")+IFERROR(SUMIFS('i-ltd'!$C:$C,'i-ltd'!$A:$A,G$1,'i-ltd'!$B:$B,"otros_ingresos")/AVERAGEIFS('fx-rates'!$C:$C,'fx-rates'!$A:$A,G$1,'fx-rates'!$B:$B,"GBP"),0)+IFERROR(SUMIFS('i-inc'!$C:$C,'i-inc'!$A:$A,G$1,'i-inc'!$B:$B,"otros_ingresos")/AVERAGEIFS('fx-rates'!$C:$C,'fx-rates'!$A:$A,G$1,'fx-rates'!$B:$B,"USD"),0) | H18: =SUMIFS('i-sl'!$C:$C,'i-sl'!$A:$A,H$1,'i-sl'!$B:$B,"otros_ingresos")+IFERROR(SUMIFS('i-ltd'!$C:$C,'i-ltd'!$A:$A,H$1,'i-ltd'!$B:$B,"otros_ingresos")/AVERAGEIFS('fx-rates'!$C:$C,'fx-rates'!$A:$A,H$1,'fx-rates'!$B:$B,"GBP"),0)+IFERROR(SUMIFS('i-inc'!$C:$C,'i-inc'!$A:$A,H$1,'i-inc'!$B:$B,"otros_ingresos")/AVERAGEIFS('fx-rates'!$C:$C,'fx-rates'!$A:$A,H$1,'fx-rates'!$B:$B,"USD"),0) | I18: =SUMIFS('i-sl'!$C:$C,'i-sl'!$A:$A,I$1,'i-sl'!$B:$B,"otros_ingresos")+IFERROR(SUMIFS('i-ltd'!$C:$C,'i-ltd'!$A:$A,I$1,'i-ltd'!$B:$B,"otros_ingresos")/AVERAGEIFS('fx-rates'!$C:$C,'fx-rates'!$A:$A,I$1,'fx-rates'!$B:$B,"GBP"),0)+IFERROR(SUMIFS('i-inc'!$C:$C,'i-inc'!$A:$A,I$1,'i-inc'!$B:$B,"otros_ingresos")/AVERAGEIFS('fx-rates'!$C:$C,'fx-rates'!$A:$A,I$1,'fx-rates'!$B:$B,"USD"),0) | J18: =SUMIFS('i-sl'!$C:$C,'i-sl'!$A:$A,J$1,'i-sl'!$B:$B,"otros_ingresos")+IFERROR(SUMIFS('i-ltd'!$C:$C,'i-ltd'!$A:$A,J$1,'i-ltd'!$B:$B,"otros_ingresos")/AVERAGEIFS('fx-rates'!$C:$C,'fx-rates'!$A:$A,J$1,'fx-rates'!$B:$B,"GBP"),0)+IFERROR(SUMIFS('i-inc'!$C:$C,'i-inc'!$A:$A,J$1,'i-inc'!$B:$B,"otros_ingresos")/AVERAGEIFS('fx-rates'!$C:$C,'fx-rates'!$A:$A,J$1,'fx-rates'!$B:$B,"USD"),0) | K18: =SUMIFS('i-sl'!$C:$C,'i-sl'!$A:$A,K$1,'i-sl'!$B:$B,"otros_ingresos")+IFERROR(SUMIFS('i-ltd'!$C:$C,'i-ltd'!$A:$A,K$1,'i-ltd'!$B:$B,"otros_ingresos")/AVERAGEIFS('fx-rates'!$C:$C,'fx-rates'!$A:$A,K$1,'fx-rates'!$B:$B,"GBP"),0)+IFERROR(SUMIFS('i-inc'!$C:$C,'i-inc'!$A:$A,K$1,'i-inc'!$B:$B,"otros_ingresos")/AVERAGEIFS('fx-rates'!$C:$C,'fx-rates'!$A:$A,K$1,'fx-rates'!$B:$B,"USD"),0) | ... O18: =SUMIFS('i-sl'!$C:$C,'i-sl'!$A:$A,O$1,'i-sl'!$B:$B,"otros_ingresos")+IFERROR(SUMIFS('i-ltd'!$C:$C,'i-ltd'!$A:$A,O$1,'i-ltd'!$B:$B,"otros_ingresos")/AVERAGEIFS('fx-rates'!$C:$C,'fx-rates'!$A:$A,O$1,'fx-rates'!$B:$B,"GBP"),0)+IFERROR(SUMIFS('i-inc'!$C:$C,'i-inc'!$A:$A,O$1,'i-inc'!$B:$B,"otros_ingresos")/AVERAGEIFS('fx-rates'!$C:$C,'fx-rates'!$A:$A,O$1,'fx-rates'!$B:$B,"USD"),0) | P18: =SUM(D18:O18)
A19: EXPENSES | D19: =D20+D29 | E19: =E20+E29 | F19: =F20+F29 | G19: =G20+G29 | H19: =H20+H29 | I19: =I20+I29 | J19: =J20+J29 | K19: =K20+K29 | ... O19: =O20+O29 | P19: =SUM(D19:O19)
A20: COGS | D20: =D21+D22+D23+D24 | E20: =E21+E22+E23+E24 | F20: =F21+F22+F23+F24 | G20: =G21+G22+G23+G24 | H20: =H21+H22+H23+H24 | I20: =I21+I22+I23+I24 | J20: =J21+J22+J23+J24 | K20: =K21+K22+K23+K24 | ... O20: =O21+O22+O23+O24 | P20: =SUM(D20:O20)
A21: Manufacturing | D21: =SUMIFS('i-sl'!$C:$C,'i-sl'!$A:$A,D$1,'i-sl'!$B:$B,"manufacturing")+IFERROR(SUMIFS('i-ltd'!$C:$C,'i-ltd'!$A:$A,D$1,'i-ltd'!$B:$B,"manufacturing")/AVERAGEIFS('fx-rates'!$C:$C,'fx-rates'!$A:$A,D$1,'fx-rates'!$B:$B,"GBP"),0)+IFERROR(SUMIFS('i-inc'!$C:$C,'i-inc'!$A:$A,D$1,'i-inc'!$B:$B,"manufacturing")/AVERAGEIFS('fx-rates'!$C:$C,'fx-rates'!$A:$A,D$1,'fx-rates'!$B:$B,"USD"),0) | E21: =SUMIFS('i-sl'!$C:$C,'i-sl'!$A:$A,E$1,'i-sl'!$B:$B,"manufacturing")+IFERROR(SUMIFS('i-ltd'!$C:$C,'i-ltd'!$A:$A,E$1,'i-ltd'!$B:$B,"manufacturing")/AVERAGEIFS('fx-rates'!$C:$C,'fx-rates'!$A:$A,E$1,'fx-rates'!$B:$B,"GBP"),0)+IFERROR(SUMIFS('i-inc'!$C:$C,'i-inc'!$A:$A,E$1,'i-inc'!$B:$B,"manufacturing")/AVERAGEIFS('fx-rates'!$C:$C,'fx-rates'!$A:$A,E$1,'fx-rates'!$B:$B,"USD"),0) | F21: =SUMIFS('i-sl'!$C:$C,'i-sl'!$A:$A,F$1,'i-sl'!$B:$B,"manufacturing")+IFERROR(SUMIFS('i-ltd'!$C:$C,'i-ltd'!$A:$A,F$1,'i-ltd'!$B:$B,"manufacturing")/AVERAGEIFS('fx-rates'!$C:$C,'fx-rates'!$A:$A,F$1,'fx-rates'!$B:$B,"GBP"),0)+IFERROR(SUMIFS('i-inc'!$C:$C,'i-inc'!$A:$A,F$1,'i-inc'!$B:$B,"manufacturing")/AVERAGEIFS('fx-rates'!$C:$C,'fx-rates'!$A:$A,F$1,'fx-rates'!$B:$B,"USD"),0) | G21: =SUMIFS('i-sl'!$C:$C,'i-sl'!$A:$A,G$1,'i-sl'!$B:$B,"manufacturing")+IFERROR(SUMIFS('i-ltd'!$C:$C,'i-ltd'!$A:$A,G$1,'i-ltd'!$B:$B,"manufacturing")/AVERAGEIFS('fx-rates'!$C:$C,'fx-rates'!$A:$A,G$1,'fx-rates'!$B:$B,"GBP"),0)+IFERROR(SUMIFS('i-inc'!$C:$C,'i-inc'!$A:$A,G$1,'i-inc'!$B:$B,"manufacturing")/AVERAGEIFS('fx-rates'!$C:$C,'fx-rates'!$A:$A,G$1,'fx-rates'!$B:$B,"USD"),0) | H21: =SUMIFS('i-sl'!$C:$C,'i-sl'!$A:$A,H$1,'i-sl'!$B:$B,"manufacturing")+IFERROR(SUMIFS('i-ltd'!$C:$C,'i-ltd'!$A:$A,H$1,'i-ltd'!$B:$B,"manufacturing")/AVERAGEIFS('fx-rates'!$C:$C,'fx-rates'!$A:$A,H$1,'fx-rates'!$B:$B,"GBP"),0)+IFERROR(SUMIFS('i-inc'!$C:$C,'i-inc'!$A:$A,H$1,'i-inc'!$B:$B,"manufacturing")/AVERAGEIFS('fx-rates'!$C:$C,'fx-rates'!$A:$A,H$1,'fx-rates'!$B:$B,"USD"),0) | I21: =SUMIFS('i-sl'!$C:$C,'i-sl'!$A:$A,I$1,'i-sl'!$B:$B,"manufacturing")+IFERROR(SUMIFS('i-ltd'!$C:$C,'i-ltd'!$A:$A,I$1,'i-ltd'!$B:$B,"manufacturing")/AVERAGEIFS('fx-rates'!$C:$C,'fx-rates'!$A:$A,I$1,'fx-rates'!$B:$B,"GBP"),0)+IFERROR(SUMIFS('i-inc'!$C:$C,'i-inc'!$A:$A,I$1,'i-inc'!$B:$B,"manufacturing")/AVERAGEIFS('fx-rates'!$C:$C,'fx-rates'!$A:$A,I$1,'fx-rates'!$B:$B,"USD"),0) | J21: =SUMIFS('i-sl'!$C:$C,'i-sl'!$A:$A,J$1,'i-sl'!$B:$B,"manufacturing")+IFERROR(SUMIFS('i-ltd'!$C:$C,'i-ltd'!$A:$A,J$1,'i-ltd'!$B:$B,"manufacturing")/AVERAGEIFS('fx-rates'!$C:$C,'fx-rates'!$A:$A,J$1,'fx-rates'!$B:$B,"GBP"),0)+IFERROR(SUMIFS('i-inc'!$C:$C,'i-inc'!$A:$A,J$1,'i-inc'!$B:$B,"manufacturing")/AVERAGEIFS('fx-rates'!$C:$C,'fx-rates'!$A:$A,J$1,'fx-rates'!$B:$B,"USD"),0) | K21: =SUMIFS('i-sl'!$C:$C,'i-sl'!$A:$A,K$1,'i-sl'!$B:$B,"manufacturing")+IFERROR(SUMIFS('i-ltd'!$C:$C,'i-ltd'!$A:$A,K$1,'i-ltd'!$B:$B,"manufacturing")/AVERAGEIFS('fx-rates'!$C:$C,'fx-rates'!$A:$A,K$1,'fx-rates'!$B:$B,"GBP"),0)+IFERROR(SUMIFS('i-inc'!$C:$C,'i-inc'!$A:$A,K$1,'i-inc'!$B:$B,"manufacturing")/AVERAGEIFS('fx-rates'!$C:$C,'fx-rates'!$A:$A,K$1,'fx-rates'!$B:$B,"USD"),0) | ... O21: =SUMIFS('i-sl'!$C:$C,'i-sl'!$A:$A,O$1,'i-sl'!$B:$B,"manufacturing")+IFERROR(SUMIFS('i-ltd'!$C:$C,'i-ltd'!$A:$A,O$1,'i-ltd'!$B:$B,"manufacturing")/AVERAGEIFS('fx-rates'!$C:$C,'fx-rates'!$A:$A,O$1,'fx-rates'!$B:$B,"GBP"),0)+IFERROR(SUMIFS('i-inc'!$C:$C,'i-inc'!$A:$A,O$1,'i-inc'!$B:$B,"manufacturing")/AVERAGEIFS('fx-rates'!$C:$C,'fx-rates'!$A:$A,O$1,'fx-rates'!$B:$B,"USD"),0) | P21: =SUM(D21:O21)
A22: Logistics | D22: =SUMIFS('i-sl'!$C:$C,'i-sl'!$A:$A,D$1,'i-sl'!$B:$B,"logistics")+IFERROR(SUMIFS('i-ltd'!$C:$C,'i-ltd'!$A:$A,D$1,'i-ltd'!$B:$B,"logistics")/AVERAGEIFS('fx-rates'!$C:$C,'fx-rates'!$A:$A,D$1,'fx-rates'!$B:$B,"GBP"),0)+IFERROR(SUMIFS('i-inc'!$C:$C,'i-inc'!$A:$A,D$1,'i-inc'!$B:$B,"logistics")/AVERAGEIFS('fx-rates'!$C:$C,'fx-rates'!$A:$A,D$1,'fx-rates'!$B:$B,"USD"),0) | E22: =SUMIFS('i-sl'!$C:$C,'i-sl'!$A:$A,E$1,'i-sl'!$B:$B,"logistics")+IFERROR(SUMIFS('i-ltd'!$C:$C,'i-ltd'!$A:$A,E$1,'i-ltd'!$B:$B,"logistics")/AVERAGEIFS('fx-rates'!$C:$C,'fx-rates'!$A:$A,E$1,'fx-rates'!$B:$B,"GBP"),0)+IFERROR(SUMIFS('i-inc'!$C:$C,'i-inc'!$A:$A,E$1,'i-inc'!$B:$B,"logistics")/AVERAGEIFS('fx-rates'!$C:$C,'fx-rates'!$A:$A,E$1,'fx-rates'!$B:$B,"USD"),0) | F22: =SUMIFS('i-sl'!$C:$C,'i-sl'!$A:$A,F$1,'i-sl'!$B:$B,"logistics")+IFERROR(SUMIFS('i-ltd'!$C:$C,'i-ltd'!$A:$A,F$1,'i-ltd'!$B:$B,"logistics")/AVERAGEIFS('fx-rates'!$C:$C,'fx-rates'!$A:$A,F$1,'fx-rates'!$B:$B,"GBP"),0)+IFERROR(SUMIFS('i-inc'!$C:$C,'i-inc'!$A:$A,F$1,'i-inc'!$B:$B,"logistics")/AVERAGEIFS('fx-rates'!$C:$C,'fx-rates'!$A:$A,F$1,'fx-rates'!$B:$B,"USD"),0) | G22: =SUMIFS('i-sl'!$C:$C,'i-sl'!$A:$A,G$1,'i-sl'!$B:$B,"logistics")+IFERROR(SUMIFS('i-ltd'!$C:$C,'i-ltd'!$A:$A,G$1,'i-ltd'!$B:$B,"logistics")/AVERAGEIFS('fx-rates'!$C:$C,'fx-rates'!$A:$A,G$1,'fx-rates'!$B:$B,"GBP"),0)+IFERROR(SUMIFS('i-inc'!$C:$C,'i-inc'!$A:$A,G$1,'i-inc'!$B:$B,"logistics")/AVERAGEIFS('fx-rates'!$C:$C,'fx-rates'!$A:$A,G$1,'fx-rates'!$B:$B,"USD"),0) | H22: =SUMIFS('i-sl'!$C:$C,'i-sl'!$A:$A,H$1,'i-sl'!$B:$B,"logistics")+IFERROR(SUMIFS('i-ltd'!$C:$C,'i-ltd'!$A:$A,H$1,'i-ltd'!$B:$B,"logistics")/AVERAGEIFS('fx-rates'!$C:$C,'fx-rates'!$A:$A,H$1,'fx-rates'!$B:$B,"GBP"),0)+IFERROR(SUMIFS('i-inc'!$C:$C,'i-inc'!$A:$A,H$1,'i-inc'!$B:$B,"logistics")/AVERAGEIFS('fx-rates'!$C:$C,'fx-rates'!$A:$A,H$1,'fx-rates'!$B:$B,"USD"),0) | I22: =SUMIFS('i-sl'!$C:$C,'i-sl'!$A:$A,I$1,'i-sl'!$B:$B,"logistics")+IFERROR(SUMIFS('i-ltd'!$C:$C,'i-ltd'!$A:$A,I$1,'i-ltd'!$B:$B,"logistics")/AVERAGEIFS('fx-rates'!$C:$C,'fx-rates'!$A:$A,I$1,'fx-rates'!$B:$B,"GBP"),0)+IFERROR(SUMIFS('i-inc'!$C:$C,'i-inc'!$A:$A,I$1,'i-inc'!$B:$B,"logistics")/AVERAGEIFS('fx-rates'!$C:$C,'fx-rates'!$A:$A,I$1,'fx-rates'!$B:$B,"USD"),0) | J22: =SUMIFS('i-sl'!$C:$C,'i-sl'!$A:$A,J$1,'i-sl'!$B:$B,"logistics")+IFERROR(SUMIFS('i-ltd'!$C:$C,'i-ltd'!$A:$A,J$1,'i-ltd'!$B:$B,"logistics")/AVERAGEIFS('fx-rates'!$C:$C,'fx-rates'!$A:$A,J$1,'fx-rates'!$B:$B,"GBP"),0)+IFERROR(SUMIFS('i-inc'!$C:$C,'i-inc'!$A:$A,J$1,'i-inc'!$B:$B,"logistics")/AVERAGEIFS('fx-rates'!$C:$C,'fx-rates'!$A:$A,J$1,'fx-rates'!$B:$B,"USD"),0) | K22: =SUMIFS('i-sl'!$C:$C,'i-sl'!$A:$A,K$1,'i-sl'!$B:$B,"logistics")+IFERROR(SUMIFS('i-ltd'!$C:$C,'i-ltd'!$A:$A,K$1,'i-ltd'!$B:$B,"logistics")/AVERAGEIFS('fx-rates'!$C:$C,'fx-rates'!$A:$A,K$1,'fx-rates'!$B:$B,"GBP"),0)+IFERROR(SUMIFS('i-inc'!$C:$C,'i-inc'!$A:$A,K$1,'i-inc'!$B:$B,"logistics")/AVERAGEIFS('fx-rates'!$C:$C,'fx-rates'!$A:$A,K$1,'fx-rates'!$B:$B,"USD"),0) | ... O22: =SUMIFS('i-sl'!$C:$C,'i-sl'!$A:$A,O$1,'i-sl'!$B:$B,"logistics")+IFERROR(SUMIFS('i-ltd'!$C:$C,'i-ltd'!$A:$A,O$1,'i-ltd'!$B:$B,"logistics")/AVERAGEIFS('fx-rates'!$C:$C,'fx-rates'!$A:$A,O$1,'fx-rates'!$B:$B,"GBP"),0)+IFERROR(SUMIFS('i-inc'!$C:$C,'i-inc'!$A:$A,O$1,'i-inc'!$B:$B,"logistics")/AVERAGEIFS('fx-rates'!$C:$C,'fx-rates'!$A:$A,O$1,'fx-rates'!$B:$B,"USD"),0) | P22: =SUM(D22:O22)
A23: Royalties | D23: =SUMIFS('i-sl'!$C:$C,'i-sl'!$A:$A,D$1,'i-sl'!$B:$B,"royalties") | E23: =SUMIFS('i-sl'!$C:$C,'i-sl'!$A:$A,E$1,'i-sl'!$B:$B,"royalties") | F23: =SUMIFS('i-sl'!$C:$C,'i-sl'!$A:$A,F$1,'i-sl'!$B:$B,"royalties") | G23: =SUMIFS('i-sl'!$C:$C,'i-sl'!$A:$A,G$1,'i-sl'!$B:$B,"royalties") | H23: =SUMIFS('i-sl'!$C:$C,'i-sl'!$A:$A,H$1,'i-sl'!$B:$B,"royalties") | I23: =SUMIFS('i-sl'!$C:$C,'i-sl'!$A:$A,I$1,'i-sl'!$B:$B,"royalties") | J23: =SUMIFS('i-sl'!$C:$C,'i-sl'!$A:$A,J$1,'i-sl'!$B:$B,"royalties") | K23: =SUMIFS('i-sl'!$C:$C,'i-sl'!$A:$A,K$1,'i-sl'!$B:$B,"royalties") | ... O23: =SUMIFS('i-sl'!$C:$C,'i-sl'!$A:$A,O$1,'i-sl'!$B:$B,"royalties") | P23: =SUM(D23:O23)
A24: Payment fees | D24: =SUMIFS('i-sl'!$C:$C,'i-sl'!$A:$A,D$1,'i-sl'!$B:$B,"payment_fees")+IFERROR(SUMIFS('i-ltd'!$C:$C,'i-ltd'!$A:$A,D$1,'i-ltd'!$B:$B,"payment_fees")/AVERAGEIFS('fx-rates'!$C:$C,'fx-rates'!$A:$A,D$1,'fx-rates'!$B:$B,"GBP"),0)+IFERROR(SUMIFS('i-inc'!$C:$C,'i-inc'!$A:$A,D$1,'i-inc'!$B:$B,"payment_fees")/AVERAGEIFS('fx-rates'!$C:$C,'fx-rates'!$A:$A,D$1,'fx-rates'!$B:$B,"USD"),0) | E24: =SUMIFS('i-sl'!$C:$C,'i-sl'!$A:$A,E$1,'i-sl'!$B:$B,"payment_fees")+IFERROR(SUMIFS('i-ltd'!$C:$C,'i-ltd'!$A:$A,E$1,'i-ltd'!$B:$B,"payment_fees")/AVERAGEIFS('fx-rates'!$C:$C,'fx-rates'!$A:$A,E$1,'fx-rates'!$B:$B,"GBP"),0)+IFERROR(SUMIFS('i-inc'!$C:$C,'i-inc'!$A:$A,E$1,'i-inc'!$B:$B,"payment_fees")/AVERAGEIFS('fx-rates'!$C:$C,'fx-rates'!$A:$A,E$1,'fx-rates'!$B:$B,"USD"),0) | F24: =SUMIFS('i-sl'!$C:$C,'i-sl'!$A:$A,F$1,'i-sl'!$B:$B,"payment_fees")+IFERROR(SUMIFS('i-ltd'!$C:$C,'i-ltd'!$A:$A,F$1,'i-ltd'!$B:$B,"payment_fees")/AVERAGEIFS('fx-rates'!$C:$C,'fx-rates'!$A:$A,F$1,'fx-rates'!$B:$B,"GBP"),0)+IFERROR(SUMIFS('i-inc'!$C:$C,'i-inc'!$A:$A,F$1,'i-inc'!$B:$B,"payment_fees")/AVERAGEIFS('fx-rates'!$C:$C,'fx-rates'!$A:$A,F$1,'fx-rates'!$B:$B,"USD"),0) | G24: =SUMIFS('i-sl'!$C:$C,'i-sl'!$A:$A,G$1,'i-sl'!$B:$B,"payment_fees")+IFERROR(SUMIFS('i-ltd'!$C:$C,'i-ltd'!$A:$A,G$1,'i-ltd'!$B:$B,"payment_fees")/AVERAGEIFS('fx-rates'!$C:$C,'fx-rates'!$A:$A,G$1,'fx-rates'!$B:$B,"GBP"),0)+IFERROR(SUMIFS('i-inc'!$C:$C,'i-inc'!$A:$A,G$1,'i-inc'!$B:$B,"payment_fees")/AVERAGEIFS('fx-rates'!$C:$C,'fx-rates'!$A:$A,G$1,'fx-rates'!$B:$B,"USD"),0) | H24: =SUMIFS('i-sl'!$C:$C,'i-sl'!$A:$A,H$1,'i-sl'!$B:$B,"payment_fees")+IFERROR(SUMIFS('i-ltd'!$C:$C,'i-ltd'!$A:$A,H$1,'i-ltd'!$B:$B,"payment_fees")/AVERAGEIFS('fx-rates'!$C:$C,'fx-rates'!$A:$A,H$1,'fx-rates'!$B:$B,"GBP"),0)+IFERROR(SUMIFS('i-inc'!$C:$C,'i-inc'!$A:$A,H$1,'i-inc'!$B:$B,"payment_fees")/AVERAGEIFS('fx-rates'!$C:$C,'fx-rates'!$A:$A,H$1,'fx-rates'!$B:$B,"USD"),0) | I24: =SUMIFS('i-sl'!$C:$C,'i-sl'!$A:$A,I$1,'i-sl'!$B:$B,"payment_fees")+IFERROR(SUMIFS('i-ltd'!$C:$C,'i-ltd'!$A:$A,I$1,'i-ltd'!$B:$B,"payment_fees")/AVERAGEIFS('fx-rates'!$C:$C,'fx-rates'!$A:$A,I$1,'fx-rates'!$B:$B,"GBP"),0)+IFERROR(SUMIFS('i-inc'!$C:$C,'i-inc'!$A:$A,I$1,'i-inc'!$B:$B,"payment_fees")/AVERAGEIFS('fx-rates'!$C:$C,'fx-rates'!$A:$A,I$1,'fx-rates'!$B:$B,"USD"),0) | J24: =SUMIFS('i-sl'!$C:$C,'i-sl'!$A:$A,J$1,'i-sl'!$B:$B,"payment_fees")+IFERROR(SUMIFS('i-ltd'!$C:$C,'i-ltd'!$A:$A,J$1,'i-ltd'!$B:$B,"payment_fees")/AVERAGEIFS('fx-rates'!$C:$C,'fx-rates'!$A:$A,J$1,'fx-rates'!$B:$B,"GBP"),0)+IFERROR(SUMIFS('i-inc'!$C:$C,'i-inc'!$A:$A,J$1,'i-inc'!$B:$B,"payment_fees")/AVERAGEIFS('fx-rates'!$C:$C,'fx-rates'!$A:$A,J$1,'fx-rates'!$B:$B,"USD"),0) | K24: =SUMIFS('i-sl'!$C:$C,'i-sl'!$A:$A,K$1,'i-sl'!$B:$B,"payment_fees")+IFERROR(SUMIFS('i-ltd'!$C:$C,'i-ltd'!$A:$A,K$1,'i-ltd'!$B:$B,"payment_fees")/AVERAGEIFS('fx-rates'!$C:$C,'fx-rates'!$A:$A,K$1,'fx-rates'!$B:$B,"GBP"),0)+IFERROR(SUMIFS('i-inc'!$C:$C,'i-inc'!$A:$A,K$1,'i-inc'!$B:$B,"payment_fees")/AVERAGEIFS('fx-rates'!$C:$C,'fx-rates'!$A:$A,K$1,'fx-rates'!$B:$B,"USD"),0) | ... O24: =SUMIFS('i-sl'!$C:$C,'i-sl'!$A:$A,O$1,'i-sl'!$B:$B,"payment_fees")+IFERROR(SUMIFS('i-ltd'!$C:$C,'i-ltd'!$A:$A,O$1,'i-ltd'!$B:$B,"payment_fees")/AVERAGEIFS('fx-rates'!$C:$C,'fx-rates'!$A:$A,O$1,'fx-rates'!$B:$B,"GBP"),0)+IFERROR(SUMIFS('i-inc'!$C:$C,'i-inc'!$A:$A,O$1,'i-inc'!$B:$B,"payment_fees")/AVERAGEIFS('fx-rates'!$C:$C,'fx-rates'!$A:$A,O$1,'fx-rates'!$B:$B,"USD"),0) | P24: =SUM(D24:O24)
A25: GROSS MARGIN (SALES-MANUFACTURING) | D25: =D5-D21 | E25: =E5-E21 | F25: =F5-F21 | G25: =G5-G21 | H25: =H5-H21 | I25: =I5-I21 | J25: =J5-J21 | K25: =K5-K21 | ... O25: =O5-O21 | P25: =SUM(D25:O25)
A26: % gross margin | D26: =IFERROR(D25/D5,0) | E26: =IFERROR(E25/E5,0) | F26: =IFERROR(F25/F5,0) | G26: =IFERROR(G25/G5,0) | H26: =IFERROR(H25/H5,0) | I26: =IFERROR(I25/I5,0) | J26: =IFERROR(J25/J5,0) | K26: =IFERROR(K25/K5,0) | ... P26: =IFERROR(P25/P5,0)
A27: Contributive margin (product sales-COGS) | D27: =D5-D20 | E27: =E5-E20 | F27: =F5-F20 | G27: =G5-G20 | H27: =H5-H20 | I27: =I5-I20 | J27: =J5-J20 | K27: =K5-K20 | ... O27: =O5-O20 | P27: =SUM(D27:O27)
A28: % contributive margin | D28: =IFERROR(D27/D5,0) | E28: =IFERROR(E27/E5,0) | F28: =IFERROR(F27/F5,0) | G28: =IFERROR(G27/G5,0) | H28: =IFERROR(H27/H5,0) | I28: =IFERROR(I27/I5,0) | J28: =IFERROR(J27/J5,0) | K28: =IFERROR(K27/K5,0) | ... P28: =IFERROR(P27/P5,0)
A29: OPEX | D29: =D30+D31+D32+D33+D34 | E29: =E30+E31+E32+E33+E34 | F29: =F30+F31+F32+F33+F34 | G29: =G30+G31+G32+G33+G34 | H29: =H30+H31+H32+H33+H34 | I29: =I30+I31+I32+I33+I34 | J29: =J30+J31+J32+J33+J34 | K29: =K30+K31+K32+K33+K34 | ... O29: =O30+O31+O32+O33+O34 | P29: =SUM(D29:O29)
A30: Marketing | D30: =SUMIFS('i-sl'!$C:$C,'i-sl'!$A:$A,D$1,'i-sl'!$B:$B,"marketing") | E30: =SUMIFS('i-sl'!$C:$C,'i-sl'!$A:$A,E$1,'i-sl'!$B:$B,"marketing") | F30: =SUMIFS('i-sl'!$C:$C,'i-sl'!$A:$A,F$1,'i-sl'!$B:$B,"marketing") | G30: =SUMIFS('i-sl'!$C:$C,'i-sl'!$A:$A,G$1,'i-sl'!$B:$B,"marketing") | H30: =SUMIFS('i-sl'!$C:$C,'i-sl'!$A:$A,H$1,'i-sl'!$B:$B,"marketing") | I30: =SUMIFS('i-sl'!$C:$C,'i-sl'!$A:$A,I$1,'i-sl'!$B:$B,"marketing") | J30: =SUMIFS('i-sl'!$C:$C,'i-sl'!$A:$A,J$1,'i-sl'!$B:$B,"marketing") | K30: =SUMIFS('i-sl'!$C:$C,'i-sl'!$A:$A,K$1,'i-sl'!$B:$B,"marketing") | ... O30: =SUMIFS('i-sl'!$C:$C,'i-sl'!$A:$A,O$1,'i-sl'!$B:$B,"marketing") | P30: =SUM(D30:O30)
A31: Staff | D31: =SUMIFS('i-sl'!$C:$C,'i-sl'!$A:$A,D$1,'i-sl'!$B:$B,"staff") | E31: =SUMIFS('i-sl'!$C:$C,'i-sl'!$A:$A,E$1,'i-sl'!$B:$B,"staff") | F31: =SUMIFS('i-sl'!$C:$C,'i-sl'!$A:$A,F$1,'i-sl'!$B:$B,"staff") | G31: =SUMIFS('i-sl'!$C:$C,'i-sl'!$A:$A,G$1,'i-sl'!$B:$B,"staff") | H31: =SUMIFS('i-sl'!$C:$C,'i-sl'!$A:$A,H$1,'i-sl'!$B:$B,"staff") | I31: =SUMIFS('i-sl'!$C:$C,'i-sl'!$A:$A,I$1,'i-sl'!$B:$B,"staff") | J31: =SUMIFS('i-sl'!$C:$C,'i-sl'!$A:$A,J$1,'i-sl'!$B:$B,"staff") | K31: =SUMIFS('i-sl'!$C:$C,'i-sl'!$A:$A,K$1,'i-sl'!$B:$B,"staff") | ... O31: =SUMIFS('i-sl'!$C:$C,'i-sl'!$A:$A,O$1,'i-sl'!$B:$B,"staff") | P31: =SUM(D31:O31)
A32: Administration | D32: =SUMIFS('i-sl'!$C:$C,'i-sl'!$A:$A,D$1,'i-sl'!$B:$B,"administration")+IFERROR(SUMIFS('i-ltd'!$C:$C,'i-ltd'!$A:$A,D$1,'i-ltd'!$B:$B,"administration")/AVERAGEIFS('fx-rates'!$C:$C,'fx-rates'!$A:$A,D$1,'fx-rates'!$B:$B,"GBP"),0)+IFERROR(SUMIFS('i-inc'!$C:$C,'i-inc'!$A:$A,D$1,'i-inc'!$B:$B,"administration")/AVERAGEIFS('fx-rates'!$C:$C,'fx-rates'!$A:$A,D$1,'fx-rates'!$B:$B,"USD"),0) | E32: =SUMIFS('i-sl'!$C:$C,'i-sl'!$A:$A,E$1,'i-sl'!$B:$B,"administration")+IFERROR(SUMIFS('i-ltd'!$C:$C,'i-ltd'!$A:$A,E$1,'i-ltd'!$B:$B,"administration")/AVERAGEIFS('fx-rates'!$C:$C,'fx-rates'!$A:$A,E$1,'fx-rates'!$B:$B,"GBP"),0)+IFERROR(SUMIFS('i-inc'!$C:$C,'i-inc'!$A:$A,E$1,'i-inc'!$B:$B,"administration")/AVERAGEIFS('fx-rates'!$C:$C,'fx-rates'!$A:$A,E$1,'fx-rates'!$B:$B,"USD"),0) | F32: =SUMIFS('i-sl'!$C:$C,'i-sl'!$A:$A,F$1,'i-sl'!$B:$B,"administration")+IFERROR(SUMIFS('i-ltd'!$C:$C,'i-ltd'!$A:$A,F$1,'i-ltd'!$B:$B,"administration")/AVERAGEIFS('fx-rates'!$C:$C,'fx-rates'!$A:$A,F$1,'fx-rates'!$B:$B,"GBP"),0)+IFERROR(SUMIFS('i-inc'!$C:$C,'i-inc'!$A:$A,F$1,'i-inc'!$B:$B,"administration")/AVERAGEIFS('fx-rates'!$C:$C,'fx-rates'!$A:$A,F$1,'fx-rates'!$B:$B,"USD"),0) | G32: =SUMIFS('i-sl'!$C:$C,'i-sl'!$A:$A,G$1,'i-sl'!$B:$B,"administration")+IFERROR(SUMIFS('i-ltd'!$C:$C,'i-ltd'!$A:$A,G$1,'i-ltd'!$B:$B,"administration")/AVERAGEIFS('fx-rates'!$C:$C,'fx-rates'!$A:$A,G$1,'fx-rates'!$B:$B,"GBP"),0)+IFERROR(SUMIFS('i-inc'!$C:$C,'i-inc'!$A:$A,G$1,'i-inc'!$B:$B,"administration")/AVERAGEIFS('fx-rates'!$C:$C,'fx-rates'!$A:$A,G$1,'fx-rates'!$B:$B,"USD"),0) | H32: =SUMIFS('i-sl'!$C:$C,'i-sl'!$A:$A,H$1,'i-sl'!$B:$B,"administration")+IFERROR(SUMIFS('i-ltd'!$C:$C,'i-ltd'!$A:$A,H$1,'i-ltd'!$B:$B,"administration")/AVERAGEIFS('fx-rates'!$C:$C,'fx-rates'!$A:$A,H$1,'fx-rates'!$B:$B,"GBP"),0)+IFERROR(SUMIFS('i-inc'!$C:$C,'i-inc'!$A:$A,H$1,'i-inc'!$B:$B,"administration")/AVERAGEIFS('fx-rates'!$C:$C,'fx-rates'!$A:$A,H$1,'fx-rates'!$B:$B,"USD"),0) | I32: =SUMIFS('i-sl'!$C:$C,'i-sl'!$A:$A,I$1,'i-sl'!$B:$B,"administration")+IFERROR(SUMIFS('i-ltd'!$C:$C,'i-ltd'!$A:$A,I$1,'i-ltd'!$B:$B,"administration")/AVERAGEIFS('fx-rates'!$C:$C,'fx-rates'!$A:$A,I$1,'fx-rates'!$B:$B,"GBP"),0)+IFERROR(SUMIFS('i-inc'!$C:$C,'i-inc'!$A:$A,I$1,'i-inc'!$B:$B,"administration")/AVERAGEIFS('fx-rates'!$C:$C,'fx-rates'!$A:$A,I$1,'fx-rates'!$B:$B,"USD"),0) | J32: =SUMIFS('i-sl'!$C:$C,'i-sl'!$A:$A,J$1,'i-sl'!$B:$B,"administration")+IFERROR(SUMIFS('i-ltd'!$C:$C,'i-ltd'!$A:$A,J$1,'i-ltd'!$B:$B,"administration")/AVERAGEIFS('fx-rates'!$C:$C,'fx-rates'!$A:$A,J$1,'fx-rates'!$B:$B,"GBP"),0)+IFERROR(SUMIFS('i-inc'!$C:$C,'i-inc'!$A:$A,J$1,'i-inc'!$B:$B,"administration")/AVERAGEIFS('fx-rates'!$C:$C,'fx-rates'!$A:$A,J$1,'fx-rates'!$B:$B,"USD"),0) | K32: =SUMIFS('i-sl'!$C:$C,'i-sl'!$A:$A,K$1,'i-sl'!$B:$B,"administration")+IFERROR(SUMIFS('i-ltd'!$C:$C,'i-ltd'!$A:$A,K$1,'i-ltd'!$B:$B,"administration")/AVERAGEIFS('fx-rates'!$C:$C,'fx-rates'!$A:$A,K$1,'fx-rates'!$B:$B,"GBP"),0)+IFERROR(SUMIFS('i-inc'!$C:$C,'i-inc'!$A:$A,K$1,'i-inc'!$B:$B,"administration")/AVERAGEIFS('fx-rates'!$C:$C,'fx-rates'!$A:$A,K$1,'fx-rates'!$B:$B,"USD"),0) | ... O32: =SUMIFS('i-sl'!$C:$C,'i-sl'!$A:$A,O$1,'i-sl'!$B:$B,"administration")+IFERROR(SUMIFS('i-ltd'!$C:$C,'i-ltd'!$A:$A,O$1,'i-ltd'!$B:$B,"administration")/AVERAGEIFS('fx-rates'!$C:$C,'fx-rates'!$A:$A,O$1,'fx-rates'!$B:$B,"GBP"),0)+IFERROR(SUMIFS('i-inc'!$C:$C,'i-inc'!$A:$A,O$1,'i-inc'!$B:$B,"administration")/AVERAGEIFS('fx-rates'!$C:$C,'fx-rates'!$A:$A,O$1,'fx-rates'!$B:$B,"USD"),0) | P32: =SUM(D32:O32)
A33: Technology | D33: =SUMIFS('i-sl'!$C:$C,'i-sl'!$A:$A,D$1,'i-sl'!$B:$B,"technology")+IFERROR(SUMIFS('i-ltd'!$C:$C,'i-ltd'!$A:$A,D$1,'i-ltd'!$B:$B,"technology")/AVERAGEIFS('fx-rates'!$C:$C,'fx-rates'!$A:$A,D$1,'fx-rates'!$B:$B,"GBP"),0)+IFERROR(SUMIFS('i-inc'!$C:$C,'i-inc'!$A:$A,D$1,'i-inc'!$B:$B,"technology")/AVERAGEIFS('fx-rates'!$C:$C,'fx-rates'!$A:$A,D$1,'fx-rates'!$B:$B,"USD"),0) | E33: =SUMIFS('i-sl'!$C:$C,'i-sl'!$A:$A,E$1,'i-sl'!$B:$B,"technology")+IFERROR(SUMIFS('i-ltd'!$C:$C,'i-ltd'!$A:$A,E$1,'i-ltd'!$B:$B,"technology")/AVERAGEIFS('fx-rates'!$C:$C,'fx-rates'!$A:$A,E$1,'fx-rates'!$B:$B,"GBP"),0)+IFERROR(SUMIFS('i-inc'!$C:$C,'i-inc'!$A:$A,E$1,'i-inc'!$B:$B,"technology")/AVERAGEIFS('fx-rates'!$C:$C,'fx-rates'!$A:$A,E$1,'fx-rates'!$B:$B,"USD"),0) | F33: =SUMIFS('i-sl'!$C:$C,'i-sl'!$A:$A,F$1,'i-sl'!$B:$B,"technology")+IFERROR(SUMIFS('i-ltd'!$C:$C,'i-ltd'!$A:$A,F$1,'i-ltd'!$B:$B,"technology")/AVERAGEIFS('fx-rates'!$C:$C,'fx-rates'!$A:$A,F$1,'fx-rates'!$B:$B,"GBP"),0)+IFERROR(SUMIFS('i-inc'!$C:$C,'i-inc'!$A:$A,F$1,'i-inc'!$B:$B,"technology")/AVERAGEIFS('fx-rates'!$C:$C,'fx-rates'!$A:$A,F$1,'fx-rates'!$B:$B,"USD"),0) | G33: =SUMIFS('i-sl'!$C:$C,'i-sl'!$A:$A,G$1,'i-sl'!$B:$B,"technology")+IFERROR(SUMIFS('i-ltd'!$C:$C,'i-ltd'!$A:$A,G$1,'i-ltd'!$B:$B,"technology")/AVERAGEIFS('fx-rates'!$C:$C,'fx-rates'!$A:$A,G$1,'fx-rates'!$B:$B,"GBP"),0)+IFERROR(SUMIFS('i-inc'!$C:$C,'i-inc'!$A:$A,G$1,'i-inc'!$B:$B,"technology")/AVERAGEIFS('fx-rates'!$C:$C,'fx-rates'!$A:$A,G$1,'fx-rates'!$B:$B,"USD"),0) | H33: =SUMIFS('i-sl'!$C:$C,'i-sl'!$A:$A,H$1,'i-sl'!$B:$B,"technology")+IFERROR(SUMIFS('i-ltd'!$C:$C,'i-ltd'!$A:$A,H$1,'i-ltd'!$B:$B,"technology")/AVERAGEIFS('fx-rates'!$C:$C,'fx-rates'!$A:$A,H$1,'fx-rates'!$B:$B,"GBP"),0)+IFERROR(SUMIFS('i-inc'!$C:$C,'i-inc'!$A:$A,H$1,'i-inc'!$B:$B,"technology")/AVERAGEIFS('fx-rates'!$C:$C,'fx-rates'!$A:$A,H$1,'fx-rates'!$B:$B,"USD"),0) | I33: =SUMIFS('i-sl'!$C:$C,'i-sl'!$A:$A,I$1,'i-sl'!$B:$B,"technology")+IFERROR(SUMIFS('i-ltd'!$C:$C,'i-ltd'!$A:$A,I$1,'i-ltd'!$B:$B,"technology")/AVERAGEIFS('fx-rates'!$C:$C,'fx-rates'!$A:$A,I$1,'fx-rates'!$B:$B,"GBP"),0)+IFERROR(SUMIFS('i-inc'!$C:$C,'i-inc'!$A:$A,I$1,'i-inc'!$B:$B,"technology")/AVERAGEIFS('fx-rates'!$C:$C,'fx-rates'!$A:$A,I$1,'fx-rates'!$B:$B,"USD"),0) | J33: =SUMIFS('i-sl'!$C:$C,'i-sl'!$A:$A,J$1,'i-sl'!$B:$B,"technology")+IFERROR(SUMIFS('i-ltd'!$C:$C,'i-ltd'!$A:$A,J$1,'i-ltd'!$B:$B,"technology")/AVERAGEIFS('fx-rates'!$C:$C,'fx-rates'!$A:$A,J$1,'fx-rates'!$B:$B,"GBP"),0)+IFERROR(SUMIFS('i-inc'!$C:$C,'i-inc'!$A:$A,J$1,'i-inc'!$B:$B,"technology")/AVERAGEIFS('fx-rates'!$C:$C,'fx-rates'!$A:$A,J$1,'fx-rates'!$B:$B,"USD"),0) | K33: =SUMIFS('i-sl'!$C:$C,'i-sl'!$A:$A,K$1,'i-sl'!$B:$B,"technology")+IFERROR(SUMIFS('i-ltd'!$C:$C,'i-ltd'!$A:$A,K$1,'i-ltd'!$B:$B,"technology")/AVERAGEIFS('fx-rates'!$C:$C,'fx-rates'!$A:$A,K$1,'fx-rates'!$B:$B,"GBP"),0)+IFERROR(SUMIFS('i-inc'!$C:$C,'i-inc'!$A:$A,K$1,'i-inc'!$B:$B,"technology")/AVERAGEIFS('fx-rates'!$C:$C,'fx-rates'!$A:$A,K$1,'fx-rates'!$B:$B,"USD"),0) | ... O33: =SUMIFS('i-sl'!$C:$C,'i-sl'!$A:$A,O$1,'i-sl'!$B:$B,"technology")+IFERROR(SUMIFS('i-ltd'!$C:$C,'i-ltd'!$A:$A,O$1,'i-ltd'!$B:$B,"technology")/AVERAGEIFS('fx-rates'!$C:$C,'fx-rates'!$A:$A,O$1,'fx-rates'!$B:$B,"GBP"),0)+IFERROR(SUMIFS('i-inc'!$C:$C,'i-inc'!$A:$A,O$1,'i-inc'!$B:$B,"technology")/AVERAGEIFS('fx-rates'!$C:$C,'fx-rates'!$A:$A,O$1,'fx-rates'!$B:$B,"USD"),0) | P33: =SUM(D33:O33)
A34: Uncategorized Expenses | D34: =SUMIFS('i-sl'!$C:$C,'i-sl'!$A:$A,D$1,'i-sl'!$B:$B,"otros_gastos")+IFERROR(SUMIFS('i-ltd'!$C:$C,'i-ltd'!$A:$A,D$1,'i-ltd'!$B:$B,"otros_gastos")/AVERAGEIFS('fx-rates'!$C:$C,'fx-rates'!$A:$A,D$1,'fx-rates'!$B:$B,"GBP"),0)+IFERROR(SUMIFS('i-inc'!$C:$C,'i-inc'!$A:$A,D$1,'i-inc'!$B:$B,"otros_gastos")/AVERAGEIFS('fx-rates'!$C:$C,'fx-rates'!$A:$A,D$1,'fx-rates'!$B:$B,"USD"),0) | E34: =SUMIFS('i-sl'!$C:$C,'i-sl'!$A:$A,E$1,'i-sl'!$B:$B,"otros_gastos")+IFERROR(SUMIFS('i-ltd'!$C:$C,'i-ltd'!$A:$A,E$1,'i-ltd'!$B:$B,"otros_gastos")/AVERAGEIFS('fx-rates'!$C:$C,'fx-rates'!$A:$A,E$1,'fx-rates'!$B:$B,"GBP"),0)+IFERROR(SUMIFS('i-inc'!$C:$C,'i-inc'!$A:$A,E$1,'i-inc'!$B:$B,"otros_gastos")/AVERAGEIFS('fx-rates'!$C:$C,'fx-rates'!$A:$A,E$1,'fx-rates'!$B:$B,"USD"),0) | F34: =SUMIFS('i-sl'!$C:$C,'i-sl'!$A:$A,F$1,'i-sl'!$B:$B,"otros_gastos")+IFERROR(SUMIFS('i-ltd'!$C:$C,'i-ltd'!$A:$A,F$1,'i-ltd'!$B:$B,"otros_gastos")/AVERAGEIFS('fx-rates'!$C:$C,'fx-rates'!$A:$A,F$1,'fx-rates'!$B:$B,"GBP"),0)+IFERROR(SUMIFS('i-inc'!$C:$C,'i-inc'!$A:$A,F$1,'i-inc'!$B:$B,"otros_gastos")/AVERAGEIFS('fx-rates'!$C:$C,'fx-rates'!$A:$A,F$1,'fx-rates'!$B:$B,"USD"),0) | G34: =SUMIFS('i-sl'!$C:$C,'i-sl'!$A:$A,G$1,'i-sl'!$B:$B,"otros_gastos")+IFERROR(SUMIFS('i-ltd'!$C:$C,'i-ltd'!$A:$A,G$1,'i-ltd'!$B:$B,"otros_gastos")/AVERAGEIFS('fx-rates'!$C:$C,'fx-rates'!$A:$A,G$1,'fx-rates'!$B:$B,"GBP"),0)+IFERROR(SUMIFS('i-inc'!$C:$C,'i-inc'!$A:$A,G$1,'i-inc'!$B:$B,"otros_gastos")/AVERAGEIFS('fx-rates'!$C:$C,'fx-rates'!$A:$A,G$1,'fx-rates'!$B:$B,"USD"),0) | H34: =SUMIFS('i-sl'!$C:$C,'i-sl'!$A:$A,H$1,'i-sl'!$B:$B,"otros_gastos")+IFERROR(SUMIFS('i-ltd'!$C:$C,'i-ltd'!$A:$A,H$1,'i-ltd'!$B:$B,"otros_gastos")/AVERAGEIFS('fx-rates'!$C:$C,'fx-rates'!$A:$A,H$1,'fx-rates'!$B:$B,"GBP"),0)+IFERROR(SUMIFS('i-inc'!$C:$C,'i-inc'!$A:$A,H$1,'i-inc'!$B:$B,"otros_gastos")/AVERAGEIFS('fx-rates'!$C:$C,'fx-rates'!$A:$A,H$1,'fx-rates'!$B:$B,"USD"),0) | I34: =SUMIFS('i-sl'!$C:$C,'i-sl'!$A:$A,I$1,'i-sl'!$B:$B,"otros_gastos")+IFERROR(SUMIFS('i-ltd'!$C:$C,'i-ltd'!$A:$A,I$1,'i-ltd'!$B:$B,"otros_gastos")/AVERAGEIFS('fx-rates'!$C:$C,'fx-rates'!$A:$A,I$1,'fx-rates'!$B:$B,"GBP"),0)+IFERROR(SUMIFS('i-inc'!$C:$C,'i-inc'!$A:$A,I$1,'i-inc'!$B:$B,"otros_gastos")/AVERAGEIFS('fx-rates'!$C:$C,'fx-rates'!$A:$A,I$1,'fx-rates'!$B:$B,"USD"),0) | J34: =SUMIFS('i-sl'!$C:$C,'i-sl'!$A:$A,J$1,'i-sl'!$B:$B,"otros_gastos")+IFERROR(SUMIFS('i-ltd'!$C:$C,'i-ltd'!$A:$A,J$1,'i-ltd'!$B:$B,"otros_gastos")/AVERAGEIFS('fx-rates'!$C:$C,'fx-rates'!$A:$A,J$1,'fx-rates'!$B:$B,"GBP"),0)+IFERROR(SUMIFS('i-inc'!$C:$C,'i-inc'!$A:$A,J$1,'i-inc'!$B:$B,"otros_gastos")/AVERAGEIFS('fx-rates'!$C:$C,'fx-rates'!$A:$A,J$1,'fx-rates'!$B:$B,"USD"),0) | K34: =SUMIFS('i-sl'!$C:$C,'i-sl'!$A:$A,K$1,'i-sl'!$B:$B,"otros_gastos")+IFERROR(SUMIFS('i-ltd'!$C:$C,'i-ltd'!$A:$A,K$1,'i-ltd'!$B:$B,"otros_gastos")/AVERAGEIFS('fx-rates'!$C:$C,'fx-rates'!$A:$A,K$1,'fx-rates'!$B:$B,"GBP"),0)+IFERROR(SUMIFS('i-inc'!$C:$C,'i-inc'!$A:$A,K$1,'i-inc'!$B:$B,"otros_gastos")/AVERAGEIFS('fx-rates'!$C:$C,'fx-rates'!$A:$A,K$1,'fx-rates'!$B:$B,"USD"),0) | ... O34: =SUMIFS('i-sl'!$C:$C,'i-sl'!$A:$A,O$1,'i-sl'!$B:$B,"otros_gastos")+IFERROR(SUMIFS('i-ltd'!$C:$C,'i-ltd'!$A:$A,O$1,'i-ltd'!$B:$B,"otros_gastos")/AVERAGEIFS('fx-rates'!$C:$C,'fx-rates'!$A:$A,O$1,'fx-rates'!$B:$B,"GBP"),0)+IFERROR(SUMIFS('i-inc'!$C:$C,'i-inc'!$A:$A,O$1,'i-inc'!$B:$B,"otros_gastos")/AVERAGEIFS('fx-rates'!$C:$C,'fx-rates'!$A:$A,O$1,'fx-rates'!$B:$B,"USD"),0) | P34: =SUM(D34:O34)
A35: Currency Adjustment | D35: =SUMIFS('i-sl'!$C:$C,'i-sl'!$A:$A,D$1,'i-sl'!$B:$B,"diferencias_divisas")+IFERROR(SUMIFS('i-ltd'!$C:$C,'i-ltd'!$A:$A,D$1,'i-ltd'!$B:$B,"diferencias_divisas")/AVERAGEIFS('fx-rates'!$C:$C,'fx-rates'!$A:$A,D$1,'fx-rates'!$B:$B,"GBP"),0)+IFERROR(SUMIFS('i-inc'!$C:$C,'i-inc'!$A:$A,D$1,'i-inc'!$B:$B,"diferencias_divisas")/AVERAGEIFS('fx-rates'!$C:$C,'fx-rates'!$A:$A,D$1,'fx-rates'!$B:$B,"USD"),0) | E35: =SUMIFS('i-sl'!$C:$C,'i-sl'!$A:$A,E$1,'i-sl'!$B:$B,"diferencias_divisas")+IFERROR(SUMIFS('i-ltd'!$C:$C,'i-ltd'!$A:$A,E$1,'i-ltd'!$B:$B,"diferencias_divisas")/AVERAGEIFS('fx-rates'!$C:$C,'fx-rates'!$A:$A,E$1,'fx-rates'!$B:$B,"GBP"),0)+IFERROR(SUMIFS('i-inc'!$C:$C,'i-inc'!$A:$A,E$1,'i-inc'!$B:$B,"diferencias_divisas")/AVERAGEIFS('fx-rates'!$C:$C,'fx-rates'!$A:$A,E$1,'fx-rates'!$B:$B,"USD"),0) | F35: =SUMIFS('i-sl'!$C:$C,'i-sl'!$A:$A,F$1,'i-sl'!$B:$B,"diferencias_divisas")+IFERROR(SUMIFS('i-ltd'!$C:$C,'i-ltd'!$A:$A,F$1,'i-ltd'!$B:$B,"diferencias_divisas")/AVERAGEIFS('fx-rates'!$C:$C,'fx-rates'!$A:$A,F$1,'fx-rates'!$B:$B,"GBP"),0)+IFERROR(SUMIFS('i-inc'!$C:$C,'i-inc'!$A:$A,F$1,'i-inc'!$B:$B,"diferencias_divisas")/AVERAGEIFS('fx-rates'!$C:$C,'fx-rates'!$A:$A,F$1,'fx-rates'!$B:$B,"USD"),0) | G35: =SUMIFS('i-sl'!$C:$C,'i-sl'!$A:$A,G$1,'i-sl'!$B:$B,"diferencias_divisas")+IFERROR(SUMIFS('i-ltd'!$C:$C,'i-ltd'!$A:$A,G$1,'i-ltd'!$B:$B,"diferencias_divisas")/AVERAGEIFS('fx-rates'!$C:$C,'fx-rates'!$A:$A,G$1,'fx-rates'!$B:$B,"GBP"),0)+IFERROR(SUMIFS('i-inc'!$C:$C,'i-inc'!$A:$A,G$1,'i-inc'!$B:$B,"diferencias_divisas")/AVERAGEIFS('fx-rates'!$C:$C,'fx-rates'!$A:$A,G$1,'fx-rates'!$B:$B,"USD"),0) | H35: =SUMIFS('i-sl'!$C:$C,'i-sl'!$A:$A,H$1,'i-sl'!$B:$B,"diferencias_divisas")+IFERROR(SUMIFS('i-ltd'!$C:$C,'i-ltd'!$A:$A,H$1,'i-ltd'!$B:$B,"diferencias_divisas")/AVERAGEIFS('fx-rates'!$C:$C,'fx-rates'!$A:$A,H$1,'fx-rates'!$B:$B,"GBP"),0)+IFERROR(SUMIFS('i-inc'!$C:$C,'i-inc'!$A:$A,H$1,'i-inc'!$B:$B,"diferencias_divisas")/AVERAGEIFS('fx-rates'!$C:$C,'fx-rates'!$A:$A,H$1,'fx-rates'!$B:$B,"USD"),0) | I35: =SUMIFS('i-sl'!$C:$C,'i-sl'!$A:$A,I$1,'i-sl'!$B:$B,"diferencias_divisas")+IFERROR(SUMIFS('i-ltd'!$C:$C,'i-ltd'!$A:$A,I$1,'i-ltd'!$B:$B,"diferencias_divisas")/AVERAGEIFS('fx-rates'!$C:$C,'fx-rates'!$A:$A,I$1,'fx-rates'!$B:$B,"GBP"),0)+IFERROR(SUMIFS('i-inc'!$C:$C,'i-inc'!$A:$A,I$1,'i-inc'!$B:$B,"diferencias_divisas")/AVERAGEIFS('fx-rates'!$C:$C,'fx-rates'!$A:$A,I$1,'fx-rates'!$B:$B,"USD"),0) | J35: =SUMIFS('i-sl'!$C:$C,'i-sl'!$A:$A,J$1,'i-sl'!$B:$B,"diferencias_divisas")+IFERROR(SUMIFS('i-ltd'!$C:$C,'i-ltd'!$A:$A,J$1,'i-ltd'!$B:$B,"diferencias_divisas")/AVERAGEIFS('fx-rates'!$C:$C,'fx-rates'!$A:$A,J$1,'fx-rates'!$B:$B,"GBP"),0)+IFERROR(SUMIFS('i-inc'!$C:$C,'i-inc'!$A:$A,J$1,'i-inc'!$B:$B,"diferencias_divisas")/AVERAGEIFS('fx-rates'!$C:$C,'fx-rates'!$A:$A,J$1,'fx-rates'!$B:$B,"USD"),0) | K35: =SUMIFS('i-sl'!$C:$C,'i-sl'!$A:$A,K$1,'i-sl'!$B:$B,"diferencias_divisas")+IFERROR(SUMIFS('i-ltd'!$C:$C,'i-ltd'!$A:$A,K$1,'i-ltd'!$B:$B,"diferencias_divisas")/AVERAGEIFS('fx-rates'!$C:$C,'fx-rates'!$A:$A,K$1,'fx-rates'!$B:$B,"GBP"),0)+IFERROR(SUMIFS('i-inc'!$C:$C,'i-inc'!$A:$A,K$1,'i-inc'!$B:$B,"diferencias_divisas")/AVERAGEIFS('fx-rates'!$C:$C,'fx-rates'!$A:$A,K$1,'fx-rates'!$B:$B,"USD"),0) | ... O35: =SUMIFS('i-sl'!$C:$C,'i-sl'!$A:$A,O$1,'i-sl'!$B:$B,"diferencias_divisas")+IFERROR(SUMIFS('i-ltd'!$C:$C,'i-ltd'!$A:$A,O$1,'i-ltd'!$B:$B,"diferencias_divisas")/AVERAGEIFS('fx-rates'!$C:$C,'fx-rates'!$A:$A,O$1,'fx-rates'!$B:$B,"GBP"),0)+IFERROR(SUMIFS('i-inc'!$C:$C,'i-inc'!$A:$A,O$1,'i-inc'!$B:$B,"diferencias_divisas")/AVERAGEIFS('fx-rates'!$C:$C,'fx-rates'!$A:$A,O$1,'fx-rates'!$B:$B,"USD"),0) | P35: =SUM(D35:O35)
A36: PROFIT | D36: =D4-D20-D29-D35 | E36: =E4-E20-E29-E35 | F36: =F4-F20-F29-F35 | G36: =G4-G20-G29-G35 | H36: =H4-H20-H29-H35 | I36: =I4-I20-I29-I35 | J36: =J4-J20-J29-J35 | K36: =K4-K20-K29-K35 | ... O36: =O4-O20-O29-O35 | P36: =SUM(D36:O36)
A37: % profit / product sales | D37: =IFERROR(D36/D5,0) | E37: =IFERROR(E36/E5,0) | F37: =IFERROR(F36/F5,0) | G37: =IFERROR(G36/G5,0) | H37: =IFERROR(H36/H5,0) | I37: =IFERROR(I36/I5,0) | J37: =IFERROR(J36/J5,0) | K37: =IFERROR(K36/K5,0) | ... P37: =IFERROR(P36/P5,0)

Sheet i-sl
A1: yyyymm | B1: line_key | C1: amount_eur
A2: 202601 | B2: administration | C2: 2673
A3: 202601 | B3: diferencias_divisas | C3: -132.9
A4: 202601 | B4: logistics | C4: 17203.81
A5: 202601 | B5: manufacturing | C5: 56636.72
A6: 202601 | B6: marketing | C6: 54648.52
A7: 202601 | B7: marketplaces | C7: 1419.7
A8: 202601 | B8: otros_gastos | C8: 411.87
A9: 202601 | B9: otros_ingresos | C9: 3586.77
A10: 202601 | B10: payment_fees | C10: 4006.6
A11: 202601 | B11: rappels | C11: -1118.95
A12: 202601 | B12: royalties | C12: 13737
A13: 202601 | B13: services_ext | C13: 1191.18
... A208: 202609 | B208: technology | C208: 106.35

Sheet i-ltd
A1: yyyymm | B1: line_key | C1: amount_gbp
A2: 202601 | B2: administration | C2: 130.17
A3: 202601 | B3: logistics | C3: 1255.05
A4: 202601 | B4: manufacturing | C4: 7985.13
A5: 202601 | B5: payment_fees | C5: 394.29
A6: 202601 | B6: product_sales | C6: 15702.66
A7: 202601 | B7: shopify_gb | C7: 15702.66
A8: 202602 | B8: administration | C8: 185.17
A9: 202602 | B9: logistics | C9: 1670.3
A10: 202602 | B10: manufacturing | C10: 8101.87
A11: 202602 | B11: payment_fees | C11: 488.84
A12: 202602 | B12: product_sales | C12: 19429.25
A13: 202602 | B13: shopify_gb | C13: 19429.25
... A64: 202612 | B64: manufacturing | C64: 0

Sheet i-inc
A1: yyyymm | B1: line_key | C1: amount_usd
A2: 202601 | B2: administration | C2: 1332.48
A3: 202601 | B3: logistics | C3: 2888.86
A4: 202601 | B4: manufacturing | C4: 4789.72
A5: 202601 | B5: payment_fees | C5: 293.05
A6: 202601 | B6: product_sales | C6: 10261.58
A7: 202601 | B7: shopify_us | C7: 10261.58
A8: 202602 | B8: administration | C8: 1316.39
A9: 202602 | B9: logistics | C9: 4445.62
A10: 202602 | B10: manufacturing | C10: 5220.72
A11: 202602 | B11: payment_fees | C11: 470.09
A12: 202602 | B12: product_sales | C12: 15549.06
A13: 202602 | B13: shopify_us | C13: 15549.06
... A56: 202612 | B56: manufacturing | C56: 0

Sheet fx-rates
A1: yyyymm | B1: currency | C1: reference_rate
A2: 202601 | B2: GBP | C2: 0.8662
A3: 202601 | B3: USD | C3: 1.1919
A4: 202602 | B4: GBP | C4: 0.8763
A5: 202602 | B5: USD | C5: 1.1805
A6: 202603 | B6: GBP | C6: 0.86833
A7: 202603 | B7: USD | C7: 1.1498
A8: 202604 | B8: GBP | C8: 0.86625
A9: 202604 | B9: USD | C9: 1.1702
A10: 202605 | B10: GBP | C10: 0.86723
A11: 202605 | B11: USD | C11: 1.1644
A12: 202606 | B12: GBP | C12: 0.86178
A13: 202606 | B13: USD | C13: 1.1394
... A25: 202612 | B25: USD | C25: 1.1615

Sheet P&G-TRIMESTRAL
A2: P&G CONSOLIDADO TRIMESTRAL 2026 (EUR) | B2: Q1 | C2: Q2 | D2: Q3 | E2: Q4 | F2: Total
A3: ='P&G-CONSOLIDADO'!A3
A4: TURNOVER | B4: =SUM('P&G-CONSOLIDADO'!D4:F4) | C4: =SUM('P&G-CONSOLIDADO'!G4:I4) | D4: =SUM('P&G-CONSOLIDADO'!J4:L4) | E4: =SUM('P&G-CONSOLIDADO'!M4:O4) | F4: ='P&G-CONSOLIDADO'!P4
A5: Product sales | B5: =SUM('P&G-CONSOLIDADO'!D5:F5) | C5: =SUM('P&G-CONSOLIDADO'!G5:I5) | D5: =SUM('P&G-CONSOLIDADO'!J5:L5) | E5: =SUM('P&G-CONSOLIDADO'!M5:O5) | F5: ='P&G-CONSOLIDADO'!P5
A6: Shopify | B6: =SUM('P&G-CONSOLIDADO'!D6:F6) | C6: =SUM('P&G-CONSOLIDADO'!G6:I6) | D6: =SUM('P&G-CONSOLIDADO'!J6:L6) | E6: =SUM('P&G-CONSOLIDADO'!M6:O6) | F6: ='P&G-CONSOLIDADO'!P6
A7: SL | B7: =SUM('P&G-CONSOLIDADO'!D7:F7) | C7: =SUM('P&G-CONSOLIDADO'!G7:I7) | D7: =SUM('P&G-CONSOLIDADO'!J7:L7) | E7: =SUM('P&G-CONSOLIDADO'!M7:O7) | F7: ='P&G-CONSOLIDADO'!P7
A8: avg/day | B8: =SUM('P&G-CONSOLIDADO'!D8:F8) | C8: =SUM('P&G-CONSOLIDADO'!G8:I8) | D8: =SUM('P&G-CONSOLIDADO'!J8:L8) | E8: =SUM('P&G-CONSOLIDADO'!M8:O8) | F8: ='P&G-CONSOLIDADO'!P8
A9: LTD | B9: =SUM('P&G-CONSOLIDADO'!D9:F9) | C9: =SUM('P&G-CONSOLIDADO'!G9:I9) | D9: =SUM('P&G-CONSOLIDADO'!J9:L9) | E9: =SUM('P&G-CONSOLIDADO'!M9:O9) | F9: ='P&G-CONSOLIDADO'!P9
A10: avg/day | B10: =SUM('P&G-CONSOLIDADO'!D10:F10) | C10: =SUM('P&G-CONSOLIDADO'!G10:I10) | D10: =SUM('P&G-CONSOLIDADO'!J10:L10) | E10: =SUM('P&G-CONSOLIDADO'!M10:O10) | F10: ='P&G-CONSOLIDADO'!P10
A11: INC | B11: =SUM('P&G-CONSOLIDADO'!D11:F11) | C11: =SUM('P&G-CONSOLIDADO'!G11:I11) | D11: =SUM('P&G-CONSOLIDADO'!J11:L11) | E11: =SUM('P&G-CONSOLIDADO'!M11:O11) | F11: ='P&G-CONSOLIDADO'!P11
A12: avg/day | B12: =SUM('P&G-CONSOLIDADO'!D12:F12) | C12: =SUM('P&G-CONSOLIDADO'!G12:I12) | D12: =SUM('P&G-CONSOLIDADO'!J12:L12) | E12: =SUM('P&G-CONSOLIDADO'!M12:O12) | F12: ='P&G-CONSOLIDADO'!P12
A13: Shopify daily average | B13: =SUM('P&G-CONSOLIDADO'!D13:F13) | C13: =SUM('P&G-CONSOLIDADO'!G13:I13) | D13: =SUM('P&G-CONSOLIDADO'!J13:L13) | E13: =SUM('P&G-CONSOLIDADO'!M13:O13) | F13: ='P&G-CONSOLIDADO'!P13
A14: Marketplaces | B14: =SUM('P&G-CONSOLIDADO'!D14:F14) | C14: =SUM('P&G-CONSOLIDADO'!G14:I14) | D14: =SUM('P&G-CONSOLIDADO'!J14:L14) | E14: =SUM('P&G-CONSOLIDADO'!M14:O14) | F14: ='P&G-CONSOLIDADO'!P14
A15: Rappels | B15: =SUM('P&G-CONSOLIDADO'!D15:F15) | C15: =SUM('P&G-CONSOLIDADO'!G15:I15) | D15: =SUM('P&G-CONSOLIDADO'!J15:L15) | E15: =SUM('P&G-CONSOLIDADO'!M15:O15) | F15: ='P&G-CONSOLIDADO'!P15
... A25: GROSS MARGIN (SALES-MANUFACTURING) | B25: =SUM('P&G-CONSOLIDADO'!D25:F25) | C25: =SUM('P&G-CONSOLIDADO'!G25:I25) | D25: =SUM('P&G-CONSOLIDADO'!J25:L25) | E25: =SUM('P&G-CONSOLIDADO'!M25:O25) | F25: ='P&G-CONSOLIDADO'!P25
A26: % gross margin | B26: =IFERROR(SUM('P&G-CONSOLIDADO'!D25:F25)/SUM('P&G-CONSOLIDADO'!D5:F5),0) | C26: =IFERROR(SUM('P&G-CONSOLIDADO'!G25:I25)/SUM('P&G-CONSOLIDADO'!G5:I5),0) | D26: =IFERROR(SUM('P&G-CONSOLIDADO'!J25:L25)/SUM('P&G-CONSOLIDADO'!J5:L5),0) | E26: =IFERROR(SUM('P&G-CONSOLIDADO'!M25:O25)/SUM('P&G-CONSOLIDADO'!M5:O5),0) | F26: =IFERROR('P&G-CONSOLIDADO'!P25/'P&G-CONSOLIDADO'!P5,0)
A27: Contributive margin (product sales-COGS) | B27: =SUM('P&G-CONSOLIDADO'!D27:F27) | C27: =SUM('P&G-CONSOLIDADO'!G27:I27) | D27: =SUM('P&G-CONSOLIDADO'!J27:L27) | E27: =SUM('P&G-CONSOLIDADO'!M27:O27) | F27: ='P&G-CONSOLIDADO'!P27
A28: % contributive margin | B28: =IFERROR(SUM('P&G-CONSOLIDADO'!D27:F27)/SUM('P&G-CONSOLIDADO'!D5:F5),0) | C28: =IFERROR(SUM('P&G-CONSOLIDADO'!G27:I27)/SUM('P&G-CONSOLIDADO'!G5:I5),0) | D28: =IFERROR(SUM('P&G-CONSOLIDADO'!J27:L27)/SUM('P&G-CONSOLIDADO'!J5:L5),0) | E28: =IFERROR(SUM('P&G-CONSOLIDADO'!M27:O27)/SUM('P&G-CONSOLIDADO'!M5:O5),0) | F28: =IFERROR('P&G-CONSOLIDADO'!P27/'P&G-CONSOLIDADO'!P5,0)
A29: OPEX | B29: =SUM('P&G-CONSOLIDADO'!D29:F29) | C29: =SUM('P&G-CONSOLIDADO'!G29:I29) | D29: =SUM('P&G-CONSOLIDADO'!J29:L29) | E29: =SUM('P&G-CONSOLIDADO'!M29:O29) | F29: ='P&G-CONSOLIDADO'!P29
A30: Marketing | B30: =SUM('P&G-CONSOLIDADO'!D30:F30) | C30: =SUM('P&G-CONSOLIDADO'!G30:I30) | D30: =SUM('P&G-CONSOLIDADO'!J30:L30) | E30: =SUM('P&G-CONSOLIDADO'!M30:O30) | F30: ='P&G-CONSOLIDADO'!P30
A31: Staff | B31: =SUM('P&G-CONSOLIDADO'!D31:F31) | C31: =SUM('P&G-CONSOLIDADO'!G31:I31) | D31: =SUM('P&G-CONSOLIDADO'!J31:L31) | E31: =SUM('P&G-CONSOLIDADO'!M31:O31) | F31: ='P&G-CONSOLIDADO'!P31
A32: Administration | B32: =SUM('P&G-CONSOLIDADO'!D32:F32) | C32: =SUM('P&G-CONSOLIDADO'!G32:I32) | D32: =SUM('P&G-CONSOLIDADO'!J32:L32) | E32: =SUM('P&G-CONSOLIDADO'!M32:O32) | F32: ='P&G-CONSOLIDADO'!P32
A33: Technology | B33: =SUM('P&G-CONSOLIDADO'!D33:F33) | C33: =SUM('P&G-CONSOLIDADO'!G33:I33) | D33: =SUM('P&G-CONSOLIDADO'!J33:L33) | E33: =SUM('P&G-CONSOLIDADO'!M33:O33) | F33: ='P&G-CONSOLIDADO'!P33
A34: Uncategorized Expenses | B34: =SUM('P&G-CONSOLIDADO'!D34:F34) | C34: =SUM('P&G-CONSOLIDADO'!G34:I34) | D34: =SUM('P&G-CONSOLIDADO'!J34:L34) | E34: =SUM('P&G-CONSOLIDADO'!M34:O34) | F34: ='P&G-CONSOLIDADO'!P34
A35: Currency Adjustment | B35: =SUM('P&G-CONSOLIDADO'!D35:F35) | C35: =SUM('P&G-CONSOLIDADO'!G35:I35) | D35: =SUM('P&G-CONSOLIDADO'!J35:L35) | E35: =SUM('P&G-CONSOLIDADO'!M35:O35) | F35: ='P&G-CONSOLIDADO'!P35
A36: PROFIT | B36: =SUM('P&G-CONSOLIDADO'!D36:F36) | C36: =SUM('P&G-CONSOLIDADO'!G36:I36) | D36: =SUM('P&G-CONSOLIDADO'!J36:L36) | E36: =SUM('P&G-CONSOLIDADO'!M36:O36) | F36: ='P&G-CONSOLIDADO'!P36
A37: % profit / product sales | B37: =IFERROR(SUM('P&G-CONSOLIDADO'!D36:F36)/SUM('P&G-CONSOLIDADO'!D5:F5),0) | C37: =IFERROR(SUM('P&G-CONSOLIDADO'!G36:I36)/SUM('P&G-CONSOLIDADO'!G5:I5),0) | D37: =IFERROR(SUM('P&G-CONSOLIDADO'!J36:L36)/SUM('P&G-CONSOLIDADO'!J5:L5),0) | E37: =IFERROR(SUM('P&G-CONSOLIDADO'!M36:O36)/SUM('P&G-CONSOLIDADO'!M5:O5),0) | F37: =IFERROR('P&G-CONSOLIDADO'!P36/'P&G-CONSOLIDADO'!P5,0)
