Workbook

Sheet val_pyg_old_vs_new_por
A4: Sales
A5: #VALUE! | B5: Spain | E5: =+('P&G-SL'!I6-data_pyg_old!B3)/data_pyg_old!B3 -> -0.42854758 | F5: =+('P&G-SL'!J6-data_pyg_old!C3)/data_pyg_old!C3 -> -0.019304881 | G5: =+('P&G-SL'!K6-data_pyg_old!D3)/data_pyg_old!D3 -> -0.39952653 | H5: =+('P&G-SL'!L6-data_pyg_old!E3)/data_pyg_old!E3 -> -1 | I5: =+('P&G-SL'!M6-data_pyg_old!F3)/data_pyg_old!F3 -> -1 | J5: =+('P&G-SL'!N6-data_pyg_old!G3)/data_pyg_old!G3 -> -1 | K5: =+('P&G-SL'!O6-data_pyg_old!H3)/data_pyg_old!H3 -> -1 | L5: =+('P&G-SL'!P6-data_pyg_old!I3)/data_pyg_old!I3 -> -1 | ... P5: =+('P&G-SL'!T6-data_pyg_old!M3)/data_pyg_old!M3 -> #VALUE!
A6: #VALUE! | B6: Germany | E6: =+('P&G-SL'!I7-data_pyg_old!B22)/data_pyg_old!B22 -> -0.22947362 | F6: =+('P&G-SL'!J7-data_pyg_old!C22)/data_pyg_old!C22 -> -0.20288045 | G6: =+('P&G-SL'!K7-data_pyg_old!D22)/data_pyg_old!D22 -> -0.38898447 | H6: =+('P&G-SL'!L7-data_pyg_old!E22)/data_pyg_old!E22 -> -1 | I6: =+('P&G-SL'!M7-data_pyg_old!F22)/data_pyg_old!F22 -> -1 | J6: =+('P&G-SL'!N7-data_pyg_old!G22)/data_pyg_old!G22 -> -1 | K6: =+('P&G-SL'!O7-data_pyg_old!H22)/data_pyg_old!H22 -> -1 | L6: =+('P&G-SL'!P7-data_pyg_old!I22)/data_pyg_old!I22 -> -1 | ... P6: =+('P&G-SL'!T7-data_pyg_old!M22)/data_pyg_old!M22 -> #VALUE!
A7: #VALUE! | B7: France | E7: =(+'P&G-SL'!I8-data_pyg_old!B37)/data_pyg_old!B37 -> -0.27458723 | F7: =(+'P&G-SL'!J8-data_pyg_old!C37)/data_pyg_old!C37 -> 1.0280014 | G7: =(+'P&G-SL'!K8-data_pyg_old!D37)/data_pyg_old!D37 -> 0.35204661 | H7: =(+'P&G-SL'!L8-data_pyg_old!E37)/data_pyg_old!E37 -> -1 | I7: =(+'P&G-SL'!M8-data_pyg_old!F37)/data_pyg_old!F37 -> -1 | J7: =(+'P&G-SL'!N8-data_pyg_old!G37)/data_pyg_old!G37 -> -1 | K7: =(+'P&G-SL'!O8-data_pyg_old!H37)/data_pyg_old!H37 -> -1 | L7: =(+'P&G-SL'!P8-data_pyg_old!I37)/data_pyg_old!I37 -> -1 | ... P7: =(+'P&G-SL'!T8-data_pyg_old!M37)/data_pyg_old!M37 -> #VALUE!
A8: #VALUE! | B8: Italy | E8: =+('P&G-SL'!I9-data_pyg_old!B52)/data_pyg_old!B52 -> 3.4047303 | F8: =+('P&G-SL'!J9-data_pyg_old!C52)/data_pyg_old!C52 -> 3.548509 | G8: =+('P&G-SL'!K9-data_pyg_old!D52)/data_pyg_old!D52 -> 0.75869978 | H8: =+('P&G-SL'!L9-data_pyg_old!E52)/data_pyg_old!E52 -> -1 | I8: =+('P&G-SL'!M9-data_pyg_old!F52)/data_pyg_old!F52 -> -1 | J8: =+('P&G-SL'!N9-data_pyg_old!G52)/data_pyg_old!G52 -> -1 | K8: =+('P&G-SL'!O9-data_pyg_old!H52)/data_pyg_old!H52 -> -1 | L8: =+('P&G-SL'!P9-data_pyg_old!I52)/data_pyg_old!I52 -> -1 | ... P8: =+('P&G-SL'!T9-data_pyg_old!M52)/data_pyg_old!M52 -> #VALUE!
A9: #VALUE! | B9: Austria | E9: =+('P&G-SL'!I10-data_pyg_old!B98)/data_pyg_old!B98 -> 9.8625889 | F9: =+('P&G-SL'!J10-data_pyg_old!C98)/data_pyg_old!C98 -> 22.318396 | G9: =+('P&G-SL'!K10-data_pyg_old!D98)/data_pyg_old!D98 -> 3.1233172 | H9: =+('P&G-SL'!L10-data_pyg_old!E98)/data_pyg_old!E98 -> -1 | I9: =+('P&G-SL'!M10-data_pyg_old!F98)/data_pyg_old!F98 -> -1 | J9: =+('P&G-SL'!N10-data_pyg_old!G98)/data_pyg_old!G98 -> -1 | K9: =+('P&G-SL'!O10-data_pyg_old!H98)/data_pyg_old!H98 -> -1 | L9: =+('P&G-SL'!P10-data_pyg_old!I98)/data_pyg_old!I98 -> -1 | ... P9: =+('P&G-SL'!T10-data_pyg_old!M98)/data_pyg_old!M98 -> #VALUE!

Sheet data_pyg_old
A1: Turnover | B1: 190037.6 | C1: 134163.24 | D1: 166288.41 | E1: 110118.52 | F1: 145019.23 | G1: 112800.06 | H1: 145105.3 | I1: 131261.64 | J1: - € | K1: - € | L1: - € | M1: - € | N1: 1134794
A2: Sales | B2: 174998.39 | C2: 118201.5 | D2: 126289.62 | E2: 96766.19 | F2: 132420.92 | G2: 98426.07 | H2: 122634.13 | I2: 111690.24 | J2: - € | K2: - € | L2: - € | M2: - € | N2: 981427.06 | Q2: January | R2: February | S2: March | T2: April | U2: May | V2: June | W2: July | X2: August | Y2: September | Z2: October | AA2: November | AB2: December | AC2: TOTAL
A3: Spain | B3: 107085.8 | C3: 74793.52 | D3: 76591.76 | E3: 60258.69 | F3: 72717.13 | G3: 66400.2 | H3: 78448.45 | I3: 56561.37 | J3: - € | K3: - € | L3: - € | M3: - € | N3: 592856.92 | P3: Turnover | Q3: 28261.01 | R3: 31634.75 | S3: 32185.53 | T3: 25510.99 | U3: 25273.31 | V3: 27123.55 | W3: 26037.43 | X3: 22881.03 | Y3: - | Z3: - | AA3: - | AB3: - | AC3: 218907.6
A4: Share % | B4: 0.61 | C4: 0.63 | D4: 0.61 | E4: 0.62 | F4: 0.55 | G4: 0.63 | H4: 0.64 | I4: 0.51 | J4: #DIV/0! | K4: #DIV/0! | L4: #DIV/0! | M4: #DIV/0! | N4: 0.6 | P4: the UK | Q4: 28261.01 | R4: 31634.75 | S4: 32185.53 | T4: 25510.99 | U4: 25273.31 | V4: 27123.55 | W4: 26037.43 | X4: 22881.03 | Y4: - | Z4: - | AA4: - | AB4: - | AC4: 218907.6
A5: Web | B5: 101430.37 | C5: 65195.15 | D5: 66244.47 | E5: - € | F5: - € | G5: - € | I5: - € | J5: - € | K5: - € | L5: - € | M5: - € | N5: 232869.99 | P5: Web | Q5: 28135.76 | R5: 31521 | S5: 28707.38 | T5: 25470.24 | U5: 25232.56 | V5: 821.82 | W5: - | X5: - | Y5: - | Z5: - | AA5: - | AB5: - | AC5: 139888.76
A6: Shopify | B6: 87370.09 | C6: 52964.62 | D6: 53946.7 | E6: - € | F6: - € | G6: - € | I6: - € | J6: - € | K6: - € | L6: - € | M6: - € | N6: 194281.41 | P6: Shopify | Q6: 23454.86 | R6: 26313.42 | S6: 26810.64 | T6: 22279.23 | U6: 21676.29 | V6: - | W6: - | X6: - | Y6: - | Z6: - | AA6: - | AB6: - | AC6: 120534.44
A7: Paypal | B7: 10946.77 | C7: 8806.36 | D7: 9617.1 | E7: - € | F7: - € | G7: - € | I7: - € | J7: - € | K7: - € | L7: - € | M7: - € | N7: 29370.23 | P7: Paypal | Q7: 3973.2 | R7: 4626.66 | S7: 936.91 | T7: 2479.59 | U7: 3178.86 | V7: - | W7: - | X7: - | Y7: - | Z7: - | AA7: - | AB7: - | AC7: 15195.22
A8: Amazon Pay | B8: - € | C8: - € | E8: - € | F8: - € | G8: - € | I8: - € | J8: - € | K8: - € | L8: - € | M8: - € | N8: - € | P8: Amazon Pay | Q8: - | R8: - | S8: - | T8: - | U8: - | V8: - | W8: - | X8: - | Y8: - | Z8: - | AA8: - | AB8: - | AC8: -
A9: Klarna | B9: 1477.01 | C9: 1523.75 | D9: 1731.8 | E9: - € | F9: - € | G9: - € | I9: - € | J9: - € | K9: - € | L9: - € | M9: - € | N9: 4732.56 | P9: Klarna | Q9: 707.7 | R9: 580.92 | S9: 959.83 | T9: 639.97 | U9: 377.41 | V9: 821.82 | W9: - | X9: - | Y9: - | Z9: - | AA9: - | AB9: - | AC9: 4087.65
A10: Revolut | B10: 482.29 | C10: 347.84 | D10: 50.5 | E10: - € | F10: - € | G10: - € | I10: - € | J10: - € | K10: - € | L10: - € | M10: - € | N10: 880.63 | P10: Revolut | R10: - | S10: - | T10: - | U10: - | V10: - | W10: - | X10: - | Y10: - | Z10: - | AA10: - | AB10: - | AC10: -
A11: SeQura | B11: - € | C11: - € | D11: - € | E11: - € | F11: - € | G11: - € | I11: - € | J11: - € | K11: - € | L11: - € | M11: - € | N11: - € | P11: Bank transfer | Q11: - | R11: - | S11: - | T11: 71.45 | U11: - | V11: - | W11: - | X11: - | Y11: - | Z11: - | AA11: - | AB11: - | AC11: 71.45
A12: Hannun | B12: 1154.21 | C12: 1552.58 | D12: 898.37 | E12: - € | F12: - € | G12: - € | I12: - € | J12: - € | K12: - € | L12: - € | M12: - € | N12: 3605.16 | P12: Marketplace | Q12: 125.25 | R12: 113.75 | S12: - | T12: 40.75 | U12: 40.75 | V12: - | W12: - | X12: - | Y12: - | Z12: - | AA12: - | AB12: - | AC12: 320.5
A13: B2B | B13: 4386.25 | C13: 8435.65 | D13: 9467.3 | E13: - € | F13: - € | G13: - € | I13: - € | J13: - € | K13: - € | L13: - € | M13: - € | N13: 22289.2 | P13: Amazon Seller | Q13: 125.25 | R13: 113.75 | S13: - | T13: 40.75 | U13: 40.75 | V13: - | W13: - | X13: - | Y13: - | Z13: - | AA13: - | AB13: - | AC13: 320.5
A14: Bank transfer | B14: 4386.25 | C14: 8435.65 | D14: 9467.3 | E14: - € | F14: - € | G14: - € | I14: - € | J14: - € | K14: - € | L14: - € | M14: - € | N14: 22289.2 | P14: B2B | Q14: - | R14: - | S14: 3478.15 | T14: - € | U14: - € | V14: - € | W14: - € | X14: - € | Y14: - € | Z14: - € | AA14: - € | AB14: - € | AC14: 3478.15
A15: Web | B15: - € | C15: - € | E15: - € | F15: - € | G15: - € | I15: - € | J15: - € | K15: - € | L15: - € | M15: - € | N15: - € | P15: Bank transfer | Q15: - | R15: - | S15: - | T15: - € | U15: - € | V15: - € | W15: - € | X15: - € | Y15: - € | Z15: - € | AA15: - € | AB15: - € | AC15: - €
A16: Paypal | P16: Web | Q16: - | R16: - | S16: 2459.35 | T16: - € | U16: - € | V16: - € | W16: - € | X16: - € | Y16: - € | Z16: - € | AA16: - € | AB16: - € | AC16: 2459.35
A17: Marketplace | B17: 1269.18 | C17: 1162.72 | D17: 879.99 | E17: - € | F17: - € | G17: - € | I17: - € | J17: - € | K17: - € | L17: - € | M17: - € | N17: 3190.12 | P17: Paypal | S17: £ 1.018,80
A18: Amazon Seller | B18: 223.01 | C18: 256.19 | D18: 174.5 | E18: - € | F18: - € | G18: - € | I18: - € | J18: - € | K18: - € | L18: - € | M18: - € | N18: 653.7
A19: Maisons du Monde | B19: 979.43 | C19: 906.53 | D19: 650.46 | E19: - € | F19: - € | G19: - € | I19: - € | J19: - € | K19: - € | L19: - € | M19: - € | N19: 2536.42
A20: Leroy Merlin | B20: 66.74 | C20: - € | D20: 55.03 | E20: - € | F20: - € | G20: - € | I20: - € | J20: - € | K20: - € | L20: - € | M20: - € | N20: 121.77
A22: Germany | B22: 27155.67 | C22: 24289.28 | D22: 25631.82 | E22: 24271.09 | F22: 22639.29 | G22: 23154.4 | H22: 17733.42 | I22: 17029.18 | J22: - € | K22: - € | L22: - € | M22: - € | N22: 181904.15
A23: Share % | B23: 0.16 | C23: 0.21 | D23: 0.2 | E23: 0.25 | F23: 0.17 | G23: 0.22 | I23: 0.15 | J23: #DIV/0! | K23: #DIV/0! | L23: #DIV/0! | M23: #DIV/0! | N23: 0.19
A24: Web | B24: 25515.08 | C24: 22629.75 | D24: 24618.7 | E24: - € | F24: - € | G24: - € | I24: - € | J24: - € | K24: - € | L24: - € | M24: - € | N24: 72763.53
A25: Shopify | B25: 7756.93 | C25: 8263.46 | D25: 10156.8 | E25: - € | F25: - € | G25: - € | I25: - € | J25: - € | K25: - € | L25: - € | M25: - € | N25: 26177.19
A26: Paypal | B26: 17758.15 | C26: 14205.5 | D26: 13052.4 | E26: - € | F26: - € | G26: - € | I26: - € | J26: - € | K26: - € | L26: - € | M26: - € | N26: 45016.05
A27: Amazon Pay | B27: - € | C27: - € | D27: - € | E27: - € | F27: - € | G27: - € | I27: - € | J27: - € | K27: - € | L27: - € | M27: - € | N27: - €
A28: Klarna | B28: - € | C28: - € | D28: - € | E28: - € | F28: - € | G28: - € | I28: - € | J28: - € | K28: - € | L28: - € | M28: - € | N28: - €
A29: Revolut | B29: - € | C29: - € | D29: - € | E29: - € | F29: - € | G29: - € | I29: - € | J29: - € | K29: - € | L29: - € | M29: - € | N29: - €
A30: Bank transfer | B30: - € | C30: 160.79 | D30: 1409.5 | E30: - € | F30: - € | G30: - € | I30: - € | J30: - € | K30: - € | L30: - € | M30: - € | N30: 1570.29
A31: Marketplace | B31: 1640.59 | C31: 1659.53 | D31: 1013.12 | E31: - € | F31: - € | G31: - € | I31: - € | J31: - € | K31: - € | L31: - € | M31: - € | N31: 792.23
A32: Amazon Seller | B32: 310.91 | C32: 203.62 | D32: 277.7 | E32: - € | F32: - € | G32: - € | I32: - € | J32: - € | K32: - € | L32: - € | M32: - € | N32: 792.23
A33: Maisons du Monde | B33: 1329.68 | C33: 1350.25 | D33: 340.2 | E33: - € | F33: - € | G33: - € | I33: - € | J33: - € | K33: - € | L33: - € | M33: - € | N33: - €
A34: Leroy Merlin | B34: - € | C34: - € | D34: - € | E34: - € | F34: - € | G34: - € | I34: - € | J34: - € | K34: - € | L34: - € | M34: - € | N34: - €
A35: Home24 | B35: - € | C35: 105.66 | D35: 395.22 | E35: - € | F35: - € | G35: - € | I35: - € | J35: - € | K35: - € | L35: - € | M35: - € | N35: 500.88
A37: France | B37: 35276.95 | C37: 13561.45 | D37: 16399.05 | E37: 8456.84 | F37: 32386.23 | G37: 6207.97 | H37: 14615.31 | I37: 18120.88 | J37: - € | K37: - € | L37: - € | M37: - € | N37: 145024.68
A38: Web | B38: 15640.02 | C38: 13561.45 | D38: 13617.4 | E38: - € | F38: 11538.53 | G38: 13612.1 | I38: - € | J38: - € | K38: - € | L38: - € | M38: - € | N38: 67969.5
A39: Shopify | B39: 12765.42 | C39: 10947.48 | D39: 11594.3 | E39: - € | F39: - € | G39: - € | I39: - € | J39: - € | K39: - € | L39: - € | M39: - € | N39: 35307.2
A40: Paypal | B40: 2874.6 | C40: 2463.75 | D40: 1875.4 | E40: - € | F40: - € | G40: - € | I40: - € | J40: - € | K40: - € | L40: - € | M40: - € | N40: 7213.75
A41: Amazon Pay | B41: - € | C41: - € | D41: - € | E41: - € | F41: - € | G41: - € | I41: - € | J41: - € | K41: - € | L41: - € | M41: - € | N41: - €
A42: Klarna | B42: - € | C42: - € | D42: - € | E42: - € | F42: - € | G42: - € | I42: - € | J42: - € | K42: - € | L42: - € | M42: - € | N42: - €
A43: Revolut | B43: - € | C43: 34.87 | D43: - € | E43: - € | F43: - € | G43: - € | I43: - € | J43: - € | K43: - € | L43: - € | M43: - € | N43: 34.87
A44: Bank transfer | B44: - € | C44: 115.35 | D44: 147.7 | E44: - € | F44: - € | G44: - € | I44: - € | J44: - € | K44: - € | L44: - € | M44: - € | N44: 263.05
A45: Marketplace | B45: 19636.93 | C45: - € | D45: 2781.65 | E45: - € | F45: 20847.7 | G45: -7404.13 | I45: - € | J45: - € | K45: - € | L45: - € | M45: - € | N45: 35862.15
A46: Amazon Seller | B46: - € | C46: - € | D46: - € | E46: - € | F46: - € | G46: - € | I46: - € | J46: - € | K46: - € | L46: - € | M46: - € | N46: - €
A47: Choose | B47: 19636.93 | C47: - € | D47: 2781.65 | E47: - € | F47: 20847.7 | G47: -7404.13 | I47: - € | J47: - € | K47: - € | L47: - € | M47: - € | N47: 35862.15
A48: Maisons du Monde | B48: - € | C48: - € | D48: - € | E48: - € | F48: - € | G48: - € | I48: - € | J48: - € | K48: - € | L48: - € | M48: - € | N48: - €
A49: Leroy Merlin | B49: - € | C49: - € | D49: - € | E49: - € | F49: - € | G49: - € | I49: - € | J49: - € | K49: - € | L49: - € | M49: - € | N49: - €
A51: Share % | B51: 0.2 | C51: 0.11 | D51: 0.13 | E51: 0.09 | F51: 0.24 | G51: 0.06 | I51: 0.16 | J51: #DIV/0! | K51: #DIV/0! | L51: #DIV/0! | M51: #DIV/0! | N51: 0.15
A52: Italy | B52: 4196.35 | C52: 4406.91 | D52: 6073.72 | E52: 2936.99 | F52: 2074.75 | G52: 2056.2 | H52: 9924.85 | I52: 13695.03 | J52: - € | K52: - € | L52: - € | M52: - € | N52: 45364.8
A53: Share % | B53: 0.02 | C53: 0.04 | D53: 0.05 | E53: 0.03 | F53: 0.02 | G53: 0.02 | I53: 0.12 | J53: #DIV/0! | K53: #DIV/0! | L53: #DIV/0! | M53: #DIV/0! | N53: 0.05
A54: Web | B54: 4114.24 | C54: 4382.36 | D54: 5994.7 | E54: - € | F54: - € | G54: - € | I54: - € | J54: - € | K54: - € | L54: - € | M54: - € | N54: 14491.3
A55: Shopify | B55: 1463.84 | C55: 2855.62 | D55: 5944.6 | E55: - € | F55: - € | G55: - € | I55: - € | J55: - € | K55: - € | L55: - € | M55: - € | N55: 10264.06
A56: Paypal | B56: 2650.4 | C56: 1526.74 | D56: 50.1 | E56: - € | F56: - € | G56: - € | I56: - € | J56: - € | K56: - € | L56: - € | M56: - € | N56: 4227.24
A57: Amazon Pay | B57: - € | C57: - € | D57: - € | E57: - € | F57: - € | G57: - € | I57: - € | J57: - € | K57: - € | L57: - € | M57: - € | N57: - €
A58: Klarna | B58: - € | C58: - € | D58: - € | E58: - € | F58: - € | G58: - € | I58: - € | J58: - € | K58: - € | L58: - € | M58: - € | N58: - €
A59: Revolut | B59: - € | C59: - € | D59: - € | E59: - € | F59: - € | G59: - € | I59: - € | J59: - € | K59: - € | L59: - € | M59: - € | N59: - €
A60: Bank transfer | B60: - € | C60: - € | D60: - € | E60: - € | F60: - € | G60: - € | I60: - € | J60: - € | K60: - € | L60: - € | M60: - € | N60: - €
A61: Marketplace | B61: 82.11 | C61: 24.55 | D61: 79.02 | E61: - € | F61: - € | G61: - € | I61: - € | J61: - € | K61: - € | L61: - € | M61: - € | N61: 185.68
A62: Amazon Seller | B62: 82.11 | C62: 24.55 | D62: 79.02 | E62: - € | F62: - € | G62: - € | I62: - € | J62: - € | K62: - € | L62: - € | M62: - € | N62: 185.68
A64: the Netherlands | B64: 374.65 | C64: 254.08 | D64: 31.07 | E64: 14.83 | F64: 49.5 | G64: 57.9 | H64: 150.99 | I64: 416.82 | J64: - € | K64: - € | L64: - € | M64: - € | N64: 1349.84
A65: Share % | B65: 0 | C65: 0 | D65: 0 | E65: 0 | F65: 0 | G65: 0 | I65: 0 | J65: #DIV/0! | K65: #DIV/0! | L65: #DIV/0! | M65: #DIV/0! | N65: 0.01
A66: Web | B66: 374.65 | C66: 254.08 | D66: 31.07 | E66: - € | F66: - € | G66: - € | I66: - € | J66: - € | K66: - € | L66: - € | M66: - € | N66: 659.8
A67: Shopify | B67: 374.65 | C67: 254.08 | D67: 31.07 | E67: - € | F67: - € | G67: - € | I67: - € | J67: - € | K67: - € | L67: - € | M67: - € | N67: 659.8
A68: Paypal | B68: - € | C68: - € | D68: - € | E68: - € | F68: - € | G68: - € | I68: - € | J68: - € | K68: - € | L68: - € | M68: - € | N68: - €
A69: Amazon Pay | B69: - € | C69: - € | D69: - € | E69: - € | F69: - € | G69: - € | I69: - € | J69: - € | K69: - € | L69: - € | M69: - € | N69: - €
A70: Klarna | B70: - € | C70: - € | D70: - € | E70: - € | F70: - € | G70: - € | I70: - € | J70: - € | K70: - € | L70: - € | M70: - € | N70: - €
A71: Revolut | B71: - € | C71: - € | D71: - € | E71: - € | F71: - € | G71: - € | I71: - € | J71: - € | K71: - € | L71: - € | M71: - € | N71: - €
A72: Marketplace | B72: - € | C72: - € | D72: - € | E72: - € | F72: - € | G72: - € | I72: - € | J72: - € | K72: - € | L72: - € | M72: - € | N72: - €
A73: Amazon Seller | B73: - € | C73: - € | D73: - € | E73: - € | F73: - € | G73: - € | I73: - € | J73: - € | K73: - € | L73: - € | M73: - € | N73: - €
A75: Belgium | B75: 235.61 | C75: 50.29 | D75: 76.7 | E75: 232.18 | F75: 533.77 | G75: 54.2 | H75: 54.2 | I75: 461.61 | J75: - € | K75: - € | L75: - € | M75: - € | N75: 1698.56
A76: Share % | B76: 0 | C76: 0 | D76: 0 | E76: 0 | F76: 0 | G76: 0 | I76: 0 | J76: #DIV/0! | K76: #DIV/0! | L76: #DIV/0! | M76: #DIV/0! | N76: 0.01
A77: Web | B77: 235.61 | C77: 50.29 | D77: 76.7 | E77: - € | F77: - € | G77: - € | I77: - € | J77: - € | K77: - € | L77: - € | M77: - € | N77: 362.6
A78: Shopify | B78: 175.45 | C78: 50.29 | D78: 76.7 | E78: - € | F78: - € | G78: - € | I78: - € | J78: - € | K78: - € | L78: - € | M78: - € | N78: 302.44
A79: Paypal | B79: 60.16 | C79: - € | D79: - € | E79: - € | F79: - € | G79: - € | I79: - € | J79: - € | K79: - € | L79: - € | M79: - € | N79: 60.16
A80: Amazon Pay | B80: - € | C80: - € | D80: - € | E80: - € | F80: - € | G80: - € | I80: - € | J80: - € | K80: - € | L80: - € | M80: - € | N80: - €
A81: Klarna | B81: - € | C81: - € | D81: - € | E81: - € | F81: - € | G81: - € | I81: - € | J81: - € | K81: - € | L81: - € | M81: - € | N81: - €
A82: Revolut | B82: - € | C82: - € | D82: - € | E82: - € | F82: - € | G82: - € | I82: - € | J82: - € | K82: - € | L82: - € | M82: - € | N82: - €
A83: Marketplace | B83: - € | C83: - € | D83: - € | E83: - € | F83: - € | G83: - € | I83: - € | J83: - € | K83: - € | L83: - € | M83: - € | N83: - €
A84: Amazon Seller | B84: - € | C84: - € | D84: - € | E84: - € | F84: - € | G84: - € | I84: - € | J84: - € | K84: - € | L84: - € | M84: - € | N84: - €
A85: Choose | B85: - € | C85: - € | D85: - € | E85: - € | F85: - € | G85: - € | I85: - € | J85: - € | K85: - € | L85: - € | M85: - € | N85: - €
A87: Portugal | B87: 94.44 | C87: 45.45 | D87: 28.8 | E87: 67.69 | F87: 46.59 | G87: 57.9 | H87: 92.15 | I87: 386.5 | J87: - € | K87: - € | L87: - € | M87: - € | N87: 819.52
A88: Share % | B88: 0 | C88: 0 | D88: 0 | E88: 0 | F88: 0 | G88: 0 | I88: 0 | J88: #DIV/0! | K88: #DIV/0! | L88: #DIV/0! | M88: #DIV/0! | N88: 0
A89: Web | B89: 94.44 | C89: 45.45 | D89: 28.8 | E89: - € | F89: - € | G89: - € | I89: - € | J89: - € | K89: - € | L89: - € | M89: - € | N89: 168.69
A90: Shopify | B90: 94.44 | C90: 45.45 | D90: 28.8 | E90: - € | F90: - € | G90: - € | I90: - € | J90: - € | K90: - € | L90: - € | M90: - € | N90: 168.69
A91: Paypal | B91: - € | C91: - € | D91: - € | E91: - € | F91: - € | G91: - € | I91: - € | J91: - € | K91: - € | L91: - € | M91: - €
A92: Amazon Pay | B92: - € | C92: - € | D92: - € | E92: - € | F92: - € | G92: - € | I92: - € | J92: - € | K92: - € | L92: - € | M92: - € | N92: - €
A93: Klarna | B93: - € | C93: - € | D93: - € | E93: - € | F93: - € | G93: - € | I93: - € | J93: - € | K93: - € | L93: - € | M93: - € | N93: - €
A94: Revolut | B94: - € | C94: - € | D94: - € | E94: - € | F94: - € | G94: - € | I94: - € | J94: - € | K94: - € | L94: - € | M94: - € | N94: - €
A95: Marketplace | B95: - € | C95: - € | D95: - € | E95: - € | F95: - € | G95: - € | I95: - € | J95: - € | K95: - € | L95: - € | M95: - € | N95: - €
A96: Amazon Seller | B96: - € | C96: - € | D96: - € | E96: - € | F96: - € | G96: - € | I96: - € | J96: - € | K96: - € | L96: - € | M96: - € | N96: - €
A98: Austria | B98: 504.69 | C98: 260.65 | D98: 867.6 | E98: 291.64 | F98: 511.26 | G98: 383.1 | H98: 1508.86 | I98: 4924.93 | J98: - € | K98: - € | L98: - € | M98: - € | N98: 9252.73
A99: Share % | B99: 0 | C99: 0 | D99: 0.01 | E99: 0 | F99: 0 | G99: 0 | I99: 0.04 | J99: #DIV/0! | K99: #DIV/0! | L99: #DIV/0! | M99: #DIV/0! | N99: 0.05
A100: Web | B100: 504.69 | C100: 260.65 | D100: 867.6 | E100: - € | F100: - € | G100: - € | H100: - € | I100: - € | J100: - € | K100: - € | L100: - € | M100: - € | N100: 1632.94
A101: Shopify | B101: 139.98 | C101: - € | D101: 731.3 | E101: - € | F101: - € | G101: - € | H101: - € | I101: - € | J101: - € | K101: - € | L101: - € | M101: - € | N101: 871.28
A102: Paypal | B102: 364.71 | C102: 260.65 | D102: 136.3 | E102: - € | F102: - € | G102: - € | H102: - € | I102: - € | J102: - € | K102: - € | L102: - € | M102: - € | N102: 761.66
A103: Amazon Pay | B103: - € | C103: - € | D103: - € | E103: - € | F103: - € | G103: - € | H103: - € | I103: - € | J103: - € | K103: - € | L103: - € | M103: - € | N103: - €
A104: Klarna | B104: - € | C104: - € | D104: - € | E104: - € | F104: - € | G104: - € | H104: - € | I104: - € | J104: - € | K104: - € | L104: - € | M104: - € | N104: - €
A105: Revolut | B105: - € | C105: - € | D105: - € | E105: - € | F105: - € | G105: - € | H105: - € | I105: - € | J105: - € | K105: - € | L105: - € | M105: - € | N105: - €
A106: Marketplace | B106: - € | C106: - € | D106: - € | E106: - € | F106: - € | G106: - € | H106: - € | I106: - € | J106: - € | K106: - € | L106: - € | M106: - € | N106: - €
A107: Amazon Seller | B107: - € | C107: - € | D107: - € | E107: - € | F107: - € | G107: - € | H107: - € | I107: - € | J107: - € | K107: - € | L107: - € | M107: - € | N107: - €
...

Sheet val_pyg_old_vs_new_imp
A4: Sales
A5: #VALUE! | B5: Spain | C5: =+'P&G-SL'!I6-data_pyg_old!B3 -> -45891.36 | D5: =+'P&G-SL'!J6-data_pyg_old!C3 -> -1443.88 | E5: =+'P&G-SL'!K6-data_pyg_old!D3 -> -30600.44 | F5: =+'P&G-SL'!L6-data_pyg_old!E3 -> -60258.69 | G5: =+'P&G-SL'!M6-data_pyg_old!F3 -> -72717.13 | H5: =+'P&G-SL'!N6-data_pyg_old!G3 -> -66400.2 | I5: =+'P&G-SL'!O6-data_pyg_old!H3 -> -78448.45 | J5: =+'P&G-SL'!P6-data_pyg_old!I3 -> -56561.37
A6: #VALUE! | B6: Germany | C6: =+'P&G-SL'!I7-data_pyg_old!B22 -> -6231.51 | D6: =+'P&G-SL'!J7-data_pyg_old!C22 -> -4927.82 | E6: =+'P&G-SL'!K7-data_pyg_old!D22 -> -9970.38 | F6: =+'P&G-SL'!L7-data_pyg_old!E22 -> -24271.09 | G6: =+'P&G-SL'!M7-data_pyg_old!F22 -> -22639.29 | H6: =+'P&G-SL'!N7-data_pyg_old!G22 -> -23154.4 | I6: =+'P&G-SL'!O7-data_pyg_old!H22 -> -17733.42 | J6: =+'P&G-SL'!P7-data_pyg_old!I22 -> -17029.18
A7: #VALUE! | B7: France | C7: =+'P&G-SL'!I8-data_pyg_old!B37 -> -9686.6 | D7: =+'P&G-SL'!J8-data_pyg_old!C37 -> 13941.19 | E7: =+'P&G-SL'!K8-data_pyg_old!D37 -> 5773.23 | F7: =+'P&G-SL'!L8-data_pyg_old!E37 -> -8456.84 | G7: =+'P&G-SL'!M8-data_pyg_old!F37 -> -32386.23 | H7: =+'P&G-SL'!N8-data_pyg_old!G37 -> -6207.97 | I7: =+'P&G-SL'!O8-data_pyg_old!H37 -> -14615.31 | J7: =+'P&G-SL'!P8-data_pyg_old!I37 -> -18120.88
A8: #VALUE! | B8: Italy | C8: =+'P&G-SL'!I9-data_pyg_old!B52 -> 14287.44 | D8: =+'P&G-SL'!J9-data_pyg_old!C52 -> 15637.96 | E8: =+'P&G-SL'!K9-data_pyg_old!D52 -> 4608.13 | F8: =+'P&G-SL'!L9-data_pyg_old!E52 -> -2936.99 | G8: =+'P&G-SL'!M9-data_pyg_old!F52 -> -2074.75 | H8: =+'P&G-SL'!N9-data_pyg_old!G52 -> -2056.2 | I8: =+'P&G-SL'!O9-data_pyg_old!H52 -> -9924.85 | J8: =+'P&G-SL'!P9-data_pyg_old!I52 -> -13695.03
A9: #VALUE! | B9: Austria | C9: =+'P&G-SL'!I10-data_pyg_old!B98 -> 4977.55 | D9: =+'P&G-SL'!J10-data_pyg_old!C98 -> 5817.29 | E9: =+'P&G-SL'!K10-data_pyg_old!D98 -> 2709.79 | F9: =+'P&G-SL'!L10-data_pyg_old!E98 -> -291.64 | G9: =+'P&G-SL'!M10-data_pyg_old!F98 -> -511.26 | H9: =+'P&G-SL'!N10-data_pyg_old!G98 -> -383.1 | I9: =+'P&G-SL'!O10-data_pyg_old!H98 -> -1508.86 | J9: =+'P&G-SL'!P10-data_pyg_old!I98 -> -4924.93
A10: #VALUE! | B10: the Netherlands | C10: =+'P&G-SL'!I12-data_pyg_old!B64 -> -259.07 | D10: =+'P&G-SL'!J12-data_pyg_old!C64 -> -78.21 | E10: =+'P&G-SL'!K12-data_pyg_old!D64 -> 8.52 | F10: =+'P&G-SL'!L12-data_pyg_old!E64 -> -14.83 | G10: =+'P&G-SL'!M12-data_pyg_old!F64 -> -49.5 | H10: =+'P&G-SL'!N12-data_pyg_old!G64 -> -57.9 | I10: =+'P&G-SL'!O12-data_pyg_old!H64 -> -150.99 | J10: =+'P&G-SL'!P12-data_pyg_old!I64 -> -416.82
A11: #VALUE! | B11: Belgium | C11: =+'P&G-SL'!I11-data_pyg_old!B75 -> 187.1 | D11: =+'P&G-SL'!J11-data_pyg_old!C75 -> 948.39 | E11: =+'P&G-SL'!K11-data_pyg_old!D75 -> -50.34 | F11: =+'P&G-SL'!L11-data_pyg_old!E75 -> -232.18 | G11: =+'P&G-SL'!M11-data_pyg_old!F75 -> -533.77 | H11: =+'P&G-SL'!N11-data_pyg_old!G75 -> -54.2 | I11: =+'P&G-SL'!O11-data_pyg_old!H75 -> -54.2 | J11: =+'P&G-SL'!P11-data_pyg_old!I75 -> -461.61
A12: #VALUE! | B12: Portugal | C12: =+'P&G-SL'!I13-data_pyg_old!B87 -> 634.87 | D12: =+'P&G-SL'!J13-data_pyg_old!C87 -> 1236.05 | E12: =+'P&G-SL'!K13-data_pyg_old!D87 -> -28.8 | F12: =+'P&G-SL'!L13-data_pyg_old!E87 -> -67.69 | G12: =+'P&G-SL'!M13-data_pyg_old!F87 -> -46.59 | H12: =+'P&G-SL'!N13-data_pyg_old!G87 -> -57.9 | I12: =+'P&G-SL'!O13-data_pyg_old!H87 -> -92.15 | J12: =+'P&G-SL'!P13-data_pyg_old!I87 -> -386.5
A13: #VALUE! | B13: Other markets | C13: =+'P&G-SL'!I14-data_pyg_old!B109 -> 616.96 | D13: =+'P&G-SL'!J14-data_pyg_old!C109 -> -275.39 | E13: =+'P&G-SL'!K14-data_pyg_old!D109 -> -361.88 | F13: =+'P&G-SL'!L14-data_pyg_old!E109 -> -236.24 | G13: =+'P&G-SL'!M14-data_pyg_old!F109 -> -1462.4 | H13: =+'P&G-SL'!N14-data_pyg_old!G109 -> -54.2 | I13: =+'P&G-SL'!O14-data_pyg_old!H109 -> -105.9 | J13: =+'P&G-SL'!P14-data_pyg_old!I109 -> -93.92
A14: #VALUE! | B14: United Kingdom | C14: =+'P&G-Ltd'!H5-data_pyg_old!Q3 -> -12558.35 | D14: =+'P&G-Ltd'!I5-data_pyg_old!R3 -> -12205.5 | E14: =+'P&G-Ltd'!J5-data_pyg_old!S3 -> -18542.89 | F14: =+'P&G-Ltd'!K5-data_pyg_old!T3 -> -25510.99 | G14: =+'P&G-Ltd'!L5-data_pyg_old!U3 -> -25273.31 | H14: =+'P&G-Ltd'!M5-data_pyg_old!V3 -> -27123.55 | I14: =+'P&G-Ltd'!N5-data_pyg_old!W3 -> -26037.43 | J14: =+'P&G-Ltd'!O5-data_pyg_old!X3 -> -22881.03

Sheet Val_FR_202501
A1: Sales channel | B1: Order name | C1: Total sales | D1: Orders | E1: Gross sales | F1: Discounts | G1: Returns | H1: Net sales | I1: Shipping charges | J1: Duties | K1: Additional fees | L1: Taxes
A2: Online Store | B2: ES-69606 | C2: 632.52 | D2: 1 | E2: 585.59 | F2: -58.49 | G2: 0 | H2: 527.1 | I2: 0 | J2: 0 | K2: 0 | L2: 105.42
A3: Online Store | B3: ES-67388 | C3: 618.48 | D3: 1 | E3: 572.62 | F3: -57.22 | G3: 0 | H3: 515.4 | I3: 0 | J3: 0 | K3: 0 | L3: 103.08
A4: Online Store | B4: ES-68305 | C4: 314.4 | D4: 1 | E4: 262 | F4: 0 | G4: 0 | H4: 262 | I4: 0 | J4: 0 | K4: 0 | L4: 52.4
A5: Online Store | B5: ES-69281 | C5: 305.46 | D5: 1 | E5: 282.79 | F5: -28.24 | G5: 0 | H5: 254.55 | I5: 0 | J5: 0 | K5: 0 | L5: 50.91
A6: Online Store | B6: ES-69525 | C6: 275.55 | D6: 1 | E6: 229.62 | F6: 0 | G6: 0 | H6: 229.62 | I6: 0 | J6: 0 | K6: 0 | L6: 45.93
A7: Online Store | B7: ES-67042 | C7: 272.5 | D7: 1 | E7: 227.08 | F7: 0 | G7: 0 | H7: 227.08 | I7: 0 | J7: 0 | K7: 0 | L7: 45.42
A8: Online Store | B8: ES-69264 | C8: 265.5 | D8: 1 | E8: 221.25 | F8: 0 | G8: 0 | H8: 221.25 | I8: 0 | J8: 0 | K8: 0 | L8: 44.25
A9: Online Store | B9: ES-69047 | C9: 242.6 | D9: 1 | E9: 202.17 | F9: 0 | G9: 0 | H9: 202.17 | I9: 0 | J9: 0 | K9: 0 | L9: 40.43
A10: Online Store | B10: ES-68426 | C10: 233.64 | D10: 1 | E10: 216.3 | F10: -21.6 | G10: 0 | H10: 194.7 | I10: 0 | J10: 0 | K10: 0 | L10: 38.94
A11: Online Store | B11: ES-69526 | C11: 230.5 | D11: 1 | E11: 192.08 | F11: 0 | G11: 0 | H11: 192.08 | I11: 0 | J11: 0 | K11: 0 | L11: 38.42
A12: Online Store | B12: ES-68010 | C12: 223.5 | D12: 1 | E12: 186.25 | F12: 0 | G12: 0 | H12: 186.25 | I12: 0 | J12: 0 | K12: 0 | L12: 37.25
A13: Online Store | B13: ES-69205 | C13: 206.1 | D13: 1 | E13: 171.75 | F13: 0 | G13: 0 | H13: 171.75 | I13: 0 | J13: 0 | K13: 0 | L13: 34.35
... A309: Online Store | B309: ES-64976 | C309: -245.7 | D309: 0 | E309: 0 | F309: 0 | G309: -204.75 | H309: -204.75 | I309: 0 | J309: 0 | K309: 0 | L309: -40.95

Sheet P&G-SL
I1: =+params!B4 -> 202601 | J1: =+params!C4 -> 202602 | K1: =+params!D4 -> 202603 | L1: =+params!E4 -> 202604 | M1: =+params!F4 -> 202605 | N1: =+params!G4 -> 202606 | O1: =+params!H4 -> 202607 | P1: =+params!I4 -> 202608 | ... T1: =+params!M4 -> 202612
E2: 2026 | I2: Enero | J2: Febrero | K2: Marzo | L2: Abril | M2: Mayo | N2: Junio | O2: Julio | P2: Agosto | Q2: Septiembre | R2: Octubre | S2: Noviembre | T2: Diciembre | U2: Total
D3: Turnover | I3: =+I4+I30 -> 152677.71 | J3: =+J4+J30 -> 174132.08 | K3: =+K4+K30 -> 113987.41 | L3: =+L4+L30 -> 0 | M3: =+M4+M30 -> 0 | N3: =+N4+N30 -> 0 | O3: =+O4+O30 -> 0 | P3: =+P4+P30 -> 0 | ... T3: =+T4+T30 -> 0 | U3: =SUM(I3:T3) -> 440797.2
D4: SALES | I4: =+I5+I16+I21+I23 -> 131758.06 | J4: =+J5+J16+J21+J23 -> 151409.56 | K4: =+K5+K16+K21+K23 -> 113987.41 | L4: =+L5+L16+L21+L23 -> 0 | M4: =+M5+M16+M21+M23 -> 0 | N4: =+N5+N16+N21+N23 -> 0 | O4: =+O5+O16+O21+O23 -> 0 | P4: =+P5+P16+P21+P23 -> 0 | ... T4: =+T5+T16+T21+T23 -> 0 | U4: =SUM(I4:T4) -> 397155.03
A5: Hannun | B5: Mirakl | C5: Country | E5: Shopify | I5: =SUM(I6:I14) -> 133633.77 | J5: =SUM(J6:J14) -> 149057.08 | K5: =SUM(K6:K14) -> 98377.45 | L5: =SUM(L6:L14) -> 0 | M5: =SUM(M6:M14) -> 0 | N5: =SUM(N6:N14) -> 0 | O5: =SUM(O6:O14) -> 0 | P5: =SUM(P6:P14) -> 0 | ... T5: =SUM(T6:T14) -> 0 | U5: =SUM(I5:T5) -> 381068.3
A6: 0 | B6: 0 | C6: ES | E6: #VALUE! | F6: Spain | I6: =SUMIFS('i-sales'!$K:$K, 'i-sales'!$C:$C,'P&G-SL'!I$1, 'i-sales'!$D:$D,'P&G-SL'!$C6, 'i-sales'!$G:$G,'P&G-SL'!$A6, 'i-sales'!$H:$H,'P&G-SL'!$B6 ) -> 61194.44 | J6: =SUMIFS('i-sales'!$K:$K, 'i-sales'!$C:$C,'P&G-SL'!J$1, 'i-sales'!$D:$D,'P&G-SL'!$C6, 'i-sales'!$G:$G,'P&G-SL'!$A6, 'i-sales'!$H:$H,'P&G-SL'!$B6 ) -> 73349.64 | K6: =SUMIFS('i-sales'!$K:$K, 'i-sales'!$C:$C,'P&G-SL'!K$1, 'i-sales'!$D:$D,'P&G-SL'!$C6, 'i-sales'!$G:$G,'P&G-SL'!$A6, 'i-sales'!$H:$H,'P&G-SL'!$B6 ) -> 45991.32 | L6: =SUMIFS('i-sales'!$K:$K, 'i-sales'!$C:$C,'P&G-SL'!L$1, 'i-sales'!$D:$D,'P&G-SL'!$C6, 'i-sales'!$G:$G,'P&G-SL'!$A6, 'i-sales'!$H:$H,'P&G-SL'!$B6 ) -> 0 | M6: =SUMIFS('i-sales'!$K:$K, 'i-sales'!$C:$C,'P&G-SL'!M$1, 'i-sales'!$D:$D,'P&G-SL'!$C6, 'i-sales'!$G:$G,'P&G-SL'!$A6, 'i-sales'!$H:$H,'P&G-SL'!$B6 ) -> 0 | N6: =SUMIFS('i-sales'!$K:$K, 'i-sales'!$C:$C,'P&G-SL'!N$1, 'i-sales'!$D:$D,'P&G-SL'!$C6, 'i-sales'!$G:$G,'P&G-SL'!$A6, 'i-sales'!$H:$H,'P&G-SL'!$B6 ) -> 0 | O6: =SUMIFS('i-sales'!$K:$K, 'i-sales'!$C:$C,'P&G-SL'!O$1, 'i-sales'!$D:$D,'P&G-SL'!$C6, 'i-sales'!$G:$G,'P&G-SL'!$A6, 'i-sales'!$H:$H,'P&G-SL'!$B6 ) -> 0 | P6: =SUMIFS('i-sales'!$K:$K, 'i-sales'!$C:$C,'P&G-SL'!P$1, 'i-sales'!$D:$D,'P&G-SL'!$C6, 'i-sales'!$G:$G,'P&G-SL'!$A6, 'i-sales'!$H:$H,'P&G-SL'!$B6 ) -> 0 | ... T6: =SUMIFS('i-sales'!$K:$K, 'i-sales'!$C:$C,'P&G-SL'!T$1, 'i-sales'!$D:$D,'P&G-SL'!$C6, 'i-sales'!$G:$G,'P&G-SL'!$A6, 'i-sales'!$H:$H,'P&G-SL'!$B6 ) -> 0 | U6: =SUM(I6:T6) -> 180535.4
A7: 0 | B7: 0 | C7: DE | E7: #VALUE! | F7: Germany | I7: =SUMIFS('i-sales'!$K:$K, 'i-sales'!$C:$C,'P&G-SL'!I$1, 'i-sales'!$D:$D,'P&G-SL'!$C7, 'i-sales'!$G:$G,'P&G-SL'!$A7, 'i-sales'!$H:$H,'P&G-SL'!$B7 ) -> 20924.16 | J7: =SUMIFS('i-sales'!$K:$K, 'i-sales'!$C:$C,'P&G-SL'!J$1, 'i-sales'!$D:$D,'P&G-SL'!$C7, 'i-sales'!$G:$G,'P&G-SL'!$A7, 'i-sales'!$H:$H,'P&G-SL'!$B7 ) -> 19361.46 | K7: =SUMIFS('i-sales'!$K:$K, 'i-sales'!$C:$C,'P&G-SL'!K$1, 'i-sales'!$D:$D,'P&G-SL'!$C7, 'i-sales'!$G:$G,'P&G-SL'!$A7, 'i-sales'!$H:$H,'P&G-SL'!$B7 ) -> 15661.44 | L7: =SUMIFS('i-sales'!$K:$K, 'i-sales'!$C:$C,'P&G-SL'!L$1, 'i-sales'!$D:$D,'P&G-SL'!$C7, 'i-sales'!$G:$G,'P&G-SL'!$A7, 'i-sales'!$H:$H,'P&G-SL'!$B7 ) -> 0 | M7: =SUMIFS('i-sales'!$K:$K, 'i-sales'!$C:$C,'P&G-SL'!M$1, 'i-sales'!$D:$D,'P&G-SL'!$C7, 'i-sales'!$G:$G,'P&G-SL'!$A7, 'i-sales'!$H:$H,'P&G-SL'!$B7 ) -> 0 | N7: =SUMIFS('i-sales'!$K:$K, 'i-sales'!$C:$C,'P&G-SL'!N$1, 'i-sales'!$D:$D,'P&G-SL'!$C7, 'i-sales'!$G:$G,'P&G-SL'!$A7, 'i-sales'!$H:$H,'P&G-SL'!$B7 ) -> 0 | O7: =SUMIFS('i-sales'!$K:$K, 'i-sales'!$C:$C,'P&G-SL'!O$1, 'i-sales'!$D:$D,'P&G-SL'!$C7, 'i-sales'!$G:$G,'P&G-SL'!$A7, 'i-sales'!$H:$H,'P&G-SL'!$B7 ) -> 0 | P7: =SUMIFS('i-sales'!$K:$K, 'i-sales'!$C:$C,'P&G-SL'!P$1, 'i-sales'!$D:$D,'P&G-SL'!$C7, 'i-sales'!$G:$G,'P&G-SL'!$A7, 'i-sales'!$H:$H,'P&G-SL'!$B7 ) -> 0 | ... T7: =SUMIFS('i-sales'!$K:$K, 'i-sales'!$C:$C,'P&G-SL'!T$1, 'i-sales'!$D:$D,'P&G-SL'!$C7, 'i-sales'!$G:$G,'P&G-SL'!$A7, 'i-sales'!$H:$H,'P&G-SL'!$B7 ) -> 0 | U7: =SUM(I7:T7) -> 55947.06
A8: 0 | B8: 0 | C8: FR | E8: #VALUE! | F8: France | I8: =SUMIFS('i-sales'!$K:$K, 'i-sales'!$C:$C,'P&G-SL'!I$1, 'i-sales'!$D:$D,'P&G-SL'!$C8, 'i-sales'!$G:$G,'P&G-SL'!$A8, 'i-sales'!$H:$H,'P&G-SL'!$B8 ) -> 25590.35 | J8: =SUMIFS('i-sales'!$K:$K, 'i-sales'!$C:$C,'P&G-SL'!J$1, 'i-sales'!$D:$D,'P&G-SL'!$C8, 'i-sales'!$G:$G,'P&G-SL'!$A8, 'i-sales'!$H:$H,'P&G-SL'!$B8 ) -> 27502.64 | K8: =SUMIFS('i-sales'!$K:$K, 'i-sales'!$C:$C,'P&G-SL'!K$1, 'i-sales'!$D:$D,'P&G-SL'!$C8, 'i-sales'!$G:$G,'P&G-SL'!$A8, 'i-sales'!$H:$H,'P&G-SL'!$B8 ) -> 22172.28 | L8: =SUMIFS('i-sales'!$K:$K, 'i-sales'!$C:$C,'P&G-SL'!L$1, 'i-sales'!$D:$D,'P&G-SL'!$C8, 'i-sales'!$G:$G,'P&G-SL'!$A8, 'i-sales'!$H:$H,'P&G-SL'!$B8 ) -> 0 | M8: =SUMIFS('i-sales'!$K:$K, 'i-sales'!$C:$C,'P&G-SL'!M$1, 'i-sales'!$D:$D,'P&G-SL'!$C8, 'i-sales'!$G:$G,'P&G-SL'!$A8, 'i-sales'!$H:$H,'P&G-SL'!$B8 ) -> 0 | N8: =SUMIFS('i-sales'!$K:$K, 'i-sales'!$C:$C,'P&G-SL'!N$1, 'i-sales'!$D:$D,'P&G-SL'!$C8, 'i-sales'!$G:$G,'P&G-SL'!$A8, 'i-sales'!$H:$H,'P&G-SL'!$B8 ) -> 0 | O8: =SUMIFS('i-sales'!$K:$K, 'i-sales'!$C:$C,'P&G-SL'!O$1, 'i-sales'!$D:$D,'P&G-SL'!$C8, 'i-sales'!$G:$G,'P&G-SL'!$A8, 'i-sales'!$H:$H,'P&G-SL'!$B8 ) -> 0 | P8: =SUMIFS('i-sales'!$K:$K, 'i-sales'!$C:$C,'P&G-SL'!P$1, 'i-sales'!$D:$D,'P&G-SL'!$C8, 'i-sales'!$G:$G,'P&G-SL'!$A8, 'i-sales'!$H:$H,'P&G-SL'!$B8 ) -> 0 | ... T8: =SUMIFS('i-sales'!$K:$K, 'i-sales'!$C:$C,'P&G-SL'!T$1, 'i-sales'!$D:$D,'P&G-SL'!$C8, 'i-sales'!$G:$G,'P&G-SL'!$A8, 'i-sales'!$H:$H,'P&G-SL'!$B8 ) -> 0 | U8: =SUM(I8:T8) -> 75265.27
A9: 0 | B9: 0 | C9: IT | E9: #VALUE! | F9: Italy | I9: =SUMIFS('i-sales'!$K:$K, 'i-sales'!$C:$C,'P&G-SL'!I$1, 'i-sales'!$D:$D,'P&G-SL'!$C9, 'i-sales'!$G:$G,'P&G-SL'!$A9, 'i-sales'!$H:$H,'P&G-SL'!$B9 ) -> 18483.79 | J9: =SUMIFS('i-sales'!$K:$K, 'i-sales'!$C:$C,'P&G-SL'!J$1, 'i-sales'!$D:$D,'P&G-SL'!$C9, 'i-sales'!$G:$G,'P&G-SL'!$A9, 'i-sales'!$H:$H,'P&G-SL'!$B9 ) -> 20044.87 | K9: =SUMIFS('i-sales'!$K:$K, 'i-sales'!$C:$C,'P&G-SL'!K$1, 'i-sales'!$D:$D,'P&G-SL'!$C9, 'i-sales'!$G:$G,'P&G-SL'!$A9, 'i-sales'!$H:$H,'P&G-SL'!$B9 ) -> 10681.85 | L9: =SUMIFS('i-sales'!$K:$K, 'i-sales'!$C:$C,'P&G-SL'!L$1, 'i-sales'!$D:$D,'P&G-SL'!$C9, 'i-sales'!$G:$G,'P&G-SL'!$A9, 'i-sales'!$H:$H,'P&G-SL'!$B9 ) -> 0 | M9: =SUMIFS('i-sales'!$K:$K, 'i-sales'!$C:$C,'P&G-SL'!M$1, 'i-sales'!$D:$D,'P&G-SL'!$C9, 'i-sales'!$G:$G,'P&G-SL'!$A9, 'i-sales'!$H:$H,'P&G-SL'!$B9 ) -> 0 | N9: =SUMIFS('i-sales'!$K:$K, 'i-sales'!$C:$C,'P&G-SL'!N$1, 'i-sales'!$D:$D,'P&G-SL'!$C9, 'i-sales'!$G:$G,'P&G-SL'!$A9, 'i-sales'!$H:$H,'P&G-SL'!$B9 ) -> 0 | O9: =SUMIFS('i-sales'!$K:$K, 'i-sales'!$C:$C,'P&G-SL'!O$1, 'i-sales'!$D:$D,'P&G-SL'!$C9, 'i-sales'!$G:$G,'P&G-SL'!$A9, 'i-sales'!$H:$H,'P&G-SL'!$B9 ) -> 0 | P9: =SUMIFS('i-sales'!$K:$K, 'i-sales'!$C:$C,'P&G-SL'!P$1, 'i-sales'!$D:$D,'P&G-SL'!$C9, 'i-sales'!$G:$G,'P&G-SL'!$A9, 'i-sales'!$H:$H,'P&G-SL'!$B9 ) -> 0 | ... T9: =SUMIFS('i-sales'!$K:$K, 'i-sales'!$C:$C,'P&G-SL'!T$1, 'i-sales'!$D:$D,'P&G-SL'!$C9, 'i-sales'!$G:$G,'P&G-SL'!$A9, 'i-sales'!$H:$H,'P&G-SL'!$B9 ) -> 0 | U9: =SUM(I9:T9) -> 49210.51
A10: 0 | B10: 0 | C10: AT | E10: #VALUE! | F10: Austria | I10: =SUMIFS('i-sales'!$K:$K, 'i-sales'!$C:$C,'P&G-SL'!I$1, 'i-sales'!$D:$D,'P&G-SL'!$C10, 'i-sales'!$G:$G,'P&G-SL'!$A10, 'i-sales'!$H:$H,'P&G-SL'!$B10 ) -> 5482.24 | J10: =SUMIFS('i-sales'!$K:$K, 'i-sales'!$C:$C,'P&G-SL'!J$1, 'i-sales'!$D:$D,'P&G-SL'!$C10, 'i-sales'!$G:$G,'P&G-SL'!$A10, 'i-sales'!$H:$H,'P&G-SL'!$B10 ) -> 6077.94 | K10: =SUMIFS('i-sales'!$K:$K, 'i-sales'!$C:$C,'P&G-SL'!K$1, 'i-sales'!$D:$D,'P&G-SL'!$C10, 'i-sales'!$G:$G,'P&G-SL'!$A10, 'i-sales'!$H:$H,'P&G-SL'!$B10 ) -> 3577.39 | L10: =SUMIFS('i-sales'!$K:$K, 'i-sales'!$C:$C,'P&G-SL'!L$1, 'i-sales'!$D:$D,'P&G-SL'!$C10, 'i-sales'!$G:$G,'P&G-SL'!$A10, 'i-sales'!$H:$H,'P&G-SL'!$B10 ) -> 0 | M10: =SUMIFS('i-sales'!$K:$K, 'i-sales'!$C:$C,'P&G-SL'!M$1, 'i-sales'!$D:$D,'P&G-SL'!$C10, 'i-sales'!$G:$G,'P&G-SL'!$A10, 'i-sales'!$H:$H,'P&G-SL'!$B10 ) -> 0 | N10: =SUMIFS('i-sales'!$K:$K, 'i-sales'!$C:$C,'P&G-SL'!N$1, 'i-sales'!$D:$D,'P&G-SL'!$C10, 'i-sales'!$G:$G,'P&G-SL'!$A10, 'i-sales'!$H:$H,'P&G-SL'!$B10 ) -> 0 | O10: =SUMIFS('i-sales'!$K:$K, 'i-sales'!$C:$C,'P&G-SL'!O$1, 'i-sales'!$D:$D,'P&G-SL'!$C10, 'i-sales'!$G:$G,'P&G-SL'!$A10, 'i-sales'!$H:$H,'P&G-SL'!$B10 ) -> 0 | P10: =SUMIFS('i-sales'!$K:$K, 'i-sales'!$C:$C,'P&G-SL'!P$1, 'i-sales'!$D:$D,'P&G-SL'!$C10, 'i-sales'!$G:$G,'P&G-SL'!$A10, 'i-sales'!$H:$H,'P&G-SL'!$B10 ) -> 0 | ... T10: =SUMIFS('i-sales'!$K:$K, 'i-sales'!$C:$C,'P&G-SL'!T$1, 'i-sales'!$D:$D,'P&G-SL'!$C10, 'i-sales'!$G:$G,'P&G-SL'!$A10, 'i-sales'!$H:$H,'P&G-SL'!$B10 ) -> 0 | U10: =SUM(I10:T10) -> 15137.57
A11: 0 | B11: 0 | C11: BE | E11: #VALUE! | F11: Belgium | I11: =SUMIFS('i-sales'!$K:$K, 'i-sales'!$C:$C,'P&G-SL'!I$1, 'i-sales'!$D:$D,'P&G-SL'!$C11, 'i-sales'!$G:$G,'P&G-SL'!$A11, 'i-sales'!$H:$H,'P&G-SL'!$B11 ) -> 422.71 | J11: =SUMIFS('i-sales'!$K:$K, 'i-sales'!$C:$C,'P&G-SL'!J$1, 'i-sales'!$D:$D,'P&G-SL'!$C11, 'i-sales'!$G:$G,'P&G-SL'!$A11, 'i-sales'!$H:$H,'P&G-SL'!$B11 ) -> 998.68 | K11: =SUMIFS('i-sales'!$K:$K, 'i-sales'!$C:$C,'P&G-SL'!K$1, 'i-sales'!$D:$D,'P&G-SL'!$C11, 'i-sales'!$G:$G,'P&G-SL'!$A11, 'i-sales'!$H:$H,'P&G-SL'!$B11 ) -> 26.36 | L11: =SUMIFS('i-sales'!$K:$K, 'i-sales'!$C:$C,'P&G-SL'!L$1, 'i-sales'!$D:$D,'P&G-SL'!$C11, 'i-sales'!$G:$G,'P&G-SL'!$A11, 'i-sales'!$H:$H,'P&G-SL'!$B11 ) -> 0 | M11: =SUMIFS('i-sales'!$K:$K, 'i-sales'!$C:$C,'P&G-SL'!M$1, 'i-sales'!$D:$D,'P&G-SL'!$C11, 'i-sales'!$G:$G,'P&G-SL'!$A11, 'i-sales'!$H:$H,'P&G-SL'!$B11 ) -> 0 | N11: =SUMIFS('i-sales'!$K:$K, 'i-sales'!$C:$C,'P&G-SL'!N$1, 'i-sales'!$D:$D,'P&G-SL'!$C11, 'i-sales'!$G:$G,'P&G-SL'!$A11, 'i-sales'!$H:$H,'P&G-SL'!$B11 ) -> 0 | O11: =SUMIFS('i-sales'!$K:$K, 'i-sales'!$C:$C,'P&G-SL'!O$1, 'i-sales'!$D:$D,'P&G-SL'!$C11, 'i-sales'!$G:$G,'P&G-SL'!$A11, 'i-sales'!$H:$H,'P&G-SL'!$B11 ) -> 0 | P11: =SUMIFS('i-sales'!$K:$K, 'i-sales'!$C:$C,'P&G-SL'!P$1, 'i-sales'!$D:$D,'P&G-SL'!$C11, 'i-sales'!$G:$G,'P&G-SL'!$A11, 'i-sales'!$H:$H,'P&G-SL'!$B11 ) -> 0 | ... T11: =SUMIFS('i-sales'!$K:$K, 'i-sales'!$C:$C,'P&G-SL'!T$1, 'i-sales'!$D:$D,'P&G-SL'!$C11, 'i-sales'!$G:$G,'P&G-SL'!$A11, 'i-sales'!$H:$H,'P&G-SL'!$B11 ) -> 0 | U11: =SUM(I11:T11) -> 1447.75
A12: 0 | B12: 0 | C12: NL | E12: #VALUE! | F12: the Netherlands | I12: =SUMIFS('i-sales'!$K:$K, 'i-sales'!$C:$C,'P&G-SL'!I$1, 'i-sales'!$D:$D,'P&G-SL'!$C12, 'i-sales'!$G:$G,'P&G-SL'!$A12, 'i-sales'!$H:$H,'P&G-SL'!$B12 ) -> 115.58 | J12: =SUMIFS('i-sales'!$K:$K, 'i-sales'!$C:$C,'P&G-SL'!J$1, 'i-sales'!$D:$D,'P&G-SL'!$C12, 'i-sales'!$G:$G,'P&G-SL'!$A12, 'i-sales'!$H:$H,'P&G-SL'!$B12 ) -> 175.87 | K12: =SUMIFS('i-sales'!$K:$K, 'i-sales'!$C:$C,'P&G-SL'!K$1, 'i-sales'!$D:$D,'P&G-SL'!$C12, 'i-sales'!$G:$G,'P&G-SL'!$A12, 'i-sales'!$H:$H,'P&G-SL'!$B12 ) -> 39.59 | L12: =SUMIFS('i-sales'!$K:$K, 'i-sales'!$C:$C,'P&G-SL'!L$1, 'i-sales'!$D:$D,'P&G-SL'!$C12, 'i-sales'!$G:$G,'P&G-SL'!$A12, 'i-sales'!$H:$H,'P&G-SL'!$B12 ) -> 0 | M12: =SUMIFS('i-sales'!$K:$K, 'i-sales'!$C:$C,'P&G-SL'!M$1, 'i-sales'!$D:$D,'P&G-SL'!$C12, 'i-sales'!$G:$G,'P&G-SL'!$A12, 'i-sales'!$H:$H,'P&G-SL'!$B12 ) -> 0 | N12: =SUMIFS('i-sales'!$K:$K, 'i-sales'!$C:$C,'P&G-SL'!N$1, 'i-sales'!$D:$D,'P&G-SL'!$C12, 'i-sales'!$G:$G,'P&G-SL'!$A12, 'i-sales'!$H:$H,'P&G-SL'!$B12 ) -> 0 | O12: =SUMIFS('i-sales'!$K:$K, 'i-sales'!$C:$C,'P&G-SL'!O$1, 'i-sales'!$D:$D,'P&G-SL'!$C12, 'i-sales'!$G:$G,'P&G-SL'!$A12, 'i-sales'!$H:$H,'P&G-SL'!$B12 ) -> 0 | P12: =SUMIFS('i-sales'!$K:$K, 'i-sales'!$C:$C,'P&G-SL'!P$1, 'i-sales'!$D:$D,'P&G-SL'!$C12, 'i-sales'!$G:$G,'P&G-SL'!$A12, 'i-sales'!$H:$H,'P&G-SL'!$B12 ) -> 0 | ... T12: =SUMIFS('i-sales'!$K:$K, 'i-sales'!$C:$C,'P&G-SL'!T$1, 'i-sales'!$D:$D,'P&G-SL'!$C12, 'i-sales'!$G:$G,'P&G-SL'!$A12, 'i-sales'!$H:$H,'P&G-SL'!$B12 ) -> 0 | U12: =SUM(I12:T12) -> 331.04
A13: 0 | B13: 0 | C13: PT | E13: #VALUE! | F13: Portugal | I13: =SUMIFS('i-sales'!$K:$K, 'i-sales'!$C:$C,'P&G-SL'!I$1, 'i-sales'!$D:$D,'P&G-SL'!$C13, 'i-sales'!$G:$G,'P&G-SL'!$A13, 'i-sales'!$H:$H,'P&G-SL'!$B13 ) -> 729.31 | J13: =SUMIFS('i-sales'!$K:$K, 'i-sales'!$C:$C,'P&G-SL'!J$1, 'i-sales'!$D:$D,'P&G-SL'!$C13, 'i-sales'!$G:$G,'P&G-SL'!$A13, 'i-sales'!$H:$H,'P&G-SL'!$B13 ) -> 1281.5 | K13: =SUMIFS('i-sales'!$K:$K, 'i-sales'!$C:$C,'P&G-SL'!K$1, 'i-sales'!$D:$D,'P&G-SL'!$C13, 'i-sales'!$G:$G,'P&G-SL'!$A13, 'i-sales'!$H:$H,'P&G-SL'!$B13 ) -> 0 | L13: =SUMIFS('i-sales'!$K:$K, 'i-sales'!$C:$C,'P&G-SL'!L$1, 'i-sales'!$D:$D,'P&G-SL'!$C13, 'i-sales'!$G:$G,'P&G-SL'!$A13, 'i-sales'!$H:$H,'P&G-SL'!$B13 ) -> 0 | M13: =SUMIFS('i-sales'!$K:$K, 'i-sales'!$C:$C,'P&G-SL'!M$1, 'i-sales'!$D:$D,'P&G-SL'!$C13, 'i-sales'!$G:$G,'P&G-SL'!$A13, 'i-sales'!$H:$H,'P&G-SL'!$B13 ) -> 0 | N13: =SUMIFS('i-sales'!$K:$K, 'i-sales'!$C:$C,'P&G-SL'!N$1, 'i-sales'!$D:$D,'P&G-SL'!$C13, 'i-sales'!$G:$G,'P&G-SL'!$A13, 'i-sales'!$H:$H,'P&G-SL'!$B13 ) -> 0 | O13: =SUMIFS('i-sales'!$K:$K, 'i-sales'!$C:$C,'P&G-SL'!O$1, 'i-sales'!$D:$D,'P&G-SL'!$C13, 'i-sales'!$G:$G,'P&G-SL'!$A13, 'i-sales'!$H:$H,'P&G-SL'!$B13 ) -> 0 | P13: =SUMIFS('i-sales'!$K:$K, 'i-sales'!$C:$C,'P&G-SL'!P$1, 'i-sales'!$D:$D,'P&G-SL'!$C13, 'i-sales'!$G:$G,'P&G-SL'!$A13, 'i-sales'!$H:$H,'P&G-SL'!$B13 ) -> 0 | ... T13: =SUMIFS('i-sales'!$K:$K, 'i-sales'!$C:$C,'P&G-SL'!T$1, 'i-sales'!$D:$D,'P&G-SL'!$C13, 'i-sales'!$G:$G,'P&G-SL'!$A13, 'i-sales'!$H:$H,'P&G-SL'!$B13 ) -> 0 | U13: =SUM(I13:T13) -> 2010.81
A14: 0 | B14: 0 | C14: XX | E14: #VALUE! | F14: Other markets | I14: =SUMIFS('i-sales'!$K:$K, 'i-sales'!$C:$C,'P&G-SL'!I$1, 'i-sales'!$D:$D,'P&G-SL'!$C14, 'i-sales'!$G:$G,'P&G-SL'!$A14, 'i-sales'!$H:$H,'P&G-SL'!$B14 ) -> 691.19 | J14: =SUMIFS('i-sales'!$K:$K, 'i-sales'!$C:$C,'P&G-SL'!J$1, 'i-sales'!$D:$D,'P&G-SL'!$C14, 'i-sales'!$G:$G,'P&G-SL'!$A14, 'i-sales'!$H:$H,'P&G-SL'!$B14 ) -> 264.48 | K14: =SUMIFS('i-sales'!$K:$K, 'i-sales'!$C:$C,'P&G-SL'!K$1, 'i-sales'!$D:$D,'P&G-SL'!$C14, 'i-sales'!$G:$G,'P&G-SL'!$A14, 'i-sales'!$H:$H,'P&G-SL'!$B14 ) -> 227.22 | L14: =SUMIFS('i-sales'!$K:$K, 'i-sales'!$C:$C,'P&G-SL'!L$1, 'i-sales'!$D:$D,'P&G-SL'!$C14, 'i-sales'!$G:$G,'P&G-SL'!$A14, 'i-sales'!$H:$H,'P&G-SL'!$B14 ) -> 0 | M14: =SUMIFS('i-sales'!$K:$K, 'i-sales'!$C:$C,'P&G-SL'!M$1, 'i-sales'!$D:$D,'P&G-SL'!$C14, 'i-sales'!$G:$G,'P&G-SL'!$A14, 'i-sales'!$H:$H,'P&G-SL'!$B14 ) -> 0 | N14: =SUMIFS('i-sales'!$K:$K, 'i-sales'!$C:$C,'P&G-SL'!N$1, 'i-sales'!$D:$D,'P&G-SL'!$C14, 'i-sales'!$G:$G,'P&G-SL'!$A14, 'i-sales'!$H:$H,'P&G-SL'!$B14 ) -> 0 | O14: =SUMIFS('i-sales'!$K:$K, 'i-sales'!$C:$C,'P&G-SL'!O$1, 'i-sales'!$D:$D,'P&G-SL'!$C14, 'i-sales'!$G:$G,'P&G-SL'!$A14, 'i-sales'!$H:$H,'P&G-SL'!$B14 ) -> 0 | P14: =SUMIFS('i-sales'!$K:$K, 'i-sales'!$C:$C,'P&G-SL'!P$1, 'i-sales'!$D:$D,'P&G-SL'!$C14, 'i-sales'!$G:$G,'P&G-SL'!$A14, 'i-sales'!$H:$H,'P&G-SL'!$B14 ) -> 0 | ... T14: =SUMIFS('i-sales'!$K:$K, 'i-sales'!$C:$C,'P&G-SL'!T$1, 'i-sales'!$D:$D,'P&G-SL'!$C14, 'i-sales'!$G:$G,'P&G-SL'!$A14, 'i-sales'!$H:$H,'P&G-SL'!$B14 ) -> 0 | U14: =SUM(I14:T14) -> 1182.89
E16: Marketplaces | I16: =SUM(I17:I19) -> 1419.7 | J16: =SUM(J17:J19) -> 2875.02 | K16: =SUM(K17:K19) -> 15609.96 | L16: =SUM(L17:L19) -> 0 | M16: =SUM(M17:M19) -> 0 | N16: =SUM(N17:N19) -> 0 | O16: =SUM(O17:O19) -> 0 | P16: =SUM(P17:P19) -> 0 | ... T16: =SUM(T17:T19) -> 0 | U16: =SUM(I16:T16) -> 19904.68
E17: H | F17: Hannun | I17: =SUMIFS(i_marketplaces_sl[[net]:[net]],i_marketplaces_sl[[yyyymm]:[yyyymm]],I$1,i_marketplaces_sl[[client_name]:[client_name]],$F17) -> 1419.7 | J17: =SUMIFS(i_marketplaces_sl[[net]:[net]],i_marketplaces_sl[[yyyymm]:[yyyymm]],J$1,i_marketplaces_sl[[client_name]:[client_name]],$F17) -> 1128.42 | K17: =SUMIFS(i_marketplaces_sl[[net]:[net]],i_marketplaces_sl[[yyyymm]:[yyyymm]],K$1,i_marketplaces_sl[[client_name]:[client_name]],$F17) -> 0 | L17: =SUMIFS(i_marketplaces_sl[[net]:[net]],i_marketplaces_sl[[yyyymm]:[yyyymm]],L$1,i_marketplaces_sl[[client_name]:[client_name]],$F17) -> 0 | M17: =SUMIFS(i_marketplaces_sl[[net]:[net]],i_marketplaces_sl[[yyyymm]:[yyyymm]],M$1,i_marketplaces_sl[[client_name]:[client_name]],$F17) -> 0 | N17: =SUMIFS(i_marketplaces_sl[[net]:[net]],i_marketplaces_sl[[yyyymm]:[yyyymm]],N$1,i_marketplaces_sl[[client_name]:[client_name]],$F17) -> 0 | O17: =SUMIFS(i_marketplaces_sl[[net]:[net]],i_marketplaces_sl[[yyyymm]:[yyyymm]],O$1,i_marketplaces_sl[[client_name]:[client_name]],$F17) -> 0 | P17: =SUMIFS(i_marketplaces_sl[[net]:[net]],i_marketplaces_sl[[yyyymm]:[yyyymm]],P$1,i_marketplaces_sl[[client_name]:[client_name]],$F17) -> 0 | ... T17: =SUMIFS(i_marketplaces_sl[[net]:[net]],i_marketplaces_sl[[yyyymm]:[yyyymm]],T$1,i_marketplaces_sl[[client_name]:[client_name]],$F17) -> 0 | U17: =SUM(I17:T17) -> 2548.12
E18: #VALUE! | F18: Choose | I18: =SUMIFS(i_marketplaces_sl[[net]:[net]],i_marketplaces_sl[[yyyymm]:[yyyymm]],I$1,i_marketplaces_sl[[client_name]:[client_name]],$F18) -> 0 | J18: =SUMIFS(i_marketplaces_sl[[net]:[net]],i_marketplaces_sl[[yyyymm]:[yyyymm]],J$1,i_marketplaces_sl[[client_name]:[client_name]],$F18) -> 0 | K18: =SUMIFS(i_marketplaces_sl[[net]:[net]],i_marketplaces_sl[[yyyymm]:[yyyymm]],K$1,i_marketplaces_sl[[client_name]:[client_name]],$F18) -> 15609.96 | L18: =SUMIFS(i_marketplaces_sl[[net]:[net]],i_marketplaces_sl[[yyyymm]:[yyyymm]],L$1,i_marketplaces_sl[[client_name]:[client_name]],$F18) -> 0 | M18: =SUMIFS(i_marketplaces_sl[[net]:[net]],i_marketplaces_sl[[yyyymm]:[yyyymm]],M$1,i_marketplaces_sl[[client_name]:[client_name]],$F18) -> 0 | N18: =SUMIFS(i_marketplaces_sl[[net]:[net]],i_marketplaces_sl[[yyyymm]:[yyyymm]],N$1,i_marketplaces_sl[[client_name]:[client_name]],$F18) -> 0 | O18: =SUMIFS(i_marketplaces_sl[[net]:[net]],i_marketplaces_sl[[yyyymm]:[yyyymm]],O$1,i_marketplaces_sl[[client_name]:[client_name]],$F18) -> 0 | P18: =SUMIFS(i_marketplaces_sl[[net]:[net]],i_marketplaces_sl[[yyyymm]:[yyyymm]],P$1,i_marketplaces_sl[[client_name]:[client_name]],$F18) -> 0 | ... T18: =SUMIFS(i_marketplaces_sl[[net]:[net]],i_marketplaces_sl[[yyyymm]:[yyyymm]],T$1,i_marketplaces_sl[[client_name]:[client_name]],$F18) -> 0 | U18: =SUM(I18:T18) -> 15609.96
E19: #VALUE! | F19: Toasty | I19: =SUMIFS(i_marketplaces_sl[[net]:[net]],i_marketplaces_sl[[yyyymm]:[yyyymm]],I$1,i_marketplaces_sl[[client_name]:[client_name]],$F19) -> 0 | J19: =SUMIFS(i_marketplaces_sl[[net]:[net]],i_marketplaces_sl[[yyyymm]:[yyyymm]],J$1,i_marketplaces_sl[[client_name]:[client_name]],$F19) -> 1746.6 | K19: =SUMIFS(i_marketplaces_sl[[net]:[net]],i_marketplaces_sl[[yyyymm]:[yyyymm]],K$1,i_marketplaces_sl[[client_name]:[client_name]],$F19) -> 0 | L19: =SUMIFS(i_marketplaces_sl[[net]:[net]],i_marketplaces_sl[[yyyymm]:[yyyymm]],L$1,i_marketplaces_sl[[client_name]:[client_name]],$F19) -> 0 | M19: =SUMIFS(i_marketplaces_sl[[net]:[net]],i_marketplaces_sl[[yyyymm]:[yyyymm]],M$1,i_marketplaces_sl[[client_name]:[client_name]],$F19) -> 0 | N19: =SUMIFS(i_marketplaces_sl[[net]:[net]],i_marketplaces_sl[[yyyymm]:[yyyymm]],N$1,i_marketplaces_sl[[client_name]:[client_name]],$F19) -> 0 | O19: =SUMIFS(i_marketplaces_sl[[net]:[net]],i_marketplaces_sl[[yyyymm]:[yyyymm]],O$1,i_marketplaces_sl[[client_name]:[client_name]],$F19) -> 0 | P19: =SUMIFS(i_marketplaces_sl[[net]:[net]],i_marketplaces_sl[[yyyymm]:[yyyymm]],P$1,i_marketplaces_sl[[client_name]:[client_name]],$F19) -> 0 | ... T19: =SUMIFS(i_marketplaces_sl[[net]:[net]],i_marketplaces_sl[[yyyymm]:[yyyymm]],T$1,i_marketplaces_sl[[client_name]:[client_name]],$F19) -> 0 | U19: =SUM(I19:T19) -> 1746.6
E21: Rever Supplies | I21: =SUMIFS(i_suplidos_sl[[net]:[net]],i_suplidos_sl[[yyyymm]:[yyyymm]],I$1) -> -2176.46 | J21: =SUMIFS(i_suplidos_sl[[net]:[net]],i_suplidos_sl[[yyyymm]:[yyyymm]],J$1) -> -522.54 | K21: =SUMIFS(i_suplidos_sl[[net]:[net]],i_suplidos_sl[[yyyymm]:[yyyymm]],K$1) -> 0 | L21: =SUMIFS(i_suplidos_sl[[net]:[net]],i_suplidos_sl[[yyyymm]:[yyyymm]],L$1) -> 0 | M21: =SUMIFS(i_suplidos_sl[[net]:[net]],i_suplidos_sl[[yyyymm]:[yyyymm]],M$1) -> 0 | N21: =SUMIFS(i_suplidos_sl[[net]:[net]],i_suplidos_sl[[yyyymm]:[yyyymm]],N$1) -> 0 | O21: =SUMIFS(i_suplidos_sl[[net]:[net]],i_suplidos_sl[[yyyymm]:[yyyymm]],O$1) -> 0 | P21: =SUMIFS(i_suplidos_sl[[net]:[net]],i_suplidos_sl[[yyyymm]:[yyyymm]],P$1) -> 0 | ... T21: =SUMIFS(i_suplidos_sl[[net]:[net]],i_suplidos_sl[[yyyymm]:[yyyymm]],T$1) -> 0
E23: Sales Rappels (B2B) | I23: =SUMIFS(i_rapels_sl[[net]:[net]],i_rapels_sl[[yyyymm]:[yyyymm]],I$1) -> -1118.95 | J23: =SUMIFS(i_rapels_sl[[net]:[net]],i_rapels_sl[[yyyymm]:[yyyymm]],J$1) -> 0 | K23: =SUMIFS(i_rapels_sl[[net]:[net]],i_rapels_sl[[yyyymm]:[yyyymm]],K$1) -> 0 | L23: =SUMIFS(i_rapels_sl[[net]:[net]],i_rapels_sl[[yyyymm]:[yyyymm]],L$1) -> 0 | M23: =SUMIFS(i_rapels_sl[[net]:[net]],i_rapels_sl[[yyyymm]:[yyyymm]],M$1) -> 0 | N23: =SUMIFS(i_rapels_sl[[net]:[net]],i_rapels_sl[[yyyymm]:[yyyymm]],N$1) -> 0 | O23: =SUMIFS(i_rapels_sl[[net]:[net]],i_rapels_sl[[yyyymm]:[yyyymm]],O$1) -> 0 | P23: =SUMIFS(i_rapels_sl[[net]:[net]],i_rapels_sl[[yyyymm]:[yyyymm]],P$1) -> 0 | ... T23: =SUMIFS(i_rapels_sl[[net]:[net]],i_rapels_sl[[yyyymm]:[yyyymm]],T$1) -> 0 | U23: =SUM(I23:T23) -> -1118.95
E25: Sales Adjustments | I25: =SUM(I26:I28) -> 23.483436 | J25: =SUM(J26:J28) -> -152.16827 | K25: =SUM(K26:K28) -> 0 | L25: =SUM(L26:L28) -> 0 | M25: =SUM(M26:M28) -> 0 | N25: =SUM(N26:N28) -> 0 | O25: =SUM(O26:O28) -> 0 | P25: =SUM(P26:P28) -> 0 | ... T25: =SUM(T26:T28) -> 0 | U25: =SUM(I25:T25) -> -128.68484
F26: Chargeback Shopify | I26: =SUMIFS(i_adjustments_sl[[net]:[net]],i_adjustments_sl[[yyyymm]:[yyyymm]],I$1,i_adjustments_sl[[type]:[type]],$F26) -> -97.252101 | J26: =SUMIFS(i_adjustments_sl[[net]:[net]],i_adjustments_sl[[yyyymm]:[yyyymm]],J$1,i_adjustments_sl[[type]:[type]],$F26) -> 47.823529 | K26: =SUMIFS(i_adjustments_sl[[net]:[net]],i_adjustments_sl[[yyyymm]:[yyyymm]],K$1,i_adjustments_sl[[type]:[type]],$F26) -> 0 | L26: =SUMIFS(i_adjustments_sl[[net]:[net]],i_adjustments_sl[[yyyymm]:[yyyymm]],L$1,i_adjustments_sl[[type]:[type]],$F26) -> 0 | M26: =SUMIFS(i_adjustments_sl[[net]:[net]],i_adjustments_sl[[yyyymm]:[yyyymm]],M$1,i_adjustments_sl[[type]:[type]],$F26) -> 0 | N26: =SUMIFS(i_adjustments_sl[[net]:[net]],i_adjustments_sl[[yyyymm]:[yyyymm]],N$1,i_adjustments_sl[[type]:[type]],$F26) -> 0 | O26: =SUMIFS(i_adjustments_sl[[net]:[net]],i_adjustments_sl[[yyyymm]:[yyyymm]],O$1,i_adjustments_sl[[type]:[type]],$F26) -> 0 | P26: =SUMIFS(i_adjustments_sl[[net]:[net]],i_adjustments_sl[[yyyymm]:[yyyymm]],P$1,i_adjustments_sl[[type]:[type]],$F26) -> 0 | ... T26: =SUMIFS(i_adjustments_sl[[net]:[net]],i_adjustments_sl[[yyyymm]:[yyyymm]],T$1,i_adjustments_sl[[type]:[type]],$F26) -> 0 | U26: =SUM(I26:T26) -> -49.428571
F27: Chargeback Paypal | I27: =SUMIFS(i_adjustments_sl[[net]:[net]],i_adjustments_sl[[yyyymm]:[yyyymm]],I$1,i_adjustments_sl[[type]:[type]],$F27) -> 120.73554 | J27: =SUMIFS(i_adjustments_sl[[net]:[net]],i_adjustments_sl[[yyyymm]:[yyyymm]],J$1,i_adjustments_sl[[type]:[type]],$F27) -> -199.9918 | K27: =SUMIFS(i_adjustments_sl[[net]:[net]],i_adjustments_sl[[yyyymm]:[yyyymm]],K$1,i_adjustments_sl[[type]:[type]],$F27) -> 0 | L27: =SUMIFS(i_adjustments_sl[[net]:[net]],i_adjustments_sl[[yyyymm]:[yyyymm]],L$1,i_adjustments_sl[[type]:[type]],$F27) -> 0 | M27: =SUMIFS(i_adjustments_sl[[net]:[net]],i_adjustments_sl[[yyyymm]:[yyyymm]],M$1,i_adjustments_sl[[type]:[type]],$F27) -> 0 | N27: =SUMIFS(i_adjustments_sl[[net]:[net]],i_adjustments_sl[[yyyymm]:[yyyymm]],N$1,i_adjustments_sl[[type]:[type]],$F27) -> 0 | O27: =SUMIFS(i_adjustments_sl[[net]:[net]],i_adjustments_sl[[yyyymm]:[yyyymm]],O$1,i_adjustments_sl[[type]:[type]],$F27) -> 0 | P27: =SUMIFS(i_adjustments_sl[[net]:[net]],i_adjustments_sl[[yyyymm]:[yyyymm]],P$1,i_adjustments_sl[[type]:[type]],$F27) -> 0 | ... T27: =SUMIFS(i_adjustments_sl[[net]:[net]],i_adjustments_sl[[yyyymm]:[yyyymm]],T$1,i_adjustments_sl[[type]:[type]],$F27) -> 0 | U27: =SUM(I27:T27) -> -79.256266
F28: Impagos | I28: =SUMIFS(i_adjustments_sl[[net]:[net]],i_adjustments_sl[[yyyymm]:[yyyymm]],I$1,i_adjustments_sl[[type]:[type]],$F28) -> 0 | J28: =SUMIFS(i_adjustments_sl[[net]:[net]],i_adjustments_sl[[yyyymm]:[yyyymm]],J$1,i_adjustments_sl[[type]:[type]],$F28) -> 0 | K28: =SUMIFS(i_adjustments_sl[[net]:[net]],i_adjustments_sl[[yyyymm]:[yyyymm]],K$1,i_adjustments_sl[[type]:[type]],$F28) -> 0 | L28: =SUMIFS(i_adjustments_sl[[net]:[net]],i_adjustments_sl[[yyyymm]:[yyyymm]],L$1,i_adjustments_sl[[type]:[type]],$F28) -> 0 | M28: =SUMIFS(i_adjustments_sl[[net]:[net]],i_adjustments_sl[[yyyymm]:[yyyymm]],M$1,i_adjustments_sl[[type]:[type]],$F28) -> 0 | N28: =SUMIFS(i_adjustments_sl[[net]:[net]],i_adjustments_sl[[yyyymm]:[yyyymm]],N$1,i_adjustments_sl[[type]:[type]],$F28) -> 0 | O28: =SUMIFS(i_adjustments_sl[[net]:[net]],i_adjustments_sl[[yyyymm]:[yyyymm]],O$1,i_adjustments_sl[[type]:[type]],$F28) -> 0 | P28: =SUMIFS(i_adjustments_sl[[net]:[net]],i_adjustments_sl[[yyyymm]:[yyyymm]],P$1,i_adjustments_sl[[type]:[type]],$F28) -> 0 | ... T28: =SUMIFS(i_adjustments_sl[[net]:[net]],i_adjustments_sl[[yyyymm]:[yyyymm]],T$1,i_adjustments_sl[[type]:[type]],$F28) -> 0 | U28: =SUM(I28:T28) -> 0
D30: PRESTACION SERVICIOS | I30: =+I31 -> 20919.65 | J30: =+J31 -> 22722.52 | K30: =+K31 -> 0 | L30: =+L31 -> 0 | M30: =+M31 -> 0 | N30: =+N31 -> 0 | O30: =+O31 -> 0 | P30: =+P31 -> 0 | ... T30: =+T31 -> 0 | U30: =SUM(I30:T30) -> 43642.17
E31: Shared Services | I31: =+I37+I45+I48 -> 20919.65 | J31: =+J37+J45+J48 -> 22722.52 | K31: =+K37+K45+K48 -> 0 | L31: =+L37+L45+L48 -> 0 | M31: =+M37+M45+M48 -> 0 | N31: =+N37+N45+N48 -> 0 | O31: =+O37+O45+O48 -> 0 | P31: =+P37+P45+P48 -> 0 | ... T31: =+T37+T45+T48 -> 0 | U31: =SUM(I31:T31) -> 43642.17
E32: #VALUE! | F32: UK € - Theorical | I32: =SUM(I33:I36) -> 11560.246 | J32: =SUM(J33:J36) -> 13751.863 | K32: =SUM(K33:K36) -> 0 | L32: =SUM(L33:L36) -> 0 | M32: =SUM(M33:M36) -> 0 | N32: =SUM(N33:N36) -> 0 | O32: =SUM(O33:O36) -> 0 | P32: =SUM(P33:P36) -> 0 | ... T32: =SUM(T33:T36) -> 0 | U32: =SUM(I32:T32) -> 25312.109
G33: Royalties (Real) | I33: =+I72 -> 1272 | J33: =+J72 -> 1596 | K33: =+K72 -> 0 | L33: =+L72 -> 0 | M33: =+M72 -> 0 | N33: =+N72 -> 0 | O33: =+O72 -> 0 | P33: =+P72 -> 0 | ... T33: =+T72 -> 0 | U33: =SUM(I33:T33) -> 2868
G34: Staff (20%) | I34: =+I109 -> 2946.368 | J34: =+J109 -> 2983.136 | K34: =+K109 -> 0 | L34: =+L109 -> 0 | M34: =+M109 -> 0 | N34: =+N109 -> 0 | O34: =+O109 -> 0 | P34: =+P109 -> 0 | ... T34: =+T109 -> 0 | U34: =SUM(I34:T34) -> 5929.504
G35: Marketing (Real) | I35: =+I95 -> 6005.65 | J35: =+J95 -> 7802.34 | K35: =+K95 -> 0 | L35: =+L95 -> 0 | M35: =+M95 -> 0 | N35: =+N95 -> 0 | O35: =+O95 -> 0 | P35: =+P95 -> 0 | ... T35: =+T95 -> 0 | U35: =SUM(I35:T35) -> 13807.99
G36: Administrative (20%) | I36: =+I142 -> 1336.228 | J36: =+J142 -> 1370.3873 | K36: =+K142 -> 0 | L36: =+L142 -> 0 | M36: =+M142 -> 0 | N36: =+N142 -> 0 | O36: =+O142 -> 0 | P36: =+P142 -> 0 | ... T36: =+T142 -> 0 | U36: =SUM(I36:T36) -> 2706.6153
E37: #VALUE! | F37: UK € - Invoice | I37: =SUMIFS(i_sharedservices_sl[[net]:[net]],i_sharedservices_sl[[yyyymm]:[yyyymm]],I$1,i_sharedservices_sl[[type]:[type]],LEFT($F$37,2)) -> 10732.87 | J37: =SUMIFS(i_sharedservices_sl[[net]:[net]],i_sharedservices_sl[[yyyymm]:[yyyymm]],J$1,i_sharedservices_sl[[type]:[type]],LEFT($F$37,2)) -> 13068.98 | K37: =SUMIFS(i_sharedservices_sl[[net]:[net]],i_sharedservices_sl[[yyyymm]:[yyyymm]],K$1,i_sharedservices_sl[[type]:[type]],LEFT($F$37,2)) -> 0 | L37: =SUMIFS(i_sharedservices_sl[[net]:[net]],i_sharedservices_sl[[yyyymm]:[yyyymm]],L$1,i_sharedservices_sl[[type]:[type]],LEFT($F$37,2)) -> 0 | M37: =SUMIFS(i_sharedservices_sl[[net]:[net]],i_sharedservices_sl[[yyyymm]:[yyyymm]],M$1,i_sharedservices_sl[[type]:[type]],LEFT($F$37,2)) -> 0 | N37: =SUMIFS(i_sharedservices_sl[[net]:[net]],i_sharedservices_sl[[yyyymm]:[yyyymm]],N$1,i_sharedservices_sl[[type]:[type]],LEFT($F$37,2)) -> 0 | O37: =SUMIFS(i_sharedservices_sl[[net]:[net]],i_sharedservices_sl[[yyyymm]:[yyyymm]],O$1,i_sharedservices_sl[[type]:[type]],LEFT($F$37,2)) -> 0 | P37: =SUMIFS(i_sharedservices_sl[[net]:[net]],i_sharedservices_sl[[yyyymm]:[yyyymm]],P$1,i_sharedservices_sl[[type]:[type]],LEFT($F$37,2)) -> 0 | ... T37: =SUMIFS(i_sharedservices_sl[[net]:[net]],i_sharedservices_sl[[yyyymm]:[yyyymm]],T$1,i_sharedservices_sl[[type]:[type]],LEFT($F$37,2)) -> 0 | U37: =SUM(I37:T37) -> 23801.85
F38: UK £ - Invoice | I38: =+I37/exchange_rates!$B2 -> 9332.9304 | J38: =+J37/exchange_rates!$B2 -> 11364.33 | K38: =+K37/exchange_rates!$B2 -> 0 | L38: =+L37/exchange_rates!$B2 -> 0 | M38: =+M37/exchange_rates!$B2 -> 0 | N38: =+N37/exchange_rates!$B2 -> 0 | O38: =+O37/exchange_rates!$B2 -> 0 | P38: =+P37/exchange_rates!$B2 -> 0 | ... T38: =+T37/exchange_rates!$B2 -> 0 | U38: =SUM(I38:T38) -> 20697.261
E40: #VALUE! | F40: US € - Theorical | I40: =SUM(I41:I44) -> 7344.8521 | J40: =SUM(J41:J44) -> 8501.744 | K40: =SUM(K41:K44) -> 0 | L40: =SUM(L41:L44) -> 0 | M40: =SUM(M41:M44) -> 0 | N40: =SUM(N41:N44) -> 0 | O40: =SUM(O41:O44) -> 0 | P40: =SUM(P41:P44) -> 0 | ... T40: =SUM(T41:T44) -> 0 | U40: =SUM(I40:T40) -> 15846.596
G41: Royalties (Real) | I41: =+I73 -> 471 | J41: =+J73 -> 744 | K41: =+K73 -> 0 | L41: =+L73 -> 0 | M41: =+M73 -> 0 | N41: =+N73 -> 0 | O41: =+O73 -> 0 | P41: =+P73 -> 0 | ... T41: =+T73 -> 0 | U41: =SUM(I41:T41) -> 1215
G42: Staff (20%) | I42: =+I110 -> 2946.368 | J42: =+J110 -> 2983.136 | K42: =+K110 -> 0 | L42: =+L110 -> 0 | M42: =+M110 -> 0 | N42: =+N110 -> 0 | O42: =+O110 -> 0 | P42: =+P110 -> 0 | ... T42: =+T110 -> 0 | U42: =SUM(I42:T42) -> 5929.504
G43: Marketing (Real) | I43: =+I98 -> 3899.81 | J43: =+J98 -> 4744.08 | K43: =+K98 -> 0 | L43: =+L98 -> 0 | M43: =+M98 -> 0 | N43: =+N98 -> 0 | O43: =+O98 -> 0 | P43: =+P98 -> 0 | ... T43: =+T98 -> 0 | U43: =SUM(I43:T43) -> 8643.89
G44: Administrative (20%) | I44: =+I143 -> 27.6741 | J44: =+J143 -> 30.528 | K44: =+K143 -> 0 | L44: =+L143 -> 0 | M44: =+M143 -> 0 | N44: =+N143 -> 0 | O44: =+O143 -> 0 | P44: =+P143 -> 0 | ... T44: =+T143 -> 0 | U44: =SUM(I44:T44) -> 58.2021
E45: #VALUE! | F45: US € - Invoice | I45: =SUMIFS(i_sharedservices_sl[[net]:[net]],i_sharedservices_sl[[yyyymm]:[yyyymm]],I$1,i_sharedservices_sl[[type]:[type]],LEFT($F$45,2)) -> 7334.44 | J45: =SUMIFS(i_sharedservices_sl[[net]:[net]],i_sharedservices_sl[[yyyymm]:[yyyymm]],J$1,i_sharedservices_sl[[type]:[type]],LEFT($F$45,2)) -> 8462.36 | K45: =SUMIFS(i_sharedservices_sl[[net]:[net]],i_sharedservices_sl[[yyyymm]:[yyyymm]],K$1,i_sharedservices_sl[[type]:[type]],LEFT($F$45,2)) -> 0 | L45: =SUMIFS(i_sharedservices_sl[[net]:[net]],i_sharedservices_sl[[yyyymm]:[yyyymm]],L$1,i_sharedservices_sl[[type]:[type]],LEFT($F$45,2)) -> 0 | M45: =SUMIFS(i_sharedservices_sl[[net]:[net]],i_sharedservices_sl[[yyyymm]:[yyyymm]],M$1,i_sharedservices_sl[[type]:[type]],LEFT($F$45,2)) -> 0 | N45: =SUMIFS(i_sharedservices_sl[[net]:[net]],i_sharedservices_sl[[yyyymm]:[yyyymm]],N$1,i_sharedservices_sl[[type]:[type]],LEFT($F$45,2)) -> 0 | O45: =SUMIFS(i_sharedservices_sl[[net]:[net]],i_sharedservices_sl[[yyyymm]:[yyyymm]],O$1,i_sharedservices_sl[[type]:[type]],LEFT($F$45,2)) -> 0 | P45: =SUMIFS(i_sharedservices_sl[[net]:[net]],i_sharedservices_sl[[yyyymm]:[yyyymm]],P$1,i_sharedservices_sl[[type]:[type]],LEFT($F$45,2)) -> 0 | ... T45: =SUMIFS(i_sharedservices_sl[[net]:[net]],i_sharedservices_sl[[yyyymm]:[yyyymm]],T$1,i_sharedservices_sl[[type]:[type]],LEFT($F$45,2)) -> 0 | U45: =SUM(I45:T45) -> 15796.8
F46: US $ - Invoice | I46: =IFERROR(+I45/exchange_rates!B$3,0) -> 8731.4762 | J46: =IFERROR(+J45/exchange_rates!C$3,0) -> 9955.7176 | K46: =IFERROR(+K45/exchange_rates!D$3,0) -> 0 | L46: =IFERROR(+L45/exchange_rates!E$3,0) -> 0 | M46: =IFERROR(+M45/exchange_rates!F$3,0) -> 0 | N46: =IFERROR(+N45/exchange_rates!G$3,0) -> 0 | O46: =IFERROR(+O45/exchange_rates!H$3,0) -> 0 | P46: =IFERROR(+P45/exchange_rates!I$3,0) -> 0 | ... T46: =IFERROR(+T45/exchange_rates!M$3,0) -> 0 | U46: =SUM(I46:T46) -> 18687.194
E48: H | F48: Hannun | I48: =SUM(I49:I50) -> 2852.34 | J48: =SUM(J49:J50) -> 1191.18 | K48: =SUM(K49:K50) -> 0 | L48: =SUM(L49:L50) -> 0 | M48: =SUM(M49:M50) -> 0 | N48: =SUM(N49:N50) -> 0 | O48: =SUM(O49:O50) -> 0 | P48: =SUM(P49:P50) -> 0 | ... T48: =SUM(T49:T50) -> 0 | U48: =SUM(I48:T48) -> 4043.52
G49: Staff | I49: =SUMIFS(i_sharedservices_sl[[net]:[net]],i_sharedservices_sl[[yyyymm]:[yyyymm]],I$1,i_sharedservices_sl[[type]:[type]],$F$48,i_sharedservices_sl[[subtype]:[subtype]],$G49) -> 1191.18 | J49: =SUMIFS(i_sharedservices_sl[[net]:[net]],i_sharedservices_sl[[yyyymm]:[yyyymm]],J$1,i_sharedservices_sl[[type]:[type]],$F$48,i_sharedservices_sl[[subtype]:[subtype]],$G49) -> 1191.18 | K49: =SUMIFS(i_sharedservices_sl[[net]:[net]],i_sharedservices_sl[[yyyymm]:[yyyymm]],K$1,i_sharedservices_sl[[type]:[type]],$F$48,i_sharedservices_sl[[subtype]:[subtype]],$G49) -> 0 | L49: =SUMIFS(i_sharedservices_sl[[net]:[net]],i_sharedservices_sl[[yyyymm]:[yyyymm]],L$1,i_sharedservices_sl[[type]:[type]],$F$48,i_sharedservices_sl[[subtype]:[subtype]],$G49) -> 0 | M49: =SUMIFS(i_sharedservices_sl[[net]:[net]],i_sharedservices_sl[[yyyymm]:[yyyymm]],M$1,i_sharedservices_sl[[type]:[type]],$F$48,i_sharedservices_sl[[subtype]:[subtype]],$G49) -> 0 | N49: =SUMIFS(i_sharedservices_sl[[net]:[net]],i_sharedservices_sl[[yyyymm]:[yyyymm]],N$1,i_sharedservices_sl[[type]:[type]],$F$48,i_sharedservices_sl[[subtype]:[subtype]],$G49) -> 0 | O49: =SUMIFS(i_sharedservices_sl[[net]:[net]],i_sharedservices_sl[[yyyymm]:[yyyymm]],O$1,i_sharedservices_sl[[type]:[type]],$F$48,i_sharedservices_sl[[subtype]:[subtype]],$G49) -> 0 | P49: =SUMIFS(i_sharedservices_sl[[net]:[net]],i_sharedservices_sl[[yyyymm]:[yyyymm]],P$1,i_sharedservices_sl[[type]:[type]],$F$48,i_sharedservices_sl[[subtype]:[subtype]],$G49) -> 0 | ... T49: =SUMIFS(i_sharedservices_sl[[net]:[net]],i_sharedservices_sl[[yyyymm]:[yyyymm]],T$1,i_sharedservices_sl[[type]:[type]],$F$48,i_sharedservices_sl[[subtype]:[subtype]],$G49) -> 0 | U49: =SUM(I49:T49) -> 2382.36
G50: CNC | I50: =SUMIFS(i_sharedservices_sl[[net]:[net]],i_sharedservices_sl[[yyyymm]:[yyyymm]],I$1,i_sharedservices_sl[[type]:[type]],$F$48,i_sharedservices_sl[[subtype]:[subtype]],$G50) -> 1661.16 | J50: =SUMIFS(i_sharedservices_sl[[net]:[net]],i_sharedservices_sl[[yyyymm]:[yyyymm]],J$1,i_sharedservices_sl[[type]:[type]],$F$48,i_sharedservices_sl[[subtype]:[subtype]],$G50) -> 0 | K50: =SUMIFS(i_sharedservices_sl[[net]:[net]],i_sharedservices_sl[[yyyymm]:[yyyymm]],K$1,i_sharedservices_sl[[type]:[type]],$F$48,i_sharedservices_sl[[subtype]:[subtype]],$G50) -> 0 | L50: =SUMIFS(i_sharedservices_sl[[net]:[net]],i_sharedservices_sl[[yyyymm]:[yyyymm]],L$1,i_sharedservices_sl[[type]:[type]],$F$48,i_sharedservices_sl[[subtype]:[subtype]],$G50) -> 0 | M50: =SUMIFS(i_sharedservices_sl[[net]:[net]],i_sharedservices_sl[[yyyymm]:[yyyymm]],M$1,i_sharedservices_sl[[type]:[type]],$F$48,i_sharedservices_sl[[subtype]:[subtype]],$G50) -> 0 | N50: =SUMIFS(i_sharedservices_sl[[net]:[net]],i_sharedservices_sl[[yyyymm]:[yyyymm]],N$1,i_sharedservices_sl[[type]:[type]],$F$48,i_sharedservices_sl[[subtype]:[subtype]],$G50) -> 0 | O50: =SUMIFS(i_sharedservices_sl[[net]:[net]],i_sharedservices_sl[[yyyymm]:[yyyymm]],O$1,i_sharedservices_sl[[type]:[type]],$F$48,i_sharedservices_sl[[subtype]:[subtype]],$G50) -> 0 | P50: =SUMIFS(i_sharedservices_sl[[net]:[net]],i_sharedservices_sl[[yyyymm]:[yyyymm]],P$1,i_sharedservices_sl[[type]:[type]],$F$48,i_sharedservices_sl[[subtype]:[subtype]],$G50) -> 0 | ... T50: =SUMIFS(i_sharedservices_sl[[net]:[net]],i_sharedservices_sl[[yyyymm]:[yyyymm]],T$1,i_sharedservices_sl[[type]:[type]],$F$48,i_sharedservices_sl[[subtype]:[subtype]],$G50) -> 0 | U50: =SUM(I50:T50) -> 1661.16 | V50: Factura
I52: =+I54+I62+I69+I75 -> 0.69504014 | J52: =+J54+J62+J69+J75 -> 0.66993881 | K52: =+K54+K62+K69+K75 -> 0.011123948 | L52: =+L54+L62+L69+L75 -> #DIV/0! | M52: =+M54+M62+M69+M75 -> #DIV/0! | N52: =+N54+N62+N69+N75 -> #DIV/0! | O52: =+O54+O62+O69+O75 -> #DIV/0! | P52: =+P54+P62+P69+P75 -> #DIV/0! | ... U52: =+U54+U62+U69+U75 -> 0.48917993
D53: Cost of sales | I53: =+I55+I63+I70+I76 -> 91577.14 | J53: =+J55+J63+J70+J76 -> 101435.14 | K53: =+K55+K63+K70+K76 -> 1267.99 | L53: =+L55+L63+L70+L76 -> 0 | M53: =+M55+M63+M70+M76 -> 0 | N53: =+N55+N63+N70+N76 -> 0 | O53: =+O55+O63+O70+O76 -> 0 | P53: =+P55+P63+P70+P76 -> 0 | ... T53: =+T55+T63+T70+T76 -> 0 | U53: =SUM(I53:T53) -> 194280.27
I54: =+I55/I$4 -> 0.42985393 | J54: =+J55/J$4 -> 0.4192794 | K54: =+K55/K$4 -> 0.011123948 | L54: =+L55/L$4 -> #DIV/0! | M54: =+M55/M$4 -> #DIV/0! | N54: =+N55/N$4 -> #DIV/0! | O54: =+O55/O$4 -> #DIV/0! | P54: =+P55/P$4 -> #DIV/0! | ... U54: =+U55/U$4 -> 0.30564291
D55: Manufacturing | I55: =SUM(I56:I60) -> 56636.72 | J55: =SUM(J56:J60) -> 63482.91 | K55: =SUM(K56:K60) -> 1267.99 | L55: =SUM(L56:L60) -> 0 | M55: =SUM(M56:M60) -> 0 | N55: =SUM(N56:N60) -> 0 | O55: =SUM(O56:O60) -> 0 | P55: =SUM(P56:P60) -> 0 | ... T55: =SUM(T56:T60) -> 0 | U55: =SUM(I55:T55) -> 121387.62
C56: manufacturing - Apphoto España -> SL | F56: #VALUE! | G56: AP Photo - ES | I56: =SUMIFS(g_manufacturing_sl[[net]:[net]], g_manufacturing_sl[[yyyymm]:[yyyymm]],I$1, g_manufacturing_sl[[supplier]:[supplier]],$G56) -> 17898.08 | J56: =SUMIFS(g_manufacturing_sl[[net]:[net]], g_manufacturing_sl[[yyyymm]:[yyyymm]],J$1, g_manufacturing_sl[[supplier]:[supplier]],$G56) -> 22987.13 | K56: =SUMIFS(g_manufacturing_sl[[net]:[net]], g_manufacturing_sl[[yyyymm]:[yyyymm]],K$1, g_manufacturing_sl[[supplier]:[supplier]],$G56) -> 697.99 | L56: =SUMIFS(g_manufacturing_sl[[net]:[net]], g_manufacturing_sl[[yyyymm]:[yyyymm]],L$1, g_manufacturing_sl[[supplier]:[supplier]],$G56) -> 0 | M56: =SUMIFS(g_manufacturing_sl[[net]:[net]], g_manufacturing_sl[[yyyymm]:[yyyymm]],M$1, g_manufacturing_sl[[supplier]:[supplier]],$G56) -> 0 | N56: =SUMIFS(g_manufacturing_sl[[net]:[net]], g_manufacturing_sl[[yyyymm]:[yyyymm]],N$1, g_manufacturing_sl[[supplier]:[supplier]],$G56) -> 0 | O56: =SUMIFS(g_manufacturing_sl[[net]:[net]], g_manufacturing_sl[[yyyymm]:[yyyymm]],O$1, g_manufacturing_sl[[supplier]:[supplier]],$G56) -> 0 | P56: =SUMIFS(g_manufacturing_sl[[net]:[net]], g_manufacturing_sl[[yyyymm]:[yyyymm]],P$1, g_manufacturing_sl[[supplier]:[supplier]],$G56) -> 0 | ... T56: =SUMIFS(g_manufacturing_sl[[net]:[net]], g_manufacturing_sl[[yyyymm]:[yyyymm]],T$1, g_manufacturing_sl[[supplier]:[supplier]],$G56) -> 0 | U56: =SUM(I56:T56) -> 41583.2
C57: manufacturing - Apphoto Canarias -> SL | F57: #VALUE! | G57: AP Photo - Canarias | I57: =SUMIFS(g_manufacturing_sl[[net]:[net]], g_manufacturing_sl[[yyyymm]:[yyyymm]],I$1, g_manufacturing_sl[[supplier]:[supplier]],$G57) -> 29.22 | J57: =SUMIFS(g_manufacturing_sl[[net]:[net]], g_manufacturing_sl[[yyyymm]:[yyyymm]],J$1, g_manufacturing_sl[[supplier]:[supplier]],$G57) -> 59.84 | K57: =SUMIFS(g_manufacturing_sl[[net]:[net]], g_manufacturing_sl[[yyyymm]:[yyyymm]],K$1, g_manufacturing_sl[[supplier]:[supplier]],$G57) -> 0 | L57: =SUMIFS(g_manufacturing_sl[[net]:[net]], g_manufacturing_sl[[yyyymm]:[yyyymm]],L$1, g_manufacturing_sl[[supplier]:[supplier]],$G57) -> 0 | M57: =SUMIFS(g_manufacturing_sl[[net]:[net]], g_manufacturing_sl[[yyyymm]:[yyyymm]],M$1, g_manufacturing_sl[[supplier]:[supplier]],$G57) -> 0 | N57: =SUMIFS(g_manufacturing_sl[[net]:[net]], g_manufacturing_sl[[yyyymm]:[yyyymm]],N$1, g_manufacturing_sl[[supplier]:[supplier]],$G57) -> 0 | O57: =SUMIFS(g_manufacturing_sl[[net]:[net]], g_manufacturing_sl[[yyyymm]:[yyyymm]],O$1, g_manufacturing_sl[[supplier]:[supplier]],$G57) -> 0 | P57: =SUMIFS(g_manufacturing_sl[[net]:[net]], g_manufacturing_sl[[yyyymm]:[yyyymm]],P$1, g_manufacturing_sl[[supplier]:[supplier]],$G57) -> 0 | ... T57: =SUMIFS(g_manufacturing_sl[[net]:[net]], g_manufacturing_sl[[yyyymm]:[yyyymm]],T$1, g_manufacturing_sl[[supplier]:[supplier]],$G57) -> 0 | U57: =SUM(I57:T57) -> 89.06 | W57: -63513.33
C58: manufacturing - Pressing -> SL | F58: #VALUE! | G58: Pressing | I58: =SUMIFS(g_manufacturing_sl[[net]:[net]], g_manufacturing_sl[[yyyymm]:[yyyymm]],I$1, g_manufacturing_sl[[supplier]:[supplier]],$G58) -> 28979.31 | J58: =SUMIFS(g_manufacturing_sl[[net]:[net]], g_manufacturing_sl[[yyyymm]:[yyyymm]],J$1, g_manufacturing_sl[[supplier]:[supplier]],$G58) -> 33510.62 | K58: =SUMIFS(g_manufacturing_sl[[net]:[net]], g_manufacturing_sl[[yyyymm]:[yyyymm]],K$1, g_manufacturing_sl[[supplier]:[supplier]],$G58) -> 0 | L58: =SUMIFS(g_manufacturing_sl[[net]:[net]], g_manufacturing_sl[[yyyymm]:[yyyymm]],L$1, g_manufacturing_sl[[supplier]:[supplier]],$G58) -> 0 | M58: =SUMIFS(g_manufacturing_sl[[net]:[net]], g_manufacturing_sl[[yyyymm]:[yyyymm]],M$1, g_manufacturing_sl[[supplier]:[supplier]],$G58) -> 0 | N58: =SUMIFS(g_manufacturing_sl[[net]:[net]], g_manufacturing_sl[[yyyymm]:[yyyymm]],N$1, g_manufacturing_sl[[supplier]:[supplier]],$G58) -> 0 | O58: =SUMIFS(g_manufacturing_sl[[net]:[net]], g_manufacturing_sl[[yyyymm]:[yyyymm]],O$1, g_manufacturing_sl[[supplier]:[supplier]],$G58) -> 0 | P58: =SUMIFS(g_manufacturing_sl[[net]:[net]], g_manufacturing_sl[[yyyymm]:[yyyymm]],P$1, g_manufacturing_sl[[supplier]:[supplier]],$G58) -> 0 | ... T58: =SUMIFS(g_manufacturing_sl[[net]:[net]], g_manufacturing_sl[[yyyymm]:[yyyymm]],T$1, g_manufacturing_sl[[supplier]:[supplier]],$G58) -> 0 | U58: =SUM(I58:T58) -> 62489.93 | W58: 63482.91
C59: manufacturing - DCT -> SL | F59: #VALUE! | G59: DCT | I59: =SUMIFS(g_manufacturing_sl[[net]:[net]], g_manufacturing_sl[[yyyymm]:[yyyymm]],I$1, g_manufacturing_sl[[supplier]:[supplier]],$G59) -> 9730.11 | J59: =SUMIFS(g_manufacturing_sl[[net]:[net]], g_manufacturing_sl[[yyyymm]:[yyyymm]],J$1, g_manufacturing_sl[[supplier]:[supplier]],$G59) -> 6925.32 | K59: =SUMIFS(g_manufacturing_sl[[net]:[net]], g_manufacturing_sl[[yyyymm]:[yyyymm]],K$1, g_manufacturing_sl[[supplier]:[supplier]],$G59) -> 0 | L59: =SUMIFS(g_manufacturing_sl[[net]:[net]], g_manufacturing_sl[[yyyymm]:[yyyymm]],L$1, g_manufacturing_sl[[supplier]:[supplier]],$G59) -> 0 | M59: =SUMIFS(g_manufacturing_sl[[net]:[net]], g_manufacturing_sl[[yyyymm]:[yyyymm]],M$1, g_manufacturing_sl[[supplier]:[supplier]],$G59) -> 0 | N59: =SUMIFS(g_manufacturing_sl[[net]:[net]], g_manufacturing_sl[[yyyymm]:[yyyymm]],N$1, g_manufacturing_sl[[supplier]:[supplier]],$G59) -> 0 | O59: =SUMIFS(g_manufacturing_sl[[net]:[net]], g_manufacturing_sl[[yyyymm]:[yyyymm]],O$1, g_manufacturing_sl[[supplier]:[supplier]],$G59) -> 0 | P59: =SUMIFS(g_manufacturing_sl[[net]:[net]], g_manufacturing_sl[[yyyymm]:[yyyymm]],P$1, g_manufacturing_sl[[supplier]:[supplier]],$G59) -> 0 | ... T59: =SUMIFS(g_manufacturing_sl[[net]:[net]], g_manufacturing_sl[[yyyymm]:[yyyymm]],T$1, g_manufacturing_sl[[supplier]:[supplier]],$G59) -> 0 | U59: =SUM(I59:T59) -> 16655.43 | W59: =+W58+W57 -> -30.42
B60: logistics - artlink -> SL | C60: logistics - debex -> SL | F60: #VALUE! | G60: Artlink | I60: =SUMIFS(g_manufacturing_sl[[net]:[net]], g_manufacturing_sl[[yyyymm]:[yyyymm]],I$1, g_manufacturing_sl[[supplier]:[supplier]],$G60) -> 0 | J60: =SUMIFS(g_manufacturing_sl[[net]:[net]], g_manufacturing_sl[[yyyymm]:[yyyymm]],J$1, g_manufacturing_sl[[supplier]:[supplier]],$G60) -> 0 | K60: =SUMIFS(g_manufacturing_sl[[net]:[net]], g_manufacturing_sl[[yyyymm]:[yyyymm]],K$1, g_manufacturing_sl[[supplier]:[supplier]],$G60) -> 570 | L60: =SUMIFS(g_manufacturing_sl[[net]:[net]], g_manufacturing_sl[[yyyymm]:[yyyymm]],L$1, g_manufacturing_sl[[supplier]:[supplier]],$G60) -> 0 | M60: =SUMIFS(g_manufacturing_sl[[net]:[net]], g_manufacturing_sl[[yyyymm]:[yyyymm]],M$1, g_manufacturing_sl[[supplier]:[supplier]],$G60) -> 0 | N60: =SUMIFS(g_manufacturing_sl[[net]:[net]], g_manufacturing_sl[[yyyymm]:[yyyymm]],N$1, g_manufacturing_sl[[supplier]:[supplier]],$G60) -> 0 | O60: =SUMIFS(g_manufacturing_sl[[net]:[net]], g_manufacturing_sl[[yyyymm]:[yyyymm]],O$1, g_manufacturing_sl[[supplier]:[supplier]],$G60) -> 0 | P60: =SUMIFS(g_manufacturing_sl[[net]:[net]], g_manufacturing_sl[[yyyymm]:[yyyymm]],P$1, g_manufacturing_sl[[supplier]:[supplier]],$G60) -> 0 | ... T60: =SUMIFS(g_manufacturing_sl[[net]:[net]], g_manufacturing_sl[[yyyymm]:[yyyymm]],T$1, g_manufacturing_sl[[supplier]:[supplier]],$G60) -> 0 | U60: =SUM(I60:T60) -> 570
I62: =+I63/I$4 -> 0.13056643 | J62: =+J63/J$4 -> 0.11813475 | K62: =+K63/K$4 -> 0 | L62: =+L63/L$4 -> #DIV/0! | M62: =+M63/M$4 -> #DIV/0! | N62: =+N63/N$4 -> #DIV/0! | O62: =+O63/O$4 -> #DIV/0! | P62: =+P63/P$4 -> #DIV/0! | ... U62: =+U63/U$4 -> 0.08835318
D63: Shipping | I63: =SUM(I64:I67) -> 17203.18 | J63: =SUM(J64:J67) -> 17886.73 | K63: =SUM(K64:K67) -> 0 | L63: =SUM(L64:L67) -> 0 | M63: =SUM(M64:M67) -> 0 | N63: =SUM(N64:N67) -> 0 | O63: =SUM(O64:O67) -> 0 | P63: =SUM(P64:P67) -> 0 | ... T63: =SUM(T64:T67) -> 0 | U63: =SUM(I63:T63) -> 35089.91
C64: logistics - GLS -> SL | G64: GLS | I64: =SUMIFS(g_shipping_sl[[net]:[net]],g_shipping_sl[[yyyymm]:[yyyymm]],I$1,g_shipping_sl[[supplier]:[supplier]],$G64) -> 12319.26 | J64: =SUMIFS(g_shipping_sl[[net]:[net]],g_shipping_sl[[yyyymm]:[yyyymm]],J$1,g_shipping_sl[[supplier]:[supplier]],$G64) -> 15947.02 | K64: =SUMIFS(g_shipping_sl[[net]:[net]],g_shipping_sl[[yyyymm]:[yyyymm]],K$1,g_shipping_sl[[supplier]:[supplier]],$G64) -> 0 | L64: =SUMIFS(g_shipping_sl[[net]:[net]],g_shipping_sl[[yyyymm]:[yyyymm]],L$1,g_shipping_sl[[supplier]:[supplier]],$G64) -> 0 | M64: =SUMIFS(g_shipping_sl[[net]:[net]],g_shipping_sl[[yyyymm]:[yyyymm]],M$1,g_shipping_sl[[supplier]:[supplier]],$G64) -> 0 | N64: =SUMIFS(g_shipping_sl[[net]:[net]],g_shipping_sl[[yyyymm]:[yyyymm]],N$1,g_shipping_sl[[supplier]:[supplier]],$G64) -> 0 | O64: =SUMIFS(g_shipping_sl[[net]:[net]],g_shipping_sl[[yyyymm]:[yyyymm]],O$1,g_shipping_sl[[supplier]:[supplier]],$G64) -> 0 | P64: =SUMIFS(g_shipping_sl[[net]:[net]],g_shipping_sl[[yyyymm]:[yyyymm]],P$1,g_shipping_sl[[supplier]:[supplier]],$G64) -> 0 | ... T64: =SUMIFS(g_shipping_sl[[net]:[net]],g_shipping_sl[[yyyymm]:[yyyymm]],T$1,g_shipping_sl[[supplier]:[supplier]],$G64) -> 0 | U64: =SUM(I64:T64) -> 28266.28
C65: logistics - Correos -> SL | G65: Correos | I65: =SUMIFS(g_shipping_sl[[net]:[net]],g_shipping_sl[[yyyymm]:[yyyymm]],I$1,g_shipping_sl[[supplier]:[supplier]],$G65) -> 575.07 | J65: =SUMIFS(g_shipping_sl[[net]:[net]],g_shipping_sl[[yyyymm]:[yyyymm]],J$1,g_shipping_sl[[supplier]:[supplier]],$G65) -> 113.22 | K65: =SUMIFS(g_shipping_sl[[net]:[net]],g_shipping_sl[[yyyymm]:[yyyymm]],K$1,g_shipping_sl[[supplier]:[supplier]],$G65) -> 0 | L65: =SUMIFS(g_shipping_sl[[net]:[net]],g_shipping_sl[[yyyymm]:[yyyymm]],L$1,g_shipping_sl[[supplier]:[supplier]],$G65) -> 0 | M65: =SUMIFS(g_shipping_sl[[net]:[net]],g_shipping_sl[[yyyymm]:[yyyymm]],M$1,g_shipping_sl[[supplier]:[supplier]],$G65) -> 0 | N65: =SUMIFS(g_shipping_sl[[net]:[net]],g_shipping_sl[[yyyymm]:[yyyymm]],N$1,g_shipping_sl[[supplier]:[supplier]],$G65) -> 0 | O65: =SUMIFS(g_shipping_sl[[net]:[net]],g_shipping_sl[[yyyymm]:[yyyymm]],O$1,g_shipping_sl[[supplier]:[supplier]],$G65) -> 0 | P65: =SUMIFS(g_shipping_sl[[net]:[net]],g_shipping_sl[[yyyymm]:[yyyymm]],P$1,g_shipping_sl[[supplier]:[supplier]],$G65) -> 0 | ... T65: =SUMIFS(g_shipping_sl[[net]:[net]],g_shipping_sl[[yyyymm]:[yyyymm]],T$1,g_shipping_sl[[supplier]:[supplier]],$G65) -> 0 | U65: =SUM(I65:T65) -> 688.29
C66: logistics - Spring -> SL | G66: Spring | I66: =SUMIFS(g_shipping_sl[[net]:[net]],g_shipping_sl[[yyyymm]:[yyyymm]],I$1,g_shipping_sl[[supplier]:[supplier]],$G66) -> 3.3 | J66: =SUMIFS(g_shipping_sl[[net]:[net]],g_shipping_sl[[yyyymm]:[yyyymm]],J$1,g_shipping_sl[[supplier]:[supplier]],$G66) -> 0 | K66: =SUMIFS(g_shipping_sl[[net]:[net]],g_shipping_sl[[yyyymm]:[yyyymm]],K$1,g_shipping_sl[[supplier]:[supplier]],$G66) -> 0 | L66: =SUMIFS(g_shipping_sl[[net]:[net]],g_shipping_sl[[yyyymm]:[yyyymm]],L$1,g_shipping_sl[[supplier]:[supplier]],$G66) -> 0 | M66: =SUMIFS(g_shipping_sl[[net]:[net]],g_shipping_sl[[yyyymm]:[yyyymm]],M$1,g_shipping_sl[[supplier]:[supplier]],$G66) -> 0 | N66: =SUMIFS(g_shipping_sl[[net]:[net]],g_shipping_sl[[yyyymm]:[yyyymm]],N$1,g_shipping_sl[[supplier]:[supplier]],$G66) -> 0 | O66: =SUMIFS(g_shipping_sl[[net]:[net]],g_shipping_sl[[yyyymm]:[yyyymm]],O$1,g_shipping_sl[[supplier]:[supplier]],$G66) -> 0 | P66: =SUMIFS(g_shipping_sl[[net]:[net]],g_shipping_sl[[yyyymm]:[yyyymm]],P$1,g_shipping_sl[[supplier]:[supplier]],$G66) -> 0 | ... T66: =SUMIFS(g_shipping_sl[[net]:[net]],g_shipping_sl[[yyyymm]:[yyyymm]],T$1,g_shipping_sl[[supplier]:[supplier]],$G66) -> 0 | U66: =SUM(I66:T66) -> 3.3
C67: logistics - UPS DE -> SL | G67: UPS | I67: =SUMIFS(g_shipping_sl[[net]:[net]],g_shipping_sl[[yyyymm]:[yyyymm]],I$1,g_shipping_sl[[supplier]:[supplier]],$G67) -> 4305.55 | J67: =SUMIFS(g_shipping_sl[[net]:[net]],g_shipping_sl[[yyyymm]:[yyyymm]],J$1,g_shipping_sl[[supplier]:[supplier]],$G67) -> 1826.49 | K67: =SUMIFS(g_shipping_sl[[net]:[net]],g_shipping_sl[[yyyymm]:[yyyymm]],K$1,g_shipping_sl[[supplier]:[supplier]],$G67) -> 0 | L67: =SUMIFS(g_shipping_sl[[net]:[net]],g_shipping_sl[[yyyymm]:[yyyymm]],L$1,g_shipping_sl[[supplier]:[supplier]],$G67) -> 0 | M67: =SUMIFS(g_shipping_sl[[net]:[net]],g_shipping_sl[[yyyymm]:[yyyymm]],M$1,g_shipping_sl[[supplier]:[supplier]],$G67) -> 0 | N67: =SUMIFS(g_shipping_sl[[net]:[net]],g_shipping_sl[[yyyymm]:[yyyymm]],N$1,g_shipping_sl[[supplier]:[supplier]],$G67) -> 0 | O67: =SUMIFS(g_shipping_sl[[net]:[net]],g_shipping_sl[[yyyymm]:[yyyymm]],O$1,g_shipping_sl[[supplier]:[supplier]],$G67) -> 0 | P67: =SUMIFS(g_shipping_sl[[net]:[net]],g_shipping_sl[[yyyymm]:[yyyymm]],P$1,g_shipping_sl[[supplier]:[supplier]],$G67) -> 0 | ... T67: =SUMIFS(g_shipping_sl[[net]:[net]],g_shipping_sl[[yyyymm]:[yyyymm]],T$1,g_shipping_sl[[supplier]:[supplier]],$G67) -> 0 | U67: =SUM(I67:T67) -> 6132.04
I69: =+I70/I$4 -> 0.10425928 | J69: =+J70/J$4 -> 0.11004589 | K69: =+K70/K$4 -> 0 | L69: =+L70/L$4 -> #DIV/0! | M69: =+M70/M$4 -> #DIV/0! | N69: =+N70/N$4 -> #DIV/0! | O69: =+O70/O$4 -> #DIV/0! | P69: =+P70/P$4 -> #DIV/0! | ... U69: =+U70/U$4 -> 0.076541899
D70: Royalties | I70: =SUMIFS(g_royalties_sl[[total]:[total]],g_royalties_sl[[yyyymm]:[yyyymm]],I$1) -> 13737 | J70: =SUMIFS(g_royalties_sl[[total]:[total]],g_royalties_sl[[yyyymm]:[yyyymm]],J$1) -> 16662 | K70: =SUMIFS(g_royalties_sl[[total]:[total]],g_royalties_sl[[yyyymm]:[yyyymm]],K$1) -> 0 | L70: =SUMIFS(g_royalties_sl[[total]:[total]],g_royalties_sl[[yyyymm]:[yyyymm]],L$1) -> 0 | M70: =SUMIFS(g_royalties_sl[[total]:[total]],g_royalties_sl[[yyyymm]:[yyyymm]],M$1) -> 0 | N70: =SUMIFS(g_royalties_sl[[total]:[total]],g_royalties_sl[[yyyymm]:[yyyymm]],N$1) -> 0 | O70: =SUMIFS(g_royalties_sl[[total]:[total]],g_royalties_sl[[yyyymm]:[yyyymm]],O$1) -> 0 | P70: =SUMIFS(g_royalties_sl[[total]:[total]],g_royalties_sl[[yyyymm]:[yyyymm]],P$1) -> 0 | ... T70: =SUMIFS(g_royalties_sl[[total]:[total]],g_royalties_sl[[yyyymm]:[yyyymm]],T$1) -> 0 | U70: =SUM(I70:T70) -> 30399
C71: royalties - Artistas -> SL | G71: UE | I71: =+I70-I72-I73 -> 11994 | J71: =+J70-J72-J73 -> 14322 | K71: =+K70-K72-K73 -> 0 | L71: =+L70-L72-L73 -> 0 | M71: =+M70-M72-M73 -> 0 | N71: =+N70-N72-N73 -> 0 | O71: =+O70-O72-O73 -> 0 | P71: =+P70-P72-P73 -> 0 | ... T71: =+T70-T72-T73 -> 0 | U71: =SUM(I71:T71) -> 26316
C72: royalties - Artistas -> Ltd | G72: Shared services - UK | I72: =SUMIFS(g_royalties_sl[[uk]:[uk]],g_royalties_sl[[yyyymm]:[yyyymm]],I$1) -> 1272 | J72: =SUMIFS(g_royalties_sl[[uk]:[uk]],g_royalties_sl[[yyyymm]:[yyyymm]],J$1) -> 1596 | K72: =SUMIFS(g_royalties_sl[[uk]:[uk]],g_royalties_sl[[yyyymm]:[yyyymm]],K$1) -> 0 | L72: =SUMIFS(g_royalties_sl[[uk]:[uk]],g_royalties_sl[[yyyymm]:[yyyymm]],L$1) -> 0 | M72: =SUMIFS(g_royalties_sl[[uk]:[uk]],g_royalties_sl[[yyyymm]:[yyyymm]],M$1) -> 0 | N72: =SUMIFS(g_royalties_sl[[uk]:[uk]],g_royalties_sl[[yyyymm]:[yyyymm]],N$1) -> 0 | O72: =SUMIFS(g_royalties_sl[[uk]:[uk]],g_royalties_sl[[yyyymm]:[yyyymm]],O$1) -> 0 | P72: =SUMIFS(g_royalties_sl[[uk]:[uk]],g_royalties_sl[[yyyymm]:[yyyymm]],P$1) -> 0 | ... T72: =SUMIFS(g_royalties_sl[[uk]:[uk]],g_royalties_sl[[yyyymm]:[yyyymm]],T$1) -> 0 | U72: =SUM(I72:T72) -> 2868
C73: royalties - Artistas -> Inc | G73: Shared services - US | I73: =SUMIFS(g_royalties_sl[[us]:[us]],g_royalties_sl[[yyyymm]:[yyyymm]],I$1) -> 471 | J73: =SUMIFS(g_royalties_sl[[us]:[us]],g_royalties_sl[[yyyymm]:[yyyymm]],J$1) -> 744 | K73: =SUMIFS(g_royalties_sl[[us]:[us]],g_royalties_sl[[yyyymm]:[yyyymm]],K$1) -> 0 | L73: =SUMIFS(g_royalties_sl[[us]:[us]],g_royalties_sl[[yyyymm]:[yyyymm]],L$1) -> 0 | M73: =SUMIFS(g_royalties_sl[[us]:[us]],g_royalties_sl[[yyyymm]:[yyyymm]],M$1) -> 0 | N73: =SUMIFS(g_royalties_sl[[us]:[us]],g_royalties_sl[[yyyymm]:[yyyymm]],N$1) -> 0 | O73: =SUMIFS(g_royalties_sl[[us]:[us]],g_royalties_sl[[yyyymm]:[yyyymm]],O$1) -> 0 | P73: =SUMIFS(g_royalties_sl[[us]:[us]],g_royalties_sl[[yyyymm]:[yyyymm]],P$1) -> 0 | ... T73: =SUMIFS(g_royalties_sl[[us]:[us]],g_royalties_sl[[yyyymm]:[yyyymm]],T$1) -> 0 | U73: =SUM(I73:T73) -> 1215 | W73: -17203.18 | X73: -17886.73 | Y73: =+X73+W73 -> -35089.91
I75: =+I76/I$4 -> 0.030360496 | J75: =+J76/J$4 -> 0.022478766 | K75: =+K76/K$4 -> 0 | L75: =+L76/L$4 -> #DIV/0! | M75: =+M76/M$4 -> #DIV/0! | N75: =+N76/N$4 -> #DIV/0! | O75: =+O76/O$4 -> #DIV/0! | P75: =+P76/P$4 -> #DIV/0! | ... U75: =+U76/U$4 -> 0.018641939
D76: Payments suppliers | I76: =SUM(I77:I79) -> 4000.24 | J76: =SUM(J77:J79) -> 3403.5 | K76: =SUM(K77:K79) -> 0 | L76: =SUM(L77:L79) -> 0 | M76: =SUM(M77:M79) -> 0 | N76: =SUM(N77:N79) -> 0 | O76: =SUM(O77:O79) -> 0 | P76: =SUM(P77:P79) -> 0 | ... T76: =SUM(T77:T79) -> 0 | U76: =SUM(I76:T76) -> 7403.74 | Y76: =+J63+I63 -> 35089.91
C77: payment-suppliers - Shopify -> SL | G77: Shopify | I77: =SUMIFS(g_paymentsuplier_sl[[total]:[total]],g_paymentsuplier_sl[[yyyymm]:[yyyymm]],I$1,g_paymentsuplier_sl[[supplier]:[supplier]],$G77) -> 2623.76 | J77: =SUMIFS(g_paymentsuplier_sl[[total]:[total]],g_paymentsuplier_sl[[yyyymm]:[yyyymm]],J$1,g_paymentsuplier_sl[[supplier]:[supplier]],$G77) -> 2221.5 | K77: =SUMIFS(g_paymentsuplier_sl[[total]:[total]],g_paymentsuplier_sl[[yyyymm]:[yyyymm]],K$1,g_paymentsuplier_sl[[supplier]:[supplier]],$G77) -> 0 | L77: =SUMIFS(g_paymentsuplier_sl[[total]:[total]],g_paymentsuplier_sl[[yyyymm]:[yyyymm]],L$1,g_paymentsuplier_sl[[supplier]:[supplier]],$G77) -> 0 | M77: =SUMIFS(g_paymentsuplier_sl[[total]:[total]],g_paymentsuplier_sl[[yyyymm]:[yyyymm]],M$1,g_paymentsuplier_sl[[supplier]:[supplier]],$G77) -> 0 | N77: =SUMIFS(g_paymentsuplier_sl[[total]:[total]],g_paymentsuplier_sl[[yyyymm]:[yyyymm]],N$1,g_paymentsuplier_sl[[supplier]:[supplier]],$G77) -> 0 | O77: =SUMIFS(g_paymentsuplier_sl[[total]:[total]],g_paymentsuplier_sl[[yyyymm]:[yyyymm]],O$1,g_paymentsuplier_sl[[supplier]:[supplier]],$G77) -> 0 | P77: =SUMIFS(g_paymentsuplier_sl[[total]:[total]],g_paymentsuplier_sl[[yyyymm]:[yyyymm]],P$1,g_paymentsuplier_sl[[supplier]:[supplier]],$G77) -> 0 | ... T77: =SUMIFS(g_paymentsuplier_sl[[total]:[total]],g_paymentsuplier_sl[[yyyymm]:[yyyymm]],T$1,g_paymentsuplier_sl[[supplier]:[supplier]],$G77) -> 0 | U77: =SUM(I77:T77) -> 4845.26 | Y77: =+Y76+Y73 -> 0
C78: payment-suppliers - Paypal -> SL | G78: Paypal | I78: =SUMIFS(g_paymentsuplier_sl[[total]:[total]],g_paymentsuplier_sl[[yyyymm]:[yyyymm]],I$1,g_paymentsuplier_sl[[supplier]:[supplier]],$G78) -> 1366.48 | J78: =SUMIFS(g_paymentsuplier_sl[[total]:[total]],g_paymentsuplier_sl[[yyyymm]:[yyyymm]],J$1,g_paymentsuplier_sl[[supplier]:[supplier]],$G78) -> 1172 | K78: =SUMIFS(g_paymentsuplier_sl[[total]:[total]],g_paymentsuplier_sl[[yyyymm]:[yyyymm]],K$1,g_paymentsuplier_sl[[supplier]:[supplier]],$G78) -> 0 | L78: =SUMIFS(g_paymentsuplier_sl[[total]:[total]],g_paymentsuplier_sl[[yyyymm]:[yyyymm]],L$1,g_paymentsuplier_sl[[supplier]:[supplier]],$G78) -> 0 | M78: =SUMIFS(g_paymentsuplier_sl[[total]:[total]],g_paymentsuplier_sl[[yyyymm]:[yyyymm]],M$1,g_paymentsuplier_sl[[supplier]:[supplier]],$G78) -> 0 | N78: =SUMIFS(g_paymentsuplier_sl[[total]:[total]],g_paymentsuplier_sl[[yyyymm]:[yyyymm]],N$1,g_paymentsuplier_sl[[supplier]:[supplier]],$G78) -> 0 | O78: =SUMIFS(g_paymentsuplier_sl[[total]:[total]],g_paymentsuplier_sl[[yyyymm]:[yyyymm]],O$1,g_paymentsuplier_sl[[supplier]:[supplier]],$G78) -> 0 | P78: =SUMIFS(g_paymentsuplier_sl[[total]:[total]],g_paymentsuplier_sl[[yyyymm]:[yyyymm]],P$1,g_paymentsuplier_sl[[supplier]:[supplier]],$G78) -> 0 | ... T78: =SUMIFS(g_paymentsuplier_sl[[total]:[total]],g_paymentsuplier_sl[[yyyymm]:[yyyymm]],T$1,g_paymentsuplier_sl[[supplier]:[supplier]],$G78) -> 0 | U78: =SUM(I78:T78) -> 2538.48
G79: Revolut | I79: =SUMIFS(g_paymentsuplier_sl[[total]:[total]],g_paymentsuplier_sl[[yyyymm]:[yyyymm]],I$1,g_paymentsuplier_sl[[supplier]:[supplier]],$G79) -> 10 | J79: =SUMIFS(g_paymentsuplier_sl[[total]:[total]],g_paymentsuplier_sl[[yyyymm]:[yyyymm]],J$1,g_paymentsuplier_sl[[supplier]:[supplier]],$G79) -> 10 | K79: =SUMIFS(g_paymentsuplier_sl[[total]:[total]],g_paymentsuplier_sl[[yyyymm]:[yyyymm]],K$1,g_paymentsuplier_sl[[supplier]:[supplier]],$G79) -> 0 | L79: =SUMIFS(g_paymentsuplier_sl[[total]:[total]],g_paymentsuplier_sl[[yyyymm]:[yyyymm]],L$1,g_paymentsuplier_sl[[supplier]:[supplier]],$G79) -> 0 | M79: =SUMIFS(g_paymentsuplier_sl[[total]:[total]],g_paymentsuplier_sl[[yyyymm]:[yyyymm]],M$1,g_paymentsuplier_sl[[supplier]:[supplier]],$G79) -> 0 | N79: =SUMIFS(g_paymentsuplier_sl[[total]:[total]],g_paymentsuplier_sl[[yyyymm]:[yyyymm]],N$1,g_paymentsuplier_sl[[supplier]:[supplier]],$G79) -> 0 | O79: =SUMIFS(g_paymentsuplier_sl[[total]:[total]],g_paymentsuplier_sl[[yyyymm]:[yyyymm]],O$1,g_paymentsuplier_sl[[supplier]:[supplier]],$G79) -> 0 | P79: =SUMIFS(g_paymentsuplier_sl[[total]:[total]],g_paymentsuplier_sl[[yyyymm]:[yyyymm]],P$1,g_paymentsuplier_sl[[supplier]:[supplier]],$G79) -> 0 | ... T79: =SUMIFS(g_paymentsuplier_sl[[total]:[total]],g_paymentsuplier_sl[[yyyymm]:[yyyymm]],T$1,g_paymentsuplier_sl[[supplier]:[supplier]],$G79) -> 0
A81: Gross margin % | I81: =1-(I55/(+I5+I16+I21+I23)) -> 0.57014607 | J81: =1-(J55/(+J5+J16+J21+J23)) -> 0.5807206 | K81: =1-(K55/(+K5+K16+K21+K23)) -> 0.98887605 | L81: =1-(L55/(+L5+L16+L21+L23)) -> #DIV/0! | M81: =1-(M55/(+M5+M16+M21+M23)) -> #DIV/0! | N81: =1-(N55/(+N5+N16+N21+N23)) -> #DIV/0! | O81: =1-(O55/(+O5+O16+O21+O23)) -> #DIV/0! | P81: =1-(P55/(+P5+P16+P21+P23)) -> #DIV/0! | ... T81: =1-(T55/(+T5+T16+T21+T23)) -> #DIV/0! | U81: =SUMIFS( INDIRECT("input_invoice[net]"), INDIRECT("input_invoice[yyyymm]"), 'P&G-SL'!U$1, INDIRECT("input_invoice[concept/supplier]"), 'P&G-SL'!$C81 ) -> 0
A82: Gross margin | I82: =+I4-I55 -> 75121.34 | J82: =+J4-J55 -> 87926.65 | K82: =+K4-K55 -> 112719.42 | L82: =+L4-L55 -> 0 | M82: =+M4-M55 -> 0 | N82: =+N4-N55 -> 0 | O82: =+O4-O55 -> 0 | P82: =+P4-P55 -> 0 | ... T82: =+T4-T55 -> 0
D83: Contributive margin % | I83: =1-((I53)/I3) -> 0.40019313 | J83: =1-((J53)/J3) -> 0.4174816 | K83: =1-((K53)/K3) -> 0.98887605 | L83: =1-((L53)/L3) -> #DIV/0! | M83: =1-((M53)/M3) -> #DIV/0! | N83: =1-((N53)/N3) -> #DIV/0! | O83: =1-((O53)/O3) -> #DIV/0! | P83: =1-((P53)/P3) -> #DIV/0! | ... T83: =1-((T53)/T3) -> #DIV/0! | U83: =SUMIFS( INDIRECT("input_invoice[net]"), INDIRECT("input_invoice[yyyymm]"), 'P&G-SL'!U$1, INDIRECT("input_invoice[concept/supplier]"), 'P&G-SL'!$C83 ) -> 0
D84: Contributive margin | I84: =+I3-I53 -> 61100.57 | J84: =+J3-J53 -> 72696.94 | K84: =+K3-K53 -> 112719.42 | L84: =+L3-L53 -> 0 | M84: =+M3-M53 -> 0 | N84: =+N3-N53 -> 0 | O84: =+O3-O53 -> 0 | P84: =+P3-P53 -> 0 | ... T84: =+T3-T53 -> 0 | U84: =SUM(I84:T84) -> 246516.93
I86: =+I87/I3 -> 0.49836465 | J86: =+J87/J3 -> 0.39868728 | K86: =+K87/K3 -> 0 | L86: =+L87/L3 -> #DIV/0! | M86: =+M87/M3 -> #DIV/0! | N86: =+N87/N3 -> #DIV/0! | O86: =+O87/O3 -> #DIV/0! | P86: =+P87/P3 -> #DIV/0! | ... U86: =+U87/U3 -> 0.33011421
D87: Fixed costs | I87: =+I89+I103+I113+I145 -> 76089.174 | J87: =+J89+J103+J113+J145 -> 69424.245 | K87: =+K89+K103+K113+K145 -> 0 | L87: =+L89+L103+L113+L145 -> 0 | M87: =+M89+M103+M113+M145 -> 0 | N87: =+N89+N103+N113+N145 -> 0 | O87: =+O89+O103+O113+O145 -> 0 | P87: =+P89+P103+P113+P145 -> 0 | ... T87: =+T89+T103+T113+T145 -> 0 | U87: =SUM(I87:T87) -> 145513.42
I88: =+I89/I$84 -> 0.89440279 | J88: =+J89/J$84 -> 0.65513211 | K88: =+K89/K$84 -> 0 | L88: =+L89/L$84 -> #DIV/0! | M88: =+M89/M$84 -> #DIV/0! | N88: =+N89/N$84 -> #DIV/0! | O88: =+O89/O$84 -> #DIV/0! | P88: =+P89/P$84 -> #DIV/0! | ... T88: =+T89/T$84 -> #DIV/0!
E89: Marketing | I89: =+I90+I91 -> 54648.52 | J89: =+J90+J91 -> 47626.1 | K89: =+K90+K91 -> 0 | L89: =+L90+L91 -> 0 | M89: =+M90+M91 -> 0 | N89: =+N90+N91 -> 0 | O89: =+O90+O91 -> 0 | P89: =+P90+P91 -> 0 | ... T89: =+T90+T91 -> 0 | U89: =SUM(I89:T89) -> 102274.62
F90: Google - Invoice | I90: 29164.06 | J90: 27551.11
F91: Meta - Invoice | I91: 25484.46 | J91: 20074.99
F92: UE | I92: =SUM(I93:I94) -> 44184.2 | J92: =SUM(J93:J94) -> 34583.83 | K92: =SUM(K93:K94) -> 0 | L92: =SUM(L93:L94) -> 0 | M92: =SUM(M93:M94) -> 0 | N92: =SUM(N93:N94) -> 0 | O92: =SUM(O93:O94) -> 0 | P92: =SUM(P93:P94) -> 0 | ... T92: =SUM(T93:T94) -> 0 | U92: =SUM(I92:T92) -> 78768.03
C93: marketing - google -> SL | G93: google | I93: =SUMIFS( INDIRECT("input_provisions[import]"), INDIRECT("input_provisions[yyyymm]"), 'P&G-SL'!I$1, INDIRECT("input_provisions[concept/supplier]"), 'P&G-SL'!$C93 ) -> 23864.87 | J93: =SUMIFS( INDIRECT("input_provisions[import]"), INDIRECT("input_provisions[yyyymm]"), 'P&G-SL'!J$1, INDIRECT("input_provisions[concept/supplier]"), 'P&G-SL'!$C93 ) -> 18700.28 | K93: =SUMIFS( INDIRECT("input_provisions[import]"), INDIRECT("input_provisions[yyyymm]"), 'P&G-SL'!K$1, INDIRECT("input_provisions[concept/supplier]"), 'P&G-SL'!$C93 ) -> 0 | L93: =SUMIFS( INDIRECT("input_provisions[import]"), INDIRECT("input_provisions[yyyymm]"), 'P&G-SL'!L$1, INDIRECT("input_provisions[concept/supplier]"), 'P&G-SL'!$C93 ) -> 0 | M93: =SUMIFS( INDIRECT("input_provisions[import]"), INDIRECT("input_provisions[yyyymm]"), 'P&G-SL'!M$1, INDIRECT("input_provisions[concept/supplier]"), 'P&G-SL'!$C93 ) -> 0 | N93: =SUMIFS( INDIRECT("input_provisions[import]"), INDIRECT("input_provisions[yyyymm]"), 'P&G-SL'!N$1, INDIRECT("input_provisions[concept/supplier]"), 'P&G-SL'!$C93 ) -> 0 | O93: =SUMIFS( INDIRECT("input_provisions[import]"), INDIRECT("input_provisions[yyyymm]"), 'P&G-SL'!O$1, INDIRECT("input_provisions[concept/supplier]"), 'P&G-SL'!$C93 ) -> 0 | P93: =SUMIFS( INDIRECT("input_provisions[import]"), INDIRECT("input_provisions[yyyymm]"), 'P&G-SL'!P$1, INDIRECT("input_provisions[concept/supplier]"), 'P&G-SL'!$C93 ) -> 0 | ... T93: =SUMIFS( INDIRECT("input_provisions[import]"), INDIRECT("input_provisions[yyyymm]"), 'P&G-SL'!T$1, INDIRECT("input_provisions[concept/supplier]"), 'P&G-SL'!$C93 ) -> 0 | U93: =SUM(I93:T93) -> 42565.15
C94: marketing - meta -> SL | G94: meta | I94: =SUMIFS( INDIRECT("input_provisions[import]"), INDIRECT("input_provisions[yyyymm]"), 'P&G-SL'!I$1, INDIRECT("input_provisions[concept/supplier]"), 'P&G-SL'!$C94 ) -> 20319.33 | J94: =SUMIFS( INDIRECT("input_provisions[import]"), INDIRECT("input_provisions[yyyymm]"), 'P&G-SL'!J$1, INDIRECT("input_provisions[concept/supplier]"), 'P&G-SL'!$C94 ) -> 15883.55 | K94: =SUMIFS( INDIRECT("input_provisions[import]"), INDIRECT("input_provisions[yyyymm]"), 'P&G-SL'!K$1, INDIRECT("input_provisions[concept/supplier]"), 'P&G-SL'!$C94 ) -> 0 | L94: =SUMIFS( INDIRECT("input_provisions[import]"), INDIRECT("input_provisions[yyyymm]"), 'P&G-SL'!L$1, INDIRECT("input_provisions[concept/supplier]"), 'P&G-SL'!$C94 ) -> 0 | M94: =SUMIFS( INDIRECT("input_provisions[import]"), INDIRECT("input_provisions[yyyymm]"), 'P&G-SL'!M$1, INDIRECT("input_provisions[concept/supplier]"), 'P&G-SL'!$C94 ) -> 0 | N94: =SUMIFS( INDIRECT("input_provisions[import]"), INDIRECT("input_provisions[yyyymm]"), 'P&G-SL'!N$1, INDIRECT("input_provisions[concept/supplier]"), 'P&G-SL'!$C94 ) -> 0 | O94: =SUMIFS( INDIRECT("input_provisions[import]"), INDIRECT("input_provisions[yyyymm]"), 'P&G-SL'!O$1, INDIRECT("input_provisions[concept/supplier]"), 'P&G-SL'!$C94 ) -> 0 | P94: =SUMIFS( INDIRECT("input_provisions[import]"), INDIRECT("input_provisions[yyyymm]"), 'P&G-SL'!P$1, INDIRECT("input_provisions[concept/supplier]"), 'P&G-SL'!$C94 ) -> 0 | ... T94: =SUMIFS( INDIRECT("input_provisions[import]"), INDIRECT("input_provisions[yyyymm]"), 'P&G-SL'!T$1, INDIRECT("input_provisions[concept/supplier]"), 'P&G-SL'!$C94 ) -> 0 | U94: =SUM(I94:T94) -> 36202.88
F95: Shared services - UK | I95: =SUM(I96:I97) -> 6005.65 | J95: =SUM(J96:J97) -> 7802.34 | K95: =SUM(K96:K97) -> 0 | L95: =SUM(L96:L97) -> 0 | M95: =SUM(M96:M97) -> 0 | N95: =SUM(N96:N97) -> 0 | O95: =SUM(O96:O97) -> 0 | P95: =SUM(P96:P97) -> 0 | ... T95: =SUM(T96:T97) -> 0 | U95: =SUM(I95:T95) -> 13807.99
C96: marketing - google -> Ltd | G96: google | I96: =SUMIFS( INDIRECT("input_provisions[import]"), INDIRECT("input_provisions[yyyymm]"), 'P&G-SL'!I$1, INDIRECT("input_provisions[concept/supplier]"), 'P&G-SL'!$C96 ) -> 2620.19 | J96: =SUMIFS( INDIRECT("input_provisions[import]"), INDIRECT("input_provisions[yyyymm]"), 'P&G-SL'!J$1, INDIRECT("input_provisions[concept/supplier]"), 'P&G-SL'!$C96 ) -> 5008.3 | K96: =SUMIFS( INDIRECT("input_provisions[import]"), INDIRECT("input_provisions[yyyymm]"), 'P&G-SL'!K$1, INDIRECT("input_provisions[concept/supplier]"), 'P&G-SL'!$C96 ) -> 0 | L96: =SUMIFS( INDIRECT("input_provisions[import]"), INDIRECT("input_provisions[yyyymm]"), 'P&G-SL'!L$1, INDIRECT("input_provisions[concept/supplier]"), 'P&G-SL'!$C96 ) -> 0 | M96: =SUMIFS( INDIRECT("input_provisions[import]"), INDIRECT("input_provisions[yyyymm]"), 'P&G-SL'!M$1, INDIRECT("input_provisions[concept/supplier]"), 'P&G-SL'!$C96 ) -> 0 | N96: =SUMIFS( INDIRECT("input_provisions[import]"), INDIRECT("input_provisions[yyyymm]"), 'P&G-SL'!N$1, INDIRECT("input_provisions[concept/supplier]"), 'P&G-SL'!$C96 ) -> 0 | O96: =SUMIFS( INDIRECT("input_provisions[import]"), INDIRECT("input_provisions[yyyymm]"), 'P&G-SL'!O$1, INDIRECT("input_provisions[concept/supplier]"), 'P&G-SL'!$C96 ) -> 0 | P96: =SUMIFS( INDIRECT("input_provisions[import]"), INDIRECT("input_provisions[yyyymm]"), 'P&G-SL'!P$1, INDIRECT("input_provisions[concept/supplier]"), 'P&G-SL'!$C96 ) -> 0 | ... T96: =SUMIFS( INDIRECT("input_provisions[import]"), INDIRECT("input_provisions[yyyymm]"), 'P&G-SL'!T$1, INDIRECT("input_provisions[concept/supplier]"), 'P&G-SL'!$C96 ) -> 0 | U96: =SUM(I96:T96) -> 7628.49
C97: marketing - meta -> Ltd | G97: meta | I97: =SUMIFS( INDIRECT("input_provisions[import]"), INDIRECT("input_provisions[yyyymm]"), 'P&G-SL'!I$1, INDIRECT("input_provisions[concept/supplier]"), 'P&G-SL'!$C97 ) -> 3385.46 | J97: =SUMIFS( INDIRECT("input_provisions[import]"), INDIRECT("input_provisions[yyyymm]"), 'P&G-SL'!J$1, INDIRECT("input_provisions[concept/supplier]"), 'P&G-SL'!$C97 ) -> 2794.04 | K97: =SUMIFS( INDIRECT("input_provisions[import]"), INDIRECT("input_provisions[yyyymm]"), 'P&G-SL'!K$1, INDIRECT("input_provisions[concept/supplier]"), 'P&G-SL'!$C97 ) -> 0 | L97: =SUMIFS( INDIRECT("input_provisions[import]"), INDIRECT("input_provisions[yyyymm]"), 'P&G-SL'!L$1, INDIRECT("input_provisions[concept/supplier]"), 'P&G-SL'!$C97 ) -> 0 | M97: =SUMIFS( INDIRECT("input_provisions[import]"), INDIRECT("input_provisions[yyyymm]"), 'P&G-SL'!M$1, INDIRECT("input_provisions[concept/supplier]"), 'P&G-SL'!$C97 ) -> 0 | N97: =SUMIFS( INDIRECT("input_provisions[import]"), INDIRECT("input_provisions[yyyymm]"), 'P&G-SL'!N$1, INDIRECT("input_provisions[concept/supplier]"), 'P&G-SL'!$C97 ) -> 0 | O97: =SUMIFS( INDIRECT("input_provisions[import]"), INDIRECT("input_provisions[yyyymm]"), 'P&G-SL'!O$1, INDIRECT("input_provisions[concept/supplier]"), 'P&G-SL'!$C97 ) -> 0 | P97: =SUMIFS( INDIRECT("input_provisions[import]"), INDIRECT("input_provisions[yyyymm]"), 'P&G-SL'!P$1, INDIRECT("input_provisions[concept/supplier]"), 'P&G-SL'!$C97 ) -> 0 | ... T97: =SUMIFS( INDIRECT("input_provisions[import]"), INDIRECT("input_provisions[yyyymm]"), 'P&G-SL'!T$1, INDIRECT("input_provisions[concept/supplier]"), 'P&G-SL'!$C97 ) -> 0 | U97: =SUM(I97:T97) -> 6179.5
F98: Shared services - US | I98: =SUM(I99:I100) -> 3899.81 | J98: =SUM(J99:J100) -> 4744.08 | K98: =SUM(K99:K100) -> 0 | L98: =SUM(L99:L100) -> 0 | M98: =SUM(M99:M100) -> 0 | N98: =SUM(N99:N100) -> 0 | O98: =SUM(O99:O100) -> 0 | P98: =SUM(P99:P100) -> 0 | ... T98: =SUM(T99:T100) -> 0 | U98: =SUM(I98:T98) -> 8643.89
C99: marketing - google -> Inc | G99: google | I99: =SUMIFS( INDIRECT("input_provisions[import]"), INDIRECT("input_provisions[yyyymm]"), 'P&G-SL'!I$1, INDIRECT("input_provisions[concept/supplier]"), 'P&G-SL'!$C99 ) -> 2120.13 | J99: =SUMIFS( INDIRECT("input_provisions[import]"), INDIRECT("input_provisions[yyyymm]"), 'P&G-SL'!J$1, INDIRECT("input_provisions[concept/supplier]"), 'P&G-SL'!$C99 ) -> 3346.68 | K99: =SUMIFS( INDIRECT("input_provisions[import]"), INDIRECT("input_provisions[yyyymm]"), 'P&G-SL'!K$1, INDIRECT("input_provisions[concept/supplier]"), 'P&G-SL'!$C99 ) -> 0 | L99: =SUMIFS( INDIRECT("input_provisions[import]"), INDIRECT("input_provisions[yyyymm]"), 'P&G-SL'!L$1, INDIRECT("input_provisions[concept/supplier]"), 'P&G-SL'!$C99 ) -> 0 | M99: =SUMIFS( INDIRECT("input_provisions[import]"), INDIRECT("input_provisions[yyyymm]"), 'P&G-SL'!M$1, INDIRECT("input_provisions[concept/supplier]"), 'P&G-SL'!$C99 ) -> 0 | N99: =SUMIFS( INDIRECT("input_provisions[import]"), INDIRECT("input_provisions[yyyymm]"), 'P&G-SL'!N$1, INDIRECT("input_provisions[concept/supplier]"), 'P&G-SL'!$C99 ) -> 0 | O99: =SUMIFS( INDIRECT("input_provisions[import]"), INDIRECT("input_provisions[yyyymm]"), 'P&G-SL'!O$1, INDIRECT("input_provisions[concept/supplier]"), 'P&G-SL'!$C99 ) -> 0 | P99: =SUMIFS( INDIRECT("input_provisions[import]"), INDIRECT("input_provisions[yyyymm]"), 'P&G-SL'!P$1, INDIRECT("input_provisions[concept/supplier]"), 'P&G-SL'!$C99 ) -> 0 | ... T99: =SUMIFS( INDIRECT("input_provisions[import]"), INDIRECT("input_provisions[yyyymm]"), 'P&G-SL'!T$1, INDIRECT("input_provisions[concept/supplier]"), 'P&G-SL'!$C99 ) -> 0 | U99: =SUM(I99:T99) -> 5466.81
C100: marketing - meta -> Inc | G100: meta | I100: =SUMIFS( INDIRECT("input_provisions[import]"), INDIRECT("input_provisions[yyyymm]"), 'P&G-SL'!I$1, INDIRECT("input_provisions[concept/supplier]"), 'P&G-SL'!$C100 ) -> 1779.68 | J100: =SUMIFS( INDIRECT("input_provisions[import]"), INDIRECT("input_provisions[yyyymm]"), 'P&G-SL'!J$1, INDIRECT("input_provisions[concept/supplier]"), 'P&G-SL'!$C100 ) -> 1397.4 | K100: =SUMIFS( INDIRECT("input_provisions[import]"), INDIRECT("input_provisions[yyyymm]"), 'P&G-SL'!K$1, INDIRECT("input_provisions[concept/supplier]"), 'P&G-SL'!$C100 ) -> 0 | L100: =SUMIFS( INDIRECT("input_provisions[import]"), INDIRECT("input_provisions[yyyymm]"), 'P&G-SL'!L$1, INDIRECT("input_provisions[concept/supplier]"), 'P&G-SL'!$C100 ) -> 0 | M100: =SUMIFS( INDIRECT("input_provisions[import]"), INDIRECT("input_provisions[yyyymm]"), 'P&G-SL'!M$1, INDIRECT("input_provisions[concept/supplier]"), 'P&G-SL'!$C100 ) -> 0 | N100: =SUMIFS( INDIRECT("input_provisions[import]"), INDIRECT("input_provisions[yyyymm]"), 'P&G-SL'!N$1, INDIRECT("input_provisions[concept/supplier]"), 'P&G-SL'!$C100 ) -> 0 | O100: =SUMIFS( INDIRECT("input_provisions[import]"), INDIRECT("input_provisions[yyyymm]"), 'P&G-SL'!O$1, INDIRECT("input_provisions[concept/supplier]"), 'P&G-SL'!$C100 ) -> 0 | P100: =SUMIFS( INDIRECT("input_provisions[import]"), INDIRECT("input_provisions[yyyymm]"), 'P&G-SL'!P$1, INDIRECT("input_provisions[concept/supplier]"), 'P&G-SL'!$C100 ) -> 0 | ... T100: =SUMIFS( INDIRECT("input_provisions[import]"), INDIRECT("input_provisions[yyyymm]"), 'P&G-SL'!T$1, INDIRECT("input_provisions[concept/supplier]"), 'P&G-SL'!$C100 ) -> 0 | U100: =SUM(I100:T100) -> 3177.08
I102: =+I103/I$84 -> 0.24110806 | J102: =+J103/J$84 -> 0.20517617 | K102: =+K103/K$84 -> 0 | L102: =+L103/L$84 -> #DIV/0! | M102: =+M103/M$84 -> #DIV/0! | N102: =+N103/N$84 -> #DIV/0! | O102: =+O103/O$84 -> #DIV/0! | P102: =+P103/P$84 -> #DIV/0! | ... T102: =+T103/T$84 -> #DIV/0!
E103: Staff | I103: =SUM(I104:I107) -> 14731.84 | J103: =SUM(J104:J107) -> 14915.68 | K103: =SUM(K104:K107) -> 0 | L103: =SUM(L104:L107) -> 0 | M103: =SUM(M104:M107) -> 0 | N103: =SUM(N104:N107) -> 0 | O103: =SUM(O104:O107) -> 0 | P103: =SUM(P104:P107) -> 0 | ... T103: =SUM(T104:T107) -> 0 | U103: =SUM(I103:T103) -> 29647.52
C104: staff - nomina-ceo -> SL | H104: CEO | I104: =SUMIFS( INDIRECT("input_staff[import]"), INDIRECT("input_staff[yyyymm]"), 'P&G-SL'!I$1, INDIRECT("input_staff[concept/supplier]"), 'P&G-SL'!$C104 ) -> 6174.01 | J104: =SUMIFS( INDIRECT("input_staff[import]"), INDIRECT("input_staff[yyyymm]"), 'P&G-SL'!J$1, INDIRECT("input_staff[concept/supplier]"), 'P&G-SL'!$C104 ) -> 6174.01 | K104: =SUMIFS( INDIRECT("input_staff[import]"), INDIRECT("input_staff[yyyymm]"), 'P&G-SL'!K$1, INDIRECT("input_staff[concept/supplier]"), 'P&G-SL'!$C104 ) -> 0 | L104: =SUMIFS( INDIRECT("input_staff[import]"), INDIRECT("input_staff[yyyymm]"), 'P&G-SL'!L$1, INDIRECT("input_staff[concept/supplier]"), 'P&G-SL'!$C104 ) -> 0 | M104: =SUMIFS( INDIRECT("input_staff[import]"), INDIRECT("input_staff[yyyymm]"), 'P&G-SL'!M$1, INDIRECT("input_staff[concept/supplier]"), 'P&G-SL'!$C104 ) -> 0 | N104: =SUMIFS( INDIRECT("input_staff[import]"), INDIRECT("input_staff[yyyymm]"), 'P&G-SL'!N$1, INDIRECT("input_staff[concept/supplier]"), 'P&G-SL'!$C104 ) -> 0 | O104: =SUMIFS( INDIRECT("input_staff[import]"), INDIRECT("input_staff[yyyymm]"), 'P&G-SL'!O$1, INDIRECT("input_staff[concept/supplier]"), 'P&G-SL'!$C104 ) -> 0 | P104: =SUMIFS( INDIRECT("input_staff[import]"), INDIRECT("input_staff[yyyymm]"), 'P&G-SL'!P$1, INDIRECT("input_staff[concept/supplier]"), 'P&G-SL'!$C104 ) -> 0 | ... T104: =SUMIFS( INDIRECT("input_staff[import]"), INDIRECT("input_staff[yyyymm]"), 'P&G-SL'!T$1, INDIRECT("input_staff[concept/supplier]"), 'P&G-SL'!$C104 ) -> 0 | U104: =SUM(I104:T104) -> 12348.02
C105: staff - nomina-coo -> SL | H105: COO | I105: =SUMIFS( INDIRECT("input_staff[import]"), INDIRECT("input_staff[yyyymm]"), 'P&G-SL'!I$1, INDIRECT("input_staff[concept/supplier]"), 'P&G-SL'!$C105 ) -> 6174.01 | J105: =SUMIFS( INDIRECT("input_staff[import]"), INDIRECT("input_staff[yyyymm]"), 'P&G-SL'!J$1, INDIRECT("input_staff[concept/supplier]"), 'P&G-SL'!$C105 ) -> 6174.01 | K105: =SUMIFS( INDIRECT("input_staff[import]"), INDIRECT("input_staff[yyyymm]"), 'P&G-SL'!K$1, INDIRECT("input_staff[concept/supplier]"), 'P&G-SL'!$C105 ) -> 0 | L105: =SUMIFS( INDIRECT("input_staff[import]"), INDIRECT("input_staff[yyyymm]"), 'P&G-SL'!L$1, INDIRECT("input_staff[concept/supplier]"), 'P&G-SL'!$C105 ) -> 0 | M105: =SUMIFS( INDIRECT("input_staff[import]"), INDIRECT("input_staff[yyyymm]"), 'P&G-SL'!M$1, INDIRECT("input_staff[concept/supplier]"), 'P&G-SL'!$C105 ) -> 0 | N105: =SUMIFS( INDIRECT("input_staff[import]"), INDIRECT("input_staff[yyyymm]"), 'P&G-SL'!N$1, INDIRECT("input_staff[concept/supplier]"), 'P&G-SL'!$C105 ) -> 0 | O105: =SUMIFS( INDIRECT("input_staff[import]"), INDIRECT("input_staff[yyyymm]"), 'P&G-SL'!O$1, INDIRECT("input_staff[concept/supplier]"), 'P&G-SL'!$C105 ) -> 0 | P105: =SUMIFS( INDIRECT("input_staff[import]"), INDIRECT("input_staff[yyyymm]"), 'P&G-SL'!P$1, INDIRECT("input_staff[concept/supplier]"), 'P&G-SL'!$C105 ) -> 0 | ... T105: =SUMIFS( INDIRECT("input_staff[import]"), INDIRECT("input_staff[yyyymm]"), 'P&G-SL'!T$1, INDIRECT("input_staff[concept/supplier]"), 'P&G-SL'!$C105 ) -> 0 | U105: =SUM(I105:T105) -> 12348.02 | W105: -14731.84 | X105: -14915.68 | Y105: =+X105-W105 -> -183.84
C106: staff - nomina-sac -> SL | H106: SAC | I106: =SUMIFS( INDIRECT("input_staff[import]"), INDIRECT("input_staff[yyyymm]"), 'P&G-SL'!I$1, INDIRECT("input_staff[concept/supplier]"), 'P&G-SL'!$C106 ) -> 2383.82 | J106: =SUMIFS( INDIRECT("input_staff[import]"), INDIRECT("input_staff[yyyymm]"), 'P&G-SL'!J$1, INDIRECT("input_staff[concept/supplier]"), 'P&G-SL'!$C106 ) -> 2383.82 | K106: =SUMIFS( INDIRECT("input_staff[import]"), INDIRECT("input_staff[yyyymm]"), 'P&G-SL'!K$1, INDIRECT("input_staff[concept/supplier]"), 'P&G-SL'!$C106 ) -> 0 | L106: =SUMIFS( INDIRECT("input_staff[import]"), INDIRECT("input_staff[yyyymm]"), 'P&G-SL'!L$1, INDIRECT("input_staff[concept/supplier]"), 'P&G-SL'!$C106 ) -> 0 | M106: =SUMIFS( INDIRECT("input_staff[import]"), INDIRECT("input_staff[yyyymm]"), 'P&G-SL'!M$1, INDIRECT("input_staff[concept/supplier]"), 'P&G-SL'!$C106 ) -> 0 | N106: =SUMIFS( INDIRECT("input_staff[import]"), INDIRECT("input_staff[yyyymm]"), 'P&G-SL'!N$1, INDIRECT("input_staff[concept/supplier]"), 'P&G-SL'!$C106 ) -> 0 | O106: =SUMIFS( INDIRECT("input_staff[import]"), INDIRECT("input_staff[yyyymm]"), 'P&G-SL'!O$1, INDIRECT("input_staff[concept/supplier]"), 'P&G-SL'!$C106 ) -> 0 | P106: =SUMIFS( INDIRECT("input_staff[import]"), INDIRECT("input_staff[yyyymm]"), 'P&G-SL'!P$1, INDIRECT("input_staff[concept/supplier]"), 'P&G-SL'!$C106 ) -> 0 | ... T106: =SUMIFS( INDIRECT("input_staff[import]"), INDIRECT("input_staff[yyyymm]"), 'P&G-SL'!T$1, INDIRECT("input_staff[concept/supplier]"), 'P&G-SL'!$C106 ) -> 0 | U106: =SUM(I106:T106) -> 4767.64
C107: staff - nomina-mkt -> SL | H107: Marketing Trainee | I107: =SUMIFS( INDIRECT("input_staff[import]"), INDIRECT("input_staff[yyyymm]"), 'P&G-SL'!I$1, INDIRECT("input_staff[concept/supplier]"), 'P&G-SL'!$C107 ) -> 0 | J107: =SUMIFS( INDIRECT("input_staff[import]"), INDIRECT("input_staff[yyyymm]"), 'P&G-SL'!J$1, INDIRECT("input_staff[concept/supplier]"), 'P&G-SL'!$C107 ) -> 183.84 | K107: =SUMIFS( INDIRECT("input_staff[import]"), INDIRECT("input_staff[yyyymm]"), 'P&G-SL'!K$1, INDIRECT("input_staff[concept/supplier]"), 'P&G-SL'!$C107 ) -> 0 | L107: =SUMIFS( INDIRECT("input_staff[import]"), INDIRECT("input_staff[yyyymm]"), 'P&G-SL'!L$1, INDIRECT("input_staff[concept/supplier]"), 'P&G-SL'!$C107 ) -> 0 | M107: =SUMIFS( INDIRECT("input_staff[import]"), INDIRECT("input_staff[yyyymm]"), 'P&G-SL'!M$1, INDIRECT("input_staff[concept/supplier]"), 'P&G-SL'!$C107 ) -> 0 | N107: =SUMIFS( INDIRECT("input_staff[import]"), INDIRECT("input_staff[yyyymm]"), 'P&G-SL'!N$1, INDIRECT("input_staff[concept/supplier]"), 'P&G-SL'!$C107 ) -> 0 | O107: =SUMIFS( INDIRECT("input_staff[import]"), INDIRECT("input_staff[yyyymm]"), 'P&G-SL'!O$1, INDIRECT("input_staff[concept/supplier]"), 'P&G-SL'!$C107 ) -> 0 | P107: =SUMIFS( INDIRECT("input_staff[import]"), INDIRECT("input_staff[yyyymm]"), 'P&G-SL'!P$1, INDIRECT("input_staff[concept/supplier]"), 'P&G-SL'!$C107 ) -> 0 | ... T107: =SUMIFS( INDIRECT("input_staff[import]"), INDIRECT("input_staff[yyyymm]"), 'P&G-SL'!T$1, INDIRECT("input_staff[concept/supplier]"), 'P&G-SL'!$C107 ) -> 0 | U107: =SUM(I107:T107) -> 183.84
H108: Finance
G109: Shared services - UK | I109: =+I103*0.2 -> 2946.368 | J109: =+J103*0.2 -> 2983.136 | K109: =+K103*0.2 -> 0 | L109: =+L103*0.2 -> 0 | M109: =+M103*0.2 -> 0 | N109: =+N103*0.2 -> 0 | O109: =+O103*0.2 -> 0 | P109: =+P103*0.2 -> 0 | ... T109: =+T103*0.2 -> 0 | U109: =SUM(I109:T109) -> 5929.504
G110: Shared services - US | I110: =+I103*0.2 -> 2946.368 | J110: =+J103*0.2 -> 2983.136 | K110: =+K103*0 -> 0 | L110: =+L103*0 -> 0 | M110: =+M103*0 -> 0 | N110: =+N103*0.2 -> 0 | O110: =+O103*0.2 -> 0 | P110: =+P103*0.2 -> 0 | Q110: =+Q103*0.2 -> 0 | R110: =+R103*0.2 -> 0 | S110: =+S103*0.2 -> 0 | T110: =+T103*0.2 -> 0 | U110: =SUM(I110:T110) -> 5929.504
I112: =+I113/I$84 -> 0.10979953 | J112: =+J113/J$84 -> 0.094673374 | K112: =+K113/K$84 -> 0 | L112: =+L113/L$84 -> #DIV/0! | M112: =+M113/M$84 -> #DIV/0! | N112: =+N113/N$84 -> #DIV/0! | O112: =+O113/O$84 -> #DIV/0! | P112: =+P113/P$84 -> #DIV/0! | ... T112: =+T113/T$84 -> #DIV/0!
E113: Administrative costs | I113: =+I114+I121 -> 6708.8141 | J113: =+J114+J121 -> 6882.4646 | K113: =+K114+K121 -> 0 | L113: =+L114+L121 -> 0 | M113: =+M114+M121 -> 0 | N113: =+N114+N121 -> 0 | O113: =+O114+O121 -> 0 | P113: =+P114+P121 -> 0 | ... T113: =+T114+T121 -> 0 | U113: =SUM(I113:T113) -> 13591.279
G114: Administración y legal | I114: =SUM(I115:I120) -> 2764.9041 | J114: =SUM(J115:J120) -> 2842.548 | K114: =SUM(K115:K120) -> 0 | L114: =SUM(L115:L120) -> 0 | M114: =SUM(M115:M120) -> 0 | N114: =SUM(N115:N120) -> 0 | O114: =SUM(O115:O120) -> 0 | P114: =SUM(P115:P120) -> 0 | ... T114: =SUM(T115:T120) -> 0 | U114: =SUM(I114:T114) -> 5607.4521
C115: administrative - Claris Gestio -> SL | H115: Claris Gestió | I115: =SUMIFS( INDIRECT("input_invoice[net]"), INDIRECT("input_invoice[yyyymm]"), 'P&G-SL'!I$1, INDIRECT("input_invoice[concept/supplier]"), 'P&G-SL'!$C115 ) -> 808.08 | J115: =SUMIFS( INDIRECT("input_invoice[net]"), INDIRECT("input_invoice[yyyymm]"), 'P&G-SL'!J$1, INDIRECT("input_invoice[concept/supplier]"), 'P&G-SL'!$C115 ) -> 808.08 | K115: =SUMIFS( INDIRECT("input_invoice[net]"), INDIRECT("input_invoice[yyyymm]"), 'P&G-SL'!K$1, INDIRECT("input_invoice[concept/supplier]"), 'P&G-SL'!$C115 ) -> 0 | L115: =SUMIFS( INDIRECT("input_invoice[net]"), INDIRECT("input_invoice[yyyymm]"), 'P&G-SL'!L$1, INDIRECT("input_invoice[concept/supplier]"), 'P&G-SL'!$C115 ) -> 0 | M115: =SUMIFS( INDIRECT("input_invoice[net]"), INDIRECT("input_invoice[yyyymm]"), 'P&G-SL'!M$1, INDIRECT("input_invoice[concept/supplier]"), 'P&G-SL'!$C115 ) -> 0 | N115: =SUMIFS( INDIRECT("input_invoice[net]"), INDIRECT("input_invoice[yyyymm]"), 'P&G-SL'!N$1, INDIRECT("input_invoice[concept/supplier]"), 'P&G-SL'!$C115 ) -> 0 | O115: =SUMIFS( INDIRECT("input_invoice[net]"), INDIRECT("input_invoice[yyyymm]"), 'P&G-SL'!O$1, INDIRECT("input_invoice[concept/supplier]"), 'P&G-SL'!$C115 ) -> 0 | P115: =SUMIFS( INDIRECT("input_invoice[net]"), INDIRECT("input_invoice[yyyymm]"), 'P&G-SL'!P$1, INDIRECT("input_invoice[concept/supplier]"), 'P&G-SL'!$C115 ) -> 0 | ... T115: =SUMIFS( INDIRECT("input_invoice[net]"), INDIRECT("input_invoice[yyyymm]"), 'P&G-SL'!T$1, INDIRECT("input_invoice[concept/supplier]"), 'P&G-SL'!$C115 ) -> 0 | U115: =SUM(I115:T115) -> 1616.16
...

Sheet P&G-Ltd
H1: 202601 | I1: 202602 | J1: 202603 | K1: 202604 | L1: 202605 | M1: 202606 | N1: 202607 | O1: 202608 | P1: 202609 | Q1: 202610 | R1: 202611 | S1: 202612
D2: =+#REF!&"-"&#REF! -> #REF! | H2: Enero | I2: Febrero | J2: Marzo | K2: Abril | L2: Mayo | M2: Junio | N2: Julio | O2: Agosto | P2: Septiembre | Q2: Octubre | R2: Noviembre | S2: Diciembre | T2: Total
D3: Turnover | H3: =+H4 -> 15702.66 | I3: =+I4 -> 19429.25 | J3: =+J4 -> 13642.64 | K3: =+K4 -> 0 | L3: =+L4 -> 0 | M3: =+M4 -> 0 | N3: =+N4 -> 0 | O3: =+O4 -> 0 | ... S3: =+S4 -> 0 | T3: =SUM(H3:S3) -> 48774.55
A4: Hannun | B4: Mirakl | C4: Country | D4: Sales | H4: =+H5 -> 15702.66 | I4: =+I5 -> 19429.25 | J4: =+J5 -> 13642.64 | K4: =+K5 -> 0 | L4: =+L5 -> 0 | M4: =+M5 -> 0 | N4: =+N5 -> 0 | O4: =+O5 -> 0 | ... S4: =+S5 -> 0 | T4: =SUM(H4:S4) -> 48774.55
D5: #VALUE! | E5: United Kingdom | H5: =+H7+H8 -> 15702.66 | I5: =+I7+I8 -> 19429.25 | J5: =+J7+J8 -> 13642.64 | K5: =+K7+K8 -> 0 | L5: =+L7+L8 -> 0 | M5: =+M7+M8 -> 0 | N5: =+N7+N8 -> 0 | O5: =+O7+O8 -> 0 | ... S5: =+S7+S8 -> 0 | T5: =SUM(H5:S5) -> 48774.55
G6: Share % | H6: =IFERROR(+H5/H$4,0) -> 1 | I6: =IFERROR(+I5/I$4,0) -> 1 | J6: =IFERROR(+J5/J$4,0) -> 1 | K6: =IFERROR(+K5/K$4,0) -> 0 | L6: =IFERROR(+L5/L$4,0) -> 0 | M6: =IFERROR(+M5/M$4,0) -> 0 | N6: =IFERROR(+N5/N$4,0) -> 0 | O6: =IFERROR(+O5/O$4,0) -> 0 | ... T6: =IFERROR(+T5/T$4,0) -> 1
A7: 0 | B7: 0 | C7: GB | F7: Shopify | H7: =SUMIFS('i-sales'!$K:$K, 'i-sales'!$C:$C,'P&G-Ltd'!H$1, 'i-sales'!$D:$D,'P&G-Ltd'!$C7, 'i-sales'!$G:$G,'P&G-Ltd'!$A7, 'i-sales'!$H:$H,'P&G-Ltd'!$B7 ) -> 15702.66 | I7: =SUMIFS('i-sales'!$K:$K, 'i-sales'!$C:$C,'P&G-Ltd'!I$1, 'i-sales'!$D:$D,'P&G-Ltd'!$C7, 'i-sales'!$G:$G,'P&G-Ltd'!$A7, 'i-sales'!$H:$H,'P&G-Ltd'!$B7 ) -> 19429.25 | J7: =SUMIFS('i-sales'!$K:$K, 'i-sales'!$C:$C,'P&G-Ltd'!J$1, 'i-sales'!$D:$D,'P&G-Ltd'!$C7, 'i-sales'!$G:$G,'P&G-Ltd'!$A7, 'i-sales'!$H:$H,'P&G-Ltd'!$B7 ) -> 13642.64 | K7: =SUMIFS('i-sales'!$K:$K, 'i-sales'!$C:$C,'P&G-Ltd'!K$1, 'i-sales'!$D:$D,'P&G-Ltd'!$C7, 'i-sales'!$G:$G,'P&G-Ltd'!$A7, 'i-sales'!$H:$H,'P&G-Ltd'!$B7 ) -> 0 | L7: =SUMIFS('i-sales'!$K:$K, 'i-sales'!$C:$C,'P&G-Ltd'!L$1, 'i-sales'!$D:$D,'P&G-Ltd'!$C7, 'i-sales'!$G:$G,'P&G-Ltd'!$A7, 'i-sales'!$H:$H,'P&G-Ltd'!$B7 ) -> 0 | M7: =SUMIFS('i-sales'!$K:$K, 'i-sales'!$C:$C,'P&G-Ltd'!M$1, 'i-sales'!$D:$D,'P&G-Ltd'!$C7, 'i-sales'!$G:$G,'P&G-Ltd'!$A7, 'i-sales'!$H:$H,'P&G-Ltd'!$B7 ) -> 0 | N7: =SUMIFS('i-sales'!$K:$K, 'i-sales'!$C:$C,'P&G-Ltd'!N$1, 'i-sales'!$D:$D,'P&G-Ltd'!$C7, 'i-sales'!$G:$G,'P&G-Ltd'!$A7, 'i-sales'!$H:$H,'P&G-Ltd'!$B7 ) -> 0 | O7: =SUMIFS('i-sales'!$K:$K, 'i-sales'!$C:$C,'P&G-Ltd'!O$1, 'i-sales'!$D:$D,'P&G-Ltd'!$C7, 'i-sales'!$G:$G,'P&G-Ltd'!$A7, 'i-sales'!$H:$H,'P&G-Ltd'!$B7 ) -> 0 | ... S7: =SUMIFS('i-sales'!$K:$K, 'i-sales'!$C:$C,'P&G-Ltd'!S$1, 'i-sales'!$D:$D,'P&G-Ltd'!$C7, 'i-sales'!$G:$G,'P&G-Ltd'!$A7, 'i-sales'!$H:$H,'P&G-Ltd'!$B7 ) -> 0 | T7: =SUM(H7:S7) -> 48774.55
F8: Marketplaces | H8: =SUM(H9:H14) -> 0 | I8: =SUM(I9:I14) -> 0 | J8: =SUM(J9:J14) -> 0 | K8: =SUM(K9:K14) -> 0 | L8: =SUM(L9:L14) -> 0 | M8: =SUM(M9:M14) -> 0 | N8: =SUM(N9:N14) -> 0 | O8: =SUM(O9:O14) -> 0 | ... S8: =SUM(S9:S14) -> 0 | T8: =SUM(H8:S8) -> 0
G9: Amazon Seller | T9: =SUM(H9:S9) -> 0
G10: Choose | T10: =SUM(H10:S10) -> 0
A11: 1 | B11: 0 | C11: GB | G11: Hannun | H11: =SUMIFS('i-sales'!$K:$K, 'i-sales'!$C:$C,'P&G-Ltd'!H$1, 'i-sales'!$D:$D,'P&G-Ltd'!$C11, 'i-sales'!$G:$G,'P&G-Ltd'!$A11, 'i-sales'!$H:$H,'P&G-Ltd'!$B11 ) -> 0 | I11: =SUMIFS('i-sales'!$K:$K, 'i-sales'!$C:$C,'P&G-Ltd'!I$1, 'i-sales'!$D:$D,'P&G-Ltd'!$C11, 'i-sales'!$G:$G,'P&G-Ltd'!$A11, 'i-sales'!$H:$H,'P&G-Ltd'!$B11 ) -> 0 | J11: =SUMIFS('i-sales'!$K:$K, 'i-sales'!$C:$C,'P&G-Ltd'!J$1, 'i-sales'!$D:$D,'P&G-Ltd'!$C11, 'i-sales'!$G:$G,'P&G-Ltd'!$A11, 'i-sales'!$H:$H,'P&G-Ltd'!$B11 ) -> 0 | K11: =SUMIFS('i-sales'!$K:$K, 'i-sales'!$C:$C,'P&G-Ltd'!K$1, 'i-sales'!$D:$D,'P&G-Ltd'!$C11, 'i-sales'!$G:$G,'P&G-Ltd'!$A11, 'i-sales'!$H:$H,'P&G-Ltd'!$B11 ) -> 0 | L11: =SUMIFS('i-sales'!$K:$K, 'i-sales'!$C:$C,'P&G-Ltd'!L$1, 'i-sales'!$D:$D,'P&G-Ltd'!$C11, 'i-sales'!$G:$G,'P&G-Ltd'!$A11, 'i-sales'!$H:$H,'P&G-Ltd'!$B11 ) -> 0 | M11: =SUMIFS('i-sales'!$K:$K, 'i-sales'!$C:$C,'P&G-Ltd'!M$1, 'i-sales'!$D:$D,'P&G-Ltd'!$C11, 'i-sales'!$G:$G,'P&G-Ltd'!$A11, 'i-sales'!$H:$H,'P&G-Ltd'!$B11 ) -> 0 | N11: =SUMIFS('i-sales'!$K:$K, 'i-sales'!$C:$C,'P&G-Ltd'!N$1, 'i-sales'!$D:$D,'P&G-Ltd'!$C11, 'i-sales'!$G:$G,'P&G-Ltd'!$A11, 'i-sales'!$H:$H,'P&G-Ltd'!$B11 ) -> 0 | O11: =SUMIFS('i-sales'!$K:$K, 'i-sales'!$C:$C,'P&G-Ltd'!O$1, 'i-sales'!$D:$D,'P&G-Ltd'!$C11, 'i-sales'!$G:$G,'P&G-Ltd'!$A11, 'i-sales'!$H:$H,'P&G-Ltd'!$B11 ) -> 0 | ... S11: =SUMIFS('i-sales'!$K:$K, 'i-sales'!$C:$C,'P&G-Ltd'!S$1, 'i-sales'!$D:$D,'P&G-Ltd'!$C11, 'i-sales'!$G:$G,'P&G-Ltd'!$A11, 'i-sales'!$H:$H,'P&G-Ltd'!$B11 ) -> 0 | T11: =SUM(H11:S11) -> 0
G12: Home24 | T12: =SUM(H12:S12) -> 0
G13: Leroy Merlin | T13: =SUM(H13:S13) -> 0
A14: 0 | B14: 1 | C14: GB | G14: Maisons du Monde | H14: =SUMIFS('i-sales'!$K:$K, 'i-sales'!$C:$C,'P&G-Ltd'!H$1, 'i-sales'!$D:$D,'P&G-Ltd'!$C14, 'i-sales'!$G:$G,'P&G-Ltd'!$A14, 'i-sales'!$H:$H,'P&G-Ltd'!$B14 )/1.21 -> 0 | I14: =SUMIFS('i-sales'!$K:$K, 'i-sales'!$C:$C,'P&G-Ltd'!I$1, 'i-sales'!$D:$D,'P&G-Ltd'!$C14, 'i-sales'!$G:$G,'P&G-Ltd'!$A14, 'i-sales'!$H:$H,'P&G-Ltd'!$B14 )/1.21 -> 0 | J14: =SUMIFS('i-sales'!$K:$K, 'i-sales'!$C:$C,'P&G-Ltd'!J$1, 'i-sales'!$D:$D,'P&G-Ltd'!$C14, 'i-sales'!$G:$G,'P&G-Ltd'!$A14, 'i-sales'!$H:$H,'P&G-Ltd'!$B14 )/1.21 -> 0 | K14: =SUMIFS('i-sales'!$K:$K, 'i-sales'!$C:$C,'P&G-Ltd'!K$1, 'i-sales'!$D:$D,'P&G-Ltd'!$C14, 'i-sales'!$G:$G,'P&G-Ltd'!$A14, 'i-sales'!$H:$H,'P&G-Ltd'!$B14 )/1.21 -> 0 | L14: =SUMIFS('i-sales'!$K:$K, 'i-sales'!$C:$C,'P&G-Ltd'!L$1, 'i-sales'!$D:$D,'P&G-Ltd'!$C14, 'i-sales'!$G:$G,'P&G-Ltd'!$A14, 'i-sales'!$H:$H,'P&G-Ltd'!$B14 )/1.21 -> 0 | M14: =SUMIFS('i-sales'!$K:$K, 'i-sales'!$C:$C,'P&G-Ltd'!M$1, 'i-sales'!$D:$D,'P&G-Ltd'!$C14, 'i-sales'!$G:$G,'P&G-Ltd'!$A14, 'i-sales'!$H:$H,'P&G-Ltd'!$B14 )/1.21 -> 0 | N14: =SUMIFS('i-sales'!$K:$K, 'i-sales'!$C:$C,'P&G-Ltd'!N$1, 'i-sales'!$D:$D,'P&G-Ltd'!$C14, 'i-sales'!$G:$G,'P&G-Ltd'!$A14, 'i-sales'!$H:$H,'P&G-Ltd'!$B14 )/1.21 -> 0 | O14: =SUMIFS('i-sales'!$K:$K, 'i-sales'!$C:$C,'P&G-Ltd'!O$1, 'i-sales'!$D:$D,'P&G-Ltd'!$C14, 'i-sales'!$G:$G,'P&G-Ltd'!$A14, 'i-sales'!$H:$H,'P&G-Ltd'!$B14 )/1.21 -> 0 | ... S14: =SUMIFS('i-sales'!$K:$K, 'i-sales'!$C:$C,'P&G-Ltd'!S$1, 'i-sales'!$D:$D,'P&G-Ltd'!$C14, 'i-sales'!$G:$G,'P&G-Ltd'!$A14, 'i-sales'!$H:$H,'P&G-Ltd'!$B14 )/1.21 -> 0 | T14: =SUM(H14:S14) -> 0
D16: Cost of sales | H16: =+H17+H26+H31+H34+H41 -> #REF! | I16: =+I17+I26+I31+I34+I41 -> #REF! | J16: =+J17+J26+J31+J34+J41 -> #REF! | K16: =+K17+K26+K31+K34+K41 -> #REF! | L16: =+L17+L26+L31+L34+L41 -> #REF! | M16: =+M17+M26+M31+M34+M41 -> #REF! | N16: =+N17+N26+N31+N34+N41 -> #REF! | O16: =+O17+O26+O31+O34+O41 -> #REF! | ... S16: =+S17+S26+S31+S34+S41 -> #REF! | T16: =SUM(H16:S16) -> #REF!
D17: Manufacturing | H17: =SUM(H18:H24) -> 4754.19 | I17: =SUM(I18:I24) -> 4593.8 | J17: =SUM(J18:J24) -> 0 | K17: =SUM(K18:K24) -> 0 | L17: =SUM(L18:L24) -> 0 | M17: =SUM(M18:M24) -> 0 | N17: =SUM(N18:N24) -> 0 | O17: =SUM(O18:O24) -> 0 | ... S17: =SUM(S18:S24) -> 0 | T17: =SUM(H17:S17) -> 9347.99
C18: manufacturing - Proco print -> Ltd | E18: #VALUE! | F18: Proco - Print | H18: =SUMIFS( INDIRECT("input_invoice[net]"), INDIRECT("input_invoice[yyyymm]"), 'P&G-Ltd'!H$1, INDIRECT("input_invoice[concept/supplier]"), 'P&G-Ltd'!$C18 ) -> 964.48 | I18: =SUMIFS( INDIRECT("input_invoice[net]"), INDIRECT("input_invoice[yyyymm]"), 'P&G-Ltd'!I$1, INDIRECT("input_invoice[concept/supplier]"), 'P&G-Ltd'!$C18 ) -> 1235.84 | J18: =SUMIFS( INDIRECT("input_invoice[net]"), INDIRECT("input_invoice[yyyymm]"), 'P&G-Ltd'!J$1, INDIRECT("input_invoice[concept/supplier]"), 'P&G-Ltd'!$C18 ) -> 0 | K18: =SUMIFS( INDIRECT("input_invoice[net]"), INDIRECT("input_invoice[yyyymm]"), 'P&G-Ltd'!K$1, INDIRECT("input_invoice[concept/supplier]"), 'P&G-Ltd'!$C18 ) -> 0 | L18: =SUMIFS( INDIRECT("input_invoice[net]"), INDIRECT("input_invoice[yyyymm]"), 'P&G-Ltd'!L$1, INDIRECT("input_invoice[concept/supplier]"), 'P&G-Ltd'!$C18 ) -> 0 | M18: =SUMIFS( INDIRECT("input_invoice[net]"), INDIRECT("input_invoice[yyyymm]"), 'P&G-Ltd'!M$1, INDIRECT("input_invoice[concept/supplier]"), 'P&G-Ltd'!$C18 ) -> 0 | N18: =SUMIFS( INDIRECT("input_invoice[net]"), INDIRECT("input_invoice[yyyymm]"), 'P&G-Ltd'!N$1, INDIRECT("input_invoice[concept/supplier]"), 'P&G-Ltd'!$C18 ) -> 0 | O18: =SUMIFS( INDIRECT("input_invoice[net]"), INDIRECT("input_invoice[yyyymm]"), 'P&G-Ltd'!O$1, INDIRECT("input_invoice[concept/supplier]"), 'P&G-Ltd'!$C18 ) -> 0 | ... S18: =SUMIFS( INDIRECT("input_invoice[net]"), INDIRECT("input_invoice[yyyymm]"), 'P&G-Ltd'!S$1, INDIRECT("input_invoice[concept/supplier]"), 'P&G-Ltd'!$C18 ) -> 0 | T18: =SUM(H18:S18) -> 2200.32
C19: manufacturing - Proco direct mailing -> Ltd | E19: #VALUE! | F19: Proco - Direct mailing | H19: =SUMIFS( INDIRECT("input_invoice[net]"), INDIRECT("input_invoice[yyyymm]"), 'P&G-Ltd'!H$1, INDIRECT("input_invoice[concept/supplier]"), 'P&G-Ltd'!$C19 ) -> 3092.21 | I19: =SUMIFS( INDIRECT("input_invoice[net]"), INDIRECT("input_invoice[yyyymm]"), 'P&G-Ltd'!I$1, INDIRECT("input_invoice[concept/supplier]"), 'P&G-Ltd'!$C19 ) -> 2737.96 | J19: =SUMIFS( INDIRECT("input_invoice[net]"), INDIRECT("input_invoice[yyyymm]"), 'P&G-Ltd'!J$1, INDIRECT("input_invoice[concept/supplier]"), 'P&G-Ltd'!$C19 ) -> 0 | K19: =SUMIFS( INDIRECT("input_invoice[net]"), INDIRECT("input_invoice[yyyymm]"), 'P&G-Ltd'!K$1, INDIRECT("input_invoice[concept/supplier]"), 'P&G-Ltd'!$C19 ) -> 0 | L19: =SUMIFS( INDIRECT("input_invoice[net]"), INDIRECT("input_invoice[yyyymm]"), 'P&G-Ltd'!L$1, INDIRECT("input_invoice[concept/supplier]"), 'P&G-Ltd'!$C19 ) -> 0 | M19: =SUMIFS( INDIRECT("input_invoice[net]"), INDIRECT("input_invoice[yyyymm]"), 'P&G-Ltd'!M$1, INDIRECT("input_invoice[concept/supplier]"), 'P&G-Ltd'!$C19 ) -> 0 | N19: =SUMIFS( INDIRECT("input_invoice[net]"), INDIRECT("input_invoice[yyyymm]"), 'P&G-Ltd'!N$1, INDIRECT("input_invoice[concept/supplier]"), 'P&G-Ltd'!$C19 ) -> 0 | O19: =SUMIFS( INDIRECT("input_invoice[net]"), INDIRECT("input_invoice[yyyymm]"), 'P&G-Ltd'!O$1, INDIRECT("input_invoice[concept/supplier]"), 'P&G-Ltd'!$C19 ) -> 0 | ... S19: =SUMIFS( INDIRECT("input_invoice[net]"), INDIRECT("input_invoice[yyyymm]"), 'P&G-Ltd'!S$1, INDIRECT("input_invoice[concept/supplier]"), 'P&G-Ltd'!$C19 ) -> 0 | T19: =SUM(H19:S19) -> 5830.17
C20: manufacturing - Proco Storage -> Ltd | E20: #VALUE! | F20: Proco Storage | H20: =SUMIFS( INDIRECT("input_invoice[net]"), INDIRECT("input_invoice[yyyymm]"), 'P&G-Ltd'!H$1, INDIRECT("input_invoice[concept/supplier]"), 'P&G-Ltd'!$C20 ) -> 697.5 | I20: =SUMIFS( INDIRECT("input_invoice[net]"), INDIRECT("input_invoice[yyyymm]"), 'P&G-Ltd'!I$1, INDIRECT("input_invoice[concept/supplier]"), 'P&G-Ltd'!$C20 ) -> 620 | J20: =SUMIFS( INDIRECT("input_invoice[net]"), INDIRECT("input_invoice[yyyymm]"), 'P&G-Ltd'!J$1, INDIRECT("input_invoice[concept/supplier]"), 'P&G-Ltd'!$C20 ) -> 0 | K20: =SUMIFS( INDIRECT("input_invoice[net]"), INDIRECT("input_invoice[yyyymm]"), 'P&G-Ltd'!K$1, INDIRECT("input_invoice[concept/supplier]"), 'P&G-Ltd'!$C20 ) -> 0 | L20: =SUMIFS( INDIRECT("input_invoice[net]"), INDIRECT("input_invoice[yyyymm]"), 'P&G-Ltd'!L$1, INDIRECT("input_invoice[concept/supplier]"), 'P&G-Ltd'!$C20 ) -> 0 | M20: =SUMIFS( INDIRECT("input_invoice[net]"), INDIRECT("input_invoice[yyyymm]"), 'P&G-Ltd'!M$1, INDIRECT("input_invoice[concept/supplier]"), 'P&G-Ltd'!$C20 ) -> 0 | N20: =SUMIFS( INDIRECT("input_invoice[net]"), INDIRECT("input_invoice[yyyymm]"), 'P&G-Ltd'!N$1, INDIRECT("input_invoice[concept/supplier]"), 'P&G-Ltd'!$C20 ) -> 0 | O20: =SUMIFS( INDIRECT("input_invoice[net]"), INDIRECT("input_invoice[yyyymm]"), 'P&G-Ltd'!O$1, INDIRECT("input_invoice[concept/supplier]"), 'P&G-Ltd'!$C20 ) -> 0 | ... S20: =SUMIFS( INDIRECT("input_invoice[net]"), INDIRECT("input_invoice[yyyymm]"), 'P&G-Ltd'!S$1, INDIRECT("input_invoice[concept/supplier]"), 'P&G-Ltd'!$C20 ) -> 0 | T20: =SUM(H20:S20) -> 1317.5
C21: manufacturing - Proco others -> Ltd | E21: #VALUE! | F21: Proco - Others | H21: =SUMIFS( INDIRECT("input_invoice[net]"), INDIRECT("input_invoice[yyyymm]"), 'P&G-Ltd'!H$1, INDIRECT("input_invoice[concept/supplier]"), 'P&G-Ltd'!$C21 ) -> 0 | I21: =SUMIFS( INDIRECT("input_invoice[net]"), INDIRECT("input_invoice[yyyymm]"), 'P&G-Ltd'!I$1, INDIRECT("input_invoice[concept/supplier]"), 'P&G-Ltd'!$C21 ) -> 0 | J21: =SUMIFS( INDIRECT("input_invoice[net]"), INDIRECT("input_invoice[yyyymm]"), 'P&G-Ltd'!J$1, INDIRECT("input_invoice[concept/supplier]"), 'P&G-Ltd'!$C21 ) -> 0 | K21: =SUMIFS( INDIRECT("input_invoice[net]"), INDIRECT("input_invoice[yyyymm]"), 'P&G-Ltd'!K$1, INDIRECT("input_invoice[concept/supplier]"), 'P&G-Ltd'!$C21 ) -> 0 | L21: =SUMIFS( INDIRECT("input_invoice[net]"), INDIRECT("input_invoice[yyyymm]"), 'P&G-Ltd'!L$1, INDIRECT("input_invoice[concept/supplier]"), 'P&G-Ltd'!$C21 ) -> 0 | M21: =SUMIFS( INDIRECT("input_invoice[net]"), INDIRECT("input_invoice[yyyymm]"), 'P&G-Ltd'!M$1, INDIRECT("input_invoice[concept/supplier]"), 'P&G-Ltd'!$C21 ) -> 0 | N21: =SUMIFS( INDIRECT("input_invoice[net]"), INDIRECT("input_invoice[yyyymm]"), 'P&G-Ltd'!N$1, INDIRECT("input_invoice[concept/supplier]"), 'P&G-Ltd'!$C21 ) -> 0 | O21: =SUMIFS( INDIRECT("input_invoice[net]"), INDIRECT("input_invoice[yyyymm]"), 'P&G-Ltd'!O$1, INDIRECT("input_invoice[concept/supplier]"), 'P&G-Ltd'!$C21 ) -> 0 | ... S21: =SUMIFS( INDIRECT("input_invoice[net]"), INDIRECT("input_invoice[yyyymm]"), 'P&G-Ltd'!S$1, INDIRECT("input_invoice[concept/supplier]"), 'P&G-Ltd'!$C21 ) -> 0 | T21: =SUM(H21:S21) -> 0
C22: manufacturing - Proco frames -> Ltd | E22: #VALUE! | F22: Frames Purchase | H22: =SUMIFS( INDIRECT("input_invoice[net]"), INDIRECT("input_invoice[yyyymm]"), 'P&G-Ltd'!H$1, INDIRECT("input_invoice[concept/supplier]"), 'P&G-Ltd'!$C22 ) -> 0 | I22: =SUMIFS( INDIRECT("input_invoice[net]"), INDIRECT("input_invoice[yyyymm]"), 'P&G-Ltd'!I$1, INDIRECT("input_invoice[concept/supplier]"), 'P&G-Ltd'!$C22 ) -> 0 | J22: =SUMIFS( INDIRECT("input_invoice[net]"), INDIRECT("input_invoice[yyyymm]"), 'P&G-Ltd'!J$1, INDIRECT("input_invoice[concept/supplier]"), 'P&G-Ltd'!$C22 ) -> 0 | K22: =SUMIFS( INDIRECT("input_invoice[net]"), INDIRECT("input_invoice[yyyymm]"), 'P&G-Ltd'!K$1, INDIRECT("input_invoice[concept/supplier]"), 'P&G-Ltd'!$C22 ) -> 0 | L22: =SUMIFS( INDIRECT("input_invoice[net]"), INDIRECT("input_invoice[yyyymm]"), 'P&G-Ltd'!L$1, INDIRECT("input_invoice[concept/supplier]"), 'P&G-Ltd'!$C22 ) -> 0 | M22: =SUMIFS( INDIRECT("input_invoice[net]"), INDIRECT("input_invoice[yyyymm]"), 'P&G-Ltd'!M$1, INDIRECT("input_invoice[concept/supplier]"), 'P&G-Ltd'!$C22 ) -> 0 | N22: =SUMIFS( INDIRECT("input_invoice[net]"), INDIRECT("input_invoice[yyyymm]"), 'P&G-Ltd'!N$1, INDIRECT("input_invoice[concept/supplier]"), 'P&G-Ltd'!$C22 ) -> 0 | O22: =SUMIFS( INDIRECT("input_invoice[net]"), INDIRECT("input_invoice[yyyymm]"), 'P&G-Ltd'!O$1, INDIRECT("input_invoice[concept/supplier]"), 'P&G-Ltd'!$C22 ) -> 0 | ... S22: =SUMIFS( INDIRECT("input_invoice[net]"), INDIRECT("input_invoice[yyyymm]"), 'P&G-Ltd'!S$1, INDIRECT("input_invoice[concept/supplier]"), 'P&G-Ltd'!$C22 ) -> 0 | T22: =SUM(H22:S22) -> 0
C23: logistics - artlink -> Ltd | E23: #VALUE! | F23: Shipping Frames/Customs | H23: =SUMIFS( INDIRECT("input_invoice[net]"), INDIRECT("input_invoice[yyyymm]"), 'P&G-Ltd'!H$1, INDIRECT("input_invoice[concept/supplier]"), 'P&G-Ltd'!$C23 ) -> 0 | I23: =SUMIFS( INDIRECT("input_invoice[net]"), INDIRECT("input_invoice[yyyymm]"), 'P&G-Ltd'!I$1, INDIRECT("input_invoice[concept/supplier]"), 'P&G-Ltd'!$C23 ) -> 0 | J23: =SUMIFS( INDIRECT("input_invoice[net]"), INDIRECT("input_invoice[yyyymm]"), 'P&G-Ltd'!J$1, INDIRECT("input_invoice[concept/supplier]"), 'P&G-Ltd'!$C23 ) -> 0 | K23: =SUMIFS( INDIRECT("input_invoice[net]"), INDIRECT("input_invoice[yyyymm]"), 'P&G-Ltd'!K$1, INDIRECT("input_invoice[concept/supplier]"), 'P&G-Ltd'!$C23 ) -> 0 | L23: =SUMIFS( INDIRECT("input_invoice[net]"), INDIRECT("input_invoice[yyyymm]"), 'P&G-Ltd'!L$1, INDIRECT("input_invoice[concept/supplier]"), 'P&G-Ltd'!$C23 ) -> 0 | M23: =SUMIFS( INDIRECT("input_invoice[net]"), INDIRECT("input_invoice[yyyymm]"), 'P&G-Ltd'!M$1, INDIRECT("input_invoice[concept/supplier]"), 'P&G-Ltd'!$C23 ) -> 0 | N23: =SUMIFS( INDIRECT("input_invoice[net]"), INDIRECT("input_invoice[yyyymm]"), 'P&G-Ltd'!N$1, INDIRECT("input_invoice[concept/supplier]"), 'P&G-Ltd'!$C23 ) -> 0 | O23: =SUMIFS( INDIRECT("input_invoice[net]"), INDIRECT("input_invoice[yyyymm]"), 'P&G-Ltd'!O$1, INDIRECT("input_invoice[concept/supplier]"), 'P&G-Ltd'!$C23 ) -> 0 | ... S23: =SUMIFS( INDIRECT("input_invoice[net]"), INDIRECT("input_invoice[yyyymm]"), 'P&G-Ltd'!S$1, INDIRECT("input_invoice[concept/supplier]"), 'P&G-Ltd'!$C23 ) -> 0 | T23: =SUM(H23:S23) -> 0
C24: manufacturing - jondo -> Ltd | E24: #VALUE! | F24: Jondo Canvas | H24: =SUMIFS( INDIRECT("input_invoice[net]"), INDIRECT("input_invoice[yyyymm]"), 'P&G-Ltd'!H$1, INDIRECT("input_invoice[concept/supplier]"), 'P&G-Ltd'!$C24 ) -> 0 | I24: =SUMIFS( INDIRECT("input_invoice[net]"), INDIRECT("input_invoice[yyyymm]"), 'P&G-Ltd'!I$1, INDIRECT("input_invoice[concept/supplier]"), 'P&G-Ltd'!$C24 ) -> 0 | J24: =SUMIFS( INDIRECT("input_invoice[net]"), INDIRECT("input_invoice[yyyymm]"), 'P&G-Ltd'!J$1, INDIRECT("input_invoice[concept/supplier]"), 'P&G-Ltd'!$C24 ) -> 0 | K24: =SUMIFS( INDIRECT("input_invoice[net]"), INDIRECT("input_invoice[yyyymm]"), 'P&G-Ltd'!K$1, INDIRECT("input_invoice[concept/supplier]"), 'P&G-Ltd'!$C24 ) -> 0 | L24: =SUMIFS( INDIRECT("input_invoice[net]"), INDIRECT("input_invoice[yyyymm]"), 'P&G-Ltd'!L$1, INDIRECT("input_invoice[concept/supplier]"), 'P&G-Ltd'!$C24 ) -> 0 | M24: =SUMIFS( INDIRECT("input_invoice[net]"), INDIRECT("input_invoice[yyyymm]"), 'P&G-Ltd'!M$1, INDIRECT("input_invoice[concept/supplier]"), 'P&G-Ltd'!$C24 ) -> 0 | N24: =SUMIFS( INDIRECT("input_invoice[net]"), INDIRECT("input_invoice[yyyymm]"), 'P&G-Ltd'!N$1, INDIRECT("input_invoice[concept/supplier]"), 'P&G-Ltd'!$C24 ) -> 0 | O24: =SUMIFS( INDIRECT("input_invoice[net]"), INDIRECT("input_invoice[yyyymm]"), 'P&G-Ltd'!O$1, INDIRECT("input_invoice[concept/supplier]"), 'P&G-Ltd'!$C24 ) -> 0 | ... S24: =SUMIFS( INDIRECT("input_invoice[net]"), INDIRECT("input_invoice[yyyymm]"), 'P&G-Ltd'!S$1, INDIRECT("input_invoice[concept/supplier]"), 'P&G-Ltd'!$C24 ) -> 0 | T24: =SUM(H24:S24) -> 0
T25: =SUM(H25:S25) -> 0
D26: Shipping | H26: =SUM(H27:H29) -> 1609.11 | I26: =SUM(I27:I29) -> 3518.57 | J26: =SUM(J27:J29) -> 0 | K26: =SUM(K27:K29) -> 0 | L26: =SUM(L27:L29) -> 0 | M26: =SUM(M27:M29) -> 0 | N26: =SUM(N27:N29) -> 0 | O26: =SUM(O27:O29) -> 0 | ... S26: =SUM(S27:S29) -> 0 | T26: =SUM(H26:S26) -> 5127.68
C27: logistics - Proco carriage -> Ltd | F27: Proco - DPD | H27: =SUMIFS( INDIRECT("input_invoice[net]"), INDIRECT("input_invoice[yyyymm]"), 'P&G-Ltd'!H$1, INDIRECT("input_invoice[concept/supplier]"), 'P&G-Ltd'!$C27 ) -> 691.2 | I27: =SUMIFS( INDIRECT("input_invoice[net]"), INDIRECT("input_invoice[yyyymm]"), 'P&G-Ltd'!I$1, INDIRECT("input_invoice[concept/supplier]"), 'P&G-Ltd'!$C27 ) -> 1008 | J27: =SUMIFS( INDIRECT("input_invoice[net]"), INDIRECT("input_invoice[yyyymm]"), 'P&G-Ltd'!J$1, INDIRECT("input_invoice[concept/supplier]"), 'P&G-Ltd'!$C27 ) -> 0 | K27: =SUMIFS( INDIRECT("input_invoice[net]"), INDIRECT("input_invoice[yyyymm]"), 'P&G-Ltd'!K$1, INDIRECT("input_invoice[concept/supplier]"), 'P&G-Ltd'!$C27 ) -> 0 | L27: =SUMIFS( INDIRECT("input_invoice[net]"), INDIRECT("input_invoice[yyyymm]"), 'P&G-Ltd'!L$1, INDIRECT("input_invoice[concept/supplier]"), 'P&G-Ltd'!$C27 ) -> 0 | M27: =SUMIFS( INDIRECT("input_invoice[net]"), INDIRECT("input_invoice[yyyymm]"), 'P&G-Ltd'!M$1, INDIRECT("input_invoice[concept/supplier]"), 'P&G-Ltd'!$C27 ) -> 0 | N27: =SUMIFS( INDIRECT("input_invoice[net]"), INDIRECT("input_invoice[yyyymm]"), 'P&G-Ltd'!N$1, INDIRECT("input_invoice[concept/supplier]"), 'P&G-Ltd'!$C27 ) -> 0 | O27: =SUMIFS( INDIRECT("input_invoice[net]"), INDIRECT("input_invoice[yyyymm]"), 'P&G-Ltd'!O$1, INDIRECT("input_invoice[concept/supplier]"), 'P&G-Ltd'!$C27 ) -> 0 | ... S27: =SUMIFS( INDIRECT("input_invoice[net]"), INDIRECT("input_invoice[yyyymm]"), 'P&G-Ltd'!S$1, INDIRECT("input_invoice[concept/supplier]"), 'P&G-Ltd'!$C27 ) -> 0 | T27: =SUM(H27:S27) -> 1699.2
C28: logistics - Proco postage -> Ltd | F28: Proco - Royal Mail | H28: =SUMIFS( INDIRECT("input_invoice[net]"), INDIRECT("input_invoice[yyyymm]"), 'P&G-Ltd'!H$1, INDIRECT("input_invoice[concept/supplier]"), 'P&G-Ltd'!$C28 ) -> 563.85 | I28: =SUMIFS( INDIRECT("input_invoice[net]"), INDIRECT("input_invoice[yyyymm]"), 'P&G-Ltd'!I$1, INDIRECT("input_invoice[concept/supplier]"), 'P&G-Ltd'!$C28 ) -> 662.3 | J28: =SUMIFS( INDIRECT("input_invoice[net]"), INDIRECT("input_invoice[yyyymm]"), 'P&G-Ltd'!J$1, INDIRECT("input_invoice[concept/supplier]"), 'P&G-Ltd'!$C28 ) -> 0 | K28: =SUMIFS( INDIRECT("input_invoice[net]"), INDIRECT("input_invoice[yyyymm]"), 'P&G-Ltd'!K$1, INDIRECT("input_invoice[concept/supplier]"), 'P&G-Ltd'!$C28 ) -> 0 | L28: =SUMIFS( INDIRECT("input_invoice[net]"), INDIRECT("input_invoice[yyyymm]"), 'P&G-Ltd'!L$1, INDIRECT("input_invoice[concept/supplier]"), 'P&G-Ltd'!$C28 ) -> 0 | M28: =SUMIFS( INDIRECT("input_invoice[net]"), INDIRECT("input_invoice[yyyymm]"), 'P&G-Ltd'!M$1, INDIRECT("input_invoice[concept/supplier]"), 'P&G-Ltd'!$C28 ) -> 0 | N28: =SUMIFS( INDIRECT("input_invoice[net]"), INDIRECT("input_invoice[yyyymm]"), 'P&G-Ltd'!N$1, INDIRECT("input_invoice[concept/supplier]"), 'P&G-Ltd'!$C28 ) -> 0 | O28: =SUMIFS( INDIRECT("input_invoice[net]"), INDIRECT("input_invoice[yyyymm]"), 'P&G-Ltd'!O$1, INDIRECT("input_invoice[concept/supplier]"), 'P&G-Ltd'!$C28 ) -> 0 | ... S28: =SUMIFS( INDIRECT("input_invoice[net]"), INDIRECT("input_invoice[yyyymm]"), 'P&G-Ltd'!S$1, INDIRECT("input_invoice[concept/supplier]"), 'P&G-Ltd'!$C28 ) -> 0 | T28: =SUM(H28:S28) -> 1226.15
C29: logistics - jondo -> Ltd | F29: Jondo Canvas | H29: =SUMIFS( INDIRECT("input_invoice[net]"), INDIRECT("input_invoice[yyyymm]"), 'P&G-Ltd'!H$1, INDIRECT("input_invoice[concept/supplier]"), 'P&G-Ltd'!$C29 ) -> 354.06 | I29: =SUMIFS( INDIRECT("input_invoice[net]"), INDIRECT("input_invoice[yyyymm]"), 'P&G-Ltd'!I$1, INDIRECT("input_invoice[concept/supplier]"), 'P&G-Ltd'!$C29 ) -> 1848.27 | J29: =SUMIFS( INDIRECT("input_invoice[net]"), INDIRECT("input_invoice[yyyymm]"), 'P&G-Ltd'!J$1, INDIRECT("input_invoice[concept/supplier]"), 'P&G-Ltd'!$C29 ) -> 0 | K29: =SUMIFS( INDIRECT("input_invoice[net]"), INDIRECT("input_invoice[yyyymm]"), 'P&G-Ltd'!K$1, INDIRECT("input_invoice[concept/supplier]"), 'P&G-Ltd'!$C29 ) -> 0 | L29: =SUMIFS( INDIRECT("input_invoice[net]"), INDIRECT("input_invoice[yyyymm]"), 'P&G-Ltd'!L$1, INDIRECT("input_invoice[concept/supplier]"), 'P&G-Ltd'!$C29 ) -> 0 | M29: =SUMIFS( INDIRECT("input_invoice[net]"), INDIRECT("input_invoice[yyyymm]"), 'P&G-Ltd'!M$1, INDIRECT("input_invoice[concept/supplier]"), 'P&G-Ltd'!$C29 ) -> 0 | N29: =SUMIFS( INDIRECT("input_invoice[net]"), INDIRECT("input_invoice[yyyymm]"), 'P&G-Ltd'!N$1, INDIRECT("input_invoice[concept/supplier]"), 'P&G-Ltd'!$C29 ) -> 0 | O29: =SUMIFS( INDIRECT("input_invoice[net]"), INDIRECT("input_invoice[yyyymm]"), 'P&G-Ltd'!O$1, INDIRECT("input_invoice[concept/supplier]"), 'P&G-Ltd'!$C29 ) -> 0 | ... S29: =SUMIFS( INDIRECT("input_invoice[net]"), INDIRECT("input_invoice[yyyymm]"), 'P&G-Ltd'!S$1, INDIRECT("input_invoice[concept/supplier]"), 'P&G-Ltd'!$C29 ) -> 0 | T29: =SUM(H29:S29) -> 2202.33
D31: Royalties | H31: =SUM(H32:H32) -> #REF! | I31: =SUM(I32:I32) -> #REF! | J31: =SUM(J32:J32) -> #REF! | K31: =SUM(K32:K32) -> #REF! | L31: =SUM(L32:L32) -> #REF! | M31: =SUM(M32:M32) -> #REF! | N31: =SUM(N32:N32) -> #REF! | O31: =SUM(O32:O32) -> #REF! | ... S31: =SUM(S32:S32) -> #REF! | T31: =SUM(H31:S31) -> #REF!
C32: royalties - Artistas -> Ltd | F32: Shared services - UK | H32: =SUMIFS( INDIRECT("input_roy[net]"), INDIRECT("input_roy[yyyymm]"), 'P&G-Ltd'!H$1, INDIRECT("input_roy[concept/supplier]"), 'P&G-Ltd'!$C32 )*H82 -> #REF! | I32: =SUMIFS( INDIRECT("input_roy[net]"), INDIRECT("input_roy[yyyymm]"), 'P&G-Ltd'!I$1, INDIRECT("input_roy[concept/supplier]"), 'P&G-Ltd'!$C32 )*I82 -> #REF! | J32: =SUMIFS( INDIRECT("input_roy[net]"), INDIRECT("input_roy[yyyymm]"), 'P&G-Ltd'!J$1, INDIRECT("input_roy[concept/supplier]"), 'P&G-Ltd'!$C32 )*J82 -> #REF! | K32: =SUMIFS( INDIRECT("input_roy[net]"), INDIRECT("input_roy[yyyymm]"), 'P&G-Ltd'!K$1, INDIRECT("input_roy[concept/supplier]"), 'P&G-Ltd'!$C32 )*K82 -> #REF! | L32: =SUMIFS( INDIRECT("input_roy[net]"), INDIRECT("input_roy[yyyymm]"), 'P&G-Ltd'!L$1, INDIRECT("input_roy[concept/supplier]"), 'P&G-Ltd'!$C32 )*L82 -> #REF! | M32: =SUMIFS( INDIRECT("input_roy[net]"), INDIRECT("input_roy[yyyymm]"), 'P&G-Ltd'!M$1, INDIRECT("input_roy[concept/supplier]"), 'P&G-Ltd'!$C32 )*M82 -> #REF! | N32: =SUMIFS( INDIRECT("input_roy[net]"), INDIRECT("input_roy[yyyymm]"), 'P&G-Ltd'!N$1, INDIRECT("input_roy[concept/supplier]"), 'P&G-Ltd'!$C32 )*N82 -> #REF! | O32: =SUMIFS( INDIRECT("input_roy[net]"), INDIRECT("input_roy[yyyymm]"), 'P&G-Ltd'!O$1, INDIRECT("input_roy[concept/supplier]"), 'P&G-Ltd'!$C32 )*O82 -> #REF! | ... S32: =SUMIFS( INDIRECT("input_roy[net]"), INDIRECT("input_roy[yyyymm]"), 'P&G-Ltd'!S$1, INDIRECT("input_roy[concept/supplier]"), 'P&G-Ltd'!$C32 )*S82 -> #REF! | T32: =SUM(H32:S32) -> #REF!
D34: Payments suppliers | H34: =SUM(H35:H40) -> 0 | I34: =SUM(I35:I40) -> 0 | J34: =SUM(J35:J40) -> 0 | K34: =SUM(K35:K40) -> 0 | L34: =SUM(L35:L40) -> 0 | M34: =SUM(M35:M40) -> 0 | N34: =SUM(N35:N40) -> 0 | O34: =SUM(O35:O40) -> 0 | ... S34: =SUM(S35:S40) -> 0 | T34: =SUM(H34:S34) -> 0
C35: payment-suppliers - Shopify -> Ltd | F35: Shopify | H35: =SUMIFS( INDIRECT("input_invoice[net]"), INDIRECT("input_invoice[yyyymm]"), 'P&G-Ltd'!H$1, INDIRECT("input_invoice[concept/supplier]"), 'P&G-Ltd'!$C35 ) -> 0 | I35: =SUMIFS( INDIRECT("input_invoice[net]"), INDIRECT("input_invoice[yyyymm]"), 'P&G-Ltd'!I$1, INDIRECT("input_invoice[concept/supplier]"), 'P&G-Ltd'!$C35 ) -> 0 | J35: =SUMIFS( INDIRECT("input_invoice[net]"), INDIRECT("input_invoice[yyyymm]"), 'P&G-Ltd'!J$1, INDIRECT("input_invoice[concept/supplier]"), 'P&G-Ltd'!$C35 ) -> 0 | K35: =SUMIFS( INDIRECT("input_invoice[net]"), INDIRECT("input_invoice[yyyymm]"), 'P&G-Ltd'!K$1, INDIRECT("input_invoice[concept/supplier]"), 'P&G-Ltd'!$C35 ) -> 0 | L35: =SUMIFS( INDIRECT("input_invoice[net]"), INDIRECT("input_invoice[yyyymm]"), 'P&G-Ltd'!L$1, INDIRECT("input_invoice[concept/supplier]"), 'P&G-Ltd'!$C35 ) -> 0 | M35: =SUMIFS( INDIRECT("input_invoice[net]"), INDIRECT("input_invoice[yyyymm]"), 'P&G-Ltd'!M$1, INDIRECT("input_invoice[concept/supplier]"), 'P&G-Ltd'!$C35 ) -> 0 | N35: =SUMIFS( INDIRECT("input_invoice[net]"), INDIRECT("input_invoice[yyyymm]"), 'P&G-Ltd'!N$1, INDIRECT("input_invoice[concept/supplier]"), 'P&G-Ltd'!$C35 ) -> 0 | O35: =SUMIFS( INDIRECT("input_invoice[net]"), INDIRECT("input_invoice[yyyymm]"), 'P&G-Ltd'!O$1, INDIRECT("input_invoice[concept/supplier]"), 'P&G-Ltd'!$C35 ) -> 0 | ... S35: =SUMIFS( INDIRECT("input_invoice[net]"), INDIRECT("input_invoice[yyyymm]"), 'P&G-Ltd'!S$1, INDIRECT("input_invoice[concept/supplier]"), 'P&G-Ltd'!$C35 ) -> 0 | T35: =SUM(H35:S35) -> 0
C36: payment-suppliers - Paypal -> Ltd | F36: Paypal | H36: =SUMIFS( INDIRECT("input_invoice[net]"), INDIRECT("input_invoice[yyyymm]"), 'P&G-Ltd'!H$1, INDIRECT("input_invoice[concept/supplier]"), 'P&G-Ltd'!$C36 ) -> 0 | I36: =SUMIFS( INDIRECT("input_invoice[net]"), INDIRECT("input_invoice[yyyymm]"), 'P&G-Ltd'!I$1, INDIRECT("input_invoice[concept/supplier]"), 'P&G-Ltd'!$C36 ) -> 0 | J36: =SUMIFS( INDIRECT("input_invoice[net]"), INDIRECT("input_invoice[yyyymm]"), 'P&G-Ltd'!J$1, INDIRECT("input_invoice[concept/supplier]"), 'P&G-Ltd'!$C36 ) -> 0 | K36: =SUMIFS( INDIRECT("input_invoice[net]"), INDIRECT("input_invoice[yyyymm]"), 'P&G-Ltd'!K$1, INDIRECT("input_invoice[concept/supplier]"), 'P&G-Ltd'!$C36 ) -> 0 | L36: =SUMIFS( INDIRECT("input_invoice[net]"), INDIRECT("input_invoice[yyyymm]"), 'P&G-Ltd'!L$1, INDIRECT("input_invoice[concept/supplier]"), 'P&G-Ltd'!$C36 ) -> 0 | M36: =SUMIFS( INDIRECT("input_invoice[net]"), INDIRECT("input_invoice[yyyymm]"), 'P&G-Ltd'!M$1, INDIRECT("input_invoice[concept/supplier]"), 'P&G-Ltd'!$C36 ) -> 0 | N36: =SUMIFS( INDIRECT("input_invoice[net]"), INDIRECT("input_invoice[yyyymm]"), 'P&G-Ltd'!N$1, INDIRECT("input_invoice[concept/supplier]"), 'P&G-Ltd'!$C36 ) -> 0 | O36: =SUMIFS( INDIRECT("input_invoice[net]"), INDIRECT("input_invoice[yyyymm]"), 'P&G-Ltd'!O$1, INDIRECT("input_invoice[concept/supplier]"), 'P&G-Ltd'!$C36 ) -> 0 | ... S36: =SUMIFS( INDIRECT("input_invoice[net]"), INDIRECT("input_invoice[yyyymm]"), 'P&G-Ltd'!S$1, INDIRECT("input_invoice[concept/supplier]"), 'P&G-Ltd'!$C36 ) -> 0 | T36: =SUM(H36:S36) -> 0
C37: payment-suppliers - Amazon Pay -> Ltd | F37: Amazon Pay | H37: =SUMIFS( INDIRECT("input_invoice[net]"), INDIRECT("input_invoice[yyyymm]"), 'P&G-Ltd'!H$1, INDIRECT("input_invoice[concept/supplier]"), 'P&G-Ltd'!$C37 ) -> 0 | I37: =SUMIFS( INDIRECT("input_invoice[net]"), INDIRECT("input_invoice[yyyymm]"), 'P&G-Ltd'!I$1, INDIRECT("input_invoice[concept/supplier]"), 'P&G-Ltd'!$C37 ) -> 0 | J37: =SUMIFS( INDIRECT("input_invoice[net]"), INDIRECT("input_invoice[yyyymm]"), 'P&G-Ltd'!J$1, INDIRECT("input_invoice[concept/supplier]"), 'P&G-Ltd'!$C37 ) -> 0 | K37: =SUMIFS( INDIRECT("input_invoice[net]"), INDIRECT("input_invoice[yyyymm]"), 'P&G-Ltd'!K$1, INDIRECT("input_invoice[concept/supplier]"), 'P&G-Ltd'!$C37 ) -> 0 | L37: =SUMIFS( INDIRECT("input_invoice[net]"), INDIRECT("input_invoice[yyyymm]"), 'P&G-Ltd'!L$1, INDIRECT("input_invoice[concept/supplier]"), 'P&G-Ltd'!$C37 ) -> 0 | M37: =SUMIFS( INDIRECT("input_invoice[net]"), INDIRECT("input_invoice[yyyymm]"), 'P&G-Ltd'!M$1, INDIRECT("input_invoice[concept/supplier]"), 'P&G-Ltd'!$C37 ) -> 0 | N37: =SUMIFS( INDIRECT("input_invoice[net]"), INDIRECT("input_invoice[yyyymm]"), 'P&G-Ltd'!N$1, INDIRECT("input_invoice[concept/supplier]"), 'P&G-Ltd'!$C37 ) -> 0 | O37: =SUMIFS( INDIRECT("input_invoice[net]"), INDIRECT("input_invoice[yyyymm]"), 'P&G-Ltd'!O$1, INDIRECT("input_invoice[concept/supplier]"), 'P&G-Ltd'!$C37 ) -> 0 | ... S37: =SUMIFS( INDIRECT("input_invoice[net]"), INDIRECT("input_invoice[yyyymm]"), 'P&G-Ltd'!S$1, INDIRECT("input_invoice[concept/supplier]"), 'P&G-Ltd'!$C37 ) -> 0 | T37: =SUM(H37:S37) -> 0
C38: payment-suppliers - Klarna -> Ltd | F38: Klarna | H38: =SUMIFS( INDIRECT("input_invoice[net]"), INDIRECT("input_invoice[yyyymm]"), 'P&G-Ltd'!H$1, INDIRECT("input_invoice[concept/supplier]"), 'P&G-Ltd'!$C38 ) -> 0 | I38: =SUMIFS( INDIRECT("input_invoice[net]"), INDIRECT("input_invoice[yyyymm]"), 'P&G-Ltd'!I$1, INDIRECT("input_invoice[concept/supplier]"), 'P&G-Ltd'!$C38 ) -> 0 | J38: =SUMIFS( INDIRECT("input_invoice[net]"), INDIRECT("input_invoice[yyyymm]"), 'P&G-Ltd'!J$1, INDIRECT("input_invoice[concept/supplier]"), 'P&G-Ltd'!$C38 ) -> 0 | K38: =SUMIFS( INDIRECT("input_invoice[net]"), INDIRECT("input_invoice[yyyymm]"), 'P&G-Ltd'!K$1, INDIRECT("input_invoice[concept/supplier]"), 'P&G-Ltd'!$C38 ) -> 0 | L38: =SUMIFS( INDIRECT("input_invoice[net]"), INDIRECT("input_invoice[yyyymm]"), 'P&G-Ltd'!L$1, INDIRECT("input_invoice[concept/supplier]"), 'P&G-Ltd'!$C38 ) -> 0 | M38: =SUMIFS( INDIRECT("input_invoice[net]"), INDIRECT("input_invoice[yyyymm]"), 'P&G-Ltd'!M$1, INDIRECT("input_invoice[concept/supplier]"), 'P&G-Ltd'!$C38 ) -> 0 | N38: =SUMIFS( INDIRECT("input_invoice[net]"), INDIRECT("input_invoice[yyyymm]"), 'P&G-Ltd'!N$1, INDIRECT("input_invoice[concept/supplier]"), 'P&G-Ltd'!$C38 ) -> 0 | O38: =SUMIFS( INDIRECT("input_invoice[net]"), INDIRECT("input_invoice[yyyymm]"), 'P&G-Ltd'!O$1, INDIRECT("input_invoice[concept/supplier]"), 'P&G-Ltd'!$C38 ) -> 0 | ... S38: =SUMIFS( INDIRECT("input_invoice[net]"), INDIRECT("input_invoice[yyyymm]"), 'P&G-Ltd'!S$1, INDIRECT("input_invoice[concept/supplier]"), 'P&G-Ltd'!$C38 ) -> 0 | T38: =SUM(H38:S38) -> 0
C39: payment-suppliers - Revolut -> Ltd | F39: Revolut | H39: =SUMIFS( INDIRECT("input_invoice[net]"), INDIRECT("input_invoice[yyyymm]"), 'P&G-Ltd'!H$1, INDIRECT("input_invoice[concept/supplier]"), 'P&G-Ltd'!$C39 ) -> 0 | I39: =SUMIFS( INDIRECT("input_invoice[net]"), INDIRECT("input_invoice[yyyymm]"), 'P&G-Ltd'!I$1, INDIRECT("input_invoice[concept/supplier]"), 'P&G-Ltd'!$C39 ) -> 0 | J39: =SUMIFS( INDIRECT("input_invoice[net]"), INDIRECT("input_invoice[yyyymm]"), 'P&G-Ltd'!J$1, INDIRECT("input_invoice[concept/supplier]"), 'P&G-Ltd'!$C39 ) -> 0 | K39: =SUMIFS( INDIRECT("input_invoice[net]"), INDIRECT("input_invoice[yyyymm]"), 'P&G-Ltd'!K$1, INDIRECT("input_invoice[concept/supplier]"), 'P&G-Ltd'!$C39 ) -> 0 | L39: =SUMIFS( INDIRECT("input_invoice[net]"), INDIRECT("input_invoice[yyyymm]"), 'P&G-Ltd'!L$1, INDIRECT("input_invoice[concept/supplier]"), 'P&G-Ltd'!$C39 ) -> 0 | M39: =SUMIFS( INDIRECT("input_invoice[net]"), INDIRECT("input_invoice[yyyymm]"), 'P&G-Ltd'!M$1, INDIRECT("input_invoice[concept/supplier]"), 'P&G-Ltd'!$C39 ) -> 0 | N39: =SUMIFS( INDIRECT("input_invoice[net]"), INDIRECT("input_invoice[yyyymm]"), 'P&G-Ltd'!N$1, INDIRECT("input_invoice[concept/supplier]"), 'P&G-Ltd'!$C39 ) -> 0 | O39: =SUMIFS( INDIRECT("input_invoice[net]"), INDIRECT("input_invoice[yyyymm]"), 'P&G-Ltd'!O$1, INDIRECT("input_invoice[concept/supplier]"), 'P&G-Ltd'!$C39 ) -> 0 | ... S39: =SUMIFS( INDIRECT("input_invoice[net]"), INDIRECT("input_invoice[yyyymm]"), 'P&G-Ltd'!S$1, INDIRECT("input_invoice[concept/supplier]"), 'P&G-Ltd'!$C39 ) -> 0 | T39: =SUM(H39:S39) -> 0
C40: payment-suppliers - Amazon Seller -> Ltd | F40: Amazon Seller | H40: =SUMIFS( INDIRECT("input_invoice[net]"), INDIRECT("input_invoice[yyyymm]"), 'P&G-Ltd'!H$1, INDIRECT("input_invoice[concept/supplier]"), 'P&G-Ltd'!$C40 ) -> 0 | I40: =SUMIFS( INDIRECT("input_invoice[net]"), INDIRECT("input_invoice[yyyymm]"), 'P&G-Ltd'!I$1, INDIRECT("input_invoice[concept/supplier]"), 'P&G-Ltd'!$C40 ) -> 0 | J40: =SUMIFS( INDIRECT("input_invoice[net]"), INDIRECT("input_invoice[yyyymm]"), 'P&G-Ltd'!J$1, INDIRECT("input_invoice[concept/supplier]"), 'P&G-Ltd'!$C40 ) -> 0 | K40: =SUMIFS( INDIRECT("input_invoice[net]"), INDIRECT("input_invoice[yyyymm]"), 'P&G-Ltd'!K$1, INDIRECT("input_invoice[concept/supplier]"), 'P&G-Ltd'!$C40 ) -> 0 | L40: =SUMIFS( INDIRECT("input_invoice[net]"), INDIRECT("input_invoice[yyyymm]"), 'P&G-Ltd'!L$1, INDIRECT("input_invoice[concept/supplier]"), 'P&G-Ltd'!$C40 ) -> 0 | M40: =SUMIFS( INDIRECT("input_invoice[net]"), INDIRECT("input_invoice[yyyymm]"), 'P&G-Ltd'!M$1, INDIRECT("input_invoice[concept/supplier]"), 'P&G-Ltd'!$C40 ) -> 0 | N40: =SUMIFS( INDIRECT("input_invoice[net]"), INDIRECT("input_invoice[yyyymm]"), 'P&G-Ltd'!N$1, INDIRECT("input_invoice[concept/supplier]"), 'P&G-Ltd'!$C40 ) -> 0 | O40: =SUMIFS( INDIRECT("input_invoice[net]"), INDIRECT("input_invoice[yyyymm]"), 'P&G-Ltd'!O$1, INDIRECT("input_invoice[concept/supplier]"), 'P&G-Ltd'!$C40 ) -> 0 | ... S40: =SUMIFS( INDIRECT("input_invoice[net]"), INDIRECT("input_invoice[yyyymm]"), 'P&G-Ltd'!S$1, INDIRECT("input_invoice[concept/supplier]"), 'P&G-Ltd'!$C40 ) -> 0 | T40: =SUM(H40:S40) -> 0
D41: Returns - Rever | H41: =+H42 -> 0 | I41: =+I42 -> 0 | J41: =+J42 -> 0 | K41: =+K42 -> 0 | L41: =+L42 -> 0 | M41: =+M42 -> 0 | N41: =+N42 -> 0 | O41: =+O42 -> 0 | ... S41: =+S42 -> 0 | T41: =SUM(H41:S41) -> 0
C42: returns - rever -> Ltd | F42: UK | H42: =SUMIFS( INDIRECT("input_invoice[net]"), INDIRECT("input_invoice[yyyymm]"), 'P&G-Ltd'!H$1, INDIRECT("input_invoice[concept/supplier]"), 'P&G-Ltd'!$C42 ) -> 0 | I42: =SUMIFS( INDIRECT("input_invoice[net]"), INDIRECT("input_invoice[yyyymm]"), 'P&G-Ltd'!I$1, INDIRECT("input_invoice[concept/supplier]"), 'P&G-Ltd'!$C42 ) -> 0 | J42: =SUMIFS( INDIRECT("input_invoice[net]"), INDIRECT("input_invoice[yyyymm]"), 'P&G-Ltd'!J$1, INDIRECT("input_invoice[concept/supplier]"), 'P&G-Ltd'!$C42 ) -> 0 | K42: =SUMIFS( INDIRECT("input_invoice[net]"), INDIRECT("input_invoice[yyyymm]"), 'P&G-Ltd'!K$1, INDIRECT("input_invoice[concept/supplier]"), 'P&G-Ltd'!$C42 ) -> 0 | L42: =SUMIFS( INDIRECT("input_invoice[net]"), INDIRECT("input_invoice[yyyymm]"), 'P&G-Ltd'!L$1, INDIRECT("input_invoice[concept/supplier]"), 'P&G-Ltd'!$C42 ) -> 0 | M42: =SUMIFS( INDIRECT("input_invoice[net]"), INDIRECT("input_invoice[yyyymm]"), 'P&G-Ltd'!M$1, INDIRECT("input_invoice[concept/supplier]"), 'P&G-Ltd'!$C42 ) -> 0 | N42: =SUMIFS( INDIRECT("input_invoice[net]"), INDIRECT("input_invoice[yyyymm]"), 'P&G-Ltd'!N$1, INDIRECT("input_invoice[concept/supplier]"), 'P&G-Ltd'!$C42 ) -> 0 | O42: =SUMIFS( INDIRECT("input_invoice[net]"), INDIRECT("input_invoice[yyyymm]"), 'P&G-Ltd'!O$1, INDIRECT("input_invoice[concept/supplier]"), 'P&G-Ltd'!$C42 ) -> 0 | ... S42: =SUMIFS( INDIRECT("input_invoice[net]"), INDIRECT("input_invoice[yyyymm]"), 'P&G-Ltd'!S$1, INDIRECT("input_invoice[concept/supplier]"), 'P&G-Ltd'!$C42 ) -> 0 | T42: =SUM(H42:S42) -> 0
D43: Gross margin % | H43: =1-((H17)/H4) -> 0.69723665 | I43: =1-((I17)/I4) -> 0.76356267 | J43: =1-((J17)/J4) -> 1 | K43: =1-((K17)/K4) -> #DIV/0! | L43: =1-((L17)/L4) -> #DIV/0! | M43: =1-((M17)/M4) -> #DIV/0! | N43: =1-((N17)/N4) -> #DIV/0! | O43: =1-((O17)/O4) -> #DIV/0! | ... S43: =1-((S17)/S4) -> #DIV/0! | T43: =SUMIFS( INDIRECT("input_invoice[net]"), INDIRECT("input_invoice[yyyymm]"), 'P&G-Ltd'!T$1, INDIRECT("input_invoice[concept/supplier]"), 'P&G-Ltd'!$C86 ) -> 0
D44: Gross margin | H44: =+H4-H17 -> 10948.47 | I44: =+I4-I17 -> 14835.45 | J44: =+J4-J17 -> 13642.64 | K44: =+K4-K17 -> 0 | L44: =+L4-L17 -> 0 | M44: =+M4-M17 -> 0 | N44: =+N4-N17 -> 0 | O44: =+O4-O17 -> 0 | ... S44: =+S4-S17 -> 0
D45: Contributive margin % | H45: =1-((H16)/H3) -> #REF! | I45: =1-((I16)/I3) -> #REF! | J45: =1-((J16)/J3) -> #REF! | K45: =1-((K16)/K3) -> #REF! | L45: =1-((L16)/L3) -> #REF! | M45: =1-((M16)/M3) -> #REF! | N45: =1-((N16)/N3) -> #REF! | O45: =1-((O16)/O3) -> #REF! | ... S45: =1-((S16)/S3) -> #REF! | T45: =SUMIFS( INDIRECT("input_invoice[net]"), INDIRECT("input_invoice[yyyymm]"), 'P&G-Ltd'!T$1, INDIRECT("input_invoice[concept/supplier]"), 'P&G-Ltd'!$C88 ) -> 0
D46: Contributive margin | H46: =+H3-H16 -> #REF! | I46: =+I3-I16 -> #REF! | J46: =+J3-J16 -> #REF! | K46: =+K3-K16 -> #REF! | L46: =+L3-L16 -> #REF! | M46: =+M3-M16 -> #REF! | N46: =+N3-N16 -> #REF! | O46: =+O3-O16 -> #REF! | ... S46: =+S3-S16 -> #REF! | T46: =SUM(H46:S46) -> #REF!
T47: =SUM(H47:S47) -> 0
D48: Fixed costs | H48: =+H49+H55+H58 -> 8847.8916 | I48: =+I49+I55+I58 -> 10332.484 | J48: =+J49+J55+J58 -> 0 | K48: =+K49+K55+K58 -> 0 | L48: =+L49+L55+L58 -> 0 | M48: =+M49+M55+M58 -> 0 | N48: =+N49+N55+N58 -> 0 | O48: =+O49+O55+O58 -> 0 | ... S48: =+S49+S55+S58 -> 0 | T48: =SUM(H48:S48) -> 19180.375
D49: Marketing | H49: =SUM(H50:H53) -> 5164.859 | I49: =SUM(I50:I53) -> 6631.989 | J49: =SUM(J50:J53) -> 0 | K49: =SUM(K50:K53) -> 0 | L49: =SUM(L50:L53) -> 0 | M49: =SUM(M50:M53) -> 0 | N49: =SUM(N50:N53) -> 0 | O49: =SUM(O50:O53) -> 0 | ... S49: =SUM(S50:S53) -> 0 | T49: =SUM(H49:S49) -> 11796.848
C50: marketing - google -> Ltd | F50: google | H50: =SUMIFS( INDIRECT("input_provisions[import]"), INDIRECT("input_provisions[yyyymm]"), 'P&G-Ltd'!H$1, INDIRECT("input_provisions[concept/supplier]"), 'P&G-Ltd'!$C50 )*H82 -> 2253.3634 | I50: =SUMIFS( INDIRECT("input_provisions[import]"), INDIRECT("input_provisions[yyyymm]"), 'P&G-Ltd'!I$1, INDIRECT("input_provisions[concept/supplier]"), 'P&G-Ltd'!$C50 )*I82 -> 4257.055 | J50: =SUMIFS( INDIRECT("input_provisions[import]"), INDIRECT("input_provisions[yyyymm]"), 'P&G-Ltd'!J$1, INDIRECT("input_provisions[concept/supplier]"), 'P&G-Ltd'!$C50 )*J82 -> 0 | K50: =SUMIFS( INDIRECT("input_provisions[import]"), INDIRECT("input_provisions[yyyymm]"), 'P&G-Ltd'!K$1, INDIRECT("input_provisions[concept/supplier]"), 'P&G-Ltd'!$C50 )*K82 -> 0 | L50: =SUMIFS( INDIRECT("input_provisions[import]"), INDIRECT("input_provisions[yyyymm]"), 'P&G-Ltd'!L$1, INDIRECT("input_provisions[concept/supplier]"), 'P&G-Ltd'!$C50 )*L82 -> 0 | M50: =SUMIFS( INDIRECT("input_provisions[import]"), INDIRECT("input_provisions[yyyymm]"), 'P&G-Ltd'!M$1, INDIRECT("input_provisions[concept/supplier]"), 'P&G-Ltd'!$C50 )*M82 -> 0 | N50: =SUMIFS( INDIRECT("input_provisions[import]"), INDIRECT("input_provisions[yyyymm]"), 'P&G-Ltd'!N$1, INDIRECT("input_provisions[concept/supplier]"), 'P&G-Ltd'!$C50 )*N82 -> 0 | O50: =SUMIFS( INDIRECT("input_provisions[import]"), INDIRECT("input_provisions[yyyymm]"), 'P&G-Ltd'!O$1, INDIRECT("input_provisions[concept/supplier]"), 'P&G-Ltd'!$C50 )*O82 -> 0 | ... S50: =SUMIFS( INDIRECT("input_provisions[import]"), INDIRECT("input_provisions[yyyymm]"), 'P&G-Ltd'!S$1, INDIRECT("input_provisions[concept/supplier]"), 'P&G-Ltd'!$C50 )*S82 -> 0 | T50: =SUM(H50:S50) -> 6510.4184
C51: marketing - meta -> Ltd | F51: meta | H51: =SUMIFS( INDIRECT("input_provisions[import]"), INDIRECT("input_provisions[yyyymm]"), 'P&G-Ltd'!H$1, INDIRECT("input_provisions[concept/supplier]"), 'P&G-Ltd'!$C51 )*H82 -> 2911.4956 | I51: =SUMIFS( INDIRECT("input_provisions[import]"), INDIRECT("input_provisions[yyyymm]"), 'P&G-Ltd'!I$1, INDIRECT("input_provisions[concept/supplier]"), 'P&G-Ltd'!$C51 )*I82 -> 2374.934 | J51: =SUMIFS( INDIRECT("input_provisions[import]"), INDIRECT("input_provisions[yyyymm]"), 'P&G-Ltd'!J$1, INDIRECT("input_provisions[concept/supplier]"), 'P&G-Ltd'!$C51 )*J82 -> 0 | K51: =SUMIFS( INDIRECT("input_provisions[import]"), INDIRECT("input_provisions[yyyymm]"), 'P&G-Ltd'!K$1, INDIRECT("input_provisions[concept/supplier]"), 'P&G-Ltd'!$C51 )*K82 -> 0 | L51: =SUMIFS( INDIRECT("input_provisions[import]"), INDIRECT("input_provisions[yyyymm]"), 'P&G-Ltd'!L$1, INDIRECT("input_provisions[concept/supplier]"), 'P&G-Ltd'!$C51 )*L82 -> 0 | M51: =SUMIFS( INDIRECT("input_provisions[import]"), INDIRECT("input_provisions[yyyymm]"), 'P&G-Ltd'!M$1, INDIRECT("input_provisions[concept/supplier]"), 'P&G-Ltd'!$C51 )*M82 -> 0 | N51: =SUMIFS( INDIRECT("input_provisions[import]"), INDIRECT("input_provisions[yyyymm]"), 'P&G-Ltd'!N$1, INDIRECT("input_provisions[concept/supplier]"), 'P&G-Ltd'!$C51 )*N82 -> 0 | O51: =SUMIFS( INDIRECT("input_provisions[import]"), INDIRECT("input_provisions[yyyymm]"), 'P&G-Ltd'!O$1, INDIRECT("input_provisions[concept/supplier]"), 'P&G-Ltd'!$C51 )*O82 -> 0 | ... S51: =SUMIFS( INDIRECT("input_provisions[import]"), INDIRECT("input_provisions[yyyymm]"), 'P&G-Ltd'!S$1, INDIRECT("input_provisions[concept/supplier]"), 'P&G-Ltd'!$C51 )*S82 -> 0 | T51: =SUM(H51:S51) -> 5286.4296
C52: marketing - tiktok -> Ltd | F52: tiktok | H52: =SUMIFS( INDIRECT("input_provisions[import]"), INDIRECT("input_provisions[yyyymm]"), 'P&G-Ltd'!H$1, INDIRECT("input_provisions[concept/supplier]"), 'P&G-Ltd'!$C52 )*H82 -> 0 | I52: =SUMIFS( INDIRECT("input_provisions[import]"), INDIRECT("input_provisions[yyyymm]"), 'P&G-Ltd'!I$1, INDIRECT("input_provisions[concept/supplier]"), 'P&G-Ltd'!$C52 )*I82 -> 0 | J52: =SUMIFS( INDIRECT("input_provisions[import]"), INDIRECT("input_provisions[yyyymm]"), 'P&G-Ltd'!J$1, INDIRECT("input_provisions[concept/supplier]"), 'P&G-Ltd'!$C52 )*J82 -> 0 | K52: =SUMIFS( INDIRECT("input_provisions[import]"), INDIRECT("input_provisions[yyyymm]"), 'P&G-Ltd'!K$1, INDIRECT("input_provisions[concept/supplier]"), 'P&G-Ltd'!$C52 )*K82 -> 0 | L52: =SUMIFS( INDIRECT("input_provisions[import]"), INDIRECT("input_provisions[yyyymm]"), 'P&G-Ltd'!L$1, INDIRECT("input_provisions[concept/supplier]"), 'P&G-Ltd'!$C52 )*L82 -> 0 | M52: =SUMIFS( INDIRECT("input_provisions[import]"), INDIRECT("input_provisions[yyyymm]"), 'P&G-Ltd'!M$1, INDIRECT("input_provisions[concept/supplier]"), 'P&G-Ltd'!$C52 )*M82 -> 0 | N52: =SUMIFS( INDIRECT("input_provisions[import]"), INDIRECT("input_provisions[yyyymm]"), 'P&G-Ltd'!N$1, INDIRECT("input_provisions[concept/supplier]"), 'P&G-Ltd'!$C52 )*N82 -> 0 | O52: =SUMIFS( INDIRECT("input_provisions[import]"), INDIRECT("input_provisions[yyyymm]"), 'P&G-Ltd'!O$1, INDIRECT("input_provisions[concept/supplier]"), 'P&G-Ltd'!$C52 )*O82 -> 0 | ... S52: =SUMIFS( INDIRECT("input_provisions[import]"), INDIRECT("input_provisions[yyyymm]"), 'P&G-Ltd'!S$1, INDIRECT("input_provisions[concept/supplier]"), 'P&G-Ltd'!$C52 )*S82 -> 0 | T52: =SUM(H52:S52) -> 0
C53: marketing - pinterest -> Ltd | F53: pinterest | H53: =SUMIFS( INDIRECT("input_provisions[import]"), INDIRECT("input_provisions[yyyymm]"), 'P&G-Ltd'!H$1, INDIRECT("input_provisions[concept/supplier]"), 'P&G-Ltd'!$C53 )*H82 -> 0 | I53: =SUMIFS( INDIRECT("input_provisions[import]"), INDIRECT("input_provisions[yyyymm]"), 'P&G-Ltd'!I$1, INDIRECT("input_provisions[concept/supplier]"), 'P&G-Ltd'!$C53 )*I82 -> 0 | J53: =SUMIFS( INDIRECT("input_provisions[import]"), INDIRECT("input_provisions[yyyymm]"), 'P&G-Ltd'!J$1, INDIRECT("input_provisions[concept/supplier]"), 'P&G-Ltd'!$C53 )*J82 -> 0 | K53: =SUMIFS( INDIRECT("input_provisions[import]"), INDIRECT("input_provisions[yyyymm]"), 'P&G-Ltd'!K$1, INDIRECT("input_provisions[concept/supplier]"), 'P&G-Ltd'!$C53 )*K82 -> 0 | L53: =SUMIFS( INDIRECT("input_provisions[import]"), INDIRECT("input_provisions[yyyymm]"), 'P&G-Ltd'!L$1, INDIRECT("input_provisions[concept/supplier]"), 'P&G-Ltd'!$C53 )*L82 -> 0 | M53: =SUMIFS( INDIRECT("input_provisions[import]"), INDIRECT("input_provisions[yyyymm]"), 'P&G-Ltd'!M$1, INDIRECT("input_provisions[concept/supplier]"), 'P&G-Ltd'!$C53 )*M82 -> 0 | N53: =SUMIFS( INDIRECT("input_provisions[import]"), INDIRECT("input_provisions[yyyymm]"), 'P&G-Ltd'!N$1, INDIRECT("input_provisions[concept/supplier]"), 'P&G-Ltd'!$C53 )*N82 -> 0 | O53: =SUMIFS( INDIRECT("input_provisions[import]"), INDIRECT("input_provisions[yyyymm]"), 'P&G-Ltd'!O$1, INDIRECT("input_provisions[concept/supplier]"), 'P&G-Ltd'!$C53 )*O82 -> 0 | ... S53: =SUMIFS( INDIRECT("input_provisions[import]"), INDIRECT("input_provisions[yyyymm]"), 'P&G-Ltd'!S$1, INDIRECT("input_provisions[concept/supplier]"), 'P&G-Ltd'!$C53 )*S82 -> 0 | T53: =SUM(H53:S53) -> 0
D55: Staff | H55: =+H56 -> 2533.8765 | I55: =+I56 -> 2535.6656 | J55: =+J56 -> 0 | K55: =+K56 -> 0 | L55: =+L56 -> 0 | M55: =+M56 -> 0 | N55: =+N56 -> 0 | O55: =+O56 -> 0 | ... S55: =+S56 -> 0 | T55: =SUM(H55:S55) -> 5069.5421
F56: Shared services - UK | H56: =+'P&G-SL'!I109*H82 -> 2533.8765 | I56: =+'P&G-SL'!J109*I82 -> 2535.6656 | J56: =+'P&G-SL'!K109*J82 -> 0 | K56: =+'P&G-SL'!L109*K82 -> 0 | L56: =+'P&G-SL'!M109*L82 -> 0 | M56: =+'P&G-SL'!N109*M82 -> 0 | N56: =+'P&G-SL'!O109*N82 -> 0 | O56: =+'P&G-SL'!P109*O82 -> 0 | ... S56: =+'P&G-SL'!T109*S82 -> 0 | T56: =SUM(H56:S56) -> 5069.5421
D58: Administrative costs | H58: =+H59+H62+H65 -> 1149.1561 | I58: =+I59+I62+I65 -> 1164.8292 | J58: =+J59+J62+J65 -> 0 | K58: =+K59+K62+K65 -> 0 | L58: =+L59+L62+L65 -> 0 | M58: =+M59+M62+M65 -> 0 | N58: =+N59+N62+N65 -> 0 | O58: =+O59+O62+O65 -> 0 | ... S58: =+S59+S62+S65 -> 0 | T58: =SUM(H58:S58) -> 2313.9853
F59: Administración y legal | H59: =SUM(H60:H61) -> 0 | I59: =SUM(I60:I61) -> 0 | J59: =SUM(J60:J61) -> 0 | K59: =SUM(K60:K61) -> 0 | L59: =SUM(L60:L61) -> 0 | M59: =SUM(M60:M61) -> 0 | N59: =SUM(N60:N61) -> 0 | O59: =SUM(O60:O61) -> 0 | ... S59: =SUM(S60:S61) -> 0 | T59: =SUM(H59:S59) -> 0
C60: administrative - youraccountsntaxes -> Ltd | G60: YourAccountNTaxes | H60: =SUMIFS( INDIRECT("input_invoice[net]"), INDIRECT("input_invoice[yyyymm]"), 'P&G-Ltd'!H$1, INDIRECT("input_invoice[concept/supplier]"), 'P&G-Ltd'!$C60 ) -> 0 | I60: =SUMIFS( INDIRECT("input_invoice[net]"), INDIRECT("input_invoice[yyyymm]"), 'P&G-Ltd'!I$1, INDIRECT("input_invoice[concept/supplier]"), 'P&G-Ltd'!$C60 ) -> 0 | J60: =SUMIFS( INDIRECT("input_invoice[net]"), INDIRECT("input_invoice[yyyymm]"), 'P&G-Ltd'!J$1, INDIRECT("input_invoice[concept/supplier]"), 'P&G-Ltd'!$C60 ) -> 0 | K60: =SUMIFS( INDIRECT("input_invoice[net]"), INDIRECT("input_invoice[yyyymm]"), 'P&G-Ltd'!K$1, INDIRECT("input_invoice[concept/supplier]"), 'P&G-Ltd'!$C60 ) -> 0 | L60: =SUMIFS( INDIRECT("input_invoice[net]"), INDIRECT("input_invoice[yyyymm]"), 'P&G-Ltd'!L$1, INDIRECT("input_invoice[concept/supplier]"), 'P&G-Ltd'!$C60 ) -> 0 | M60: =SUMIFS( INDIRECT("input_invoice[net]"), INDIRECT("input_invoice[yyyymm]"), 'P&G-Ltd'!M$1, INDIRECT("input_invoice[concept/supplier]"), 'P&G-Ltd'!$C60 ) -> 0 | N60: =SUMIFS( INDIRECT("input_invoice[net]"), INDIRECT("input_invoice[yyyymm]"), 'P&G-Ltd'!N$1, INDIRECT("input_invoice[concept/supplier]"), 'P&G-Ltd'!$C60 ) -> 0 | O60: =SUMIFS( INDIRECT("input_invoice[net]"), INDIRECT("input_invoice[yyyymm]"), 'P&G-Ltd'!O$1, INDIRECT("input_invoice[concept/supplier]"), 'P&G-Ltd'!$C60 ) -> 0 | ... S60: =SUMIFS( INDIRECT("input_invoice[net]"), INDIRECT("input_invoice[yyyymm]"), 'P&G-Ltd'!S$1, INDIRECT("input_invoice[concept/supplier]"), 'P&G-Ltd'!$C60 ) -> 0 | T60: =SUM(H60:S60) -> 0
C61: administrative - otros -> Ltd | G61: Otros | H61: =SUMIFS( INDIRECT("input_invoice[net]"), INDIRECT("input_invoice[yyyymm]"), 'P&G-Ltd'!H$1, INDIRECT("input_invoice[concept/supplier]"), 'P&G-Ltd'!$C61 ) -> 0 | I61: =SUMIFS( INDIRECT("input_invoice[net]"), INDIRECT("input_invoice[yyyymm]"), 'P&G-Ltd'!I$1, INDIRECT("input_invoice[concept/supplier]"), 'P&G-Ltd'!$C61 ) -> 0 | J61: =SUMIFS( INDIRECT("input_invoice[net]"), INDIRECT("input_invoice[yyyymm]"), 'P&G-Ltd'!J$1, INDIRECT("input_invoice[concept/supplier]"), 'P&G-Ltd'!$C61 ) -> 0 | K61: =SUMIFS( INDIRECT("input_invoice[net]"), INDIRECT("input_invoice[yyyymm]"), 'P&G-Ltd'!K$1, INDIRECT("input_invoice[concept/supplier]"), 'P&G-Ltd'!$C61 ) -> 0 | L61: =SUMIFS( INDIRECT("input_invoice[net]"), INDIRECT("input_invoice[yyyymm]"), 'P&G-Ltd'!L$1, INDIRECT("input_invoice[concept/supplier]"), 'P&G-Ltd'!$C61 ) -> 0 | M61: =SUMIFS( INDIRECT("input_invoice[net]"), INDIRECT("input_invoice[yyyymm]"), 'P&G-Ltd'!M$1, INDIRECT("input_invoice[concept/supplier]"), 'P&G-Ltd'!$C61 ) -> 0 | N61: =SUMIFS( INDIRECT("input_invoice[net]"), INDIRECT("input_invoice[yyyymm]"), 'P&G-Ltd'!N$1, INDIRECT("input_invoice[concept/supplier]"), 'P&G-Ltd'!$C61 ) -> 0 | O61: =SUMIFS( INDIRECT("input_invoice[net]"), INDIRECT("input_invoice[yyyymm]"), 'P&G-Ltd'!O$1, INDIRECT("input_invoice[concept/supplier]"), 'P&G-Ltd'!$C61 ) -> 0 | ... S61: =SUMIFS( INDIRECT("input_invoice[net]"), INDIRECT("input_invoice[yyyymm]"), 'P&G-Ltd'!S$1, INDIRECT("input_invoice[concept/supplier]"), 'P&G-Ltd'!$C61 ) -> 0 | T61: =SUM(H61:S61) -> 0
F62: Technology | H62: =SUM(H63:H64) -> 0 | I62: =SUM(I63:I64) -> 0 | J62: =SUM(J63:J64) -> 0 | K62: =SUM(K63:K64) -> 0 | L62: =SUM(L63:L64) -> 0 | M62: =SUM(M63:M64) -> 0 | N62: =SUM(N63:N64) -> 0 | O62: =SUM(O63:O64) -> 0 | ... S62: =SUM(S63:S64) -> 0 | T62: =SUM(H62:S62) -> 0
C63: it - Shopify -> Ltd | G63: Shopify | H63: =SUMIFS( INDIRECT("input_invoice[net]"), INDIRECT("input_invoice[yyyymm]"), 'P&G-Ltd'!H$1, INDIRECT("input_invoice[concept/supplier]"), 'P&G-Ltd'!$C63 ) -> 0 | I63: =SUMIFS( INDIRECT("input_invoice[net]"), INDIRECT("input_invoice[yyyymm]"), 'P&G-Ltd'!I$1, INDIRECT("input_invoice[concept/supplier]"), 'P&G-Ltd'!$C63 ) -> 0 | J63: =SUMIFS( INDIRECT("input_invoice[net]"), INDIRECT("input_invoice[yyyymm]"), 'P&G-Ltd'!J$1, INDIRECT("input_invoice[concept/supplier]"), 'P&G-Ltd'!$C63 ) -> 0 | K63: =SUMIFS( INDIRECT("input_invoice[net]"), INDIRECT("input_invoice[yyyymm]"), 'P&G-Ltd'!K$1, INDIRECT("input_invoice[concept/supplier]"), 'P&G-Ltd'!$C63 ) -> 0 | L63: =SUMIFS( INDIRECT("input_invoice[net]"), INDIRECT("input_invoice[yyyymm]"), 'P&G-Ltd'!L$1, INDIRECT("input_invoice[concept/supplier]"), 'P&G-Ltd'!$C63 ) -> 0 | M63: =SUMIFS( INDIRECT("input_invoice[net]"), INDIRECT("input_invoice[yyyymm]"), 'P&G-Ltd'!M$1, INDIRECT("input_invoice[concept/supplier]"), 'P&G-Ltd'!$C63 ) -> 0 | N63: =SUMIFS( INDIRECT("input_invoice[net]"), INDIRECT("input_invoice[yyyymm]"), 'P&G-Ltd'!N$1, INDIRECT("input_invoice[concept/supplier]"), 'P&G-Ltd'!$C63 ) -> 0 | O63: =SUMIFS( INDIRECT("input_invoice[net]"), INDIRECT("input_invoice[yyyymm]"), 'P&G-Ltd'!O$1, INDIRECT("input_invoice[concept/supplier]"), 'P&G-Ltd'!$C63 ) -> 0 | ... S63: =SUMIFS( INDIRECT("input_invoice[net]"), INDIRECT("input_invoice[yyyymm]"), 'P&G-Ltd'!S$1, INDIRECT("input_invoice[concept/supplier]"), 'P&G-Ltd'!$C63 ) -> 0 | T63: =SUM(H63:S63) -> 0
C64: it - Amazon Subscription -> Ltd | G64: Amazon Subscrition | H64: =SUMIFS( INDIRECT("input_invoice[net]"), INDIRECT("input_invoice[yyyymm]"), 'P&G-Ltd'!H$1, INDIRECT("input_invoice[concept/supplier]"), 'P&G-Ltd'!$C64 ) -> 0 | I64: =SUMIFS( INDIRECT("input_invoice[net]"), INDIRECT("input_invoice[yyyymm]"), 'P&G-Ltd'!I$1, INDIRECT("input_invoice[concept/supplier]"), 'P&G-Ltd'!$C64 ) -> 0 | J64: =SUMIFS( INDIRECT("input_invoice[net]"), INDIRECT("input_invoice[yyyymm]"), 'P&G-Ltd'!J$1, INDIRECT("input_invoice[concept/supplier]"), 'P&G-Ltd'!$C64 ) -> 0 | K64: =SUMIFS( INDIRECT("input_invoice[net]"), INDIRECT("input_invoice[yyyymm]"), 'P&G-Ltd'!K$1, INDIRECT("input_invoice[concept/supplier]"), 'P&G-Ltd'!$C64 ) -> 0 | L64: =SUMIFS( INDIRECT("input_invoice[net]"), INDIRECT("input_invoice[yyyymm]"), 'P&G-Ltd'!L$1, INDIRECT("input_invoice[concept/supplier]"), 'P&G-Ltd'!$C64 ) -> 0 | M64: =SUMIFS( INDIRECT("input_invoice[net]"), INDIRECT("input_invoice[yyyymm]"), 'P&G-Ltd'!M$1, INDIRECT("input_invoice[concept/supplier]"), 'P&G-Ltd'!$C64 ) -> 0 | N64: =SUMIFS( INDIRECT("input_invoice[net]"), INDIRECT("input_invoice[yyyymm]"), 'P&G-Ltd'!N$1, INDIRECT("input_invoice[concept/supplier]"), 'P&G-Ltd'!$C64 ) -> 0 | O64: =SUMIFS( INDIRECT("input_invoice[net]"), INDIRECT("input_invoice[yyyymm]"), 'P&G-Ltd'!O$1, INDIRECT("input_invoice[concept/supplier]"), 'P&G-Ltd'!$C64 ) -> 0 | ... S64: =SUMIFS( INDIRECT("input_invoice[net]"), INDIRECT("input_invoice[yyyymm]"), 'P&G-Ltd'!S$1, INDIRECT("input_invoice[concept/supplier]"), 'P&G-Ltd'!$C64 ) -> 0
F65: Shared services the UK | H65: =+'P&G-SL'!I142*H82 -> 1149.1561 | I65: =+'P&G-SL'!J142*I82 -> 1164.8292 | J65: =+'P&G-SL'!K142*J82 -> 0 | K65: =+'P&G-SL'!L142*K82 -> 0 | L65: =+'P&G-SL'!M142*L82 -> 0 | M65: =+'P&G-SL'!N142*M82 -> 0 | N65: =+'P&G-SL'!O142*N82 -> 0 | O65: =+'P&G-SL'!P142*O82 -> 0 | ... S65: =+'P&G-SL'!T142*S82 -> 0 | T65: =SUM(H65:S65) -> 2313.9853
T66: =SUM(H66:S66) -> 0
T67: =SUM(H67:S67) -> 0
D68: Operating profit | G68: Operating profit | H68: =+H46-H48 -> #REF! | I68: =+I46-I48 -> #REF! | J68: =+J46-J48 -> #REF! | K68: =+K46-K48 -> #REF! | L68: =+L46-L48 -> #REF! | M68: =+M46-M48 -> #REF! | N68: =+N46-N48 -> #REF! | O68: =+O46-O48 -> #REF! | ... S68: =+S46-S48 -> #REF! | T68: =SUM(H68:S68) -> #REF!
C69: uncategorized - incomes -> Ltd | G69: Uncategorized income | H69: =SUMIFS( INDIRECT("input_invoice[net]"), INDIRECT("input_invoice[yyyymm]"), 'P&G-Ltd'!H$1, INDIRECT("input_invoice[concept/supplier]"), 'P&G-Ltd'!$C133 ) -> 0 | I69: =SUMIFS( INDIRECT("input_invoice[net]"), INDIRECT("input_invoice[yyyymm]"), 'P&G-Ltd'!I$1, INDIRECT("input_invoice[concept/supplier]"), 'P&G-Ltd'!$C133 ) -> 0 | J69: =SUMIFS( INDIRECT("input_invoice[net]"), INDIRECT("input_invoice[yyyymm]"), 'P&G-Ltd'!J$1, INDIRECT("input_invoice[concept/supplier]"), 'P&G-Ltd'!$C133 ) -> 0 | K69: =SUMIFS( INDIRECT("input_invoice[net]"), INDIRECT("input_invoice[yyyymm]"), 'P&G-Ltd'!K$1, INDIRECT("input_invoice[concept/supplier]"), 'P&G-Ltd'!$C133 ) -> 0 | L69: =SUMIFS( INDIRECT("input_invoice[net]"), INDIRECT("input_invoice[yyyymm]"), 'P&G-Ltd'!L$1, INDIRECT("input_invoice[concept/supplier]"), 'P&G-Ltd'!$C133 ) -> 0 | M69: =SUMIFS( INDIRECT("input_invoice[net]"), INDIRECT("input_invoice[yyyymm]"), 'P&G-Ltd'!M$1, INDIRECT("input_invoice[concept/supplier]"), 'P&G-Ltd'!$C133 ) -> 0 | N69: =SUMIFS( INDIRECT("input_invoice[net]"), INDIRECT("input_invoice[yyyymm]"), 'P&G-Ltd'!N$1, INDIRECT("input_invoice[concept/supplier]"), 'P&G-Ltd'!$C133 ) -> 0 | O69: =SUMIFS( INDIRECT("input_invoice[net]"), INDIRECT("input_invoice[yyyymm]"), 'P&G-Ltd'!O$1, INDIRECT("input_invoice[concept/supplier]"), 'P&G-Ltd'!$C133 ) -> 0 | ... S69: =SUMIFS( INDIRECT("input_invoice[net]"), INDIRECT("input_invoice[yyyymm]"), 'P&G-Ltd'!S$1, INDIRECT("input_invoice[concept/supplier]"), 'P&G-Ltd'!$C133 ) -> 0 | T69: =SUM(H69:S69) -> 0
C70: uncategorized - expenses -> Ltd | G70: Uncategorized expenses | H70: =SUMIFS( INDIRECT("input_invoice[net]"), INDIRECT("input_invoice[yyyymm]"), 'P&G-Ltd'!H$1, INDIRECT("input_invoice[concept/supplier]"), 'P&G-Ltd'!$C134 ) -> 0 | I70: =SUMIFS( INDIRECT("input_invoice[net]"), INDIRECT("input_invoice[yyyymm]"), 'P&G-Ltd'!I$1, INDIRECT("input_invoice[concept/supplier]"), 'P&G-Ltd'!$C134 ) -> 0 | J70: =SUMIFS( INDIRECT("input_invoice[net]"), INDIRECT("input_invoice[yyyymm]"), 'P&G-Ltd'!J$1, INDIRECT("input_invoice[concept/supplier]"), 'P&G-Ltd'!$C134 ) -> 0 | K70: =SUMIFS( INDIRECT("input_invoice[net]"), INDIRECT("input_invoice[yyyymm]"), 'P&G-Ltd'!K$1, INDIRECT("input_invoice[concept/supplier]"), 'P&G-Ltd'!$C134 ) -> 0 | L70: =SUMIFS( INDIRECT("input_invoice[net]"), INDIRECT("input_invoice[yyyymm]"), 'P&G-Ltd'!L$1, INDIRECT("input_invoice[concept/supplier]"), 'P&G-Ltd'!$C134 ) -> 0 | M70: =SUMIFS( INDIRECT("input_invoice[net]"), INDIRECT("input_invoice[yyyymm]"), 'P&G-Ltd'!M$1, INDIRECT("input_invoice[concept/supplier]"), 'P&G-Ltd'!$C134 ) -> 0 | N70: =SUMIFS( INDIRECT("input_invoice[net]"), INDIRECT("input_invoice[yyyymm]"), 'P&G-Ltd'!N$1, INDIRECT("input_invoice[concept/supplier]"), 'P&G-Ltd'!$C134 ) -> 0 | O70: =SUMIFS( INDIRECT("input_invoice[net]"), INDIRECT("input_invoice[yyyymm]"), 'P&G-Ltd'!O$1, INDIRECT("input_invoice[concept/supplier]"), 'P&G-Ltd'!$C134 ) -> 0 | ... S70: =SUMIFS( INDIRECT("input_invoice[net]"), INDIRECT("input_invoice[yyyymm]"), 'P&G-Ltd'!S$1, INDIRECT("input_invoice[concept/supplier]"), 'P&G-Ltd'!$C134 ) -> 0 | T70: =SUM(H70:S70) -> 0
T71: =SUM(H71:S71) -> 0
D72: Profits before taxation | G72: Profits before taxation | H72: =+H68+H69-H70 -> #REF! | I72: =+I68+I69-I70 -> #REF! | J72: =+J68+J69-J70 -> #REF! | K72: =+K68+K69-K70 -> #REF! | L72: =+L68+L69-L70 -> #REF! | M72: =+M68+M69-M70 -> #REF! | N72: =+N68+N69-N70 -> #REF! | O72: =+O68+O69-O70 -> #REF! | ... S72: =+S68+S69-S70 -> #REF! | T72: =SUM(H72:S72) -> #REF!
G73: Taxes | T73: =SUM(H73:S73) -> 0
T74: =SUM(H74:S74) -> 0
D75: Profits after taxation | G75: Profits after taxation | H75: =+H72-H73 -> #REF! | I75: =+I72-I73 -> #REF! | J75: =+J72-J73 -> #REF! | K75: =+K72-K73 -> #REF! | L75: =+L72-L73 -> #REF! | M75: =+M72-M73 -> #REF! | N75: =+N72-N73 -> #REF! | O75: =+O72-O73 -> #REF! | ... S75: =+S72-S73 -> #REF! | T75: =SUM(H75:S75) -> #REF!
T76: =SUM(H76:S76) -> 0
G82: Exchange rate GBP | H82: =+'input-divisas'!B4 -> 0.86 | I82: =+'input-divisas'!C4 -> 0.85 | J82: =+'input-divisas'!D4 -> 0.855 | K82: =+'input-divisas'!E4 -> 0.86 | L82: =+'input-divisas'!F4 -> 0.85 | M82: =+'input-divisas'!G4 -> 0.85 | N82: =+'input-divisas'!H4 -> 0.85 | O82: =+'input-divisas'!I4 -> 0.85 | ... S82: =+'input-divisas'!M4 -> 0.85
H88: =+H2 -> Enero | I88: =+I2 -> Febrero | J88: =+J2 -> Marzo | K88: =+K2 -> Abril | L88: =+L2 -> Mayo | M88: =+M2 -> Junio | N88: =+N2 -> Julio | O88: =+O2 -> Agosto | ... R88: =+R2 -> Noviembre
D89: Shared services | H89: =+H32+H56+H65+H49 -> #REF! | I89: =+I32+I56+I65+I49 -> #REF! | J89: =+J32+J56+J65+J49 -> #REF! | K89: =+K32+K56+K65+K49 -> #REF! | L89: =+L32+L56+L65+L49 -> #REF! | M89: =+M32+M56+M65+M49 -> #REF! | N89: =+N32+N56+N65+N49 -> #REF! | O89: =+O32+O56+O65+O49 -> #REF! | ... R89: =+R32+R56+R65+R49 -> #REF! | S89: =+S32+S56+S65 -> #REF!
Q90: 12165.66 | R90: 20793.48
Q91: =+Q90-Q89 -> #REF! | R91: =R90-R89 -> #REF!
P96: Shared Services
Q97: enero | R97: febrero
P98: PYG nuestro | Q98: 9826.2091 | R98: 11657.831
P99: PYG christine | Q99: 12165.66 | R99: 20793.48
P100: Diferencia | Q100: 2339.4509 | R100: 9135.649
Q102: 10732.87 | R102: 13068.98
Q103: =+Q102/1.15 -> 9332.9304 | R103: =+R102/1.15 -> 11364.33

Sheet P&G-Inc
H1: 202601 | I1: 202602 | J1: 202603 | K1: 202604 | L1: 202605 | M1: 202606 | N1: 202607 | O1: 202608 | P1: 202609 | Q1: 202610 | R1: 202611 | S1: 202612
D2: =+#REF!&"-"&#REF! -> #REF! | H2: Enero | I2: Febrero | J2: Marzo | K2: Abril | L2: Mayo | M2: Junio | N2: Julio | O2: Agosto | P2: Septiembre | Q2: Octubre | R2: Noviembre | S2: Diciembre | T2: Total
D3: Turnover | H3: =+H4 -> 10261.58 | I3: =+I4 -> 15549.06 | J3: =+J4 -> 10787.15 | K3: =+K4 -> 0 | L3: =+L4 -> 0 | M3: =+M4 -> 0 | N3: =+N4 -> 0 | O3: =+O4 -> 0 | ... S3: =+S4 -> 0 | T3: =SUM(H3:S3) -> 36597.79
A4: Hannun | B4: Mirakl | C4: Country | D4: Sales | H4: =+H5 -> 10261.58 | I4: =+I5 -> 15549.06 | J4: =+J5 -> 10787.15 | K4: =+K5 -> 0 | L4: =+L5 -> 0 | M4: =+M5 -> 0 | N4: =+N5 -> 0 | O4: =+O5 -> 0 | ... S4: =+S5 -> 0 | T4: =SUM(H4:S4) -> 36597.79
D5: #VALUE! | E5: United States | H5: =+H7 -> 10261.58 | I5: =+I7 -> 15549.06 | J5: =+J7 -> 10787.15 | K5: =+K7 -> 0 | L5: =+L7 -> 0 | M5: =+M7 -> 0 | N5: =+N7 -> 0 | O5: =+O7 -> 0 | ... S5: =+S7 -> 0 | T5: =SUM(H5:S5) -> 36597.79
G6: Share % | H6: =IFERROR(+H5/H$4,0) -> 1 | I6: =IFERROR(+I5/I$4,0) -> 1 | J6: =IFERROR(+J5/J$4,0) -> 1 | K6: =IFERROR(+K5/K$4,0) -> 0 | L6: =IFERROR(+L5/L$4,0) -> 0 | M6: =IFERROR(+M5/M$4,0) -> 0 | N6: =IFERROR(+N5/N$4,0) -> 0 | O6: =IFERROR(+O5/O$4,0) -> 0 | ... T6: =IFERROR(+T5/T$4,0) -> 1
A7: 0 | B7: 0 | C7: US | F7: Shopify | H7: =SUMIFS('i-sales'!$K:$K, 'i-sales'!$C:$C,'P&G-Inc'!H$1, 'i-sales'!$D:$D,'P&G-Inc'!$C7, 'i-sales'!$G:$G,'P&G-Inc'!$A7, 'i-sales'!$H:$H,'P&G-Inc'!$B7 ) -> 10261.58 | I7: =SUMIFS('i-sales'!$K:$K, 'i-sales'!$C:$C,'P&G-Inc'!I$1, 'i-sales'!$D:$D,'P&G-Inc'!$C7, 'i-sales'!$G:$G,'P&G-Inc'!$A7, 'i-sales'!$H:$H,'P&G-Inc'!$B7 ) -> 15549.06 | J7: =SUMIFS('i-sales'!$K:$K, 'i-sales'!$C:$C,'P&G-Inc'!J$1, 'i-sales'!$D:$D,'P&G-Inc'!$C7, 'i-sales'!$G:$G,'P&G-Inc'!$A7, 'i-sales'!$H:$H,'P&G-Inc'!$B7 ) -> 10787.15 | K7: =SUMIFS('i-sales'!$K:$K, 'i-sales'!$C:$C,'P&G-Inc'!K$1, 'i-sales'!$D:$D,'P&G-Inc'!$C7, 'i-sales'!$G:$G,'P&G-Inc'!$A7, 'i-sales'!$H:$H,'P&G-Inc'!$B7 ) -> 0 | L7: =SUMIFS('i-sales'!$K:$K, 'i-sales'!$C:$C,'P&G-Inc'!L$1, 'i-sales'!$D:$D,'P&G-Inc'!$C7, 'i-sales'!$G:$G,'P&G-Inc'!$A7, 'i-sales'!$H:$H,'P&G-Inc'!$B7 ) -> 0 | M7: =SUMIFS('i-sales'!$K:$K, 'i-sales'!$C:$C,'P&G-Inc'!M$1, 'i-sales'!$D:$D,'P&G-Inc'!$C7, 'i-sales'!$G:$G,'P&G-Inc'!$A7, 'i-sales'!$H:$H,'P&G-Inc'!$B7 ) -> 0 | N7: =SUMIFS('i-sales'!$K:$K, 'i-sales'!$C:$C,'P&G-Inc'!N$1, 'i-sales'!$D:$D,'P&G-Inc'!$C7, 'i-sales'!$G:$G,'P&G-Inc'!$A7, 'i-sales'!$H:$H,'P&G-Inc'!$B7 ) -> 0 | O7: =SUMIFS('i-sales'!$K:$K, 'i-sales'!$C:$C,'P&G-Inc'!O$1, 'i-sales'!$D:$D,'P&G-Inc'!$C7, 'i-sales'!$G:$G,'P&G-Inc'!$A7, 'i-sales'!$H:$H,'P&G-Inc'!$B7 ) -> 0 | ... S7: =SUMIFS('i-sales'!$K:$K, 'i-sales'!$C:$C,'P&G-Inc'!S$1, 'i-sales'!$D:$D,'P&G-Inc'!$C7, 'i-sales'!$G:$G,'P&G-Inc'!$A7, 'i-sales'!$H:$H,'P&G-Inc'!$B7 ) -> 0 | T7: =SUM(H7:S7) -> 36597.79
S8: =+((S10)+S15)/S4 -> #DIV/0!
D9: Cost of sales | H9: =+H10+H15+H20+H23+H30 -> #REF! | I9: =+I10+I15+I20+I23+I30 -> #REF! | J9: =+J10+J15+J20+J23+J30 -> #REF! | K9: =+K10+K15+K20+K23+K30 -> #REF! | L9: =+L10+L15+L20+L23+L30 -> #REF! | M9: =+M10+M15+M20+M23+M30 -> #REF! | N9: =+N10+N15+N20+N23+N30 -> #REF! | O9: =+O10+O15+O20+O23+O30 -> #REF! | ... S9: =+S10+S15+S20+S23+S30 -> #REF! | T9: =SUM(H9:S9) -> #REF!
D10: Manufacturing | H10: =SUM(H11:H13) -> 1562.55 | I10: =SUM(I11:I13) -> 2616.28 | J10: =SUM(J11:J13) -> 0 | K10: =SUM(K11:K13) -> 0 | L10: =SUM(L11:L13) -> 0 | M10: =SUM(M11:M13) -> 0 | N10: =SUM(N11:N13) -> 0 | O10: =SUM(O11:O13) -> 0 | ... S10: =SUM(S11:S13) -> 0 | T10: =SUM(H10:S10) -> 4178.83
C11: manufacturing - TGI Inc -> Inc | E11: #VALUE! | F11: TGI | H11: =SUMIFS( INDIRECT("input_invoice[net]"), INDIRECT("input_invoice[yyyymm]"), 'P&G-Inc'!H$1, INDIRECT("input_invoice[concept/supplier]"), 'P&G-Inc'!$C11 ) -> 1562.55 | I11: =SUMIFS( INDIRECT("input_invoice[net]"), INDIRECT("input_invoice[yyyymm]"), 'P&G-Inc'!I$1, INDIRECT("input_invoice[concept/supplier]"), 'P&G-Inc'!$C11 ) -> 2616.28 | J11: =SUMIFS( INDIRECT("input_invoice[net]"), INDIRECT("input_invoice[yyyymm]"), 'P&G-Inc'!J$1, INDIRECT("input_invoice[concept/supplier]"), 'P&G-Inc'!$C11 ) -> 0 | K11: =SUMIFS( INDIRECT("input_invoice[net]"), INDIRECT("input_invoice[yyyymm]"), 'P&G-Inc'!K$1, INDIRECT("input_invoice[concept/supplier]"), 'P&G-Inc'!$C11 ) -> 0 | L11: =SUMIFS( INDIRECT("input_invoice[net]"), INDIRECT("input_invoice[yyyymm]"), 'P&G-Inc'!L$1, INDIRECT("input_invoice[concept/supplier]"), 'P&G-Inc'!$C11 ) -> 0 | M11: =SUMIFS( INDIRECT("input_invoice[net]"), INDIRECT("input_invoice[yyyymm]"), 'P&G-Inc'!M$1, INDIRECT("input_invoice[concept/supplier]"), 'P&G-Inc'!$C11 ) -> 0 | N11: =SUMIFS( INDIRECT("input_invoice[net]"), INDIRECT("input_invoice[yyyymm]"), 'P&G-Inc'!N$1, INDIRECT("input_invoice[concept/supplier]"), 'P&G-Inc'!$C11 ) -> 0 | O11: =SUMIFS( INDIRECT("input_invoice[net]"), INDIRECT("input_invoice[yyyymm]"), 'P&G-Inc'!O$1, INDIRECT("input_invoice[concept/supplier]"), 'P&G-Inc'!$C11 ) -> 0 | ... S11: =SUMIFS( INDIRECT("input_invoice[net]"), INDIRECT("input_invoice[yyyymm]"), 'P&G-Inc'!S$1, INDIRECT("input_invoice[concept/supplier]"), 'P&G-Inc'!$C11 ) -> 0 | T11: =SUM(H11:S11) -> 4178.83
C12: manufacturing - jondo -> Inc | E12: #VALUE! | F12: Jondo Canvas | H12: =SUMIFS( INDIRECT("input_invoice[net]"), INDIRECT("input_invoice[yyyymm]"), 'P&G-Inc'!H$1, INDIRECT("input_invoice[concept/supplier]"), 'P&G-Inc'!$C12 ) -> 0 | I12: =SUMIFS( INDIRECT("input_invoice[net]"), INDIRECT("input_invoice[yyyymm]"), 'P&G-Inc'!I$1, INDIRECT("input_invoice[concept/supplier]"), 'P&G-Inc'!$C12 ) -> 0 | J12: =SUMIFS( INDIRECT("input_invoice[net]"), INDIRECT("input_invoice[yyyymm]"), 'P&G-Inc'!J$1, INDIRECT("input_invoice[concept/supplier]"), 'P&G-Inc'!$C12 ) -> 0 | K12: =SUMIFS( INDIRECT("input_invoice[net]"), INDIRECT("input_invoice[yyyymm]"), 'P&G-Inc'!K$1, INDIRECT("input_invoice[concept/supplier]"), 'P&G-Inc'!$C12 ) -> 0 | L12: =SUMIFS( INDIRECT("input_invoice[net]"), INDIRECT("input_invoice[yyyymm]"), 'P&G-Inc'!L$1, INDIRECT("input_invoice[concept/supplier]"), 'P&G-Inc'!$C12 ) -> 0 | M12: =SUMIFS( INDIRECT("input_invoice[net]"), INDIRECT("input_invoice[yyyymm]"), 'P&G-Inc'!M$1, INDIRECT("input_invoice[concept/supplier]"), 'P&G-Inc'!$C12 ) -> 0 | N12: =SUMIFS( INDIRECT("input_invoice[net]"), INDIRECT("input_invoice[yyyymm]"), 'P&G-Inc'!N$1, INDIRECT("input_invoice[concept/supplier]"), 'P&G-Inc'!$C12 ) -> 0 | O12: =SUMIFS( INDIRECT("input_invoice[net]"), INDIRECT("input_invoice[yyyymm]"), 'P&G-Inc'!O$1, INDIRECT("input_invoice[concept/supplier]"), 'P&G-Inc'!$C12 ) -> 0 | ... S12: =SUMIFS( INDIRECT("input_invoice[net]"), INDIRECT("input_invoice[yyyymm]"), 'P&G-Inc'!S$1, INDIRECT("input_invoice[concept/supplier]"), 'P&G-Inc'!$C12 ) -> 0 | T12: =SUM(H12:S12) -> 0
C13: manufacturing - frames -> Inc | F13: Frames - units sold | H13: =SUMIFS( INDIRECT("input_provisions[import]"), INDIRECT("input_provisions[yyyymm]"), 'P&G-Inc'!H$1, INDIRECT("input_provisions[concept/supplier]"), 'P&G-Inc'!$C13 )*(1/H71) -> 0 | I13: =SUMIFS( INDIRECT("input_provisions[import]"), INDIRECT("input_provisions[yyyymm]"), 'P&G-Inc'!I$1, INDIRECT("input_provisions[concept/supplier]"), 'P&G-Inc'!$C13 )*(1/I71) -> 0 | J13: =SUMIFS( INDIRECT("input_provisions[import]"), INDIRECT("input_provisions[yyyymm]"), 'P&G-Inc'!J$1, INDIRECT("input_provisions[concept/supplier]"), 'P&G-Inc'!$C13 )*(1/J71) -> 0 | K13: =SUMIFS( INDIRECT("input_provisions[import]"), INDIRECT("input_provisions[yyyymm]"), 'P&G-Inc'!K$1, INDIRECT("input_provisions[concept/supplier]"), 'P&G-Inc'!$C13 )*(1/K71) -> 0 | L13: =SUMIFS( INDIRECT("input_provisions[import]"), INDIRECT("input_provisions[yyyymm]"), 'P&G-Inc'!L$1, INDIRECT("input_provisions[concept/supplier]"), 'P&G-Inc'!$C13 )*(1/L71) -> 0 | M13: =SUMIFS( INDIRECT("input_provisions[import]"), INDIRECT("input_provisions[yyyymm]"), 'P&G-Inc'!M$1, INDIRECT("input_provisions[concept/supplier]"), 'P&G-Inc'!$C13 )*(1/M71) -> 0 | N13: =SUMIFS( INDIRECT("input_provisions[import]"), INDIRECT("input_provisions[yyyymm]"), 'P&G-Inc'!N$1, INDIRECT("input_provisions[concept/supplier]"), 'P&G-Inc'!$C13 )*(1/N71) -> 0 | O13: =SUMIFS( INDIRECT("input_provisions[import]"), INDIRECT("input_provisions[yyyymm]"), 'P&G-Inc'!O$1, INDIRECT("input_provisions[concept/supplier]"), 'P&G-Inc'!$C13 )*(1/O71) -> 0 | ... S13: =SUMIFS( INDIRECT("input_provisions[import]"), INDIRECT("input_provisions[yyyymm]"), 'P&G-Inc'!S$1, INDIRECT("input_provisions[concept/supplier]"), 'P&G-Inc'!$C13 )*(1/S71) -> 0 | T13: =SUM(H13:S13) -> 0
T14: =SUM(H14:S14) -> 0
D15: Shipping | H15: =SUM(H16:H18) -> 2888.86 | I15: =SUM(I16:I18) -> 5579.69 | J15: =SUM(J16:J18) -> 0 | K15: =SUM(K16:K18) -> 0 | L15: =SUM(L16:L18) -> 0 | M15: =SUM(M16:M18) -> 0 | N15: =SUM(N16:N18) -> 0 | O15: =SUM(O16:O18) -> 0 | ... S15: =SUM(S16:S18) -> 0 | T15: =SUM(H15:S15) -> 8468.55
C16: logistics - TGI Inc -> Inc | F16: TGI - Shipping | H16: =SUMIFS( INDIRECT("input_invoice[net]"), INDIRECT("input_invoice[yyyymm]"), 'P&G-Inc'!H$1, INDIRECT("input_invoice[concept/supplier]"), 'P&G-Inc'!$C16 ) -> 2888.86 | I16: =SUMIFS( INDIRECT("input_invoice[net]"), INDIRECT("input_invoice[yyyymm]"), 'P&G-Inc'!I$1, INDIRECT("input_invoice[concept/supplier]"), 'P&G-Inc'!$C16 ) -> 4445.62 | J16: =SUMIFS( INDIRECT("input_invoice[net]"), INDIRECT("input_invoice[yyyymm]"), 'P&G-Inc'!J$1, INDIRECT("input_invoice[concept/supplier]"), 'P&G-Inc'!$C16 ) -> 0 | K16: =SUMIFS( INDIRECT("input_invoice[net]"), INDIRECT("input_invoice[yyyymm]"), 'P&G-Inc'!K$1, INDIRECT("input_invoice[concept/supplier]"), 'P&G-Inc'!$C16 ) -> 0 | L16: =SUMIFS( INDIRECT("input_invoice[net]"), INDIRECT("input_invoice[yyyymm]"), 'P&G-Inc'!L$1, INDIRECT("input_invoice[concept/supplier]"), 'P&G-Inc'!$C16 ) -> 0 | M16: =SUMIFS( INDIRECT("input_invoice[net]"), INDIRECT("input_invoice[yyyymm]"), 'P&G-Inc'!M$1, INDIRECT("input_invoice[concept/supplier]"), 'P&G-Inc'!$C16 ) -> 0 | N16: =SUMIFS( INDIRECT("input_invoice[net]"), INDIRECT("input_invoice[yyyymm]"), 'P&G-Inc'!N$1, INDIRECT("input_invoice[concept/supplier]"), 'P&G-Inc'!$C16 ) -> 0 | O16: =SUMIFS( INDIRECT("input_invoice[net]"), INDIRECT("input_invoice[yyyymm]"), 'P&G-Inc'!O$1, INDIRECT("input_invoice[concept/supplier]"), 'P&G-Inc'!$C16 ) -> 0 | ... S16: =SUMIFS( INDIRECT("input_invoice[net]"), INDIRECT("input_invoice[yyyymm]"), 'P&G-Inc'!S$1, INDIRECT("input_invoice[concept/supplier]"), 'P&G-Inc'!$C16 ) -> 0 | T16: =SUM(H16:S16) -> 7334.48
C17: logistics - jondo -> Inc | F17: Jondo Canvas | H17: =SUMIFS( INDIRECT("input_invoice[net]"), INDIRECT("input_invoice[yyyymm]"), 'P&G-Inc'!H$1, INDIRECT("input_invoice[concept/supplier]"), 'P&G-Inc'!$C17 ) -> 0 | I17: =SUMIFS( INDIRECT("input_invoice[net]"), INDIRECT("input_invoice[yyyymm]"), 'P&G-Inc'!I$1, INDIRECT("input_invoice[concept/supplier]"), 'P&G-Inc'!$C17 ) -> 1134.07 | J17: =SUMIFS( INDIRECT("input_invoice[net]"), INDIRECT("input_invoice[yyyymm]"), 'P&G-Inc'!J$1, INDIRECT("input_invoice[concept/supplier]"), 'P&G-Inc'!$C17 ) -> 0 | K17: =SUMIFS( INDIRECT("input_invoice[net]"), INDIRECT("input_invoice[yyyymm]"), 'P&G-Inc'!K$1, INDIRECT("input_invoice[concept/supplier]"), 'P&G-Inc'!$C17 ) -> 0 | L17: =SUMIFS( INDIRECT("input_invoice[net]"), INDIRECT("input_invoice[yyyymm]"), 'P&G-Inc'!L$1, INDIRECT("input_invoice[concept/supplier]"), 'P&G-Inc'!$C17 ) -> 0 | M17: =SUMIFS( INDIRECT("input_invoice[net]"), INDIRECT("input_invoice[yyyymm]"), 'P&G-Inc'!M$1, INDIRECT("input_invoice[concept/supplier]"), 'P&G-Inc'!$C17 ) -> 0 | N17: =SUMIFS( INDIRECT("input_invoice[net]"), INDIRECT("input_invoice[yyyymm]"), 'P&G-Inc'!N$1, INDIRECT("input_invoice[concept/supplier]"), 'P&G-Inc'!$C17 ) -> 0 | O17: =SUMIFS( INDIRECT("input_invoice[net]"), INDIRECT("input_invoice[yyyymm]"), 'P&G-Inc'!O$1, INDIRECT("input_invoice[concept/supplier]"), 'P&G-Inc'!$C17 ) -> 0 | ... S17: =SUMIFS( INDIRECT("input_invoice[net]"), INDIRECT("input_invoice[yyyymm]"), 'P&G-Inc'!S$1, INDIRECT("input_invoice[concept/supplier]"), 'P&G-Inc'!$C17 ) -> 0 | T17: =SUM(H17:S17) -> 1134.07
C18: logistics - debex -> Inc | F18: Frames - Freight | H18: =SUMIFS( INDIRECT("input_invoice[net]"), INDIRECT("input_invoice[yyyymm]"), 'P&G-Inc'!H$1, INDIRECT("input_invoice[concept/supplier]"), 'P&G-Inc'!$C18 ) -> 0 | I18: =SUMIFS( INDIRECT("input_invoice[net]"), INDIRECT("input_invoice[yyyymm]"), 'P&G-Inc'!I$1, INDIRECT("input_invoice[concept/supplier]"), 'P&G-Inc'!$C18 ) -> 0 | J18: =SUMIFS( INDIRECT("input_invoice[net]"), INDIRECT("input_invoice[yyyymm]"), 'P&G-Inc'!J$1, INDIRECT("input_invoice[concept/supplier]"), 'P&G-Inc'!$C18 ) -> 0 | K18: =SUMIFS( INDIRECT("input_invoice[net]"), INDIRECT("input_invoice[yyyymm]"), 'P&G-Inc'!K$1, INDIRECT("input_invoice[concept/supplier]"), 'P&G-Inc'!$C18 ) -> 0 | L18: =SUMIFS( INDIRECT("input_invoice[net]"), INDIRECT("input_invoice[yyyymm]"), 'P&G-Inc'!L$1, INDIRECT("input_invoice[concept/supplier]"), 'P&G-Inc'!$C18 ) -> 0 | M18: =SUMIFS( INDIRECT("input_invoice[net]"), INDIRECT("input_invoice[yyyymm]"), 'P&G-Inc'!M$1, INDIRECT("input_invoice[concept/supplier]"), 'P&G-Inc'!$C18 ) -> 0 | N18: =SUMIFS( INDIRECT("input_invoice[net]"), INDIRECT("input_invoice[yyyymm]"), 'P&G-Inc'!N$1, INDIRECT("input_invoice[concept/supplier]"), 'P&G-Inc'!$C18 ) -> 0 | O18: =SUMIFS( INDIRECT("input_invoice[net]"), INDIRECT("input_invoice[yyyymm]"), 'P&G-Inc'!O$1, INDIRECT("input_invoice[concept/supplier]"), 'P&G-Inc'!$C18 ) -> 0 | ... S18: =SUMIFS( INDIRECT("input_invoice[net]"), INDIRECT("input_invoice[yyyymm]"), 'P&G-Inc'!S$1, INDIRECT("input_invoice[concept/supplier]"), 'P&G-Inc'!$C18 ) -> 0 | T18: =SUM(H18:S18) -> 0
T19: =SUM(H19:S19) -> 0
D20: Royalties | H20: =SUM(H21:H21) -> #REF! | I20: =SUM(I21:I21) -> #REF! | J20: =SUM(J21:J21) -> #REF! | K20: =SUM(K21:K21) -> #REF! | L20: =SUM(L21:L21) -> #REF! | M20: =SUM(M21:M21) -> #REF! | N20: =SUM(N21:N21) -> #REF! | O20: =SUM(O21:O21) -> #REF! | ... S20: =SUM(S21:S21) -> #REF! | T20: =SUM(H20:S20) -> #REF!
C21: royalties - Artistas -> Inc | F21: Shared services - US | H21: =SUMIFS( INDIRECT("input_roy[net]"), INDIRECT("input_roy[yyyymm]"), 'P&G-Inc'!H$1, INDIRECT("input_roy[concept/supplier]"), 'P&G-Inc'!$C21 )*(1/H71) -> #REF! | I21: =SUMIFS( INDIRECT("input_roy[net]"), INDIRECT("input_roy[yyyymm]"), 'P&G-Inc'!I$1, INDIRECT("input_roy[concept/supplier]"), 'P&G-Inc'!$C21 )*(1/I71) -> #REF! | J21: =SUMIFS( INDIRECT("input_roy[net]"), INDIRECT("input_roy[yyyymm]"), 'P&G-Inc'!J$1, INDIRECT("input_roy[concept/supplier]"), 'P&G-Inc'!$C21 )*(1/J71) -> #REF! | K21: =SUMIFS( INDIRECT("input_roy[net]"), INDIRECT("input_roy[yyyymm]"), 'P&G-Inc'!K$1, INDIRECT("input_roy[concept/supplier]"), 'P&G-Inc'!$C21 )*(1/K71) -> #REF! | L21: =SUMIFS( INDIRECT("input_roy[net]"), INDIRECT("input_roy[yyyymm]"), 'P&G-Inc'!L$1, INDIRECT("input_roy[concept/supplier]"), 'P&G-Inc'!$C21 )*(1/L71) -> #REF! | M21: =SUMIFS( INDIRECT("input_roy[net]"), INDIRECT("input_roy[yyyymm]"), 'P&G-Inc'!M$1, INDIRECT("input_roy[concept/supplier]"), 'P&G-Inc'!$C21 )*(1/M71) -> #REF! | N21: =SUMIFS( INDIRECT("input_roy[net]"), INDIRECT("input_roy[yyyymm]"), 'P&G-Inc'!N$1, INDIRECT("input_roy[concept/supplier]"), 'P&G-Inc'!$C21 )*(1/N71) -> #REF! | O21: =SUMIFS( INDIRECT("input_roy[net]"), INDIRECT("input_roy[yyyymm]"), 'P&G-Inc'!O$1, INDIRECT("input_roy[concept/supplier]"), 'P&G-Inc'!$C21 )*(1/O71) -> #REF! | ... S21: =SUMIFS( INDIRECT("input_roy[net]"), INDIRECT("input_roy[yyyymm]"), 'P&G-Inc'!S$1, INDIRECT("input_roy[concept/supplier]"), 'P&G-Inc'!$C21 )*(1/S71) -> #REF! | T21: =SUM(H21:S21) -> #REF!
D23: Payments suppliers | H23: =SUM(H24:H29) -> 0 | I23: =SUM(I24:I29) -> 0 | J23: =SUM(J24:J29) -> 0 | K23: =SUM(K24:K29) -> 0 | L23: =SUM(L24:L29) -> 0 | M23: =SUM(M24:M29) -> 0 | N23: =SUM(N24:N29) -> 0 | O23: =SUM(O24:O29) -> 0 | ... S23: =SUM(S24:S29) -> 0 | T23: =SUM(H23:S23) -> 0
C24: payment-suppliers - Shopify -> Inc | F24: Shopify | H24: =SUMIFS( INDIRECT("input_invoice[net]"), INDIRECT("input_invoice[yyyymm]"), 'P&G-Inc'!H$1, INDIRECT("input_invoice[concept/supplier]"), 'P&G-Inc'!$C24 ) -> 0 | I24: =SUMIFS( INDIRECT("input_invoice[net]"), INDIRECT("input_invoice[yyyymm]"), 'P&G-Inc'!I$1, INDIRECT("input_invoice[concept/supplier]"), 'P&G-Inc'!$C24 ) -> 0 | J24: =SUMIFS( INDIRECT("input_invoice[net]"), INDIRECT("input_invoice[yyyymm]"), 'P&G-Inc'!J$1, INDIRECT("input_invoice[concept/supplier]"), 'P&G-Inc'!$C24 ) -> 0 | K24: =SUMIFS( INDIRECT("input_invoice[net]"), INDIRECT("input_invoice[yyyymm]"), 'P&G-Inc'!K$1, INDIRECT("input_invoice[concept/supplier]"), 'P&G-Inc'!$C24 ) -> 0 | L24: =SUMIFS( INDIRECT("input_invoice[net]"), INDIRECT("input_invoice[yyyymm]"), 'P&G-Inc'!L$1, INDIRECT("input_invoice[concept/supplier]"), 'P&G-Inc'!$C24 ) -> 0 | M24: =SUMIFS( INDIRECT("input_invoice[net]"), INDIRECT("input_invoice[yyyymm]"), 'P&G-Inc'!M$1, INDIRECT("input_invoice[concept/supplier]"), 'P&G-Inc'!$C24 ) -> 0 | N24: =SUMIFS( INDIRECT("input_invoice[net]"), INDIRECT("input_invoice[yyyymm]"), 'P&G-Inc'!N$1, INDIRECT("input_invoice[concept/supplier]"), 'P&G-Inc'!$C24 ) -> 0 | O24: =SUMIFS( INDIRECT("input_invoice[net]"), INDIRECT("input_invoice[yyyymm]"), 'P&G-Inc'!O$1, INDIRECT("input_invoice[concept/supplier]"), 'P&G-Inc'!$C24 ) -> 0 | ... S24: =SUMIFS( INDIRECT("input_invoice[net]"), INDIRECT("input_invoice[yyyymm]"), 'P&G-Inc'!S$1, INDIRECT("input_invoice[concept/supplier]"), 'P&G-Inc'!$C24 ) -> 0 | T24: =SUM(H24:S24) -> 0
C25: payment-suppliers - Paypal -> Inc | F25: Paypal | H25: =SUMIFS( INDIRECT("input_invoice[net]"), INDIRECT("input_invoice[yyyymm]"), 'P&G-Inc'!H$1, INDIRECT("input_invoice[concept/supplier]"), 'P&G-Inc'!$C25 ) -> 0 | I25: =SUMIFS( INDIRECT("input_invoice[net]"), INDIRECT("input_invoice[yyyymm]"), 'P&G-Inc'!I$1, INDIRECT("input_invoice[concept/supplier]"), 'P&G-Inc'!$C25 ) -> 0 | J25: =SUMIFS( INDIRECT("input_invoice[net]"), INDIRECT("input_invoice[yyyymm]"), 'P&G-Inc'!J$1, INDIRECT("input_invoice[concept/supplier]"), 'P&G-Inc'!$C25 ) -> 0 | K25: =SUMIFS( INDIRECT("input_invoice[net]"), INDIRECT("input_invoice[yyyymm]"), 'P&G-Inc'!K$1, INDIRECT("input_invoice[concept/supplier]"), 'P&G-Inc'!$C25 ) -> 0 | L25: =SUMIFS( INDIRECT("input_invoice[net]"), INDIRECT("input_invoice[yyyymm]"), 'P&G-Inc'!L$1, INDIRECT("input_invoice[concept/supplier]"), 'P&G-Inc'!$C25 ) -> 0 | M25: =SUMIFS( INDIRECT("input_invoice[net]"), INDIRECT("input_invoice[yyyymm]"), 'P&G-Inc'!M$1, INDIRECT("input_invoice[concept/supplier]"), 'P&G-Inc'!$C25 ) -> 0 | N25: =SUMIFS( INDIRECT("input_invoice[net]"), INDIRECT("input_invoice[yyyymm]"), 'P&G-Inc'!N$1, INDIRECT("input_invoice[concept/supplier]"), 'P&G-Inc'!$C25 ) -> 0 | O25: =SUMIFS( INDIRECT("input_invoice[net]"), INDIRECT("input_invoice[yyyymm]"), 'P&G-Inc'!O$1, INDIRECT("input_invoice[concept/supplier]"), 'P&G-Inc'!$C25 ) -> 0 | ... S25: =SUMIFS( INDIRECT("input_invoice[net]"), INDIRECT("input_invoice[yyyymm]"), 'P&G-Inc'!S$1, INDIRECT("input_invoice[concept/supplier]"), 'P&G-Inc'!$C25 ) -> 0 | T25: =SUM(H25:S25) -> 0
C26: payment-suppliers - Amazon Pay -> Inc | F26: Amazon Pay | H26: =SUMIFS( INDIRECT("input_invoice[net]"), INDIRECT("input_invoice[yyyymm]"), 'P&G-Inc'!H$1, INDIRECT("input_invoice[concept/supplier]"), 'P&G-Inc'!$C26 ) -> 0 | I26: =SUMIFS( INDIRECT("input_invoice[net]"), INDIRECT("input_invoice[yyyymm]"), 'P&G-Inc'!I$1, INDIRECT("input_invoice[concept/supplier]"), 'P&G-Inc'!$C26 ) -> 0 | J26: =SUMIFS( INDIRECT("input_invoice[net]"), INDIRECT("input_invoice[yyyymm]"), 'P&G-Inc'!J$1, INDIRECT("input_invoice[concept/supplier]"), 'P&G-Inc'!$C26 ) -> 0 | K26: =SUMIFS( INDIRECT("input_invoice[net]"), INDIRECT("input_invoice[yyyymm]"), 'P&G-Inc'!K$1, INDIRECT("input_invoice[concept/supplier]"), 'P&G-Inc'!$C26 ) -> 0 | L26: =SUMIFS( INDIRECT("input_invoice[net]"), INDIRECT("input_invoice[yyyymm]"), 'P&G-Inc'!L$1, INDIRECT("input_invoice[concept/supplier]"), 'P&G-Inc'!$C26 ) -> 0 | M26: =SUMIFS( INDIRECT("input_invoice[net]"), INDIRECT("input_invoice[yyyymm]"), 'P&G-Inc'!M$1, INDIRECT("input_invoice[concept/supplier]"), 'P&G-Inc'!$C26 ) -> 0 | N26: =SUMIFS( INDIRECT("input_invoice[net]"), INDIRECT("input_invoice[yyyymm]"), 'P&G-Inc'!N$1, INDIRECT("input_invoice[concept/supplier]"), 'P&G-Inc'!$C26 ) -> 0 | O26: =SUMIFS( INDIRECT("input_invoice[net]"), INDIRECT("input_invoice[yyyymm]"), 'P&G-Inc'!O$1, INDIRECT("input_invoice[concept/supplier]"), 'P&G-Inc'!$C26 ) -> 0 | ... S26: =SUMIFS( INDIRECT("input_invoice[net]"), INDIRECT("input_invoice[yyyymm]"), 'P&G-Inc'!S$1, INDIRECT("input_invoice[concept/supplier]"), 'P&G-Inc'!$C26 ) -> 0 | T26: =SUM(H26:S26) -> 0
C27: payment-suppliers - Klarna -> Inc | F27: Klarna | H27: =SUMIFS( INDIRECT("input_invoice[net]"), INDIRECT("input_invoice[yyyymm]"), 'P&G-Inc'!H$1, INDIRECT("input_invoice[concept/supplier]"), 'P&G-Inc'!$C27 ) -> 0 | I27: =SUMIFS( INDIRECT("input_invoice[net]"), INDIRECT("input_invoice[yyyymm]"), 'P&G-Inc'!I$1, INDIRECT("input_invoice[concept/supplier]"), 'P&G-Inc'!$C27 ) -> 0 | J27: =SUMIFS( INDIRECT("input_invoice[net]"), INDIRECT("input_invoice[yyyymm]"), 'P&G-Inc'!J$1, INDIRECT("input_invoice[concept/supplier]"), 'P&G-Inc'!$C27 ) -> 0 | K27: =SUMIFS( INDIRECT("input_invoice[net]"), INDIRECT("input_invoice[yyyymm]"), 'P&G-Inc'!K$1, INDIRECT("input_invoice[concept/supplier]"), 'P&G-Inc'!$C27 ) -> 0 | L27: =SUMIFS( INDIRECT("input_invoice[net]"), INDIRECT("input_invoice[yyyymm]"), 'P&G-Inc'!L$1, INDIRECT("input_invoice[concept/supplier]"), 'P&G-Inc'!$C27 ) -> 0 | M27: =SUMIFS( INDIRECT("input_invoice[net]"), INDIRECT("input_invoice[yyyymm]"), 'P&G-Inc'!M$1, INDIRECT("input_invoice[concept/supplier]"), 'P&G-Inc'!$C27 ) -> 0 | N27: =SUMIFS( INDIRECT("input_invoice[net]"), INDIRECT("input_invoice[yyyymm]"), 'P&G-Inc'!N$1, INDIRECT("input_invoice[concept/supplier]"), 'P&G-Inc'!$C27 ) -> 0 | O27: =SUMIFS( INDIRECT("input_invoice[net]"), INDIRECT("input_invoice[yyyymm]"), 'P&G-Inc'!O$1, INDIRECT("input_invoice[concept/supplier]"), 'P&G-Inc'!$C27 ) -> 0 | ... S27: =SUMIFS( INDIRECT("input_invoice[net]"), INDIRECT("input_invoice[yyyymm]"), 'P&G-Inc'!S$1, INDIRECT("input_invoice[concept/supplier]"), 'P&G-Inc'!$C27 ) -> 0 | T27: =SUM(H27:S27) -> 0
C28: payment-suppliers - Revolut -> Inc | F28: Revolut | H28: =SUMIFS( INDIRECT("input_invoice[net]"), INDIRECT("input_invoice[yyyymm]"), 'P&G-Inc'!H$1, INDIRECT("input_invoice[concept/supplier]"), 'P&G-Inc'!$C28 ) -> 0 | I28: =SUMIFS( INDIRECT("input_invoice[net]"), INDIRECT("input_invoice[yyyymm]"), 'P&G-Inc'!I$1, INDIRECT("input_invoice[concept/supplier]"), 'P&G-Inc'!$C28 ) -> 0 | J28: =SUMIFS( INDIRECT("input_invoice[net]"), INDIRECT("input_invoice[yyyymm]"), 'P&G-Inc'!J$1, INDIRECT("input_invoice[concept/supplier]"), 'P&G-Inc'!$C28 ) -> 0 | K28: =SUMIFS( INDIRECT("input_invoice[net]"), INDIRECT("input_invoice[yyyymm]"), 'P&G-Inc'!K$1, INDIRECT("input_invoice[concept/supplier]"), 'P&G-Inc'!$C28 ) -> 0 | L28: =SUMIFS( INDIRECT("input_invoice[net]"), INDIRECT("input_invoice[yyyymm]"), 'P&G-Inc'!L$1, INDIRECT("input_invoice[concept/supplier]"), 'P&G-Inc'!$C28 ) -> 0 | M28: =SUMIFS( INDIRECT("input_invoice[net]"), INDIRECT("input_invoice[yyyymm]"), 'P&G-Inc'!M$1, INDIRECT("input_invoice[concept/supplier]"), 'P&G-Inc'!$C28 ) -> 0 | N28: =SUMIFS( INDIRECT("input_invoice[net]"), INDIRECT("input_invoice[yyyymm]"), 'P&G-Inc'!N$1, INDIRECT("input_invoice[concept/supplier]"), 'P&G-Inc'!$C28 ) -> 0 | O28: =SUMIFS( INDIRECT("input_invoice[net]"), INDIRECT("input_invoice[yyyymm]"), 'P&G-Inc'!O$1, INDIRECT("input_invoice[concept/supplier]"), 'P&G-Inc'!$C28 ) -> 0 | ... S28: =SUMIFS( INDIRECT("input_invoice[net]"), INDIRECT("input_invoice[yyyymm]"), 'P&G-Inc'!S$1, INDIRECT("input_invoice[concept/supplier]"), 'P&G-Inc'!$C28 ) -> 0 | T28: =SUM(H28:S28) -> 0
C29: payment-suppliers - Amazon Seller -> Inc | F29: Amazon Seller | H29: =SUMIFS( INDIRECT("input_invoice[net]"), INDIRECT("input_invoice[yyyymm]"), 'P&G-Inc'!H$1, INDIRECT("input_invoice[concept/supplier]"), 'P&G-Inc'!$C29 ) -> 0 | I29: =SUMIFS( INDIRECT("input_invoice[net]"), INDIRECT("input_invoice[yyyymm]"), 'P&G-Inc'!I$1, INDIRECT("input_invoice[concept/supplier]"), 'P&G-Inc'!$C29 ) -> 0 | J29: =SUMIFS( INDIRECT("input_invoice[net]"), INDIRECT("input_invoice[yyyymm]"), 'P&G-Inc'!J$1, INDIRECT("input_invoice[concept/supplier]"), 'P&G-Inc'!$C29 ) -> 0 | K29: =SUMIFS( INDIRECT("input_invoice[net]"), INDIRECT("input_invoice[yyyymm]"), 'P&G-Inc'!K$1, INDIRECT("input_invoice[concept/supplier]"), 'P&G-Inc'!$C29 ) -> 0 | L29: =SUMIFS( INDIRECT("input_invoice[net]"), INDIRECT("input_invoice[yyyymm]"), 'P&G-Inc'!L$1, INDIRECT("input_invoice[concept/supplier]"), 'P&G-Inc'!$C29 ) -> 0 | M29: =SUMIFS( INDIRECT("input_invoice[net]"), INDIRECT("input_invoice[yyyymm]"), 'P&G-Inc'!M$1, INDIRECT("input_invoice[concept/supplier]"), 'P&G-Inc'!$C29 ) -> 0 | N29: =SUMIFS( INDIRECT("input_invoice[net]"), INDIRECT("input_invoice[yyyymm]"), 'P&G-Inc'!N$1, INDIRECT("input_invoice[concept/supplier]"), 'P&G-Inc'!$C29 ) -> 0 | O29: =SUMIFS( INDIRECT("input_invoice[net]"), INDIRECT("input_invoice[yyyymm]"), 'P&G-Inc'!O$1, INDIRECT("input_invoice[concept/supplier]"), 'P&G-Inc'!$C29 ) -> 0 | ... S29: =SUMIFS( INDIRECT("input_invoice[net]"), INDIRECT("input_invoice[yyyymm]"), 'P&G-Inc'!S$1, INDIRECT("input_invoice[concept/supplier]"), 'P&G-Inc'!$C29 ) -> 0 | T29: =SUM(H29:S29) -> 0
D30: Returns - Rever | H30: =+H31 -> 0 | I30: =+I31 -> 0 | J30: =+J31 -> 0 | K30: =+K31 -> 0 | L30: =+L31 -> 0 | M30: =+M31 -> 0 | N30: =+N31 -> 0 | O30: =+O31 -> 0 | ... S30: =+S31 -> 0 | T30: =SUM(H30:S30) -> 0
C31: returns - rever -> Inc | F31: US | H31: =SUMIFS( INDIRECT("input_invoice[net]"), INDIRECT("input_invoice[yyyymm]"), 'P&G-Inc'!H$1, INDIRECT("input_invoice[concept/supplier]"), 'P&G-Inc'!$C31 ) -> 0 | I31: =SUMIFS( INDIRECT("input_invoice[net]"), INDIRECT("input_invoice[yyyymm]"), 'P&G-Inc'!I$1, INDIRECT("input_invoice[concept/supplier]"), 'P&G-Inc'!$C31 ) -> 0 | J31: =SUMIFS( INDIRECT("input_invoice[net]"), INDIRECT("input_invoice[yyyymm]"), 'P&G-Inc'!J$1, INDIRECT("input_invoice[concept/supplier]"), 'P&G-Inc'!$C31 ) -> 0 | K31: =SUMIFS( INDIRECT("input_invoice[net]"), INDIRECT("input_invoice[yyyymm]"), 'P&G-Inc'!K$1, INDIRECT("input_invoice[concept/supplier]"), 'P&G-Inc'!$C31 ) -> 0 | L31: =SUMIFS( INDIRECT("input_invoice[net]"), INDIRECT("input_invoice[yyyymm]"), 'P&G-Inc'!L$1, INDIRECT("input_invoice[concept/supplier]"), 'P&G-Inc'!$C31 ) -> 0 | M31: =SUMIFS( INDIRECT("input_invoice[net]"), INDIRECT("input_invoice[yyyymm]"), 'P&G-Inc'!M$1, INDIRECT("input_invoice[concept/supplier]"), 'P&G-Inc'!$C31 ) -> 0 | N31: =SUMIFS( INDIRECT("input_invoice[net]"), INDIRECT("input_invoice[yyyymm]"), 'P&G-Inc'!N$1, INDIRECT("input_invoice[concept/supplier]"), 'P&G-Inc'!$C31 ) -> 0 | O31: =SUMIFS( INDIRECT("input_invoice[net]"), INDIRECT("input_invoice[yyyymm]"), 'P&G-Inc'!O$1, INDIRECT("input_invoice[concept/supplier]"), 'P&G-Inc'!$C31 ) -> 0 | ... S31: =SUMIFS( INDIRECT("input_invoice[net]"), INDIRECT("input_invoice[yyyymm]"), 'P&G-Inc'!S$1, INDIRECT("input_invoice[concept/supplier]"), 'P&G-Inc'!$C31 ) -> 0 | T31: =SUM(H31:S31) -> 0
D32: Gross margin % | H32: =1-((H10)/H4) -> 0.84772813 | I32: =1-((I10)/I4) -> 0.83174031 | J32: =1-((J10)/J4) -> 1 | K32: =1-((K10)/K4) -> #DIV/0! | L32: =1-((L10)/L4) -> #DIV/0! | M32: =1-((M10)/M4) -> #DIV/0! | N32: =1-((N10)/N4) -> #DIV/0! | O32: =1-((O10)/O4) -> #DIV/0! | ... T32: =1-((T10)/T4) -> 0.88581742
D33: Gross margin | H33: =+H4-H10 -> 8699.03 | I33: =+I4-I10 -> 12932.78 | J33: =+J4-J10 -> 10787.15 | K33: =+K4-K10 -> 0 | L33: =+L4-L10 -> 0 | M33: =+M4-M10 -> 0 | N33: =+N4-N10 -> 0 | O33: =+O4-O10 -> 0 | ... S33: =+S4-S10 -> 0 | T33: =SUM(H33:S33) -> 32418.96
D34: Contributive margin % | H34: =1-((H9)/H3) -> #REF! | I34: =1-((I9)/I3) -> #REF! | J34: =1-((J9)/J3) -> #REF! | K34: =1-((K9)/K3) -> #REF! | L34: =1-((L9)/L3) -> #REF! | M34: =1-((M9)/M3) -> #REF! | N34: =1-((N9)/N3) -> #REF! | O34: =1-((O9)/O3) -> #REF! | ... S34: =1-((S9)/S3) -> #REF! | T34: =SUMIFS( INDIRECT("input_invoice[net]"), INDIRECT("input_invoice[yyyymm]"), 'P&G-Inc'!T$1, INDIRECT("input_invoice[concept/supplier]"), 'P&G-Inc'!$C77 ) -> 0
D35: Contributive margin | H35: =+H3-H9 -> #REF! | I35: =+I3-I9 -> #REF! | J35: =+J3-J9 -> #REF! | K35: =+K3-K9 -> #REF! | L35: =+L3-L9 -> #REF! | M35: =+M3-M9 -> #REF! | N35: =+N3-N9 -> #REF! | O35: =+O3-O9 -> #REF! | ... S35: =+S3-S9 -> #REF! | T35: =SUM(H35:S35) -> #REF!
D37: Fixed costs | H37: =+H38+H44+H47 -> 8236.4455 | I37: =+I38+I44+I47 -> 9352.8833 | J37: =+J38+J44+J47 -> 0 | K37: =+K38+K44+K47 -> 0 | L37: =+L38+L44+L47 -> 0 | M37: =+M38+M44+M47 -> 0 | N37: =+N38+N44+N47 -> 0 | O37: =+O38+O44+O47 -> 0 | ... S37: =+S38+S44+S47 -> 0 | T37: =SUM(H37:S37) -> 17589.329
D38: Marketing | H38: =SUM(H39:H42) -> 4020.4227 | I38: =SUM(I39:I42) -> 4941.75 | J38: =SUM(J39:J42) -> 0 | K38: =SUM(K39:K42) -> 0 | L38: =SUM(L39:L42) -> 0 | M38: =SUM(M39:M42) -> 0 | N38: =SUM(N39:N42) -> 0 | O38: =SUM(O39:O42) -> 0 | ... S38: =SUM(S39:S42) -> 0 | T38: =SUM(H38:S38) -> 8962.1727
C39: marketing - google -> Inc | F39: google | H39: =SUMIFS( INDIRECT("input_provisions[import]"), INDIRECT("input_provisions[yyyymm]"), 'P&G-Inc'!H$1, INDIRECT("input_provisions[concept/supplier]"), 'P&G-Inc'!$C39 )*(1/H71) -> 2185.701 | I39: =SUMIFS( INDIRECT("input_provisions[import]"), INDIRECT("input_provisions[yyyymm]"), 'P&G-Inc'!I$1, INDIRECT("input_provisions[concept/supplier]"), 'P&G-Inc'!$C39 )*(1/I71) -> 3486.125 | J39: =SUMIFS( INDIRECT("input_provisions[import]"), INDIRECT("input_provisions[yyyymm]"), 'P&G-Inc'!J$1, INDIRECT("input_provisions[concept/supplier]"), 'P&G-Inc'!$C39 )*(1/J71) -> 0 | K39: =SUMIFS( INDIRECT("input_provisions[import]"), INDIRECT("input_provisions[yyyymm]"), 'P&G-Inc'!K$1, INDIRECT("input_provisions[concept/supplier]"), 'P&G-Inc'!$C39 )*(1/K71) -> 0 | L39: =SUMIFS( INDIRECT("input_provisions[import]"), INDIRECT("input_provisions[yyyymm]"), 'P&G-Inc'!L$1, INDIRECT("input_provisions[concept/supplier]"), 'P&G-Inc'!$C39 )*(1/L71) -> 0 | M39: =SUMIFS( INDIRECT("input_provisions[import]"), INDIRECT("input_provisions[yyyymm]"), 'P&G-Inc'!M$1, INDIRECT("input_provisions[concept/supplier]"), 'P&G-Inc'!$C39 )*(1/M71) -> 0 | N39: =SUMIFS( INDIRECT("input_provisions[import]"), INDIRECT("input_provisions[yyyymm]"), 'P&G-Inc'!N$1, INDIRECT("input_provisions[concept/supplier]"), 'P&G-Inc'!$C39 )*(1/N71) -> 0 | O39: =SUMIFS( INDIRECT("input_provisions[import]"), INDIRECT("input_provisions[yyyymm]"), 'P&G-Inc'!O$1, INDIRECT("input_provisions[concept/supplier]"), 'P&G-Inc'!$C39 )*(1/O71) -> 0 | ... S39: =SUMIFS( INDIRECT("input_provisions[import]"), INDIRECT("input_provisions[yyyymm]"), 'P&G-Inc'!S$1, INDIRECT("input_provisions[concept/supplier]"), 'P&G-Inc'!$C39 )*(1/S71) -> 0 | T39: =SUM(H39:S39) -> 5671.826
