Workbook

Sheet P&G-SL
D1: 202601 | E1: 202602 | F1: 202603 | G1: 202604 | H1: 202605 | I1: 202606 | J1: 202607 | K1: 202608 | L1: 202609 | M1: 202610 | N1: 202611 | O1: 202612 | Q1: TOTAL
A2: P&G SL 2026 | D2: Enero | E2: Febrero | F2: Marzo | G2: Abril | H2: Mayo | I2: Junio | J2: Julio | K2: Agosto | L2: Septiembre | M2: Octubre | N2: Noviembre | O2: Diciembre | Q2: Total
A3: Actualizado: 23/03/2026 02:15 h
A4: Turnover | D4: =D5+D25 | E4: =E5+E25 | F4: =F5+F25 | G4: =G5+G25 | H4: =H5+H25 | I4: =I5+I25 | J4: =J5+J25 | K4: =K5+K25 | ... O4: =O5+O25 | Q4: =SUM(D4:O4)
A5: Product sales | B5: Product sales | D5: =D6+D16+D20+D22 | E5: =E6+E16+E20+E22 | F5: =F6+F16+F20+F22 | G5: =G6+G16+G20+G22 | H5: =H6+H16+H20+H22 | I5: =I6+I16+I20+I22 | J5: =J6+J16+J20+J22 | K5: =K6+K16+K20+K22 | ... O5: =O6+O16+O20+O22 | Q5: =SUM(D5:O5)
A6: Shopify | C6: Shopify | D6: =SUM(D7:D15) | E6: =SUM(E7:E15) | F6: =SUM(F7:F15) | G6: =SUM(G7:G15) | H6: =SUM(H7:H15) | I6: =SUM(I7:I15) | J6: =SUM(J7:J15) | K6: =SUM(K7:K15) | ... O6: =SUM(O7:O15) | P6: -> | Q6: =SUM(D6:O6)
A7: ES | C7: ES | D7: =SUMIFS('i-shopify-sl'!$E:$E,'i-shopify-sl'!$A:$A,D$1,'i-shopify-sl'!$C:$C,$C7) | E7: =SUMIFS('i-shopify-sl'!$E:$E,'i-shopify-sl'!$A:$A,E$1,'i-shopify-sl'!$C:$C,$C7) | F7: =SUMIFS('i-shopify-sl'!$E:$E,'i-shopify-sl'!$A:$A,F$1,'i-shopify-sl'!$C:$C,$C7) | G7: =SUMIFS('i-shopify-sl'!$E:$E,'i-shopify-sl'!$A:$A,G$1,'i-shopify-sl'!$C:$C,$C7) | H7: =SUMIFS('i-shopify-sl'!$E:$E,'i-shopify-sl'!$A:$A,H$1,'i-shopify-sl'!$C:$C,$C7) | I7: =SUMIFS('i-shopify-sl'!$E:$E,'i-shopify-sl'!$A:$A,I$1,'i-shopify-sl'!$C:$C,$C7) | J7: =SUMIFS('i-shopify-sl'!$E:$E,'i-shopify-sl'!$A:$A,J$1,'i-shopify-sl'!$C:$C,$C7) | K7: =SUMIFS('i-shopify-sl'!$E:$E,'i-shopify-sl'!$A:$A,K$1,'i-shopify-sl'!$C:$C,$C7) | ... O7: =SUMIFS('i-shopify-sl'!$E:$E,'i-shopify-sl'!$A:$A,O$1,'i-shopify-sl'!$C:$C,$C7) | P7: -> | Q7: =SUM(D7:O7)
A8: FR | C8: FR | D8: =SUMIFS('i-shopify-sl'!$E:$E,'i-shopify-sl'!$A:$A,D$1,'i-shopify-sl'!$C:$C,$C8) | E8: =SUMIFS('i-shopify-sl'!$E:$E,'i-shopify-sl'!$A:$A,E$1,'i-shopify-sl'!$C:$C,$C8) | F8: =SUMIFS('i-shopify-sl'!$E:$E,'i-shopify-sl'!$A:$A,F$1,'i-shopify-sl'!$C:$C,$C8) | G8: =SUMIFS('i-shopify-sl'!$E:$E,'i-shopify-sl'!$A:$A,G$1,'i-shopify-sl'!$C:$C,$C8) | H8: =SUMIFS('i-shopify-sl'!$E:$E,'i-shopify-sl'!$A:$A,H$1,'i-shopify-sl'!$C:$C,$C8) | I8: =SUMIFS('i-shopify-sl'!$E:$E,'i-shopify-sl'!$A:$A,I$1,'i-shopify-sl'!$C:$C,$C8) | J8: =SUMIFS('i-shopify-sl'!$E:$E,'i-shopify-sl'!$A:$A,J$1,'i-shopify-sl'!$C:$C,$C8) | K8: =SUMIFS('i-shopify-sl'!$E:$E,'i-shopify-sl'!$A:$A,K$1,'i-shopify-sl'!$C:$C,$C8) | ... O8: =SUMIFS('i-shopify-sl'!$E:$E,'i-shopify-sl'!$A:$A,O$1,'i-shopify-sl'!$C:$C,$C8) | P8: -> | Q8: =SUM(D8:O8)
A9: DE | C9: DE | D9: =SUMIFS('i-shopify-sl'!$E:$E,'i-shopify-sl'!$A:$A,D$1,'i-shopify-sl'!$C:$C,$C9) | E9: =SUMIFS('i-shopify-sl'!$E:$E,'i-shopify-sl'!$A:$A,E$1,'i-shopify-sl'!$C:$C,$C9) | F9: =SUMIFS('i-shopify-sl'!$E:$E,'i-shopify-sl'!$A:$A,F$1,'i-shopify-sl'!$C:$C,$C9) | G9: =SUMIFS('i-shopify-sl'!$E:$E,'i-shopify-sl'!$A:$A,G$1,'i-shopify-sl'!$C:$C,$C9) | H9: =SUMIFS('i-shopify-sl'!$E:$E,'i-shopify-sl'!$A:$A,H$1,'i-shopify-sl'!$C:$C,$C9) | I9: =SUMIFS('i-shopify-sl'!$E:$E,'i-shopify-sl'!$A:$A,I$1,'i-shopify-sl'!$C:$C,$C9) | J9: =SUMIFS('i-shopify-sl'!$E:$E,'i-shopify-sl'!$A:$A,J$1,'i-shopify-sl'!$C:$C,$C9) | K9: =SUMIFS('i-shopify-sl'!$E:$E,'i-shopify-sl'!$A:$A,K$1,'i-shopify-sl'!$C:$C,$C9) | ... O9: =SUMIFS('i-shopify-sl'!$E:$E,'i-shopify-sl'!$A:$A,O$1,'i-shopify-sl'!$C:$C,$C9) | P9: -> | Q9: =SUM(D9:O9)
A10: IT | C10: IT | D10: =SUMIFS('i-shopify-sl'!$E:$E,'i-shopify-sl'!$A:$A,D$1,'i-shopify-sl'!$C:$C,$C10) | E10: =SUMIFS('i-shopify-sl'!$E:$E,'i-shopify-sl'!$A:$A,E$1,'i-shopify-sl'!$C:$C,$C10) | F10: =SUMIFS('i-shopify-sl'!$E:$E,'i-shopify-sl'!$A:$A,F$1,'i-shopify-sl'!$C:$C,$C10) | G10: =SUMIFS('i-shopify-sl'!$E:$E,'i-shopify-sl'!$A:$A,G$1,'i-shopify-sl'!$C:$C,$C10) | H10: =SUMIFS('i-shopify-sl'!$E:$E,'i-shopify-sl'!$A:$A,H$1,'i-shopify-sl'!$C:$C,$C10) | I10: =SUMIFS('i-shopify-sl'!$E:$E,'i-shopify-sl'!$A:$A,I$1,'i-shopify-sl'!$C:$C,$C10) | J10: =SUMIFS('i-shopify-sl'!$E:$E,'i-shopify-sl'!$A:$A,J$1,'i-shopify-sl'!$C:$C,$C10) | K10: =SUMIFS('i-shopify-sl'!$E:$E,'i-shopify-sl'!$A:$A,K$1,'i-shopify-sl'!$C:$C,$C10) | ... O10: =SUMIFS('i-shopify-sl'!$E:$E,'i-shopify-sl'!$A:$A,O$1,'i-shopify-sl'!$C:$C,$C10) | P10: -> | Q10: =SUM(D10:O10)
A11: AT | C11: AT | D11: =SUMIFS('i-shopify-sl'!$E:$E,'i-shopify-sl'!$A:$A,D$1,'i-shopify-sl'!$C:$C,$C11) | E11: =SUMIFS('i-shopify-sl'!$E:$E,'i-shopify-sl'!$A:$A,E$1,'i-shopify-sl'!$C:$C,$C11) | F11: =SUMIFS('i-shopify-sl'!$E:$E,'i-shopify-sl'!$A:$A,F$1,'i-shopify-sl'!$C:$C,$C11) | G11: =SUMIFS('i-shopify-sl'!$E:$E,'i-shopify-sl'!$A:$A,G$1,'i-shopify-sl'!$C:$C,$C11) | H11: =SUMIFS('i-shopify-sl'!$E:$E,'i-shopify-sl'!$A:$A,H$1,'i-shopify-sl'!$C:$C,$C11) | I11: =SUMIFS('i-shopify-sl'!$E:$E,'i-shopify-sl'!$A:$A,I$1,'i-shopify-sl'!$C:$C,$C11) | J11: =SUMIFS('i-shopify-sl'!$E:$E,'i-shopify-sl'!$A:$A,J$1,'i-shopify-sl'!$C:$C,$C11) | K11: =SUMIFS('i-shopify-sl'!$E:$E,'i-shopify-sl'!$A:$A,K$1,'i-shopify-sl'!$C:$C,$C11) | ... O11: =SUMIFS('i-shopify-sl'!$E:$E,'i-shopify-sl'!$A:$A,O$1,'i-shopify-sl'!$C:$C,$C11) | P11: -> | Q11: =SUM(D11:O11)
A12: BE | C12: BE | D12: =SUMIFS('i-shopify-sl'!$E:$E,'i-shopify-sl'!$A:$A,D$1,'i-shopify-sl'!$C:$C,$C12) | E12: =SUMIFS('i-shopify-sl'!$E:$E,'i-shopify-sl'!$A:$A,E$1,'i-shopify-sl'!$C:$C,$C12) | F12: =SUMIFS('i-shopify-sl'!$E:$E,'i-shopify-sl'!$A:$A,F$1,'i-shopify-sl'!$C:$C,$C12) | G12: =SUMIFS('i-shopify-sl'!$E:$E,'i-shopify-sl'!$A:$A,G$1,'i-shopify-sl'!$C:$C,$C12) | H12: =SUMIFS('i-shopify-sl'!$E:$E,'i-shopify-sl'!$A:$A,H$1,'i-shopify-sl'!$C:$C,$C12) | I12: =SUMIFS('i-shopify-sl'!$E:$E,'i-shopify-sl'!$A:$A,I$1,'i-shopify-sl'!$C:$C,$C12) | J12: =SUMIFS('i-shopify-sl'!$E:$E,'i-shopify-sl'!$A:$A,J$1,'i-shopify-sl'!$C:$C,$C12) | K12: =SUMIFS('i-shopify-sl'!$E:$E,'i-shopify-sl'!$A:$A,K$1,'i-shopify-sl'!$C:$C,$C12) | ... O12: =SUMIFS('i-shopify-sl'!$E:$E,'i-shopify-sl'!$A:$A,O$1,'i-shopify-sl'!$C:$C,$C12) | P12: -> | Q12: =SUM(D12:O12)
A13: NL | C13: NL | D13: =SUMIFS('i-shopify-sl'!$E:$E,'i-shopify-sl'!$A:$A,D$1,'i-shopify-sl'!$C:$C,$C13) | E13: =SUMIFS('i-shopify-sl'!$E:$E,'i-shopify-sl'!$A:$A,E$1,'i-shopify-sl'!$C:$C,$C13) | F13: =SUMIFS('i-shopify-sl'!$E:$E,'i-shopify-sl'!$A:$A,F$1,'i-shopify-sl'!$C:$C,$C13) | G13: =SUMIFS('i-shopify-sl'!$E:$E,'i-shopify-sl'!$A:$A,G$1,'i-shopify-sl'!$C:$C,$C13) | H13: =SUMIFS('i-shopify-sl'!$E:$E,'i-shopify-sl'!$A:$A,H$1,'i-shopify-sl'!$C:$C,$C13) | I13: =SUMIFS('i-shopify-sl'!$E:$E,'i-shopify-sl'!$A:$A,I$1,'i-shopify-sl'!$C:$C,$C13) | J13: =SUMIFS('i-shopify-sl'!$E:$E,'i-shopify-sl'!$A:$A,J$1,'i-shopify-sl'!$C:$C,$C13) | K13: =SUMIFS('i-shopify-sl'!$E:$E,'i-shopify-sl'!$A:$A,K$1,'i-shopify-sl'!$C:$C,$C13) | ... O13: =SUMIFS('i-shopify-sl'!$E:$E,'i-shopify-sl'!$A:$A,O$1,'i-shopify-sl'!$C:$C,$C13) | P13: -> | Q13: =SUM(D13:O13)
A14: PT | C14: PT | D14: =SUMIFS('i-shopify-sl'!$E:$E,'i-shopify-sl'!$A:$A,D$1,'i-shopify-sl'!$C:$C,$C14) | E14: =SUMIFS('i-shopify-sl'!$E:$E,'i-shopify-sl'!$A:$A,E$1,'i-shopify-sl'!$C:$C,$C14) | F14: =SUMIFS('i-shopify-sl'!$E:$E,'i-shopify-sl'!$A:$A,F$1,'i-shopify-sl'!$C:$C,$C14) | G14: =SUMIFS('i-shopify-sl'!$E:$E,'i-shopify-sl'!$A:$A,G$1,'i-shopify-sl'!$C:$C,$C14) | H14: =SUMIFS('i-shopify-sl'!$E:$E,'i-shopify-sl'!$A:$A,H$1,'i-shopify-sl'!$C:$C,$C14) | I14: =SUMIFS('i-shopify-sl'!$E:$E,'i-shopify-sl'!$A:$A,I$1,'i-shopify-sl'!$C:$C,$C14) | J14: =SUMIFS('i-shopify-sl'!$E:$E,'i-shopify-sl'!$A:$A,J$1,'i-shopify-sl'!$C:$C,$C14) | K14: =SUMIFS('i-shopify-sl'!$E:$E,'i-shopify-sl'!$A:$A,K$1,'i-shopify-sl'!$C:$C,$C14) | ... O14: =SUMIFS('i-shopify-sl'!$E:$E,'i-shopify-sl'!$A:$A,O$1,'i-shopify-sl'!$C:$C,$C14) | P14: -> | Q14: =SUM(D14:O14)
A15: XX | C15: XX | D15: =SUMIFS('i-shopify-sl'!$E:$E,'i-shopify-sl'!$A:$A,D$1,'i-shopify-sl'!$C:$C,$C15) | E15: =SUMIFS('i-shopify-sl'!$E:$E,'i-shopify-sl'!$A:$A,E$1,'i-shopify-sl'!$C:$C,$C15) | F15: =SUMIFS('i-shopify-sl'!$E:$E,'i-shopify-sl'!$A:$A,F$1,'i-shopify-sl'!$C:$C,$C15) | G15: =SUMIFS('i-shopify-sl'!$E:$E,'i-shopify-sl'!$A:$A,G$1,'i-shopify-sl'!$C:$C,$C15) | H15: =SUMIFS('i-shopify-sl'!$E:$E,'i-shopify-sl'!$A:$A,H$1,'i-shopify-sl'!$C:$C,$C15) | I15: =SUMIFS('i-shopify-sl'!$E:$E,'i-shopify-sl'!$A:$A,I$1,'i-shopify-sl'!$C:$C,$C15) | J15: =SUMIFS('i-shopify-sl'!$E:$E,'i-shopify-sl'!$A:$A,J$1,'i-shopify-sl'!$C:$C,$C15) | K15: =SUMIFS('i-shopify-sl'!$E:$E,'i-shopify-sl'!$A:$A,K$1,'i-shopify-sl'!$C:$C,$C15) | ... O15: =SUMIFS('i-shopify-sl'!$E:$E,'i-shopify-sl'!$A:$A,O$1,'i-shopify-sl'!$C:$C,$C15) | P15: -> | Q15: =SUM(D15:O15)
A16: Marketplaces | C16: Marketplaces | D16: =SUM(D17:D19) | E16: =SUM(E17:E19) | F16: =SUM(F17:F19) | G16: =SUM(G17:G19) | H16: =SUM(H17:H19) | I16: =SUM(I17:I19) | J16: =SUM(J17:J19) | K16: =SUM(K17:K19) | ... O16: =SUM(O17:O19) | P16: -> | Q16: =SUM(D16:O16)
A17: HANNUN | C17: HANNUN | D17: =SUMIFS('i-marketplaces-sl'!$E:$E,'i-marketplaces-sl'!$A:$A,D$1,'i-marketplaces-sl'!$C:$C,$C17) | E17: =SUMIFS('i-marketplaces-sl'!$E:$E,'i-marketplaces-sl'!$A:$A,E$1,'i-marketplaces-sl'!$C:$C,$C17) | F17: =SUMIFS('i-marketplaces-sl'!$E:$E,'i-marketplaces-sl'!$A:$A,F$1,'i-marketplaces-sl'!$C:$C,$C17) | G17: =SUMIFS('i-marketplaces-sl'!$E:$E,'i-marketplaces-sl'!$A:$A,G$1,'i-marketplaces-sl'!$C:$C,$C17) | H17: =SUMIFS('i-marketplaces-sl'!$E:$E,'i-marketplaces-sl'!$A:$A,H$1,'i-marketplaces-sl'!$C:$C,$C17) | I17: =SUMIFS('i-marketplaces-sl'!$E:$E,'i-marketplaces-sl'!$A:$A,I$1,'i-marketplaces-sl'!$C:$C,$C17) | J17: =SUMIFS('i-marketplaces-sl'!$E:$E,'i-marketplaces-sl'!$A:$A,J$1,'i-marketplaces-sl'!$C:$C,$C17) | K17: =SUMIFS('i-marketplaces-sl'!$E:$E,'i-marketplaces-sl'!$A:$A,K$1,'i-marketplaces-sl'!$C:$C,$C17) | ... O17: =SUMIFS('i-marketplaces-sl'!$E:$E,'i-marketplaces-sl'!$A:$A,O$1,'i-marketplaces-sl'!$C:$C,$C17) | P17: -> | Q17: =SUM(D17:O17)
A18: TOASTY | C18: TOASTY | D18: =SUMIFS('i-marketplaces-sl'!$E:$E,'i-marketplaces-sl'!$A:$A,D$1,'i-marketplaces-sl'!$C:$C,$C18) | E18: =SUMIFS('i-marketplaces-sl'!$E:$E,'i-marketplaces-sl'!$A:$A,E$1,'i-marketplaces-sl'!$C:$C,$C18) | F18: =SUMIFS('i-marketplaces-sl'!$E:$E,'i-marketplaces-sl'!$A:$A,F$1,'i-marketplaces-sl'!$C:$C,$C18) | G18: =SUMIFS('i-marketplaces-sl'!$E:$E,'i-marketplaces-sl'!$A:$A,G$1,'i-marketplaces-sl'!$C:$C,$C18) | H18: =SUMIFS('i-marketplaces-sl'!$E:$E,'i-marketplaces-sl'!$A:$A,H$1,'i-marketplaces-sl'!$C:$C,$C18) | I18: =SUMIFS('i-marketplaces-sl'!$E:$E,'i-marketplaces-sl'!$A:$A,I$1,'i-marketplaces-sl'!$C:$C,$C18) | J18: =SUMIFS('i-marketplaces-sl'!$E:$E,'i-marketplaces-sl'!$A:$A,J$1,'i-marketplaces-sl'!$C:$C,$C18) | K18: =SUMIFS('i-marketplaces-sl'!$E:$E,'i-marketplaces-sl'!$A:$A,K$1,'i-marketplaces-sl'!$C:$C,$C18) | ... O18: =SUMIFS('i-marketplaces-sl'!$E:$E,'i-marketplaces-sl'!$A:$A,O$1,'i-marketplaces-sl'!$C:$C,$C18) | P18: -> | Q18: =SUM(D18:O18)
A19: CHOOSE | C19: CHOOSE | D19: =SUMIFS('i-marketplaces-sl'!$E:$E,'i-marketplaces-sl'!$A:$A,D$1,'i-marketplaces-sl'!$C:$C,$C19) | E19: =SUMIFS('i-marketplaces-sl'!$E:$E,'i-marketplaces-sl'!$A:$A,E$1,'i-marketplaces-sl'!$C:$C,$C19) | F19: =SUMIFS('i-marketplaces-sl'!$E:$E,'i-marketplaces-sl'!$A:$A,F$1,'i-marketplaces-sl'!$C:$C,$C19) | G19: =SUMIFS('i-marketplaces-sl'!$E:$E,'i-marketplaces-sl'!$A:$A,G$1,'i-marketplaces-sl'!$C:$C,$C19) | H19: =SUMIFS('i-marketplaces-sl'!$E:$E,'i-marketplaces-sl'!$A:$A,H$1,'i-marketplaces-sl'!$C:$C,$C19) | I19: =SUMIFS('i-marketplaces-sl'!$E:$E,'i-marketplaces-sl'!$A:$A,I$1,'i-marketplaces-sl'!$C:$C,$C19) | J19: =SUMIFS('i-marketplaces-sl'!$E:$E,'i-marketplaces-sl'!$A:$A,J$1,'i-marketplaces-sl'!$C:$C,$C19) | K19: =SUMIFS('i-marketplaces-sl'!$E:$E,'i-marketplaces-sl'!$A:$A,K$1,'i-marketplaces-sl'!$C:$C,$C19) | ... O19: =SUMIFS('i-marketplaces-sl'!$E:$E,'i-marketplaces-sl'!$A:$A,O$1,'i-marketplaces-sl'!$C:$C,$C19) | P19: -> | Q19: =SUM(D19:O19)
A20: Rappels | C20: Rappels | D20: =D21 | E20: =E21 | F20: =F21 | G20: =G21 | H20: =H21 | I20: =I21 | J20: =J21 | K20: =K21 | ... O20: =O21 | P20: -> | Q20: =SUM(D20:O20)
A21: LIVITUM | C21: LIVITUM | D21: =SUMIFS('i-rappels-sl'!$E:$E,'i-rappels-sl'!$A:$A,D$1,'i-rappels-sl'!$C:$C,$C21) | E21: =SUMIFS('i-rappels-sl'!$E:$E,'i-rappels-sl'!$A:$A,E$1,'i-rappels-sl'!$C:$C,$C21) | F21: =SUMIFS('i-rappels-sl'!$E:$E,'i-rappels-sl'!$A:$A,F$1,'i-rappels-sl'!$C:$C,$C21) | G21: =SUMIFS('i-rappels-sl'!$E:$E,'i-rappels-sl'!$A:$A,G$1,'i-rappels-sl'!$C:$C,$C21) | H21: =SUMIFS('i-rappels-sl'!$E:$E,'i-rappels-sl'!$A:$A,H$1,'i-rappels-sl'!$C:$C,$C21) | I21: =SUMIFS('i-rappels-sl'!$E:$E,'i-rappels-sl'!$A:$A,I$1,'i-rappels-sl'!$C:$C,$C21) | J21: =SUMIFS('i-rappels-sl'!$E:$E,'i-rappels-sl'!$A:$A,J$1,'i-rappels-sl'!$C:$C,$C21) | K21: =SUMIFS('i-rappels-sl'!$E:$E,'i-rappels-sl'!$A:$A,K$1,'i-rappels-sl'!$C:$C,$C21) | ... O21: =SUMIFS('i-rappels-sl'!$E:$E,'i-rappels-sl'!$A:$A,O$1,'i-rappels-sl'!$C:$C,$C21) | P21: -> | Q21: =SUM(D21:O21)
A22: Supplies | C22: Supplies | D22: =D23 | E22: =E23 | F22: =F23 | G22: =G23 | H22: =H23 | I22: =I23 | J22: =J23 | K22: =K23 | ... O22: =O23 | P22: -> | Q22: =SUM(D22:O22)
A23: REVER | C23: REVER | D23: =SUMIFS('i-supplies-sl'!$E:$E,'i-supplies-sl'!$A:$A,D$1,'i-supplies-sl'!$C:$C,$C23) | E23: =SUMIFS('i-supplies-sl'!$E:$E,'i-supplies-sl'!$A:$A,E$1,'i-supplies-sl'!$C:$C,$C23) | F23: =SUMIFS('i-supplies-sl'!$E:$E,'i-supplies-sl'!$A:$A,F$1,'i-supplies-sl'!$C:$C,$C23) | G23: =SUMIFS('i-supplies-sl'!$E:$E,'i-supplies-sl'!$A:$A,G$1,'i-supplies-sl'!$C:$C,$C23) | H23: =SUMIFS('i-supplies-sl'!$E:$E,'i-supplies-sl'!$A:$A,H$1,'i-supplies-sl'!$C:$C,$C23) | I23: =SUMIFS('i-supplies-sl'!$E:$E,'i-supplies-sl'!$A:$A,I$1,'i-supplies-sl'!$C:$C,$C23) | J23: =SUMIFS('i-supplies-sl'!$E:$E,'i-supplies-sl'!$A:$A,J$1,'i-supplies-sl'!$C:$C,$C23) | K23: =SUMIFS('i-supplies-sl'!$E:$E,'i-supplies-sl'!$A:$A,K$1,'i-supplies-sl'!$C:$C,$C23) | ... O23: =SUMIFS('i-supplies-sl'!$E:$E,'i-supplies-sl'!$A:$A,O$1,'i-supplies-sl'!$C:$C,$C23) | P23: -> | Q23: =SUM(D23:O23)
Q24: =SUM(D24:O24)
A25: Services | B25: Services | D25: =SUM(D26:D29) | E25: =SUM(E26:E29) | F25: =SUM(F26:F29) | G25: =SUM(G26:G29) | H25: =SUM(H26:H29) | I25: =SUM(I26:I29) | J25: =SUM(J26:J29) | K25: =SUM(K26:K29) | ... O25: =SUM(O26:O29) | P25: -> | Q25: =SUM(D25:O25)
A26: HANNUN | C26: HANNUN | D26: =SUMIFS('i-services-sl'!$E:$E,'i-services-sl'!$A:$A,D$1,'i-services-sl'!$C:$C,$C26) | E26: =SUMIFS('i-services-sl'!$E:$E,'i-services-sl'!$A:$A,E$1,'i-services-sl'!$C:$C,$C26) | F26: =SUMIFS('i-services-sl'!$E:$E,'i-services-sl'!$A:$A,F$1,'i-services-sl'!$C:$C,$C26) | G26: =SUMIFS('i-services-sl'!$E:$E,'i-services-sl'!$A:$A,G$1,'i-services-sl'!$C:$C,$C26) | H26: =SUMIFS('i-services-sl'!$E:$E,'i-services-sl'!$A:$A,H$1,'i-services-sl'!$C:$C,$C26) | I26: =SUMIFS('i-services-sl'!$E:$E,'i-services-sl'!$A:$A,I$1,'i-services-sl'!$C:$C,$C26) | J26: =SUMIFS('i-services-sl'!$E:$E,'i-services-sl'!$A:$A,J$1,'i-services-sl'!$C:$C,$C26) | K26: =SUMIFS('i-services-sl'!$E:$E,'i-services-sl'!$A:$A,K$1,'i-services-sl'!$C:$C,$C26) | ... O26: =SUMIFS('i-services-sl'!$E:$E,'i-services-sl'!$A:$A,O$1,'i-services-sl'!$C:$C,$C26) | P26: -> | Q26: =SUM(D26:O26)
A27: QHANDS | C27: QHANDS | D27: =SUMIFS('i-services-sl'!$E:$E,'i-services-sl'!$A:$A,D$1,'i-services-sl'!$C:$C,$C27) | E27: =SUMIFS('i-services-sl'!$E:$E,'i-services-sl'!$A:$A,E$1,'i-services-sl'!$C:$C,$C27) | F27: =SUMIFS('i-services-sl'!$E:$E,'i-services-sl'!$A:$A,F$1,'i-services-sl'!$C:$C,$C27) | G27: =SUMIFS('i-services-sl'!$E:$E,'i-services-sl'!$A:$A,G$1,'i-services-sl'!$C:$C,$C27) | H27: =SUMIFS('i-services-sl'!$E:$E,'i-services-sl'!$A:$A,H$1,'i-services-sl'!$C:$C,$C27) | I27: =SUMIFS('i-services-sl'!$E:$E,'i-services-sl'!$A:$A,I$1,'i-services-sl'!$C:$C,$C27) | J27: =SUMIFS('i-services-sl'!$E:$E,'i-services-sl'!$A:$A,J$1,'i-services-sl'!$C:$C,$C27) | K27: =SUMIFS('i-services-sl'!$E:$E,'i-services-sl'!$A:$A,K$1,'i-services-sl'!$C:$C,$C27) | ... O27: =SUMIFS('i-services-sl'!$E:$E,'i-services-sl'!$A:$A,O$1,'i-services-sl'!$C:$C,$C27) | P27: -> | Q27: =SUM(D27:O27)
A28: Ltd | C28: Ltd | D28: =SUMIFS('i-services-sl'!$E:$E,'i-services-sl'!$A:$A,D$1,'i-services-sl'!$C:$C,$C28) | E28: =SUMIFS('i-services-sl'!$E:$E,'i-services-sl'!$A:$A,E$1,'i-services-sl'!$C:$C,$C28) | F28: =SUMIFS('i-services-sl'!$E:$E,'i-services-sl'!$A:$A,F$1,'i-services-sl'!$C:$C,$C28) | G28: =SUMIFS('i-services-sl'!$E:$E,'i-services-sl'!$A:$A,G$1,'i-services-sl'!$C:$C,$C28) | H28: =SUMIFS('i-services-sl'!$E:$E,'i-services-sl'!$A:$A,H$1,'i-services-sl'!$C:$C,$C28) | I28: =SUMIFS('i-services-sl'!$E:$E,'i-services-sl'!$A:$A,I$1,'i-services-sl'!$C:$C,$C28) | J28: =SUMIFS('i-services-sl'!$E:$E,'i-services-sl'!$A:$A,J$1,'i-services-sl'!$C:$C,$C28) | K28: =SUMIFS('i-services-sl'!$E:$E,'i-services-sl'!$A:$A,K$1,'i-services-sl'!$C:$C,$C28) | ... O28: =SUMIFS('i-services-sl'!$E:$E,'i-services-sl'!$A:$A,O$1,'i-services-sl'!$C:$C,$C28) | P28: -> | Q28: =SUM(D28:O28)
A29: Inc | C29: Inc | D29: =SUMIFS('i-services-sl'!$E:$E,'i-services-sl'!$A:$A,D$1,'i-services-sl'!$C:$C,$C29) | E29: =SUMIFS('i-services-sl'!$E:$E,'i-services-sl'!$A:$A,E$1,'i-services-sl'!$C:$C,$C29) | F29: =SUMIFS('i-services-sl'!$E:$E,'i-services-sl'!$A:$A,F$1,'i-services-sl'!$C:$C,$C29) | G29: =SUMIFS('i-services-sl'!$E:$E,'i-services-sl'!$A:$A,G$1,'i-services-sl'!$C:$C,$C29) | H29: =SUMIFS('i-services-sl'!$E:$E,'i-services-sl'!$A:$A,H$1,'i-services-sl'!$C:$C,$C29) | I29: =SUMIFS('i-services-sl'!$E:$E,'i-services-sl'!$A:$A,I$1,'i-services-sl'!$C:$C,$C29) | J29: =SUMIFS('i-services-sl'!$E:$E,'i-services-sl'!$A:$A,J$1,'i-services-sl'!$C:$C,$C29) | K29: =SUMIFS('i-services-sl'!$E:$E,'i-services-sl'!$A:$A,K$1,'i-services-sl'!$C:$C,$C29) | ... O29: =SUMIFS('i-services-sl'!$E:$E,'i-services-sl'!$A:$A,O$1,'i-services-sl'!$C:$C,$C29) | P29: -> | Q29: =SUM(D29:O29)
Q30: =SUM(D30:O30)
A31: Expenses | D31: =D32+D60 | E31: =E32+E60 | F31: =F32+F60 | G31: =G32+G60 | H31: =H32+H60 | I31: =I32+I60 | J31: =J32+J60 | K31: =K32+K60 | ... O31: =O32+O60 | Q31: =SUM(D31:O31)
A32: COGS | B32: COGS | D32: =D33+D40+D47+D50 | E32: =E33+E40+E47+E50 | F32: =F33+F40+F47+F50 | G32: =G33+G40+G47+G50 | H32: =H33+H40+H47+H50 | I32: =I33+I40+I47+I50 | J32: =J33+J40+J47+J50 | K32: =K33+K40+K47+K50 | ... O32: =O33+O40+O47+O50 | Q32: =SUM(D32:O32)
A33: Manufacturing (% sales) | C33: Manufacturing (% sales) | D33: =SUM(D34:D38) | E33: =SUM(E34:E38) | F33: =SUM(F34:F38) | G33: =SUM(G34:G38) | H33: =SUM(H34:H38) | I33: =SUM(I34:I38) | J33: =SUM(J34:J38) | K33: =SUM(K34:K38) | ... O33: =SUM(O34:O38) | P33: -> | Q33: =SUM(D33:O33)
A34: APPHOTOCAN | C34: APPHOTOCAN | D34: =SUMIFS('g-expenses-sl'!$F:$F,'g-expenses-sl'!$A:$A,D$1,'g-expenses-sl'!$D:$D,"manufacturing",'g-expenses-sl'!$E:$E,$C34) | E34: =SUMIFS('g-expenses-sl'!$F:$F,'g-expenses-sl'!$A:$A,E$1,'g-expenses-sl'!$D:$D,"manufacturing",'g-expenses-sl'!$E:$E,$C34) | F34: =SUMIFS('g-expenses-sl'!$F:$F,'g-expenses-sl'!$A:$A,F$1,'g-expenses-sl'!$D:$D,"manufacturing",'g-expenses-sl'!$E:$E,$C34) | G34: =SUMIFS('g-expenses-sl'!$F:$F,'g-expenses-sl'!$A:$A,G$1,'g-expenses-sl'!$D:$D,"manufacturing",'g-expenses-sl'!$E:$E,$C34) | H34: =SUMIFS('g-expenses-sl'!$F:$F,'g-expenses-sl'!$A:$A,H$1,'g-expenses-sl'!$D:$D,"manufacturing",'g-expenses-sl'!$E:$E,$C34) | I34: =SUMIFS('g-expenses-sl'!$F:$F,'g-expenses-sl'!$A:$A,I$1,'g-expenses-sl'!$D:$D,"manufacturing",'g-expenses-sl'!$E:$E,$C34) | J34: =SUMIFS('g-expenses-sl'!$F:$F,'g-expenses-sl'!$A:$A,J$1,'g-expenses-sl'!$D:$D,"manufacturing",'g-expenses-sl'!$E:$E,$C34) | K34: =SUMIFS('g-expenses-sl'!$F:$F,'g-expenses-sl'!$A:$A,K$1,'g-expenses-sl'!$D:$D,"manufacturing",'g-expenses-sl'!$E:$E,$C34) | ... O34: =SUMIFS('g-expenses-sl'!$F:$F,'g-expenses-sl'!$A:$A,O$1,'g-expenses-sl'!$D:$D,"manufacturing",'g-expenses-sl'!$E:$E,$C34) | P34: -> | Q34: =SUM(D34:O34)
A35: APPHOTOES | C35: APPHOTOES | D35: =SUMIFS('g-expenses-sl'!$F:$F,'g-expenses-sl'!$A:$A,D$1,'g-expenses-sl'!$D:$D,"manufacturing",'g-expenses-sl'!$E:$E,$C35) | E35: =SUMIFS('g-expenses-sl'!$F:$F,'g-expenses-sl'!$A:$A,E$1,'g-expenses-sl'!$D:$D,"manufacturing",'g-expenses-sl'!$E:$E,$C35) | F35: =SUMIFS('g-expenses-sl'!$F:$F,'g-expenses-sl'!$A:$A,F$1,'g-expenses-sl'!$D:$D,"manufacturing",'g-expenses-sl'!$E:$E,$C35) | G35: =SUMIFS('g-expenses-sl'!$F:$F,'g-expenses-sl'!$A:$A,G$1,'g-expenses-sl'!$D:$D,"manufacturing",'g-expenses-sl'!$E:$E,$C35) | H35: =SUMIFS('g-expenses-sl'!$F:$F,'g-expenses-sl'!$A:$A,H$1,'g-expenses-sl'!$D:$D,"manufacturing",'g-expenses-sl'!$E:$E,$C35) | I35: =SUMIFS('g-expenses-sl'!$F:$F,'g-expenses-sl'!$A:$A,I$1,'g-expenses-sl'!$D:$D,"manufacturing",'g-expenses-sl'!$E:$E,$C35) | J35: =SUMIFS('g-expenses-sl'!$F:$F,'g-expenses-sl'!$A:$A,J$1,'g-expenses-sl'!$D:$D,"manufacturing",'g-expenses-sl'!$E:$E,$C35) | K35: =SUMIFS('g-expenses-sl'!$F:$F,'g-expenses-sl'!$A:$A,K$1,'g-expenses-sl'!$D:$D,"manufacturing",'g-expenses-sl'!$E:$E,$C35) | ... O35: =SUMIFS('g-expenses-sl'!$F:$F,'g-expenses-sl'!$A:$A,O$1,'g-expenses-sl'!$D:$D,"manufacturing",'g-expenses-sl'!$E:$E,$C35) | P35: -> | Q35: =SUM(D35:O35)
A36: ARTLINK | C36: ARTLINK | D36: =SUMIFS('g-expenses-sl'!$F:$F,'g-expenses-sl'!$A:$A,D$1,'g-expenses-sl'!$D:$D,"manufacturing",'g-expenses-sl'!$E:$E,$C36) | E36: =SUMIFS('g-expenses-sl'!$F:$F,'g-expenses-sl'!$A:$A,E$1,'g-expenses-sl'!$D:$D,"manufacturing",'g-expenses-sl'!$E:$E,$C36) | F36: =SUMIFS('g-expenses-sl'!$F:$F,'g-expenses-sl'!$A:$A,F$1,'g-expenses-sl'!$D:$D,"manufacturing",'g-expenses-sl'!$E:$E,$C36) | G36: =SUMIFS('g-expenses-sl'!$F:$F,'g-expenses-sl'!$A:$A,G$1,'g-expenses-sl'!$D:$D,"manufacturing",'g-expenses-sl'!$E:$E,$C36) | H36: =SUMIFS('g-expenses-sl'!$F:$F,'g-expenses-sl'!$A:$A,H$1,'g-expenses-sl'!$D:$D,"manufacturing",'g-expenses-sl'!$E:$E,$C36) | I36: =SUMIFS('g-expenses-sl'!$F:$F,'g-expenses-sl'!$A:$A,I$1,'g-expenses-sl'!$D:$D,"manufacturing",'g-expenses-sl'!$E:$E,$C36) | J36: =SUMIFS('g-expenses-sl'!$F:$F,'g-expenses-sl'!$A:$A,J$1,'g-expenses-sl'!$D:$D,"manufacturing",'g-expenses-sl'!$E:$E,$C36) | K36: =SUMIFS('g-expenses-sl'!$F:$F,'g-expenses-sl'!$A:$A,K$1,'g-expenses-sl'!$D:$D,"manufacturing",'g-expenses-sl'!$E:$E,$C36) | ... O36: =SUMIFS('g-expenses-sl'!$F:$F,'g-expenses-sl'!$A:$A,O$1,'g-expenses-sl'!$D:$D,"manufacturing",'g-expenses-sl'!$E:$E,$C36) | P36: -> | Q36: =SUM(D36:O36)
A37: DCT | C37: DCT | D37: =SUMIFS('g-expenses-sl'!$F:$F,'g-expenses-sl'!$A:$A,D$1,'g-expenses-sl'!$D:$D,"manufacturing",'g-expenses-sl'!$E:$E,$C37) | E37: =SUMIFS('g-expenses-sl'!$F:$F,'g-expenses-sl'!$A:$A,E$1,'g-expenses-sl'!$D:$D,"manufacturing",'g-expenses-sl'!$E:$E,$C37) | F37: =SUMIFS('g-expenses-sl'!$F:$F,'g-expenses-sl'!$A:$A,F$1,'g-expenses-sl'!$D:$D,"manufacturing",'g-expenses-sl'!$E:$E,$C37) | G37: =SUMIFS('g-expenses-sl'!$F:$F,'g-expenses-sl'!$A:$A,G$1,'g-expenses-sl'!$D:$D,"manufacturing",'g-expenses-sl'!$E:$E,$C37) | H37: =SUMIFS('g-expenses-sl'!$F:$F,'g-expenses-sl'!$A:$A,H$1,'g-expenses-sl'!$D:$D,"manufacturing",'g-expenses-sl'!$E:$E,$C37) | I37: =SUMIFS('g-expenses-sl'!$F:$F,'g-expenses-sl'!$A:$A,I$1,'g-expenses-sl'!$D:$D,"manufacturing",'g-expenses-sl'!$E:$E,$C37) | J37: =SUMIFS('g-expenses-sl'!$F:$F,'g-expenses-sl'!$A:$A,J$1,'g-expenses-sl'!$D:$D,"manufacturing",'g-expenses-sl'!$E:$E,$C37) | K37: =SUMIFS('g-expenses-sl'!$F:$F,'g-expenses-sl'!$A:$A,K$1,'g-expenses-sl'!$D:$D,"manufacturing",'g-expenses-sl'!$E:$E,$C37) | ... O37: =SUMIFS('g-expenses-sl'!$F:$F,'g-expenses-sl'!$A:$A,O$1,'g-expenses-sl'!$D:$D,"manufacturing",'g-expenses-sl'!$E:$E,$C37) | P37: -> | Q37: =SUM(D37:O37)
A38: PRESSING | C38: PRESSING | D38: =SUMIFS('g-expenses-sl'!$F:$F,'g-expenses-sl'!$A:$A,D$1,'g-expenses-sl'!$D:$D,"manufacturing",'g-expenses-sl'!$E:$E,$C38) | E38: =SUMIFS('g-expenses-sl'!$F:$F,'g-expenses-sl'!$A:$A,E$1,'g-expenses-sl'!$D:$D,"manufacturing",'g-expenses-sl'!$E:$E,$C38) | F38: =SUMIFS('g-expenses-sl'!$F:$F,'g-expenses-sl'!$A:$A,F$1,'g-expenses-sl'!$D:$D,"manufacturing",'g-expenses-sl'!$E:$E,$C38) | G38: =SUMIFS('g-expenses-sl'!$F:$F,'g-expenses-sl'!$A:$A,G$1,'g-expenses-sl'!$D:$D,"manufacturing",'g-expenses-sl'!$E:$E,$C38) | H38: =SUMIFS('g-expenses-sl'!$F:$F,'g-expenses-sl'!$A:$A,H$1,'g-expenses-sl'!$D:$D,"manufacturing",'g-expenses-sl'!$E:$E,$C38) | I38: =SUMIFS('g-expenses-sl'!$F:$F,'g-expenses-sl'!$A:$A,I$1,'g-expenses-sl'!$D:$D,"manufacturing",'g-expenses-sl'!$E:$E,$C38) | J38: =SUMIFS('g-expenses-sl'!$F:$F,'g-expenses-sl'!$A:$A,J$1,'g-expenses-sl'!$D:$D,"manufacturing",'g-expenses-sl'!$E:$E,$C38) | K38: =SUMIFS('g-expenses-sl'!$F:$F,'g-expenses-sl'!$A:$A,K$1,'g-expenses-sl'!$D:$D,"manufacturing",'g-expenses-sl'!$E:$E,$C38) | ... O38: =SUMIFS('g-expenses-sl'!$F:$F,'g-expenses-sl'!$A:$A,O$1,'g-expenses-sl'!$D:$D,"manufacturing",'g-expenses-sl'!$E:$E,$C38) | P38: -> | Q38: =SUM(D38:O38)
A39: % Manufacturing / sales | C39: % Manufacturing / sales | D39: =IFERROR(D33/D5,0) | E39: =IFERROR(E33/E5,0) | F39: =IFERROR(F33/F5,0) | G39: =IFERROR(G33/G5,0) | H39: =IFERROR(H33/H5,0) | I39: =IFERROR(I33/I5,0) | J39: =IFERROR(J33/J5,0) | K39: =IFERROR(K33/K5,0) | ... O39: =IFERROR(O33/O5,0) | Q39: =SUM(D39:O39)
A40: Logistics (% sales) | C40: Logistics (% sales) | D40: =SUM(D41:D45) | E40: =SUM(E41:E45) | F40: =SUM(F41:F45) | G40: =SUM(G41:G45) | H40: =SUM(H41:H45) | I40: =SUM(I41:I45) | J40: =SUM(J41:J45) | K40: =SUM(K41:K45) | ... O40: =SUM(O41:O45) | P40: -> | Q40: =SUM(D40:O40)
A41: CORREOS | C41: CORREOS | D41: =SUMIFS('g-expenses-sl'!$F:$F,'g-expenses-sl'!$A:$A,D$1,'g-expenses-sl'!$D:$D,"logistics",'g-expenses-sl'!$E:$E,$C41) | E41: =SUMIFS('g-expenses-sl'!$F:$F,'g-expenses-sl'!$A:$A,E$1,'g-expenses-sl'!$D:$D,"logistics",'g-expenses-sl'!$E:$E,$C41) | F41: =SUMIFS('g-expenses-sl'!$F:$F,'g-expenses-sl'!$A:$A,F$1,'g-expenses-sl'!$D:$D,"logistics",'g-expenses-sl'!$E:$E,$C41) | G41: =SUMIFS('g-expenses-sl'!$F:$F,'g-expenses-sl'!$A:$A,G$1,'g-expenses-sl'!$D:$D,"logistics",'g-expenses-sl'!$E:$E,$C41) | H41: =SUMIFS('g-expenses-sl'!$F:$F,'g-expenses-sl'!$A:$A,H$1,'g-expenses-sl'!$D:$D,"logistics",'g-expenses-sl'!$E:$E,$C41) | I41: =SUMIFS('g-expenses-sl'!$F:$F,'g-expenses-sl'!$A:$A,I$1,'g-expenses-sl'!$D:$D,"logistics",'g-expenses-sl'!$E:$E,$C41) | J41: =SUMIFS('g-expenses-sl'!$F:$F,'g-expenses-sl'!$A:$A,J$1,'g-expenses-sl'!$D:$D,"logistics",'g-expenses-sl'!$E:$E,$C41) | K41: =SUMIFS('g-expenses-sl'!$F:$F,'g-expenses-sl'!$A:$A,K$1,'g-expenses-sl'!$D:$D,"logistics",'g-expenses-sl'!$E:$E,$C41) | ... O41: =SUMIFS('g-expenses-sl'!$F:$F,'g-expenses-sl'!$A:$A,O$1,'g-expenses-sl'!$D:$D,"logistics",'g-expenses-sl'!$E:$E,$C41) | P41: -> | Q41: =SUM(D41:O41)
A42: CORREOSCAN | C42: CORREOSCAN | D42: =SUMIFS('g-expenses-sl'!$F:$F,'g-expenses-sl'!$A:$A,D$1,'g-expenses-sl'!$D:$D,"logistics",'g-expenses-sl'!$E:$E,$C42) | E42: =SUMIFS('g-expenses-sl'!$F:$F,'g-expenses-sl'!$A:$A,E$1,'g-expenses-sl'!$D:$D,"logistics",'g-expenses-sl'!$E:$E,$C42) | F42: =SUMIFS('g-expenses-sl'!$F:$F,'g-expenses-sl'!$A:$A,F$1,'g-expenses-sl'!$D:$D,"logistics",'g-expenses-sl'!$E:$E,$C42) | G42: =SUMIFS('g-expenses-sl'!$F:$F,'g-expenses-sl'!$A:$A,G$1,'g-expenses-sl'!$D:$D,"logistics",'g-expenses-sl'!$E:$E,$C42) | H42: =SUMIFS('g-expenses-sl'!$F:$F,'g-expenses-sl'!$A:$A,H$1,'g-expenses-sl'!$D:$D,"logistics",'g-expenses-sl'!$E:$E,$C42) | I42: =SUMIFS('g-expenses-sl'!$F:$F,'g-expenses-sl'!$A:$A,I$1,'g-expenses-sl'!$D:$D,"logistics",'g-expenses-sl'!$E:$E,$C42) | J42: =SUMIFS('g-expenses-sl'!$F:$F,'g-expenses-sl'!$A:$A,J$1,'g-expenses-sl'!$D:$D,"logistics",'g-expenses-sl'!$E:$E,$C42) | K42: =SUMIFS('g-expenses-sl'!$F:$F,'g-expenses-sl'!$A:$A,K$1,'g-expenses-sl'!$D:$D,"logistics",'g-expenses-sl'!$E:$E,$C42) | ... O42: =SUMIFS('g-expenses-sl'!$F:$F,'g-expenses-sl'!$A:$A,O$1,'g-expenses-sl'!$D:$D,"logistics",'g-expenses-sl'!$E:$E,$C42) | P42: -> | Q42: =SUM(D42:O42)
A43: GLS | C43: GLS | D43: =SUMIFS('g-expenses-sl'!$F:$F,'g-expenses-sl'!$A:$A,D$1,'g-expenses-sl'!$D:$D,"logistics",'g-expenses-sl'!$E:$E,$C43) | E43: =SUMIFS('g-expenses-sl'!$F:$F,'g-expenses-sl'!$A:$A,E$1,'g-expenses-sl'!$D:$D,"logistics",'g-expenses-sl'!$E:$E,$C43) | F43: =SUMIFS('g-expenses-sl'!$F:$F,'g-expenses-sl'!$A:$A,F$1,'g-expenses-sl'!$D:$D,"logistics",'g-expenses-sl'!$E:$E,$C43) | G43: =SUMIFS('g-expenses-sl'!$F:$F,'g-expenses-sl'!$A:$A,G$1,'g-expenses-sl'!$D:$D,"logistics",'g-expenses-sl'!$E:$E,$C43) | H43: =SUMIFS('g-expenses-sl'!$F:$F,'g-expenses-sl'!$A:$A,H$1,'g-expenses-sl'!$D:$D,"logistics",'g-expenses-sl'!$E:$E,$C43) | I43: =SUMIFS('g-expenses-sl'!$F:$F,'g-expenses-sl'!$A:$A,I$1,'g-expenses-sl'!$D:$D,"logistics",'g-expenses-sl'!$E:$E,$C43) | J43: =SUMIFS('g-expenses-sl'!$F:$F,'g-expenses-sl'!$A:$A,J$1,'g-expenses-sl'!$D:$D,"logistics",'g-expenses-sl'!$E:$E,$C43) | K43: =SUMIFS('g-expenses-sl'!$F:$F,'g-expenses-sl'!$A:$A,K$1,'g-expenses-sl'!$D:$D,"logistics",'g-expenses-sl'!$E:$E,$C43) | ... O43: =SUMIFS('g-expenses-sl'!$F:$F,'g-expenses-sl'!$A:$A,O$1,'g-expenses-sl'!$D:$D,"logistics",'g-expenses-sl'!$E:$E,$C43) | P43: -> | Q43: =SUM(D43:O43)
A44: SPRINGGDS | C44: SPRINGGDS | D44: =SUMIFS('g-expenses-sl'!$F:$F,'g-expenses-sl'!$A:$A,D$1,'g-expenses-sl'!$D:$D,"logistics",'g-expenses-sl'!$E:$E,$C44) | E44: =SUMIFS('g-expenses-sl'!$F:$F,'g-expenses-sl'!$A:$A,E$1,'g-expenses-sl'!$D:$D,"logistics",'g-expenses-sl'!$E:$E,$C44) | F44: =SUMIFS('g-expenses-sl'!$F:$F,'g-expenses-sl'!$A:$A,F$1,'g-expenses-sl'!$D:$D,"logistics",'g-expenses-sl'!$E:$E,$C44) | G44: =SUMIFS('g-expenses-sl'!$F:$F,'g-expenses-sl'!$A:$A,G$1,'g-expenses-sl'!$D:$D,"logistics",'g-expenses-sl'!$E:$E,$C44) | H44: =SUMIFS('g-expenses-sl'!$F:$F,'g-expenses-sl'!$A:$A,H$1,'g-expenses-sl'!$D:$D,"logistics",'g-expenses-sl'!$E:$E,$C44) | I44: =SUMIFS('g-expenses-sl'!$F:$F,'g-expenses-sl'!$A:$A,I$1,'g-expenses-sl'!$D:$D,"logistics",'g-expenses-sl'!$E:$E,$C44) | J44: =SUMIFS('g-expenses-sl'!$F:$F,'g-expenses-sl'!$A:$A,J$1,'g-expenses-sl'!$D:$D,"logistics",'g-expenses-sl'!$E:$E,$C44) | K44: =SUMIFS('g-expenses-sl'!$F:$F,'g-expenses-sl'!$A:$A,K$1,'g-expenses-sl'!$D:$D,"logistics",'g-expenses-sl'!$E:$E,$C44) | ... O44: =SUMIFS('g-expenses-sl'!$F:$F,'g-expenses-sl'!$A:$A,O$1,'g-expenses-sl'!$D:$D,"logistics",'g-expenses-sl'!$E:$E,$C44) | P44: -> | Q44: =SUM(D44:O44)
A45: UPS | C45: UPS | D45: =SUMIFS('g-expenses-sl'!$F:$F,'g-expenses-sl'!$A:$A,D$1,'g-expenses-sl'!$D:$D,"logistics",'g-expenses-sl'!$E:$E,$C45) | E45: =SUMIFS('g-expenses-sl'!$F:$F,'g-expenses-sl'!$A:$A,E$1,'g-expenses-sl'!$D:$D,"logistics",'g-expenses-sl'!$E:$E,$C45) | F45: =SUMIFS('g-expenses-sl'!$F:$F,'g-expenses-sl'!$A:$A,F$1,'g-expenses-sl'!$D:$D,"logistics",'g-expenses-sl'!$E:$E,$C45) | G45: =SUMIFS('g-expenses-sl'!$F:$F,'g-expenses-sl'!$A:$A,G$1,'g-expenses-sl'!$D:$D,"logistics",'g-expenses-sl'!$E:$E,$C45) | H45: =SUMIFS('g-expenses-sl'!$F:$F,'g-expenses-sl'!$A:$A,H$1,'g-expenses-sl'!$D:$D,"logistics",'g-expenses-sl'!$E:$E,$C45) | I45: =SUMIFS('g-expenses-sl'!$F:$F,'g-expenses-sl'!$A:$A,I$1,'g-expenses-sl'!$D:$D,"logistics",'g-expenses-sl'!$E:$E,$C45) | J45: =SUMIFS('g-expenses-sl'!$F:$F,'g-expenses-sl'!$A:$A,J$1,'g-expenses-sl'!$D:$D,"logistics",'g-expenses-sl'!$E:$E,$C45) | K45: =SUMIFS('g-expenses-sl'!$F:$F,'g-expenses-sl'!$A:$A,K$1,'g-expenses-sl'!$D:$D,"logistics",'g-expenses-sl'!$E:$E,$C45) | ... O45: =SUMIFS('g-expenses-sl'!$F:$F,'g-expenses-sl'!$A:$A,O$1,'g-expenses-sl'!$D:$D,"logistics",'g-expenses-sl'!$E:$E,$C45) | P45: -> | Q45: =SUM(D45:O45)
A46: % Logistics / sales | C46: % Logistics / sales | D46: =IFERROR(D40/D5,0) | E46: =IFERROR(E40/E5,0) | F46: =IFERROR(F40/F5,0) | G46: =IFERROR(G40/G5,0) | H46: =IFERROR(H40/H5,0) | I46: =IFERROR(I40/I5,0) | J46: =IFERROR(J40/J5,0) | K46: =IFERROR(K40/K5,0) | ... O46: =IFERROR(O40/O5,0) | Q46: =SUM(D46:O46)
A47: Royalties (% sales) | C47: Royalties (% sales) | D47: =D48 | E47: =E48 | F47: =F48 | G47: =G48 | H47: =H48 | I47: =I48 | J47: =J48 | K47: =K48 | ... O47: =O48 | P47: -> | Q47: =SUM(D47:O47)
A48: ROYALTIES | C48: ROYALTIES | D48: =SUMIFS('g-expenses-sl'!$F:$F,'g-expenses-sl'!$A:$A,D$1,'g-expenses-sl'!$D:$D,"royalties",'g-expenses-sl'!$E:$E,$C48) | E48: =SUMIFS('g-expenses-sl'!$F:$F,'g-expenses-sl'!$A:$A,E$1,'g-expenses-sl'!$D:$D,"royalties",'g-expenses-sl'!$E:$E,$C48) | F48: =SUMIFS('g-expenses-sl'!$F:$F,'g-expenses-sl'!$A:$A,F$1,'g-expenses-sl'!$D:$D,"royalties",'g-expenses-sl'!$E:$E,$C48) | G48: =SUMIFS('g-expenses-sl'!$F:$F,'g-expenses-sl'!$A:$A,G$1,'g-expenses-sl'!$D:$D,"royalties",'g-expenses-sl'!$E:$E,$C48) | H48: =SUMIFS('g-expenses-sl'!$F:$F,'g-expenses-sl'!$A:$A,H$1,'g-expenses-sl'!$D:$D,"royalties",'g-expenses-sl'!$E:$E,$C48) | I48: =SUMIFS('g-expenses-sl'!$F:$F,'g-expenses-sl'!$A:$A,I$1,'g-expenses-sl'!$D:$D,"royalties",'g-expenses-sl'!$E:$E,$C48) | J48: =SUMIFS('g-expenses-sl'!$F:$F,'g-expenses-sl'!$A:$A,J$1,'g-expenses-sl'!$D:$D,"royalties",'g-expenses-sl'!$E:$E,$C48) | K48: =SUMIFS('g-expenses-sl'!$F:$F,'g-expenses-sl'!$A:$A,K$1,'g-expenses-sl'!$D:$D,"royalties",'g-expenses-sl'!$E:$E,$C48) | ... O48: =SUMIFS('g-expenses-sl'!$F:$F,'g-expenses-sl'!$A:$A,O$1,'g-expenses-sl'!$D:$D,"royalties",'g-expenses-sl'!$E:$E,$C48) | P48: -> | Q48: =SUM(D48:O48)
A49: % Royalties / sales | C49: % Royalties / sales | D49: =IFERROR(D47/D5,0) | E49: =IFERROR(E47/E5,0) | F49: =IFERROR(F47/F5,0) | G49: =IFERROR(G47/G5,0) | H49: =IFERROR(H47/H5,0) | I49: =IFERROR(I47/I5,0) | J49: =IFERROR(J47/J5,0) | K49: =IFERROR(K47/K5,0) | ... O49: =IFERROR(O47/O5,0) | Q49: =SUM(D49:O49)
A50: Payment fees (% sales) | C50: Payment fees (% sales) | D50: =SUM(D51:D52) | E50: =SUM(E51:E52) | F50: =SUM(F51:F52) | G50: =SUM(G51:G52) | H50: =SUM(H51:H52) | I50: =SUM(I51:I52) | J50: =SUM(J51:J52) | K50: =SUM(K51:K52) | ... O50: =SUM(O51:O52) | P50: -> | Q50: =SUM(D50:O50)
A51: SHOPIFY | C51: SHOPIFY | D51: =SUMIFS('g-payment-fees-sl'!$D:$D,'g-payment-fees-sl'!$A:$A,D$1,'g-payment-fees-sl'!$C:$C,$C51) | E51: =SUMIFS('g-payment-fees-sl'!$D:$D,'g-payment-fees-sl'!$A:$A,E$1,'g-payment-fees-sl'!$C:$C,$C51) | F51: =SUMIFS('g-payment-fees-sl'!$D:$D,'g-payment-fees-sl'!$A:$A,F$1,'g-payment-fees-sl'!$C:$C,$C51) | G51: =SUMIFS('g-payment-fees-sl'!$D:$D,'g-payment-fees-sl'!$A:$A,G$1,'g-payment-fees-sl'!$C:$C,$C51) | H51: =SUMIFS('g-payment-fees-sl'!$D:$D,'g-payment-fees-sl'!$A:$A,H$1,'g-payment-fees-sl'!$C:$C,$C51) | I51: =SUMIFS('g-payment-fees-sl'!$D:$D,'g-payment-fees-sl'!$A:$A,I$1,'g-payment-fees-sl'!$C:$C,$C51) | J51: =SUMIFS('g-payment-fees-sl'!$D:$D,'g-payment-fees-sl'!$A:$A,J$1,'g-payment-fees-sl'!$C:$C,$C51) | K51: =SUMIFS('g-payment-fees-sl'!$D:$D,'g-payment-fees-sl'!$A:$A,K$1,'g-payment-fees-sl'!$C:$C,$C51) | ... O51: =SUMIFS('g-payment-fees-sl'!$D:$D,'g-payment-fees-sl'!$A:$A,O$1,'g-payment-fees-sl'!$C:$C,$C51) | P51: -> | Q51: =SUM(D51:O51)
A52: PAYPAL | C52: PAYPAL | D52: =SUMIFS('g-payment-fees-sl'!$D:$D,'g-payment-fees-sl'!$A:$A,D$1,'g-payment-fees-sl'!$C:$C,$C52) | E52: =SUMIFS('g-payment-fees-sl'!$D:$D,'g-payment-fees-sl'!$A:$A,E$1,'g-payment-fees-sl'!$C:$C,$C52) | F52: =SUMIFS('g-payment-fees-sl'!$D:$D,'g-payment-fees-sl'!$A:$A,F$1,'g-payment-fees-sl'!$C:$C,$C52) | G52: =SUMIFS('g-payment-fees-sl'!$D:$D,'g-payment-fees-sl'!$A:$A,G$1,'g-payment-fees-sl'!$C:$C,$C52) | H52: =SUMIFS('g-payment-fees-sl'!$D:$D,'g-payment-fees-sl'!$A:$A,H$1,'g-payment-fees-sl'!$C:$C,$C52) | I52: =SUMIFS('g-payment-fees-sl'!$D:$D,'g-payment-fees-sl'!$A:$A,I$1,'g-payment-fees-sl'!$C:$C,$C52) | J52: =SUMIFS('g-payment-fees-sl'!$D:$D,'g-payment-fees-sl'!$A:$A,J$1,'g-payment-fees-sl'!$C:$C,$C52) | K52: =SUMIFS('g-payment-fees-sl'!$D:$D,'g-payment-fees-sl'!$A:$A,K$1,'g-payment-fees-sl'!$C:$C,$C52) | ... O52: =SUMIFS('g-payment-fees-sl'!$D:$D,'g-payment-fees-sl'!$A:$A,O$1,'g-payment-fees-sl'!$C:$C,$C52) | P52: -> | Q52: =SUM(D52:O52)
A53: % Payment fees / sales | C53: % Payment fees / sales | D53: =IFERROR(D50/D5,0) | E53: =IFERROR(E50/E5,0) | F53: =IFERROR(F50/F5,0) | G53: =IFERROR(G50/G5,0) | H53: =IFERROR(H50/H5,0) | I53: =IFERROR(I50/I5,0) | J53: =IFERROR(J50/J5,0) | K53: =IFERROR(K50/K5,0) | ... O53: =IFERROR(O50/O5,0) | Q53: =SUM(D53:O53)
Q54: =SUM(D54:O54)
A55: GROSS MARGIN (SALES-MANUFACTURING) | D55: =D5-D33 | E55: =E5-E33 | F55: =F5-F33 | G55: =G5-G33 | H55: =H5-H33 | I55: =I5-I33 | J55: =J5-J33 | K55: =K5-K33 | ... O55: =O5-O33 | Q55: =SUM(D55:O55)
A56: % GROSS MARGIN | D56: =IFERROR(D55/D5,0) | E56: =IFERROR(E55/E5,0) | F56: =IFERROR(F55/F5,0) | G56: =IFERROR(G55/G5,0) | H56: =IFERROR(H55/H5,0) | I56: =IFERROR(I55/I5,0) | J56: =IFERROR(J55/J5,0) | K56: =IFERROR(K55/K5,0) | ... O56: =IFERROR(O55/O5,0) | Q56: =SUM(D56:O56)
A57: CONTRIBUTIVE MARGIN (TURNOVER-COGS) | D57: =D4-D32 | E57: =E4-E32 | F57: =F4-F32 | G57: =G4-G32 | H57: =H4-H32 | I57: =I4-I32 | J57: =J4-J32 | K57: =K4-K32 | ... O57: =O4-O32 | Q57: =SUM(D57:O57)
A58: % CONTRIBUTIVE MARGIN | D58: =IFERROR(D57/D4,0) | E58: =IFERROR(E57/E4,0) | F58: =IFERROR(F57/F4,0) | G58: =IFERROR(G57/G4,0) | H58: =IFERROR(H57/H4,0) | I58: =IFERROR(I57/I4,0) | J58: =IFERROR(J57/J4,0) | K58: =IFERROR(K57/K4,0) | ... O58: =IFERROR(O57/O4,0) | Q58: =SUM(D58:O58)
Q59: =SUM(D59:O59)
A60: Opex | B60: Opex | D60: =D61+D65+D68+D74 | E60: =E61+E65+E68+E74 | F60: =F61+F65+F68+F74 | G60: =G61+G65+G68+G74 | H60: =H61+H65+H68+H74 | I60: =I61+I65+I68+I74 | J60: =J61+J65+J68+J74 | K60: =K61+K65+K68+K74 | ... O60: =O61+O65+O68+O74 | Q60: =SUM(D60:O60)
A61: Marketing | C61: Marketing | D61: =SUM(D62:D63) | E61: =SUM(E62:E63) | F61: =SUM(F62:F63) | G61: =SUM(G62:G63) | H61: =SUM(H62:H63) | I61: =SUM(I62:I63) | J61: =SUM(J62:J63) | K61: =SUM(K62:K63) | ... O61: =SUM(O62:O63) | P61: -> | Q61: =SUM(D61:O61)
A62: METAADS | C62: METAADS | D62: =SUMIFS('g-expenses-sl'!$F:$F,'g-expenses-sl'!$A:$A,D$1,'g-expenses-sl'!$D:$D,"marketing",'g-expenses-sl'!$E:$E,$C62) | E62: =SUMIFS('g-expenses-sl'!$F:$F,'g-expenses-sl'!$A:$A,E$1,'g-expenses-sl'!$D:$D,"marketing",'g-expenses-sl'!$E:$E,$C62) | F62: =SUMIFS('g-expenses-sl'!$F:$F,'g-expenses-sl'!$A:$A,F$1,'g-expenses-sl'!$D:$D,"marketing",'g-expenses-sl'!$E:$E,$C62) | G62: =SUMIFS('g-expenses-sl'!$F:$F,'g-expenses-sl'!$A:$A,G$1,'g-expenses-sl'!$D:$D,"marketing",'g-expenses-sl'!$E:$E,$C62) | H62: =SUMIFS('g-expenses-sl'!$F:$F,'g-expenses-sl'!$A:$A,H$1,'g-expenses-sl'!$D:$D,"marketing",'g-expenses-sl'!$E:$E,$C62) | I62: =SUMIFS('g-expenses-sl'!$F:$F,'g-expenses-sl'!$A:$A,I$1,'g-expenses-sl'!$D:$D,"marketing",'g-expenses-sl'!$E:$E,$C62) | J62: =SUMIFS('g-expenses-sl'!$F:$F,'g-expenses-sl'!$A:$A,J$1,'g-expenses-sl'!$D:$D,"marketing",'g-expenses-sl'!$E:$E,$C62) | K62: =SUMIFS('g-expenses-sl'!$F:$F,'g-expenses-sl'!$A:$A,K$1,'g-expenses-sl'!$D:$D,"marketing",'g-expenses-sl'!$E:$E,$C62) | ... O62: =SUMIFS('g-expenses-sl'!$F:$F,'g-expenses-sl'!$A:$A,O$1,'g-expenses-sl'!$D:$D,"marketing",'g-expenses-sl'!$E:$E,$C62) | P62: -> | Q62: =SUM(D62:O62)
A63: GOOGLEADS | C63: GOOGLEADS | D63: =SUMIFS('g-expenses-sl'!$F:$F,'g-expenses-sl'!$A:$A,D$1,'g-expenses-sl'!$D:$D,"marketing",'g-expenses-sl'!$E:$E,$C63) | E63: =SUMIFS('g-expenses-sl'!$F:$F,'g-expenses-sl'!$A:$A,E$1,'g-expenses-sl'!$D:$D,"marketing",'g-expenses-sl'!$E:$E,$C63) | F63: =SUMIFS('g-expenses-sl'!$F:$F,'g-expenses-sl'!$A:$A,F$1,'g-expenses-sl'!$D:$D,"marketing",'g-expenses-sl'!$E:$E,$C63) | G63: =SUMIFS('g-expenses-sl'!$F:$F,'g-expenses-sl'!$A:$A,G$1,'g-expenses-sl'!$D:$D,"marketing",'g-expenses-sl'!$E:$E,$C63) | H63: =SUMIFS('g-expenses-sl'!$F:$F,'g-expenses-sl'!$A:$A,H$1,'g-expenses-sl'!$D:$D,"marketing",'g-expenses-sl'!$E:$E,$C63) | I63: =SUMIFS('g-expenses-sl'!$F:$F,'g-expenses-sl'!$A:$A,I$1,'g-expenses-sl'!$D:$D,"marketing",'g-expenses-sl'!$E:$E,$C63) | J63: =SUMIFS('g-expenses-sl'!$F:$F,'g-expenses-sl'!$A:$A,J$1,'g-expenses-sl'!$D:$D,"marketing",'g-expenses-sl'!$E:$E,$C63) | K63: =SUMIFS('g-expenses-sl'!$F:$F,'g-expenses-sl'!$A:$A,K$1,'g-expenses-sl'!$D:$D,"marketing",'g-expenses-sl'!$E:$E,$C63) | ... O63: =SUMIFS('g-expenses-sl'!$F:$F,'g-expenses-sl'!$A:$A,O$1,'g-expenses-sl'!$D:$D,"marketing",'g-expenses-sl'!$E:$E,$C63) | P63: -> | Q63: =SUM(D63:O63)
A64: % Marketing / sales | C64: % Marketing / sales | D64: =IFERROR(D61/D6,0) | E64: =IFERROR(E61/E6,0) | F64: =IFERROR(F61/F6,0) | G64: =IFERROR(G61/G6,0) | H64: =IFERROR(H61/H6,0) | I64: =IFERROR(I61/I6,0) | J64: =IFERROR(J61/J6,0) | K64: =IFERROR(K61/K6,0) | ... O64: =IFERROR(O61/O6,0) | Q64: =SUM(D64:O64)
A65: Staff | C65: Staff | D65: =SUM(D66:D67) | E65: =SUM(E66:E67) | F65: =SUM(F66:F67) | G65: =SUM(G66:G67) | H65: =SUM(H66:H67) | I65: =SUM(I66:I67) | J65: =SUM(J66:J67) | K65: =SUM(K66:K67) | ... O65: =SUM(O66:O67) | P65: -> | Q65: =SUM(D65:O65)
A66: PAYROLL | C66: PAYROLL | D66: =SUMIFS('g-expenses-sl'!$F:$F,'g-expenses-sl'!$A:$A,D$1,'g-expenses-sl'!$D:$D,"staff",'g-expenses-sl'!$E:$E,$C66) | E66: =SUMIFS('g-expenses-sl'!$F:$F,'g-expenses-sl'!$A:$A,E$1,'g-expenses-sl'!$D:$D,"staff",'g-expenses-sl'!$E:$E,$C66) | F66: =SUMIFS('g-expenses-sl'!$F:$F,'g-expenses-sl'!$A:$A,F$1,'g-expenses-sl'!$D:$D,"staff",'g-expenses-sl'!$E:$E,$C66) | G66: =SUMIFS('g-expenses-sl'!$F:$F,'g-expenses-sl'!$A:$A,G$1,'g-expenses-sl'!$D:$D,"staff",'g-expenses-sl'!$E:$E,$C66) | H66: =SUMIFS('g-expenses-sl'!$F:$F,'g-expenses-sl'!$A:$A,H$1,'g-expenses-sl'!$D:$D,"staff",'g-expenses-sl'!$E:$E,$C66) | I66: =SUMIFS('g-expenses-sl'!$F:$F,'g-expenses-sl'!$A:$A,I$1,'g-expenses-sl'!$D:$D,"staff",'g-expenses-sl'!$E:$E,$C66) | J66: =SUMIFS('g-expenses-sl'!$F:$F,'g-expenses-sl'!$A:$A,J$1,'g-expenses-sl'!$D:$D,"staff",'g-expenses-sl'!$E:$E,$C66) | K66: =SUMIFS('g-expenses-sl'!$F:$F,'g-expenses-sl'!$A:$A,K$1,'g-expenses-sl'!$D:$D,"staff",'g-expenses-sl'!$E:$E,$C66) | ... O66: =SUMIFS('g-expenses-sl'!$F:$F,'g-expenses-sl'!$A:$A,O$1,'g-expenses-sl'!$D:$D,"staff",'g-expenses-sl'!$E:$E,$C66) | P66: -> | Q66: =SUM(D66:O66)
A67: DOSCONSULTING | C67: DOSCONSULTING | D67: =SUMIFS('g-expenses-sl'!$F:$F,'g-expenses-sl'!$A:$A,D$1,'g-expenses-sl'!$D:$D,"staff",'g-expenses-sl'!$E:$E,$C67) | E67: =SUMIFS('g-expenses-sl'!$F:$F,'g-expenses-sl'!$A:$A,E$1,'g-expenses-sl'!$D:$D,"staff",'g-expenses-sl'!$E:$E,$C67) | F67: =SUMIFS('g-expenses-sl'!$F:$F,'g-expenses-sl'!$A:$A,F$1,'g-expenses-sl'!$D:$D,"staff",'g-expenses-sl'!$E:$E,$C67) | G67: =SUMIFS('g-expenses-sl'!$F:$F,'g-expenses-sl'!$A:$A,G$1,'g-expenses-sl'!$D:$D,"staff",'g-expenses-sl'!$E:$E,$C67) | H67: =SUMIFS('g-expenses-sl'!$F:$F,'g-expenses-sl'!$A:$A,H$1,'g-expenses-sl'!$D:$D,"staff",'g-expenses-sl'!$E:$E,$C67) | I67: =SUMIFS('g-expenses-sl'!$F:$F,'g-expenses-sl'!$A:$A,I$1,'g-expenses-sl'!$D:$D,"staff",'g-expenses-sl'!$E:$E,$C67) | J67: =SUMIFS('g-expenses-sl'!$F:$F,'g-expenses-sl'!$A:$A,J$1,'g-expenses-sl'!$D:$D,"staff",'g-expenses-sl'!$E:$E,$C67) | K67: =SUMIFS('g-expenses-sl'!$F:$F,'g-expenses-sl'!$A:$A,K$1,'g-expenses-sl'!$D:$D,"staff",'g-expenses-sl'!$E:$E,$C67) | ... O67: =SUMIFS('g-expenses-sl'!$F:$F,'g-expenses-sl'!$A:$A,O$1,'g-expenses-sl'!$D:$D,"staff",'g-expenses-sl'!$E:$E,$C67) | P67: -> | Q67: =SUM(D67:O67)
A68: Administration | C68: Administration | D68: =SUM(D69:D73) | E68: =SUM(E69:E73) | F68: =SUM(F69:F73) | G68: =SUM(G69:G73) | H68: =SUM(H69:H73) | I68: =SUM(I69:I73) | J68: =SUM(J69:J73) | K68: =SUM(K69:K73) | ... O68: =SUM(O69:O73) | P68: -> | Q68: =SUM(D68:O68)
A69: CLARIS | C69: CLARIS | D69: =SUMIFS('g-expenses-sl'!$F:$F,'g-expenses-sl'!$A:$A,D$1,'g-expenses-sl'!$D:$D,"administration",'g-expenses-sl'!$E:$E,$C69) | E69: =SUMIFS('g-expenses-sl'!$F:$F,'g-expenses-sl'!$A:$A,E$1,'g-expenses-sl'!$D:$D,"administration",'g-expenses-sl'!$E:$E,$C69) | F69: =SUMIFS('g-expenses-sl'!$F:$F,'g-expenses-sl'!$A:$A,F$1,'g-expenses-sl'!$D:$D,"administration",'g-expenses-sl'!$E:$E,$C69) | G69: =SUMIFS('g-expenses-sl'!$F:$F,'g-expenses-sl'!$A:$A,G$1,'g-expenses-sl'!$D:$D,"administration",'g-expenses-sl'!$E:$E,$C69) | H69: =SUMIFS('g-expenses-sl'!$F:$F,'g-expenses-sl'!$A:$A,H$1,'g-expenses-sl'!$D:$D,"administration",'g-expenses-sl'!$E:$E,$C69) | I69: =SUMIFS('g-expenses-sl'!$F:$F,'g-expenses-sl'!$A:$A,I$1,'g-expenses-sl'!$D:$D,"administration",'g-expenses-sl'!$E:$E,$C69) | J69: =SUMIFS('g-expenses-sl'!$F:$F,'g-expenses-sl'!$A:$A,J$1,'g-expenses-sl'!$D:$D,"administration",'g-expenses-sl'!$E:$E,$C69) | K69: =SUMIFS('g-expenses-sl'!$F:$F,'g-expenses-sl'!$A:$A,K$1,'g-expenses-sl'!$D:$D,"administration",'g-expenses-sl'!$E:$E,$C69) | ... O69: =SUMIFS('g-expenses-sl'!$F:$F,'g-expenses-sl'!$A:$A,O$1,'g-expenses-sl'!$D:$D,"administration",'g-expenses-sl'!$E:$E,$C69) | P69: -> | Q69: =SUM(D69:O69)
A70: HANNUN | C70: HANNUN | D70: =SUMIFS('g-expenses-sl'!$F:$F,'g-expenses-sl'!$A:$A,D$1,'g-expenses-sl'!$D:$D,"administration",'g-expenses-sl'!$E:$E,$C70) | E70: =SUMIFS('g-expenses-sl'!$F:$F,'g-expenses-sl'!$A:$A,E$1,'g-expenses-sl'!$D:$D,"administration",'g-expenses-sl'!$E:$E,$C70) | F70: =SUMIFS('g-expenses-sl'!$F:$F,'g-expenses-sl'!$A:$A,F$1,'g-expenses-sl'!$D:$D,"administration",'g-expenses-sl'!$E:$E,$C70) | G70: =SUMIFS('g-expenses-sl'!$F:$F,'g-expenses-sl'!$A:$A,G$1,'g-expenses-sl'!$D:$D,"administration",'g-expenses-sl'!$E:$E,$C70) | H70: =SUMIFS('g-expenses-sl'!$F:$F,'g-expenses-sl'!$A:$A,H$1,'g-expenses-sl'!$D:$D,"administration",'g-expenses-sl'!$E:$E,$C70) | I70: =SUMIFS('g-expenses-sl'!$F:$F,'g-expenses-sl'!$A:$A,I$1,'g-expenses-sl'!$D:$D,"administration",'g-expenses-sl'!$E:$E,$C70) | J70: =SUMIFS('g-expenses-sl'!$F:$F,'g-expenses-sl'!$A:$A,J$1,'g-expenses-sl'!$D:$D,"administration",'g-expenses-sl'!$E:$E,$C70) | K70: =SUMIFS('g-expenses-sl'!$F:$F,'g-expenses-sl'!$A:$A,K$1,'g-expenses-sl'!$D:$D,"administration",'g-expenses-sl'!$E:$E,$C70) | ... O70: =SUMIFS('g-expenses-sl'!$F:$F,'g-expenses-sl'!$A:$A,O$1,'g-expenses-sl'!$D:$D,"administration",'g-expenses-sl'!$E:$E,$C70) | P70: -> | Q70: =SUM(D70:O70)
A71: NODA | C71: NODA | D71: =SUMIFS('g-expenses-sl'!$F:$F,'g-expenses-sl'!$A:$A,D$1,'g-expenses-sl'!$D:$D,"administration",'g-expenses-sl'!$E:$E,$C71) | E71: =SUMIFS('g-expenses-sl'!$F:$F,'g-expenses-sl'!$A:$A,E$1,'g-expenses-sl'!$D:$D,"administration",'g-expenses-sl'!$E:$E,$C71) | F71: =SUMIFS('g-expenses-sl'!$F:$F,'g-expenses-sl'!$A:$A,F$1,'g-expenses-sl'!$D:$D,"administration",'g-expenses-sl'!$E:$E,$C71) | G71: =SUMIFS('g-expenses-sl'!$F:$F,'g-expenses-sl'!$A:$A,G$1,'g-expenses-sl'!$D:$D,"administration",'g-expenses-sl'!$E:$E,$C71) | H71: =SUMIFS('g-expenses-sl'!$F:$F,'g-expenses-sl'!$A:$A,H$1,'g-expenses-sl'!$D:$D,"administration",'g-expenses-sl'!$E:$E,$C71) | I71: =SUMIFS('g-expenses-sl'!$F:$F,'g-expenses-sl'!$A:$A,I$1,'g-expenses-sl'!$D:$D,"administration",'g-expenses-sl'!$E:$E,$C71) | J71: =SUMIFS('g-expenses-sl'!$F:$F,'g-expenses-sl'!$A:$A,J$1,'g-expenses-sl'!$D:$D,"administration",'g-expenses-sl'!$E:$E,$C71) | K71: =SUMIFS('g-expenses-sl'!$F:$F,'g-expenses-sl'!$A:$A,K$1,'g-expenses-sl'!$D:$D,"administration",'g-expenses-sl'!$E:$E,$C71) | ... O71: =SUMIFS('g-expenses-sl'!$F:$F,'g-expenses-sl'!$A:$A,O$1,'g-expenses-sl'!$D:$D,"administration",'g-expenses-sl'!$E:$E,$C71) | P71: -> | Q71: =SUM(D71:O71)
A72: TORRAS | C72: TORRAS | D72: =SUMIFS('g-expenses-sl'!$F:$F,'g-expenses-sl'!$A:$A,D$1,'g-expenses-sl'!$D:$D,"administration",'g-expenses-sl'!$E:$E,$C72) | E72: =SUMIFS('g-expenses-sl'!$F:$F,'g-expenses-sl'!$A:$A,E$1,'g-expenses-sl'!$D:$D,"administration",'g-expenses-sl'!$E:$E,$C72) | F72: =SUMIFS('g-expenses-sl'!$F:$F,'g-expenses-sl'!$A:$A,F$1,'g-expenses-sl'!$D:$D,"administration",'g-expenses-sl'!$E:$E,$C72) | G72: =SUMIFS('g-expenses-sl'!$F:$F,'g-expenses-sl'!$A:$A,G$1,'g-expenses-sl'!$D:$D,"administration",'g-expenses-sl'!$E:$E,$C72) | H72: =SUMIFS('g-expenses-sl'!$F:$F,'g-expenses-sl'!$A:$A,H$1,'g-expenses-sl'!$D:$D,"administration",'g-expenses-sl'!$E:$E,$C72) | I72: =SUMIFS('g-expenses-sl'!$F:$F,'g-expenses-sl'!$A:$A,I$1,'g-expenses-sl'!$D:$D,"administration",'g-expenses-sl'!$E:$E,$C72) | J72: =SUMIFS('g-expenses-sl'!$F:$F,'g-expenses-sl'!$A:$A,J$1,'g-expenses-sl'!$D:$D,"administration",'g-expenses-sl'!$E:$E,$C72) | K72: =SUMIFS('g-expenses-sl'!$F:$F,'g-expenses-sl'!$A:$A,K$1,'g-expenses-sl'!$D:$D,"administration",'g-expenses-sl'!$E:$E,$C72) | ... O72: =SUMIFS('g-expenses-sl'!$F:$F,'g-expenses-sl'!$A:$A,O$1,'g-expenses-sl'!$D:$D,"administration",'g-expenses-sl'!$E:$E,$C72) | P72: -> | Q72: =SUM(D72:O72)
A73: VITALY | C73: VITALY | D73: =SUMIFS('g-expenses-sl'!$F:$F,'g-expenses-sl'!$A:$A,D$1,'g-expenses-sl'!$D:$D,"administration",'g-expenses-sl'!$E:$E,$C73) | E73: =SUMIFS('g-expenses-sl'!$F:$F,'g-expenses-sl'!$A:$A,E$1,'g-expenses-sl'!$D:$D,"administration",'g-expenses-sl'!$E:$E,$C73) | F73: =SUMIFS('g-expenses-sl'!$F:$F,'g-expenses-sl'!$A:$A,F$1,'g-expenses-sl'!$D:$D,"administration",'g-expenses-sl'!$E:$E,$C73) | G73: =SUMIFS('g-expenses-sl'!$F:$F,'g-expenses-sl'!$A:$A,G$1,'g-expenses-sl'!$D:$D,"administration",'g-expenses-sl'!$E:$E,$C73) | H73: =SUMIFS('g-expenses-sl'!$F:$F,'g-expenses-sl'!$A:$A,H$1,'g-expenses-sl'!$D:$D,"administration",'g-expenses-sl'!$E:$E,$C73) | I73: =SUMIFS('g-expenses-sl'!$F:$F,'g-expenses-sl'!$A:$A,I$1,'g-expenses-sl'!$D:$D,"administration",'g-expenses-sl'!$E:$E,$C73) | J73: =SUMIFS('g-expenses-sl'!$F:$F,'g-expenses-sl'!$A:$A,J$1,'g-expenses-sl'!$D:$D,"administration",'g-expenses-sl'!$E:$E,$C73) | K73: =SUMIFS('g-expenses-sl'!$F:$F,'g-expenses-sl'!$A:$A,K$1,'g-expenses-sl'!$D:$D,"administration",'g-expenses-sl'!$E:$E,$C73) | ... O73: =SUMIFS('g-expenses-sl'!$F:$F,'g-expenses-sl'!$A:$A,O$1,'g-expenses-sl'!$D:$D,"administration",'g-expenses-sl'!$E:$E,$C73) | P73: -> | Q73: =SUM(D73:O73)
A74: Technology | C74: Technology | D74: =SUM(D75:D89) | E74: =SUM(E75:E89) | F74: =SUM(F75:F89) | G74: =SUM(G75:G89) | H74: =SUM(H75:H89) | I74: =SUM(I75:I89) | J74: =SUM(J75:J89) | K74: =SUM(K75:K89) | ... O74: =SUM(O75:O89) | P74: -> | Q74: =SUM(D74:O74)
A75: ADOBE | C75: ADOBE | D75: =SUMIFS('g-expenses-sl'!$F:$F,'g-expenses-sl'!$A:$A,D$1,'g-expenses-sl'!$D:$D,"technology",'g-expenses-sl'!$E:$E,$C75) | E75: =SUMIFS('g-expenses-sl'!$F:$F,'g-expenses-sl'!$A:$A,E$1,'g-expenses-sl'!$D:$D,"technology",'g-expenses-sl'!$E:$E,$C75) | F75: =SUMIFS('g-expenses-sl'!$F:$F,'g-expenses-sl'!$A:$A,F$1,'g-expenses-sl'!$D:$D,"technology",'g-expenses-sl'!$E:$E,$C75) | G75: =SUMIFS('g-expenses-sl'!$F:$F,'g-expenses-sl'!$A:$A,G$1,'g-expenses-sl'!$D:$D,"technology",'g-expenses-sl'!$E:$E,$C75) | H75: =SUMIFS('g-expenses-sl'!$F:$F,'g-expenses-sl'!$A:$A,H$1,'g-expenses-sl'!$D:$D,"technology",'g-expenses-sl'!$E:$E,$C75) | I75: =SUMIFS('g-expenses-sl'!$F:$F,'g-expenses-sl'!$A:$A,I$1,'g-expenses-sl'!$D:$D,"technology",'g-expenses-sl'!$E:$E,$C75) | J75: =SUMIFS('g-expenses-sl'!$F:$F,'g-expenses-sl'!$A:$A,J$1,'g-expenses-sl'!$D:$D,"technology",'g-expenses-sl'!$E:$E,$C75) | K75: =SUMIFS('g-expenses-sl'!$F:$F,'g-expenses-sl'!$A:$A,K$1,'g-expenses-sl'!$D:$D,"technology",'g-expenses-sl'!$E:$E,$C75) | ... O75: =SUMIFS('g-expenses-sl'!$F:$F,'g-expenses-sl'!$A:$A,O$1,'g-expenses-sl'!$D:$D,"technology",'g-expenses-sl'!$E:$E,$C75) | P75: -> | Q75: =SUM(D75:O75)
A76: CANVA | C76: CANVA | D76: =SUMIFS('g-expenses-sl'!$F:$F,'g-expenses-sl'!$A:$A,D$1,'g-expenses-sl'!$D:$D,"technology",'g-expenses-sl'!$E:$E,$C76) | E76: =SUMIFS('g-expenses-sl'!$F:$F,'g-expenses-sl'!$A:$A,E$1,'g-expenses-sl'!$D:$D,"technology",'g-expenses-sl'!$E:$E,$C76) | F76: =SUMIFS('g-expenses-sl'!$F:$F,'g-expenses-sl'!$A:$A,F$1,'g-expenses-sl'!$D:$D,"technology",'g-expenses-sl'!$E:$E,$C76) | G76: =SUMIFS('g-expenses-sl'!$F:$F,'g-expenses-sl'!$A:$A,G$1,'g-expenses-sl'!$D:$D,"technology",'g-expenses-sl'!$E:$E,$C76) | H76: =SUMIFS('g-expenses-sl'!$F:$F,'g-expenses-sl'!$A:$A,H$1,'g-expenses-sl'!$D:$D,"technology",'g-expenses-sl'!$E:$E,$C76) | I76: =SUMIFS('g-expenses-sl'!$F:$F,'g-expenses-sl'!$A:$A,I$1,'g-expenses-sl'!$D:$D,"technology",'g-expenses-sl'!$E:$E,$C76) | J76: =SUMIFS('g-expenses-sl'!$F:$F,'g-expenses-sl'!$A:$A,J$1,'g-expenses-sl'!$D:$D,"technology",'g-expenses-sl'!$E:$E,$C76) | K76: =SUMIFS('g-expenses-sl'!$F:$F,'g-expenses-sl'!$A:$A,K$1,'g-expenses-sl'!$D:$D,"technology",'g-expenses-sl'!$E:$E,$C76) | ... O76: =SUMIFS('g-expenses-sl'!$F:$F,'g-expenses-sl'!$A:$A,O$1,'g-expenses-sl'!$D:$D,"technology",'g-expenses-sl'!$E:$E,$C76) | P76: -> | Q76: =SUM(D76:O76)
A77: GODADDY | C77: GODADDY | D77: =SUMIFS('g-expenses-sl'!$F:$F,'g-expenses-sl'!$A:$A,D$1,'g-expenses-sl'!$D:$D,"technology",'g-expenses-sl'!$E:$E,$C77) | E77: =SUMIFS('g-expenses-sl'!$F:$F,'g-expenses-sl'!$A:$A,E$1,'g-expenses-sl'!$D:$D,"technology",'g-expenses-sl'!$E:$E,$C77) | F77: =SUMIFS('g-expenses-sl'!$F:$F,'g-expenses-sl'!$A:$A,F$1,'g-expenses-sl'!$D:$D,"technology",'g-expenses-sl'!$E:$E,$C77) | G77: =SUMIFS('g-expenses-sl'!$F:$F,'g-expenses-sl'!$A:$A,G$1,'g-expenses-sl'!$D:$D,"technology",'g-expenses-sl'!$E:$E,$C77) | H77: =SUMIFS('g-expenses-sl'!$F:$F,'g-expenses-sl'!$A:$A,H$1,'g-expenses-sl'!$D:$D,"technology",'g-expenses-sl'!$E:$E,$C77) | I77: =SUMIFS('g-expenses-sl'!$F:$F,'g-expenses-sl'!$A:$A,I$1,'g-expenses-sl'!$D:$D,"technology",'g-expenses-sl'!$E:$E,$C77) | J77: =SUMIFS('g-expenses-sl'!$F:$F,'g-expenses-sl'!$A:$A,J$1,'g-expenses-sl'!$D:$D,"technology",'g-expenses-sl'!$E:$E,$C77) | K77: =SUMIFS('g-expenses-sl'!$F:$F,'g-expenses-sl'!$A:$A,K$1,'g-expenses-sl'!$D:$D,"technology",'g-expenses-sl'!$E:$E,$C77) | ... O77: =SUMIFS('g-expenses-sl'!$F:$F,'g-expenses-sl'!$A:$A,O$1,'g-expenses-sl'!$D:$D,"technology",'g-expenses-sl'!$E:$E,$C77) | P77: -> | Q77: =SUM(D77:O77)
A78: GOOGLEWORKSPACE | C78: GOOGLEWORKSPACE | D78: =SUMIFS('g-expenses-sl'!$F:$F,'g-expenses-sl'!$A:$A,D$1,'g-expenses-sl'!$D:$D,"technology",'g-expenses-sl'!$E:$E,$C78) | E78: =SUMIFS('g-expenses-sl'!$F:$F,'g-expenses-sl'!$A:$A,E$1,'g-expenses-sl'!$D:$D,"technology",'g-expenses-sl'!$E:$E,$C78) | F78: =SUMIFS('g-expenses-sl'!$F:$F,'g-expenses-sl'!$A:$A,F$1,'g-expenses-sl'!$D:$D,"technology",'g-expenses-sl'!$E:$E,$C78) | G78: =SUMIFS('g-expenses-sl'!$F:$F,'g-expenses-sl'!$A:$A,G$1,'g-expenses-sl'!$D:$D,"technology",'g-expenses-sl'!$E:$E,$C78) | H78: =SUMIFS('g-expenses-sl'!$F:$F,'g-expenses-sl'!$A:$A,H$1,'g-expenses-sl'!$D:$D,"technology",'g-expenses-sl'!$E:$E,$C78) | I78: =SUMIFS('g-expenses-sl'!$F:$F,'g-expenses-sl'!$A:$A,I$1,'g-expenses-sl'!$D:$D,"technology",'g-expenses-sl'!$E:$E,$C78) | J78: =SUMIFS('g-expenses-sl'!$F:$F,'g-expenses-sl'!$A:$A,J$1,'g-expenses-sl'!$D:$D,"technology",'g-expenses-sl'!$E:$E,$C78) | K78: =SUMIFS('g-expenses-sl'!$F:$F,'g-expenses-sl'!$A:$A,K$1,'g-expenses-sl'!$D:$D,"technology",'g-expenses-sl'!$E:$E,$C78) | ... O78: =SUMIFS('g-expenses-sl'!$F:$F,'g-expenses-sl'!$A:$A,O$1,'g-expenses-sl'!$D:$D,"technology",'g-expenses-sl'!$E:$E,$C78) | P78: -> | Q78: =SUM(D78:O78)
A79: GORGIAS | C79: GORGIAS | D79: =SUMIFS('g-expenses-sl'!$F:$F,'g-expenses-sl'!$A:$A,D$1,'g-expenses-sl'!$D:$D,"technology",'g-expenses-sl'!$E:$E,$C79) | E79: =SUMIFS('g-expenses-sl'!$F:$F,'g-expenses-sl'!$A:$A,E$1,'g-expenses-sl'!$D:$D,"technology",'g-expenses-sl'!$E:$E,$C79) | F79: =SUMIFS('g-expenses-sl'!$F:$F,'g-expenses-sl'!$A:$A,F$1,'g-expenses-sl'!$D:$D,"technology",'g-expenses-sl'!$E:$E,$C79) | G79: =SUMIFS('g-expenses-sl'!$F:$F,'g-expenses-sl'!$A:$A,G$1,'g-expenses-sl'!$D:$D,"technology",'g-expenses-sl'!$E:$E,$C79) | H79: =SUMIFS('g-expenses-sl'!$F:$F,'g-expenses-sl'!$A:$A,H$1,'g-expenses-sl'!$D:$D,"technology",'g-expenses-sl'!$E:$E,$C79) | I79: =SUMIFS('g-expenses-sl'!$F:$F,'g-expenses-sl'!$A:$A,I$1,'g-expenses-sl'!$D:$D,"technology",'g-expenses-sl'!$E:$E,$C79) | J79: =SUMIFS('g-expenses-sl'!$F:$F,'g-expenses-sl'!$A:$A,J$1,'g-expenses-sl'!$D:$D,"technology",'g-expenses-sl'!$E:$E,$C79) | K79: =SUMIFS('g-expenses-sl'!$F:$F,'g-expenses-sl'!$A:$A,K$1,'g-expenses-sl'!$D:$D,"technology",'g-expenses-sl'!$E:$E,$C79) | ... O79: =SUMIFS('g-expenses-sl'!$F:$F,'g-expenses-sl'!$A:$A,O$1,'g-expenses-sl'!$D:$D,"technology",'g-expenses-sl'!$E:$E,$C79) | P79: -> | Q79: =SUM(D79:O79)
A80: HETZNER | C80: HETZNER | D80: =SUMIFS('g-expenses-sl'!$F:$F,'g-expenses-sl'!$A:$A,D$1,'g-expenses-sl'!$D:$D,"technology",'g-expenses-sl'!$E:$E,$C80) | E80: =SUMIFS('g-expenses-sl'!$F:$F,'g-expenses-sl'!$A:$A,E$1,'g-expenses-sl'!$D:$D,"technology",'g-expenses-sl'!$E:$E,$C80) | F80: =SUMIFS('g-expenses-sl'!$F:$F,'g-expenses-sl'!$A:$A,F$1,'g-expenses-sl'!$D:$D,"technology",'g-expenses-sl'!$E:$E,$C80) | G80: =SUMIFS('g-expenses-sl'!$F:$F,'g-expenses-sl'!$A:$A,G$1,'g-expenses-sl'!$D:$D,"technology",'g-expenses-sl'!$E:$E,$C80) | H80: =SUMIFS('g-expenses-sl'!$F:$F,'g-expenses-sl'!$A:$A,H$1,'g-expenses-sl'!$D:$D,"technology",'g-expenses-sl'!$E:$E,$C80) | I80: =SUMIFS('g-expenses-sl'!$F:$F,'g-expenses-sl'!$A:$A,I$1,'g-expenses-sl'!$D:$D,"technology",'g-expenses-sl'!$E:$E,$C80) | J80: =SUMIFS('g-expenses-sl'!$F:$F,'g-expenses-sl'!$A:$A,J$1,'g-expenses-sl'!$D:$D,"technology",'g-expenses-sl'!$E:$E,$C80) | K80: =SUMIFS('g-expenses-sl'!$F:$F,'g-expenses-sl'!$A:$A,K$1,'g-expenses-sl'!$D:$D,"technology",'g-expenses-sl'!$E:$E,$C80) | ... O80: =SUMIFS('g-expenses-sl'!$F:$F,'g-expenses-sl'!$A:$A,O$1,'g-expenses-sl'!$D:$D,"technology",'g-expenses-sl'!$E:$E,$C80) | P80: -> | Q80: =SUM(D80:O80)
A81: KONVOAI | C81: KONVOAI | D81: =SUMIFS('g-expenses-sl'!$F:$F,'g-expenses-sl'!$A:$A,D$1,'g-expenses-sl'!$D:$D,"technology",'g-expenses-sl'!$E:$E,$C81) | E81: =SUMIFS('g-expenses-sl'!$F:$F,'g-expenses-sl'!$A:$A,E$1,'g-expenses-sl'!$D:$D,"technology",'g-expenses-sl'!$E:$E,$C81) | F81: =SUMIFS('g-expenses-sl'!$F:$F,'g-expenses-sl'!$A:$A,F$1,'g-expenses-sl'!$D:$D,"technology",'g-expenses-sl'!$E:$E,$C81) | G81: =SUMIFS('g-expenses-sl'!$F:$F,'g-expenses-sl'!$A:$A,G$1,'g-expenses-sl'!$D:$D,"technology",'g-expenses-sl'!$E:$E,$C81) | H81: =SUMIFS('g-expenses-sl'!$F:$F,'g-expenses-sl'!$A:$A,H$1,'g-expenses-sl'!$D:$D,"technology",'g-expenses-sl'!$E:$E,$C81) | I81: =SUMIFS('g-expenses-sl'!$F:$F,'g-expenses-sl'!$A:$A,I$1,'g-expenses-sl'!$D:$D,"technology",'g-expenses-sl'!$E:$E,$C81) | J81: =SUMIFS('g-expenses-sl'!$F:$F,'g-expenses-sl'!$A:$A,J$1,'g-expenses-sl'!$D:$D,"technology",'g-expenses-sl'!$E:$E,$C81) | K81: =SUMIFS('g-expenses-sl'!$F:$F,'g-expenses-sl'!$A:$A,K$1,'g-expenses-sl'!$D:$D,"technology",'g-expenses-sl'!$E:$E,$C81) | ... O81: =SUMIFS('g-expenses-sl'!$F:$F,'g-expenses-sl'!$A:$A,O$1,'g-expenses-sl'!$D:$D,"technology",'g-expenses-sl'!$E:$E,$C81) | P81: -> | Q81: =SUM(D81:O81)
A82: MASMOVIL | C82: MASMOVIL | D82: =SUMIFS('g-expenses-sl'!$F:$F,'g-expenses-sl'!$A:$A,D$1,'g-expenses-sl'!$D:$D,"technology",'g-expenses-sl'!$E:$E,$C82) | E82: =SUMIFS('g-expenses-sl'!$F:$F,'g-expenses-sl'!$A:$A,E$1,'g-expenses-sl'!$D:$D,"technology",'g-expenses-sl'!$E:$E,$C82) | F82: =SUMIFS('g-expenses-sl'!$F:$F,'g-expenses-sl'!$A:$A,F$1,'g-expenses-sl'!$D:$D,"technology",'g-expenses-sl'!$E:$E,$C82) | G82: =SUMIFS('g-expenses-sl'!$F:$F,'g-expenses-sl'!$A:$A,G$1,'g-expenses-sl'!$D:$D,"technology",'g-expenses-sl'!$E:$E,$C82) | H82: =SUMIFS('g-expenses-sl'!$F:$F,'g-expenses-sl'!$A:$A,H$1,'g-expenses-sl'!$D:$D,"technology",'g-expenses-sl'!$E:$E,$C82) | I82: =SUMIFS('g-expenses-sl'!$F:$F,'g-expenses-sl'!$A:$A,I$1,'g-expenses-sl'!$D:$D,"technology",'g-expenses-sl'!$E:$E,$C82) | J82: =SUMIFS('g-expenses-sl'!$F:$F,'g-expenses-sl'!$A:$A,J$1,'g-expenses-sl'!$D:$D,"technology",'g-expenses-sl'!$E:$E,$C82) | K82: =SUMIFS('g-expenses-sl'!$F:$F,'g-expenses-sl'!$A:$A,K$1,'g-expenses-sl'!$D:$D,"technology",'g-expenses-sl'!$E:$E,$C82) | ... O82: =SUMIFS('g-expenses-sl'!$F:$F,'g-expenses-sl'!$A:$A,O$1,'g-expenses-sl'!$D:$D,"technology",'g-expenses-sl'!$E:$E,$C82) | P82: -> | Q82: =SUM(D82:O82)
A83: MICROSOFT | C83: MICROSOFT | D83: =SUMIFS('g-expenses-sl'!$F:$F,'g-expenses-sl'!$A:$A,D$1,'g-expenses-sl'!$D:$D,"technology",'g-expenses-sl'!$E:$E,$C83) | E83: =SUMIFS('g-expenses-sl'!$F:$F,'g-expenses-sl'!$A:$A,E$1,'g-expenses-sl'!$D:$D,"technology",'g-expenses-sl'!$E:$E,$C83) | F83: =SUMIFS('g-expenses-sl'!$F:$F,'g-expenses-sl'!$A:$A,F$1,'g-expenses-sl'!$D:$D,"technology",'g-expenses-sl'!$E:$E,$C83) | G83: =SUMIFS('g-expenses-sl'!$F:$F,'g-expenses-sl'!$A:$A,G$1,'g-expenses-sl'!$D:$D,"technology",'g-expenses-sl'!$E:$E,$C83) | H83: =SUMIFS('g-expenses-sl'!$F:$F,'g-expenses-sl'!$A:$A,H$1,'g-expenses-sl'!$D:$D,"technology",'g-expenses-sl'!$E:$E,$C83) | I83: =SUMIFS('g-expenses-sl'!$F:$F,'g-expenses-sl'!$A:$A,I$1,'g-expenses-sl'!$D:$D,"technology",'g-expenses-sl'!$E:$E,$C83) | J83: =SUMIFS('g-expenses-sl'!$F:$F,'g-expenses-sl'!$A:$A,J$1,'g-expenses-sl'!$D:$D,"technology",'g-expenses-sl'!$E:$E,$C83) | K83: =SUMIFS('g-expenses-sl'!$F:$F,'g-expenses-sl'!$A:$A,K$1,'g-expenses-sl'!$D:$D,"technology",'g-expenses-sl'!$E:$E,$C83) | ... O83: =SUMIFS('g-expenses-sl'!$F:$F,'g-expenses-sl'!$A:$A,O$1,'g-expenses-sl'!$D:$D,"technology",'g-expenses-sl'!$E:$E,$C83) | P83: -> | Q83: =SUM(D83:O83)
A84: OPENAI | C84: OPENAI | D84: =SUMIFS('g-expenses-sl'!$F:$F,'g-expenses-sl'!$A:$A,D$1,'g-expenses-sl'!$D:$D,"technology",'g-expenses-sl'!$E:$E,$C84) | E84: =SUMIFS('g-expenses-sl'!$F:$F,'g-expenses-sl'!$A:$A,E$1,'g-expenses-sl'!$D:$D,"technology",'g-expenses-sl'!$E:$E,$C84) | F84: =SUMIFS('g-expenses-sl'!$F:$F,'g-expenses-sl'!$A:$A,F$1,'g-expenses-sl'!$D:$D,"technology",'g-expenses-sl'!$E:$E,$C84) | G84: =SUMIFS('g-expenses-sl'!$F:$F,'g-expenses-sl'!$A:$A,G$1,'g-expenses-sl'!$D:$D,"technology",'g-expenses-sl'!$E:$E,$C84) | H84: =SUMIFS('g-expenses-sl'!$F:$F,'g-expenses-sl'!$A:$A,H$1,'g-expenses-sl'!$D:$D,"technology",'g-expenses-sl'!$E:$E,$C84) | I84: =SUMIFS('g-expenses-sl'!$F:$F,'g-expenses-sl'!$A:$A,I$1,'g-expenses-sl'!$D:$D,"technology",'g-expenses-sl'!$E:$E,$C84) | J84: =SUMIFS('g-expenses-sl'!$F:$F,'g-expenses-sl'!$A:$A,J$1,'g-expenses-sl'!$D:$D,"technology",'g-expenses-sl'!$E:$E,$C84) | K84: =SUMIFS('g-expenses-sl'!$F:$F,'g-expenses-sl'!$A:$A,K$1,'g-expenses-sl'!$D:$D,"technology",'g-expenses-sl'!$E:$E,$C84) | ... O84: =SUMIFS('g-expenses-sl'!$F:$F,'g-expenses-sl'!$A:$A,O$1,'g-expenses-sl'!$D:$D,"technology",'g-expenses-sl'!$E:$E,$C84) | P84: -> | Q84: =SUM(D84:O84)
A85: PRODUCTHERO | C85: PRODUCTHERO | D85: =SUMIFS('g-expenses-sl'!$F:$F,'g-expenses-sl'!$A:$A,D$1,'g-expenses-sl'!$D:$D,"technology",'g-expenses-sl'!$E:$E,$C85) | E85: =SUMIFS('g-expenses-sl'!$F:$F,'g-expenses-sl'!$A:$A,E$1,'g-expenses-sl'!$D:$D,"technology",'g-expenses-sl'!$E:$E,$C85) | F85: =SUMIFS('g-expenses-sl'!$F:$F,'g-expenses-sl'!$A:$A,F$1,'g-expenses-sl'!$D:$D,"technology",'g-expenses-sl'!$E:$E,$C85) | G85: =SUMIFS('g-expenses-sl'!$F:$F,'g-expenses-sl'!$A:$A,G$1,'g-expenses-sl'!$D:$D,"technology",'g-expenses-sl'!$E:$E,$C85) | H85: =SUMIFS('g-expenses-sl'!$F:$F,'g-expenses-sl'!$A:$A,H$1,'g-expenses-sl'!$D:$D,"technology",'g-expenses-sl'!$E:$E,$C85) | I85: =SUMIFS('g-expenses-sl'!$F:$F,'g-expenses-sl'!$A:$A,I$1,'g-expenses-sl'!$D:$D,"technology",'g-expenses-sl'!$E:$E,$C85) | J85: =SUMIFS('g-expenses-sl'!$F:$F,'g-expenses-sl'!$A:$A,J$1,'g-expenses-sl'!$D:$D,"technology",'g-expenses-sl'!$E:$E,$C85) | K85: =SUMIFS('g-expenses-sl'!$F:$F,'g-expenses-sl'!$A:$A,K$1,'g-expenses-sl'!$D:$D,"technology",'g-expenses-sl'!$E:$E,$C85) | ... O85: =SUMIFS('g-expenses-sl'!$F:$F,'g-expenses-sl'!$A:$A,O$1,'g-expenses-sl'!$D:$D,"technology",'g-expenses-sl'!$E:$E,$C85) | P85: -> | Q85: =SUM(D85:O85)
A86: RAILWAY | C86: RAILWAY | D86: =SUMIFS('g-expenses-sl'!$F:$F,'g-expenses-sl'!$A:$A,D$1,'g-expenses-sl'!$D:$D,"technology",'g-expenses-sl'!$E:$E,$C86) | E86: =SUMIFS('g-expenses-sl'!$F:$F,'g-expenses-sl'!$A:$A,E$1,'g-expenses-sl'!$D:$D,"technology",'g-expenses-sl'!$E:$E,$C86) | F86: =SUMIFS('g-expenses-sl'!$F:$F,'g-expenses-sl'!$A:$A,F$1,'g-expenses-sl'!$D:$D,"technology",'g-expenses-sl'!$E:$E,$C86) | G86: =SUMIFS('g-expenses-sl'!$F:$F,'g-expenses-sl'!$A:$A,G$1,'g-expenses-sl'!$D:$D,"technology",'g-expenses-sl'!$E:$E,$C86) | H86: =SUMIFS('g-expenses-sl'!$F:$F,'g-expenses-sl'!$A:$A,H$1,'g-expenses-sl'!$D:$D,"technology",'g-expenses-sl'!$E:$E,$C86) | I86: =SUMIFS('g-expenses-sl'!$F:$F,'g-expenses-sl'!$A:$A,I$1,'g-expenses-sl'!$D:$D,"technology",'g-expenses-sl'!$E:$E,$C86) | J86: =SUMIFS('g-expenses-sl'!$F:$F,'g-expenses-sl'!$A:$A,J$1,'g-expenses-sl'!$D:$D,"technology",'g-expenses-sl'!$E:$E,$C86) | K86: =SUMIFS('g-expenses-sl'!$F:$F,'g-expenses-sl'!$A:$A,K$1,'g-expenses-sl'!$D:$D,"technology",'g-expenses-sl'!$E:$E,$C86) | ... O86: =SUMIFS('g-expenses-sl'!$F:$F,'g-expenses-sl'!$A:$A,O$1,'g-expenses-sl'!$D:$D,"technology",'g-expenses-sl'!$E:$E,$C86) | P86: -> | Q86: =SUM(D86:O86)
... A89: YUMAAI | C89: YUMAAI | D89: =SUMIFS('g-expenses-sl'!$F:$F,'g-expenses-sl'!$A:$A,D$1,'g-expenses-sl'!$D:$D,"technology",'g-expenses-sl'!$E:$E,$C89) | E89: =SUMIFS('g-expenses-sl'!$F:$F,'g-expenses-sl'!$A:$A,E$1,'g-expenses-sl'!$D:$D,"technology",'g-expenses-sl'!$E:$E,$C89) | F89: =SUMIFS('g-expenses-sl'!$F:$F,'g-expenses-sl'!$A:$A,F$1,'g-expenses-sl'!$D:$D,"technology",'g-expenses-sl'!$E:$E,$C89) | G89: =SUMIFS('g-expenses-sl'!$F:$F,'g-expenses-sl'!$A:$A,G$1,'g-expenses-sl'!$D:$D,"technology",'g-expenses-sl'!$E:$E,$C89) | H89: =SUMIFS('g-expenses-sl'!$F:$F,'g-expenses-sl'!$A:$A,H$1,'g-expenses-sl'!$D:$D,"technology",'g-expenses-sl'!$E:$E,$C89) | I89: =SUMIFS('g-expenses-sl'!$F:$F,'g-expenses-sl'!$A:$A,I$1,'g-expenses-sl'!$D:$D,"technology",'g-expenses-sl'!$E:$E,$C89) | J89: =SUMIFS('g-expenses-sl'!$F:$F,'g-expenses-sl'!$A:$A,J$1,'g-expenses-sl'!$D:$D,"technology",'g-expenses-sl'!$E:$E,$C89) | K89: =SUMIFS('g-expenses-sl'!$F:$F,'g-expenses-sl'!$A:$A,K$1,'g-expenses-sl'!$D:$D,"technology",'g-expenses-sl'!$E:$E,$C89) | ... O89: =SUMIFS('g-expenses-sl'!$F:$F,'g-expenses-sl'!$A:$A,O$1,'g-expenses-sl'!$D:$D,"technology",'g-expenses-sl'!$E:$E,$C89) | P89: -> | Q89: =SUM(D89:O89)
Q90: =SUM(D90:O90)
A91: PROFIT | D91: =D4-D32-D60 | E91: =E4-E32-E60 | F91: =F4-F32-F60 | G91: =G4-G32-G60 | H91: =H4-H32-H60 | I91: =I4-I32-I60 | J91: =J4-J32-J60 | K91: =K4-K32-K60 | ... O91: =O4-O32-O60 | Q91: =SUM(D91:O91)
A92: % Profit / turnover | D92: =IFERROR(D91/D4,0) | E92: =IFERROR(E91/E4,0) | F92: =IFERROR(F91/F4,0) | G92: =IFERROR(G91/G4,0) | H92: =IFERROR(H91/H4,0) | I92: =IFERROR(I91/I4,0) | J92: =IFERROR(J91/J4,0) | K92: =IFERROR(K91/K4,0) | ... O92: =IFERROR(O91/O4,0) | Q92: =SUM(D92:O92)

Sheet params
A1: <- Volver a P&G-SL
A2: key | B2: value
A3: entity | B3: SL
A4: year | B4: 2026
A5: generated_at_utc | B5: 2026-03-23T01:15:03Z

Sheet i-shopify-sl
A1: <- Volver a P&G-SL
A2: yyyymm | B2: entity | C2: line_item | D2: detail | E2: amount_net | F2: currency | G2: source
A3: 202601 | B3: SL | C3: AT | D3: AT | E3: 5482.24 | F3: EUR | G3: finance.ventas_pyg
A4: 202601 | B4: SL | C4: BE | D4: BE | E4: 422.71 | F4: EUR | G4: finance.ventas_pyg
A5: 202601 | B5: SL | C5: DE | D5: DE | E5: 20924.16 | F5: EUR | G5: finance.ventas_pyg
A6: 202601 | B6: SL | C6: ES | D6: ES | E6: 61194.44 | F6: EUR | G6: finance.ventas_pyg
A7: 202601 | B7: SL | C7: FR | D7: FR | E7: 25590.35 | F7: EUR | G7: finance.ventas_pyg
A8: 202601 | B8: SL | C8: IT | D8: IT | E8: 18483.79 | F8: EUR | G8: finance.ventas_pyg
A9: 202601 | B9: SL | C9: NL | D9: NL | E9: 115.58 | F9: EUR | G9: finance.ventas_pyg
A10: 202601 | B10: SL | C10: PT | D10: PT | E10: 729.31 | F10: EUR | G10: finance.ventas_pyg
A11: 202601 | B11: SL | C11: XX | D11: XX | E11: 691.19 | F11: EUR | G11: finance.ventas_pyg
A12: 202602 | B12: SL | C12: AT | D12: AT | E12: 6077.94 | F12: EUR | G12: finance.ventas_pyg
A13: 202602 | B13: SL | C13: BE | D13: BE | E13: 998.68 | F13: EUR | G13: finance.ventas_pyg
A14: 202602 | B14: SL | C14: DE | D14: DE | E14: 19361.46 | F14: EUR | G14: finance.ventas_pyg
... A28: 202603 | B28: SL | C28: XX | D28: XX | E28: 227.22 | F28: EUR | G28: finance.ventas_pyg

Sheet i-marketplaces-sl
A1: <- Volver a P&G-SL
A2: yyyymm | B2: entity | C2: line_item | D2: detail | E2: amount_net | F2: currency | G2: source
A3: 202601 | B3: SL | C3: HANNUN | D3: DE | E3: 116.89 | F3: EUR | G3: finance.ventas_pyg
A4: 202601 | B4: SL | C4: HANNUN | D4: ES | E4: 900.37 | F4: EUR | G4: finance.ventas_pyg
A5: 202601 | B5: SL | C5: HANNUN | D5: FR | E5: 213.09 | F5: EUR | G5: finance.ventas_pyg
A6: 202601 | B6: SL | C6: HANNUN | D6: IT | E6: 81.15 | F6: EUR | G6: finance.ventas_pyg
A7: 202601 | B7: SL | C7: HANNUN | D7: PT | E7: 213.92 | F7: EUR | G7: finance.ventas_pyg
A8: 202602 | B8: SL | C8: HANNUN | D8: AT | E8: 57.8 | F8: EUR | G8: finance.ventas_pyg
A9: 202602 | B9: SL | C9: HANNUN | D9: DE | E9: 23.11 | F9: EUR | G9: finance.ventas_pyg
A10: 202602 | B10: SL | C10: HANNUN | D10: ES | E10: 832.95 | F10: EUR | G10: finance.ventas_pyg
A11: 202602 | B11: SL | C11: HANNUN | D11: FR | E11: 54.82 | F11: EUR | G11: finance.ventas_pyg
A12: 202602 | B12: SL | C12: HANNUN | D12: IT | E12: 97.1 | F12: EUR | G12: finance.ventas_pyg
A13: 202602 | B13: SL | C13: TOASTY | D13: b2b_partner | E13: 1746.6 | F13: EUR | G13: documents
A14: 202603 | B14: SL | C14: CHOOSE | D14: campaign | E14: 15609.96 | F14: EUR | G14: documents
... A19: 202603 | B19: SL | C19: HANNUN | D19: PT | E19: 134.09 | F19: EUR | G19: finance.ventas_pyg

Sheet i-rappels-sl
A1: <- Volver a P&G-SL
A2: yyyymm | B2: entity | C2: line_item | D2: detail | E2: amount_net | F2: currency | G2: source
A3: 202601 | B3: SL | C3: LIVITUM | D3: rappels | E3: -1118.95 | F3: EUR | G3: documents

Sheet i-supplies-sl
A1: <- Volver a P&G-SL
A2: yyyymm | B2: entity | C2: line_item | D2: detail | E2: amount_net | F2: currency | G2: source
A3: 202601 | B3: SL | C3: REVER | D3: supplied_note | E3: -2176.46 | F3: EUR | G3: documents
A4: 202602 | B4: SL | C4: REVER | D4: supplied_note | E4: -522.54 | F4: EUR | G4: documents

Sheet i-services-sl
A1: <- Volver a P&G-SL
A2: yyyymm | B2: entity | C2: line_item | D2: detail | E2: amount_net | F2: currency | G2: source
A3: 202601 | B3: SL | C3: HANNUN | D3: orders | E3: 1419.7 | F3: EUR | G3: documents
A4: 202601 | B4: SL | C4: HANNUN | D4: renting_cnc | E4: 1661.16 | F4: EUR | G4: documents
A5: 202601 | B5: SL | C5: HANNUN | D5: staff | E5: 1191.18 | F5: EUR | G5: documents
A6: 202601 | B6: SL | C6: Inc | D6: shared_services | E6: 7334.44 | F6: EUR | G6: documents:shared_services
A7: 202601 | B7: SL | C7: Ltd | D7: shared_services | E7: 10732.87 | F7: EUR | G7: documents:shared_services
A8: 202602 | B8: SL | C8: HANNUN | D8: orders | E8: 1128.42 | F8: EUR | G8: documents
A9: 202602 | B9: SL | C9: HANNUN | D9: staff | E9: 1191.91 | F9: EUR | G9: documents
A10: 202602 | B10: SL | C10: Inc | D10: shared_services | E10: 8462.36 | F10: EUR | G10: documents:shared_services
A11: 202602 | B11: SL | C11: Ltd | D11: shared_services | E11: 13068.98 | F11: EUR | G11: documents:shared_services
A12: 202602 | B12: SL | C12: QHANDS | D12: renting_cnc | E12: 1661.16 | F12: EUR | G12: documents

Sheet g-expenses-sl
A1: <- Volver a P&G-SL
A2: yyyymm | B2: entity | C2: category | D2: subcategory | E2: supplier_code | F2: amount_net | G2: currency | H2: source
A3: 202601 | B3: SL | C3: opex | D3: technology | E3: ADOBE | F3: 33.49 | G3: EUR | H3: documents
A4: 202601 | B4: SL | C4: cogs | D4: manufacturing | E4: APPHOTOCAN | F4: 29.22 | G4: EUR | H4: documents
A5: 202601 | B5: SL | C5: cogs | D5: manufacturing | E5: APPHOTOES | F5: 17898.08 | G5: EUR | H5: documents
A6: 202601 | B6: SL | C6: opex | D6: technology | E6: CANVA | F6: 9.91 | G6: EUR | H6: documents
A7: 202601 | B7: SL | C7: opex | D7: administration | E7: CLARIS | F7: 808.08 | G7: EUR | H7: documents
A8: 202601 | B8: SL | C8: cogs | D8: logistics | E8: CORREOS | F8: 553.76 | G8: EUR | H8: documents
A9: 202601 | B9: SL | C9: cogs | D9: manufacturing | E9: DCT | F9: 9730.11 | G9: EUR | H9: documents
A10: 202601 | B10: SL | C10: cogs | D10: logistics | E10: GLS | F10: 12319.26 | G10: EUR | H10: documents
A11: 202601 | B11: SL | C11: opex | D11: technology | E11: GODADDY | F11: 34.23 | G11: EUR | H11: documents
A12: 202601 | B12: SL | C12: opex | D12: marketing | E12: GOOGLEADS | F12: 24746.34 | G12: EUR | H12: documents
A13: 202601 | B13: SL | C13: opex | D13: marketing | E13: GOOGLEADS | F13: 2298.67 | G13: EUR | H13: documents
A14: 202601 | B14: SL | C14: opex | D14: marketing | E14: GOOGLEADS | F14: 2119.05 | G14: EUR | H14: documents
... A78: 202602 | B78: SL | C78: opex | D78: staff | E78: PAYROLL | F78: 14915.68 | G78: EUR | H78: payroll_documents

Sheet g-payment-fees-sl
A1: <- Volver a P&G-SL
A2: yyyymm | B2: entity | C2: supplier_code | D2: amount_net | E2: currency | F2: source
A3: 202601 | B3: SL | C3: SHOPIFY | D3: 2616.7 | E3: EUR | F3: payment_fee_monthly_summary
A4: 202602 | B4: SL | C4: SHOPIFY | D4: 2778.19 | E4: EUR | F4: payment_fee_monthly_summary
A5: 202603 | B5: SL | C5: SHOPIFY | D5: 2014.7 | E5: EUR | F5: payment_fee_monthly_summary

Sheet catalog-sl
A1: <- Volver a P&G-SL
A2: supplier_code | B2: supplier_name | C2: current_folder | D2: destination_path | E2: notes
A3: CORREOS | B3: CORREOS | C3: Correos | D3: expenses/cogs/logistics | E3: Peninsula/Baleares 21% IVA
A4: CORREOSCAN | B4: CORREOSCAN | C4: Correos | D4: expenses/cogs/logistics | E4: Canarias 7% IGIC
A5: GLS | B5: GLS | C5: GLS | D5: expenses/cogs/logistics | E5: OCR-based GLS parser via scanned PDF
A6: SPRINGGDS | B6: SPRINGGDS | C6: SPRING | D6: expenses/cogs/logistics | E6: Spring operating brand
A7: UPS | B7: UPS | C7: UPS | D7: expenses/cogs/logistics
A8: APPHOTOCAN | B8: APPHOTOCAN | C8: AP Photo | D8: expenses/cogs/manufacturing | E8: IGIC 7%
A9: APPHOTOES | B9: APPHOTOES | C9: AP Photo | D9: expenses/cogs/manufacturing
A10: ARTLINK | B10: ARTLINK | C10: Artlink | D10: expenses/cogs/manufacturing | E10: Frame purchases and related freight are treated as manufacturing
A11: DCT | B11: DCT | C11: DCT | D11: expenses/cogs/manufacturing
A12: PRESSING | B12: PRESSING | C12: Pressing | D12: expenses/cogs/manufacturing
A13: ROYALTIES | B13: ROYALTIES | C13: Artistas | D13: expenses/cogs/royalties | E13: Artist royalties received and issued by Artesta
A14: CLARIS | B14: CLARIS | C14: CLARIS | D14: expenses/opex/administration
A15: HANNUN | B15: HANNUN | C15: HANNUN | D15: expenses/opex/administration | E15: Bidirectional HANNUN relationship; incoming expense invoices and outgoing customer invoices
A16: NODA | B16: NODA | C16: NODA Asesores | D16: expenses/opex/administration
A17: TORRAS | B17: TORRAS | C17: TORRAS | D17: expenses/opex/administration
A18: VITALY | B18: VITALY | C18: Vitaly | D18: expenses/opex/administration | E18: Annual prevention and occupational health service
A19: GOOGLEADS | B19: GOOGLEADS | C19: Google | D19: expenses/opex/marketing
A20: METAADS | B20: METAADS | C20: Meta | D20: expenses/opex/marketing
A21: DOSCONSULTING | B21: DOSCONSULTING | C21: Nóminas | D21: expenses/opex/staff | E21: Monthly payroll management for SL
A22: ADOBE | B22: ADOBE | C22: ADOBE | D22: expenses/opex/technology
A23: CANVA | B23: CANVA | C23: canva | D23: expenses/opex/technology
A24: GODADDY | B24: GODADDY | C24: godaddy | D24: expenses/opex/technology
A25: GOOGLEWORKSPACE | B25: GOOGLEWORKSPACE | C25: Google | D25: expenses/opex/technology
A26: GORGIAS | B26: GORGIAS | C26: Gorgias | D26: expenses/opex/technology
A27: HETZNER | B27: HETZNER | C27: HETZNER | D27: expenses/opex/technology
A28: KONVOAI | B28: KONVOAI | C28: konvo | D28: expenses/opex/technology
A29: MASMOVIL | B29: MASMOVIL | C29: mas movil | D29: expenses/opex/technology
A30: MICROSOFT | B30: MICROSOFT | C30: MICROSOFT | D30: expenses/opex/technology
A31: OPENAI | B31: OPENAI | C31: chatgpt | D31: expenses/opex/technology | E31: Groups ChatGPT and API
A32: PRODUCTHERO | B32: PRODUCTHERO | C32: ProductHERO | D32: expenses/opex/technology
A33: RAILWAY | B33: RAILWAY | C33: RAILWAY | D33: expenses/opex/technology
A34: REVER | B34: REVER | C34: REVER | D34: expenses/opex/technology
A35: SHOPIFY | B35: SHOPIFY | C35: Shopify | D35: expenses/opex/technology
A36: YUMAAI | B36: YUMAAI | C36: YUMA | D36: expenses/opex/technology
A37: LIVITUM | B37: LIVITUM | C37: 709. Rappels | D37: income/other_income/rappels | E37: Rappel issued to Livitum
A38: CHOOSE | B38: CHOOSE | C38: CHOOSE | D38: income/sales/marketplaces | E38: Outgoing partner invoice
A39: TOASTY | B39: TOASTY | C39: TOASTY | D39: income/sales/marketplaces | E39: Outgoing partner invoice
A40: QHANDS | B40: QHANDS | C40: QHANDS | D40: income/shared-services | E40: Outgoing CNC rental invoice
