Workbook

Sheet P&G-SL
D1: 202601 | E1: 202602 | F1: 202603 | G1: 202604 | H1: 202605 | I1: 202606 | J1: 202607 | K1: 202608 | L1: 202609 | M1: 202610 | N1: 202611 | O1: 202612 | P1: TOTAL
A2: P&G SL 2026 | D2: Enero | E2: Febrero | F2: Marzo | G2: Abril | H2: Mayo | I2: Junio | J2: Julio | K2: Agosto | L2: Septiembre | M2: Octubre | N2: Noviembre | O2: Diciembre | P2: Total
A3: Actualizado: 23/03/2026 09:26 h
A4: Turnover | D4: =D5+D25 | E4: =E5+E25 | F4: =F5+F25 | G4: =G5+G25 | H4: =H5+H25 | I4: =I5+I25 | J4: =J5+J25 | K4: =K5+K25 | ... O4: =O5+O25 | P4: =SUM(D4:O4)
A5: Product sales | B5: Product sales | D5: =D6+D16+D20+D22 | E5: =E6+E16+E20+E22 | F5: =F6+F16+F20+F22 | G5: =G6+G16+G20+G22 | H5: =H6+H16+H20+H22 | I5: =I6+I16+I20+I22 | J5: =J6+J16+J20+J22 | K5: =K6+K16+K20+K22 | ... O5: =O6+O16+O20+O22 | P5: =SUM(D5:O5)
A6: Shopify | C6: Shopify | D6: =SUM(D7:D15) | E6: =SUM(E7:E15) | F6: =SUM(F7:F15) | G6: =SUM(G7:G15) | H6: =SUM(H7:H15) | I6: =SUM(I7:I15) | J6: =SUM(J7:J15) | K6: =SUM(K7:K15) | ... O6: =SUM(O7:O15) | P6: =SUM(D6:O6) | Q6: ->
A7: ES | C7: ES | D7: =SUMIFS('i-shopify-sl'!$E:$E,'i-shopify-sl'!$A:$A,D$1,'i-shopify-sl'!$C:$C,$C7) | E7: =SUMIFS('i-shopify-sl'!$E:$E,'i-shopify-sl'!$A:$A,E$1,'i-shopify-sl'!$C:$C,$C7) | F7: =SUMIFS('i-shopify-sl'!$E:$E,'i-shopify-sl'!$A:$A,F$1,'i-shopify-sl'!$C:$C,$C7) | G7: =SUMIFS('i-shopify-sl'!$E:$E,'i-shopify-sl'!$A:$A,G$1,'i-shopify-sl'!$C:$C,$C7) | H7: =SUMIFS('i-shopify-sl'!$E:$E,'i-shopify-sl'!$A:$A,H$1,'i-shopify-sl'!$C:$C,$C7) | I7: =SUMIFS('i-shopify-sl'!$E:$E,'i-shopify-sl'!$A:$A,I$1,'i-shopify-sl'!$C:$C,$C7) | J7: =SUMIFS('i-shopify-sl'!$E:$E,'i-shopify-sl'!$A:$A,J$1,'i-shopify-sl'!$C:$C,$C7) | K7: =SUMIFS('i-shopify-sl'!$E:$E,'i-shopify-sl'!$A:$A,K$1,'i-shopify-sl'!$C:$C,$C7) | ... O7: =SUMIFS('i-shopify-sl'!$E:$E,'i-shopify-sl'!$A:$A,O$1,'i-shopify-sl'!$C:$C,$C7) | P7: =SUM(D7:O7) | Q7: ->
A8: FR | C8: FR | D8: =SUMIFS('i-shopify-sl'!$E:$E,'i-shopify-sl'!$A:$A,D$1,'i-shopify-sl'!$C:$C,$C8) | E8: =SUMIFS('i-shopify-sl'!$E:$E,'i-shopify-sl'!$A:$A,E$1,'i-shopify-sl'!$C:$C,$C8) | F8: =SUMIFS('i-shopify-sl'!$E:$E,'i-shopify-sl'!$A:$A,F$1,'i-shopify-sl'!$C:$C,$C8) | G8: =SUMIFS('i-shopify-sl'!$E:$E,'i-shopify-sl'!$A:$A,G$1,'i-shopify-sl'!$C:$C,$C8) | H8: =SUMIFS('i-shopify-sl'!$E:$E,'i-shopify-sl'!$A:$A,H$1,'i-shopify-sl'!$C:$C,$C8) | I8: =SUMIFS('i-shopify-sl'!$E:$E,'i-shopify-sl'!$A:$A,I$1,'i-shopify-sl'!$C:$C,$C8) | J8: =SUMIFS('i-shopify-sl'!$E:$E,'i-shopify-sl'!$A:$A,J$1,'i-shopify-sl'!$C:$C,$C8) | K8: =SUMIFS('i-shopify-sl'!$E:$E,'i-shopify-sl'!$A:$A,K$1,'i-shopify-sl'!$C:$C,$C8) | ... O8: =SUMIFS('i-shopify-sl'!$E:$E,'i-shopify-sl'!$A:$A,O$1,'i-shopify-sl'!$C:$C,$C8) | P8: =SUM(D8:O8) | Q8: ->
A9: DE | C9: DE | D9: =SUMIFS('i-shopify-sl'!$E:$E,'i-shopify-sl'!$A:$A,D$1,'i-shopify-sl'!$C:$C,$C9) | E9: =SUMIFS('i-shopify-sl'!$E:$E,'i-shopify-sl'!$A:$A,E$1,'i-shopify-sl'!$C:$C,$C9) | F9: =SUMIFS('i-shopify-sl'!$E:$E,'i-shopify-sl'!$A:$A,F$1,'i-shopify-sl'!$C:$C,$C9) | G9: =SUMIFS('i-shopify-sl'!$E:$E,'i-shopify-sl'!$A:$A,G$1,'i-shopify-sl'!$C:$C,$C9) | H9: =SUMIFS('i-shopify-sl'!$E:$E,'i-shopify-sl'!$A:$A,H$1,'i-shopify-sl'!$C:$C,$C9) | I9: =SUMIFS('i-shopify-sl'!$E:$E,'i-shopify-sl'!$A:$A,I$1,'i-shopify-sl'!$C:$C,$C9) | J9: =SUMIFS('i-shopify-sl'!$E:$E,'i-shopify-sl'!$A:$A,J$1,'i-shopify-sl'!$C:$C,$C9) | K9: =SUMIFS('i-shopify-sl'!$E:$E,'i-shopify-sl'!$A:$A,K$1,'i-shopify-sl'!$C:$C,$C9) | ... O9: =SUMIFS('i-shopify-sl'!$E:$E,'i-shopify-sl'!$A:$A,O$1,'i-shopify-sl'!$C:$C,$C9) | P9: =SUM(D9:O9) | Q9: ->
A10: IT | C10: IT | D10: =SUMIFS('i-shopify-sl'!$E:$E,'i-shopify-sl'!$A:$A,D$1,'i-shopify-sl'!$C:$C,$C10) | E10: =SUMIFS('i-shopify-sl'!$E:$E,'i-shopify-sl'!$A:$A,E$1,'i-shopify-sl'!$C:$C,$C10) | F10: =SUMIFS('i-shopify-sl'!$E:$E,'i-shopify-sl'!$A:$A,F$1,'i-shopify-sl'!$C:$C,$C10) | G10: =SUMIFS('i-shopify-sl'!$E:$E,'i-shopify-sl'!$A:$A,G$1,'i-shopify-sl'!$C:$C,$C10) | H10: =SUMIFS('i-shopify-sl'!$E:$E,'i-shopify-sl'!$A:$A,H$1,'i-shopify-sl'!$C:$C,$C10) | I10: =SUMIFS('i-shopify-sl'!$E:$E,'i-shopify-sl'!$A:$A,I$1,'i-shopify-sl'!$C:$C,$C10) | J10: =SUMIFS('i-shopify-sl'!$E:$E,'i-shopify-sl'!$A:$A,J$1,'i-shopify-sl'!$C:$C,$C10) | K10: =SUMIFS('i-shopify-sl'!$E:$E,'i-shopify-sl'!$A:$A,K$1,'i-shopify-sl'!$C:$C,$C10) | ... O10: =SUMIFS('i-shopify-sl'!$E:$E,'i-shopify-sl'!$A:$A,O$1,'i-shopify-sl'!$C:$C,$C10) | P10: =SUM(D10:O10) | Q10: ->
A11: AT | C11: AT | D11: =SUMIFS('i-shopify-sl'!$E:$E,'i-shopify-sl'!$A:$A,D$1,'i-shopify-sl'!$C:$C,$C11) | E11: =SUMIFS('i-shopify-sl'!$E:$E,'i-shopify-sl'!$A:$A,E$1,'i-shopify-sl'!$C:$C,$C11) | F11: =SUMIFS('i-shopify-sl'!$E:$E,'i-shopify-sl'!$A:$A,F$1,'i-shopify-sl'!$C:$C,$C11) | G11: =SUMIFS('i-shopify-sl'!$E:$E,'i-shopify-sl'!$A:$A,G$1,'i-shopify-sl'!$C:$C,$C11) | H11: =SUMIFS('i-shopify-sl'!$E:$E,'i-shopify-sl'!$A:$A,H$1,'i-shopify-sl'!$C:$C,$C11) | I11: =SUMIFS('i-shopify-sl'!$E:$E,'i-shopify-sl'!$A:$A,I$1,'i-shopify-sl'!$C:$C,$C11) | J11: =SUMIFS('i-shopify-sl'!$E:$E,'i-shopify-sl'!$A:$A,J$1,'i-shopify-sl'!$C:$C,$C11) | K11: =SUMIFS('i-shopify-sl'!$E:$E,'i-shopify-sl'!$A:$A,K$1,'i-shopify-sl'!$C:$C,$C11) | ... O11: =SUMIFS('i-shopify-sl'!$E:$E,'i-shopify-sl'!$A:$A,O$1,'i-shopify-sl'!$C:$C,$C11) | P11: =SUM(D11:O11) | Q11: ->
A12: BE | C12: BE | D12: =SUMIFS('i-shopify-sl'!$E:$E,'i-shopify-sl'!$A:$A,D$1,'i-shopify-sl'!$C:$C,$C12) | E12: =SUMIFS('i-shopify-sl'!$E:$E,'i-shopify-sl'!$A:$A,E$1,'i-shopify-sl'!$C:$C,$C12) | F12: =SUMIFS('i-shopify-sl'!$E:$E,'i-shopify-sl'!$A:$A,F$1,'i-shopify-sl'!$C:$C,$C12) | G12: =SUMIFS('i-shopify-sl'!$E:$E,'i-shopify-sl'!$A:$A,G$1,'i-shopify-sl'!$C:$C,$C12) | H12: =SUMIFS('i-shopify-sl'!$E:$E,'i-shopify-sl'!$A:$A,H$1,'i-shopify-sl'!$C:$C,$C12) | I12: =SUMIFS('i-shopify-sl'!$E:$E,'i-shopify-sl'!$A:$A,I$1,'i-shopify-sl'!$C:$C,$C12) | J12: =SUMIFS('i-shopify-sl'!$E:$E,'i-shopify-sl'!$A:$A,J$1,'i-shopify-sl'!$C:$C,$C12) | K12: =SUMIFS('i-shopify-sl'!$E:$E,'i-shopify-sl'!$A:$A,K$1,'i-shopify-sl'!$C:$C,$C12) | ... O12: =SUMIFS('i-shopify-sl'!$E:$E,'i-shopify-sl'!$A:$A,O$1,'i-shopify-sl'!$C:$C,$C12) | P12: =SUM(D12:O12) | Q12: ->
A13: NL | C13: NL | D13: =SUMIFS('i-shopify-sl'!$E:$E,'i-shopify-sl'!$A:$A,D$1,'i-shopify-sl'!$C:$C,$C13) | E13: =SUMIFS('i-shopify-sl'!$E:$E,'i-shopify-sl'!$A:$A,E$1,'i-shopify-sl'!$C:$C,$C13) | F13: =SUMIFS('i-shopify-sl'!$E:$E,'i-shopify-sl'!$A:$A,F$1,'i-shopify-sl'!$C:$C,$C13) | G13: =SUMIFS('i-shopify-sl'!$E:$E,'i-shopify-sl'!$A:$A,G$1,'i-shopify-sl'!$C:$C,$C13) | H13: =SUMIFS('i-shopify-sl'!$E:$E,'i-shopify-sl'!$A:$A,H$1,'i-shopify-sl'!$C:$C,$C13) | I13: =SUMIFS('i-shopify-sl'!$E:$E,'i-shopify-sl'!$A:$A,I$1,'i-shopify-sl'!$C:$C,$C13) | J13: =SUMIFS('i-shopify-sl'!$E:$E,'i-shopify-sl'!$A:$A,J$1,'i-shopify-sl'!$C:$C,$C13) | K13: =SUMIFS('i-shopify-sl'!$E:$E,'i-shopify-sl'!$A:$A,K$1,'i-shopify-sl'!$C:$C,$C13) | ... O13: =SUMIFS('i-shopify-sl'!$E:$E,'i-shopify-sl'!$A:$A,O$1,'i-shopify-sl'!$C:$C,$C13) | P13: =SUM(D13:O13) | Q13: ->
A14: PT | C14: PT | D14: =SUMIFS('i-shopify-sl'!$E:$E,'i-shopify-sl'!$A:$A,D$1,'i-shopify-sl'!$C:$C,$C14) | E14: =SUMIFS('i-shopify-sl'!$E:$E,'i-shopify-sl'!$A:$A,E$1,'i-shopify-sl'!$C:$C,$C14) | F14: =SUMIFS('i-shopify-sl'!$E:$E,'i-shopify-sl'!$A:$A,F$1,'i-shopify-sl'!$C:$C,$C14) | G14: =SUMIFS('i-shopify-sl'!$E:$E,'i-shopify-sl'!$A:$A,G$1,'i-shopify-sl'!$C:$C,$C14) | H14: =SUMIFS('i-shopify-sl'!$E:$E,'i-shopify-sl'!$A:$A,H$1,'i-shopify-sl'!$C:$C,$C14) | I14: =SUMIFS('i-shopify-sl'!$E:$E,'i-shopify-sl'!$A:$A,I$1,'i-shopify-sl'!$C:$C,$C14) | J14: =SUMIFS('i-shopify-sl'!$E:$E,'i-shopify-sl'!$A:$A,J$1,'i-shopify-sl'!$C:$C,$C14) | K14: =SUMIFS('i-shopify-sl'!$E:$E,'i-shopify-sl'!$A:$A,K$1,'i-shopify-sl'!$C:$C,$C14) | ... O14: =SUMIFS('i-shopify-sl'!$E:$E,'i-shopify-sl'!$A:$A,O$1,'i-shopify-sl'!$C:$C,$C14) | P14: =SUM(D14:O14) | Q14: ->
A15: XX | C15: XX | D15: =SUMIFS('i-shopify-sl'!$E:$E,'i-shopify-sl'!$A:$A,D$1,'i-shopify-sl'!$C:$C,$C15) | E15: =SUMIFS('i-shopify-sl'!$E:$E,'i-shopify-sl'!$A:$A,E$1,'i-shopify-sl'!$C:$C,$C15) | F15: =SUMIFS('i-shopify-sl'!$E:$E,'i-shopify-sl'!$A:$A,F$1,'i-shopify-sl'!$C:$C,$C15) | G15: =SUMIFS('i-shopify-sl'!$E:$E,'i-shopify-sl'!$A:$A,G$1,'i-shopify-sl'!$C:$C,$C15) | H15: =SUMIFS('i-shopify-sl'!$E:$E,'i-shopify-sl'!$A:$A,H$1,'i-shopify-sl'!$C:$C,$C15) | I15: =SUMIFS('i-shopify-sl'!$E:$E,'i-shopify-sl'!$A:$A,I$1,'i-shopify-sl'!$C:$C,$C15) | J15: =SUMIFS('i-shopify-sl'!$E:$E,'i-shopify-sl'!$A:$A,J$1,'i-shopify-sl'!$C:$C,$C15) | K15: =SUMIFS('i-shopify-sl'!$E:$E,'i-shopify-sl'!$A:$A,K$1,'i-shopify-sl'!$C:$C,$C15) | ... O15: =SUMIFS('i-shopify-sl'!$E:$E,'i-shopify-sl'!$A:$A,O$1,'i-shopify-sl'!$C:$C,$C15) | P15: =SUM(D15:O15) | Q15: ->
A16: Marketplaces | C16: Marketplaces | D16: =SUM(D17:D19) | E16: =SUM(E17:E19) | F16: =SUM(F17:F19) | G16: =SUM(G17:G19) | H16: =SUM(H17:H19) | I16: =SUM(I17:I19) | J16: =SUM(J17:J19) | K16: =SUM(K17:K19) | ... O16: =SUM(O17:O19) | P16: =SUM(D16:O16) | Q16: ->
A17: HANNUN | C17: HANNUN | D17: =SUMIFS('i-marketplaces-sl'!$E:$E,'i-marketplaces-sl'!$A:$A,D$1,'i-marketplaces-sl'!$C:$C,$C17) | E17: =SUMIFS('i-marketplaces-sl'!$E:$E,'i-marketplaces-sl'!$A:$A,E$1,'i-marketplaces-sl'!$C:$C,$C17) | F17: =SUMIFS('i-marketplaces-sl'!$E:$E,'i-marketplaces-sl'!$A:$A,F$1,'i-marketplaces-sl'!$C:$C,$C17) | G17: =SUMIFS('i-marketplaces-sl'!$E:$E,'i-marketplaces-sl'!$A:$A,G$1,'i-marketplaces-sl'!$C:$C,$C17) | H17: =SUMIFS('i-marketplaces-sl'!$E:$E,'i-marketplaces-sl'!$A:$A,H$1,'i-marketplaces-sl'!$C:$C,$C17) | I17: =SUMIFS('i-marketplaces-sl'!$E:$E,'i-marketplaces-sl'!$A:$A,I$1,'i-marketplaces-sl'!$C:$C,$C17) | J17: =SUMIFS('i-marketplaces-sl'!$E:$E,'i-marketplaces-sl'!$A:$A,J$1,'i-marketplaces-sl'!$C:$C,$C17) | K17: =SUMIFS('i-marketplaces-sl'!$E:$E,'i-marketplaces-sl'!$A:$A,K$1,'i-marketplaces-sl'!$C:$C,$C17) | ... O17: =SUMIFS('i-marketplaces-sl'!$E:$E,'i-marketplaces-sl'!$A:$A,O$1,'i-marketplaces-sl'!$C:$C,$C17) | P17: =SUM(D17:O17) | Q17: ->
A18: TOASTY | C18: TOASTY | D18: =SUMIFS('i-marketplaces-sl'!$E:$E,'i-marketplaces-sl'!$A:$A,D$1,'i-marketplaces-sl'!$C:$C,$C18) | E18: =SUMIFS('i-marketplaces-sl'!$E:$E,'i-marketplaces-sl'!$A:$A,E$1,'i-marketplaces-sl'!$C:$C,$C18) | F18: =SUMIFS('i-marketplaces-sl'!$E:$E,'i-marketplaces-sl'!$A:$A,F$1,'i-marketplaces-sl'!$C:$C,$C18) | G18: =SUMIFS('i-marketplaces-sl'!$E:$E,'i-marketplaces-sl'!$A:$A,G$1,'i-marketplaces-sl'!$C:$C,$C18) | H18: =SUMIFS('i-marketplaces-sl'!$E:$E,'i-marketplaces-sl'!$A:$A,H$1,'i-marketplaces-sl'!$C:$C,$C18) | I18: =SUMIFS('i-marketplaces-sl'!$E:$E,'i-marketplaces-sl'!$A:$A,I$1,'i-marketplaces-sl'!$C:$C,$C18) | J18: =SUMIFS('i-marketplaces-sl'!$E:$E,'i-marketplaces-sl'!$A:$A,J$1,'i-marketplaces-sl'!$C:$C,$C18) | K18: =SUMIFS('i-marketplaces-sl'!$E:$E,'i-marketplaces-sl'!$A:$A,K$1,'i-marketplaces-sl'!$C:$C,$C18) | ... O18: =SUMIFS('i-marketplaces-sl'!$E:$E,'i-marketplaces-sl'!$A:$A,O$1,'i-marketplaces-sl'!$C:$C,$C18) | P18: =SUM(D18:O18) | Q18: ->
A19: CHOOSE | C19: CHOOSE | D19: =SUMIFS('i-marketplaces-sl'!$E:$E,'i-marketplaces-sl'!$A:$A,D$1,'i-marketplaces-sl'!$C:$C,$C19) | E19: =SUMIFS('i-marketplaces-sl'!$E:$E,'i-marketplaces-sl'!$A:$A,E$1,'i-marketplaces-sl'!$C:$C,$C19) | F19: =SUMIFS('i-marketplaces-sl'!$E:$E,'i-marketplaces-sl'!$A:$A,F$1,'i-marketplaces-sl'!$C:$C,$C19) | G19: =SUMIFS('i-marketplaces-sl'!$E:$E,'i-marketplaces-sl'!$A:$A,G$1,'i-marketplaces-sl'!$C:$C,$C19) | H19: =SUMIFS('i-marketplaces-sl'!$E:$E,'i-marketplaces-sl'!$A:$A,H$1,'i-marketplaces-sl'!$C:$C,$C19) | I19: =SUMIFS('i-marketplaces-sl'!$E:$E,'i-marketplaces-sl'!$A:$A,I$1,'i-marketplaces-sl'!$C:$C,$C19) | J19: =SUMIFS('i-marketplaces-sl'!$E:$E,'i-marketplaces-sl'!$A:$A,J$1,'i-marketplaces-sl'!$C:$C,$C19) | K19: =SUMIFS('i-marketplaces-sl'!$E:$E,'i-marketplaces-sl'!$A:$A,K$1,'i-marketplaces-sl'!$C:$C,$C19) | ... O19: =SUMIFS('i-marketplaces-sl'!$E:$E,'i-marketplaces-sl'!$A:$A,O$1,'i-marketplaces-sl'!$C:$C,$C19) | P19: =SUM(D19:O19) | Q19: ->
A20: Rappels | C20: Rappels | D20: =D21 | E20: =E21 | F20: =F21 | G20: =G21 | H20: =H21 | I20: =I21 | J20: =J21 | K20: =K21 | ... O20: =O21 | P20: =SUM(D20:O20) | Q20: ->
A21: LIVITUM | C21: LIVITUM | D21: =SUMIFS('i-rappels-sl'!$E:$E,'i-rappels-sl'!$A:$A,D$1,'i-rappels-sl'!$C:$C,$C21) | E21: =SUMIFS('i-rappels-sl'!$E:$E,'i-rappels-sl'!$A:$A,E$1,'i-rappels-sl'!$C:$C,$C21) | F21: =SUMIFS('i-rappels-sl'!$E:$E,'i-rappels-sl'!$A:$A,F$1,'i-rappels-sl'!$C:$C,$C21) | G21: =SUMIFS('i-rappels-sl'!$E:$E,'i-rappels-sl'!$A:$A,G$1,'i-rappels-sl'!$C:$C,$C21) | H21: =SUMIFS('i-rappels-sl'!$E:$E,'i-rappels-sl'!$A:$A,H$1,'i-rappels-sl'!$C:$C,$C21) | I21: =SUMIFS('i-rappels-sl'!$E:$E,'i-rappels-sl'!$A:$A,I$1,'i-rappels-sl'!$C:$C,$C21) | J21: =SUMIFS('i-rappels-sl'!$E:$E,'i-rappels-sl'!$A:$A,J$1,'i-rappels-sl'!$C:$C,$C21) | K21: =SUMIFS('i-rappels-sl'!$E:$E,'i-rappels-sl'!$A:$A,K$1,'i-rappels-sl'!$C:$C,$C21) | ... O21: =SUMIFS('i-rappels-sl'!$E:$E,'i-rappels-sl'!$A:$A,O$1,'i-rappels-sl'!$C:$C,$C21) | P21: =SUM(D21:O21) | Q21: ->
A22: Supplies | C22: Supplies | D22: =D23 | E22: =E23 | F22: =F23 | G22: =G23 | H22: =H23 | I22: =I23 | J22: =J23 | K22: =K23 | ... O22: =O23 | P22: =SUM(D22:O22) | Q22: ->
A23: REVER | C23: REVER | D23: =SUMIFS('i-supplies-sl'!$E:$E,'i-supplies-sl'!$A:$A,D$1,'i-supplies-sl'!$C:$C,$C23) | E23: =SUMIFS('i-supplies-sl'!$E:$E,'i-supplies-sl'!$A:$A,E$1,'i-supplies-sl'!$C:$C,$C23) | F23: =SUMIFS('i-supplies-sl'!$E:$E,'i-supplies-sl'!$A:$A,F$1,'i-supplies-sl'!$C:$C,$C23) | G23: =SUMIFS('i-supplies-sl'!$E:$E,'i-supplies-sl'!$A:$A,G$1,'i-supplies-sl'!$C:$C,$C23) | H23: =SUMIFS('i-supplies-sl'!$E:$E,'i-supplies-sl'!$A:$A,H$1,'i-supplies-sl'!$C:$C,$C23) | I23: =SUMIFS('i-supplies-sl'!$E:$E,'i-supplies-sl'!$A:$A,I$1,'i-supplies-sl'!$C:$C,$C23) | J23: =SUMIFS('i-supplies-sl'!$E:$E,'i-supplies-sl'!$A:$A,J$1,'i-supplies-sl'!$C:$C,$C23) | K23: =SUMIFS('i-supplies-sl'!$E:$E,'i-supplies-sl'!$A:$A,K$1,'i-supplies-sl'!$C:$C,$C23) | ... O23: =SUMIFS('i-supplies-sl'!$E:$E,'i-supplies-sl'!$A:$A,O$1,'i-supplies-sl'!$C:$C,$C23) | P23: =SUM(D23:O23) | Q23: ->
P24: =SUM(D24:O24)
A25: Services | B25: Services | D25: =SUM(D26:D29) | E25: =SUM(E26:E29) | F25: =SUM(F26:F29) | G25: =SUM(G26:G29) | H25: =SUM(H26:H29) | I25: =SUM(I26:I29) | J25: =SUM(J26:J29) | K25: =SUM(K26:K29) | ... O25: =SUM(O26:O29) | P25: =SUM(D25:O25) | Q25: ->
A26: HANNUN | C26: HANNUN | D26: =SUMIFS('i-services-sl'!$E:$E,'i-services-sl'!$A:$A,D$1,'i-services-sl'!$C:$C,$C26) | E26: =SUMIFS('i-services-sl'!$E:$E,'i-services-sl'!$A:$A,E$1,'i-services-sl'!$C:$C,$C26) | F26: =SUMIFS('i-services-sl'!$E:$E,'i-services-sl'!$A:$A,F$1,'i-services-sl'!$C:$C,$C26) | G26: =SUMIFS('i-services-sl'!$E:$E,'i-services-sl'!$A:$A,G$1,'i-services-sl'!$C:$C,$C26) | H26: =SUMIFS('i-services-sl'!$E:$E,'i-services-sl'!$A:$A,H$1,'i-services-sl'!$C:$C,$C26) | I26: =SUMIFS('i-services-sl'!$E:$E,'i-services-sl'!$A:$A,I$1,'i-services-sl'!$C:$C,$C26) | J26: =SUMIFS('i-services-sl'!$E:$E,'i-services-sl'!$A:$A,J$1,'i-services-sl'!$C:$C,$C26) | K26: =SUMIFS('i-services-sl'!$E:$E,'i-services-sl'!$A:$A,K$1,'i-services-sl'!$C:$C,$C26) | ... O26: =SUMIFS('i-services-sl'!$E:$E,'i-services-sl'!$A:$A,O$1,'i-services-sl'!$C:$C,$C26) | P26: =SUM(D26:O26) | Q26: ->
A27: QHANDS | C27: QHANDS | D27: =SUMIFS('i-services-sl'!$E:$E,'i-services-sl'!$A:$A,D$1,'i-services-sl'!$C:$C,$C27) | E27: =SUMIFS('i-services-sl'!$E:$E,'i-services-sl'!$A:$A,E$1,'i-services-sl'!$C:$C,$C27) | F27: =SUMIFS('i-services-sl'!$E:$E,'i-services-sl'!$A:$A,F$1,'i-services-sl'!$C:$C,$C27) | G27: =SUMIFS('i-services-sl'!$E:$E,'i-services-sl'!$A:$A,G$1,'i-services-sl'!$C:$C,$C27) | H27: =SUMIFS('i-services-sl'!$E:$E,'i-services-sl'!$A:$A,H$1,'i-services-sl'!$C:$C,$C27) | I27: =SUMIFS('i-services-sl'!$E:$E,'i-services-sl'!$A:$A,I$1,'i-services-sl'!$C:$C,$C27) | J27: =SUMIFS('i-services-sl'!$E:$E,'i-services-sl'!$A:$A,J$1,'i-services-sl'!$C:$C,$C27) | K27: =SUMIFS('i-services-sl'!$E:$E,'i-services-sl'!$A:$A,K$1,'i-services-sl'!$C:$C,$C27) | ... O27: =SUMIFS('i-services-sl'!$E:$E,'i-services-sl'!$A:$A,O$1,'i-services-sl'!$C:$C,$C27) | P27: =SUM(D27:O27) | Q27: ->
A28: Ltd | C28: Ltd | D28: =SUMIFS('i-services-sl'!$E:$E,'i-services-sl'!$A:$A,D$1,'i-services-sl'!$C:$C,$C28) | E28: =SUMIFS('i-services-sl'!$E:$E,'i-services-sl'!$A:$A,E$1,'i-services-sl'!$C:$C,$C28) | F28: =SUMIFS('i-services-sl'!$E:$E,'i-services-sl'!$A:$A,F$1,'i-services-sl'!$C:$C,$C28) | G28: =SUMIFS('i-services-sl'!$E:$E,'i-services-sl'!$A:$A,G$1,'i-services-sl'!$C:$C,$C28) | H28: =SUMIFS('i-services-sl'!$E:$E,'i-services-sl'!$A:$A,H$1,'i-services-sl'!$C:$C,$C28) | I28: =SUMIFS('i-services-sl'!$E:$E,'i-services-sl'!$A:$A,I$1,'i-services-sl'!$C:$C,$C28) | J28: =SUMIFS('i-services-sl'!$E:$E,'i-services-sl'!$A:$A,J$1,'i-services-sl'!$C:$C,$C28) | K28: =SUMIFS('i-services-sl'!$E:$E,'i-services-sl'!$A:$A,K$1,'i-services-sl'!$C:$C,$C28) | ... O28: =SUMIFS('i-services-sl'!$E:$E,'i-services-sl'!$A:$A,O$1,'i-services-sl'!$C:$C,$C28) | P28: =SUM(D28:O28) | Q28: ->
A29: Inc | C29: Inc | D29: =SUMIFS('i-services-sl'!$E:$E,'i-services-sl'!$A:$A,D$1,'i-services-sl'!$C:$C,$C29) | E29: =SUMIFS('i-services-sl'!$E:$E,'i-services-sl'!$A:$A,E$1,'i-services-sl'!$C:$C,$C29) | F29: =SUMIFS('i-services-sl'!$E:$E,'i-services-sl'!$A:$A,F$1,'i-services-sl'!$C:$C,$C29) | G29: =SUMIFS('i-services-sl'!$E:$E,'i-services-sl'!$A:$A,G$1,'i-services-sl'!$C:$C,$C29) | H29: =SUMIFS('i-services-sl'!$E:$E,'i-services-sl'!$A:$A,H$1,'i-services-sl'!$C:$C,$C29) | I29: =SUMIFS('i-services-sl'!$E:$E,'i-services-sl'!$A:$A,I$1,'i-services-sl'!$C:$C,$C29) | J29: =SUMIFS('i-services-sl'!$E:$E,'i-services-sl'!$A:$A,J$1,'i-services-sl'!$C:$C,$C29) | K29: =SUMIFS('i-services-sl'!$E:$E,'i-services-sl'!$A:$A,K$1,'i-services-sl'!$C:$C,$C29) | ... O29: =SUMIFS('i-services-sl'!$E:$E,'i-services-sl'!$A:$A,O$1,'i-services-sl'!$C:$C,$C29) | P29: =SUM(D29:O29) | Q29: ->
P30: =SUM(D30:O30)
A31: Expenses | D31: =D32+D60 | E31: =E32+E60 | F31: =F32+F60 | G31: =G32+G60 | H31: =H32+H60 | I31: =I32+I60 | J31: =J32+J60 | K31: =K32+K60 | ... O31: =O32+O60 | P31: =SUM(D31:O31)
A32: COGS | B32: COGS | D32: =D33+D40+D47+D50 | E32: =E33+E40+E47+E50 | F32: =F33+F40+F47+F50 | G32: =G33+G40+G47+G50 | H32: =H33+H40+H47+H50 | I32: =I33+I40+I47+I50 | J32: =J33+J40+J47+J50 | K32: =K33+K40+K47+K50 | ... O32: =O33+O40+O47+O50 | P32: =SUM(D32:O32)
A33: Manufacturing (% sales) | C33: Manufacturing (% sales) | D33: =SUM(D34:D38) | E33: =SUM(E34:E38) | F33: =SUM(F34:F38) | G33: =SUM(G34:G38) | H33: =SUM(H34:H38) | I33: =SUM(I34:I38) | J33: =SUM(J34:J38) | K33: =SUM(K34:K38) | ... O33: =SUM(O34:O38) | P33: =SUM(D33:O33) | Q33: ->
A34: APPHOTOCAN | C34: APPHOTOCAN | D34: =SUMIFS('g-expenses-sl'!$G:$G,'g-expenses-sl'!$A:$A,D$1,'g-expenses-sl'!$D:$D,"manufacturing",'g-expenses-sl'!$E:$E,$C34) | E34: =SUMIFS('g-expenses-sl'!$G:$G,'g-expenses-sl'!$A:$A,E$1,'g-expenses-sl'!$D:$D,"manufacturing",'g-expenses-sl'!$E:$E,$C34) | F34: =SUMIFS('g-expenses-sl'!$G:$G,'g-expenses-sl'!$A:$A,F$1,'g-expenses-sl'!$D:$D,"manufacturing",'g-expenses-sl'!$E:$E,$C34) | G34: =SUMIFS('g-expenses-sl'!$G:$G,'g-expenses-sl'!$A:$A,G$1,'g-expenses-sl'!$D:$D,"manufacturing",'g-expenses-sl'!$E:$E,$C34) | H34: =SUMIFS('g-expenses-sl'!$G:$G,'g-expenses-sl'!$A:$A,H$1,'g-expenses-sl'!$D:$D,"manufacturing",'g-expenses-sl'!$E:$E,$C34) | I34: =SUMIFS('g-expenses-sl'!$G:$G,'g-expenses-sl'!$A:$A,I$1,'g-expenses-sl'!$D:$D,"manufacturing",'g-expenses-sl'!$E:$E,$C34) | J34: =SUMIFS('g-expenses-sl'!$G:$G,'g-expenses-sl'!$A:$A,J$1,'g-expenses-sl'!$D:$D,"manufacturing",'g-expenses-sl'!$E:$E,$C34) | K34: =SUMIFS('g-expenses-sl'!$G:$G,'g-expenses-sl'!$A:$A,K$1,'g-expenses-sl'!$D:$D,"manufacturing",'g-expenses-sl'!$E:$E,$C34) | ... O34: =SUMIFS('g-expenses-sl'!$G:$G,'g-expenses-sl'!$A:$A,O$1,'g-expenses-sl'!$D:$D,"manufacturing",'g-expenses-sl'!$E:$E,$C34) | P34: =SUM(D34:O34) | Q34: ->
A35: APPHOTOES | C35: APPHOTOES | D35: =SUMIFS('g-expenses-sl'!$G:$G,'g-expenses-sl'!$A:$A,D$1,'g-expenses-sl'!$D:$D,"manufacturing",'g-expenses-sl'!$E:$E,$C35) | E35: =SUMIFS('g-expenses-sl'!$G:$G,'g-expenses-sl'!$A:$A,E$1,'g-expenses-sl'!$D:$D,"manufacturing",'g-expenses-sl'!$E:$E,$C35) | F35: =SUMIFS('g-expenses-sl'!$G:$G,'g-expenses-sl'!$A:$A,F$1,'g-expenses-sl'!$D:$D,"manufacturing",'g-expenses-sl'!$E:$E,$C35) | G35: =SUMIFS('g-expenses-sl'!$G:$G,'g-expenses-sl'!$A:$A,G$1,'g-expenses-sl'!$D:$D,"manufacturing",'g-expenses-sl'!$E:$E,$C35) | H35: =SUMIFS('g-expenses-sl'!$G:$G,'g-expenses-sl'!$A:$A,H$1,'g-expenses-sl'!$D:$D,"manufacturing",'g-expenses-sl'!$E:$E,$C35) | I35: =SUMIFS('g-expenses-sl'!$G:$G,'g-expenses-sl'!$A:$A,I$1,'g-expenses-sl'!$D:$D,"manufacturing",'g-expenses-sl'!$E:$E,$C35) | J35: =SUMIFS('g-expenses-sl'!$G:$G,'g-expenses-sl'!$A:$A,J$1,'g-expenses-sl'!$D:$D,"manufacturing",'g-expenses-sl'!$E:$E,$C35) | K35: =SUMIFS('g-expenses-sl'!$G:$G,'g-expenses-sl'!$A:$A,K$1,'g-expenses-sl'!$D:$D,"manufacturing",'g-expenses-sl'!$E:$E,$C35) | ... O35: =SUMIFS('g-expenses-sl'!$G:$G,'g-expenses-sl'!$A:$A,O$1,'g-expenses-sl'!$D:$D,"manufacturing",'g-expenses-sl'!$E:$E,$C35) | P35: =SUM(D35:O35) | Q35: ->
A36: ARTLINK | C36: ARTLINK | D36: =SUMIFS('g-expenses-sl'!$G:$G,'g-expenses-sl'!$A:$A,D$1,'g-expenses-sl'!$D:$D,"manufacturing",'g-expenses-sl'!$E:$E,$C36) | E36: =SUMIFS('g-expenses-sl'!$G:$G,'g-expenses-sl'!$A:$A,E$1,'g-expenses-sl'!$D:$D,"manufacturing",'g-expenses-sl'!$E:$E,$C36) | F36: =SUMIFS('g-expenses-sl'!$G:$G,'g-expenses-sl'!$A:$A,F$1,'g-expenses-sl'!$D:$D,"manufacturing",'g-expenses-sl'!$E:$E,$C36) | G36: =SUMIFS('g-expenses-sl'!$G:$G,'g-expenses-sl'!$A:$A,G$1,'g-expenses-sl'!$D:$D,"manufacturing",'g-expenses-sl'!$E:$E,$C36) | H36: =SUMIFS('g-expenses-sl'!$G:$G,'g-expenses-sl'!$A:$A,H$1,'g-expenses-sl'!$D:$D,"manufacturing",'g-expenses-sl'!$E:$E,$C36) | I36: =SUMIFS('g-expenses-sl'!$G:$G,'g-expenses-sl'!$A:$A,I$1,'g-expenses-sl'!$D:$D,"manufacturing",'g-expenses-sl'!$E:$E,$C36) | J36: =SUMIFS('g-expenses-sl'!$G:$G,'g-expenses-sl'!$A:$A,J$1,'g-expenses-sl'!$D:$D,"manufacturing",'g-expenses-sl'!$E:$E,$C36) | K36: =SUMIFS('g-expenses-sl'!$G:$G,'g-expenses-sl'!$A:$A,K$1,'g-expenses-sl'!$D:$D,"manufacturing",'g-expenses-sl'!$E:$E,$C36) | ... O36: =SUMIFS('g-expenses-sl'!$G:$G,'g-expenses-sl'!$A:$A,O$1,'g-expenses-sl'!$D:$D,"manufacturing",'g-expenses-sl'!$E:$E,$C36) | P36: =SUM(D36:O36) | Q36: ->
A37: DCT | C37: DCT | D37: =SUMIFS('g-expenses-sl'!$G:$G,'g-expenses-sl'!$A:$A,D$1,'g-expenses-sl'!$D:$D,"manufacturing",'g-expenses-sl'!$E:$E,$C37) | E37: =SUMIFS('g-expenses-sl'!$G:$G,'g-expenses-sl'!$A:$A,E$1,'g-expenses-sl'!$D:$D,"manufacturing",'g-expenses-sl'!$E:$E,$C37) | F37: =SUMIFS('g-expenses-sl'!$G:$G,'g-expenses-sl'!$A:$A,F$1,'g-expenses-sl'!$D:$D,"manufacturing",'g-expenses-sl'!$E:$E,$C37) | G37: =SUMIFS('g-expenses-sl'!$G:$G,'g-expenses-sl'!$A:$A,G$1,'g-expenses-sl'!$D:$D,"manufacturing",'g-expenses-sl'!$E:$E,$C37) | H37: =SUMIFS('g-expenses-sl'!$G:$G,'g-expenses-sl'!$A:$A,H$1,'g-expenses-sl'!$D:$D,"manufacturing",'g-expenses-sl'!$E:$E,$C37) | I37: =SUMIFS('g-expenses-sl'!$G:$G,'g-expenses-sl'!$A:$A,I$1,'g-expenses-sl'!$D:$D,"manufacturing",'g-expenses-sl'!$E:$E,$C37) | J37: =SUMIFS('g-expenses-sl'!$G:$G,'g-expenses-sl'!$A:$A,J$1,'g-expenses-sl'!$D:$D,"manufacturing",'g-expenses-sl'!$E:$E,$C37) | K37: =SUMIFS('g-expenses-sl'!$G:$G,'g-expenses-sl'!$A:$A,K$1,'g-expenses-sl'!$D:$D,"manufacturing",'g-expenses-sl'!$E:$E,$C37) | ... O37: =SUMIFS('g-expenses-sl'!$G:$G,'g-expenses-sl'!$A:$A,O$1,'g-expenses-sl'!$D:$D,"manufacturing",'g-expenses-sl'!$E:$E,$C37) | P37: =SUM(D37:O37) | Q37: ->
A38: PRESSING | C38: PRESSING | D38: =SUMIFS('g-expenses-sl'!$G:$G,'g-expenses-sl'!$A:$A,D$1,'g-expenses-sl'!$D:$D,"manufacturing",'g-expenses-sl'!$E:$E,$C38) | E38: =SUMIFS('g-expenses-sl'!$G:$G,'g-expenses-sl'!$A:$A,E$1,'g-expenses-sl'!$D:$D,"manufacturing",'g-expenses-sl'!$E:$E,$C38) | F38: =SUMIFS('g-expenses-sl'!$G:$G,'g-expenses-sl'!$A:$A,F$1,'g-expenses-sl'!$D:$D,"manufacturing",'g-expenses-sl'!$E:$E,$C38) | G38: =SUMIFS('g-expenses-sl'!$G:$G,'g-expenses-sl'!$A:$A,G$1,'g-expenses-sl'!$D:$D,"manufacturing",'g-expenses-sl'!$E:$E,$C38) | H38: =SUMIFS('g-expenses-sl'!$G:$G,'g-expenses-sl'!$A:$A,H$1,'g-expenses-sl'!$D:$D,"manufacturing",'g-expenses-sl'!$E:$E,$C38) | I38: =SUMIFS('g-expenses-sl'!$G:$G,'g-expenses-sl'!$A:$A,I$1,'g-expenses-sl'!$D:$D,"manufacturing",'g-expenses-sl'!$E:$E,$C38) | J38: =SUMIFS('g-expenses-sl'!$G:$G,'g-expenses-sl'!$A:$A,J$1,'g-expenses-sl'!$D:$D,"manufacturing",'g-expenses-sl'!$E:$E,$C38) | K38: =SUMIFS('g-expenses-sl'!$G:$G,'g-expenses-sl'!$A:$A,K$1,'g-expenses-sl'!$D:$D,"manufacturing",'g-expenses-sl'!$E:$E,$C38) | ... O38: =SUMIFS('g-expenses-sl'!$G:$G,'g-expenses-sl'!$A:$A,O$1,'g-expenses-sl'!$D:$D,"manufacturing",'g-expenses-sl'!$E:$E,$C38) | P38: =SUM(D38:O38) | Q38: ->
A39: % Manufacturing / sales | C39: % Manufacturing / sales | D39: =IFERROR(D33/D5,0) | E39: =IFERROR(E33/E5,0) | F39: =IFERROR(F33/F5,0) | G39: =IFERROR(G33/G5,0) | H39: =IFERROR(H33/H5,0) | I39: =IFERROR(I33/I5,0) | J39: =IFERROR(J33/J5,0) | K39: =IFERROR(K33/K5,0) | ... O39: =IFERROR(O33/O5,0) | P39: =SUM(D39:O39)
A40: Logistics (% sales) | C40: Logistics (% sales) | D40: =SUM(D41:D45) | E40: =SUM(E41:E45) | F40: =SUM(F41:F45) | G40: =SUM(G41:G45) | H40: =SUM(H41:H45) | I40: =SUM(I41:I45) | J40: =SUM(J41:J45) | K40: =SUM(K41:K45) | ... O40: =SUM(O41:O45) | P40: =SUM(D40:O40) | Q40: ->
A41: CORREOS | C41: CORREOS | D41: =SUMIFS('g-expenses-sl'!$G:$G,'g-expenses-sl'!$A:$A,D$1,'g-expenses-sl'!$D:$D,"logistics",'g-expenses-sl'!$E:$E,$C41) | E41: =SUMIFS('g-expenses-sl'!$G:$G,'g-expenses-sl'!$A:$A,E$1,'g-expenses-sl'!$D:$D,"logistics",'g-expenses-sl'!$E:$E,$C41) | F41: =SUMIFS('g-expenses-sl'!$G:$G,'g-expenses-sl'!$A:$A,F$1,'g-expenses-sl'!$D:$D,"logistics",'g-expenses-sl'!$E:$E,$C41) | G41: =SUMIFS('g-expenses-sl'!$G:$G,'g-expenses-sl'!$A:$A,G$1,'g-expenses-sl'!$D:$D,"logistics",'g-expenses-sl'!$E:$E,$C41) | H41: =SUMIFS('g-expenses-sl'!$G:$G,'g-expenses-sl'!$A:$A,H$1,'g-expenses-sl'!$D:$D,"logistics",'g-expenses-sl'!$E:$E,$C41) | I41: =SUMIFS('g-expenses-sl'!$G:$G,'g-expenses-sl'!$A:$A,I$1,'g-expenses-sl'!$D:$D,"logistics",'g-expenses-sl'!$E:$E,$C41) | J41: =SUMIFS('g-expenses-sl'!$G:$G,'g-expenses-sl'!$A:$A,J$1,'g-expenses-sl'!$D:$D,"logistics",'g-expenses-sl'!$E:$E,$C41) | K41: =SUMIFS('g-expenses-sl'!$G:$G,'g-expenses-sl'!$A:$A,K$1,'g-expenses-sl'!$D:$D,"logistics",'g-expenses-sl'!$E:$E,$C41) | ... O41: =SUMIFS('g-expenses-sl'!$G:$G,'g-expenses-sl'!$A:$A,O$1,'g-expenses-sl'!$D:$D,"logistics",'g-expenses-sl'!$E:$E,$C41) | P41: =SUM(D41:O41) | Q41: ->
A42: CORREOSCAN | C42: CORREOSCAN | D42: =SUMIFS('g-expenses-sl'!$G:$G,'g-expenses-sl'!$A:$A,D$1,'g-expenses-sl'!$D:$D,"logistics",'g-expenses-sl'!$E:$E,$C42) | E42: =SUMIFS('g-expenses-sl'!$G:$G,'g-expenses-sl'!$A:$A,E$1,'g-expenses-sl'!$D:$D,"logistics",'g-expenses-sl'!$E:$E,$C42) | F42: =SUMIFS('g-expenses-sl'!$G:$G,'g-expenses-sl'!$A:$A,F$1,'g-expenses-sl'!$D:$D,"logistics",'g-expenses-sl'!$E:$E,$C42) | G42: =SUMIFS('g-expenses-sl'!$G:$G,'g-expenses-sl'!$A:$A,G$1,'g-expenses-sl'!$D:$D,"logistics",'g-expenses-sl'!$E:$E,$C42) | H42: =SUMIFS('g-expenses-sl'!$G:$G,'g-expenses-sl'!$A:$A,H$1,'g-expenses-sl'!$D:$D,"logistics",'g-expenses-sl'!$E:$E,$C42) | I42: =SUMIFS('g-expenses-sl'!$G:$G,'g-expenses-sl'!$A:$A,I$1,'g-expenses-sl'!$D:$D,"logistics",'g-expenses-sl'!$E:$E,$C42) | J42: =SUMIFS('g-expenses-sl'!$G:$G,'g-expenses-sl'!$A:$A,J$1,'g-expenses-sl'!$D:$D,"logistics",'g-expenses-sl'!$E:$E,$C42) | K42: =SUMIFS('g-expenses-sl'!$G:$G,'g-expenses-sl'!$A:$A,K$1,'g-expenses-sl'!$D:$D,"logistics",'g-expenses-sl'!$E:$E,$C42) | ... O42: =SUMIFS('g-expenses-sl'!$G:$G,'g-expenses-sl'!$A:$A,O$1,'g-expenses-sl'!$D:$D,"logistics",'g-expenses-sl'!$E:$E,$C42) | P42: =SUM(D42:O42) | Q42: ->
A43: GLS | C43: GLS | D43: =SUMIFS('g-expenses-sl'!$G:$G,'g-expenses-sl'!$A:$A,D$1,'g-expenses-sl'!$D:$D,"logistics",'g-expenses-sl'!$E:$E,$C43) | E43: =SUMIFS('g-expenses-sl'!$G:$G,'g-expenses-sl'!$A:$A,E$1,'g-expenses-sl'!$D:$D,"logistics",'g-expenses-sl'!$E:$E,$C43) | F43: =SUMIFS('g-expenses-sl'!$G:$G,'g-expenses-sl'!$A:$A,F$1,'g-expenses-sl'!$D:$D,"logistics",'g-expenses-sl'!$E:$E,$C43) | G43: =SUMIFS('g-expenses-sl'!$G:$G,'g-expenses-sl'!$A:$A,G$1,'g-expenses-sl'!$D:$D,"logistics",'g-expenses-sl'!$E:$E,$C43) | H43: =SUMIFS('g-expenses-sl'!$G:$G,'g-expenses-sl'!$A:$A,H$1,'g-expenses-sl'!$D:$D,"logistics",'g-expenses-sl'!$E:$E,$C43) | I43: =SUMIFS('g-expenses-sl'!$G:$G,'g-expenses-sl'!$A:$A,I$1,'g-expenses-sl'!$D:$D,"logistics",'g-expenses-sl'!$E:$E,$C43) | J43: =SUMIFS('g-expenses-sl'!$G:$G,'g-expenses-sl'!$A:$A,J$1,'g-expenses-sl'!$D:$D,"logistics",'g-expenses-sl'!$E:$E,$C43) | K43: =SUMIFS('g-expenses-sl'!$G:$G,'g-expenses-sl'!$A:$A,K$1,'g-expenses-sl'!$D:$D,"logistics",'g-expenses-sl'!$E:$E,$C43) | ... O43: =SUMIFS('g-expenses-sl'!$G:$G,'g-expenses-sl'!$A:$A,O$1,'g-expenses-sl'!$D:$D,"logistics",'g-expenses-sl'!$E:$E,$C43) | P43: =SUM(D43:O43) | Q43: ->
A44: SPRINGGDS | C44: SPRINGGDS | D44: =SUMIFS('g-expenses-sl'!$G:$G,'g-expenses-sl'!$A:$A,D$1,'g-expenses-sl'!$D:$D,"logistics",'g-expenses-sl'!$E:$E,$C44) | E44: =SUMIFS('g-expenses-sl'!$G:$G,'g-expenses-sl'!$A:$A,E$1,'g-expenses-sl'!$D:$D,"logistics",'g-expenses-sl'!$E:$E,$C44) | F44: =SUMIFS('g-expenses-sl'!$G:$G,'g-expenses-sl'!$A:$A,F$1,'g-expenses-sl'!$D:$D,"logistics",'g-expenses-sl'!$E:$E,$C44) | G44: =SUMIFS('g-expenses-sl'!$G:$G,'g-expenses-sl'!$A:$A,G$1,'g-expenses-sl'!$D:$D,"logistics",'g-expenses-sl'!$E:$E,$C44) | H44: =SUMIFS('g-expenses-sl'!$G:$G,'g-expenses-sl'!$A:$A,H$1,'g-expenses-sl'!$D:$D,"logistics",'g-expenses-sl'!$E:$E,$C44) | I44: =SUMIFS('g-expenses-sl'!$G:$G,'g-expenses-sl'!$A:$A,I$1,'g-expenses-sl'!$D:$D,"logistics",'g-expenses-sl'!$E:$E,$C44) | J44: =SUMIFS('g-expenses-sl'!$G:$G,'g-expenses-sl'!$A:$A,J$1,'g-expenses-sl'!$D:$D,"logistics",'g-expenses-sl'!$E:$E,$C44) | K44: =SUMIFS('g-expenses-sl'!$G:$G,'g-expenses-sl'!$A:$A,K$1,'g-expenses-sl'!$D:$D,"logistics",'g-expenses-sl'!$E:$E,$C44) | ... O44: =SUMIFS('g-expenses-sl'!$G:$G,'g-expenses-sl'!$A:$A,O$1,'g-expenses-sl'!$D:$D,"logistics",'g-expenses-sl'!$E:$E,$C44) | P44: =SUM(D44:O44) | Q44: ->
A45: UPS | C45: UPS | D45: =SUMIFS('g-expenses-sl'!$G:$G,'g-expenses-sl'!$A:$A,D$1,'g-expenses-sl'!$D:$D,"logistics",'g-expenses-sl'!$E:$E,$C45) | E45: =SUMIFS('g-expenses-sl'!$G:$G,'g-expenses-sl'!$A:$A,E$1,'g-expenses-sl'!$D:$D,"logistics",'g-expenses-sl'!$E:$E,$C45) | F45: =SUMIFS('g-expenses-sl'!$G:$G,'g-expenses-sl'!$A:$A,F$1,'g-expenses-sl'!$D:$D,"logistics",'g-expenses-sl'!$E:$E,$C45) | G45: =SUMIFS('g-expenses-sl'!$G:$G,'g-expenses-sl'!$A:$A,G$1,'g-expenses-sl'!$D:$D,"logistics",'g-expenses-sl'!$E:$E,$C45) | H45: =SUMIFS('g-expenses-sl'!$G:$G,'g-expenses-sl'!$A:$A,H$1,'g-expenses-sl'!$D:$D,"logistics",'g-expenses-sl'!$E:$E,$C45) | I45: =SUMIFS('g-expenses-sl'!$G:$G,'g-expenses-sl'!$A:$A,I$1,'g-expenses-sl'!$D:$D,"logistics",'g-expenses-sl'!$E:$E,$C45) | J45: =SUMIFS('g-expenses-sl'!$G:$G,'g-expenses-sl'!$A:$A,J$1,'g-expenses-sl'!$D:$D,"logistics",'g-expenses-sl'!$E:$E,$C45) | K45: =SUMIFS('g-expenses-sl'!$G:$G,'g-expenses-sl'!$A:$A,K$1,'g-expenses-sl'!$D:$D,"logistics",'g-expenses-sl'!$E:$E,$C45) | ... O45: =SUMIFS('g-expenses-sl'!$G:$G,'g-expenses-sl'!$A:$A,O$1,'g-expenses-sl'!$D:$D,"logistics",'g-expenses-sl'!$E:$E,$C45) | P45: =SUM(D45:O45) | Q45: ->
A46: % Logistics / sales | C46: % Logistics / sales | D46: =IFERROR(D40/D5,0) | E46: =IFERROR(E40/E5,0) | F46: =IFERROR(F40/F5,0) | G46: =IFERROR(G40/G5,0) | H46: =IFERROR(H40/H5,0) | I46: =IFERROR(I40/I5,0) | J46: =IFERROR(J40/J5,0) | K46: =IFERROR(K40/K5,0) | ... O46: =IFERROR(O40/O5,0) | P46: =SUM(D46:O46)
A47: Royalties (% sales) | C47: Royalties (% sales) | D47: =D48 | E47: =E48 | F47: =F48 | G47: =G48 | H47: =H48 | I47: =I48 | J47: =J48 | K47: =K48 | ... O47: =O48 | P47: =SUM(D47:O47) | Q47: ->
A48: ROYALTIES | C48: ROYALTIES | D48: =SUMIFS('g-expenses-sl'!$G:$G,'g-expenses-sl'!$A:$A,D$1,'g-expenses-sl'!$D:$D,"royalties",'g-expenses-sl'!$E:$E,$C48) | E48: =SUMIFS('g-expenses-sl'!$G:$G,'g-expenses-sl'!$A:$A,E$1,'g-expenses-sl'!$D:$D,"royalties",'g-expenses-sl'!$E:$E,$C48) | F48: =SUMIFS('g-expenses-sl'!$G:$G,'g-expenses-sl'!$A:$A,F$1,'g-expenses-sl'!$D:$D,"royalties",'g-expenses-sl'!$E:$E,$C48) | G48: =SUMIFS('g-expenses-sl'!$G:$G,'g-expenses-sl'!$A:$A,G$1,'g-expenses-sl'!$D:$D,"royalties",'g-expenses-sl'!$E:$E,$C48) | H48: =SUMIFS('g-expenses-sl'!$G:$G,'g-expenses-sl'!$A:$A,H$1,'g-expenses-sl'!$D:$D,"royalties",'g-expenses-sl'!$E:$E,$C48) | I48: =SUMIFS('g-expenses-sl'!$G:$G,'g-expenses-sl'!$A:$A,I$1,'g-expenses-sl'!$D:$D,"royalties",'g-expenses-sl'!$E:$E,$C48) | J48: =SUMIFS('g-expenses-sl'!$G:$G,'g-expenses-sl'!$A:$A,J$1,'g-expenses-sl'!$D:$D,"royalties",'g-expenses-sl'!$E:$E,$C48) | K48: =SUMIFS('g-expenses-sl'!$G:$G,'g-expenses-sl'!$A:$A,K$1,'g-expenses-sl'!$D:$D,"royalties",'g-expenses-sl'!$E:$E,$C48) | ... O48: =SUMIFS('g-expenses-sl'!$G:$G,'g-expenses-sl'!$A:$A,O$1,'g-expenses-sl'!$D:$D,"royalties",'g-expenses-sl'!$E:$E,$C48) | P48: =SUM(D48:O48) | Q48: ->
A49: % Royalties / sales | C49: % Royalties / sales | D49: =IFERROR(D47/D5,0) | E49: =IFERROR(E47/E5,0) | F49: =IFERROR(F47/F5,0) | G49: =IFERROR(G47/G5,0) | H49: =IFERROR(H47/H5,0) | I49: =IFERROR(I47/I5,0) | J49: =IFERROR(J47/J5,0) | K49: =IFERROR(K47/K5,0) | ... O49: =IFERROR(O47/O5,0) | P49: =SUM(D49:O49)
A50: Payment fees (% sales) | C50: Payment fees (% sales) | D50: =SUM(D51:D52) | E50: =SUM(E51:E52) | F50: =SUM(F51:F52) | G50: =SUM(G51:G52) | H50: =SUM(H51:H52) | I50: =SUM(I51:I52) | J50: =SUM(J51:J52) | K50: =SUM(K51:K52) | ... O50: =SUM(O51:O52) | P50: =SUM(D50:O50) | Q50: ->
A51: SHOPIFY | C51: SHOPIFY | D51: =SUMIFS('g-payment-fees-sl'!$D:$D,'g-payment-fees-sl'!$A:$A,D$1,'g-payment-fees-sl'!$C:$C,$C51) | E51: =SUMIFS('g-payment-fees-sl'!$D:$D,'g-payment-fees-sl'!$A:$A,E$1,'g-payment-fees-sl'!$C:$C,$C51) | F51: =SUMIFS('g-payment-fees-sl'!$D:$D,'g-payment-fees-sl'!$A:$A,F$1,'g-payment-fees-sl'!$C:$C,$C51) | G51: =SUMIFS('g-payment-fees-sl'!$D:$D,'g-payment-fees-sl'!$A:$A,G$1,'g-payment-fees-sl'!$C:$C,$C51) | H51: =SUMIFS('g-payment-fees-sl'!$D:$D,'g-payment-fees-sl'!$A:$A,H$1,'g-payment-fees-sl'!$C:$C,$C51) | I51: =SUMIFS('g-payment-fees-sl'!$D:$D,'g-payment-fees-sl'!$A:$A,I$1,'g-payment-fees-sl'!$C:$C,$C51) | J51: =SUMIFS('g-payment-fees-sl'!$D:$D,'g-payment-fees-sl'!$A:$A,J$1,'g-payment-fees-sl'!$C:$C,$C51) | K51: =SUMIFS('g-payment-fees-sl'!$D:$D,'g-payment-fees-sl'!$A:$A,K$1,'g-payment-fees-sl'!$C:$C,$C51) | ... O51: =SUMIFS('g-payment-fees-sl'!$D:$D,'g-payment-fees-sl'!$A:$A,O$1,'g-payment-fees-sl'!$C:$C,$C51) | P51: =SUM(D51:O51) | Q51: ->
A52: PAYPAL | C52: PAYPAL | D52: =SUMIFS('g-payment-fees-sl'!$D:$D,'g-payment-fees-sl'!$A:$A,D$1,'g-payment-fees-sl'!$C:$C,$C52) | E52: =SUMIFS('g-payment-fees-sl'!$D:$D,'g-payment-fees-sl'!$A:$A,E$1,'g-payment-fees-sl'!$C:$C,$C52) | F52: =SUMIFS('g-payment-fees-sl'!$D:$D,'g-payment-fees-sl'!$A:$A,F$1,'g-payment-fees-sl'!$C:$C,$C52) | G52: =SUMIFS('g-payment-fees-sl'!$D:$D,'g-payment-fees-sl'!$A:$A,G$1,'g-payment-fees-sl'!$C:$C,$C52) | H52: =SUMIFS('g-payment-fees-sl'!$D:$D,'g-payment-fees-sl'!$A:$A,H$1,'g-payment-fees-sl'!$C:$C,$C52) | I52: =SUMIFS('g-payment-fees-sl'!$D:$D,'g-payment-fees-sl'!$A:$A,I$1,'g-payment-fees-sl'!$C:$C,$C52) | J52: =SUMIFS('g-payment-fees-sl'!$D:$D,'g-payment-fees-sl'!$A:$A,J$1,'g-payment-fees-sl'!$C:$C,$C52) | K52: =SUMIFS('g-payment-fees-sl'!$D:$D,'g-payment-fees-sl'!$A:$A,K$1,'g-payment-fees-sl'!$C:$C,$C52) | ... O52: =SUMIFS('g-payment-fees-sl'!$D:$D,'g-payment-fees-sl'!$A:$A,O$1,'g-payment-fees-sl'!$C:$C,$C52) | P52: =SUM(D52:O52) | Q52: ->
A53: % Payment fees / sales | C53: % Payment fees / sales | D53: =IFERROR(D50/D5,0) | E53: =IFERROR(E50/E5,0) | F53: =IFERROR(F50/F5,0) | G53: =IFERROR(G50/G5,0) | H53: =IFERROR(H50/H5,0) | I53: =IFERROR(I50/I5,0) | J53: =IFERROR(J50/J5,0) | K53: =IFERROR(K50/K5,0) | ... O53: =IFERROR(O50/O5,0) | P53: =SUM(D53:O53)
P54: =SUM(D54:O54)
A55: GROSS MARGIN (SALES-MANUFACTURING) | D55: =D5-D33 | E55: =E5-E33 | F55: =F5-F33 | G55: =G5-G33 | H55: =H5-H33 | I55: =I5-I33 | J55: =J5-J33 | K55: =K5-K33 | ... O55: =O5-O33 | P55: =SUM(D55:O55)
A56: % GROSS MARGIN | D56: =IFERROR(D55/D5,0) | E56: =IFERROR(E55/E5,0) | F56: =IFERROR(F55/F5,0) | G56: =IFERROR(G55/G5,0) | H56: =IFERROR(H55/H5,0) | I56: =IFERROR(I55/I5,0) | J56: =IFERROR(J55/J5,0) | K56: =IFERROR(K55/K5,0) | ... O56: =IFERROR(O55/O5,0) | P56: =SUM(D56:O56)
A57: CONTRIBUTIVE MARGIN (TURNOVER-COGS) | D57: =D4-D32 | E57: =E4-E32 | F57: =F4-F32 | G57: =G4-G32 | H57: =H4-H32 | I57: =I4-I32 | J57: =J4-J32 | K57: =K4-K32 | ... O57: =O4-O32 | P57: =SUM(D57:O57)
A58: % CONTRIBUTIVE MARGIN | D58: =IFERROR(D57/D4,0) | E58: =IFERROR(E57/E4,0) | F58: =IFERROR(F57/F4,0) | G58: =IFERROR(G57/G4,0) | H58: =IFERROR(H57/H4,0) | I58: =IFERROR(I57/I4,0) | J58: =IFERROR(J57/J4,0) | K58: =IFERROR(K57/K4,0) | ... O58: =IFERROR(O57/O4,0) | P58: =SUM(D58:O58)
P59: =SUM(D59:O59)
A60: Opex | B60: Opex | D60: =D61+D71+D74+D83 | E60: =E61+E71+E74+E83 | F60: =F61+F71+F74+F83 | G60: =G61+G71+G74+G83 | H60: =H61+H71+H74+H83 | I60: =I61+I71+I74+I83 | J60: =J61+J71+J74+J83 | K60: =K61+K71+K74+K83 | ... O60: =O61+O71+O74+O83 | P60: =SUM(D60:O60)
A61: Marketing | C61: Marketing | D61: =D62+D66 | E61: =E62+E66 | F61: =F62+F66 | G61: =G62+G66 | H61: =H62+H66 | I61: =I62+I66 | J61: =J62+J66 | K61: =K62+K66 | ... O61: =O62+O66 | P61: =SUM(D61:O61) | Q61: ->
A62: METAADS | C62: METAADS | D62: =SUM(D63:D65) | E62: =SUM(E63:E65) | F62: =SUM(F63:F65) | G62: =SUM(G63:G65) | H62: =SUM(H63:H65) | I62: =SUM(I63:I65) | J62: =SUM(J63:J65) | K62: =SUM(K63:K65) | ... O62: =SUM(O63:O65) | P62: =SUM(D62:O62) | Q62: ->
A63: EU | C63: EU | D63: =SUMIFS('g-expenses-sl'!$G:$G,'g-expenses-sl'!$A:$A,D$1,'g-expenses-sl'!$D:$D,"marketing",'g-expenses-sl'!$E:$E,"METAADS",'g-expenses-sl'!$F:$F,$C63) | E63: =SUMIFS('g-expenses-sl'!$G:$G,'g-expenses-sl'!$A:$A,E$1,'g-expenses-sl'!$D:$D,"marketing",'g-expenses-sl'!$E:$E,"METAADS",'g-expenses-sl'!$F:$F,$C63) | F63: =SUMIFS('g-expenses-sl'!$G:$G,'g-expenses-sl'!$A:$A,F$1,'g-expenses-sl'!$D:$D,"marketing",'g-expenses-sl'!$E:$E,"METAADS",'g-expenses-sl'!$F:$F,$C63) | G63: =SUMIFS('g-expenses-sl'!$G:$G,'g-expenses-sl'!$A:$A,G$1,'g-expenses-sl'!$D:$D,"marketing",'g-expenses-sl'!$E:$E,"METAADS",'g-expenses-sl'!$F:$F,$C63) | H63: =SUMIFS('g-expenses-sl'!$G:$G,'g-expenses-sl'!$A:$A,H$1,'g-expenses-sl'!$D:$D,"marketing",'g-expenses-sl'!$E:$E,"METAADS",'g-expenses-sl'!$F:$F,$C63) | I63: =SUMIFS('g-expenses-sl'!$G:$G,'g-expenses-sl'!$A:$A,I$1,'g-expenses-sl'!$D:$D,"marketing",'g-expenses-sl'!$E:$E,"METAADS",'g-expenses-sl'!$F:$F,$C63) | J63: =SUMIFS('g-expenses-sl'!$G:$G,'g-expenses-sl'!$A:$A,J$1,'g-expenses-sl'!$D:$D,"marketing",'g-expenses-sl'!$E:$E,"METAADS",'g-expenses-sl'!$F:$F,$C63) | K63: =SUMIFS('g-expenses-sl'!$G:$G,'g-expenses-sl'!$A:$A,K$1,'g-expenses-sl'!$D:$D,"marketing",'g-expenses-sl'!$E:$E,"METAADS",'g-expenses-sl'!$F:$F,$C63) | ... O63: =SUMIFS('g-expenses-sl'!$G:$G,'g-expenses-sl'!$A:$A,O$1,'g-expenses-sl'!$D:$D,"marketing",'g-expenses-sl'!$E:$E,"METAADS",'g-expenses-sl'!$F:$F,$C63) | P63: =SUM(D63:O63) | Q63: ->
A64: UK | C64: UK | D64: =SUMIFS('g-expenses-sl'!$G:$G,'g-expenses-sl'!$A:$A,D$1,'g-expenses-sl'!$D:$D,"marketing",'g-expenses-sl'!$E:$E,"METAADS",'g-expenses-sl'!$F:$F,$C64) | E64: =SUMIFS('g-expenses-sl'!$G:$G,'g-expenses-sl'!$A:$A,E$1,'g-expenses-sl'!$D:$D,"marketing",'g-expenses-sl'!$E:$E,"METAADS",'g-expenses-sl'!$F:$F,$C64) | F64: =SUMIFS('g-expenses-sl'!$G:$G,'g-expenses-sl'!$A:$A,F$1,'g-expenses-sl'!$D:$D,"marketing",'g-expenses-sl'!$E:$E,"METAADS",'g-expenses-sl'!$F:$F,$C64) | G64: =SUMIFS('g-expenses-sl'!$G:$G,'g-expenses-sl'!$A:$A,G$1,'g-expenses-sl'!$D:$D,"marketing",'g-expenses-sl'!$E:$E,"METAADS",'g-expenses-sl'!$F:$F,$C64) | H64: =SUMIFS('g-expenses-sl'!$G:$G,'g-expenses-sl'!$A:$A,H$1,'g-expenses-sl'!$D:$D,"marketing",'g-expenses-sl'!$E:$E,"METAADS",'g-expenses-sl'!$F:$F,$C64) | I64: =SUMIFS('g-expenses-sl'!$G:$G,'g-expenses-sl'!$A:$A,I$1,'g-expenses-sl'!$D:$D,"marketing",'g-expenses-sl'!$E:$E,"METAADS",'g-expenses-sl'!$F:$F,$C64) | J64: =SUMIFS('g-expenses-sl'!$G:$G,'g-expenses-sl'!$A:$A,J$1,'g-expenses-sl'!$D:$D,"marketing",'g-expenses-sl'!$E:$E,"METAADS",'g-expenses-sl'!$F:$F,$C64) | K64: =SUMIFS('g-expenses-sl'!$G:$G,'g-expenses-sl'!$A:$A,K$1,'g-expenses-sl'!$D:$D,"marketing",'g-expenses-sl'!$E:$E,"METAADS",'g-expenses-sl'!$F:$F,$C64) | ... O64: =SUMIFS('g-expenses-sl'!$G:$G,'g-expenses-sl'!$A:$A,O$1,'g-expenses-sl'!$D:$D,"marketing",'g-expenses-sl'!$E:$E,"METAADS",'g-expenses-sl'!$F:$F,$C64) | P64: =SUM(D64:O64) | Q64: ->
A65: US | C65: US | D65: =SUMIFS('g-expenses-sl'!$G:$G,'g-expenses-sl'!$A:$A,D$1,'g-expenses-sl'!$D:$D,"marketing",'g-expenses-sl'!$E:$E,"METAADS",'g-expenses-sl'!$F:$F,$C65) | E65: =SUMIFS('g-expenses-sl'!$G:$G,'g-expenses-sl'!$A:$A,E$1,'g-expenses-sl'!$D:$D,"marketing",'g-expenses-sl'!$E:$E,"METAADS",'g-expenses-sl'!$F:$F,$C65) | F65: =SUMIFS('g-expenses-sl'!$G:$G,'g-expenses-sl'!$A:$A,F$1,'g-expenses-sl'!$D:$D,"marketing",'g-expenses-sl'!$E:$E,"METAADS",'g-expenses-sl'!$F:$F,$C65) | G65: =SUMIFS('g-expenses-sl'!$G:$G,'g-expenses-sl'!$A:$A,G$1,'g-expenses-sl'!$D:$D,"marketing",'g-expenses-sl'!$E:$E,"METAADS",'g-expenses-sl'!$F:$F,$C65) | H65: =SUMIFS('g-expenses-sl'!$G:$G,'g-expenses-sl'!$A:$A,H$1,'g-expenses-sl'!$D:$D,"marketing",'g-expenses-sl'!$E:$E,"METAADS",'g-expenses-sl'!$F:$F,$C65) | I65: =SUMIFS('g-expenses-sl'!$G:$G,'g-expenses-sl'!$A:$A,I$1,'g-expenses-sl'!$D:$D,"marketing",'g-expenses-sl'!$E:$E,"METAADS",'g-expenses-sl'!$F:$F,$C65) | J65: =SUMIFS('g-expenses-sl'!$G:$G,'g-expenses-sl'!$A:$A,J$1,'g-expenses-sl'!$D:$D,"marketing",'g-expenses-sl'!$E:$E,"METAADS",'g-expenses-sl'!$F:$F,$C65) | K65: =SUMIFS('g-expenses-sl'!$G:$G,'g-expenses-sl'!$A:$A,K$1,'g-expenses-sl'!$D:$D,"marketing",'g-expenses-sl'!$E:$E,"METAADS",'g-expenses-sl'!$F:$F,$C65) | ... O65: =SUMIFS('g-expenses-sl'!$G:$G,'g-expenses-sl'!$A:$A,O$1,'g-expenses-sl'!$D:$D,"marketing",'g-expenses-sl'!$E:$E,"METAADS",'g-expenses-sl'!$F:$F,$C65) | P65: =SUM(D65:O65) | Q65: ->
A66: GOOGLEADS | C66: GOOGLEADS | D66: =SUM(D67:D69) | E66: =SUM(E67:E69) | F66: =SUM(F67:F69) | G66: =SUM(G67:G69) | H66: =SUM(H67:H69) | I66: =SUM(I67:I69) | J66: =SUM(J67:J69) | K66: =SUM(K67:K69) | ... O66: =SUM(O67:O69) | P66: =SUM(D66:O66) | Q66: ->
A67: EU | C67: EU | D67: =SUMIFS('g-expenses-sl'!$G:$G,'g-expenses-sl'!$A:$A,D$1,'g-expenses-sl'!$D:$D,"marketing",'g-expenses-sl'!$E:$E,"GOOGLEADS",'g-expenses-sl'!$F:$F,$C67) | E67: =SUMIFS('g-expenses-sl'!$G:$G,'g-expenses-sl'!$A:$A,E$1,'g-expenses-sl'!$D:$D,"marketing",'g-expenses-sl'!$E:$E,"GOOGLEADS",'g-expenses-sl'!$F:$F,$C67) | F67: =SUMIFS('g-expenses-sl'!$G:$G,'g-expenses-sl'!$A:$A,F$1,'g-expenses-sl'!$D:$D,"marketing",'g-expenses-sl'!$E:$E,"GOOGLEADS",'g-expenses-sl'!$F:$F,$C67) | G67: =SUMIFS('g-expenses-sl'!$G:$G,'g-expenses-sl'!$A:$A,G$1,'g-expenses-sl'!$D:$D,"marketing",'g-expenses-sl'!$E:$E,"GOOGLEADS",'g-expenses-sl'!$F:$F,$C67) | H67: =SUMIFS('g-expenses-sl'!$G:$G,'g-expenses-sl'!$A:$A,H$1,'g-expenses-sl'!$D:$D,"marketing",'g-expenses-sl'!$E:$E,"GOOGLEADS",'g-expenses-sl'!$F:$F,$C67) | I67: =SUMIFS('g-expenses-sl'!$G:$G,'g-expenses-sl'!$A:$A,I$1,'g-expenses-sl'!$D:$D,"marketing",'g-expenses-sl'!$E:$E,"GOOGLEADS",'g-expenses-sl'!$F:$F,$C67) | J67: =SUMIFS('g-expenses-sl'!$G:$G,'g-expenses-sl'!$A:$A,J$1,'g-expenses-sl'!$D:$D,"marketing",'g-expenses-sl'!$E:$E,"GOOGLEADS",'g-expenses-sl'!$F:$F,$C67) | K67: =SUMIFS('g-expenses-sl'!$G:$G,'g-expenses-sl'!$A:$A,K$1,'g-expenses-sl'!$D:$D,"marketing",'g-expenses-sl'!$E:$E,"GOOGLEADS",'g-expenses-sl'!$F:$F,$C67) | ... O67: =SUMIFS('g-expenses-sl'!$G:$G,'g-expenses-sl'!$A:$A,O$1,'g-expenses-sl'!$D:$D,"marketing",'g-expenses-sl'!$E:$E,"GOOGLEADS",'g-expenses-sl'!$F:$F,$C67) | P67: =SUM(D67:O67) | Q67: ->
A68: UK | C68: UK | D68: =SUMIFS('g-expenses-sl'!$G:$G,'g-expenses-sl'!$A:$A,D$1,'g-expenses-sl'!$D:$D,"marketing",'g-expenses-sl'!$E:$E,"GOOGLEADS",'g-expenses-sl'!$F:$F,$C68) | E68: =SUMIFS('g-expenses-sl'!$G:$G,'g-expenses-sl'!$A:$A,E$1,'g-expenses-sl'!$D:$D,"marketing",'g-expenses-sl'!$E:$E,"GOOGLEADS",'g-expenses-sl'!$F:$F,$C68) | F68: =SUMIFS('g-expenses-sl'!$G:$G,'g-expenses-sl'!$A:$A,F$1,'g-expenses-sl'!$D:$D,"marketing",'g-expenses-sl'!$E:$E,"GOOGLEADS",'g-expenses-sl'!$F:$F,$C68) | G68: =SUMIFS('g-expenses-sl'!$G:$G,'g-expenses-sl'!$A:$A,G$1,'g-expenses-sl'!$D:$D,"marketing",'g-expenses-sl'!$E:$E,"GOOGLEADS",'g-expenses-sl'!$F:$F,$C68) | H68: =SUMIFS('g-expenses-sl'!$G:$G,'g-expenses-sl'!$A:$A,H$1,'g-expenses-sl'!$D:$D,"marketing",'g-expenses-sl'!$E:$E,"GOOGLEADS",'g-expenses-sl'!$F:$F,$C68) | I68: =SUMIFS('g-expenses-sl'!$G:$G,'g-expenses-sl'!$A:$A,I$1,'g-expenses-sl'!$D:$D,"marketing",'g-expenses-sl'!$E:$E,"GOOGLEADS",'g-expenses-sl'!$F:$F,$C68) | J68: =SUMIFS('g-expenses-sl'!$G:$G,'g-expenses-sl'!$A:$A,J$1,'g-expenses-sl'!$D:$D,"marketing",'g-expenses-sl'!$E:$E,"GOOGLEADS",'g-expenses-sl'!$F:$F,$C68) | K68: =SUMIFS('g-expenses-sl'!$G:$G,'g-expenses-sl'!$A:$A,K$1,'g-expenses-sl'!$D:$D,"marketing",'g-expenses-sl'!$E:$E,"GOOGLEADS",'g-expenses-sl'!$F:$F,$C68) | ... O68: =SUMIFS('g-expenses-sl'!$G:$G,'g-expenses-sl'!$A:$A,O$1,'g-expenses-sl'!$D:$D,"marketing",'g-expenses-sl'!$E:$E,"GOOGLEADS",'g-expenses-sl'!$F:$F,$C68) | P68: =SUM(D68:O68) | Q68: ->
A69: US | C69: US | D69: =SUMIFS('g-expenses-sl'!$G:$G,'g-expenses-sl'!$A:$A,D$1,'g-expenses-sl'!$D:$D,"marketing",'g-expenses-sl'!$E:$E,"GOOGLEADS",'g-expenses-sl'!$F:$F,$C69) | E69: =SUMIFS('g-expenses-sl'!$G:$G,'g-expenses-sl'!$A:$A,E$1,'g-expenses-sl'!$D:$D,"marketing",'g-expenses-sl'!$E:$E,"GOOGLEADS",'g-expenses-sl'!$F:$F,$C69) | F69: =SUMIFS('g-expenses-sl'!$G:$G,'g-expenses-sl'!$A:$A,F$1,'g-expenses-sl'!$D:$D,"marketing",'g-expenses-sl'!$E:$E,"GOOGLEADS",'g-expenses-sl'!$F:$F,$C69) | G69: =SUMIFS('g-expenses-sl'!$G:$G,'g-expenses-sl'!$A:$A,G$1,'g-expenses-sl'!$D:$D,"marketing",'g-expenses-sl'!$E:$E,"GOOGLEADS",'g-expenses-sl'!$F:$F,$C69) | H69: =SUMIFS('g-expenses-sl'!$G:$G,'g-expenses-sl'!$A:$A,H$1,'g-expenses-sl'!$D:$D,"marketing",'g-expenses-sl'!$E:$E,"GOOGLEADS",'g-expenses-sl'!$F:$F,$C69) | I69: =SUMIFS('g-expenses-sl'!$G:$G,'g-expenses-sl'!$A:$A,I$1,'g-expenses-sl'!$D:$D,"marketing",'g-expenses-sl'!$E:$E,"GOOGLEADS",'g-expenses-sl'!$F:$F,$C69) | J69: =SUMIFS('g-expenses-sl'!$G:$G,'g-expenses-sl'!$A:$A,J$1,'g-expenses-sl'!$D:$D,"marketing",'g-expenses-sl'!$E:$E,"GOOGLEADS",'g-expenses-sl'!$F:$F,$C69) | K69: =SUMIFS('g-expenses-sl'!$G:$G,'g-expenses-sl'!$A:$A,K$1,'g-expenses-sl'!$D:$D,"marketing",'g-expenses-sl'!$E:$E,"GOOGLEADS",'g-expenses-sl'!$F:$F,$C69) | ... O69: =SUMIFS('g-expenses-sl'!$G:$G,'g-expenses-sl'!$A:$A,O$1,'g-expenses-sl'!$D:$D,"marketing",'g-expenses-sl'!$E:$E,"GOOGLEADS",'g-expenses-sl'!$F:$F,$C69) | P69: =SUM(D69:O69) | Q69: ->
A70: Sales / mkt EU | C70: Sales / mkt EU | D70: =IFERROR(SUM(D7:D14)/(D63+D67),0) | E70: =IFERROR(SUM(E7:E14)/(E63+E67),0) | F70: =IFERROR(SUM(F7:F14)/(F63+F67),0) | G70: =IFERROR(SUM(G7:G14)/(G63+G67),0) | H70: =IFERROR(SUM(H7:H14)/(H63+H67),0) | I70: =IFERROR(SUM(I7:I14)/(I63+I67),0) | J70: =IFERROR(SUM(J7:J14)/(J63+J67),0) | K70: =IFERROR(SUM(K7:K14)/(K63+K67),0) | ... O70: =IFERROR(SUM(O7:O14)/(O63+O67),0) | P70: =SUM(D70:O70)
A71: Staff | C71: Staff | D71: =SUM(D72:D73) | E71: =SUM(E72:E73) | F71: =SUM(F72:F73) | G71: =SUM(G72:G73) | H71: =SUM(H72:H73) | I71: =SUM(I72:I73) | J71: =SUM(J72:J73) | K71: =SUM(K72:K73) | ... O71: =SUM(O72:O73) | P71: =SUM(D71:O71) | Q71: ->
A72: PAYROLL | C72: PAYROLL | D72: =SUMIFS('g-expenses-sl'!$G:$G,'g-expenses-sl'!$A:$A,D$1,'g-expenses-sl'!$D:$D,"staff",'g-expenses-sl'!$E:$E,$C72) | E72: =SUMIFS('g-expenses-sl'!$G:$G,'g-expenses-sl'!$A:$A,E$1,'g-expenses-sl'!$D:$D,"staff",'g-expenses-sl'!$E:$E,$C72) | F72: =SUMIFS('g-expenses-sl'!$G:$G,'g-expenses-sl'!$A:$A,F$1,'g-expenses-sl'!$D:$D,"staff",'g-expenses-sl'!$E:$E,$C72) | G72: =SUMIFS('g-expenses-sl'!$G:$G,'g-expenses-sl'!$A:$A,G$1,'g-expenses-sl'!$D:$D,"staff",'g-expenses-sl'!$E:$E,$C72) | H72: =SUMIFS('g-expenses-sl'!$G:$G,'g-expenses-sl'!$A:$A,H$1,'g-expenses-sl'!$D:$D,"staff",'g-expenses-sl'!$E:$E,$C72) | I72: =SUMIFS('g-expenses-sl'!$G:$G,'g-expenses-sl'!$A:$A,I$1,'g-expenses-sl'!$D:$D,"staff",'g-expenses-sl'!$E:$E,$C72) | J72: =SUMIFS('g-expenses-sl'!$G:$G,'g-expenses-sl'!$A:$A,J$1,'g-expenses-sl'!$D:$D,"staff",'g-expenses-sl'!$E:$E,$C72) | K72: =SUMIFS('g-expenses-sl'!$G:$G,'g-expenses-sl'!$A:$A,K$1,'g-expenses-sl'!$D:$D,"staff",'g-expenses-sl'!$E:$E,$C72) | ... O72: =SUMIFS('g-expenses-sl'!$G:$G,'g-expenses-sl'!$A:$A,O$1,'g-expenses-sl'!$D:$D,"staff",'g-expenses-sl'!$E:$E,$C72) | P72: =SUM(D72:O72) | Q72: ->
A73: DOSCONSULTING | C73: DOSCONSULTING | D73: =SUMIFS('g-expenses-sl'!$G:$G,'g-expenses-sl'!$A:$A,D$1,'g-expenses-sl'!$D:$D,"staff",'g-expenses-sl'!$E:$E,$C73) | E73: =SUMIFS('g-expenses-sl'!$G:$G,'g-expenses-sl'!$A:$A,E$1,'g-expenses-sl'!$D:$D,"staff",'g-expenses-sl'!$E:$E,$C73) | F73: =SUMIFS('g-expenses-sl'!$G:$G,'g-expenses-sl'!$A:$A,F$1,'g-expenses-sl'!$D:$D,"staff",'g-expenses-sl'!$E:$E,$C73) | G73: =SUMIFS('g-expenses-sl'!$G:$G,'g-expenses-sl'!$A:$A,G$1,'g-expenses-sl'!$D:$D,"staff",'g-expenses-sl'!$E:$E,$C73) | H73: =SUMIFS('g-expenses-sl'!$G:$G,'g-expenses-sl'!$A:$A,H$1,'g-expenses-sl'!$D:$D,"staff",'g-expenses-sl'!$E:$E,$C73) | I73: =SUMIFS('g-expenses-sl'!$G:$G,'g-expenses-sl'!$A:$A,I$1,'g-expenses-sl'!$D:$D,"staff",'g-expenses-sl'!$E:$E,$C73) | J73: =SUMIFS('g-expenses-sl'!$G:$G,'g-expenses-sl'!$A:$A,J$1,'g-expenses-sl'!$D:$D,"staff",'g-expenses-sl'!$E:$E,$C73) | K73: =SUMIFS('g-expenses-sl'!$G:$G,'g-expenses-sl'!$A:$A,K$1,'g-expenses-sl'!$D:$D,"staff",'g-expenses-sl'!$E:$E,$C73) | ... O73: =SUMIFS('g-expenses-sl'!$G:$G,'g-expenses-sl'!$A:$A,O$1,'g-expenses-sl'!$D:$D,"staff",'g-expenses-sl'!$E:$E,$C73) | P73: =SUM(D73:O73) | Q73: ->
A74: Administration | C74: Administration | D74: =D75+D76+D80+D81+D82 | E74: =E75+E76+E80+E81+E82 | F74: =F75+F76+F80+F81+F82 | G74: =G75+G76+G80+G81+G82 | H74: =H75+H76+H80+H81+H82 | I74: =I75+I76+I80+I81+I82 | J74: =J75+J76+J80+J81+J82 | K74: =K75+K76+K80+K81+K82 | ... O74: =O75+O76+O80+O81+O82 | P74: =SUM(D74:O74) | Q74: ->
A75: CLARIS | C75: CLARIS | D75: =SUMIFS('g-expenses-sl'!$G:$G,'g-expenses-sl'!$A:$A,D$1,'g-expenses-sl'!$D:$D,"administration",'g-expenses-sl'!$E:$E,$C75) | E75: =SUMIFS('g-expenses-sl'!$G:$G,'g-expenses-sl'!$A:$A,E$1,'g-expenses-sl'!$D:$D,"administration",'g-expenses-sl'!$E:$E,$C75) | F75: =SUMIFS('g-expenses-sl'!$G:$G,'g-expenses-sl'!$A:$A,F$1,'g-expenses-sl'!$D:$D,"administration",'g-expenses-sl'!$E:$E,$C75) | G75: =SUMIFS('g-expenses-sl'!$G:$G,'g-expenses-sl'!$A:$A,G$1,'g-expenses-sl'!$D:$D,"administration",'g-expenses-sl'!$E:$E,$C75) | H75: =SUMIFS('g-expenses-sl'!$G:$G,'g-expenses-sl'!$A:$A,H$1,'g-expenses-sl'!$D:$D,"administration",'g-expenses-sl'!$E:$E,$C75) | I75: =SUMIFS('g-expenses-sl'!$G:$G,'g-expenses-sl'!$A:$A,I$1,'g-expenses-sl'!$D:$D,"administration",'g-expenses-sl'!$E:$E,$C75) | J75: =SUMIFS('g-expenses-sl'!$G:$G,'g-expenses-sl'!$A:$A,J$1,'g-expenses-sl'!$D:$D,"administration",'g-expenses-sl'!$E:$E,$C75) | K75: =SUMIFS('g-expenses-sl'!$G:$G,'g-expenses-sl'!$A:$A,K$1,'g-expenses-sl'!$D:$D,"administration",'g-expenses-sl'!$E:$E,$C75) | ... O75: =SUMIFS('g-expenses-sl'!$G:$G,'g-expenses-sl'!$A:$A,O$1,'g-expenses-sl'!$D:$D,"administration",'g-expenses-sl'!$E:$E,$C75) | P75: =SUM(D75:O75) | Q75: ->
A76: HANNUN | C76: HANNUN | D76: =SUMIFS('g-expenses-sl'!$G:$G,'g-expenses-sl'!$A:$A,D$1,'g-expenses-sl'!$D:$D,"administration",'g-expenses-sl'!$E:$E,$C76) | E76: =SUMIFS('g-expenses-sl'!$G:$G,'g-expenses-sl'!$A:$A,E$1,'g-expenses-sl'!$D:$D,"administration",'g-expenses-sl'!$E:$E,$C76) | F76: =SUMIFS('g-expenses-sl'!$G:$G,'g-expenses-sl'!$A:$A,F$1,'g-expenses-sl'!$D:$D,"administration",'g-expenses-sl'!$E:$E,$C76) | G76: =SUMIFS('g-expenses-sl'!$G:$G,'g-expenses-sl'!$A:$A,G$1,'g-expenses-sl'!$D:$D,"administration",'g-expenses-sl'!$E:$E,$C76) | H76: =SUMIFS('g-expenses-sl'!$G:$G,'g-expenses-sl'!$A:$A,H$1,'g-expenses-sl'!$D:$D,"administration",'g-expenses-sl'!$E:$E,$C76) | I76: =SUMIFS('g-expenses-sl'!$G:$G,'g-expenses-sl'!$A:$A,I$1,'g-expenses-sl'!$D:$D,"administration",'g-expenses-sl'!$E:$E,$C76) | J76: =SUMIFS('g-expenses-sl'!$G:$G,'g-expenses-sl'!$A:$A,J$1,'g-expenses-sl'!$D:$D,"administration",'g-expenses-sl'!$E:$E,$C76) | K76: =SUMIFS('g-expenses-sl'!$G:$G,'g-expenses-sl'!$A:$A,K$1,'g-expenses-sl'!$D:$D,"administration",'g-expenses-sl'!$E:$E,$C76) | ... O76: =SUMIFS('g-expenses-sl'!$G:$G,'g-expenses-sl'!$A:$A,O$1,'g-expenses-sl'!$D:$D,"administration",'g-expenses-sl'!$E:$E,$C76) | P76: =SUM(D76:O76) | Q76: ->
A77: administration | C77: administration | D77: =SUMIFS('g-expenses-sl'!$G:$G,'g-expenses-sl'!$A:$A,D$1,'g-expenses-sl'!$D:$D,"administration",'g-expenses-sl'!$E:$E,$C76,'g-expenses-sl'!$F:$F,$C77) | E77: =SUMIFS('g-expenses-sl'!$G:$G,'g-expenses-sl'!$A:$A,E$1,'g-expenses-sl'!$D:$D,"administration",'g-expenses-sl'!$E:$E,$C76,'g-expenses-sl'!$F:$F,$C77) | F77: =SUMIFS('g-expenses-sl'!$G:$G,'g-expenses-sl'!$A:$A,F$1,'g-expenses-sl'!$D:$D,"administration",'g-expenses-sl'!$E:$E,$C76,'g-expenses-sl'!$F:$F,$C77) | G77: =SUMIFS('g-expenses-sl'!$G:$G,'g-expenses-sl'!$A:$A,G$1,'g-expenses-sl'!$D:$D,"administration",'g-expenses-sl'!$E:$E,$C76,'g-expenses-sl'!$F:$F,$C77) | H77: =SUMIFS('g-expenses-sl'!$G:$G,'g-expenses-sl'!$A:$A,H$1,'g-expenses-sl'!$D:$D,"administration",'g-expenses-sl'!$E:$E,$C76,'g-expenses-sl'!$F:$F,$C77) | I77: =SUMIFS('g-expenses-sl'!$G:$G,'g-expenses-sl'!$A:$A,I$1,'g-expenses-sl'!$D:$D,"administration",'g-expenses-sl'!$E:$E,$C76,'g-expenses-sl'!$F:$F,$C77) | J77: =SUMIFS('g-expenses-sl'!$G:$G,'g-expenses-sl'!$A:$A,J$1,'g-expenses-sl'!$D:$D,"administration",'g-expenses-sl'!$E:$E,$C76,'g-expenses-sl'!$F:$F,$C77) | K77: =SUMIFS('g-expenses-sl'!$G:$G,'g-expenses-sl'!$A:$A,K$1,'g-expenses-sl'!$D:$D,"administration",'g-expenses-sl'!$E:$E,$C76,'g-expenses-sl'!$F:$F,$C77) | ... O77: =SUMIFS('g-expenses-sl'!$G:$G,'g-expenses-sl'!$A:$A,O$1,'g-expenses-sl'!$D:$D,"administration",'g-expenses-sl'!$E:$E,$C76,'g-expenses-sl'!$F:$F,$C77) | P77: =SUM(D77:O77) | Q77: ->
A78: office | C78: office | D78: =SUMIFS('g-expenses-sl'!$G:$G,'g-expenses-sl'!$A:$A,D$1,'g-expenses-sl'!$D:$D,"administration",'g-expenses-sl'!$E:$E,$C76,'g-expenses-sl'!$F:$F,$C78) | E78: =SUMIFS('g-expenses-sl'!$G:$G,'g-expenses-sl'!$A:$A,E$1,'g-expenses-sl'!$D:$D,"administration",'g-expenses-sl'!$E:$E,$C76,'g-expenses-sl'!$F:$F,$C78) | F78: =SUMIFS('g-expenses-sl'!$G:$G,'g-expenses-sl'!$A:$A,F$1,'g-expenses-sl'!$D:$D,"administration",'g-expenses-sl'!$E:$E,$C76,'g-expenses-sl'!$F:$F,$C78) | G78: =SUMIFS('g-expenses-sl'!$G:$G,'g-expenses-sl'!$A:$A,G$1,'g-expenses-sl'!$D:$D,"administration",'g-expenses-sl'!$E:$E,$C76,'g-expenses-sl'!$F:$F,$C78) | H78: =SUMIFS('g-expenses-sl'!$G:$G,'g-expenses-sl'!$A:$A,H$1,'g-expenses-sl'!$D:$D,"administration",'g-expenses-sl'!$E:$E,$C76,'g-expenses-sl'!$F:$F,$C78) | I78: =SUMIFS('g-expenses-sl'!$G:$G,'g-expenses-sl'!$A:$A,I$1,'g-expenses-sl'!$D:$D,"administration",'g-expenses-sl'!$E:$E,$C76,'g-expenses-sl'!$F:$F,$C78) | J78: =SUMIFS('g-expenses-sl'!$G:$G,'g-expenses-sl'!$A:$A,J$1,'g-expenses-sl'!$D:$D,"administration",'g-expenses-sl'!$E:$E,$C76,'g-expenses-sl'!$F:$F,$C78) | K78: =SUMIFS('g-expenses-sl'!$G:$G,'g-expenses-sl'!$A:$A,K$1,'g-expenses-sl'!$D:$D,"administration",'g-expenses-sl'!$E:$E,$C76,'g-expenses-sl'!$F:$F,$C78) | ... O78: =SUMIFS('g-expenses-sl'!$G:$G,'g-expenses-sl'!$A:$A,O$1,'g-expenses-sl'!$D:$D,"administration",'g-expenses-sl'!$E:$E,$C76,'g-expenses-sl'!$F:$F,$C78) | P78: =SUM(D78:O78) | Q78: ->
A79: services | C79: services | D79: =SUMIFS('g-expenses-sl'!$G:$G,'g-expenses-sl'!$A:$A,D$1,'g-expenses-sl'!$D:$D,"administration",'g-expenses-sl'!$E:$E,$C76,'g-expenses-sl'!$F:$F,$C79) | E79: =SUMIFS('g-expenses-sl'!$G:$G,'g-expenses-sl'!$A:$A,E$1,'g-expenses-sl'!$D:$D,"administration",'g-expenses-sl'!$E:$E,$C76,'g-expenses-sl'!$F:$F,$C79) | F79: =SUMIFS('g-expenses-sl'!$G:$G,'g-expenses-sl'!$A:$A,F$1,'g-expenses-sl'!$D:$D,"administration",'g-expenses-sl'!$E:$E,$C76,'g-expenses-sl'!$F:$F,$C79) | G79: =SUMIFS('g-expenses-sl'!$G:$G,'g-expenses-sl'!$A:$A,G$1,'g-expenses-sl'!$D:$D,"administration",'g-expenses-sl'!$E:$E,$C76,'g-expenses-sl'!$F:$F,$C79) | H79: =SUMIFS('g-expenses-sl'!$G:$G,'g-expenses-sl'!$A:$A,H$1,'g-expenses-sl'!$D:$D,"administration",'g-expenses-sl'!$E:$E,$C76,'g-expenses-sl'!$F:$F,$C79) | I79: =SUMIFS('g-expenses-sl'!$G:$G,'g-expenses-sl'!$A:$A,I$1,'g-expenses-sl'!$D:$D,"administration",'g-expenses-sl'!$E:$E,$C76,'g-expenses-sl'!$F:$F,$C79) | J79: =SUMIFS('g-expenses-sl'!$G:$G,'g-expenses-sl'!$A:$A,J$1,'g-expenses-sl'!$D:$D,"administration",'g-expenses-sl'!$E:$E,$C76,'g-expenses-sl'!$F:$F,$C79) | K79: =SUMIFS('g-expenses-sl'!$G:$G,'g-expenses-sl'!$A:$A,K$1,'g-expenses-sl'!$D:$D,"administration",'g-expenses-sl'!$E:$E,$C76,'g-expenses-sl'!$F:$F,$C79) | ... O79: =SUMIFS('g-expenses-sl'!$G:$G,'g-expenses-sl'!$A:$A,O$1,'g-expenses-sl'!$D:$D,"administration",'g-expenses-sl'!$E:$E,$C76,'g-expenses-sl'!$F:$F,$C79) | P79: =SUM(D79:O79) | Q79: ->
A80: NODA | C80: NODA | D80: =SUMIFS('g-expenses-sl'!$G:$G,'g-expenses-sl'!$A:$A,D$1,'g-expenses-sl'!$D:$D,"administration",'g-expenses-sl'!$E:$E,$C80) | E80: =SUMIFS('g-expenses-sl'!$G:$G,'g-expenses-sl'!$A:$A,E$1,'g-expenses-sl'!$D:$D,"administration",'g-expenses-sl'!$E:$E,$C80) | F80: =SUMIFS('g-expenses-sl'!$G:$G,'g-expenses-sl'!$A:$A,F$1,'g-expenses-sl'!$D:$D,"administration",'g-expenses-sl'!$E:$E,$C80) | G80: =SUMIFS('g-expenses-sl'!$G:$G,'g-expenses-sl'!$A:$A,G$1,'g-expenses-sl'!$D:$D,"administration",'g-expenses-sl'!$E:$E,$C80) | H80: =SUMIFS('g-expenses-sl'!$G:$G,'g-expenses-sl'!$A:$A,H$1,'g-expenses-sl'!$D:$D,"administration",'g-expenses-sl'!$E:$E,$C80) | I80: =SUMIFS('g-expenses-sl'!$G:$G,'g-expenses-sl'!$A:$A,I$1,'g-expenses-sl'!$D:$D,"administration",'g-expenses-sl'!$E:$E,$C80) | J80: =SUMIFS('g-expenses-sl'!$G:$G,'g-expenses-sl'!$A:$A,J$1,'g-expenses-sl'!$D:$D,"administration",'g-expenses-sl'!$E:$E,$C80) | K80: =SUMIFS('g-expenses-sl'!$G:$G,'g-expenses-sl'!$A:$A,K$1,'g-expenses-sl'!$D:$D,"administration",'g-expenses-sl'!$E:$E,$C80) | ... O80: =SUMIFS('g-expenses-sl'!$G:$G,'g-expenses-sl'!$A:$A,O$1,'g-expenses-sl'!$D:$D,"administration",'g-expenses-sl'!$E:$E,$C80) | P80: =SUM(D80:O80) | Q80: ->
A81: TORRAS | C81: TORRAS | D81: =SUMIFS('g-expenses-sl'!$G:$G,'g-expenses-sl'!$A:$A,D$1,'g-expenses-sl'!$D:$D,"administration",'g-expenses-sl'!$E:$E,$C81) | E81: =SUMIFS('g-expenses-sl'!$G:$G,'g-expenses-sl'!$A:$A,E$1,'g-expenses-sl'!$D:$D,"administration",'g-expenses-sl'!$E:$E,$C81) | F81: =SUMIFS('g-expenses-sl'!$G:$G,'g-expenses-sl'!$A:$A,F$1,'g-expenses-sl'!$D:$D,"administration",'g-expenses-sl'!$E:$E,$C81) | G81: =SUMIFS('g-expenses-sl'!$G:$G,'g-expenses-sl'!$A:$A,G$1,'g-expenses-sl'!$D:$D,"administration",'g-expenses-sl'!$E:$E,$C81) | H81: =SUMIFS('g-expenses-sl'!$G:$G,'g-expenses-sl'!$A:$A,H$1,'g-expenses-sl'!$D:$D,"administration",'g-expenses-sl'!$E:$E,$C81) | I81: =SUMIFS('g-expenses-sl'!$G:$G,'g-expenses-sl'!$A:$A,I$1,'g-expenses-sl'!$D:$D,"administration",'g-expenses-sl'!$E:$E,$C81) | J81: =SUMIFS('g-expenses-sl'!$G:$G,'g-expenses-sl'!$A:$A,J$1,'g-expenses-sl'!$D:$D,"administration",'g-expenses-sl'!$E:$E,$C81) | K81: =SUMIFS('g-expenses-sl'!$G:$G,'g-expenses-sl'!$A:$A,K$1,'g-expenses-sl'!$D:$D,"administration",'g-expenses-sl'!$E:$E,$C81) | ... O81: =SUMIFS('g-expenses-sl'!$G:$G,'g-expenses-sl'!$A:$A,O$1,'g-expenses-sl'!$D:$D,"administration",'g-expenses-sl'!$E:$E,$C81) | P81: =SUM(D81:O81) | Q81: ->
A82: VITALY | C82: VITALY | D82: =SUMIFS('g-expenses-sl'!$G:$G,'g-expenses-sl'!$A:$A,D$1,'g-expenses-sl'!$D:$D,"administration",'g-expenses-sl'!$E:$E,$C82) | E82: =SUMIFS('g-expenses-sl'!$G:$G,'g-expenses-sl'!$A:$A,E$1,'g-expenses-sl'!$D:$D,"administration",'g-expenses-sl'!$E:$E,$C82) | F82: =SUMIFS('g-expenses-sl'!$G:$G,'g-expenses-sl'!$A:$A,F$1,'g-expenses-sl'!$D:$D,"administration",'g-expenses-sl'!$E:$E,$C82) | G82: =SUMIFS('g-expenses-sl'!$G:$G,'g-expenses-sl'!$A:$A,G$1,'g-expenses-sl'!$D:$D,"administration",'g-expenses-sl'!$E:$E,$C82) | H82: =SUMIFS('g-expenses-sl'!$G:$G,'g-expenses-sl'!$A:$A,H$1,'g-expenses-sl'!$D:$D,"administration",'g-expenses-sl'!$E:$E,$C82) | I82: =SUMIFS('g-expenses-sl'!$G:$G,'g-expenses-sl'!$A:$A,I$1,'g-expenses-sl'!$D:$D,"administration",'g-expenses-sl'!$E:$E,$C82) | J82: =SUMIFS('g-expenses-sl'!$G:$G,'g-expenses-sl'!$A:$A,J$1,'g-expenses-sl'!$D:$D,"administration",'g-expenses-sl'!$E:$E,$C82) | K82: =SUMIFS('g-expenses-sl'!$G:$G,'g-expenses-sl'!$A:$A,K$1,'g-expenses-sl'!$D:$D,"administration",'g-expenses-sl'!$E:$E,$C82) | ... O82: =SUMIFS('g-expenses-sl'!$G:$G,'g-expenses-sl'!$A:$A,O$1,'g-expenses-sl'!$D:$D,"administration",'g-expenses-sl'!$E:$E,$C82) | P82: =SUM(D82:O82) | Q82: ->
A83: Technology | C83: Technology | D83: =SUM(D84:D98) | E83: =SUM(E84:E98) | F83: =SUM(F84:F98) | G83: =SUM(G84:G98) | H83: =SUM(H84:H98) | I83: =SUM(I84:I98) | J83: =SUM(J84:J98) | K83: =SUM(K84:K98) | ... O83: =SUM(O84:O98) | P83: =SUM(D83:O83) | Q83: ->
A84: ADOBE | C84: ADOBE | D84: =SUMIFS('g-expenses-sl'!$G:$G,'g-expenses-sl'!$A:$A,D$1,'g-expenses-sl'!$D:$D,"technology",'g-expenses-sl'!$E:$E,$C84) | E84: =SUMIFS('g-expenses-sl'!$G:$G,'g-expenses-sl'!$A:$A,E$1,'g-expenses-sl'!$D:$D,"technology",'g-expenses-sl'!$E:$E,$C84) | F84: =SUMIFS('g-expenses-sl'!$G:$G,'g-expenses-sl'!$A:$A,F$1,'g-expenses-sl'!$D:$D,"technology",'g-expenses-sl'!$E:$E,$C84) | G84: =SUMIFS('g-expenses-sl'!$G:$G,'g-expenses-sl'!$A:$A,G$1,'g-expenses-sl'!$D:$D,"technology",'g-expenses-sl'!$E:$E,$C84) | H84: =SUMIFS('g-expenses-sl'!$G:$G,'g-expenses-sl'!$A:$A,H$1,'g-expenses-sl'!$D:$D,"technology",'g-expenses-sl'!$E:$E,$C84) | I84: =SUMIFS('g-expenses-sl'!$G:$G,'g-expenses-sl'!$A:$A,I$1,'g-expenses-sl'!$D:$D,"technology",'g-expenses-sl'!$E:$E,$C84) | J84: =SUMIFS('g-expenses-sl'!$G:$G,'g-expenses-sl'!$A:$A,J$1,'g-expenses-sl'!$D:$D,"technology",'g-expenses-sl'!$E:$E,$C84) | K84: =SUMIFS('g-expenses-sl'!$G:$G,'g-expenses-sl'!$A:$A,K$1,'g-expenses-sl'!$D:$D,"technology",'g-expenses-sl'!$E:$E,$C84) | ... O84: =SUMIFS('g-expenses-sl'!$G:$G,'g-expenses-sl'!$A:$A,O$1,'g-expenses-sl'!$D:$D,"technology",'g-expenses-sl'!$E:$E,$C84) | P84: =SUM(D84:O84) | Q84: ->
A85: CANVA | C85: CANVA | D85: =SUMIFS('g-expenses-sl'!$G:$G,'g-expenses-sl'!$A:$A,D$1,'g-expenses-sl'!$D:$D,"technology",'g-expenses-sl'!$E:$E,$C85) | E85: =SUMIFS('g-expenses-sl'!$G:$G,'g-expenses-sl'!$A:$A,E$1,'g-expenses-sl'!$D:$D,"technology",'g-expenses-sl'!$E:$E,$C85) | F85: =SUMIFS('g-expenses-sl'!$G:$G,'g-expenses-sl'!$A:$A,F$1,'g-expenses-sl'!$D:$D,"technology",'g-expenses-sl'!$E:$E,$C85) | G85: =SUMIFS('g-expenses-sl'!$G:$G,'g-expenses-sl'!$A:$A,G$1,'g-expenses-sl'!$D:$D,"technology",'g-expenses-sl'!$E:$E,$C85) | H85: =SUMIFS('g-expenses-sl'!$G:$G,'g-expenses-sl'!$A:$A,H$1,'g-expenses-sl'!$D:$D,"technology",'g-expenses-sl'!$E:$E,$C85) | I85: =SUMIFS('g-expenses-sl'!$G:$G,'g-expenses-sl'!$A:$A,I$1,'g-expenses-sl'!$D:$D,"technology",'g-expenses-sl'!$E:$E,$C85) | J85: =SUMIFS('g-expenses-sl'!$G:$G,'g-expenses-sl'!$A:$A,J$1,'g-expenses-sl'!$D:$D,"technology",'g-expenses-sl'!$E:$E,$C85) | K85: =SUMIFS('g-expenses-sl'!$G:$G,'g-expenses-sl'!$A:$A,K$1,'g-expenses-sl'!$D:$D,"technology",'g-expenses-sl'!$E:$E,$C85) | ... O85: =SUMIFS('g-expenses-sl'!$G:$G,'g-expenses-sl'!$A:$A,O$1,'g-expenses-sl'!$D:$D,"technology",'g-expenses-sl'!$E:$E,$C85) | P85: =SUM(D85:O85) | Q85: ->
A86: GODADDY | C86: GODADDY | D86: =SUMIFS('g-expenses-sl'!$G:$G,'g-expenses-sl'!$A:$A,D$1,'g-expenses-sl'!$D:$D,"technology",'g-expenses-sl'!$E:$E,$C86) | E86: =SUMIFS('g-expenses-sl'!$G:$G,'g-expenses-sl'!$A:$A,E$1,'g-expenses-sl'!$D:$D,"technology",'g-expenses-sl'!$E:$E,$C86) | F86: =SUMIFS('g-expenses-sl'!$G:$G,'g-expenses-sl'!$A:$A,F$1,'g-expenses-sl'!$D:$D,"technology",'g-expenses-sl'!$E:$E,$C86) | G86: =SUMIFS('g-expenses-sl'!$G:$G,'g-expenses-sl'!$A:$A,G$1,'g-expenses-sl'!$D:$D,"technology",'g-expenses-sl'!$E:$E,$C86) | H86: =SUMIFS('g-expenses-sl'!$G:$G,'g-expenses-sl'!$A:$A,H$1,'g-expenses-sl'!$D:$D,"technology",'g-expenses-sl'!$E:$E,$C86) | I86: =SUMIFS('g-expenses-sl'!$G:$G,'g-expenses-sl'!$A:$A,I$1,'g-expenses-sl'!$D:$D,"technology",'g-expenses-sl'!$E:$E,$C86) | J86: =SUMIFS('g-expenses-sl'!$G:$G,'g-expenses-sl'!$A:$A,J$1,'g-expenses-sl'!$D:$D,"technology",'g-expenses-sl'!$E:$E,$C86) | K86: =SUMIFS('g-expenses-sl'!$G:$G,'g-expenses-sl'!$A:$A,K$1,'g-expenses-sl'!$D:$D,"technology",'g-expenses-sl'!$E:$E,$C86) | ... O86: =SUMIFS('g-expenses-sl'!$G:$G,'g-expenses-sl'!$A:$A,O$1,'g-expenses-sl'!$D:$D,"technology",'g-expenses-sl'!$E:$E,$C86) | P86: =SUM(D86:O86) | Q86: ->
A87: GOOGLEWORKSPACE | C87: GOOGLEWORKSPACE | D87: =SUMIFS('g-expenses-sl'!$G:$G,'g-expenses-sl'!$A:$A,D$1,'g-expenses-sl'!$D:$D,"technology",'g-expenses-sl'!$E:$E,$C87) | E87: =SUMIFS('g-expenses-sl'!$G:$G,'g-expenses-sl'!$A:$A,E$1,'g-expenses-sl'!$D:$D,"technology",'g-expenses-sl'!$E:$E,$C87) | F87: =SUMIFS('g-expenses-sl'!$G:$G,'g-expenses-sl'!$A:$A,F$1,'g-expenses-sl'!$D:$D,"technology",'g-expenses-sl'!$E:$E,$C87) | G87: =SUMIFS('g-expenses-sl'!$G:$G,'g-expenses-sl'!$A:$A,G$1,'g-expenses-sl'!$D:$D,"technology",'g-expenses-sl'!$E:$E,$C87) | H87: =SUMIFS('g-expenses-sl'!$G:$G,'g-expenses-sl'!$A:$A,H$1,'g-expenses-sl'!$D:$D,"technology",'g-expenses-sl'!$E:$E,$C87) | I87: =SUMIFS('g-expenses-sl'!$G:$G,'g-expenses-sl'!$A:$A,I$1,'g-expenses-sl'!$D:$D,"technology",'g-expenses-sl'!$E:$E,$C87) | J87: =SUMIFS('g-expenses-sl'!$G:$G,'g-expenses-sl'!$A:$A,J$1,'g-expenses-sl'!$D:$D,"technology",'g-expenses-sl'!$E:$E,$C87) | K87: =SUMIFS('g-expenses-sl'!$G:$G,'g-expenses-sl'!$A:$A,K$1,'g-expenses-sl'!$D:$D,"technology",'g-expenses-sl'!$E:$E,$C87) | ... O87: =SUMIFS('g-expenses-sl'!$G:$G,'g-expenses-sl'!$A:$A,O$1,'g-expenses-sl'!$D:$D,"technology",'g-expenses-sl'!$E:$E,$C87) | P87: =SUM(D87:O87) | Q87: ->
A88: GORGIAS | C88: GORGIAS | D88: =SUMIFS('g-expenses-sl'!$G:$G,'g-expenses-sl'!$A:$A,D$1,'g-expenses-sl'!$D:$D,"technology",'g-expenses-sl'!$E:$E,$C88) | E88: =SUMIFS('g-expenses-sl'!$G:$G,'g-expenses-sl'!$A:$A,E$1,'g-expenses-sl'!$D:$D,"technology",'g-expenses-sl'!$E:$E,$C88) | F88: =SUMIFS('g-expenses-sl'!$G:$G,'g-expenses-sl'!$A:$A,F$1,'g-expenses-sl'!$D:$D,"technology",'g-expenses-sl'!$E:$E,$C88) | G88: =SUMIFS('g-expenses-sl'!$G:$G,'g-expenses-sl'!$A:$A,G$1,'g-expenses-sl'!$D:$D,"technology",'g-expenses-sl'!$E:$E,$C88) | H88: =SUMIFS('g-expenses-sl'!$G:$G,'g-expenses-sl'!$A:$A,H$1,'g-expenses-sl'!$D:$D,"technology",'g-expenses-sl'!$E:$E,$C88) | I88: =SUMIFS('g-expenses-sl'!$G:$G,'g-expenses-sl'!$A:$A,I$1,'g-expenses-sl'!$D:$D,"technology",'g-expenses-sl'!$E:$E,$C88) | J88: =SUMIFS('g-expenses-sl'!$G:$G,'g-expenses-sl'!$A:$A,J$1,'g-expenses-sl'!$D:$D,"technology",'g-expenses-sl'!$E:$E,$C88) | K88: =SUMIFS('g-expenses-sl'!$G:$G,'g-expenses-sl'!$A:$A,K$1,'g-expenses-sl'!$D:$D,"technology",'g-expenses-sl'!$E:$E,$C88) | ... O88: =SUMIFS('g-expenses-sl'!$G:$G,'g-expenses-sl'!$A:$A,O$1,'g-expenses-sl'!$D:$D,"technology",'g-expenses-sl'!$E:$E,$C88) | P88: =SUM(D88:O88) | Q88: ->
A89: HETZNER | C89: HETZNER | D89: =SUMIFS('g-expenses-sl'!$G:$G,'g-expenses-sl'!$A:$A,D$1,'g-expenses-sl'!$D:$D,"technology",'g-expenses-sl'!$E:$E,$C89) | E89: =SUMIFS('g-expenses-sl'!$G:$G,'g-expenses-sl'!$A:$A,E$1,'g-expenses-sl'!$D:$D,"technology",'g-expenses-sl'!$E:$E,$C89) | F89: =SUMIFS('g-expenses-sl'!$G:$G,'g-expenses-sl'!$A:$A,F$1,'g-expenses-sl'!$D:$D,"technology",'g-expenses-sl'!$E:$E,$C89) | G89: =SUMIFS('g-expenses-sl'!$G:$G,'g-expenses-sl'!$A:$A,G$1,'g-expenses-sl'!$D:$D,"technology",'g-expenses-sl'!$E:$E,$C89) | H89: =SUMIFS('g-expenses-sl'!$G:$G,'g-expenses-sl'!$A:$A,H$1,'g-expenses-sl'!$D:$D,"technology",'g-expenses-sl'!$E:$E,$C89) | I89: =SUMIFS('g-expenses-sl'!$G:$G,'g-expenses-sl'!$A:$A,I$1,'g-expenses-sl'!$D:$D,"technology",'g-expenses-sl'!$E:$E,$C89) | J89: =SUMIFS('g-expenses-sl'!$G:$G,'g-expenses-sl'!$A:$A,J$1,'g-expenses-sl'!$D:$D,"technology",'g-expenses-sl'!$E:$E,$C89) | K89: =SUMIFS('g-expenses-sl'!$G:$G,'g-expenses-sl'!$A:$A,K$1,'g-expenses-sl'!$D:$D,"technology",'g-expenses-sl'!$E:$E,$C89) | ... O89: =SUMIFS('g-expenses-sl'!$G:$G,'g-expenses-sl'!$A:$A,O$1,'g-expenses-sl'!$D:$D,"technology",'g-expenses-sl'!$E:$E,$C89) | P89: =SUM(D89:O89) | Q89: ->
A90: KONVOAI | C90: KONVOAI | D90: =SUMIFS('g-expenses-sl'!$G:$G,'g-expenses-sl'!$A:$A,D$1,'g-expenses-sl'!$D:$D,"technology",'g-expenses-sl'!$E:$E,$C90) | E90: =SUMIFS('g-expenses-sl'!$G:$G,'g-expenses-sl'!$A:$A,E$1,'g-expenses-sl'!$D:$D,"technology",'g-expenses-sl'!$E:$E,$C90) | F90: =SUMIFS('g-expenses-sl'!$G:$G,'g-expenses-sl'!$A:$A,F$1,'g-expenses-sl'!$D:$D,"technology",'g-expenses-sl'!$E:$E,$C90) | G90: =SUMIFS('g-expenses-sl'!$G:$G,'g-expenses-sl'!$A:$A,G$1,'g-expenses-sl'!$D:$D,"technology",'g-expenses-sl'!$E:$E,$C90) | H90: =SUMIFS('g-expenses-sl'!$G:$G,'g-expenses-sl'!$A:$A,H$1,'g-expenses-sl'!$D:$D,"technology",'g-expenses-sl'!$E:$E,$C90) | I90: =SUMIFS('g-expenses-sl'!$G:$G,'g-expenses-sl'!$A:$A,I$1,'g-expenses-sl'!$D:$D,"technology",'g-expenses-sl'!$E:$E,$C90) | J90: =SUMIFS('g-expenses-sl'!$G:$G,'g-expenses-sl'!$A:$A,J$1,'g-expenses-sl'!$D:$D,"technology",'g-expenses-sl'!$E:$E,$C90) | K90: =SUMIFS('g-expenses-sl'!$G:$G,'g-expenses-sl'!$A:$A,K$1,'g-expenses-sl'!$D:$D,"technology",'g-expenses-sl'!$E:$E,$C90) | ... O90: =SUMIFS('g-expenses-sl'!$G:$G,'g-expenses-sl'!$A:$A,O$1,'g-expenses-sl'!$D:$D,"technology",'g-expenses-sl'!$E:$E,$C90) | P90: =SUM(D90:O90) | Q90: ->
A91: MASMOVIL | C91: MASMOVIL | D91: =SUMIFS('g-expenses-sl'!$G:$G,'g-expenses-sl'!$A:$A,D$1,'g-expenses-sl'!$D:$D,"technology",'g-expenses-sl'!$E:$E,$C91) | E91: =SUMIFS('g-expenses-sl'!$G:$G,'g-expenses-sl'!$A:$A,E$1,'g-expenses-sl'!$D:$D,"technology",'g-expenses-sl'!$E:$E,$C91) | F91: =SUMIFS('g-expenses-sl'!$G:$G,'g-expenses-sl'!$A:$A,F$1,'g-expenses-sl'!$D:$D,"technology",'g-expenses-sl'!$E:$E,$C91) | G91: =SUMIFS('g-expenses-sl'!$G:$G,'g-expenses-sl'!$A:$A,G$1,'g-expenses-sl'!$D:$D,"technology",'g-expenses-sl'!$E:$E,$C91) | H91: =SUMIFS('g-expenses-sl'!$G:$G,'g-expenses-sl'!$A:$A,H$1,'g-expenses-sl'!$D:$D,"technology",'g-expenses-sl'!$E:$E,$C91) | I91: =SUMIFS('g-expenses-sl'!$G:$G,'g-expenses-sl'!$A:$A,I$1,'g-expenses-sl'!$D:$D,"technology",'g-expenses-sl'!$E:$E,$C91) | J91: =SUMIFS('g-expenses-sl'!$G:$G,'g-expenses-sl'!$A:$A,J$1,'g-expenses-sl'!$D:$D,"technology",'g-expenses-sl'!$E:$E,$C91) | K91: =SUMIFS('g-expenses-sl'!$G:$G,'g-expenses-sl'!$A:$A,K$1,'g-expenses-sl'!$D:$D,"technology",'g-expenses-sl'!$E:$E,$C91) | ... O91: =SUMIFS('g-expenses-sl'!$G:$G,'g-expenses-sl'!$A:$A,O$1,'g-expenses-sl'!$D:$D,"technology",'g-expenses-sl'!$E:$E,$C91) | P91: =SUM(D91:O91) | Q91: ->
A92: MICROSOFT | C92: MICROSOFT | D92: =SUMIFS('g-expenses-sl'!$G:$G,'g-expenses-sl'!$A:$A,D$1,'g-expenses-sl'!$D:$D,"technology",'g-expenses-sl'!$E:$E,$C92) | E92: =SUMIFS('g-expenses-sl'!$G:$G,'g-expenses-sl'!$A:$A,E$1,'g-expenses-sl'!$D:$D,"technology",'g-expenses-sl'!$E:$E,$C92) | F92: =SUMIFS('g-expenses-sl'!$G:$G,'g-expenses-sl'!$A:$A,F$1,'g-expenses-sl'!$D:$D,"technology",'g-expenses-sl'!$E:$E,$C92) | G92: =SUMIFS('g-expenses-sl'!$G:$G,'g-expenses-sl'!$A:$A,G$1,'g-expenses-sl'!$D:$D,"technology",'g-expenses-sl'!$E:$E,$C92) | H92: =SUMIFS('g-expenses-sl'!$G:$G,'g-expenses-sl'!$A:$A,H$1,'g-expenses-sl'!$D:$D,"technology",'g-expenses-sl'!$E:$E,$C92) | I92: =SUMIFS('g-expenses-sl'!$G:$G,'g-expenses-sl'!$A:$A,I$1,'g-expenses-sl'!$D:$D,"technology",'g-expenses-sl'!$E:$E,$C92) | J92: =SUMIFS('g-expenses-sl'!$G:$G,'g-expenses-sl'!$A:$A,J$1,'g-expenses-sl'!$D:$D,"technology",'g-expenses-sl'!$E:$E,$C92) | K92: =SUMIFS('g-expenses-sl'!$G:$G,'g-expenses-sl'!$A:$A,K$1,'g-expenses-sl'!$D:$D,"technology",'g-expenses-sl'!$E:$E,$C92) | ... O92: =SUMIFS('g-expenses-sl'!$G:$G,'g-expenses-sl'!$A:$A,O$1,'g-expenses-sl'!$D:$D,"technology",'g-expenses-sl'!$E:$E,$C92) | P92: =SUM(D92:O92) | Q92: ->
A93: OPENAI | C93: OPENAI | D93: =SUMIFS('g-expenses-sl'!$G:$G,'g-expenses-sl'!$A:$A,D$1,'g-expenses-sl'!$D:$D,"technology",'g-expenses-sl'!$E:$E,$C93) | E93: =SUMIFS('g-expenses-sl'!$G:$G,'g-expenses-sl'!$A:$A,E$1,'g-expenses-sl'!$D:$D,"technology",'g-expenses-sl'!$E:$E,$C93) | F93: =SUMIFS('g-expenses-sl'!$G:$G,'g-expenses-sl'!$A:$A,F$1,'g-expenses-sl'!$D:$D,"technology",'g-expenses-sl'!$E:$E,$C93) | G93: =SUMIFS('g-expenses-sl'!$G:$G,'g-expenses-sl'!$A:$A,G$1,'g-expenses-sl'!$D:$D,"technology",'g-expenses-sl'!$E:$E,$C93) | H93: =SUMIFS('g-expenses-sl'!$G:$G,'g-expenses-sl'!$A:$A,H$1,'g-expenses-sl'!$D:$D,"technology",'g-expenses-sl'!$E:$E,$C93) | I93: =SUMIFS('g-expenses-sl'!$G:$G,'g-expenses-sl'!$A:$A,I$1,'g-expenses-sl'!$D:$D,"technology",'g-expenses-sl'!$E:$E,$C93) | J93: =SUMIFS('g-expenses-sl'!$G:$G,'g-expenses-sl'!$A:$A,J$1,'g-expenses-sl'!$D:$D,"technology",'g-expenses-sl'!$E:$E,$C93) | K93: =SUMIFS('g-expenses-sl'!$G:$G,'g-expenses-sl'!$A:$A,K$1,'g-expenses-sl'!$D:$D,"technology",'g-expenses-sl'!$E:$E,$C93) | ... O93: =SUMIFS('g-expenses-sl'!$G:$G,'g-expenses-sl'!$A:$A,O$1,'g-expenses-sl'!$D:$D,"technology",'g-expenses-sl'!$E:$E,$C93) | P93: =SUM(D93:O93) | Q93: ->
A94: PRODUCTHERO | C94: PRODUCTHERO | D94: =SUMIFS('g-expenses-sl'!$G:$G,'g-expenses-sl'!$A:$A,D$1,'g-expenses-sl'!$D:$D,"technology",'g-expenses-sl'!$E:$E,$C94) | E94: =SUMIFS('g-expenses-sl'!$G:$G,'g-expenses-sl'!$A:$A,E$1,'g-expenses-sl'!$D:$D,"technology",'g-expenses-sl'!$E:$E,$C94) | F94: =SUMIFS('g-expenses-sl'!$G:$G,'g-expenses-sl'!$A:$A,F$1,'g-expenses-sl'!$D:$D,"technology",'g-expenses-sl'!$E:$E,$C94) | G94: =SUMIFS('g-expenses-sl'!$G:$G,'g-expenses-sl'!$A:$A,G$1,'g-expenses-sl'!$D:$D,"technology",'g-expenses-sl'!$E:$E,$C94) | H94: =SUMIFS('g-expenses-sl'!$G:$G,'g-expenses-sl'!$A:$A,H$1,'g-expenses-sl'!$D:$D,"technology",'g-expenses-sl'!$E:$E,$C94) | I94: =SUMIFS('g-expenses-sl'!$G:$G,'g-expenses-sl'!$A:$A,I$1,'g-expenses-sl'!$D:$D,"technology",'g-expenses-sl'!$E:$E,$C94) | J94: =SUMIFS('g-expenses-sl'!$G:$G,'g-expenses-sl'!$A:$A,J$1,'g-expenses-sl'!$D:$D,"technology",'g-expenses-sl'!$E:$E,$C94) | K94: =SUMIFS('g-expenses-sl'!$G:$G,'g-expenses-sl'!$A:$A,K$1,'g-expenses-sl'!$D:$D,"technology",'g-expenses-sl'!$E:$E,$C94) | ... O94: =SUMIFS('g-expenses-sl'!$G:$G,'g-expenses-sl'!$A:$A,O$1,'g-expenses-sl'!$D:$D,"technology",'g-expenses-sl'!$E:$E,$C94) | P94: =SUM(D94:O94) | Q94: ->
A95: RAILWAY | C95: RAILWAY | D95: =SUMIFS('g-expenses-sl'!$G:$G,'g-expenses-sl'!$A:$A,D$1,'g-expenses-sl'!$D:$D,"technology",'g-expenses-sl'!$E:$E,$C95) | E95: =SUMIFS('g-expenses-sl'!$G:$G,'g-expenses-sl'!$A:$A,E$1,'g-expenses-sl'!$D:$D,"technology",'g-expenses-sl'!$E:$E,$C95) | F95: =SUMIFS('g-expenses-sl'!$G:$G,'g-expenses-sl'!$A:$A,F$1,'g-expenses-sl'!$D:$D,"technology",'g-expenses-sl'!$E:$E,$C95) | G95: =SUMIFS('g-expenses-sl'!$G:$G,'g-expenses-sl'!$A:$A,G$1,'g-expenses-sl'!$D:$D,"technology",'g-expenses-sl'!$E:$E,$C95) | H95: =SUMIFS('g-expenses-sl'!$G:$G,'g-expenses-sl'!$A:$A,H$1,'g-expenses-sl'!$D:$D,"technology",'g-expenses-sl'!$E:$E,$C95) | I95: =SUMIFS('g-expenses-sl'!$G:$G,'g-expenses-sl'!$A:$A,I$1,'g-expenses-sl'!$D:$D,"technology",'g-expenses-sl'!$E:$E,$C95) | J95: =SUMIFS('g-expenses-sl'!$G:$G,'g-expenses-sl'!$A:$A,J$1,'g-expenses-sl'!$D:$D,"technology",'g-expenses-sl'!$E:$E,$C95) | K95: =SUMIFS('g-expenses-sl'!$G:$G,'g-expenses-sl'!$A:$A,K$1,'g-expenses-sl'!$D:$D,"technology",'g-expenses-sl'!$E:$E,$C95) | ... O95: =SUMIFS('g-expenses-sl'!$G:$G,'g-expenses-sl'!$A:$A,O$1,'g-expenses-sl'!$D:$D,"technology",'g-expenses-sl'!$E:$E,$C95) | P95: =SUM(D95:O95) | Q95: ->
... A98: YUMAAI | C98: YUMAAI | D98: =SUMIFS('g-expenses-sl'!$G:$G,'g-expenses-sl'!$A:$A,D$1,'g-expenses-sl'!$D:$D,"technology",'g-expenses-sl'!$E:$E,$C98) | E98: =SUMIFS('g-expenses-sl'!$G:$G,'g-expenses-sl'!$A:$A,E$1,'g-expenses-sl'!$D:$D,"technology",'g-expenses-sl'!$E:$E,$C98) | F98: =SUMIFS('g-expenses-sl'!$G:$G,'g-expenses-sl'!$A:$A,F$1,'g-expenses-sl'!$D:$D,"technology",'g-expenses-sl'!$E:$E,$C98) | G98: =SUMIFS('g-expenses-sl'!$G:$G,'g-expenses-sl'!$A:$A,G$1,'g-expenses-sl'!$D:$D,"technology",'g-expenses-sl'!$E:$E,$C98) | H98: =SUMIFS('g-expenses-sl'!$G:$G,'g-expenses-sl'!$A:$A,H$1,'g-expenses-sl'!$D:$D,"technology",'g-expenses-sl'!$E:$E,$C98) | I98: =SUMIFS('g-expenses-sl'!$G:$G,'g-expenses-sl'!$A:$A,I$1,'g-expenses-sl'!$D:$D,"technology",'g-expenses-sl'!$E:$E,$C98) | J98: =SUMIFS('g-expenses-sl'!$G:$G,'g-expenses-sl'!$A:$A,J$1,'g-expenses-sl'!$D:$D,"technology",'g-expenses-sl'!$E:$E,$C98) | K98: =SUMIFS('g-expenses-sl'!$G:$G,'g-expenses-sl'!$A:$A,K$1,'g-expenses-sl'!$D:$D,"technology",'g-expenses-sl'!$E:$E,$C98) | ... O98: =SUMIFS('g-expenses-sl'!$G:$G,'g-expenses-sl'!$A:$A,O$1,'g-expenses-sl'!$D:$D,"technology",'g-expenses-sl'!$E:$E,$C98) | P98: =SUM(D98:O98) | Q98: ->
P99: =SUM(D99:O99)
A100: PROFIT | D100: =D4-D32-D60 | E100: =E4-E32-E60 | F100: =F4-F32-F60 | G100: =G4-G32-G60 | H100: =H4-H32-H60 | I100: =I4-I32-I60 | J100: =J4-J32-J60 | K100: =K4-K32-K60 | ... O100: =O4-O32-O60 | P100: =SUM(D100:O100)
A101: % Profit / turnover | D101: =IFERROR(D100/D4,0) | E101: =IFERROR(E100/E4,0) | F101: =IFERROR(F100/F4,0) | G101: =IFERROR(G100/G4,0) | H101: =IFERROR(H100/H4,0) | I101: =IFERROR(I100/I4,0) | J101: =IFERROR(J100/J4,0) | K101: =IFERROR(K100/K4,0) | ... O101: =IFERROR(O100/O4,0) | P101: =SUM(D101:O101)

Sheet params
A1: <- Volver a P&G-SL
A2: key | B2: value
A3: entity | B3: SL
A4: year | B4: 2026
A5: generated_at_utc | B5: 2026-03-23T08:26:33Z

Sheet i-shopify-sl
A1: <- Volver a P&G-SL
A2: yyyymm | B2: entity | C2: line_item | D2: detail | E2: amount_net | F2: currency | G2: source | H2: invoice_number | I2: drive_url
A3: 202601 | B3: SL | C3: AT | D3: AT | E3: 5482.24 | F3: EUR | G3: finance.ventas_pyg
A4: 202601 | B4: SL | C4: BE | D4: BE | E4: 422.71 | F4: EUR | G4: finance.ventas_pyg
A5: 202601 | B5: SL | C5: DE | D5: DE | E5: 20924.16 | F5: EUR | G5: finance.ventas_pyg
A6: 202601 | B6: SL | C6: ES | D6: ES | E6: 61194.44 | F6: EUR | G6: finance.ventas_pyg
A7: 202601 | B7: SL | C7: FR | D7: FR | E7: 25590.35 | F7: EUR | G7: finance.ventas_pyg
A8: 202601 | B8: SL | C8: IT | D8: IT | E8: 18483.79 | F8: EUR | G8: finance.ventas_pyg
A9: 202601 | B9: SL | C9: NL | D9: NL | E9: 115.58 | F9: EUR | G9: finance.ventas_pyg
A10: 202601 | B10: SL | C10: PT | D10: PT | E10: 729.31 | F10: EUR | G10: finance.ventas_pyg
A11: 202601 | B11: SL | C11: XX | D11: XX | E11: 691.19 | F11: EUR | G11: finance.ventas_pyg
A12: 202602 | B12: SL | C12: AT | D12: AT | E12: 6077.94 | F12: EUR | G12: finance.ventas_pyg
A13: 202602 | B13: SL | C13: BE | D13: BE | E13: 998.68 | F13: EUR | G13: finance.ventas_pyg
A14: 202602 | B14: SL | C14: DE | D14: DE | E14: 19361.46 | F14: EUR | G14: finance.ventas_pyg
... A28: 202603 | B28: SL | C28: XX | D28: XX | E28: 227.22 | F28: EUR | G28: finance.ventas_pyg

Sheet i-marketplaces-sl
A1: <- Volver a P&G-SL
A2: yyyymm | B2: entity | C2: line_item | D2: detail | E2: amount_net | F2: currency | G2: source | H2: invoice_number | I2: drive_url
A3: 202601 | B3: SL | C3: HANNUN | D3: orders | E3: 1419.7 | F3: EUR | G3: documents | H3: 2026-0008 | I3: https://drive.google.com/file/d/1SRHb07OiC_DmTMCjAnZJpaif5amIl7Fl/view?usp=drivesdk
A4: 202602 | B4: SL | C4: HANNUN | D4: orders | E4: 1128.42 | F4: EUR | G4: documents | H4: 2026-0013 | I4: https://drive.google.com/file/d/1CmAISLBvUVe78NnGfNvevigmLiHzSEsg/view?usp=drivesdk
A5: 202602 | B5: SL | C5: TOASTY | D5: b2b_partner | E5: 1746.6 | F5: EUR | G5: documents | H5: AS-99158 | I5: https://drive.google.com/file/d/1Caf6SbLhjNsliYTmwyaOj9tn_dQke6Ff/view?usp=drivesdk
A6: 202603 | B6: SL | C6: CHOOSE | D6: campaign | E6: 15609.96 | F6: EUR | G6: documents | H6: AS-101940 | I6: https://drive.google.com/file/d/18nd9g2717srK8fdaeAjNuV-HtW9zUU3A/view?usp=drivesdk

Sheet i-rappels-sl
A1: <- Volver a P&G-SL
A2: yyyymm | B2: entity | C2: line_item | D2: detail | E2: amount_net | F2: currency | G2: source | H2: invoice_number | I2: drive_url
A3: 202601 | B3: SL | C3: LIVITUM | D3: rappels | E3: -1118.95 | F3: EUR | G3: documents | H3: A_2026-0006 | I3: https://drive.google.com/file/d/1TatcT909r9lQss48nnCsBt5kjo76SoJK/view?usp=drivesdk

Sheet i-supplies-sl
A1: <- Volver a P&G-SL
A2: yyyymm | B2: entity | C2: line_item | D2: detail | E2: amount_net | F2: currency | G2: source | H2: invoice_number | I2: drive_url
A3: 202601 | B3: SL | C3: REVER | D3: supplied_note | E3: -1753.49 | F3: EUR | G3: documents | H3: SUPPLIED-202512 | I3: https://drive.google.com/file/d/1fcDMocaa4cpTPjITHzeqYj2_zqO3NWYG/view?usp=drivesdk
A4: 202601 | B4: SL | C4: REVER | D4: supplied_note | E4: -422.97 | F4: EUR | G4: documents | H4: SUPPLIED-202601 | I4: https://drive.google.com/file/d/1JrhdQBAxThJrJre0y6m_O_546LXVrueL/view?usp=drivesdk
A5: 202602 | B5: SL | C5: REVER | D5: supplied_note | E5: -522.54 | F5: EUR | G5: documents | H5: SUPPLIED-202602 | I5: https://drive.google.com/file/d/1P7U8R2vW7HJBpC4dFcTfQ6Fl5v7lZf-T/view?usp=drivesdk

Sheet i-services-sl
A1: <- Volver a P&G-SL
A2: yyyymm | B2: entity | C2: line_item | D2: detail | E2: amount_net | F2: currency | G2: source | H2: invoice_number | I2: drive_url
A3: 202601 | B3: SL | C3: HANNUN | D3: renting_cnc | E3: 1661.16 | F3: EUR | G3: documents | H3: 2026-0006 | I3: https://drive.google.com/file/d/1ZNEswgq6fNRQmQBRT6GcjgdY_sepQuvN/view?usp=drivesdk
A4: 202601 | B4: SL | C4: HANNUN | D4: staff | E4: 1191.18 | F4: EUR | G4: documents | H4: 2026-0007 | I4: https://drive.google.com/file/d/1NSgOhocDqu_GBFUbkAHX1ly92CIuLykN/view?usp=drivesdk
A5: 202601 | B5: SL | C5: Inc | D5: shared_services | E5: 7334.44 | F5: EUR | G5: documents:shared_services | H5: 2026-0009 | I5: https://drive.google.com/file/d/1f0y-ak8qjEua6xrzfcweFpWZqOtA8h9C/view?usp=drivesdk
A6: 202601 | B6: SL | C6: Ltd | D6: shared_services | E6: 10732.87 | F6: EUR | G6: documents:shared_services | H6: 2026-0010 | I6: https://drive.google.com/file/d/1DVbcrKI34TY_XRmPCWYxFfktOzy1Bqmr/view?usp=drivesdk
A7: 202602 | B7: SL | C7: HANNUN | D7: staff | E7: 1191.18 | F7: EUR | G7: documents | H7: 2026-0011 | I7: https://drive.google.com/file/d/1il-dTsdyMbUZFKcN_lnqoNWLpAFjKN7A/view?usp=drivesdk
A8: 202602 | B8: SL | C8: Inc | D8: shared_services | E8: 8462.36 | F8: EUR | G8: documents:shared_services | H8: 2026-0014 | I8: https://drive.google.com/file/d/1rlqcAuJUaWxt0Udjbpq3E6fP_lfRq58_/view?usp=drivesdk
A9: 202602 | B9: SL | C9: Ltd | D9: shared_services | E9: 13068.98 | F9: EUR | G9: documents:shared_services | H9: 2026-0015 | I9: https://drive.google.com/file/d/1pNRISEZAlDdg2kXsh98mNhDndQFk42mV/view?usp=drivesdk
A10: 202602 | B10: SL | C10: QHANDS | D10: renting_cnc | E10: 1661.16 | F10: EUR | G10: documents | H10: 2026-0012 | I10: https://drive.google.com/file/d/1m_ONfUFq-mhxCI2SVs0iWw4Ss3ohvEPU/view?usp=drivesdk

Sheet g-expenses-sl
A1: <- Volver a P&G-SL
A2: yyyymm | B2: entity | C2: category | D2: subcategory | E2: supplier_code | F2: detail | G2: amount_net | H2: currency | I2: source | J2: invoice_number | K2: drive_url
A3: 202601 | B3: SL | C3: opex | D3: technology | E3: RAILWAY | G3: 20 | H3: USD | I3: documents | J3: 1602C2F5-0015 | K3: https://drive.google.com/file/d/1ih8AMHNM7ZQvhfJOhpZ3dpM0Bv3oyAA-/view?usp=drivesdk
A4: 202602 | B4: SL | C4: opex | D4: technology | E4: RAILWAY | G4: 20 | H4: USD | I4: documents | J4: 1602C2F5-0016 | K4: https://drive.google.com/file/d/1nql7QpcMxbeNk-s_Ku_8yFOrf0x8QVss/view?usp=drivesdk
A5: 202601 | B5: SL | C5: opex | D5: technology | E5: ADOBE | G5: 33.49 | H5: EUR | I5: documents | J5: IEE2026001813920 | K5: https://drive.google.com/file/d/1bfLhUT5wi1Zga5-YKV-y_tFqtaYvhqG_/view?usp=drivesdk
A6: 202601 | B6: SL | C6: cogs | D6: manufacturing | E6: APPHOTOCAN | G6: 29.22 | H6: EUR | I6: documents | J6: 26-1-147 | K6: https://drive.google.com/file/d/1R3F1S4DkkMdWjQCije5h6JcXrv2oanjz/view?usp=drivesdk
A7: 202601 | B7: SL | C7: cogs | D7: manufacturing | E7: APPHOTOES | G7: 4472.74 | H7: EUR | I7: documents | J7: 1-1115 | K7: https://drive.google.com/file/d/1WUqPHPgca1EQI6FEQ45b4g1OBJLlBFy7/view?usp=drivesdk
A8: 202601 | B8: SL | C8: cogs | D8: manufacturing | E8: APPHOTOES | G8: 2583.61 | H8: EUR | I8: documents | J8: 1-412 | K8: https://drive.google.com/file/d/1HSHnKuD3wT5VaYKRyqQtc1Kn3jvbtI5z/view?usp=drivesdk
A9: 202601 | B9: SL | C9: cogs | D9: manufacturing | E9: APPHOTOES | G9: 1083.14 | H9: EUR | I9: documents | J9: 1-527 | K9: https://drive.google.com/file/d/1QiOFa-Pu55ImYk1EgtLQ-1AJeKteGKKN/view?usp=drivesdk
A10: 202601 | B10: SL | C10: cogs | D10: manufacturing | E10: APPHOTOES | G10: 9758.59 | H10: EUR | I10: documents | J10: 1-841 | K10: https://drive.google.com/file/d/1Nv_kf16K0jbiVtLvDOdsF2s81ubDK86-/view?usp=drivesdk
A11: 202601 | B11: SL | C11: opex | D11: technology | E11: CANVA | G11: 9.91 | H11: EUR | I11: documents | J11: 04765-19148572 | K11: https://drive.google.com/file/d/1F1T1ZbmwTiAvZymdmK5UN5ILkYzAcyjE/view?usp=drivesdk
A12: 202601 | B12: SL | C12: opex | D12: administration | E12: CLARIS | G12: 808.08 | H12: EUR | I12: documents | J12: F00036/26 | K12: https://drive.google.com/file/d/1sZGtXApoakTTNvLB9pud8pMEBdr3FgDZ/view?usp=drivesdk
A13: 202601 | B13: SL | C13: cogs | D13: logistics | E13: CORREOS | G13: 155.8 | H13: EUR | I13: documents | J13: 4004550727 | K13: https://drive.google.com/file/d/13rt7yQ8sQuRvlpYE9WCitcMHEZMp3m_O/view?usp=drivesdk
A14: 202601 | B14: SL | C14: cogs | D14: logistics | E14: CORREOS | G14: 397.96 | H14: EUR | I14: documents | J14: 4004566874 | K14: https://drive.google.com/file/d/19fXXs3bT9JRPi6FOU7JWx3Antd-__jQl/view?usp=drivesdk
... A20: 202601 | B20: SL | C20: opex | D20: technology | E20: GODADDY | G20: 17.24 | H20: EUR | I20: documents | J20: 3994794936 | K20: https://drive.google.com/file/d/1wr9Nejy--4BUDpyg8riD4WzBFOQ_RYAA/view?usp=drivesdk
A21: 202601 | B21: SL | C21: opex | D21: marketing | E21: GOOGLEADS | F21: eu | G21: 24746.34 | H21: EUR | I21: documents | J21: 5489506571 | K21: https://drive.google.com/file/d/18pxQbj0cm3VVE381utczsaBPUOMg2_rE/view?usp=drivesdk
A22: 202601 | B22: SL | C22: opex | D22: marketing | E22: GOOGLEADS | F22: uk | G22: 2298.67 | H22: EUR | I22: documents | J22: 5489506571 | K22: https://drive.google.com/file/d/18pxQbj0cm3VVE381utczsaBPUOMg2_rE/view?usp=drivesdk
A23: 202601 | B23: SL | C23: opex | D23: marketing | E23: GOOGLEADS | F23: us | G23: 2119.05 | H23: EUR | I23: documents | J23: 5489506571 | K23: https://drive.google.com/file/d/18pxQbj0cm3VVE381utczsaBPUOMg2_rE/view?usp=drivesdk
A24: 202601 | B24: SL | C24: opex | D24: technology | E24: GOOGLEWORKSPACE | G24: 194.4 | H24: EUR | I24: documents | J24: 5472439457 | K24: https://drive.google.com/file/d/1iux2hxJTx8pApkdRTQ8TxrWAycKskSLW/view?usp=drivesdk
A25: 202601 | B25: SL | C25: opex | D25: technology | E25: GORGIAS | G25: 201.2 | H25: USD | I25: documents | J25: INC-01-2026-35934 | K25: https://drive.google.com/file/d/1cCVWMZjXH5GZ4KJ7Owu69neJD3Mu8nhQ/view?usp=drivesdk
A26: 202601 | B26: SL | C26: opex | D26: technology | E26: HETZNER | G26: 10.9 | H26: EUR | I26: documents | J26: 084000695806 | K26: https://drive.google.com/file/d/1mtjFeFve-rSAPTA0bq7zwh6FvresB1tx/view?usp=drivesdk
A27: 202601 | B27: SL | C27: opex | D27: technology | E27: KONVOAI | G27: 114.89 | H27: EUR | I27: documents | J27: B5F7DF3C-6721 | K27: https://drive.google.com/file/d/1FvjQkV9yZwLwYyh31yDEv4r6Ws9x-Gee/view?usp=drivesdk
A28: 202601 | B28: SL | C28: opex | D28: technology | E28: KONVOAI | G28: 339 | H28: EUR | I28: documents | J28: B5F7DF3C-6940 | K28: https://drive.google.com/file/d/1saa91nUMC9fiC166aUrnROE5ZHw8d_r6/view?usp=drivesdk
A29: 202601 | B29: SL | C29: opex | D29: technology | E29: MASMOVIL | G29: 5 | H29: EUR | I29: documents | J29: MC260001070524 | K29: https://drive.google.com/file/d/1Dqpxqnn8K6M513jJX6b-_iaNJoHc9CRf/view?usp=drivesdk
A30: 202601 | B30: SL | C30: opex | D30: marketing | E30: METAADS | F30: eu | G30: 20319.32 | H30: EUR | I30: documents | J30: 250807809 | K30: https://drive.google.com/file/d/18umjaalA1qWOFkhllNu22AbrnmcOGohV/view?usp=drivesdk
A31: 202601 | B31: SL | C31: opex | D31: marketing | E31: METAADS | F31: uk | G31: 3385.46 | H31: EUR | I31: documents | J31: 250807809 | K31: https://drive.google.com/file/d/18umjaalA1qWOFkhllNu22AbrnmcOGohV/view?usp=drivesdk
A32: 202601 | B32: SL | C32: opex | D32: marketing | E32: METAADS | F32: us | G32: 1779.68 | H32: EUR | I32: documents | J32: 250807809 | K32: https://drive.google.com/file/d/18umjaalA1qWOFkhllNu22AbrnmcOGohV/view?usp=drivesdk
A33: 202601 | B33: SL | C33: opex | D33: technology | E33: MICROSOFT | G33: 30.87 | H33: EUR | I33: documents | J33: G135222851 | K33: https://drive.google.com/file/d/1YkkVd0CygsXrJ-x-3pub1Sw9g6ZsG1la/view?usp=drivesdk
A34: 202601 | B34: SL | C34: opex | D34: technology | E34: OPENAI | F34: api_usage | G34: 10 | H34: USD | I34: documents | J34: BZHJNTUB0001 | K34: https://drive.google.com/file/d/1c_a7u0uC_WNkVQzPENEHHzZf2GoRgYzp/view?usp=drivesdk
A35: 202601 | B35: SL | C35: opex | D35: technology | E35: OPENAI | F35: chatgpt_plus | G35: 19.01 | H35: EUR | I35: documents | J35: 7BSDV5AM0001 | K35: https://drive.google.com/file/d/1Z8crn0ZC5tm2cibuFjiaNGAUQ32eDz4H/view?usp=drivesdk
A36: 202601 | B36: SL | C36: cogs | D36: manufacturing | E36: PRESSING | G36: 28979.31 | H36: EUR | I36: documents | J36: FAC/2026/26100000691 | K36: https://drive.google.com/file/d/1OUc0Fa83_INuKCsZQC_juJA8WSWOmU7e/view?usp=drivesdk
A37: 202601 | B37: SL | C37: opex | D37: technology | E37: PRODUCTHERO | G37: 134 | H37: EUR | I37: documents | J37: 205588 | K37: https://drive.google.com/file/d/14DyM0O39wOTD_wOQwkZ2nqk44A4Xr0Pd/view?usp=drivesdk
A38: 202601 | B38: SL | C38: opex | D38: technology | E38: REVER | G38: 434.8 | H38: EUR | I38: documents | J38: RVR-16471 | K38: https://drive.google.com/file/d/1MOlMl6uaY6n-XUO8ZDVih0oyxqYCdtvw/view?usp=drivesdk
A39: 202601 | B39: SL | C39: opex | D39: technology | E39: REVER | G39: 79 | H39: EUR | I39: documents | J39: RVR-16823 | K39: https://drive.google.com/file/d/15PYo6Nf9Rs0V66jula2uxmSQ1q_sREm9/view?usp=drivesdk
A40: 202601 | B40: SL | C40: opex | D40: technology | E40: SHOPIFY | G40: 2674.4 | H40: USD | I40: documents | J40: 479105361 | K40: https://drive.google.com/file/d/1xcXRJuhK0s-9Giwr-lbqS68FlhkSzTWB/view?usp=drivesdk
A41: 202601 | B41: SL | C41: cogs | D41: logistics | E41: SPRINGGDS | G41: 3.3 | H41: EUR | I41: documents | J41: E2600764 | K41: https://drive.google.com/file/d/1VbeIR7bk7enIlMQGnI8ZlR-KDaMoHDKn/view?usp=drivesdk
A42: 202601 | B42: SL | C42: opex | D42: administration | E42: TORRAS | G42: 15 | H42: EUR | I42: documents | J42: 7/186 | K42: https://drive.google.com/file/d/1PKaZMRQ1ZsO4JALcKcucZLVdRyUxpOON/view?usp=drivesdk
A43: 202601 | B43: SL | C43: cogs | D43: logistics | E43: UPS | G43: 204.42 | H43: EUR | I43: documents | J43: 326821409 | K43: https://drive.google.com/file/d/1j2ya4FHybtMpbOwe_dwCTFuK0BuXysGa/view?usp=drivesdk
A44: 202601 | B44: SL | C44: cogs | D44: logistics | E44: UPS | G44: 440.99 | H44: EUR | I44: documents | J44: 326838548 | K44: https://drive.google.com/file/d/1zXVkELtv1Sfm3Hs-3PVSAH4pEWbvWaOX/view?usp=drivesdk
A45: 202601 | B45: SL | C45: cogs | D45: logistics | E45: UPS | G45: 2253.28 | H45: EUR | I45: documents | J45: 326867966 | K45: https://drive.google.com/file/d/1icRXW3dXluuRK-dzvuDcN-maR8sKfRW3/view?usp=drivesdk
A46: 202601 | B46: SL | C46: cogs | D46: logistics | E46: UPS | G46: 602.88 | H46: EUR | I46: documents | J46: 326899416 | K46: https://drive.google.com/file/d/148ysN83vJtMLS2_lbKu7r5cH1NMHbVNL/view?usp=drivesdk
A47: 202601 | B47: SL | C47: cogs | D47: logistics | E47: UPS | G47: 604.6 | H47: EUR | I47: documents | J47: 326966374 | K47: https://drive.google.com/file/d/1P3C1c_Df7dkPtnnAevEEMApNVP550O_O/view?usp=drivesdk
... A71: 202602 | B71: SL | C71: cogs | D71: logistics | E71: GLS | G71: 15947.02 | H71: EUR | I71: documents | J71: 20260082 | K71: https://drive.google.com/file/d/1KY46ho8xsJpWU6Q3w32ZWRQ8btywV8Ax/view?usp=drivesdk
A72: 202602 | B72: SL | C72: opex | D72: marketing | E72: GOOGLEADS | F72: eu | G72: 19199.14 | H72: EUR | I72: documents | J72: 5509802536 | K72: https://drive.google.com/file/d/192ghVBMKOyFtFrKk5lPoccixcsZlK4GH/view?usp=drivesdk
A73: 202602 | B73: SL | C73: opex | D73: marketing | E73: GOOGLEADS | F73: uk | G73: 5006.17 | H73: EUR | I73: documents | J73: 5509802536 | K73: https://drive.google.com/file/d/192ghVBMKOyFtFrKk5lPoccixcsZlK4GH/view?usp=drivesdk
A74: 202602 | B74: SL | C74: opex | D74: marketing | E74: GOOGLEADS | F74: us | G74: 3345.8 | H74: EUR | I74: documents | J74: 5509802536 | K74: https://drive.google.com/file/d/192ghVBMKOyFtFrKk5lPoccixcsZlK4GH/view?usp=drivesdk
A75: 202602 | B75: SL | C75: opex | D75: technology | E75: GOOGLEWORKSPACE | G75: 201.91 | H75: EUR | I75: documents | J75: 5505030303 | K75: https://drive.google.com/file/d/1_odcqxdXxEYZNzgQx5UzslhIG3hh5krH/view?usp=drivesdk
A76: 202602 | B76: SL | C76: opex | D76: technology | E76: GORGIAS | G76: 120 | H76: USD | I76: documents | J76: INC-02-2026-50341 | K76: https://drive.google.com/file/d/1tAciOjLJ3-E_udDrY3cL0A7b-CfOvIlm/view?usp=drivesdk
A77: 202602 | B77: SL | C77: opex | D77: administration | E77: HANNUN | F77: administration | G77: 43192.69 | H77: EUR | I77: documents | J77: VTA/26-007207 | K77: https://drive.google.com/file/d/1FAnrtU5R53FcPCbpc94bYjpEq0clb5Pm/view?usp=drivesdk
A78: 202601 | B78: SL | C78: opex | D78: administration | E78: HANNUN | F78: office | G78: 175 | H78: EUR | I78: documents | J78: VTA/26-010327 | K78: https://drive.google.com/file/d/1E8JfN7YXvjRIfPjaLKj_8zJSQJ-990YT/view?usp=drivesdk
A79: 202602 | B79: SL | C79: opex | D79: administration | E79: HANNUN | F79: office | G79: 175 | H79: EUR | I79: documents | J79: VTA/26-010329 | K79: https://drive.google.com/file/d/1r2Hw0N7VZ6vvloF4IqY4SxfuvX_2VozE/view?usp=drivesdk
A80: 202601 | B80: SL | C80: opex | D80: administration | E80: HANNUN | F80: services | G80: 1504.92 | H80: EUR | I80: documents | J80: VTA/26-010328 | K80: https://drive.google.com/file/d/1PRJ__aaxThVGTbIcvHAJI7pgUFchpvsa/view?usp=drivesdk
A81: 202602 | B81: SL | C81: opex | D81: administration | E81: HANNUN | F81: services | G81: 1504.92 | H81: EUR | I81: documents | J81: VTA/26-010330 | K81: https://drive.google.com/file/d/1HgIvIqgrCSyQY0-INtfhp-GPqb5Et1eA/view?usp=drivesdk
A82: 202602 | B82: SL | C82: opex | D82: technology | E82: HETZNER | G82: 10.9 | H82: EUR | I82: documents | J82: 086000751422 | K82: https://drive.google.com/file/d/1bMdMTYSXLytnvUKxINvo3C-fdr43SmgJ/view?usp=drivesdk
A83: 202602 | B83: SL | C83: opex | D83: technology | E83: KONVOAI | G83: 136.96 | H83: EUR | I83: documents | J83: B5F7DF3C-7132 | K83: https://drive.google.com/file/d/1n2bq_tMI3rNE2XsFpxvWnwo1ZZV6_K21/view?usp=drivesdk
A84: 202602 | B84: SL | C84: opex | D84: technology | E84: KONVOAI | G84: 339 | H84: EUR | I84: documents | J84: B5F7DF3C-7296 | K84: https://drive.google.com/file/d/1Mbfxr1V40xsgbj8F0soExM05QND6zjoa/view?usp=drivesdk
A85: 202602 | B85: SL | C85: opex | D85: technology | E85: MASMOVIL | G85: 5 | H85: EUR | I85: documents | J85: MC260002345804 | K85: https://drive.google.com/file/d/1WOvzAAmEygTW3UfGCE2EpvFGcNYl4yVq/view?usp=drivesdk
A86: 202602 | B86: SL | C86: opex | D86: marketing | E86: METAADS | F86: eu | G86: 15883.55 | H86: EUR | I86: documents | J86: 251380763 | K86: https://drive.google.com/file/d/1fDDyyoah7JlWMHXzqFDIqm2howZDBJMq/view?usp=drivesdk
A87: 202602 | B87: SL | C87: opex | D87: marketing | E87: METAADS | F87: uk | G87: 2794.04 | H87: EUR | I87: documents | J87: 251380763 | K87: https://drive.google.com/file/d/1fDDyyoah7JlWMHXzqFDIqm2howZDBJMq/view?usp=drivesdk
A88: 202602 | B88: SL | C88: opex | D88: marketing | E88: METAADS | F88: us | G88: 1397.4 | H88: EUR | I88: documents | J88: 251380763 | K88: https://drive.google.com/file/d/1fDDyyoah7JlWMHXzqFDIqm2howZDBJMq/view?usp=drivesdk
A89: 202602 | B89: SL | C89: opex | D89: technology | E89: MICROSOFT | G89: 30.87 | H89: EUR | I89: documents | J89: G140910268 | K89: https://drive.google.com/file/d/1IS2fSxolw6pxcI9vC65EJRYlFK7zyUTY/view?usp=drivesdk
A90: 202602 | B90: SL | C90: opex | D90: technology | E90: OPENAI | F90: api_usage | G90: 10.12 | H90: USD | I90: documents | J90: BZHJNTUB0003 | K90: https://drive.google.com/file/d/1bbYR8-vHGj7nUKVcEnARnepPzYzNIFVw/view?usp=drivesdk
A91: 202602 | B91: SL | C91: opex | D91: technology | E91: OPENAI | F91: api_usage | G91: 10.19 | H91: USD | I91: documents | J91: BZHJNTUB0005 | K91: https://drive.google.com/file/d/1s-Ni6ccpvcuZUGwwhFepiSbUNzPwXVDG/view?usp=drivesdk
A92: 202602 | B92: SL | C92: opex | D92: technology | E92: OPENAI | F92: api_usage | G92: 30 | H92: USD | I92: documents | J92: BZHJNTUB0006 | K92: https://drive.google.com/file/d/1j0GTnf9iA8T0YG7zocdvmE1v-yFf-dmk/view?usp=drivesdk
A93: 202602 | B93: SL | C93: opex | D93: technology | E93: OPENAI | F93: api_usage | G93: 10.41 | H93: USD | I93: documents | J93: BZHJNTUB0007 | K93: https://drive.google.com/file/d/1kgfYW187O8CHpqvovwje1T5Vb0O1df6d/view?usp=drivesdk
A94: 202602 | B94: SL | C94: opex | D94: technology | E94: OPENAI | F94: receipt | G94: 10.13 | H94: USD | I94: documents | J94: BZHJNTUB0004 | K94: https://drive.google.com/file/d/1ylJiskEHkRFsuhK4EXI9Mv5Hk31tTSeX/view?usp=drivesdk
A95: 202602 | B95: SL | C95: cogs | D95: manufacturing | E95: PRESSING | G95: 33510.62 | H95: EUR | I95: documents | J95: FAC/2026/26100001651 | K95: https://drive.google.com/file/d/1Ht3FP9y_KBG3F1Wui0f7dj36Nz4gORY9/view?usp=drivesdk
A96: 202602 | B96: SL | C96: opex | D96: technology | E96: PRODUCTHERO | G96: 134 | H96: EUR | I96: documents | J96: 211723 | K96: https://drive.google.com/file/d/1axe5iqNHDnZKEyTVyAhJ5hBtI1BR5ejL/view?usp=drivesdk
A97: 202602 | B97: SL | C97: opex | D97: technology | E97: REVER | G97: 79 | H97: EUR | I97: documents | J97: RVR-17688 | K97: https://drive.google.com/file/d/1D3oOwMbnoMx_ZwdzSUQ07lRdDelVCXX6/view?usp=drivesdk
A98: 202602 | B98: SL | C98: opex | D98: technology | E98: SHOPIFY | G98: 2812.25 | H98: USD | I98: documents | J98: 493806587 | K98: https://drive.google.com/file/d/1FNZalAzXj8a7ZNUt2CefEIFu_sLZ6iOY/view?usp=drivesdk
A99: 202602 | B99: SL | C99: opex | D99: administration | E99: TORRAS | G99: 15 | H99: EUR | I99: documents | J99: 7/517 | K99: https://drive.google.com/file/d/1ryYPmeaeN0WBdXxhk4O9pmdF4BlNsACt/view?usp=drivesdk
A100: 202602 | B100: SL | C100: cogs | D100: logistics | E100: UPS | G100: 643.82 | H100: EUR | I100: documents | J100: 326997856 | K100: https://drive.google.com/file/d/1FyBHZEA9qWMwRhMfdTuL7ySwcplaqQc2/view?usp=drivesdk
A101: 202602 | B101: SL | C101: cogs | D101: logistics | E101: UPS | G101: 629.73 | H101: EUR | I101: documents | J101: 327030108 | K101: https://drive.google.com/file/d/1iPkhcnUQ6IlOI2t9Y4lt6fcN9NoE8559/view?usp=drivesdk
A102: 202602 | B102: SL | C102: cogs | D102: logistics | E102: UPS | G102: 512.62 | H102: EUR | I102: documents | J102: 327061645 | K102: https://drive.google.com/file/d/1nrrH_8TfwdiHGNLlFgfu6hEx8mBDTA67/view?usp=drivesdk
A103: 202602 | B103: SL | C103: cogs | D103: logistics | E103: UPS | G103: 40.32 | H103: EUR | I103: documents | J103: 838088024 | K103: https://drive.google.com/file/d/1Lq08NNbxsMBp7B7MMjUiEknDIr3kxPc0/view?usp=drivesdk
A104: 202602 | B104: SL | C104: opex | D104: technology | E104: YUMAAI | G104: 440 | H104: EUR | I104: documents | J104: OQXBYXMP-0005 | K104: https://drive.google.com/file/d/1y53mv0-BjFCp7Z4Tp9mguo1WuS7RRlVK/view?usp=drivesdk
A105: 202603 | B105: SL | C105: cogs | D105: manufacturing | E105: APPHOTOES | G105: 697.99 | H105: EUR | I105: documents | J105: 1-2805 | K105: https://drive.google.com/file/d/1n1TdGRm0xbbUrhiWxso3ucgcPhj4jbzx/view?usp=drivesdk
A106: 202603 | B106: SL | C106: cogs | D106: manufacturing | E106: APPHOTOES | G106: 26.57 | H106: EUR | I106: documents | J106: 1-2806 | K106: https://drive.google.com/file/d/1ao5r16qm7GhBSrW3YeiF3erPmxlcHELA/view?usp=drivesdk
... A111: 202603 | B111: SL | C111: cogs | D111: manufacturing | E111: APPHOTOES | G111: 4435.99 | H111: EUR | I111: documents | J111: 1-3283 | K111: https://drive.google.com/file/d/1MkhCT3OZenS4bJf5_J2qB8oGGw8oFzkf/view?usp=drivesdk
A112: 202603 | B112: SL | C112: cogs | D112: manufacturing | E112: ARTLINK | F112: manufacturing | G112: 570 | H112: EUR | I112: documents | J112: 000203570 | K112: https://drive.google.com/file/d/1cfzsuLvXSAtRD2pLnRBZ59veQeIWQKjQ/view?usp=drivesdk
A113: 202603 | B113: SL | C113: opex | D113: administration | E113: CLARIS | G113: 808.08 | H113: EUR | I113: documents | J113: F00658/26 | K113: https://drive.google.com/file/d/194sPXt7bz4RYudtr1LLnRSTHRD3IRfX_/view?usp=drivesdk
A114: 202603 | B114: SL | C114: cogs | D114: manufacturing | E114: DCT | G114: 2646.66 | H114: EUR | I114: documents | J114: 26-0463 | K114: https://drive.google.com/file/d/1d9bGOdNerfRkG8hm-9tNwNLOClNoUKV1/view?usp=drivesdk
A115: 202603 | B115: SL | C115: opex | D115: technology | E115: GORGIAS | G115: 126.4 | H115: USD | I115: documents | J115: INC-03-2026-64889 | K115: https://drive.google.com/file/d/1r5NeAkt6BuK7stM77wMD2GmwfOkmyuaE/view?usp=drivesdk
A116: 202603 | B116: SL | C116: opex | D116: administration | E116: HANNUN | F116: administration | G116: 30 | H116: EUR | I116: documents | J116: VTA/26-010337 | K116: https://drive.google.com/file/d/1jBhJD7kS5_SPwJKWbOaHjrF8mX4mpiT8/view?usp=drivesdk
A117: 202603 | B117: SL | C117: opex | D117: technology | E117: OPENAI | F117: api_usage | G117: 15 | H117: USD | I117: documents | J117: BZHJNTUB0008 | K117: https://drive.google.com/file/d/14mLVYewapKRBwsNP7f6wLOc4WRmROQLm/view?usp=drivesdk
A118: 202603 | B118: SL | C118: opex | D118: technology | E118: RAILWAY | G118: 21.36 | H118: USD | I118: documents | J118: 1602C2F5-0017 | K118: https://drive.google.com/file/d/1_zSaGhAEICAUBmqreT7FKVxXgv2-r3jW/view?usp=drivesdk
A119: 202603 | B119: SL | C119: opex | D119: administration | E119: TORRAS | G119: 15 | H119: EUR | I119: documents | J119: 7/800 | K119: https://drive.google.com/file/d/1qLKvi2Ja2apUNKYZBiLqZTt00IfYF7J2/view?usp=drivesdk
A120: 202603 | B120: SL | C120: opex | D120: administration | E120: VITALY | G120: 369 | H120: EUR | I120: documents | J120: IFC2603-18831 | K120: https://drive.google.com/file/d/1YylC1UsF8Mmxn_K1BFQWDm5IBpU5pT4S/view?usp=drivesdk
A121: 202603 | B121: SL | C121: opex | D121: technology | E121: YUMAAI | G121: 440 | H121: EUR | I121: documents | J121: OQXBYXMP-0006 | K121: https://drive.google.com/file/d/1Dfe3TUTMjwwXhP0sW7OA-brj3bzdreVa/view?usp=drivesdk
A122: 202601 | B122: SL | C122: cogs | D122: royalties | E122: ROYALTIES | G122: 13737 | H122: EUR | I122: artist_royalties_monthly_summary
A123: 202602 | B123: SL | C123: cogs | D123: royalties | E123: ROYALTIES | G123: 16662 | H123: EUR | I123: artist_royalties_monthly_summary
A124: 202601 | B124: SL | C124: opex | D124: staff | E124: PAYROLL | G124: 14731.84 | H124: EUR | I124: payroll_documents
A125: 202602 | B125: SL | C125: opex | D125: staff | E125: PAYROLL | G125: 14915.68 | H125: EUR | I125: payroll_documents

Sheet g-payment-fees-sl
A1: <- Volver a P&G-SL
A2: yyyymm | B2: entity | C2: supplier_code | D2: amount_net | E2: currency | F2: source
A3: 202601 | B3: SL | C3: PAYPAL | D3: 1405.82 | E3: EUR | F3: payment_fee_monthly_summary
A4: 202601 | B4: SL | C4: SHOPIFY | D4: 2616.7 | E4: EUR | F4: payment_fee_monthly_summary
A5: 202602 | B5: SL | C5: PAYPAL | D5: 1126.69 | E5: EUR | F5: payment_fee_monthly_summary
A6: 202602 | B6: SL | C6: SHOPIFY | D6: 2778.19 | E6: EUR | F6: payment_fee_monthly_summary
A7: 202603 | B7: SL | C7: PAYPAL | D7: 850.46 | E7: EUR | F7: payment_fee_monthly_summary
A8: 202603 | B8: SL | C8: SHOPIFY | D8: 2014.7 | E8: EUR | F8: payment_fee_monthly_summary

Sheet catalog-sl
A1: <- Volver a P&G-SL
A2: supplier_code | B2: supplier_name | C2: current_folder | D2: destination_path | E2: notes
A3: CORREOS | B3: CORREOS | C3: Correos | D3: expenses/cogs/logistics | E3: Peninsula/Baleares 21% IVA
A4: CORREOSCAN | B4: CORREOSCAN | C4: Correos | D4: expenses/cogs/logistics | E4: Canarias 7% IGIC
A5: GLS | B5: GLS | C5: GLS | D5: expenses/cogs/logistics | E5: OCR-based GLS parser via scanned PDF
A6: SPRINGGDS | B6: SPRINGGDS | C6: SPRING | D6: expenses/cogs/logistics | E6: Spring operating brand
A7: UPS | B7: UPS | C7: UPS | D7: expenses/cogs/logistics
A8: APPHOTOCAN | B8: APPHOTOCAN | C8: AP Photo | D8: expenses/cogs/manufacturing | E8: IGIC 7%
A9: APPHOTOES | B9: APPHOTOES | C9: AP Photo | D9: expenses/cogs/manufacturing
A10: ARTLINK | B10: ARTLINK | C10: Artlink | D10: expenses/cogs/manufacturing | E10: Frame purchases and related freight are treated as manufacturing
A11: DCT | B11: DCT | C11: DCT | D11: expenses/cogs/manufacturing
A12: PRESSING | B12: PRESSING | C12: Pressing | D12: expenses/cogs/manufacturing
A13: ROYALTIES | B13: ROYALTIES | C13: Artistas | D13: expenses/cogs/royalties | E13: Artist royalties received and issued by Artesta
A14: CLARIS | B14: CLARIS | C14: CLARIS | D14: expenses/opex/administration
A15: HANNUN | B15: HANNUN | C15: HANNUN | D15: expenses/opex/administration | E15: Bidirectional HANNUN relationship; incoming expense invoices and outgoing customer invoices
A16: NODA | B16: NODA | C16: NODA Asesores | D16: expenses/opex/administration
A17: TORRAS | B17: TORRAS | C17: TORRAS | D17: expenses/opex/administration
A18: VITALY | B18: VITALY | C18: Vitaly | D18: expenses/opex/administration | E18: Annual prevention and occupational health service
A19: GOOGLEADS | B19: GOOGLEADS | C19: Google | D19: expenses/opex/marketing
A20: METAADS | B20: METAADS | C20: Meta | D20: expenses/opex/marketing
A21: DOSCONSULTING | B21: DOSCONSULTING | C21: Nóminas | D21: expenses/opex/staff | E21: Monthly payroll management for SL
A22: ADOBE | B22: ADOBE | C22: ADOBE | D22: expenses/opex/technology
A23: CANVA | B23: CANVA | C23: canva | D23: expenses/opex/technology
A24: GODADDY | B24: GODADDY | C24: godaddy | D24: expenses/opex/technology
A25: GOOGLEWORKSPACE | B25: GOOGLEWORKSPACE | C25: Google | D25: expenses/opex/technology
A26: GORGIAS | B26: GORGIAS | C26: Gorgias | D26: expenses/opex/technology
A27: HETZNER | B27: HETZNER | C27: HETZNER | D27: expenses/opex/technology
A28: KONVOAI | B28: KONVOAI | C28: konvo | D28: expenses/opex/technology
A29: MASMOVIL | B29: MASMOVIL | C29: mas movil | D29: expenses/opex/technology
A30: MICROSOFT | B30: MICROSOFT | C30: MICROSOFT | D30: expenses/opex/technology
A31: OPENAI | B31: OPENAI | C31: chatgpt | D31: expenses/opex/technology | E31: Groups ChatGPT and API
A32: PRODUCTHERO | B32: PRODUCTHERO | C32: ProductHERO | D32: expenses/opex/technology
A33: RAILWAY | B33: RAILWAY | C33: RAILWAY | D33: expenses/opex/technology
A34: REVER | B34: REVER | C34: REVER | D34: expenses/opex/technology
A35: SHOPIFY | B35: SHOPIFY | C35: Shopify | D35: expenses/opex/technology
A36: YUMAAI | B36: YUMAAI | C36: YUMA | D36: expenses/opex/technology
A37: LIVITUM | B37: LIVITUM | C37: 709. Rappels | D37: income/other_income/rappels | E37: Rappel issued to Livitum
A38: CHOOSE | B38: CHOOSE | C38: CHOOSE | D38: income/sales/marketplaces | E38: Outgoing partner invoice
A39: TOASTY | B39: TOASTY | C39: TOASTY | D39: income/sales/marketplaces | E39: Outgoing partner invoice
A40: QHANDS | B40: QHANDS | C40: QHANDS | D40: income/shared-services | E40: Outgoing CNC rental invoice
