Workbook

Sheet P&G-SL
D1: 202601 | E1: 202602 | F1: 202603 | G1: 202604 | H1: 202605 | I1: 202606 | J1: 202607 | K1: 202608 | L1: 202609 | M1: 202610 | N1: 202611 | O1: 202612 | P1: TOTAL
A2: P&G SL 2026 | D2: Enero | E2: Febrero | F2: Marzo | G2: Abril | H2: Mayo | I2: Junio | J2: Julio | K2: Agosto | L2: Septiembre | M2: Octubre | N2: Noviembre | O2: Diciembre | P2: Total
A3: Actualizado: 23/03/2026 03:04 h
A4: Turnover | D4: =D5+D25 | E4: =E5+E25 | F4: =F5+F25 | G4: =G5+G25 | H4: =H5+H25 | I4: =I5+I25 | J4: =J5+J25 | K4: =K5+K25 | ... O4: =O5+O25 | P4: =SUM(D4:O4)
A5: Product sales | B5: Product sales | D5: =D6+D16+D20+D22 | E5: =E6+E16+E20+E22 | F5: =F6+F16+F20+F22 | G5: =G6+G16+G20+G22 | H5: =H6+H16+H20+H22 | I5: =I6+I16+I20+I22 | J5: =J6+J16+J20+J22 | K5: =K6+K16+K20+K22 | ... O5: =O6+O16+O20+O22 | P5: =SUM(D5:O5)
A6: Shopify | C6: Shopify | D6: =SUM(D7:D15) | E6: =SUM(E7:E15) | F6: =SUM(F7:F15) | G6: =SUM(G7:G15) | H6: =SUM(H7:H15) | I6: =SUM(I7:I15) | J6: =SUM(J7:J15) | K6: =SUM(K7:K15) | ... O6: =SUM(O7:O15) | P6: =SUM(D6:O6) | Q6: ->
A7: ES | C7: ES | D7: =SUMIFS('i-shopify-sl'!$E:$E,'i-shopify-sl'!$A:$A,D$1,'i-shopify-sl'!$C:$C,$C7) | E7: =SUMIFS('i-shopify-sl'!$E:$E,'i-shopify-sl'!$A:$A,E$1,'i-shopify-sl'!$C:$C,$C7) | F7: =SUMIFS('i-shopify-sl'!$E:$E,'i-shopify-sl'!$A:$A,F$1,'i-shopify-sl'!$C:$C,$C7) | G7: =SUMIFS('i-shopify-sl'!$E:$E,'i-shopify-sl'!$A:$A,G$1,'i-shopify-sl'!$C:$C,$C7) | H7: =SUMIFS('i-shopify-sl'!$E:$E,'i-shopify-sl'!$A:$A,H$1,'i-shopify-sl'!$C:$C,$C7) | I7: =SUMIFS('i-shopify-sl'!$E:$E,'i-shopify-sl'!$A:$A,I$1,'i-shopify-sl'!$C:$C,$C7) | J7: =SUMIFS('i-shopify-sl'!$E:$E,'i-shopify-sl'!$A:$A,J$1,'i-shopify-sl'!$C:$C,$C7) | K7: =SUMIFS('i-shopify-sl'!$E:$E,'i-shopify-sl'!$A:$A,K$1,'i-shopify-sl'!$C:$C,$C7) | ... O7: =SUMIFS('i-shopify-sl'!$E:$E,'i-shopify-sl'!$A:$A,O$1,'i-shopify-sl'!$C:$C,$C7) | P7: =SUM(D7:O7) | Q7: ->
A8: FR | C8: FR | D8: =SUMIFS('i-shopify-sl'!$E:$E,'i-shopify-sl'!$A:$A,D$1,'i-shopify-sl'!$C:$C,$C8) | E8: =SUMIFS('i-shopify-sl'!$E:$E,'i-shopify-sl'!$A:$A,E$1,'i-shopify-sl'!$C:$C,$C8) | F8: =SUMIFS('i-shopify-sl'!$E:$E,'i-shopify-sl'!$A:$A,F$1,'i-shopify-sl'!$C:$C,$C8) | G8: =SUMIFS('i-shopify-sl'!$E:$E,'i-shopify-sl'!$A:$A,G$1,'i-shopify-sl'!$C:$C,$C8) | H8: =SUMIFS('i-shopify-sl'!$E:$E,'i-shopify-sl'!$A:$A,H$1,'i-shopify-sl'!$C:$C,$C8) | I8: =SUMIFS('i-shopify-sl'!$E:$E,'i-shopify-sl'!$A:$A,I$1,'i-shopify-sl'!$C:$C,$C8) | J8: =SUMIFS('i-shopify-sl'!$E:$E,'i-shopify-sl'!$A:$A,J$1,'i-shopify-sl'!$C:$C,$C8) | K8: =SUMIFS('i-shopify-sl'!$E:$E,'i-shopify-sl'!$A:$A,K$1,'i-shopify-sl'!$C:$C,$C8) | ... O8: =SUMIFS('i-shopify-sl'!$E:$E,'i-shopify-sl'!$A:$A,O$1,'i-shopify-sl'!$C:$C,$C8) | P8: =SUM(D8:O8) | Q8: ->
A9: DE | C9: DE | D9: =SUMIFS('i-shopify-sl'!$E:$E,'i-shopify-sl'!$A:$A,D$1,'i-shopify-sl'!$C:$C,$C9) | E9: =SUMIFS('i-shopify-sl'!$E:$E,'i-shopify-sl'!$A:$A,E$1,'i-shopify-sl'!$C:$C,$C9) | F9: =SUMIFS('i-shopify-sl'!$E:$E,'i-shopify-sl'!$A:$A,F$1,'i-shopify-sl'!$C:$C,$C9) | G9: =SUMIFS('i-shopify-sl'!$E:$E,'i-shopify-sl'!$A:$A,G$1,'i-shopify-sl'!$C:$C,$C9) | H9: =SUMIFS('i-shopify-sl'!$E:$E,'i-shopify-sl'!$A:$A,H$1,'i-shopify-sl'!$C:$C,$C9) | I9: =SUMIFS('i-shopify-sl'!$E:$E,'i-shopify-sl'!$A:$A,I$1,'i-shopify-sl'!$C:$C,$C9) | J9: =SUMIFS('i-shopify-sl'!$E:$E,'i-shopify-sl'!$A:$A,J$1,'i-shopify-sl'!$C:$C,$C9) | K9: =SUMIFS('i-shopify-sl'!$E:$E,'i-shopify-sl'!$A:$A,K$1,'i-shopify-sl'!$C:$C,$C9) | ... O9: =SUMIFS('i-shopify-sl'!$E:$E,'i-shopify-sl'!$A:$A,O$1,'i-shopify-sl'!$C:$C,$C9) | P9: =SUM(D9:O9) | Q9: ->
A10: IT | C10: IT | D10: =SUMIFS('i-shopify-sl'!$E:$E,'i-shopify-sl'!$A:$A,D$1,'i-shopify-sl'!$C:$C,$C10) | E10: =SUMIFS('i-shopify-sl'!$E:$E,'i-shopify-sl'!$A:$A,E$1,'i-shopify-sl'!$C:$C,$C10) | F10: =SUMIFS('i-shopify-sl'!$E:$E,'i-shopify-sl'!$A:$A,F$1,'i-shopify-sl'!$C:$C,$C10) | G10: =SUMIFS('i-shopify-sl'!$E:$E,'i-shopify-sl'!$A:$A,G$1,'i-shopify-sl'!$C:$C,$C10) | H10: =SUMIFS('i-shopify-sl'!$E:$E,'i-shopify-sl'!$A:$A,H$1,'i-shopify-sl'!$C:$C,$C10) | I10: =SUMIFS('i-shopify-sl'!$E:$E,'i-shopify-sl'!$A:$A,I$1,'i-shopify-sl'!$C:$C,$C10) | J10: =SUMIFS('i-shopify-sl'!$E:$E,'i-shopify-sl'!$A:$A,J$1,'i-shopify-sl'!$C:$C,$C10) | K10: =SUMIFS('i-shopify-sl'!$E:$E,'i-shopify-sl'!$A:$A,K$1,'i-shopify-sl'!$C:$C,$C10) | ... O10: =SUMIFS('i-shopify-sl'!$E:$E,'i-shopify-sl'!$A:$A,O$1,'i-shopify-sl'!$C:$C,$C10) | P10: =SUM(D10:O10) | Q10: ->
A11: AT | C11: AT | D11: =SUMIFS('i-shopify-sl'!$E:$E,'i-shopify-sl'!$A:$A,D$1,'i-shopify-sl'!$C:$C,$C11) | E11: =SUMIFS('i-shopify-sl'!$E:$E,'i-shopify-sl'!$A:$A,E$1,'i-shopify-sl'!$C:$C,$C11) | F11: =SUMIFS('i-shopify-sl'!$E:$E,'i-shopify-sl'!$A:$A,F$1,'i-shopify-sl'!$C:$C,$C11) | G11: =SUMIFS('i-shopify-sl'!$E:$E,'i-shopify-sl'!$A:$A,G$1,'i-shopify-sl'!$C:$C,$C11) | H11: =SUMIFS('i-shopify-sl'!$E:$E,'i-shopify-sl'!$A:$A,H$1,'i-shopify-sl'!$C:$C,$C11) | I11: =SUMIFS('i-shopify-sl'!$E:$E,'i-shopify-sl'!$A:$A,I$1,'i-shopify-sl'!$C:$C,$C11) | J11: =SUMIFS('i-shopify-sl'!$E:$E,'i-shopify-sl'!$A:$A,J$1,'i-shopify-sl'!$C:$C,$C11) | K11: =SUMIFS('i-shopify-sl'!$E:$E,'i-shopify-sl'!$A:$A,K$1,'i-shopify-sl'!$C:$C,$C11) | ... O11: =SUMIFS('i-shopify-sl'!$E:$E,'i-shopify-sl'!$A:$A,O$1,'i-shopify-sl'!$C:$C,$C11) | P11: =SUM(D11:O11) | Q11: ->
A12: BE | C12: BE | D12: =SUMIFS('i-shopify-sl'!$E:$E,'i-shopify-sl'!$A:$A,D$1,'i-shopify-sl'!$C:$C,$C12) | E12: =SUMIFS('i-shopify-sl'!$E:$E,'i-shopify-sl'!$A:$A,E$1,'i-shopify-sl'!$C:$C,$C12) | F12: =SUMIFS('i-shopify-sl'!$E:$E,'i-shopify-sl'!$A:$A,F$1,'i-shopify-sl'!$C:$C,$C12) | G12: =SUMIFS('i-shopify-sl'!$E:$E,'i-shopify-sl'!$A:$A,G$1,'i-shopify-sl'!$C:$C,$C12) | H12: =SUMIFS('i-shopify-sl'!$E:$E,'i-shopify-sl'!$A:$A,H$1,'i-shopify-sl'!$C:$C,$C12) | I12: =SUMIFS('i-shopify-sl'!$E:$E,'i-shopify-sl'!$A:$A,I$1,'i-shopify-sl'!$C:$C,$C12) | J12: =SUMIFS('i-shopify-sl'!$E:$E,'i-shopify-sl'!$A:$A,J$1,'i-shopify-sl'!$C:$C,$C12) | K12: =SUMIFS('i-shopify-sl'!$E:$E,'i-shopify-sl'!$A:$A,K$1,'i-shopify-sl'!$C:$C,$C12) | ... O12: =SUMIFS('i-shopify-sl'!$E:$E,'i-shopify-sl'!$A:$A,O$1,'i-shopify-sl'!$C:$C,$C12) | P12: =SUM(D12:O12) | Q12: ->
A13: NL | C13: NL | D13: =SUMIFS('i-shopify-sl'!$E:$E,'i-shopify-sl'!$A:$A,D$1,'i-shopify-sl'!$C:$C,$C13) | E13: =SUMIFS('i-shopify-sl'!$E:$E,'i-shopify-sl'!$A:$A,E$1,'i-shopify-sl'!$C:$C,$C13) | F13: =SUMIFS('i-shopify-sl'!$E:$E,'i-shopify-sl'!$A:$A,F$1,'i-shopify-sl'!$C:$C,$C13) | G13: =SUMIFS('i-shopify-sl'!$E:$E,'i-shopify-sl'!$A:$A,G$1,'i-shopify-sl'!$C:$C,$C13) | H13: =SUMIFS('i-shopify-sl'!$E:$E,'i-shopify-sl'!$A:$A,H$1,'i-shopify-sl'!$C:$C,$C13) | I13: =SUMIFS('i-shopify-sl'!$E:$E,'i-shopify-sl'!$A:$A,I$1,'i-shopify-sl'!$C:$C,$C13) | J13: =SUMIFS('i-shopify-sl'!$E:$E,'i-shopify-sl'!$A:$A,J$1,'i-shopify-sl'!$C:$C,$C13) | K13: =SUMIFS('i-shopify-sl'!$E:$E,'i-shopify-sl'!$A:$A,K$1,'i-shopify-sl'!$C:$C,$C13) | ... O13: =SUMIFS('i-shopify-sl'!$E:$E,'i-shopify-sl'!$A:$A,O$1,'i-shopify-sl'!$C:$C,$C13) | P13: =SUM(D13:O13) | Q13: ->
A14: PT | C14: PT | D14: =SUMIFS('i-shopify-sl'!$E:$E,'i-shopify-sl'!$A:$A,D$1,'i-shopify-sl'!$C:$C,$C14) | E14: =SUMIFS('i-shopify-sl'!$E:$E,'i-shopify-sl'!$A:$A,E$1,'i-shopify-sl'!$C:$C,$C14) | F14: =SUMIFS('i-shopify-sl'!$E:$E,'i-shopify-sl'!$A:$A,F$1,'i-shopify-sl'!$C:$C,$C14) | G14: =SUMIFS('i-shopify-sl'!$E:$E,'i-shopify-sl'!$A:$A,G$1,'i-shopify-sl'!$C:$C,$C14) | H14: =SUMIFS('i-shopify-sl'!$E:$E,'i-shopify-sl'!$A:$A,H$1,'i-shopify-sl'!$C:$C,$C14) | I14: =SUMIFS('i-shopify-sl'!$E:$E,'i-shopify-sl'!$A:$A,I$1,'i-shopify-sl'!$C:$C,$C14) | J14: =SUMIFS('i-shopify-sl'!$E:$E,'i-shopify-sl'!$A:$A,J$1,'i-shopify-sl'!$C:$C,$C14) | K14: =SUMIFS('i-shopify-sl'!$E:$E,'i-shopify-sl'!$A:$A,K$1,'i-shopify-sl'!$C:$C,$C14) | ... O14: =SUMIFS('i-shopify-sl'!$E:$E,'i-shopify-sl'!$A:$A,O$1,'i-shopify-sl'!$C:$C,$C14) | P14: =SUM(D14:O14) | Q14: ->
A15: XX | C15: XX | D15: =SUMIFS('i-shopify-sl'!$E:$E,'i-shopify-sl'!$A:$A,D$1,'i-shopify-sl'!$C:$C,$C15) | E15: =SUMIFS('i-shopify-sl'!$E:$E,'i-shopify-sl'!$A:$A,E$1,'i-shopify-sl'!$C:$C,$C15) | F15: =SUMIFS('i-shopify-sl'!$E:$E,'i-shopify-sl'!$A:$A,F$1,'i-shopify-sl'!$C:$C,$C15) | G15: =SUMIFS('i-shopify-sl'!$E:$E,'i-shopify-sl'!$A:$A,G$1,'i-shopify-sl'!$C:$C,$C15) | H15: =SUMIFS('i-shopify-sl'!$E:$E,'i-shopify-sl'!$A:$A,H$1,'i-shopify-sl'!$C:$C,$C15) | I15: =SUMIFS('i-shopify-sl'!$E:$E,'i-shopify-sl'!$A:$A,I$1,'i-shopify-sl'!$C:$C,$C15) | J15: =SUMIFS('i-shopify-sl'!$E:$E,'i-shopify-sl'!$A:$A,J$1,'i-shopify-sl'!$C:$C,$C15) | K15: =SUMIFS('i-shopify-sl'!$E:$E,'i-shopify-sl'!$A:$A,K$1,'i-shopify-sl'!$C:$C,$C15) | ... O15: =SUMIFS('i-shopify-sl'!$E:$E,'i-shopify-sl'!$A:$A,O$1,'i-shopify-sl'!$C:$C,$C15) | P15: =SUM(D15:O15) | Q15: ->
A16: Marketplaces | C16: Marketplaces | D16: =SUM(D17:D19) | E16: =SUM(E17:E19) | F16: =SUM(F17:F19) | G16: =SUM(G17:G19) | H16: =SUM(H17:H19) | I16: =SUM(I17:I19) | J16: =SUM(J17:J19) | K16: =SUM(K17:K19) | ... O16: =SUM(O17:O19) | P16: =SUM(D16:O16) | Q16: ->
A17: HANNUN | C17: HANNUN | D17: =SUMIFS('i-marketplaces-sl'!$E:$E,'i-marketplaces-sl'!$A:$A,D$1,'i-marketplaces-sl'!$C:$C,$C17) | E17: =SUMIFS('i-marketplaces-sl'!$E:$E,'i-marketplaces-sl'!$A:$A,E$1,'i-marketplaces-sl'!$C:$C,$C17) | F17: =SUMIFS('i-marketplaces-sl'!$E:$E,'i-marketplaces-sl'!$A:$A,F$1,'i-marketplaces-sl'!$C:$C,$C17) | G17: =SUMIFS('i-marketplaces-sl'!$E:$E,'i-marketplaces-sl'!$A:$A,G$1,'i-marketplaces-sl'!$C:$C,$C17) | H17: =SUMIFS('i-marketplaces-sl'!$E:$E,'i-marketplaces-sl'!$A:$A,H$1,'i-marketplaces-sl'!$C:$C,$C17) | I17: =SUMIFS('i-marketplaces-sl'!$E:$E,'i-marketplaces-sl'!$A:$A,I$1,'i-marketplaces-sl'!$C:$C,$C17) | J17: =SUMIFS('i-marketplaces-sl'!$E:$E,'i-marketplaces-sl'!$A:$A,J$1,'i-marketplaces-sl'!$C:$C,$C17) | K17: =SUMIFS('i-marketplaces-sl'!$E:$E,'i-marketplaces-sl'!$A:$A,K$1,'i-marketplaces-sl'!$C:$C,$C17) | ... O17: =SUMIFS('i-marketplaces-sl'!$E:$E,'i-marketplaces-sl'!$A:$A,O$1,'i-marketplaces-sl'!$C:$C,$C17) | P17: =SUM(D17:O17) | Q17: ->
A18: TOASTY | C18: TOASTY | D18: =SUMIFS('i-marketplaces-sl'!$E:$E,'i-marketplaces-sl'!$A:$A,D$1,'i-marketplaces-sl'!$C:$C,$C18) | E18: =SUMIFS('i-marketplaces-sl'!$E:$E,'i-marketplaces-sl'!$A:$A,E$1,'i-marketplaces-sl'!$C:$C,$C18) | F18: =SUMIFS('i-marketplaces-sl'!$E:$E,'i-marketplaces-sl'!$A:$A,F$1,'i-marketplaces-sl'!$C:$C,$C18) | G18: =SUMIFS('i-marketplaces-sl'!$E:$E,'i-marketplaces-sl'!$A:$A,G$1,'i-marketplaces-sl'!$C:$C,$C18) | H18: =SUMIFS('i-marketplaces-sl'!$E:$E,'i-marketplaces-sl'!$A:$A,H$1,'i-marketplaces-sl'!$C:$C,$C18) | I18: =SUMIFS('i-marketplaces-sl'!$E:$E,'i-marketplaces-sl'!$A:$A,I$1,'i-marketplaces-sl'!$C:$C,$C18) | J18: =SUMIFS('i-marketplaces-sl'!$E:$E,'i-marketplaces-sl'!$A:$A,J$1,'i-marketplaces-sl'!$C:$C,$C18) | K18: =SUMIFS('i-marketplaces-sl'!$E:$E,'i-marketplaces-sl'!$A:$A,K$1,'i-marketplaces-sl'!$C:$C,$C18) | ... O18: =SUMIFS('i-marketplaces-sl'!$E:$E,'i-marketplaces-sl'!$A:$A,O$1,'i-marketplaces-sl'!$C:$C,$C18) | P18: =SUM(D18:O18) | Q18: ->
A19: CHOOSE | C19: CHOOSE | D19: =SUMIFS('i-marketplaces-sl'!$E:$E,'i-marketplaces-sl'!$A:$A,D$1,'i-marketplaces-sl'!$C:$C,$C19) | E19: =SUMIFS('i-marketplaces-sl'!$E:$E,'i-marketplaces-sl'!$A:$A,E$1,'i-marketplaces-sl'!$C:$C,$C19) | F19: =SUMIFS('i-marketplaces-sl'!$E:$E,'i-marketplaces-sl'!$A:$A,F$1,'i-marketplaces-sl'!$C:$C,$C19) | G19: =SUMIFS('i-marketplaces-sl'!$E:$E,'i-marketplaces-sl'!$A:$A,G$1,'i-marketplaces-sl'!$C:$C,$C19) | H19: =SUMIFS('i-marketplaces-sl'!$E:$E,'i-marketplaces-sl'!$A:$A,H$1,'i-marketplaces-sl'!$C:$C,$C19) | I19: =SUMIFS('i-marketplaces-sl'!$E:$E,'i-marketplaces-sl'!$A:$A,I$1,'i-marketplaces-sl'!$C:$C,$C19) | J19: =SUMIFS('i-marketplaces-sl'!$E:$E,'i-marketplaces-sl'!$A:$A,J$1,'i-marketplaces-sl'!$C:$C,$C19) | K19: =SUMIFS('i-marketplaces-sl'!$E:$E,'i-marketplaces-sl'!$A:$A,K$1,'i-marketplaces-sl'!$C:$C,$C19) | ... O19: =SUMIFS('i-marketplaces-sl'!$E:$E,'i-marketplaces-sl'!$A:$A,O$1,'i-marketplaces-sl'!$C:$C,$C19) | P19: =SUM(D19:O19) | Q19: ->
A20: Rappels | C20: Rappels | D20: =D21 | E20: =E21 | F20: =F21 | G20: =G21 | H20: =H21 | I20: =I21 | J20: =J21 | K20: =K21 | ... O20: =O21 | P20: =SUM(D20:O20) | Q20: ->
A21: LIVITUM | C21: LIVITUM | D21: =SUMIFS('i-rappels-sl'!$E:$E,'i-rappels-sl'!$A:$A,D$1,'i-rappels-sl'!$C:$C,$C21) | E21: =SUMIFS('i-rappels-sl'!$E:$E,'i-rappels-sl'!$A:$A,E$1,'i-rappels-sl'!$C:$C,$C21) | F21: =SUMIFS('i-rappels-sl'!$E:$E,'i-rappels-sl'!$A:$A,F$1,'i-rappels-sl'!$C:$C,$C21) | G21: =SUMIFS('i-rappels-sl'!$E:$E,'i-rappels-sl'!$A:$A,G$1,'i-rappels-sl'!$C:$C,$C21) | H21: =SUMIFS('i-rappels-sl'!$E:$E,'i-rappels-sl'!$A:$A,H$1,'i-rappels-sl'!$C:$C,$C21) | I21: =SUMIFS('i-rappels-sl'!$E:$E,'i-rappels-sl'!$A:$A,I$1,'i-rappels-sl'!$C:$C,$C21) | J21: =SUMIFS('i-rappels-sl'!$E:$E,'i-rappels-sl'!$A:$A,J$1,'i-rappels-sl'!$C:$C,$C21) | K21: =SUMIFS('i-rappels-sl'!$E:$E,'i-rappels-sl'!$A:$A,K$1,'i-rappels-sl'!$C:$C,$C21) | ... O21: =SUMIFS('i-rappels-sl'!$E:$E,'i-rappels-sl'!$A:$A,O$1,'i-rappels-sl'!$C:$C,$C21) | P21: =SUM(D21:O21) | Q21: ->
A22: Supplies | C22: Supplies | D22: =D23 | E22: =E23 | F22: =F23 | G22: =G23 | H22: =H23 | I22: =I23 | J22: =J23 | K22: =K23 | ... O22: =O23 | P22: =SUM(D22:O22) | Q22: ->
A23: REVER | C23: REVER | D23: =SUMIFS('i-supplies-sl'!$E:$E,'i-supplies-sl'!$A:$A,D$1,'i-supplies-sl'!$C:$C,$C23) | E23: =SUMIFS('i-supplies-sl'!$E:$E,'i-supplies-sl'!$A:$A,E$1,'i-supplies-sl'!$C:$C,$C23) | F23: =SUMIFS('i-supplies-sl'!$E:$E,'i-supplies-sl'!$A:$A,F$1,'i-supplies-sl'!$C:$C,$C23) | G23: =SUMIFS('i-supplies-sl'!$E:$E,'i-supplies-sl'!$A:$A,G$1,'i-supplies-sl'!$C:$C,$C23) | H23: =SUMIFS('i-supplies-sl'!$E:$E,'i-supplies-sl'!$A:$A,H$1,'i-supplies-sl'!$C:$C,$C23) | I23: =SUMIFS('i-supplies-sl'!$E:$E,'i-supplies-sl'!$A:$A,I$1,'i-supplies-sl'!$C:$C,$C23) | J23: =SUMIFS('i-supplies-sl'!$E:$E,'i-supplies-sl'!$A:$A,J$1,'i-supplies-sl'!$C:$C,$C23) | K23: =SUMIFS('i-supplies-sl'!$E:$E,'i-supplies-sl'!$A:$A,K$1,'i-supplies-sl'!$C:$C,$C23) | ... O23: =SUMIFS('i-supplies-sl'!$E:$E,'i-supplies-sl'!$A:$A,O$1,'i-supplies-sl'!$C:$C,$C23) | P23: =SUM(D23:O23) | Q23: ->
P24: =SUM(D24:O24)
A25: Services | B25: Services | D25: =SUM(D26:D29) | E25: =SUM(E26:E29) | F25: =SUM(F26:F29) | G25: =SUM(G26:G29) | H25: =SUM(H26:H29) | I25: =SUM(I26:I29) | J25: =SUM(J26:J29) | K25: =SUM(K26:K29) | ... O25: =SUM(O26:O29) | P25: =SUM(D25:O25) | Q25: ->
A26: HANNUN | C26: HANNUN | D26: =SUMIFS('i-services-sl'!$E:$E,'i-services-sl'!$A:$A,D$1,'i-services-sl'!$C:$C,$C26) | E26: =SUMIFS('i-services-sl'!$E:$E,'i-services-sl'!$A:$A,E$1,'i-services-sl'!$C:$C,$C26) | F26: =SUMIFS('i-services-sl'!$E:$E,'i-services-sl'!$A:$A,F$1,'i-services-sl'!$C:$C,$C26) | G26: =SUMIFS('i-services-sl'!$E:$E,'i-services-sl'!$A:$A,G$1,'i-services-sl'!$C:$C,$C26) | H26: =SUMIFS('i-services-sl'!$E:$E,'i-services-sl'!$A:$A,H$1,'i-services-sl'!$C:$C,$C26) | I26: =SUMIFS('i-services-sl'!$E:$E,'i-services-sl'!$A:$A,I$1,'i-services-sl'!$C:$C,$C26) | J26: =SUMIFS('i-services-sl'!$E:$E,'i-services-sl'!$A:$A,J$1,'i-services-sl'!$C:$C,$C26) | K26: =SUMIFS('i-services-sl'!$E:$E,'i-services-sl'!$A:$A,K$1,'i-services-sl'!$C:$C,$C26) | ... O26: =SUMIFS('i-services-sl'!$E:$E,'i-services-sl'!$A:$A,O$1,'i-services-sl'!$C:$C,$C26) | P26: =SUM(D26:O26) | Q26: ->
A27: QHANDS | C27: QHANDS | D27: =SUMIFS('i-services-sl'!$E:$E,'i-services-sl'!$A:$A,D$1,'i-services-sl'!$C:$C,$C27) | E27: =SUMIFS('i-services-sl'!$E:$E,'i-services-sl'!$A:$A,E$1,'i-services-sl'!$C:$C,$C27) | F27: =SUMIFS('i-services-sl'!$E:$E,'i-services-sl'!$A:$A,F$1,'i-services-sl'!$C:$C,$C27) | G27: =SUMIFS('i-services-sl'!$E:$E,'i-services-sl'!$A:$A,G$1,'i-services-sl'!$C:$C,$C27) | H27: =SUMIFS('i-services-sl'!$E:$E,'i-services-sl'!$A:$A,H$1,'i-services-sl'!$C:$C,$C27) | I27: =SUMIFS('i-services-sl'!$E:$E,'i-services-sl'!$A:$A,I$1,'i-services-sl'!$C:$C,$C27) | J27: =SUMIFS('i-services-sl'!$E:$E,'i-services-sl'!$A:$A,J$1,'i-services-sl'!$C:$C,$C27) | K27: =SUMIFS('i-services-sl'!$E:$E,'i-services-sl'!$A:$A,K$1,'i-services-sl'!$C:$C,$C27) | ... O27: =SUMIFS('i-services-sl'!$E:$E,'i-services-sl'!$A:$A,O$1,'i-services-sl'!$C:$C,$C27) | P27: =SUM(D27:O27) | Q27: ->
A28: Ltd | C28: Ltd | D28: =SUMIFS('i-services-sl'!$E:$E,'i-services-sl'!$A:$A,D$1,'i-services-sl'!$C:$C,$C28) | E28: =SUMIFS('i-services-sl'!$E:$E,'i-services-sl'!$A:$A,E$1,'i-services-sl'!$C:$C,$C28) | F28: =SUMIFS('i-services-sl'!$E:$E,'i-services-sl'!$A:$A,F$1,'i-services-sl'!$C:$C,$C28) | G28: =SUMIFS('i-services-sl'!$E:$E,'i-services-sl'!$A:$A,G$1,'i-services-sl'!$C:$C,$C28) | H28: =SUMIFS('i-services-sl'!$E:$E,'i-services-sl'!$A:$A,H$1,'i-services-sl'!$C:$C,$C28) | I28: =SUMIFS('i-services-sl'!$E:$E,'i-services-sl'!$A:$A,I$1,'i-services-sl'!$C:$C,$C28) | J28: =SUMIFS('i-services-sl'!$E:$E,'i-services-sl'!$A:$A,J$1,'i-services-sl'!$C:$C,$C28) | K28: =SUMIFS('i-services-sl'!$E:$E,'i-services-sl'!$A:$A,K$1,'i-services-sl'!$C:$C,$C28) | ... O28: =SUMIFS('i-services-sl'!$E:$E,'i-services-sl'!$A:$A,O$1,'i-services-sl'!$C:$C,$C28) | P28: =SUM(D28:O28) | Q28: ->
A29: Inc | C29: Inc | D29: =SUMIFS('i-services-sl'!$E:$E,'i-services-sl'!$A:$A,D$1,'i-services-sl'!$C:$C,$C29) | E29: =SUMIFS('i-services-sl'!$E:$E,'i-services-sl'!$A:$A,E$1,'i-services-sl'!$C:$C,$C29) | F29: =SUMIFS('i-services-sl'!$E:$E,'i-services-sl'!$A:$A,F$1,'i-services-sl'!$C:$C,$C29) | G29: =SUMIFS('i-services-sl'!$E:$E,'i-services-sl'!$A:$A,G$1,'i-services-sl'!$C:$C,$C29) | H29: =SUMIFS('i-services-sl'!$E:$E,'i-services-sl'!$A:$A,H$1,'i-services-sl'!$C:$C,$C29) | I29: =SUMIFS('i-services-sl'!$E:$E,'i-services-sl'!$A:$A,I$1,'i-services-sl'!$C:$C,$C29) | J29: =SUMIFS('i-services-sl'!$E:$E,'i-services-sl'!$A:$A,J$1,'i-services-sl'!$C:$C,$C29) | K29: =SUMIFS('i-services-sl'!$E:$E,'i-services-sl'!$A:$A,K$1,'i-services-sl'!$C:$C,$C29) | ... O29: =SUMIFS('i-services-sl'!$E:$E,'i-services-sl'!$A:$A,O$1,'i-services-sl'!$C:$C,$C29) | P29: =SUM(D29:O29) | Q29: ->
P30: =SUM(D30:O30)
A31: Expenses | D31: =D32+D60 | E31: =E32+E60 | F31: =F32+F60 | G31: =G32+G60 | H31: =H32+H60 | I31: =I32+I60 | J31: =J32+J60 | K31: =K32+K60 | ... O31: =O32+O60 | P31: =SUM(D31:O31)
A32: COGS | B32: COGS | D32: =D33+D40+D47+D50 | E32: =E33+E40+E47+E50 | F32: =F33+F40+F47+F50 | G32: =G33+G40+G47+G50 | H32: =H33+H40+H47+H50 | I32: =I33+I40+I47+I50 | J32: =J33+J40+J47+J50 | K32: =K33+K40+K47+K50 | ... O32: =O33+O40+O47+O50 | P32: =SUM(D32:O32)
A33: Manufacturing (% sales) | C33: Manufacturing (% sales) | D33: =SUM(D34:D38) | E33: =SUM(E34:E38) | F33: =SUM(F34:F38) | G33: =SUM(G34:G38) | H33: =SUM(H34:H38) | I33: =SUM(I34:I38) | J33: =SUM(J34:J38) | K33: =SUM(K34:K38) | ... O33: =SUM(O34:O38) | P33: =SUM(D33:O33) | Q33: ->
A34: APPHOTOCAN | C34: APPHOTOCAN | D34: =SUMIFS('g-expenses-sl'!$G:$G,'g-expenses-sl'!$A:$A,D$1,'g-expenses-sl'!$D:$D,"manufacturing",'g-expenses-sl'!$E:$E,$C34) | E34: =SUMIFS('g-expenses-sl'!$G:$G,'g-expenses-sl'!$A:$A,E$1,'g-expenses-sl'!$D:$D,"manufacturing",'g-expenses-sl'!$E:$E,$C34) | F34: =SUMIFS('g-expenses-sl'!$G:$G,'g-expenses-sl'!$A:$A,F$1,'g-expenses-sl'!$D:$D,"manufacturing",'g-expenses-sl'!$E:$E,$C34) | G34: =SUMIFS('g-expenses-sl'!$G:$G,'g-expenses-sl'!$A:$A,G$1,'g-expenses-sl'!$D:$D,"manufacturing",'g-expenses-sl'!$E:$E,$C34) | H34: =SUMIFS('g-expenses-sl'!$G:$G,'g-expenses-sl'!$A:$A,H$1,'g-expenses-sl'!$D:$D,"manufacturing",'g-expenses-sl'!$E:$E,$C34) | I34: =SUMIFS('g-expenses-sl'!$G:$G,'g-expenses-sl'!$A:$A,I$1,'g-expenses-sl'!$D:$D,"manufacturing",'g-expenses-sl'!$E:$E,$C34) | J34: =SUMIFS('g-expenses-sl'!$G:$G,'g-expenses-sl'!$A:$A,J$1,'g-expenses-sl'!$D:$D,"manufacturing",'g-expenses-sl'!$E:$E,$C34) | K34: =SUMIFS('g-expenses-sl'!$G:$G,'g-expenses-sl'!$A:$A,K$1,'g-expenses-sl'!$D:$D,"manufacturing",'g-expenses-sl'!$E:$E,$C34) | ... O34: =SUMIFS('g-expenses-sl'!$G:$G,'g-expenses-sl'!$A:$A,O$1,'g-expenses-sl'!$D:$D,"manufacturing",'g-expenses-sl'!$E:$E,$C34) | P34: =SUM(D34:O34) | Q34: ->
A35: APPHOTOES | C35: APPHOTOES | D35: =SUMIFS('g-expenses-sl'!$G:$G,'g-expenses-sl'!$A:$A,D$1,'g-expenses-sl'!$D:$D,"manufacturing",'g-expenses-sl'!$E:$E,$C35) | E35: =SUMIFS('g-expenses-sl'!$G:$G,'g-expenses-sl'!$A:$A,E$1,'g-expenses-sl'!$D:$D,"manufacturing",'g-expenses-sl'!$E:$E,$C35) | F35: =SUMIFS('g-expenses-sl'!$G:$G,'g-expenses-sl'!$A:$A,F$1,'g-expenses-sl'!$D:$D,"manufacturing",'g-expenses-sl'!$E:$E,$C35) | G35: =SUMIFS('g-expenses-sl'!$G:$G,'g-expenses-sl'!$A:$A,G$1,'g-expenses-sl'!$D:$D,"manufacturing",'g-expenses-sl'!$E:$E,$C35) | H35: =SUMIFS('g-expenses-sl'!$G:$G,'g-expenses-sl'!$A:$A,H$1,'g-expenses-sl'!$D:$D,"manufacturing",'g-expenses-sl'!$E:$E,$C35) | I35: =SUMIFS('g-expenses-sl'!$G:$G,'g-expenses-sl'!$A:$A,I$1,'g-expenses-sl'!$D:$D,"manufacturing",'g-expenses-sl'!$E:$E,$C35) | J35: =SUMIFS('g-expenses-sl'!$G:$G,'g-expenses-sl'!$A:$A,J$1,'g-expenses-sl'!$D:$D,"manufacturing",'g-expenses-sl'!$E:$E,$C35) | K35: =SUMIFS('g-expenses-sl'!$G:$G,'g-expenses-sl'!$A:$A,K$1,'g-expenses-sl'!$D:$D,"manufacturing",'g-expenses-sl'!$E:$E,$C35) | ... O35: =SUMIFS('g-expenses-sl'!$G:$G,'g-expenses-sl'!$A:$A,O$1,'g-expenses-sl'!$D:$D,"manufacturing",'g-expenses-sl'!$E:$E,$C35) | P35: =SUM(D35:O35) | Q35: ->
A36: ARTLINK | C36: ARTLINK | D36: =SUMIFS('g-expenses-sl'!$G:$G,'g-expenses-sl'!$A:$A,D$1,'g-expenses-sl'!$D:$D,"manufacturing",'g-expenses-sl'!$E:$E,$C36) | E36: =SUMIFS('g-expenses-sl'!$G:$G,'g-expenses-sl'!$A:$A,E$1,'g-expenses-sl'!$D:$D,"manufacturing",'g-expenses-sl'!$E:$E,$C36) | F36: =SUMIFS('g-expenses-sl'!$G:$G,'g-expenses-sl'!$A:$A,F$1,'g-expenses-sl'!$D:$D,"manufacturing",'g-expenses-sl'!$E:$E,$C36) | G36: =SUMIFS('g-expenses-sl'!$G:$G,'g-expenses-sl'!$A:$A,G$1,'g-expenses-sl'!$D:$D,"manufacturing",'g-expenses-sl'!$E:$E,$C36) | H36: =SUMIFS('g-expenses-sl'!$G:$G,'g-expenses-sl'!$A:$A,H$1,'g-expenses-sl'!$D:$D,"manufacturing",'g-expenses-sl'!$E:$E,$C36) | I36: =SUMIFS('g-expenses-sl'!$G:$G,'g-expenses-sl'!$A:$A,I$1,'g-expenses-sl'!$D:$D,"manufacturing",'g-expenses-sl'!$E:$E,$C36) | J36: =SUMIFS('g-expenses-sl'!$G:$G,'g-expenses-sl'!$A:$A,J$1,'g-expenses-sl'!$D:$D,"manufacturing",'g-expenses-sl'!$E:$E,$C36) | K36: =SUMIFS('g-expenses-sl'!$G:$G,'g-expenses-sl'!$A:$A,K$1,'g-expenses-sl'!$D:$D,"manufacturing",'g-expenses-sl'!$E:$E,$C36) | ... O36: =SUMIFS('g-expenses-sl'!$G:$G,'g-expenses-sl'!$A:$A,O$1,'g-expenses-sl'!$D:$D,"manufacturing",'g-expenses-sl'!$E:$E,$C36) | P36: =SUM(D36:O36) | Q36: ->
A37: DCT | C37: DCT | D37: =SUMIFS('g-expenses-sl'!$G:$G,'g-expenses-sl'!$A:$A,D$1,'g-expenses-sl'!$D:$D,"manufacturing",'g-expenses-sl'!$E:$E,$C37) | E37: =SUMIFS('g-expenses-sl'!$G:$G,'g-expenses-sl'!$A:$A,E$1,'g-expenses-sl'!$D:$D,"manufacturing",'g-expenses-sl'!$E:$E,$C37) | F37: =SUMIFS('g-expenses-sl'!$G:$G,'g-expenses-sl'!$A:$A,F$1,'g-expenses-sl'!$D:$D,"manufacturing",'g-expenses-sl'!$E:$E,$C37) | G37: =SUMIFS('g-expenses-sl'!$G:$G,'g-expenses-sl'!$A:$A,G$1,'g-expenses-sl'!$D:$D,"manufacturing",'g-expenses-sl'!$E:$E,$C37) | H37: =SUMIFS('g-expenses-sl'!$G:$G,'g-expenses-sl'!$A:$A,H$1,'g-expenses-sl'!$D:$D,"manufacturing",'g-expenses-sl'!$E:$E,$C37) | I37: =SUMIFS('g-expenses-sl'!$G:$G,'g-expenses-sl'!$A:$A,I$1,'g-expenses-sl'!$D:$D,"manufacturing",'g-expenses-sl'!$E:$E,$C37) | J37: =SUMIFS('g-expenses-sl'!$G:$G,'g-expenses-sl'!$A:$A,J$1,'g-expenses-sl'!$D:$D,"manufacturing",'g-expenses-sl'!$E:$E,$C37) | K37: =SUMIFS('g-expenses-sl'!$G:$G,'g-expenses-sl'!$A:$A,K$1,'g-expenses-sl'!$D:$D,"manufacturing",'g-expenses-sl'!$E:$E,$C37) | ... O37: =SUMIFS('g-expenses-sl'!$G:$G,'g-expenses-sl'!$A:$A,O$1,'g-expenses-sl'!$D:$D,"manufacturing",'g-expenses-sl'!$E:$E,$C37) | P37: =SUM(D37:O37) | Q37: ->
A38: PRESSING | C38: PRESSING | D38: =SUMIFS('g-expenses-sl'!$G:$G,'g-expenses-sl'!$A:$A,D$1,'g-expenses-sl'!$D:$D,"manufacturing",'g-expenses-sl'!$E:$E,$C38) | E38: =SUMIFS('g-expenses-sl'!$G:$G,'g-expenses-sl'!$A:$A,E$1,'g-expenses-sl'!$D:$D,"manufacturing",'g-expenses-sl'!$E:$E,$C38) | F38: =SUMIFS('g-expenses-sl'!$G:$G,'g-expenses-sl'!$A:$A,F$1,'g-expenses-sl'!$D:$D,"manufacturing",'g-expenses-sl'!$E:$E,$C38) | G38: =SUMIFS('g-expenses-sl'!$G:$G,'g-expenses-sl'!$A:$A,G$1,'g-expenses-sl'!$D:$D,"manufacturing",'g-expenses-sl'!$E:$E,$C38) | H38: =SUMIFS('g-expenses-sl'!$G:$G,'g-expenses-sl'!$A:$A,H$1,'g-expenses-sl'!$D:$D,"manufacturing",'g-expenses-sl'!$E:$E,$C38) | I38: =SUMIFS('g-expenses-sl'!$G:$G,'g-expenses-sl'!$A:$A,I$1,'g-expenses-sl'!$D:$D,"manufacturing",'g-expenses-sl'!$E:$E,$C38) | J38: =SUMIFS('g-expenses-sl'!$G:$G,'g-expenses-sl'!$A:$A,J$1,'g-expenses-sl'!$D:$D,"manufacturing",'g-expenses-sl'!$E:$E,$C38) | K38: =SUMIFS('g-expenses-sl'!$G:$G,'g-expenses-sl'!$A:$A,K$1,'g-expenses-sl'!$D:$D,"manufacturing",'g-expenses-sl'!$E:$E,$C38) | ... O38: =SUMIFS('g-expenses-sl'!$G:$G,'g-expenses-sl'!$A:$A,O$1,'g-expenses-sl'!$D:$D,"manufacturing",'g-expenses-sl'!$E:$E,$C38) | P38: =SUM(D38:O38) | Q38: ->
A39: % Manufacturing / sales | C39: % Manufacturing / sales | D39: =IFERROR(D33/D5,0) | E39: =IFERROR(E33/E5,0) | F39: =IFERROR(F33/F5,0) | G39: =IFERROR(G33/G5,0) | H39: =IFERROR(H33/H5,0) | I39: =IFERROR(I33/I5,0) | J39: =IFERROR(J33/J5,0) | K39: =IFERROR(K33/K5,0) | ... O39: =IFERROR(O33/O5,0) | P39: =SUM(D39:O39)
A40: Logistics (% sales) | C40: Logistics (% sales) | D40: =SUM(D41:D45) | E40: =SUM(E41:E45) | F40: =SUM(F41:F45) | G40: =SUM(G41:G45) | H40: =SUM(H41:H45) | I40: =SUM(I41:I45) | J40: =SUM(J41:J45) | K40: =SUM(K41:K45) | ... O40: =SUM(O41:O45) | P40: =SUM(D40:O40) | Q40: ->
A41: CORREOS | C41: CORREOS | D41: =SUMIFS('g-expenses-sl'!$G:$G,'g-expenses-sl'!$A:$A,D$1,'g-expenses-sl'!$D:$D,"logistics",'g-expenses-sl'!$E:$E,$C41) | E41: =SUMIFS('g-expenses-sl'!$G:$G,'g-expenses-sl'!$A:$A,E$1,'g-expenses-sl'!$D:$D,"logistics",'g-expenses-sl'!$E:$E,$C41) | F41: =SUMIFS('g-expenses-sl'!$G:$G,'g-expenses-sl'!$A:$A,F$1,'g-expenses-sl'!$D:$D,"logistics",'g-expenses-sl'!$E:$E,$C41) | G41: =SUMIFS('g-expenses-sl'!$G:$G,'g-expenses-sl'!$A:$A,G$1,'g-expenses-sl'!$D:$D,"logistics",'g-expenses-sl'!$E:$E,$C41) | H41: =SUMIFS('g-expenses-sl'!$G:$G,'g-expenses-sl'!$A:$A,H$1,'g-expenses-sl'!$D:$D,"logistics",'g-expenses-sl'!$E:$E,$C41) | I41: =SUMIFS('g-expenses-sl'!$G:$G,'g-expenses-sl'!$A:$A,I$1,'g-expenses-sl'!$D:$D,"logistics",'g-expenses-sl'!$E:$E,$C41) | J41: =SUMIFS('g-expenses-sl'!$G:$G,'g-expenses-sl'!$A:$A,J$1,'g-expenses-sl'!$D:$D,"logistics",'g-expenses-sl'!$E:$E,$C41) | K41: =SUMIFS('g-expenses-sl'!$G:$G,'g-expenses-sl'!$A:$A,K$1,'g-expenses-sl'!$D:$D,"logistics",'g-expenses-sl'!$E:$E,$C41) | ... O41: =SUMIFS('g-expenses-sl'!$G:$G,'g-expenses-sl'!$A:$A,O$1,'g-expenses-sl'!$D:$D,"logistics",'g-expenses-sl'!$E:$E,$C41) | P41: =SUM(D41:O41) | Q41: ->
A42: CORREOSCAN | C42: CORREOSCAN | D42: =SUMIFS('g-expenses-sl'!$G:$G,'g-expenses-sl'!$A:$A,D$1,'g-expenses-sl'!$D:$D,"logistics",'g-expenses-sl'!$E:$E,$C42) | E42: =SUMIFS('g-expenses-sl'!$G:$G,'g-expenses-sl'!$A:$A,E$1,'g-expenses-sl'!$D:$D,"logistics",'g-expenses-sl'!$E:$E,$C42) | F42: =SUMIFS('g-expenses-sl'!$G:$G,'g-expenses-sl'!$A:$A,F$1,'g-expenses-sl'!$D:$D,"logistics",'g-expenses-sl'!$E:$E,$C42) | G42: =SUMIFS('g-expenses-sl'!$G:$G,'g-expenses-sl'!$A:$A,G$1,'g-expenses-sl'!$D:$D,"logistics",'g-expenses-sl'!$E:$E,$C42) | H42: =SUMIFS('g-expenses-sl'!$G:$G,'g-expenses-sl'!$A:$A,H$1,'g-expenses-sl'!$D:$D,"logistics",'g-expenses-sl'!$E:$E,$C42) | I42: =SUMIFS('g-expenses-sl'!$G:$G,'g-expenses-sl'!$A:$A,I$1,'g-expenses-sl'!$D:$D,"logistics",'g-expenses-sl'!$E:$E,$C42) | J42: =SUMIFS('g-expenses-sl'!$G:$G,'g-expenses-sl'!$A:$A,J$1,'g-expenses-sl'!$D:$D,"logistics",'g-expenses-sl'!$E:$E,$C42) | K42: =SUMIFS('g-expenses-sl'!$G:$G,'g-expenses-sl'!$A:$A,K$1,'g-expenses-sl'!$D:$D,"logistics",'g-expenses-sl'!$E:$E,$C42) | ... O42: =SUMIFS('g-expenses-sl'!$G:$G,'g-expenses-sl'!$A:$A,O$1,'g-expenses-sl'!$D:$D,"logistics",'g-expenses-sl'!$E:$E,$C42) | P42: =SUM(D42:O42) | Q42: ->
A43: GLS | C43: GLS | D43: =SUMIFS('g-expenses-sl'!$G:$G,'g-expenses-sl'!$A:$A,D$1,'g-expenses-sl'!$D:$D,"logistics",'g-expenses-sl'!$E:$E,$C43) | E43: =SUMIFS('g-expenses-sl'!$G:$G,'g-expenses-sl'!$A:$A,E$1,'g-expenses-sl'!$D:$D,"logistics",'g-expenses-sl'!$E:$E,$C43) | F43: =SUMIFS('g-expenses-sl'!$G:$G,'g-expenses-sl'!$A:$A,F$1,'g-expenses-sl'!$D:$D,"logistics",'g-expenses-sl'!$E:$E,$C43) | G43: =SUMIFS('g-expenses-sl'!$G:$G,'g-expenses-sl'!$A:$A,G$1,'g-expenses-sl'!$D:$D,"logistics",'g-expenses-sl'!$E:$E,$C43) | H43: =SUMIFS('g-expenses-sl'!$G:$G,'g-expenses-sl'!$A:$A,H$1,'g-expenses-sl'!$D:$D,"logistics",'g-expenses-sl'!$E:$E,$C43) | I43: =SUMIFS('g-expenses-sl'!$G:$G,'g-expenses-sl'!$A:$A,I$1,'g-expenses-sl'!$D:$D,"logistics",'g-expenses-sl'!$E:$E,$C43) | J43: =SUMIFS('g-expenses-sl'!$G:$G,'g-expenses-sl'!$A:$A,J$1,'g-expenses-sl'!$D:$D,"logistics",'g-expenses-sl'!$E:$E,$C43) | K43: =SUMIFS('g-expenses-sl'!$G:$G,'g-expenses-sl'!$A:$A,K$1,'g-expenses-sl'!$D:$D,"logistics",'g-expenses-sl'!$E:$E,$C43) | ... O43: =SUMIFS('g-expenses-sl'!$G:$G,'g-expenses-sl'!$A:$A,O$1,'g-expenses-sl'!$D:$D,"logistics",'g-expenses-sl'!$E:$E,$C43) | P43: =SUM(D43:O43) | Q43: ->
A44: SPRINGGDS | C44: SPRINGGDS | D44: =SUMIFS('g-expenses-sl'!$G:$G,'g-expenses-sl'!$A:$A,D$1,'g-expenses-sl'!$D:$D,"logistics",'g-expenses-sl'!$E:$E,$C44) | E44: =SUMIFS('g-expenses-sl'!$G:$G,'g-expenses-sl'!$A:$A,E$1,'g-expenses-sl'!$D:$D,"logistics",'g-expenses-sl'!$E:$E,$C44) | F44: =SUMIFS('g-expenses-sl'!$G:$G,'g-expenses-sl'!$A:$A,F$1,'g-expenses-sl'!$D:$D,"logistics",'g-expenses-sl'!$E:$E,$C44) | G44: =SUMIFS('g-expenses-sl'!$G:$G,'g-expenses-sl'!$A:$A,G$1,'g-expenses-sl'!$D:$D,"logistics",'g-expenses-sl'!$E:$E,$C44) | H44: =SUMIFS('g-expenses-sl'!$G:$G,'g-expenses-sl'!$A:$A,H$1,'g-expenses-sl'!$D:$D,"logistics",'g-expenses-sl'!$E:$E,$C44) | I44: =SUMIFS('g-expenses-sl'!$G:$G,'g-expenses-sl'!$A:$A,I$1,'g-expenses-sl'!$D:$D,"logistics",'g-expenses-sl'!$E:$E,$C44) | J44: =SUMIFS('g-expenses-sl'!$G:$G,'g-expenses-sl'!$A:$A,J$1,'g-expenses-sl'!$D:$D,"logistics",'g-expenses-sl'!$E:$E,$C44) | K44: =SUMIFS('g-expenses-sl'!$G:$G,'g-expenses-sl'!$A:$A,K$1,'g-expenses-sl'!$D:$D,"logistics",'g-expenses-sl'!$E:$E,$C44) | ... O44: =SUMIFS('g-expenses-sl'!$G:$G,'g-expenses-sl'!$A:$A,O$1,'g-expenses-sl'!$D:$D,"logistics",'g-expenses-sl'!$E:$E,$C44) | P44: =SUM(D44:O44) | Q44: ->
A45: UPS | C45: UPS | D45: =SUMIFS('g-expenses-sl'!$G:$G,'g-expenses-sl'!$A:$A,D$1,'g-expenses-sl'!$D:$D,"logistics",'g-expenses-sl'!$E:$E,$C45) | E45: =SUMIFS('g-expenses-sl'!$G:$G,'g-expenses-sl'!$A:$A,E$1,'g-expenses-sl'!$D:$D,"logistics",'g-expenses-sl'!$E:$E,$C45) | F45: =SUMIFS('g-expenses-sl'!$G:$G,'g-expenses-sl'!$A:$A,F$1,'g-expenses-sl'!$D:$D,"logistics",'g-expenses-sl'!$E:$E,$C45) | G45: =SUMIFS('g-expenses-sl'!$G:$G,'g-expenses-sl'!$A:$A,G$1,'g-expenses-sl'!$D:$D,"logistics",'g-expenses-sl'!$E:$E,$C45) | H45: =SUMIFS('g-expenses-sl'!$G:$G,'g-expenses-sl'!$A:$A,H$1,'g-expenses-sl'!$D:$D,"logistics",'g-expenses-sl'!$E:$E,$C45) | I45: =SUMIFS('g-expenses-sl'!$G:$G,'g-expenses-sl'!$A:$A,I$1,'g-expenses-sl'!$D:$D,"logistics",'g-expenses-sl'!$E:$E,$C45) | J45: =SUMIFS('g-expenses-sl'!$G:$G,'g-expenses-sl'!$A:$A,J$1,'g-expenses-sl'!$D:$D,"logistics",'g-expenses-sl'!$E:$E,$C45) | K45: =SUMIFS('g-expenses-sl'!$G:$G,'g-expenses-sl'!$A:$A,K$1,'g-expenses-sl'!$D:$D,"logistics",'g-expenses-sl'!$E:$E,$C45) | ... O45: =SUMIFS('g-expenses-sl'!$G:$G,'g-expenses-sl'!$A:$A,O$1,'g-expenses-sl'!$D:$D,"logistics",'g-expenses-sl'!$E:$E,$C45) | P45: =SUM(D45:O45) | Q45: ->
A46: % Logistics / sales | C46: % Logistics / sales | D46: =IFERROR(D40/D5,0) | E46: =IFERROR(E40/E5,0) | F46: =IFERROR(F40/F5,0) | G46: =IFERROR(G40/G5,0) | H46: =IFERROR(H40/H5,0) | I46: =IFERROR(I40/I5,0) | J46: =IFERROR(J40/J5,0) | K46: =IFERROR(K40/K5,0) | ... O46: =IFERROR(O40/O5,0) | P46: =SUM(D46:O46)
A47: Royalties (% sales) | C47: Royalties (% sales) | D47: =D48 | E47: =E48 | F47: =F48 | G47: =G48 | H47: =H48 | I47: =I48 | J47: =J48 | K47: =K48 | ... O47: =O48 | P47: =SUM(D47:O47) | Q47: ->
A48: ROYALTIES | C48: ROYALTIES | D48: =SUMIFS('g-expenses-sl'!$G:$G,'g-expenses-sl'!$A:$A,D$1,'g-expenses-sl'!$D:$D,"royalties",'g-expenses-sl'!$E:$E,$C48) | E48: =SUMIFS('g-expenses-sl'!$G:$G,'g-expenses-sl'!$A:$A,E$1,'g-expenses-sl'!$D:$D,"royalties",'g-expenses-sl'!$E:$E,$C48) | F48: =SUMIFS('g-expenses-sl'!$G:$G,'g-expenses-sl'!$A:$A,F$1,'g-expenses-sl'!$D:$D,"royalties",'g-expenses-sl'!$E:$E,$C48) | G48: =SUMIFS('g-expenses-sl'!$G:$G,'g-expenses-sl'!$A:$A,G$1,'g-expenses-sl'!$D:$D,"royalties",'g-expenses-sl'!$E:$E,$C48) | H48: =SUMIFS('g-expenses-sl'!$G:$G,'g-expenses-sl'!$A:$A,H$1,'g-expenses-sl'!$D:$D,"royalties",'g-expenses-sl'!$E:$E,$C48) | I48: =SUMIFS('g-expenses-sl'!$G:$G,'g-expenses-sl'!$A:$A,I$1,'g-expenses-sl'!$D:$D,"royalties",'g-expenses-sl'!$E:$E,$C48) | J48: =SUMIFS('g-expenses-sl'!$G:$G,'g-expenses-sl'!$A:$A,J$1,'g-expenses-sl'!$D:$D,"royalties",'g-expenses-sl'!$E:$E,$C48) | K48: =SUMIFS('g-expenses-sl'!$G:$G,'g-expenses-sl'!$A:$A,K$1,'g-expenses-sl'!$D:$D,"royalties",'g-expenses-sl'!$E:$E,$C48) | ... O48: =SUMIFS('g-expenses-sl'!$G:$G,'g-expenses-sl'!$A:$A,O$1,'g-expenses-sl'!$D:$D,"royalties",'g-expenses-sl'!$E:$E,$C48) | P48: =SUM(D48:O48) | Q48: ->
A49: % Royalties / sales | C49: % Royalties / sales | D49: =IFERROR(D47/D5,0) | E49: =IFERROR(E47/E5,0) | F49: =IFERROR(F47/F5,0) | G49: =IFERROR(G47/G5,0) | H49: =IFERROR(H47/H5,0) | I49: =IFERROR(I47/I5,0) | J49: =IFERROR(J47/J5,0) | K49: =IFERROR(K47/K5,0) | ... O49: =IFERROR(O47/O5,0) | P49: =SUM(D49:O49)
A50: Payment fees (% sales) | C50: Payment fees (% sales) | D50: =SUM(D51:D52) | E50: =SUM(E51:E52) | F50: =SUM(F51:F52) | G50: =SUM(G51:G52) | H50: =SUM(H51:H52) | I50: =SUM(I51:I52) | J50: =SUM(J51:J52) | K50: =SUM(K51:K52) | ... O50: =SUM(O51:O52) | P50: =SUM(D50:O50) | Q50: ->
A51: SHOPIFY | C51: SHOPIFY | D51: =SUMIFS('g-payment-fees-sl'!$D:$D,'g-payment-fees-sl'!$A:$A,D$1,'g-payment-fees-sl'!$C:$C,$C51) | E51: =SUMIFS('g-payment-fees-sl'!$D:$D,'g-payment-fees-sl'!$A:$A,E$1,'g-payment-fees-sl'!$C:$C,$C51) | F51: =SUMIFS('g-payment-fees-sl'!$D:$D,'g-payment-fees-sl'!$A:$A,F$1,'g-payment-fees-sl'!$C:$C,$C51) | G51: =SUMIFS('g-payment-fees-sl'!$D:$D,'g-payment-fees-sl'!$A:$A,G$1,'g-payment-fees-sl'!$C:$C,$C51) | H51: =SUMIFS('g-payment-fees-sl'!$D:$D,'g-payment-fees-sl'!$A:$A,H$1,'g-payment-fees-sl'!$C:$C,$C51) | I51: =SUMIFS('g-payment-fees-sl'!$D:$D,'g-payment-fees-sl'!$A:$A,I$1,'g-payment-fees-sl'!$C:$C,$C51) | J51: =SUMIFS('g-payment-fees-sl'!$D:$D,'g-payment-fees-sl'!$A:$A,J$1,'g-payment-fees-sl'!$C:$C,$C51) | K51: =SUMIFS('g-payment-fees-sl'!$D:$D,'g-payment-fees-sl'!$A:$A,K$1,'g-payment-fees-sl'!$C:$C,$C51) | ... O51: =SUMIFS('g-payment-fees-sl'!$D:$D,'g-payment-fees-sl'!$A:$A,O$1,'g-payment-fees-sl'!$C:$C,$C51) | P51: =SUM(D51:O51) | Q51: ->
A52: PAYPAL | C52: PAYPAL | D52: =SUMIFS('g-payment-fees-sl'!$D:$D,'g-payment-fees-sl'!$A:$A,D$1,'g-payment-fees-sl'!$C:$C,$C52) | E52: =SUMIFS('g-payment-fees-sl'!$D:$D,'g-payment-fees-sl'!$A:$A,E$1,'g-payment-fees-sl'!$C:$C,$C52) | F52: =SUMIFS('g-payment-fees-sl'!$D:$D,'g-payment-fees-sl'!$A:$A,F$1,'g-payment-fees-sl'!$C:$C,$C52) | G52: =SUMIFS('g-payment-fees-sl'!$D:$D,'g-payment-fees-sl'!$A:$A,G$1,'g-payment-fees-sl'!$C:$C,$C52) | H52: =SUMIFS('g-payment-fees-sl'!$D:$D,'g-payment-fees-sl'!$A:$A,H$1,'g-payment-fees-sl'!$C:$C,$C52) | I52: =SUMIFS('g-payment-fees-sl'!$D:$D,'g-payment-fees-sl'!$A:$A,I$1,'g-payment-fees-sl'!$C:$C,$C52) | J52: =SUMIFS('g-payment-fees-sl'!$D:$D,'g-payment-fees-sl'!$A:$A,J$1,'g-payment-fees-sl'!$C:$C,$C52) | K52: =SUMIFS('g-payment-fees-sl'!$D:$D,'g-payment-fees-sl'!$A:$A,K$1,'g-payment-fees-sl'!$C:$C,$C52) | ... O52: =SUMIFS('g-payment-fees-sl'!$D:$D,'g-payment-fees-sl'!$A:$A,O$1,'g-payment-fees-sl'!$C:$C,$C52) | P52: =SUM(D52:O52) | Q52: ->
A53: % Payment fees / sales | C53: % Payment fees / sales | D53: =IFERROR(D50/D5,0) | E53: =IFERROR(E50/E5,0) | F53: =IFERROR(F50/F5,0) | G53: =IFERROR(G50/G5,0) | H53: =IFERROR(H50/H5,0) | I53: =IFERROR(I50/I5,0) | J53: =IFERROR(J50/J5,0) | K53: =IFERROR(K50/K5,0) | ... O53: =IFERROR(O50/O5,0) | P53: =SUM(D53:O53)
P54: =SUM(D54:O54)
A55: GROSS MARGIN (SALES-MANUFACTURING) | D55: =D5-D33 | E55: =E5-E33 | F55: =F5-F33 | G55: =G5-G33 | H55: =H5-H33 | I55: =I5-I33 | J55: =J5-J33 | K55: =K5-K33 | ... O55: =O5-O33 | P55: =SUM(D55:O55)
A56: % GROSS MARGIN | D56: =IFERROR(D55/D5,0) | E56: =IFERROR(E55/E5,0) | F56: =IFERROR(F55/F5,0) | G56: =IFERROR(G55/G5,0) | H56: =IFERROR(H55/H5,0) | I56: =IFERROR(I55/I5,0) | J56: =IFERROR(J55/J5,0) | K56: =IFERROR(K55/K5,0) | ... O56: =IFERROR(O55/O5,0) | P56: =SUM(D56:O56)
A57: CONTRIBUTIVE MARGIN (TURNOVER-COGS) | D57: =D4-D32 | E57: =E4-E32 | F57: =F4-F32 | G57: =G4-G32 | H57: =H4-H32 | I57: =I4-I32 | J57: =J4-J32 | K57: =K4-K32 | ... O57: =O4-O32 | P57: =SUM(D57:O57)
A58: % CONTRIBUTIVE MARGIN | D58: =IFERROR(D57/D4,0) | E58: =IFERROR(E57/E4,0) | F58: =IFERROR(F57/F4,0) | G58: =IFERROR(G57/G4,0) | H58: =IFERROR(H57/H4,0) | I58: =IFERROR(I57/I4,0) | J58: =IFERROR(J57/J4,0) | K58: =IFERROR(K57/K4,0) | ... O58: =IFERROR(O57/O4,0) | P58: =SUM(D58:O58)
P59: =SUM(D59:O59)
A60: Opex | B60: Opex | D60: =D61+D71+D74+D80 | E60: =E61+E71+E74+E80 | F60: =F61+F71+F74+F80 | G60: =G61+G71+G74+G80 | H60: =H61+H71+H74+H80 | I60: =I61+I71+I74+I80 | J60: =J61+J71+J74+J80 | K60: =K61+K71+K74+K80 | ... O60: =O61+O71+O74+O80 | P60: =SUM(D60:O60)
A61: Marketing | C61: Marketing | D61: =D62+D66 | E61: =E62+E66 | F61: =F62+F66 | G61: =G62+G66 | H61: =H62+H66 | I61: =I62+I66 | J61: =J62+J66 | K61: =K62+K66 | ... O61: =O62+O66 | P61: =SUM(D61:O61) | Q61: ->
A62: METAADS | C62: METAADS | D62: =SUM(D63:D65) | E62: =SUM(E63:E65) | F62: =SUM(F63:F65) | G62: =SUM(G63:G65) | H62: =SUM(H63:H65) | I62: =SUM(I63:I65) | J62: =SUM(J63:J65) | K62: =SUM(K63:K65) | ... O62: =SUM(O63:O65) | P62: =SUM(D62:O62) | Q62: ->
A63: EU | C63: EU | D63: =SUMIFS('g-expenses-sl'!$G:$G,'g-expenses-sl'!$A:$A,D$1,'g-expenses-sl'!$D:$D,"marketing",'g-expenses-sl'!$E:$E,"METAADS",'g-expenses-sl'!$F:$F,$C63) | E63: =SUMIFS('g-expenses-sl'!$G:$G,'g-expenses-sl'!$A:$A,E$1,'g-expenses-sl'!$D:$D,"marketing",'g-expenses-sl'!$E:$E,"METAADS",'g-expenses-sl'!$F:$F,$C63) | F63: =SUMIFS('g-expenses-sl'!$G:$G,'g-expenses-sl'!$A:$A,F$1,'g-expenses-sl'!$D:$D,"marketing",'g-expenses-sl'!$E:$E,"METAADS",'g-expenses-sl'!$F:$F,$C63) | G63: =SUMIFS('g-expenses-sl'!$G:$G,'g-expenses-sl'!$A:$A,G$1,'g-expenses-sl'!$D:$D,"marketing",'g-expenses-sl'!$E:$E,"METAADS",'g-expenses-sl'!$F:$F,$C63) | H63: =SUMIFS('g-expenses-sl'!$G:$G,'g-expenses-sl'!$A:$A,H$1,'g-expenses-sl'!$D:$D,"marketing",'g-expenses-sl'!$E:$E,"METAADS",'g-expenses-sl'!$F:$F,$C63) | I63: =SUMIFS('g-expenses-sl'!$G:$G,'g-expenses-sl'!$A:$A,I$1,'g-expenses-sl'!$D:$D,"marketing",'g-expenses-sl'!$E:$E,"METAADS",'g-expenses-sl'!$F:$F,$C63) | J63: =SUMIFS('g-expenses-sl'!$G:$G,'g-expenses-sl'!$A:$A,J$1,'g-expenses-sl'!$D:$D,"marketing",'g-expenses-sl'!$E:$E,"METAADS",'g-expenses-sl'!$F:$F,$C63) | K63: =SUMIFS('g-expenses-sl'!$G:$G,'g-expenses-sl'!$A:$A,K$1,'g-expenses-sl'!$D:$D,"marketing",'g-expenses-sl'!$E:$E,"METAADS",'g-expenses-sl'!$F:$F,$C63) | ... O63: =SUMIFS('g-expenses-sl'!$G:$G,'g-expenses-sl'!$A:$A,O$1,'g-expenses-sl'!$D:$D,"marketing",'g-expenses-sl'!$E:$E,"METAADS",'g-expenses-sl'!$F:$F,$C63) | P63: =SUM(D63:O63) | Q63: ->
A64: UK | C64: UK | D64: =SUMIFS('g-expenses-sl'!$G:$G,'g-expenses-sl'!$A:$A,D$1,'g-expenses-sl'!$D:$D,"marketing",'g-expenses-sl'!$E:$E,"METAADS",'g-expenses-sl'!$F:$F,$C64) | E64: =SUMIFS('g-expenses-sl'!$G:$G,'g-expenses-sl'!$A:$A,E$1,'g-expenses-sl'!$D:$D,"marketing",'g-expenses-sl'!$E:$E,"METAADS",'g-expenses-sl'!$F:$F,$C64) | F64: =SUMIFS('g-expenses-sl'!$G:$G,'g-expenses-sl'!$A:$A,F$1,'g-expenses-sl'!$D:$D,"marketing",'g-expenses-sl'!$E:$E,"METAADS",'g-expenses-sl'!$F:$F,$C64) | G64: =SUMIFS('g-expenses-sl'!$G:$G,'g-expenses-sl'!$A:$A,G$1,'g-expenses-sl'!$D:$D,"marketing",'g-expenses-sl'!$E:$E,"METAADS",'g-expenses-sl'!$F:$F,$C64) | H64: =SUMIFS('g-expenses-sl'!$G:$G,'g-expenses-sl'!$A:$A,H$1,'g-expenses-sl'!$D:$D,"marketing",'g-expenses-sl'!$E:$E,"METAADS",'g-expenses-sl'!$F:$F,$C64) | I64: =SUMIFS('g-expenses-sl'!$G:$G,'g-expenses-sl'!$A:$A,I$1,'g-expenses-sl'!$D:$D,"marketing",'g-expenses-sl'!$E:$E,"METAADS",'g-expenses-sl'!$F:$F,$C64) | J64: =SUMIFS('g-expenses-sl'!$G:$G,'g-expenses-sl'!$A:$A,J$1,'g-expenses-sl'!$D:$D,"marketing",'g-expenses-sl'!$E:$E,"METAADS",'g-expenses-sl'!$F:$F,$C64) | K64: =SUMIFS('g-expenses-sl'!$G:$G,'g-expenses-sl'!$A:$A,K$1,'g-expenses-sl'!$D:$D,"marketing",'g-expenses-sl'!$E:$E,"METAADS",'g-expenses-sl'!$F:$F,$C64) | ... O64: =SUMIFS('g-expenses-sl'!$G:$G,'g-expenses-sl'!$A:$A,O$1,'g-expenses-sl'!$D:$D,"marketing",'g-expenses-sl'!$E:$E,"METAADS",'g-expenses-sl'!$F:$F,$C64) | P64: =SUM(D64:O64) | Q64: ->
A65: US | C65: US | D65: =SUMIFS('g-expenses-sl'!$G:$G,'g-expenses-sl'!$A:$A,D$1,'g-expenses-sl'!$D:$D,"marketing",'g-expenses-sl'!$E:$E,"METAADS",'g-expenses-sl'!$F:$F,$C65) | E65: =SUMIFS('g-expenses-sl'!$G:$G,'g-expenses-sl'!$A:$A,E$1,'g-expenses-sl'!$D:$D,"marketing",'g-expenses-sl'!$E:$E,"METAADS",'g-expenses-sl'!$F:$F,$C65) | F65: =SUMIFS('g-expenses-sl'!$G:$G,'g-expenses-sl'!$A:$A,F$1,'g-expenses-sl'!$D:$D,"marketing",'g-expenses-sl'!$E:$E,"METAADS",'g-expenses-sl'!$F:$F,$C65) | G65: =SUMIFS('g-expenses-sl'!$G:$G,'g-expenses-sl'!$A:$A,G$1,'g-expenses-sl'!$D:$D,"marketing",'g-expenses-sl'!$E:$E,"METAADS",'g-expenses-sl'!$F:$F,$C65) | H65: =SUMIFS('g-expenses-sl'!$G:$G,'g-expenses-sl'!$A:$A,H$1,'g-expenses-sl'!$D:$D,"marketing",'g-expenses-sl'!$E:$E,"METAADS",'g-expenses-sl'!$F:$F,$C65) | I65: =SUMIFS('g-expenses-sl'!$G:$G,'g-expenses-sl'!$A:$A,I$1,'g-expenses-sl'!$D:$D,"marketing",'g-expenses-sl'!$E:$E,"METAADS",'g-expenses-sl'!$F:$F,$C65) | J65: =SUMIFS('g-expenses-sl'!$G:$G,'g-expenses-sl'!$A:$A,J$1,'g-expenses-sl'!$D:$D,"marketing",'g-expenses-sl'!$E:$E,"METAADS",'g-expenses-sl'!$F:$F,$C65) | K65: =SUMIFS('g-expenses-sl'!$G:$G,'g-expenses-sl'!$A:$A,K$1,'g-expenses-sl'!$D:$D,"marketing",'g-expenses-sl'!$E:$E,"METAADS",'g-expenses-sl'!$F:$F,$C65) | ... O65: =SUMIFS('g-expenses-sl'!$G:$G,'g-expenses-sl'!$A:$A,O$1,'g-expenses-sl'!$D:$D,"marketing",'g-expenses-sl'!$E:$E,"METAADS",'g-expenses-sl'!$F:$F,$C65) | P65: =SUM(D65:O65) | Q65: ->
A66: GOOGLEADS | C66: GOOGLEADS | D66: =SUM(D67:D69) | E66: =SUM(E67:E69) | F66: =SUM(F67:F69) | G66: =SUM(G67:G69) | H66: =SUM(H67:H69) | I66: =SUM(I67:I69) | J66: =SUM(J67:J69) | K66: =SUM(K67:K69) | ... O66: =SUM(O67:O69) | P66: =SUM(D66:O66) | Q66: ->
A67: EU | C67: EU | D67: =SUMIFS('g-expenses-sl'!$G:$G,'g-expenses-sl'!$A:$A,D$1,'g-expenses-sl'!$D:$D,"marketing",'g-expenses-sl'!$E:$E,"GOOGLEADS",'g-expenses-sl'!$F:$F,$C67) | E67: =SUMIFS('g-expenses-sl'!$G:$G,'g-expenses-sl'!$A:$A,E$1,'g-expenses-sl'!$D:$D,"marketing",'g-expenses-sl'!$E:$E,"GOOGLEADS",'g-expenses-sl'!$F:$F,$C67) | F67: =SUMIFS('g-expenses-sl'!$G:$G,'g-expenses-sl'!$A:$A,F$1,'g-expenses-sl'!$D:$D,"marketing",'g-expenses-sl'!$E:$E,"GOOGLEADS",'g-expenses-sl'!$F:$F,$C67) | G67: =SUMIFS('g-expenses-sl'!$G:$G,'g-expenses-sl'!$A:$A,G$1,'g-expenses-sl'!$D:$D,"marketing",'g-expenses-sl'!$E:$E,"GOOGLEADS",'g-expenses-sl'!$F:$F,$C67) | H67: =SUMIFS('g-expenses-sl'!$G:$G,'g-expenses-sl'!$A:$A,H$1,'g-expenses-sl'!$D:$D,"marketing",'g-expenses-sl'!$E:$E,"GOOGLEADS",'g-expenses-sl'!$F:$F,$C67) | I67: =SUMIFS('g-expenses-sl'!$G:$G,'g-expenses-sl'!$A:$A,I$1,'g-expenses-sl'!$D:$D,"marketing",'g-expenses-sl'!$E:$E,"GOOGLEADS",'g-expenses-sl'!$F:$F,$C67) | J67: =SUMIFS('g-expenses-sl'!$G:$G,'g-expenses-sl'!$A:$A,J$1,'g-expenses-sl'!$D:$D,"marketing",'g-expenses-sl'!$E:$E,"GOOGLEADS",'g-expenses-sl'!$F:$F,$C67) | K67: =SUMIFS('g-expenses-sl'!$G:$G,'g-expenses-sl'!$A:$A,K$1,'g-expenses-sl'!$D:$D,"marketing",'g-expenses-sl'!$E:$E,"GOOGLEADS",'g-expenses-sl'!$F:$F,$C67) | ... O67: =SUMIFS('g-expenses-sl'!$G:$G,'g-expenses-sl'!$A:$A,O$1,'g-expenses-sl'!$D:$D,"marketing",'g-expenses-sl'!$E:$E,"GOOGLEADS",'g-expenses-sl'!$F:$F,$C67) | P67: =SUM(D67:O67) | Q67: ->
A68: UK | C68: UK | D68: =SUMIFS('g-expenses-sl'!$G:$G,'g-expenses-sl'!$A:$A,D$1,'g-expenses-sl'!$D:$D,"marketing",'g-expenses-sl'!$E:$E,"GOOGLEADS",'g-expenses-sl'!$F:$F,$C68) | E68: =SUMIFS('g-expenses-sl'!$G:$G,'g-expenses-sl'!$A:$A,E$1,'g-expenses-sl'!$D:$D,"marketing",'g-expenses-sl'!$E:$E,"GOOGLEADS",'g-expenses-sl'!$F:$F,$C68) | F68: =SUMIFS('g-expenses-sl'!$G:$G,'g-expenses-sl'!$A:$A,F$1,'g-expenses-sl'!$D:$D,"marketing",'g-expenses-sl'!$E:$E,"GOOGLEADS",'g-expenses-sl'!$F:$F,$C68) | G68: =SUMIFS('g-expenses-sl'!$G:$G,'g-expenses-sl'!$A:$A,G$1,'g-expenses-sl'!$D:$D,"marketing",'g-expenses-sl'!$E:$E,"GOOGLEADS",'g-expenses-sl'!$F:$F,$C68) | H68: =SUMIFS('g-expenses-sl'!$G:$G,'g-expenses-sl'!$A:$A,H$1,'g-expenses-sl'!$D:$D,"marketing",'g-expenses-sl'!$E:$E,"GOOGLEADS",'g-expenses-sl'!$F:$F,$C68) | I68: =SUMIFS('g-expenses-sl'!$G:$G,'g-expenses-sl'!$A:$A,I$1,'g-expenses-sl'!$D:$D,"marketing",'g-expenses-sl'!$E:$E,"GOOGLEADS",'g-expenses-sl'!$F:$F,$C68) | J68: =SUMIFS('g-expenses-sl'!$G:$G,'g-expenses-sl'!$A:$A,J$1,'g-expenses-sl'!$D:$D,"marketing",'g-expenses-sl'!$E:$E,"GOOGLEADS",'g-expenses-sl'!$F:$F,$C68) | K68: =SUMIFS('g-expenses-sl'!$G:$G,'g-expenses-sl'!$A:$A,K$1,'g-expenses-sl'!$D:$D,"marketing",'g-expenses-sl'!$E:$E,"GOOGLEADS",'g-expenses-sl'!$F:$F,$C68) | ... O68: =SUMIFS('g-expenses-sl'!$G:$G,'g-expenses-sl'!$A:$A,O$1,'g-expenses-sl'!$D:$D,"marketing",'g-expenses-sl'!$E:$E,"GOOGLEADS",'g-expenses-sl'!$F:$F,$C68) | P68: =SUM(D68:O68) | Q68: ->
A69: US | C69: US | D69: =SUMIFS('g-expenses-sl'!$G:$G,'g-expenses-sl'!$A:$A,D$1,'g-expenses-sl'!$D:$D,"marketing",'g-expenses-sl'!$E:$E,"GOOGLEADS",'g-expenses-sl'!$F:$F,$C69) | E69: =SUMIFS('g-expenses-sl'!$G:$G,'g-expenses-sl'!$A:$A,E$1,'g-expenses-sl'!$D:$D,"marketing",'g-expenses-sl'!$E:$E,"GOOGLEADS",'g-expenses-sl'!$F:$F,$C69) | F69: =SUMIFS('g-expenses-sl'!$G:$G,'g-expenses-sl'!$A:$A,F$1,'g-expenses-sl'!$D:$D,"marketing",'g-expenses-sl'!$E:$E,"GOOGLEADS",'g-expenses-sl'!$F:$F,$C69) | G69: =SUMIFS('g-expenses-sl'!$G:$G,'g-expenses-sl'!$A:$A,G$1,'g-expenses-sl'!$D:$D,"marketing",'g-expenses-sl'!$E:$E,"GOOGLEADS",'g-expenses-sl'!$F:$F,$C69) | H69: =SUMIFS('g-expenses-sl'!$G:$G,'g-expenses-sl'!$A:$A,H$1,'g-expenses-sl'!$D:$D,"marketing",'g-expenses-sl'!$E:$E,"GOOGLEADS",'g-expenses-sl'!$F:$F,$C69) | I69: =SUMIFS('g-expenses-sl'!$G:$G,'g-expenses-sl'!$A:$A,I$1,'g-expenses-sl'!$D:$D,"marketing",'g-expenses-sl'!$E:$E,"GOOGLEADS",'g-expenses-sl'!$F:$F,$C69) | J69: =SUMIFS('g-expenses-sl'!$G:$G,'g-expenses-sl'!$A:$A,J$1,'g-expenses-sl'!$D:$D,"marketing",'g-expenses-sl'!$E:$E,"GOOGLEADS",'g-expenses-sl'!$F:$F,$C69) | K69: =SUMIFS('g-expenses-sl'!$G:$G,'g-expenses-sl'!$A:$A,K$1,'g-expenses-sl'!$D:$D,"marketing",'g-expenses-sl'!$E:$E,"GOOGLEADS",'g-expenses-sl'!$F:$F,$C69) | ... O69: =SUMIFS('g-expenses-sl'!$G:$G,'g-expenses-sl'!$A:$A,O$1,'g-expenses-sl'!$D:$D,"marketing",'g-expenses-sl'!$E:$E,"GOOGLEADS",'g-expenses-sl'!$F:$F,$C69) | P69: =SUM(D69:O69) | Q69: ->
A70: Sales / mkt EU | C70: Sales / mkt EU | D70: =IFERROR(SUM(D7:D14)/(D63+D67),0) | E70: =IFERROR(SUM(E7:E14)/(E63+E67),0) | F70: =IFERROR(SUM(F7:F14)/(F63+F67),0) | G70: =IFERROR(SUM(G7:G14)/(G63+G67),0) | H70: =IFERROR(SUM(H7:H14)/(H63+H67),0) | I70: =IFERROR(SUM(I7:I14)/(I63+I67),0) | J70: =IFERROR(SUM(J7:J14)/(J63+J67),0) | K70: =IFERROR(SUM(K7:K14)/(K63+K67),0) | ... O70: =IFERROR(SUM(O7:O14)/(O63+O67),0) | P70: =SUM(D70:O70)
A71: Staff | C71: Staff | D71: =SUM(D72:D73) | E71: =SUM(E72:E73) | F71: =SUM(F72:F73) | G71: =SUM(G72:G73) | H71: =SUM(H72:H73) | I71: =SUM(I72:I73) | J71: =SUM(J72:J73) | K71: =SUM(K72:K73) | ... O71: =SUM(O72:O73) | P71: =SUM(D71:O71) | Q71: ->
A72: PAYROLL | C72: PAYROLL | D72: =SUMIFS('g-expenses-sl'!$G:$G,'g-expenses-sl'!$A:$A,D$1,'g-expenses-sl'!$D:$D,"staff",'g-expenses-sl'!$E:$E,$C72) | E72: =SUMIFS('g-expenses-sl'!$G:$G,'g-expenses-sl'!$A:$A,E$1,'g-expenses-sl'!$D:$D,"staff",'g-expenses-sl'!$E:$E,$C72) | F72: =SUMIFS('g-expenses-sl'!$G:$G,'g-expenses-sl'!$A:$A,F$1,'g-expenses-sl'!$D:$D,"staff",'g-expenses-sl'!$E:$E,$C72) | G72: =SUMIFS('g-expenses-sl'!$G:$G,'g-expenses-sl'!$A:$A,G$1,'g-expenses-sl'!$D:$D,"staff",'g-expenses-sl'!$E:$E,$C72) | H72: =SUMIFS('g-expenses-sl'!$G:$G,'g-expenses-sl'!$A:$A,H$1,'g-expenses-sl'!$D:$D,"staff",'g-expenses-sl'!$E:$E,$C72) | I72: =SUMIFS('g-expenses-sl'!$G:$G,'g-expenses-sl'!$A:$A,I$1,'g-expenses-sl'!$D:$D,"staff",'g-expenses-sl'!$E:$E,$C72) | J72: =SUMIFS('g-expenses-sl'!$G:$G,'g-expenses-sl'!$A:$A,J$1,'g-expenses-sl'!$D:$D,"staff",'g-expenses-sl'!$E:$E,$C72) | K72: =SUMIFS('g-expenses-sl'!$G:$G,'g-expenses-sl'!$A:$A,K$1,'g-expenses-sl'!$D:$D,"staff",'g-expenses-sl'!$E:$E,$C72) | ... O72: =SUMIFS('g-expenses-sl'!$G:$G,'g-expenses-sl'!$A:$A,O$1,'g-expenses-sl'!$D:$D,"staff",'g-expenses-sl'!$E:$E,$C72) | P72: =SUM(D72:O72) | Q72: ->
A73: DOSCONSULTING | C73: DOSCONSULTING | D73: =SUMIFS('g-expenses-sl'!$G:$G,'g-expenses-sl'!$A:$A,D$1,'g-expenses-sl'!$D:$D,"staff",'g-expenses-sl'!$E:$E,$C73) | E73: =SUMIFS('g-expenses-sl'!$G:$G,'g-expenses-sl'!$A:$A,E$1,'g-expenses-sl'!$D:$D,"staff",'g-expenses-sl'!$E:$E,$C73) | F73: =SUMIFS('g-expenses-sl'!$G:$G,'g-expenses-sl'!$A:$A,F$1,'g-expenses-sl'!$D:$D,"staff",'g-expenses-sl'!$E:$E,$C73) | G73: =SUMIFS('g-expenses-sl'!$G:$G,'g-expenses-sl'!$A:$A,G$1,'g-expenses-sl'!$D:$D,"staff",'g-expenses-sl'!$E:$E,$C73) | H73: =SUMIFS('g-expenses-sl'!$G:$G,'g-expenses-sl'!$A:$A,H$1,'g-expenses-sl'!$D:$D,"staff",'g-expenses-sl'!$E:$E,$C73) | I73: =SUMIFS('g-expenses-sl'!$G:$G,'g-expenses-sl'!$A:$A,I$1,'g-expenses-sl'!$D:$D,"staff",'g-expenses-sl'!$E:$E,$C73) | J73: =SUMIFS('g-expenses-sl'!$G:$G,'g-expenses-sl'!$A:$A,J$1,'g-expenses-sl'!$D:$D,"staff",'g-expenses-sl'!$E:$E,$C73) | K73: =SUMIFS('g-expenses-sl'!$G:$G,'g-expenses-sl'!$A:$A,K$1,'g-expenses-sl'!$D:$D,"staff",'g-expenses-sl'!$E:$E,$C73) | ... O73: =SUMIFS('g-expenses-sl'!$G:$G,'g-expenses-sl'!$A:$A,O$1,'g-expenses-sl'!$D:$D,"staff",'g-expenses-sl'!$E:$E,$C73) | P73: =SUM(D73:O73) | Q73: ->
A74: Administration | C74: Administration | D74: =SUM(D75:D79) | E74: =SUM(E75:E79) | F74: =SUM(F75:F79) | G74: =SUM(G75:G79) | H74: =SUM(H75:H79) | I74: =SUM(I75:I79) | J74: =SUM(J75:J79) | K74: =SUM(K75:K79) | ... O74: =SUM(O75:O79) | P74: =SUM(D74:O74) | Q74: ->
A75: CLARIS | C75: CLARIS | D75: =SUMIFS('g-expenses-sl'!$G:$G,'g-expenses-sl'!$A:$A,D$1,'g-expenses-sl'!$D:$D,"administration",'g-expenses-sl'!$E:$E,$C75) | E75: =SUMIFS('g-expenses-sl'!$G:$G,'g-expenses-sl'!$A:$A,E$1,'g-expenses-sl'!$D:$D,"administration",'g-expenses-sl'!$E:$E,$C75) | F75: =SUMIFS('g-expenses-sl'!$G:$G,'g-expenses-sl'!$A:$A,F$1,'g-expenses-sl'!$D:$D,"administration",'g-expenses-sl'!$E:$E,$C75) | G75: =SUMIFS('g-expenses-sl'!$G:$G,'g-expenses-sl'!$A:$A,G$1,'g-expenses-sl'!$D:$D,"administration",'g-expenses-sl'!$E:$E,$C75) | H75: =SUMIFS('g-expenses-sl'!$G:$G,'g-expenses-sl'!$A:$A,H$1,'g-expenses-sl'!$D:$D,"administration",'g-expenses-sl'!$E:$E,$C75) | I75: =SUMIFS('g-expenses-sl'!$G:$G,'g-expenses-sl'!$A:$A,I$1,'g-expenses-sl'!$D:$D,"administration",'g-expenses-sl'!$E:$E,$C75) | J75: =SUMIFS('g-expenses-sl'!$G:$G,'g-expenses-sl'!$A:$A,J$1,'g-expenses-sl'!$D:$D,"administration",'g-expenses-sl'!$E:$E,$C75) | K75: =SUMIFS('g-expenses-sl'!$G:$G,'g-expenses-sl'!$A:$A,K$1,'g-expenses-sl'!$D:$D,"administration",'g-expenses-sl'!$E:$E,$C75) | ... O75: =SUMIFS('g-expenses-sl'!$G:$G,'g-expenses-sl'!$A:$A,O$1,'g-expenses-sl'!$D:$D,"administration",'g-expenses-sl'!$E:$E,$C75) | P75: =SUM(D75:O75) | Q75: ->
A76: HANNUN | C76: HANNUN | D76: =SUMIFS('g-expenses-sl'!$G:$G,'g-expenses-sl'!$A:$A,D$1,'g-expenses-sl'!$D:$D,"administration",'g-expenses-sl'!$E:$E,$C76) | E76: =SUMIFS('g-expenses-sl'!$G:$G,'g-expenses-sl'!$A:$A,E$1,'g-expenses-sl'!$D:$D,"administration",'g-expenses-sl'!$E:$E,$C76) | F76: =SUMIFS('g-expenses-sl'!$G:$G,'g-expenses-sl'!$A:$A,F$1,'g-expenses-sl'!$D:$D,"administration",'g-expenses-sl'!$E:$E,$C76) | G76: =SUMIFS('g-expenses-sl'!$G:$G,'g-expenses-sl'!$A:$A,G$1,'g-expenses-sl'!$D:$D,"administration",'g-expenses-sl'!$E:$E,$C76) | H76: =SUMIFS('g-expenses-sl'!$G:$G,'g-expenses-sl'!$A:$A,H$1,'g-expenses-sl'!$D:$D,"administration",'g-expenses-sl'!$E:$E,$C76) | I76: =SUMIFS('g-expenses-sl'!$G:$G,'g-expenses-sl'!$A:$A,I$1,'g-expenses-sl'!$D:$D,"administration",'g-expenses-sl'!$E:$E,$C76) | J76: =SUMIFS('g-expenses-sl'!$G:$G,'g-expenses-sl'!$A:$A,J$1,'g-expenses-sl'!$D:$D,"administration",'g-expenses-sl'!$E:$E,$C76) | K76: =SUMIFS('g-expenses-sl'!$G:$G,'g-expenses-sl'!$A:$A,K$1,'g-expenses-sl'!$D:$D,"administration",'g-expenses-sl'!$E:$E,$C76) | ... O76: =SUMIFS('g-expenses-sl'!$G:$G,'g-expenses-sl'!$A:$A,O$1,'g-expenses-sl'!$D:$D,"administration",'g-expenses-sl'!$E:$E,$C76) | P76: =SUM(D76:O76) | Q76: ->
A77: NODA | C77: NODA | D77: =SUMIFS('g-expenses-sl'!$G:$G,'g-expenses-sl'!$A:$A,D$1,'g-expenses-sl'!$D:$D,"administration",'g-expenses-sl'!$E:$E,$C77) | E77: =SUMIFS('g-expenses-sl'!$G:$G,'g-expenses-sl'!$A:$A,E$1,'g-expenses-sl'!$D:$D,"administration",'g-expenses-sl'!$E:$E,$C77) | F77: =SUMIFS('g-expenses-sl'!$G:$G,'g-expenses-sl'!$A:$A,F$1,'g-expenses-sl'!$D:$D,"administration",'g-expenses-sl'!$E:$E,$C77) | G77: =SUMIFS('g-expenses-sl'!$G:$G,'g-expenses-sl'!$A:$A,G$1,'g-expenses-sl'!$D:$D,"administration",'g-expenses-sl'!$E:$E,$C77) | H77: =SUMIFS('g-expenses-sl'!$G:$G,'g-expenses-sl'!$A:$A,H$1,'g-expenses-sl'!$D:$D,"administration",'g-expenses-sl'!$E:$E,$C77) | I77: =SUMIFS('g-expenses-sl'!$G:$G,'g-expenses-sl'!$A:$A,I$1,'g-expenses-sl'!$D:$D,"administration",'g-expenses-sl'!$E:$E,$C77) | J77: =SUMIFS('g-expenses-sl'!$G:$G,'g-expenses-sl'!$A:$A,J$1,'g-expenses-sl'!$D:$D,"administration",'g-expenses-sl'!$E:$E,$C77) | K77: =SUMIFS('g-expenses-sl'!$G:$G,'g-expenses-sl'!$A:$A,K$1,'g-expenses-sl'!$D:$D,"administration",'g-expenses-sl'!$E:$E,$C77) | ... O77: =SUMIFS('g-expenses-sl'!$G:$G,'g-expenses-sl'!$A:$A,O$1,'g-expenses-sl'!$D:$D,"administration",'g-expenses-sl'!$E:$E,$C77) | P77: =SUM(D77:O77) | Q77: ->
A78: TORRAS | C78: TORRAS | D78: =SUMIFS('g-expenses-sl'!$G:$G,'g-expenses-sl'!$A:$A,D$1,'g-expenses-sl'!$D:$D,"administration",'g-expenses-sl'!$E:$E,$C78) | E78: =SUMIFS('g-expenses-sl'!$G:$G,'g-expenses-sl'!$A:$A,E$1,'g-expenses-sl'!$D:$D,"administration",'g-expenses-sl'!$E:$E,$C78) | F78: =SUMIFS('g-expenses-sl'!$G:$G,'g-expenses-sl'!$A:$A,F$1,'g-expenses-sl'!$D:$D,"administration",'g-expenses-sl'!$E:$E,$C78) | G78: =SUMIFS('g-expenses-sl'!$G:$G,'g-expenses-sl'!$A:$A,G$1,'g-expenses-sl'!$D:$D,"administration",'g-expenses-sl'!$E:$E,$C78) | H78: =SUMIFS('g-expenses-sl'!$G:$G,'g-expenses-sl'!$A:$A,H$1,'g-expenses-sl'!$D:$D,"administration",'g-expenses-sl'!$E:$E,$C78) | I78: =SUMIFS('g-expenses-sl'!$G:$G,'g-expenses-sl'!$A:$A,I$1,'g-expenses-sl'!$D:$D,"administration",'g-expenses-sl'!$E:$E,$C78) | J78: =SUMIFS('g-expenses-sl'!$G:$G,'g-expenses-sl'!$A:$A,J$1,'g-expenses-sl'!$D:$D,"administration",'g-expenses-sl'!$E:$E,$C78) | K78: =SUMIFS('g-expenses-sl'!$G:$G,'g-expenses-sl'!$A:$A,K$1,'g-expenses-sl'!$D:$D,"administration",'g-expenses-sl'!$E:$E,$C78) | ... O78: =SUMIFS('g-expenses-sl'!$G:$G,'g-expenses-sl'!$A:$A,O$1,'g-expenses-sl'!$D:$D,"administration",'g-expenses-sl'!$E:$E,$C78) | P78: =SUM(D78:O78) | Q78: ->
A79: VITALY | C79: VITALY | D79: =SUMIFS('g-expenses-sl'!$G:$G,'g-expenses-sl'!$A:$A,D$1,'g-expenses-sl'!$D:$D,"administration",'g-expenses-sl'!$E:$E,$C79) | E79: =SUMIFS('g-expenses-sl'!$G:$G,'g-expenses-sl'!$A:$A,E$1,'g-expenses-sl'!$D:$D,"administration",'g-expenses-sl'!$E:$E,$C79) | F79: =SUMIFS('g-expenses-sl'!$G:$G,'g-expenses-sl'!$A:$A,F$1,'g-expenses-sl'!$D:$D,"administration",'g-expenses-sl'!$E:$E,$C79) | G79: =SUMIFS('g-expenses-sl'!$G:$G,'g-expenses-sl'!$A:$A,G$1,'g-expenses-sl'!$D:$D,"administration",'g-expenses-sl'!$E:$E,$C79) | H79: =SUMIFS('g-expenses-sl'!$G:$G,'g-expenses-sl'!$A:$A,H$1,'g-expenses-sl'!$D:$D,"administration",'g-expenses-sl'!$E:$E,$C79) | I79: =SUMIFS('g-expenses-sl'!$G:$G,'g-expenses-sl'!$A:$A,I$1,'g-expenses-sl'!$D:$D,"administration",'g-expenses-sl'!$E:$E,$C79) | J79: =SUMIFS('g-expenses-sl'!$G:$G,'g-expenses-sl'!$A:$A,J$1,'g-expenses-sl'!$D:$D,"administration",'g-expenses-sl'!$E:$E,$C79) | K79: =SUMIFS('g-expenses-sl'!$G:$G,'g-expenses-sl'!$A:$A,K$1,'g-expenses-sl'!$D:$D,"administration",'g-expenses-sl'!$E:$E,$C79) | ... O79: =SUMIFS('g-expenses-sl'!$G:$G,'g-expenses-sl'!$A:$A,O$1,'g-expenses-sl'!$D:$D,"administration",'g-expenses-sl'!$E:$E,$C79) | P79: =SUM(D79:O79) | Q79: ->
A80: Technology | C80: Technology | D80: =SUM(D81:D95) | E80: =SUM(E81:E95) | F80: =SUM(F81:F95) | G80: =SUM(G81:G95) | H80: =SUM(H81:H95) | I80: =SUM(I81:I95) | J80: =SUM(J81:J95) | K80: =SUM(K81:K95) | ... O80: =SUM(O81:O95) | P80: =SUM(D80:O80) | Q80: ->
A81: ADOBE | C81: ADOBE | D81: =SUMIFS('g-expenses-sl'!$G:$G,'g-expenses-sl'!$A:$A,D$1,'g-expenses-sl'!$D:$D,"technology",'g-expenses-sl'!$E:$E,$C81) | E81: =SUMIFS('g-expenses-sl'!$G:$G,'g-expenses-sl'!$A:$A,E$1,'g-expenses-sl'!$D:$D,"technology",'g-expenses-sl'!$E:$E,$C81) | F81: =SUMIFS('g-expenses-sl'!$G:$G,'g-expenses-sl'!$A:$A,F$1,'g-expenses-sl'!$D:$D,"technology",'g-expenses-sl'!$E:$E,$C81) | G81: =SUMIFS('g-expenses-sl'!$G:$G,'g-expenses-sl'!$A:$A,G$1,'g-expenses-sl'!$D:$D,"technology",'g-expenses-sl'!$E:$E,$C81) | H81: =SUMIFS('g-expenses-sl'!$G:$G,'g-expenses-sl'!$A:$A,H$1,'g-expenses-sl'!$D:$D,"technology",'g-expenses-sl'!$E:$E,$C81) | I81: =SUMIFS('g-expenses-sl'!$G:$G,'g-expenses-sl'!$A:$A,I$1,'g-expenses-sl'!$D:$D,"technology",'g-expenses-sl'!$E:$E,$C81) | J81: =SUMIFS('g-expenses-sl'!$G:$G,'g-expenses-sl'!$A:$A,J$1,'g-expenses-sl'!$D:$D,"technology",'g-expenses-sl'!$E:$E,$C81) | K81: =SUMIFS('g-expenses-sl'!$G:$G,'g-expenses-sl'!$A:$A,K$1,'g-expenses-sl'!$D:$D,"technology",'g-expenses-sl'!$E:$E,$C81) | ... O81: =SUMIFS('g-expenses-sl'!$G:$G,'g-expenses-sl'!$A:$A,O$1,'g-expenses-sl'!$D:$D,"technology",'g-expenses-sl'!$E:$E,$C81) | P81: =SUM(D81:O81) | Q81: ->
A82: CANVA | C82: CANVA | D82: =SUMIFS('g-expenses-sl'!$G:$G,'g-expenses-sl'!$A:$A,D$1,'g-expenses-sl'!$D:$D,"technology",'g-expenses-sl'!$E:$E,$C82) | E82: =SUMIFS('g-expenses-sl'!$G:$G,'g-expenses-sl'!$A:$A,E$1,'g-expenses-sl'!$D:$D,"technology",'g-expenses-sl'!$E:$E,$C82) | F82: =SUMIFS('g-expenses-sl'!$G:$G,'g-expenses-sl'!$A:$A,F$1,'g-expenses-sl'!$D:$D,"technology",'g-expenses-sl'!$E:$E,$C82) | G82: =SUMIFS('g-expenses-sl'!$G:$G,'g-expenses-sl'!$A:$A,G$1,'g-expenses-sl'!$D:$D,"technology",'g-expenses-sl'!$E:$E,$C82) | H82: =SUMIFS('g-expenses-sl'!$G:$G,'g-expenses-sl'!$A:$A,H$1,'g-expenses-sl'!$D:$D,"technology",'g-expenses-sl'!$E:$E,$C82) | I82: =SUMIFS('g-expenses-sl'!$G:$G,'g-expenses-sl'!$A:$A,I$1,'g-expenses-sl'!$D:$D,"technology",'g-expenses-sl'!$E:$E,$C82) | J82: =SUMIFS('g-expenses-sl'!$G:$G,'g-expenses-sl'!$A:$A,J$1,'g-expenses-sl'!$D:$D,"technology",'g-expenses-sl'!$E:$E,$C82) | K82: =SUMIFS('g-expenses-sl'!$G:$G,'g-expenses-sl'!$A:$A,K$1,'g-expenses-sl'!$D:$D,"technology",'g-expenses-sl'!$E:$E,$C82) | ... O82: =SUMIFS('g-expenses-sl'!$G:$G,'g-expenses-sl'!$A:$A,O$1,'g-expenses-sl'!$D:$D,"technology",'g-expenses-sl'!$E:$E,$C82) | P82: =SUM(D82:O82) | Q82: ->
A83: GODADDY | C83: GODADDY | D83: =SUMIFS('g-expenses-sl'!$G:$G,'g-expenses-sl'!$A:$A,D$1,'g-expenses-sl'!$D:$D,"technology",'g-expenses-sl'!$E:$E,$C83) | E83: =SUMIFS('g-expenses-sl'!$G:$G,'g-expenses-sl'!$A:$A,E$1,'g-expenses-sl'!$D:$D,"technology",'g-expenses-sl'!$E:$E,$C83) | F83: =SUMIFS('g-expenses-sl'!$G:$G,'g-expenses-sl'!$A:$A,F$1,'g-expenses-sl'!$D:$D,"technology",'g-expenses-sl'!$E:$E,$C83) | G83: =SUMIFS('g-expenses-sl'!$G:$G,'g-expenses-sl'!$A:$A,G$1,'g-expenses-sl'!$D:$D,"technology",'g-expenses-sl'!$E:$E,$C83) | H83: =SUMIFS('g-expenses-sl'!$G:$G,'g-expenses-sl'!$A:$A,H$1,'g-expenses-sl'!$D:$D,"technology",'g-expenses-sl'!$E:$E,$C83) | I83: =SUMIFS('g-expenses-sl'!$G:$G,'g-expenses-sl'!$A:$A,I$1,'g-expenses-sl'!$D:$D,"technology",'g-expenses-sl'!$E:$E,$C83) | J83: =SUMIFS('g-expenses-sl'!$G:$G,'g-expenses-sl'!$A:$A,J$1,'g-expenses-sl'!$D:$D,"technology",'g-expenses-sl'!$E:$E,$C83) | K83: =SUMIFS('g-expenses-sl'!$G:$G,'g-expenses-sl'!$A:$A,K$1,'g-expenses-sl'!$D:$D,"technology",'g-expenses-sl'!$E:$E,$C83) | ... O83: =SUMIFS('g-expenses-sl'!$G:$G,'g-expenses-sl'!$A:$A,O$1,'g-expenses-sl'!$D:$D,"technology",'g-expenses-sl'!$E:$E,$C83) | P83: =SUM(D83:O83) | Q83: ->
A84: GOOGLEWORKSPACE | C84: GOOGLEWORKSPACE | D84: =SUMIFS('g-expenses-sl'!$G:$G,'g-expenses-sl'!$A:$A,D$1,'g-expenses-sl'!$D:$D,"technology",'g-expenses-sl'!$E:$E,$C84) | E84: =SUMIFS('g-expenses-sl'!$G:$G,'g-expenses-sl'!$A:$A,E$1,'g-expenses-sl'!$D:$D,"technology",'g-expenses-sl'!$E:$E,$C84) | F84: =SUMIFS('g-expenses-sl'!$G:$G,'g-expenses-sl'!$A:$A,F$1,'g-expenses-sl'!$D:$D,"technology",'g-expenses-sl'!$E:$E,$C84) | G84: =SUMIFS('g-expenses-sl'!$G:$G,'g-expenses-sl'!$A:$A,G$1,'g-expenses-sl'!$D:$D,"technology",'g-expenses-sl'!$E:$E,$C84) | H84: =SUMIFS('g-expenses-sl'!$G:$G,'g-expenses-sl'!$A:$A,H$1,'g-expenses-sl'!$D:$D,"technology",'g-expenses-sl'!$E:$E,$C84) | I84: =SUMIFS('g-expenses-sl'!$G:$G,'g-expenses-sl'!$A:$A,I$1,'g-expenses-sl'!$D:$D,"technology",'g-expenses-sl'!$E:$E,$C84) | J84: =SUMIFS('g-expenses-sl'!$G:$G,'g-expenses-sl'!$A:$A,J$1,'g-expenses-sl'!$D:$D,"technology",'g-expenses-sl'!$E:$E,$C84) | K84: =SUMIFS('g-expenses-sl'!$G:$G,'g-expenses-sl'!$A:$A,K$1,'g-expenses-sl'!$D:$D,"technology",'g-expenses-sl'!$E:$E,$C84) | ... O84: =SUMIFS('g-expenses-sl'!$G:$G,'g-expenses-sl'!$A:$A,O$1,'g-expenses-sl'!$D:$D,"technology",'g-expenses-sl'!$E:$E,$C84) | P84: =SUM(D84:O84) | Q84: ->
A85: GORGIAS | C85: GORGIAS | D85: =SUMIFS('g-expenses-sl'!$G:$G,'g-expenses-sl'!$A:$A,D$1,'g-expenses-sl'!$D:$D,"technology",'g-expenses-sl'!$E:$E,$C85) | E85: =SUMIFS('g-expenses-sl'!$G:$G,'g-expenses-sl'!$A:$A,E$1,'g-expenses-sl'!$D:$D,"technology",'g-expenses-sl'!$E:$E,$C85) | F85: =SUMIFS('g-expenses-sl'!$G:$G,'g-expenses-sl'!$A:$A,F$1,'g-expenses-sl'!$D:$D,"technology",'g-expenses-sl'!$E:$E,$C85) | G85: =SUMIFS('g-expenses-sl'!$G:$G,'g-expenses-sl'!$A:$A,G$1,'g-expenses-sl'!$D:$D,"technology",'g-expenses-sl'!$E:$E,$C85) | H85: =SUMIFS('g-expenses-sl'!$G:$G,'g-expenses-sl'!$A:$A,H$1,'g-expenses-sl'!$D:$D,"technology",'g-expenses-sl'!$E:$E,$C85) | I85: =SUMIFS('g-expenses-sl'!$G:$G,'g-expenses-sl'!$A:$A,I$1,'g-expenses-sl'!$D:$D,"technology",'g-expenses-sl'!$E:$E,$C85) | J85: =SUMIFS('g-expenses-sl'!$G:$G,'g-expenses-sl'!$A:$A,J$1,'g-expenses-sl'!$D:$D,"technology",'g-expenses-sl'!$E:$E,$C85) | K85: =SUMIFS('g-expenses-sl'!$G:$G,'g-expenses-sl'!$A:$A,K$1,'g-expenses-sl'!$D:$D,"technology",'g-expenses-sl'!$E:$E,$C85) | ... O85: =SUMIFS('g-expenses-sl'!$G:$G,'g-expenses-sl'!$A:$A,O$1,'g-expenses-sl'!$D:$D,"technology",'g-expenses-sl'!$E:$E,$C85) | P85: =SUM(D85:O85) | Q85: ->
A86: HETZNER | C86: HETZNER | D86: =SUMIFS('g-expenses-sl'!$G:$G,'g-expenses-sl'!$A:$A,D$1,'g-expenses-sl'!$D:$D,"technology",'g-expenses-sl'!$E:$E,$C86) | E86: =SUMIFS('g-expenses-sl'!$G:$G,'g-expenses-sl'!$A:$A,E$1,'g-expenses-sl'!$D:$D,"technology",'g-expenses-sl'!$E:$E,$C86) | F86: =SUMIFS('g-expenses-sl'!$G:$G,'g-expenses-sl'!$A:$A,F$1,'g-expenses-sl'!$D:$D,"technology",'g-expenses-sl'!$E:$E,$C86) | G86: =SUMIFS('g-expenses-sl'!$G:$G,'g-expenses-sl'!$A:$A,G$1,'g-expenses-sl'!$D:$D,"technology",'g-expenses-sl'!$E:$E,$C86) | H86: =SUMIFS('g-expenses-sl'!$G:$G,'g-expenses-sl'!$A:$A,H$1,'g-expenses-sl'!$D:$D,"technology",'g-expenses-sl'!$E:$E,$C86) | I86: =SUMIFS('g-expenses-sl'!$G:$G,'g-expenses-sl'!$A:$A,I$1,'g-expenses-sl'!$D:$D,"technology",'g-expenses-sl'!$E:$E,$C86) | J86: =SUMIFS('g-expenses-sl'!$G:$G,'g-expenses-sl'!$A:$A,J$1,'g-expenses-sl'!$D:$D,"technology",'g-expenses-sl'!$E:$E,$C86) | K86: =SUMIFS('g-expenses-sl'!$G:$G,'g-expenses-sl'!$A:$A,K$1,'g-expenses-sl'!$D:$D,"technology",'g-expenses-sl'!$E:$E,$C86) | ... O86: =SUMIFS('g-expenses-sl'!$G:$G,'g-expenses-sl'!$A:$A,O$1,'g-expenses-sl'!$D:$D,"technology",'g-expenses-sl'!$E:$E,$C86) | P86: =SUM(D86:O86) | Q86: ->
A87: KONVOAI | C87: KONVOAI | D87: =SUMIFS('g-expenses-sl'!$G:$G,'g-expenses-sl'!$A:$A,D$1,'g-expenses-sl'!$D:$D,"technology",'g-expenses-sl'!$E:$E,$C87) | E87: =SUMIFS('g-expenses-sl'!$G:$G,'g-expenses-sl'!$A:$A,E$1,'g-expenses-sl'!$D:$D,"technology",'g-expenses-sl'!$E:$E,$C87) | F87: =SUMIFS('g-expenses-sl'!$G:$G,'g-expenses-sl'!$A:$A,F$1,'g-expenses-sl'!$D:$D,"technology",'g-expenses-sl'!$E:$E,$C87) | G87: =SUMIFS('g-expenses-sl'!$G:$G,'g-expenses-sl'!$A:$A,G$1,'g-expenses-sl'!$D:$D,"technology",'g-expenses-sl'!$E:$E,$C87) | H87: =SUMIFS('g-expenses-sl'!$G:$G,'g-expenses-sl'!$A:$A,H$1,'g-expenses-sl'!$D:$D,"technology",'g-expenses-sl'!$E:$E,$C87) | I87: =SUMIFS('g-expenses-sl'!$G:$G,'g-expenses-sl'!$A:$A,I$1,'g-expenses-sl'!$D:$D,"technology",'g-expenses-sl'!$E:$E,$C87) | J87: =SUMIFS('g-expenses-sl'!$G:$G,'g-expenses-sl'!$A:$A,J$1,'g-expenses-sl'!$D:$D,"technology",'g-expenses-sl'!$E:$E,$C87) | K87: =SUMIFS('g-expenses-sl'!$G:$G,'g-expenses-sl'!$A:$A,K$1,'g-expenses-sl'!$D:$D,"technology",'g-expenses-sl'!$E:$E,$C87) | ... O87: =SUMIFS('g-expenses-sl'!$G:$G,'g-expenses-sl'!$A:$A,O$1,'g-expenses-sl'!$D:$D,"technology",'g-expenses-sl'!$E:$E,$C87) | P87: =SUM(D87:O87) | Q87: ->
A88: MASMOVIL | C88: MASMOVIL | D88: =SUMIFS('g-expenses-sl'!$G:$G,'g-expenses-sl'!$A:$A,D$1,'g-expenses-sl'!$D:$D,"technology",'g-expenses-sl'!$E:$E,$C88) | E88: =SUMIFS('g-expenses-sl'!$G:$G,'g-expenses-sl'!$A:$A,E$1,'g-expenses-sl'!$D:$D,"technology",'g-expenses-sl'!$E:$E,$C88) | F88: =SUMIFS('g-expenses-sl'!$G:$G,'g-expenses-sl'!$A:$A,F$1,'g-expenses-sl'!$D:$D,"technology",'g-expenses-sl'!$E:$E,$C88) | G88: =SUMIFS('g-expenses-sl'!$G:$G,'g-expenses-sl'!$A:$A,G$1,'g-expenses-sl'!$D:$D,"technology",'g-expenses-sl'!$E:$E,$C88) | H88: =SUMIFS('g-expenses-sl'!$G:$G,'g-expenses-sl'!$A:$A,H$1,'g-expenses-sl'!$D:$D,"technology",'g-expenses-sl'!$E:$E,$C88) | I88: =SUMIFS('g-expenses-sl'!$G:$G,'g-expenses-sl'!$A:$A,I$1,'g-expenses-sl'!$D:$D,"technology",'g-expenses-sl'!$E:$E,$C88) | J88: =SUMIFS('g-expenses-sl'!$G:$G,'g-expenses-sl'!$A:$A,J$1,'g-expenses-sl'!$D:$D,"technology",'g-expenses-sl'!$E:$E,$C88) | K88: =SUMIFS('g-expenses-sl'!$G:$G,'g-expenses-sl'!$A:$A,K$1,'g-expenses-sl'!$D:$D,"technology",'g-expenses-sl'!$E:$E,$C88) | ... O88: =SUMIFS('g-expenses-sl'!$G:$G,'g-expenses-sl'!$A:$A,O$1,'g-expenses-sl'!$D:$D,"technology",'g-expenses-sl'!$E:$E,$C88) | P88: =SUM(D88:O88) | Q88: ->
A89: MICROSOFT | C89: MICROSOFT | D89: =SUMIFS('g-expenses-sl'!$G:$G,'g-expenses-sl'!$A:$A,D$1,'g-expenses-sl'!$D:$D,"technology",'g-expenses-sl'!$E:$E,$C89) | E89: =SUMIFS('g-expenses-sl'!$G:$G,'g-expenses-sl'!$A:$A,E$1,'g-expenses-sl'!$D:$D,"technology",'g-expenses-sl'!$E:$E,$C89) | F89: =SUMIFS('g-expenses-sl'!$G:$G,'g-expenses-sl'!$A:$A,F$1,'g-expenses-sl'!$D:$D,"technology",'g-expenses-sl'!$E:$E,$C89) | G89: =SUMIFS('g-expenses-sl'!$G:$G,'g-expenses-sl'!$A:$A,G$1,'g-expenses-sl'!$D:$D,"technology",'g-expenses-sl'!$E:$E,$C89) | H89: =SUMIFS('g-expenses-sl'!$G:$G,'g-expenses-sl'!$A:$A,H$1,'g-expenses-sl'!$D:$D,"technology",'g-expenses-sl'!$E:$E,$C89) | I89: =SUMIFS('g-expenses-sl'!$G:$G,'g-expenses-sl'!$A:$A,I$1,'g-expenses-sl'!$D:$D,"technology",'g-expenses-sl'!$E:$E,$C89) | J89: =SUMIFS('g-expenses-sl'!$G:$G,'g-expenses-sl'!$A:$A,J$1,'g-expenses-sl'!$D:$D,"technology",'g-expenses-sl'!$E:$E,$C89) | K89: =SUMIFS('g-expenses-sl'!$G:$G,'g-expenses-sl'!$A:$A,K$1,'g-expenses-sl'!$D:$D,"technology",'g-expenses-sl'!$E:$E,$C89) | ... O89: =SUMIFS('g-expenses-sl'!$G:$G,'g-expenses-sl'!$A:$A,O$1,'g-expenses-sl'!$D:$D,"technology",'g-expenses-sl'!$E:$E,$C89) | P89: =SUM(D89:O89) | Q89: ->
A90: OPENAI | C90: OPENAI | D90: =SUMIFS('g-expenses-sl'!$G:$G,'g-expenses-sl'!$A:$A,D$1,'g-expenses-sl'!$D:$D,"technology",'g-expenses-sl'!$E:$E,$C90) | E90: =SUMIFS('g-expenses-sl'!$G:$G,'g-expenses-sl'!$A:$A,E$1,'g-expenses-sl'!$D:$D,"technology",'g-expenses-sl'!$E:$E,$C90) | F90: =SUMIFS('g-expenses-sl'!$G:$G,'g-expenses-sl'!$A:$A,F$1,'g-expenses-sl'!$D:$D,"technology",'g-expenses-sl'!$E:$E,$C90) | G90: =SUMIFS('g-expenses-sl'!$G:$G,'g-expenses-sl'!$A:$A,G$1,'g-expenses-sl'!$D:$D,"technology",'g-expenses-sl'!$E:$E,$C90) | H90: =SUMIFS('g-expenses-sl'!$G:$G,'g-expenses-sl'!$A:$A,H$1,'g-expenses-sl'!$D:$D,"technology",'g-expenses-sl'!$E:$E,$C90) | I90: =SUMIFS('g-expenses-sl'!$G:$G,'g-expenses-sl'!$A:$A,I$1,'g-expenses-sl'!$D:$D,"technology",'g-expenses-sl'!$E:$E,$C90) | J90: =SUMIFS('g-expenses-sl'!$G:$G,'g-expenses-sl'!$A:$A,J$1,'g-expenses-sl'!$D:$D,"technology",'g-expenses-sl'!$E:$E,$C90) | K90: =SUMIFS('g-expenses-sl'!$G:$G,'g-expenses-sl'!$A:$A,K$1,'g-expenses-sl'!$D:$D,"technology",'g-expenses-sl'!$E:$E,$C90) | ... O90: =SUMIFS('g-expenses-sl'!$G:$G,'g-expenses-sl'!$A:$A,O$1,'g-expenses-sl'!$D:$D,"technology",'g-expenses-sl'!$E:$E,$C90) | P90: =SUM(D90:O90) | Q90: ->
A91: PRODUCTHERO | C91: PRODUCTHERO | D91: =SUMIFS('g-expenses-sl'!$G:$G,'g-expenses-sl'!$A:$A,D$1,'g-expenses-sl'!$D:$D,"technology",'g-expenses-sl'!$E:$E,$C91) | E91: =SUMIFS('g-expenses-sl'!$G:$G,'g-expenses-sl'!$A:$A,E$1,'g-expenses-sl'!$D:$D,"technology",'g-expenses-sl'!$E:$E,$C91) | F91: =SUMIFS('g-expenses-sl'!$G:$G,'g-expenses-sl'!$A:$A,F$1,'g-expenses-sl'!$D:$D,"technology",'g-expenses-sl'!$E:$E,$C91) | G91: =SUMIFS('g-expenses-sl'!$G:$G,'g-expenses-sl'!$A:$A,G$1,'g-expenses-sl'!$D:$D,"technology",'g-expenses-sl'!$E:$E,$C91) | H91: =SUMIFS('g-expenses-sl'!$G:$G,'g-expenses-sl'!$A:$A,H$1,'g-expenses-sl'!$D:$D,"technology",'g-expenses-sl'!$E:$E,$C91) | I91: =SUMIFS('g-expenses-sl'!$G:$G,'g-expenses-sl'!$A:$A,I$1,'g-expenses-sl'!$D:$D,"technology",'g-expenses-sl'!$E:$E,$C91) | J91: =SUMIFS('g-expenses-sl'!$G:$G,'g-expenses-sl'!$A:$A,J$1,'g-expenses-sl'!$D:$D,"technology",'g-expenses-sl'!$E:$E,$C91) | K91: =SUMIFS('g-expenses-sl'!$G:$G,'g-expenses-sl'!$A:$A,K$1,'g-expenses-sl'!$D:$D,"technology",'g-expenses-sl'!$E:$E,$C91) | ... O91: =SUMIFS('g-expenses-sl'!$G:$G,'g-expenses-sl'!$A:$A,O$1,'g-expenses-sl'!$D:$D,"technology",'g-expenses-sl'!$E:$E,$C91) | P91: =SUM(D91:O91) | Q91: ->
A92: RAILWAY | C92: RAILWAY | D92: =SUMIFS('g-expenses-sl'!$G:$G,'g-expenses-sl'!$A:$A,D$1,'g-expenses-sl'!$D:$D,"technology",'g-expenses-sl'!$E:$E,$C92) | E92: =SUMIFS('g-expenses-sl'!$G:$G,'g-expenses-sl'!$A:$A,E$1,'g-expenses-sl'!$D:$D,"technology",'g-expenses-sl'!$E:$E,$C92) | F92: =SUMIFS('g-expenses-sl'!$G:$G,'g-expenses-sl'!$A:$A,F$1,'g-expenses-sl'!$D:$D,"technology",'g-expenses-sl'!$E:$E,$C92) | G92: =SUMIFS('g-expenses-sl'!$G:$G,'g-expenses-sl'!$A:$A,G$1,'g-expenses-sl'!$D:$D,"technology",'g-expenses-sl'!$E:$E,$C92) | H92: =SUMIFS('g-expenses-sl'!$G:$G,'g-expenses-sl'!$A:$A,H$1,'g-expenses-sl'!$D:$D,"technology",'g-expenses-sl'!$E:$E,$C92) | I92: =SUMIFS('g-expenses-sl'!$G:$G,'g-expenses-sl'!$A:$A,I$1,'g-expenses-sl'!$D:$D,"technology",'g-expenses-sl'!$E:$E,$C92) | J92: =SUMIFS('g-expenses-sl'!$G:$G,'g-expenses-sl'!$A:$A,J$1,'g-expenses-sl'!$D:$D,"technology",'g-expenses-sl'!$E:$E,$C92) | K92: =SUMIFS('g-expenses-sl'!$G:$G,'g-expenses-sl'!$A:$A,K$1,'g-expenses-sl'!$D:$D,"technology",'g-expenses-sl'!$E:$E,$C92) | ... O92: =SUMIFS('g-expenses-sl'!$G:$G,'g-expenses-sl'!$A:$A,O$1,'g-expenses-sl'!$D:$D,"technology",'g-expenses-sl'!$E:$E,$C92) | P92: =SUM(D92:O92) | Q92: ->
... A95: YUMAAI | C95: YUMAAI | D95: =SUMIFS('g-expenses-sl'!$G:$G,'g-expenses-sl'!$A:$A,D$1,'g-expenses-sl'!$D:$D,"technology",'g-expenses-sl'!$E:$E,$C95) | E95: =SUMIFS('g-expenses-sl'!$G:$G,'g-expenses-sl'!$A:$A,E$1,'g-expenses-sl'!$D:$D,"technology",'g-expenses-sl'!$E:$E,$C95) | F95: =SUMIFS('g-expenses-sl'!$G:$G,'g-expenses-sl'!$A:$A,F$1,'g-expenses-sl'!$D:$D,"technology",'g-expenses-sl'!$E:$E,$C95) | G95: =SUMIFS('g-expenses-sl'!$G:$G,'g-expenses-sl'!$A:$A,G$1,'g-expenses-sl'!$D:$D,"technology",'g-expenses-sl'!$E:$E,$C95) | H95: =SUMIFS('g-expenses-sl'!$G:$G,'g-expenses-sl'!$A:$A,H$1,'g-expenses-sl'!$D:$D,"technology",'g-expenses-sl'!$E:$E,$C95) | I95: =SUMIFS('g-expenses-sl'!$G:$G,'g-expenses-sl'!$A:$A,I$1,'g-expenses-sl'!$D:$D,"technology",'g-expenses-sl'!$E:$E,$C95) | J95: =SUMIFS('g-expenses-sl'!$G:$G,'g-expenses-sl'!$A:$A,J$1,'g-expenses-sl'!$D:$D,"technology",'g-expenses-sl'!$E:$E,$C95) | K95: =SUMIFS('g-expenses-sl'!$G:$G,'g-expenses-sl'!$A:$A,K$1,'g-expenses-sl'!$D:$D,"technology",'g-expenses-sl'!$E:$E,$C95) | ... O95: =SUMIFS('g-expenses-sl'!$G:$G,'g-expenses-sl'!$A:$A,O$1,'g-expenses-sl'!$D:$D,"technology",'g-expenses-sl'!$E:$E,$C95) | P95: =SUM(D95:O95) | Q95: ->
P96: =SUM(D96:O96)
A97: PROFIT | D97: =D4-D32-D60 | E97: =E4-E32-E60 | F97: =F4-F32-F60 | G97: =G4-G32-G60 | H97: =H4-H32-H60 | I97: =I4-I32-I60 | J97: =J4-J32-J60 | K97: =K4-K32-K60 | ... O97: =O4-O32-O60 | P97: =SUM(D97:O97)
A98: % Profit / turnover | D98: =IFERROR(D97/D4,0) | E98: =IFERROR(E97/E4,0) | F98: =IFERROR(F97/F4,0) | G98: =IFERROR(G97/G4,0) | H98: =IFERROR(H97/H4,0) | I98: =IFERROR(I97/I4,0) | J98: =IFERROR(J97/J4,0) | K98: =IFERROR(K97/K4,0) | ... O98: =IFERROR(O97/O4,0) | P98: =SUM(D98:O98)

Sheet params
A1: <- Volver a P&G-SL
A2: key | B2: value
A3: entity | B3: SL
A4: year | B4: 2026
A5: generated_at_utc | B5: 2026-03-23T02:04:05Z

Sheet i-shopify-sl
A1: <- Volver a P&G-SL
A2: yyyymm | B2: entity | C2: line_item | D2: detail | E2: amount_net | F2: currency | G2: source
A3: 202601 | B3: SL | C3: AT | D3: AT | E3: 5482.24 | F3: EUR | G3: finance.ventas_pyg
A4: 202601 | B4: SL | C4: BE | D4: BE | E4: 422.71 | F4: EUR | G4: finance.ventas_pyg
A5: 202601 | B5: SL | C5: DE | D5: DE | E5: 20924.16 | F5: EUR | G5: finance.ventas_pyg
A6: 202601 | B6: SL | C6: ES | D6: ES | E6: 61194.44 | F6: EUR | G6: finance.ventas_pyg
A7: 202601 | B7: SL | C7: FR | D7: FR | E7: 25590.35 | F7: EUR | G7: finance.ventas_pyg
A8: 202601 | B8: SL | C8: IT | D8: IT | E8: 18483.79 | F8: EUR | G8: finance.ventas_pyg
A9: 202601 | B9: SL | C9: NL | D9: NL | E9: 115.58 | F9: EUR | G9: finance.ventas_pyg
A10: 202601 | B10: SL | C10: PT | D10: PT | E10: 729.31 | F10: EUR | G10: finance.ventas_pyg
A11: 202601 | B11: SL | C11: XX | D11: XX | E11: 691.19 | F11: EUR | G11: finance.ventas_pyg
A12: 202602 | B12: SL | C12: AT | D12: AT | E12: 6077.94 | F12: EUR | G12: finance.ventas_pyg
A13: 202602 | B13: SL | C13: BE | D13: BE | E13: 998.68 | F13: EUR | G13: finance.ventas_pyg
A14: 202602 | B14: SL | C14: DE | D14: DE | E14: 19361.46 | F14: EUR | G14: finance.ventas_pyg
... A28: 202603 | B28: SL | C28: XX | D28: XX | E28: 227.22 | F28: EUR | G28: finance.ventas_pyg

Sheet i-marketplaces-sl
A1: <- Volver a P&G-SL
A2: yyyymm | B2: entity | C2: line_item | D2: detail | E2: amount_net | F2: currency | G2: source
A3: 202601 | B3: SL | C3: HANNUN | D3: orders | E3: 1419.7 | F3: EUR | G3: documents
A4: 202602 | B4: SL | C4: HANNUN | D4: orders | E4: 1128.42 | F4: EUR | G4: documents
A5: 202602 | B5: SL | C5: TOASTY | D5: b2b_partner | E5: 1746.6 | F5: EUR | G5: documents
A6: 202603 | B6: SL | C6: CHOOSE | D6: campaign | E6: 15609.96 | F6: EUR | G6: documents

Sheet i-rappels-sl
A1: <- Volver a P&G-SL
A2: yyyymm | B2: entity | C2: line_item | D2: detail | E2: amount_net | F2: currency | G2: source
A3: 202601 | B3: SL | C3: LIVITUM | D3: rappels | E3: -1118.95 | F3: EUR | G3: documents

Sheet i-supplies-sl
A1: <- Volver a P&G-SL
A2: yyyymm | B2: entity | C2: line_item | D2: detail | E2: amount_net | F2: currency | G2: source
A3: 202601 | B3: SL | C3: REVER | D3: supplied_note | E3: -2176.46 | F3: EUR | G3: documents
A4: 202602 | B4: SL | C4: REVER | D4: supplied_note | E4: -522.54 | F4: EUR | G4: documents

Sheet i-services-sl
A1: <- Volver a P&G-SL
A2: yyyymm | B2: entity | C2: line_item | D2: detail | E2: amount_net | F2: currency | G2: source
A3: 202601 | B3: SL | C3: HANNUN | D3: renting_cnc | E3: 1661.16 | F3: EUR | G3: documents
A4: 202601 | B4: SL | C4: HANNUN | D4: staff | E4: 1191.18 | F4: EUR | G4: documents
A5: 202601 | B5: SL | C5: Inc | D5: shared_services | E5: 7334.44 | F5: EUR | G5: documents:shared_services
A6: 202601 | B6: SL | C6: Ltd | D6: shared_services | E6: 10732.87 | F6: EUR | G6: documents:shared_services
A7: 202602 | B7: SL | C7: HANNUN | D7: staff | E7: 1191.18 | F7: EUR | G7: documents
A8: 202602 | B8: SL | C8: Inc | D8: shared_services | E8: 8462.36 | F8: EUR | G8: documents:shared_services
A9: 202602 | B9: SL | C9: Ltd | D9: shared_services | E9: 13068.98 | F9: EUR | G9: documents:shared_services
A10: 202602 | B10: SL | C10: QHANDS | D10: renting_cnc | E10: 1661.16 | F10: EUR | G10: documents

Sheet g-expenses-sl
A1: <- Volver a P&G-SL
A2: yyyymm | B2: entity | C2: category | D2: subcategory | E2: supplier_code | F2: detail | G2: amount_net | H2: currency | I2: source
A3: 202601 | B3: SL | C3: opex | D3: technology | E3: ADOBE | G3: 33.49 | H3: EUR | I3: documents
A4: 202601 | B4: SL | C4: cogs | D4: manufacturing | E4: APPHOTOCAN | G4: 29.22 | H4: EUR | I4: documents
A5: 202601 | B5: SL | C5: cogs | D5: manufacturing | E5: APPHOTOES | G5: 17898.08 | H5: EUR | I5: documents
A6: 202601 | B6: SL | C6: opex | D6: technology | E6: CANVA | G6: 9.91 | H6: EUR | I6: documents
A7: 202601 | B7: SL | C7: opex | D7: administration | E7: CLARIS | G7: 808.08 | H7: EUR | I7: documents
A8: 202601 | B8: SL | C8: cogs | D8: logistics | E8: CORREOS | G8: 553.76 | H8: EUR | I8: documents
A9: 202601 | B9: SL | C9: cogs | D9: manufacturing | E9: DCT | G9: 9730.11 | H9: EUR | I9: documents
A10: 202601 | B10: SL | C10: cogs | D10: logistics | E10: GLS | G10: 12319.26 | H10: EUR | I10: documents
A11: 202601 | B11: SL | C11: opex | D11: technology | E11: GODADDY | G11: 34.23 | H11: EUR | I11: documents
A12: 202601 | B12: SL | C12: opex | D12: marketing | E12: GOOGLEADS | F12: eu | G12: 24746.34 | H12: EUR | I12: documents
A13: 202601 | B13: SL | C13: opex | D13: marketing | E13: GOOGLEADS | F13: uk | G13: 2298.67 | H13: EUR | I13: documents
A14: 202601 | B14: SL | C14: opex | D14: marketing | E14: GOOGLEADS | F14: us | G14: 2119.05 | H14: EUR | I14: documents
A15: 202601 | B15: SL | C15: opex | D15: technology | E15: GOOGLEWORKSPACE | G15: 194.4 | H15: EUR | I15: documents
A16: 202601 | B16: SL | C16: opex | D16: technology | E16: GORGIAS | G16: 201.2 | H16: USD | I16: documents
A17: 202601 | B17: SL | C17: opex | D17: technology | E17: HETZNER | G17: 10.9 | H17: EUR | I17: documents
A18: 202601 | B18: SL | C18: opex | D18: technology | E18: KONVOAI | G18: 453.89 | H18: EUR | I18: documents
A19: 202601 | B19: SL | C19: opex | D19: technology | E19: MASMOVIL | G19: 5 | H19: EUR | I19: documents
A20: 202601 | B20: SL | C20: opex | D20: marketing | E20: METAADS | F20: eu | G20: 20319.32 | H20: EUR | I20: documents
A21: 202601 | B21: SL | C21: opex | D21: marketing | E21: METAADS | F21: uk | G21: 3385.46 | H21: EUR | I21: documents
A22: 202601 | B22: SL | C22: opex | D22: marketing | E22: METAADS | F22: us | G22: 1779.68 | H22: EUR | I22: documents
A23: 202601 | B23: SL | C23: opex | D23: technology | E23: MICROSOFT | G23: 30.87 | H23: EUR | I23: documents
A24: 202601 | B24: SL | C24: opex | D24: technology | E24: OPENAI | F24: api_usage | G24: 10 | H24: USD | I24: documents
A25: 202601 | B25: SL | C25: opex | D25: technology | E25: OPENAI | F25: chatgpt_plus | G25: 19.01 | H25: EUR | I25: documents
A26: 202601 | B26: SL | C26: cogs | D26: manufacturing | E26: PRESSING | G26: 28979.31 | H26: EUR | I26: documents
A27: 202601 | B27: SL | C27: opex | D27: technology | E27: PRODUCTHERO | G27: 134 | H27: EUR | I27: documents
A28: 202601 | B28: SL | C28: opex | D28: technology | E28: REVER | G28: 513.8 | H28: EUR | I28: documents
A29: 202601 | B29: SL | C29: opex | D29: technology | E29: SHOPIFY | G29: 2674.4 | H29: USD | I29: documents
A30: 202601 | B30: SL | C30: cogs | D30: logistics | E30: SPRINGGDS | G30: 3.3 | H30: EUR | I30: documents
A31: 202601 | B31: SL | C31: opex | D31: administration | E31: TORRAS | G31: 15 | H31: EUR | I31: documents
A32: 202601 | B32: SL | C32: cogs | D32: logistics | E32: UPS | G32: 4305.55 | H32: EUR | I32: documents
A33: 202601 | B33: SL | C33: opex | D33: technology | E33: YUMAAI | G33: 507.2 | H33: EUR | I33: documents
A34: 202602 | B34: SL | C34: opex | D34: technology | E34: ADOBE | G34: 33.49 | H34: EUR | I34: documents
A35: 202602 | B35: SL | C35: cogs | D35: manufacturing | E35: APPHOTOCAN | G35: 59.84 | H35: EUR | I35: documents
A36: 202602 | B36: SL | C36: cogs | D36: manufacturing | E36: APPHOTOES | G36: 22987.13 | H36: EUR | I36: documents
A37: 202602 | B37: SL | C37: opex | D37: technology | E37: CANVA | G37: 9.91 | H37: EUR | I37: documents
... A42: 202602 | B42: SL | C42: cogs | D42: logistics | E42: GLS | G42: 15947.02 | H42: EUR | I42: documents
A43: 202602 | B43: SL | C43: opex | D43: marketing | E43: GOOGLEADS | F43: eu | G43: 19199.14 | H43: EUR | I43: documents
A44: 202602 | B44: SL | C44: opex | D44: marketing | E44: GOOGLEADS | F44: uk | G44: 5006.17 | H44: EUR | I44: documents
A45: 202602 | B45: SL | C45: opex | D45: marketing | E45: GOOGLEADS | F45: us | G45: 3345.8 | H45: EUR | I45: documents
A46: 202602 | B46: SL | C46: opex | D46: technology | E46: GOOGLEWORKSPACE | G46: 201.91 | H46: EUR | I46: documents
A47: 202602 | B47: SL | C47: opex | D47: technology | E47: GORGIAS | G47: 120 | H47: USD | I47: documents
A48: 202602 | B48: SL | C48: opex | D48: administration | E48: HANNUN | F48: administration | G48: 43192.69 | H48: EUR | I48: documents
A49: 202602 | B49: SL | C49: opex | D49: administration | E49: HANNUN | F49: office | G49: 350 | H49: EUR | I49: documents
A50: 202602 | B50: SL | C50: opex | D50: administration | E50: HANNUN | F50: services | G50: 3009.84 | H50: EUR | I50: documents
A51: 202602 | B51: SL | C51: opex | D51: technology | E51: HETZNER | G51: 10.9 | H51: EUR | I51: documents
A52: 202602 | B52: SL | C52: opex | D52: technology | E52: KONVOAI | G52: 475.96 | H52: EUR | I52: documents
A53: 202602 | B53: SL | C53: opex | D53: technology | E53: MASMOVIL | G53: 5 | H53: EUR | I53: documents
A54: 202602 | B54: SL | C54: opex | D54: marketing | E54: METAADS | F54: eu | G54: 15883.55 | H54: EUR | I54: documents
A55: 202602 | B55: SL | C55: opex | D55: marketing | E55: METAADS | F55: uk | G55: 2794.04 | H55: EUR | I55: documents
A56: 202602 | B56: SL | C56: opex | D56: marketing | E56: METAADS | F56: us | G56: 1397.4 | H56: EUR | I56: documents
A57: 202602 | B57: SL | C57: opex | D57: technology | E57: MICROSOFT | G57: 30.87 | H57: EUR | I57: documents
A58: 202602 | B58: SL | C58: opex | D58: technology | E58: OPENAI | F58: api_usage | G58: 60.72 | H58: USD | I58: documents
A59: 202602 | B59: SL | C59: opex | D59: technology | E59: OPENAI | F59: receipt | G59: 10.13 | H59: USD | I59: documents
A60: 202602 | B60: SL | C60: cogs | D60: manufacturing | E60: PRESSING | G60: 33510.62 | H60: EUR | I60: documents
A61: 202602 | B61: SL | C61: opex | D61: technology | E61: PRODUCTHERO | G61: 134 | H61: EUR | I61: documents
A62: 202602 | B62: SL | C62: opex | D62: technology | E62: REVER | G62: 79 | H62: EUR | I62: documents
A63: 202602 | B63: SL | C63: opex | D63: technology | E63: SHOPIFY | G63: 2812.25 | H63: USD | I63: documents
A64: 202602 | B64: SL | C64: opex | D64: administration | E64: TORRAS | G64: 15 | H64: EUR | I64: documents
A65: 202602 | B65: SL | C65: cogs | D65: logistics | E65: UPS | G65: 1826.49 | H65: EUR | I65: documents
A66: 202602 | B66: SL | C66: opex | D66: technology | E66: YUMAAI | G66: 440 | H66: EUR | I66: documents
A67: 202603 | B67: SL | C67: cogs | D67: manufacturing | E67: APPHOTOES | G67: 11609.31 | H67: EUR | I67: documents
A68: 202603 | B68: SL | C68: cogs | D68: manufacturing | E68: ARTLINK | F68: manufacturing | G68: 570 | H68: EUR | I68: documents
A69: 202603 | B69: SL | C69: opex | D69: administration | E69: CLARIS | G69: 808.08 | H69: EUR | I69: documents
A70: 202603 | B70: SL | C70: cogs | D70: manufacturing | E70: DCT | G70: 2646.66 | H70: EUR | I70: documents
A71: 202603 | B71: SL | C71: opex | D71: technology | E71: GORGIAS | G71: 126.4 | H71: USD | I71: documents
A72: 202603 | B72: SL | C72: opex | D72: administration | E72: HANNUN | F72: administration | G72: 30 | H72: EUR | I72: documents
A73: 202603 | B73: SL | C73: opex | D73: technology | E73: OPENAI | F73: api_usage | G73: 15 | H73: USD | I73: documents
A74: 202603 | B74: SL | C74: opex | D74: technology | E74: RAILWAY | G74: 21.36 | H74: USD | I74: documents
A75: 202603 | B75: SL | C75: opex | D75: administration | E75: TORRAS | G75: 15 | H75: EUR | I75: documents
A76: 202603 | B76: SL | C76: opex | D76: administration | E76: VITALY | G76: 369 | H76: EUR | I76: documents
A77: 202603 | B77: SL | C77: opex | D77: technology | E77: YUMAAI | G77: 440 | H77: EUR | I77: documents
A78: 202601 | B78: SL | C78: cogs | D78: royalties | E78: ROYALTIES | G78: 13737 | H78: EUR | I78: artist_royalties_monthly_summary
A79: 202602 | B79: SL | C79: cogs | D79: royalties | E79: ROYALTIES | G79: 16662 | H79: EUR | I79: artist_royalties_monthly_summary
A80: 202601 | B80: SL | C80: opex | D80: staff | E80: PAYROLL | G80: 14731.84 | H80: EUR | I80: payroll_documents
A81: 202602 | B81: SL | C81: opex | D81: staff | E81: PAYROLL | G81: 14915.68 | H81: EUR | I81: payroll_documents

Sheet g-payment-fees-sl
A1: <- Volver a P&G-SL
A2: yyyymm | B2: entity | C2: supplier_code | D2: amount_net | E2: currency | F2: source
A3: 202601 | B3: SL | C3: SHOPIFY | D3: 2616.7 | E3: EUR | F3: payment_fee_monthly_summary
A4: 202602 | B4: SL | C4: SHOPIFY | D4: 2778.19 | E4: EUR | F4: payment_fee_monthly_summary
A5: 202603 | B5: SL | C5: SHOPIFY | D5: 2014.7 | E5: EUR | F5: payment_fee_monthly_summary

Sheet catalog-sl
A1: <- Volver a P&G-SL
A2: supplier_code | B2: supplier_name | C2: current_folder | D2: destination_path | E2: notes
A3: CORREOS | B3: CORREOS | C3: Correos | D3: expenses/cogs/logistics | E3: Peninsula/Baleares 21% IVA
A4: CORREOSCAN | B4: CORREOSCAN | C4: Correos | D4: expenses/cogs/logistics | E4: Canarias 7% IGIC
A5: GLS | B5: GLS | C5: GLS | D5: expenses/cogs/logistics | E5: OCR-based GLS parser via scanned PDF
A6: SPRINGGDS | B6: SPRINGGDS | C6: SPRING | D6: expenses/cogs/logistics | E6: Spring operating brand
A7: UPS | B7: UPS | C7: UPS | D7: expenses/cogs/logistics
A8: APPHOTOCAN | B8: APPHOTOCAN | C8: AP Photo | D8: expenses/cogs/manufacturing | E8: IGIC 7%
A9: APPHOTOES | B9: APPHOTOES | C9: AP Photo | D9: expenses/cogs/manufacturing
A10: ARTLINK | B10: ARTLINK | C10: Artlink | D10: expenses/cogs/manufacturing | E10: Frame purchases and related freight are treated as manufacturing
A11: DCT | B11: DCT | C11: DCT | D11: expenses/cogs/manufacturing
A12: PRESSING | B12: PRESSING | C12: Pressing | D12: expenses/cogs/manufacturing
A13: ROYALTIES | B13: ROYALTIES | C13: Artistas | D13: expenses/cogs/royalties | E13: Artist royalties received and issued by Artesta
A14: CLARIS | B14: CLARIS | C14: CLARIS | D14: expenses/opex/administration
A15: HANNUN | B15: HANNUN | C15: HANNUN | D15: expenses/opex/administration | E15: Bidirectional HANNUN relationship; incoming expense invoices and outgoing customer invoices
A16: NODA | B16: NODA | C16: NODA Asesores | D16: expenses/opex/administration
A17: TORRAS | B17: TORRAS | C17: TORRAS | D17: expenses/opex/administration
A18: VITALY | B18: VITALY | C18: Vitaly | D18: expenses/opex/administration | E18: Annual prevention and occupational health service
A19: GOOGLEADS | B19: GOOGLEADS | C19: Google | D19: expenses/opex/marketing
A20: METAADS | B20: METAADS | C20: Meta | D20: expenses/opex/marketing
A21: DOSCONSULTING | B21: DOSCONSULTING | C21: Nóminas | D21: expenses/opex/staff | E21: Monthly payroll management for SL
A22: ADOBE | B22: ADOBE | C22: ADOBE | D22: expenses/opex/technology
A23: CANVA | B23: CANVA | C23: canva | D23: expenses/opex/technology
A24: GODADDY | B24: GODADDY | C24: godaddy | D24: expenses/opex/technology
A25: GOOGLEWORKSPACE | B25: GOOGLEWORKSPACE | C25: Google | D25: expenses/opex/technology
A26: GORGIAS | B26: GORGIAS | C26: Gorgias | D26: expenses/opex/technology
A27: HETZNER | B27: HETZNER | C27: HETZNER | D27: expenses/opex/technology
A28: KONVOAI | B28: KONVOAI | C28: konvo | D28: expenses/opex/technology
A29: MASMOVIL | B29: MASMOVIL | C29: mas movil | D29: expenses/opex/technology
A30: MICROSOFT | B30: MICROSOFT | C30: MICROSOFT | D30: expenses/opex/technology
A31: OPENAI | B31: OPENAI | C31: chatgpt | D31: expenses/opex/technology | E31: Groups ChatGPT and API
A32: PRODUCTHERO | B32: PRODUCTHERO | C32: ProductHERO | D32: expenses/opex/technology
A33: RAILWAY | B33: RAILWAY | C33: RAILWAY | D33: expenses/opex/technology
A34: REVER | B34: REVER | C34: REVER | D34: expenses/opex/technology
A35: SHOPIFY | B35: SHOPIFY | C35: Shopify | D35: expenses/opex/technology
A36: YUMAAI | B36: YUMAAI | C36: YUMA | D36: expenses/opex/technology
A37: LIVITUM | B37: LIVITUM | C37: 709. Rappels | D37: income/other_income/rappels | E37: Rappel issued to Livitum
A38: CHOOSE | B38: CHOOSE | C38: CHOOSE | D38: income/sales/marketplaces | E38: Outgoing partner invoice
A39: TOASTY | B39: TOASTY | C39: TOASTY | D39: income/sales/marketplaces | E39: Outgoing partner invoice
A40: QHANDS | B40: QHANDS | C40: QHANDS | D40: income/shared-services | E40: Outgoing CNC rental invoice
