Workbook

Sheet Shopify_Payouts
A1: Transaction Date | B1: Type | C1: Order | D1: Card Brand | E1: Card Source | F1: Payout Status | G1: Payout Date | H1: Payout ID | I1: Available On | J1: Amount | K1: Fee | L1: Net | M1: Checkout | N1: Payment Method Name | O1: Presentment Amount | P1: Presentment Currency | Q1: Currency | R1: VAT | S1: Business Entity Name | T1: Business Entity ID
A2: 2026-01-31 22:33:19 +0100 | B2: charge | C2: AS-97246 | D2: master | E2: online | F2: paid | G2: 46057 | H2: 143913648466 | I2: 46057 | J2: 99.75 | K2: 1.6 | L2: 98.15 | M2: #47512490475858 | N2: card | O2: 99.75 | P2: EUR | Q2: EUR | R2: 0.00 | S2: Artesta Store SL | T2: MTc1MTkyNzM0Nw
A3: 2026-01-31 21:56:43 +0100 | B3: charge | C3: AS-97244 | D3: master | E3: online | F3: paid | G3: 46057 | H3: 143913648466 | I3: 46057 | J3: 67.95 | K3: 1.18 | L3: 66.77 | M3: #47512368644434 | N3: card | O3: 67.95 | P3: EUR | Q3: EUR | R3: 0.00 | S3: Artesta Store SL | T3: MTc1MTkyNzM0Nw
A4: 2026-01-31 21:49:01 +0100 | B4: charge | C4: AS-97243 | D4: visa | E4: online | F4: paid | G4: 46057 | H4: 143913648466 | I4: 46057 | J4: 85.9 | K4: 1.42 | L4: 84.48 | M4: #47512345215314 | N4: card | O4: 85.9 | P4: EUR | Q4: EUR | R4: 0.00 | S4: Artesta Store SL | T4: MTc1MTkyNzM0Nw
A5: 2026-01-31 21:16:23 +0100 | B5: charge | C5: AS-97240 | D5: master | E5: online | F5: paid | G5: 46057 | H5: 143913648466 | I5: 46057 | J5: 134.91 | K5: 2.05 | L5: 132.86 | M5: #47512226595154 | N5: card | O5: 134.91 | P5: EUR | Q5: EUR | R5: 0.00 | S5: Artesta Store SL | T5: MTc1MTkyNzM0Nw
A6: 2026-01-31 21:07:51 +0100 | B6: charge | C6: AS-97239 | D6: master | E6: online | F6: paid | G6: 46057 | H6: 143913648466 | I6: 46057 | J6: 38.87 | K6: 0.81 | L6: 38.06 | M6: #47512161616210 | N6: card | O6: 38.87 | P6: EUR | Q6: EUR | R6: 0.00 | S6: Artesta Store SL | T6: MTc1MTkyNzM0Nw
A7: 2026-01-31 21:05:59 +0100 | B7: charge | C7: AS-97238 | D7: master | E7: online | F7: paid | G7: 46057 | H7: 143913648466 | I7: 46057 | J7: 71.82 | K7: 1.23 | L7: 70.59 | M7: #47512196120914 | N7: card | O7: 71.82 | P7: EUR | Q7: EUR | R7: 0.00 | S7: Artesta Store SL | T7: MTc1MTkyNzM0Nw
A8: 2026-01-31 20:58:40 +0100 | B8: charge | C8: AS-97237 | D8: master | E8: online | F8: paid | G8: 46057 | H8: 143913648466 | I8: 46057 | J8: 67.95 | K8: 1.18 | L8: 66.77 | M8: #47512157749586 | N8: card | O8: 67.95 | P8: EUR | Q8: EUR | R8: 0.00 | S8: Artesta Store SL | T8: MTc1MTkyNzM0Nw
A9: 2026-01-31 20:00:07 +0100 | B9: charge | C9: AS-97234 | D9: master | E9: online | F9: paid | G9: 46057 | H9: 143913648466 | I9: 46057 | J9: 53.46 | K9: 0.99 | L9: 52.47 | M9: #47511953637714 | N9: card | O9: 53.46 | P9: EUR | Q9: EUR | R9: 0.00 | S9: Artesta Store SL | T9: MTc1MTkyNzM0Nw
A10: 2026-01-31 19:49:08 +0100 | B10: refund | C10: AS-97232 | D10: unknown | E10: online | F10: paid | G10: 46057 | H10: 143913648466 | I10: 46057 | J10: -49.9 | K10: 0 | L10: -49.9 | M10: #47511787929938 | N10: klarna | O10: 49.9 | P10: EUR | Q10: EUR | R10: 0.00 | S10: Artesta Store SL | T10: MTc1MTkyNzM0Nw
A11: 2026-01-31 19:45:50 +0100 | B11: charge | C11: AS-97233 | D11: unknown | E11: online | F11: paid | G11: 46057 | H11: 143913648466 | I11: 46057 | J11: 71.9 | K11: 3.94 | L11: 67.96 | M11: #47511906058578 | N11: klarna | O11: 71.9 | P11: EUR | Q11: EUR | R11: 0.00 | S11: Artesta Store SL | T11: MTc1MTkyNzM0Nw
A12: 2026-01-31 19:44:03 +0100 | B12: charge | C12: AS-97232 | D12: unknown | E12: online | F12: paid | G12: 46057 | H12: 143913648466 | I12: 46057 | J12: 49.9 | K12: 2.84 | L12: 47.06 | M12: #47511787929938 | N12: klarna | O12: 49.9 | P12: EUR | Q12: EUR | R12: 0.00 | S12: Artesta Store SL | T12: MTc1MTkyNzM0Nw
A13: 2026-01-31 19:14:51 +0100 | B13: charge | C13: AS-97229 | D13: visa | E13: online | F13: paid | G13: 46057 | H13: 143913648466 | I13: 46057 | J13: 80.85 | K13: 1.35 | L13: 79.5 | M13: #47511744381266 | N13: card | O13: 80.85 | P13: EUR | Q13: EUR | R13: 0.00 | S13: Artesta Store SL | T13: MTc1MTkyNzM0Nw
... A1531: 2026-01-01 01:13:05 +0100 | B1531: charge | C1531: AS-94794 | D1531: unknown | E1531: online | F1531: paid | G1531: 46028 | H1531: 142240285010 | I1531: 46028 | J1531: 114.95 | K1531: 6.09 | L1531: 108.86 | M1531: #47371590631762 | N1531: klarna | O1531: 114.95 | P1531: EUR | Q1531: EUR | R1531: 0.00 | S1531: Artesta Store SL | T1531: MTc1MTkyNzM0Nw

Sheet Sales_Shopify
A1: order_month_yyyymm | B1: order_name | C1: shipping_country_code | D1: shipping_state_code | E1: payment_gateway_names | F1: is_rever_tag | G1: is_hannun_tag | H1: is_mirakl_tag | I1: standard_rate | J1: payment_currency | K1: tax_rate | L1: shown_tax_presentment | M1: shown_gross_presentment | N1: shown_net_presentment | O1: tags | P1: descuadre | Q1: tax_rate_calculado
A2: 202601 | B2: AS-94795 | C2: DE | E2: ['paypal'] | F2: 0 | G2: 0 | H2: 0 | I2: 0.19 | J2: EUR | K2: 0.19 | L2: 6.05 | M2: 37.9 | N2: 31.85 | P2: 0 | Q2: 0.19
A3: 202601 | B3: AS-94797 | C3: ES | E3: ['shopify_payments'] | F3: 0 | G3: 0 | H3: 0 | I3: 0.21 | J3: EUR | K3: 0.21 | L3: 17.35 | M3: 99.95 | N3: 82.6 | P3: 0 | Q3: 0.21
A4: 202601 | B4: AS-94798 | C4: ES | E4: ['shopify_payments'] | F4: 0 | G4: 0 | H4: 0 | I4: 0.21 | J4: EUR | K4: 0.21 | L4: 9.28 | M4: 53.46 | N4: 44.18 | P4: 0 | Q4: 0.21
A5: 202601 | B5: AS-94799 | C5: DE | E5: ['paypal'] | F5: 0 | G5: 0 | H5: 0 | I5: 0.19 | J5: EUR | K5: 0.19 | L5: 2.86 | M5: 17.9 | N5: 15.04 | P5: 0 | Q5: 0.19
A6: 202601 | B6: AS-94800 | C6: ES | E6: ['shopify_payments'] | F6: 0 | G6: 0 | H6: 0 | I6: 0.21 | J6: EUR | K6: 0.21 | L6: 67.91 | M6: 391.32 | N6: 323.41 | P6: 0 | Q6: 0.21
A7: 202601 | B7: AS-94801 | C7: ES | E7: ['shopify_payments'] | F7: 0 | G7: 0 | H7: 0 | I7: 0.21 | J7: EUR | K7: 0.21 | L7: 9.36 | M7: 53.91 | N7: 44.55 | P7: 0 | Q7: 0.21
A8: 202601 | B8: AS-94802 | C8: FR | E8: ['shopify_payments'] | F8: 0 | G8: 0 | H8: 0 | I8: 0.2 | J8: EUR | K8: 0.2 | L8: 9.89 | M8: 59.31 | N8: 49.42 | P8: 0 | Q8: 0.2
A9: 202601 | B9: AS-94806 | C9: DE | E9: ['paypal'] | F9: 0 | G9: 0 | H9: 0 | I9: 0.19 | J9: EUR | K9: 0.19 | L9: 13.68 | M9: 85.7 | N9: 72.02 | P9: 0 | Q9: 0.19
A10: 202601 | B10: AS-94807 | C10: ES | E10: ['shopify_payments'] | F10: 0 | G10: 0 | H10: 0 | I10: 0.21 | J10: EUR | K10: 0.21 | L10: 7.78 | M10: 44.85 | N10: 37.07 | P10: 0 | Q10: 0.21
A11: 202601 | B11: AS-94808 | C11: IT | E11: ['paypal'] | F11: 0 | G11: 0 | H11: 0 | I11: 0.22 | J11: EUR | K11: 0.22 | L11: 7.19 | M11: 39.9 | N11: 32.71 | P11: 0 | Q11: 0.22
A12: 202601 | B12: AS-94809 | C12: DE | E12: ['paypal'] | F12: 0 | G12: 0 | H12: 0 | I12: 0.19 | J12: EUR | K12: 0.19 | L12: 6.05 | M12: 37.9 | N12: 31.85 | P12: 0 | Q12: 0.19
A13: 202601 | B13: AS-94810 | C13: AT | E13: ['shopify_payments'] | F13: 0 | G13: 0 | H13: 0 | I13: 0.2 | J13: EUR | K13: 0.2 | L13: 13.49 | M13: 80.91 | N13: 67.42 | P13: 0 | Q13: 0.2
... A43: 202601 | B43: AS-94847 | C43: DE | E43: ['paypal'] | F43: 0 | G43: 0 | H43: 0 | I43: 0.19 | J43: EUR | K43: 0.19 | L43: 6.05 | M43: 37.9 | N43: 31.85 | P43: 0 | Q43: 0.19
A44: 202601 | B44: AS-94803 | C44: ES | E44: ['shopify_payments'] | F44: 0 | G44: 0 | H44: 0 | I44: 0.21 | J44: EUR | K44: 0 | L44: 0 | M44: 0 | N44: 0 | O44: cancel-, customer-edit | P44: 0 | Q44: 0
A45: 202601 | B45: AS-94804 | C45: ES | E45: ['shopify_payments'] | F45: 0 | G45: 0 | H45: 0 | I45: 0.21 | J45: EUR | K45: 0.21 | L45: 3.63 | M45: 20.93 | N45: 17.3 | P45: 0 | Q45: 0.21
A46: 202601 | B46: AS-94796 | C46: DE | E46: ['paypal'] | F46: 0 | G46: 0 | H46: 0 | I46: 0.19 | J46: EUR | K46: 0.19 | L46: 0.8 | M46: 4.95 | N46: 4.15 | O46: Claim, Return | P46: 0 | Q46: 0.19
A47: 202601 | B47: AS-94794 | C47: DE | E47: ['shopify_payments'] | F47: 0 | G47: 0 | H47: 0 | I47: 0.19 | J47: EUR | K47: 0 | L47: 0 | M47: 0 | N47: 0 | O47: Claim, Return | P47: 0 | Q47: 0
A48: 202601 | B48: AS-88270 | C48: IT | E48: ['shopify_payments'] | F48: 0 | G48: 0 | H48: 0 | I48: 0.22 | J48: EUR | K48: 0.22 | L48: -13.33 | M48: -73.92 | N48: -60.59 | P48: 0 | Q48: 0.22
A49: 202601 | B49: AS-91995 | C49: ES | E49: ['shopify_payments'] | F49: 1 | G49: 0 | H49: 0 | I49: 0.21 | J49: EUR | K49: 0.21 | L49: -31.18 | M49: -179.64 | N49: -148.46 | O49: REVER returns | P49: 0 | Q49: 0.21
A50: 202601 | B50: AS-94849 | C50: IT | E50: ['shopify_payments'] | F50: 0 | G50: 0 | H50: 0 | I50: 0.22 | J50: EUR | K50: 0.22 | L50: 24.79 | M50: 137.48 | N50: 112.69 | P50: 0 | Q50: 0.22
A51: 202601 | B51: AS-94850 | C51: ES | E51: [] | F51: 0 | G51: 1 | H51: 0 | I51: 0.21 | J51: EUR | K51: 0 | L51: 6.51 | M51: 37.52 | N51: 31.01 | O51: Hannun | P51: 0 | Q51: 0.21
A52: 202601 | B52: AS-94851 | C52: ES | E52: ['shopify_payments'] | F52: 0 | G52: 0 | H52: 0 | I52: 0.21 | J52: EUR | K52: 0.21 | L52: 11.79 | M52: 67.95 | N52: 56.16 | P52: 0 | Q52: 0.21
A53: 202601 | B53: AS-94852 | C53: DE | E53: ['paypal'] | F53: 0 | G53: 0 | H53: 0 | I53: 0.19 | J53: EUR | K53: 0.19 | L53: 3.98 | M53: 24.9 | N53: 20.92 | P53: 0 | Q53: 0.19
A54: 202601 | B54: AS-94854 | C54: IT | E54: [] | F54: 0 | G54: 0 | H54: 0 | I54: 0.22 | J54: EUR | K54: 0 | L54: 0 | M54: 0 | N54: 0 | O54: Claim, GLS, Logistics | P54: 0 | Q54: 0
A55: 202601 | B55: AS-94855 | C55: ES | E55: ['shopify_payments'] | F55: 0 | G55: 0 | H55: 0 | I55: 0.21 | J55: EUR | K55: 0.21 | L55: 6.58 | M55: 37.9 | N55: 31.32 | P55: 0 | Q55: 0.21
A56: 202601 | B56: AS-94856 | C56: DE | E56: ['paypal'] | F56: 0 | G56: 0 | H56: 0 | I56: 0.19 | J56: EUR | K56: 0.19 | L56: 10.2 | M56: 63.9 | N56: 53.7 | P56: 0 | Q56: 0.19
A57: 202601 | B57: AS-94858 | C57: ES | E57: ['shopify_payments'] | F57: 0 | G57: 0 | H57: 0 | I57: 0.21 | J57: EUR | K57: 0.21 | L57: 17.35 | M57: 99.95 | N57: 82.6 | P57: 0 | Q57: 0.21
A58: 202601 | B58: AS-94859 | C58: IT | E58: ['shopify_payments'] | F58: 0 | G58: 0 | H58: 0 | I58: 0.22 | J58: EUR | K58: 0.22 | L58: 11.02 | M58: 61.11 | N58: 50.09 | P58: 0 | Q58: 0.22
A59: 202601 | B59: AS-94860 | C59: DE | E59: ['paypal'] | F59: 0 | G59: 0 | H59: 0 | I59: 0.19 | J59: EUR | K59: 0.19 | L59: 16.27 | M59: 101.9 | N59: 85.63 | P59: 0 | Q59: 0.19
A60: 202601 | B60: AS-94861 | C60: FR | E60: ['shopify_payments'] | F60: 0 | G60: 0 | H60: 0 | I60: 0.2 | J60: EUR | K60: 0.2 | L60: 19.16 | M60: 114.95 | N60: 95.79 | P60: 0 | Q60: 0.2
A61: 202601 | B61: AS-94862 | C61: ES | E61: [] | F61: 0 | G61: 0 | H61: 0 | I61: 0.21 | J61: EUR | K61: 0 | L61: 0 | M61: 0 | N61: 0 | O61: Claim, GLS, Logistics | P61: 0 | Q61: 0
A62: 202601 | B62: AS-94863 | C62: DE | E62: ['shopify_payments'] | F62: 0 | G62: 0 | H62: 0 | I62: 0.19 | J62: EUR | K62: 0.19 | L62: 12.76 | M62: 79.9 | N62: 67.14 | P62: 0 | Q62: 0.19
A63: 202601 | B63: AS-94864 | C63: FR | E63: ['shopify_payments'] | F63: 0 | G63: 0 | H63: 0 | I63: 0.2 | J63: EUR | K63: 0.2 | L63: 10.65 | M63: 63.9 | N63: 53.25 | P63: 0 | Q63: 0.2
A64: 202601 | B64: AS-94865 | C64: FR | E64: ['shopify_payments'] | F64: 0 | G64: 0 | H64: 0 | I64: 0.2 | J64: EUR | K64: 0.2 | L64: 14.83 | M64: 88.97 | N64: 74.14 | P64: 0 | Q64: 0.2
A65: 202601 | B65: AS-94866 | C65: FR | E65: ['shopify_payments'] | F65: 0 | G65: 0 | H65: 0 | I65: 0.2 | J65: EUR | K65: 0.2 | L65: 9.81 | M65: 58.85 | N65: 49.04 | P65: 0 | Q65: 0.2
A66: 202601 | B66: AS-94868 | C66: ES | E66: ['shopify_payments'] | F66: 0 | G66: 0 | H66: 0 | I66: 0.21 | J66: EUR | K66: 0.21 | L66: 49.97 | M66: 287.91 | N66: 237.94 | P66: 0 | Q66: 0.21
A67: 202601 | B67: AS-94869 | C67: FR | E67: ['shopify_payments'] | F67: 0 | G67: 0 | H67: 0 | I67: 0.2 | J67: EUR | K67: 0.2 | L67: 19.16 | M67: 114.95 | N67: 95.79 | P67: 0 | Q67: 0.2
A68: 202601 | B68: AS-94870 | C68: DE | E68: ['paypal'] | F68: 0 | G68: 0 | H68: 0 | I68: 0.19 | J68: EUR | K68: 0.19 | L68: 7.65 | M68: 47.9 | N68: 40.25 | P68: 0 | Q68: 0.19
A69: 202601 | B69: AS-94872 | C69: ES | E69: ['shopify_payments'] | F69: 0 | G69: 0 | H69: 0 | I69: 0.21 | J69: EUR | K69: 0.21 | L69: 6.58 | M69: 37.9 | N69: 31.32 | P69: 0 | Q69: 0.21
A70: 202601 | B70: AS-94873 | C70: AT | E70: ['paypal'] | F70: 0 | G70: 0 | H70: 0 | I70: 0.2 | J70: EUR | K70: 0.2 | L70: 5.32 | M70: 31.9 | N70: 26.58 | P70: 0 | Q70: 0.2
A71: 202601 | B71: AS-94875 | C71: FR | E71: ['shopify_payments'] | F71: 0 | G71: 0 | H71: 0 | I71: 0.2 | J71: EUR | K71: 0.2 | L71: 6.32 | M71: 37.9 | N71: 31.58 | P71: 0 | Q71: 0.2
A72: 202601 | B72: AS-94876 | C72: IT | E72: ['shopify_payments'] | F72: 0 | G72: 0 | H72: 0 | I72: 0.22 | J72: EUR | K72: 0.22 | L72: 6.83 | M72: 37.9 | N72: 31.07 | P72: 0 | Q72: 0.22
A73: 202601 | B73: AS-94877 | C73: FR | E73: ['shopify_payments'] | F73: 0 | G73: 0 | H73: 0 | I73: 0.2 | J73: EUR | K73: 0.2 | L73: 41.56 | M73: 249.35 | N73: 207.79 | P73: 0 | Q73: 0.2
... A112: 202601 | B112: AS-94927 | C112: ES | E112: ['paypal'] | F112: 0 | G112: 0 | H112: 0 | I112: 0.21 | J112: EUR | K112: 0.21 | L112: 17.16 | M112: 98.85 | N112: 81.69 | P112: 0 | Q112: 0.21
A113: 202601 | B113: AS-94928 | C113: FR | E113: ['shopify_payments'] | F113: 1 | G113: 0 | H113: 0 | I113: 0.2 | J113: EUR | K113: 0.2 | L113: 16.66 | M113: 99.95 | N113: 83.29 | O113: REVER returns | P113: 0 | Q113: 0.2
A114: 202601 | B114: AS-94930 | C114: DE | E114: ['paypal'] | F114: 0 | G114: 0 | H114: 0 | I114: 0.19 | J114: EUR | K114: 0.19 | L114: 10.52 | M114: 65.9 | N114: 55.38 | P114: 0 | Q114: 0.19
A115: 202601 | B115: AS-94931 | C115: ES | E115: ['shopify_payments'] | F115: 0 | G115: 0 | H115: 0 | I115: 0.21 | J115: EUR | K115: 0.21 | L115: 4.32 | M115: 24.9 | N115: 20.58 | P115: 0 | Q115: 0.21
A116: 202601 | B116: AS-94932 | C116: DE | E116: ['shopify_payments'] | F116: 0 | G116: 0 | H116: 0 | I116: 0.19 | J116: EUR | K116: 0.19 | L116: 24.56 | M116: 153.8 | N116: 129.24 | P116: 0 | Q116: 0.19
A117: 202601 | B117: AS-94933 | C117: ES | E117: ['shopify_payments'] | F117: 0 | G117: 0 | H117: 0 | I117: 0.21 | J117: EUR | K117: 0.21 | L117: 6.01 | M117: 34.61 | N117: 28.6 | P117: 0 | Q117: 0.21
A118: 202601 | B118: AS-94901 | C118: ES | E118: ['shopify_payments'] | F118: 0 | G118: 0 | H118: 0 | I118: 0.21 | J118: EUR | K118: 0.21 | L118: 6 | M118: 34.56 | N118: 28.56 | P118: 0 | Q118: 0.21
A119: 202601 | B119: AS-94857 | C119: DE | E119: ['shopify_payments'] | F119: 0 | G119: 0 | H119: 0 | I119: 0.19 | J119: EUR | K119: 0.19 | L119: 16.61 | M119: 104.01 | N119: 87.4 | P119: 0 | Q119: 0.19
A120: 202601 | B120: AS-94935 | C120: ES | E120: ['paypal'] | F120: 0 | G120: 0 | H120: 0 | I120: 0.21 | J120: EUR | K120: 0.21 | L120: 14.74 | M120: 84.95 | N120: 70.21 | P120: 0 | Q120: 0.21
A121: 202601 | B121: AS-94936 | C121: DE | E121: ['paypal'] | F121: 0 | G121: 0 | H121: 0 | I121: 0.19 | J121: EUR | K121: 0.19 | L121: 36.62 | M121: 229.37 | N121: 192.75 | P121: 0 | Q121: 0.19
A122: 202601 | B122: AS-94937 | C122: IT | E122: ['shopify_payments'] | F122: 0 | G122: 0 | H122: 0 | I122: 0.22 | J122: EUR | K122: 0.22 | L122: 12.25 | M122: 67.95 | N122: 55.7 | P122: 0 | Q122: 0.22
A123: 202601 | B123: AS-94938 | C123: FR | E123: ['shopify_payments'] | F123: 0 | G123: 0 | H123: 0 | I123: 0.2 | J123: EUR | K123: 0.2 | L123: 6.32 | M123: 37.9 | N123: 31.58 | P123: 0 | Q123: 0.2
A124: 202601 | B124: AS-94940 | C124: DE | E124: ['shopify_payments'] | F124: 0 | G124: 0 | H124: 0 | I124: 0.19 | J124: EUR | K124: 0.19 | L124: 12.91 | M124: 80.85 | N124: 67.94 | P124: 0 | Q124: 0.19
A125: 202601 | B125: AS-94941 | C125: IT | E125: ['shopify_payments'] | F125: 0 | G125: 0 | H125: 0 | I125: 0.22 | J125: EUR | K125: 0.22 | L125: 12.25 | M125: 67.95 | N125: 55.7 | P125: 0 | Q125: 0.22
... A162: 202601 | B162: AS-94993 | C162: FR | E162: ['shopify_payments'] | F162: 0 | G162: 0 | H162: 0 | I162: 0.2 | J162: EUR | K162: 0.2 | L162: 14.16 | M162: 84.95 | N162: 70.79 | P162: 0 | Q162: 0.2
A163: 202601 | B163: AS-94994 | C163: DE | E163: ['paypal'] | F163: 1 | G163: 0 | H163: 0 | I163: 0.19 | J163: EUR | K163: 0.19 | L163: 7.97 | M163: 49.9 | N163: 41.93 | O163: REVER returns | P163: 0 | Q163: 0.19
A164: 202601 | B164: AS-94995 | C164: ES | E164: ['shopify_payments'] | F164: 0 | G164: 0 | H164: 0 | I164: 0.21 | J164: EUR | K164: 0.21 | L164: 6.92 | M164: 39.9 | N164: 32.98 | P164: 0 | Q164: 0.21
A165: 202601 | B165: AS-94968 | C165: DE | E165: ['shopify_payments'] | F165: 0 | G165: 0 | H165: 0 | I165: 0.19 | J165: EUR | K165: 0 | L165: 0 | M165: 0 | N165: 0 | O165: cancel-Wrong product, customer-cancel | P165: 0 | Q165: 0
A166: 202601 | B166: AS-94973 | C166: DE | E166: ['shopify_payments'] | F166: 0 | G166: 0 | H166: 0 | I166: 0.19 | J166: EUR | K166: 0 | L166: 0 | M166: 0 | N166: 0 | O166: cancel-Wrong product, customer-cancel | P166: 0 | Q166: 0
A167: 202601 | B167: AS-94987 | C167: DE | E167: ['shopify_payments'] | F167: 0 | G167: 0 | H167: 0 | I167: 0.19 | J167: EUR | K167: 0 | L167: 0 | M167: 0 | N167: 0 | O167: cancel-Wrong product, customer-cancel | P167: 0 | Q167: 0
A168: 202601 | B168: AS-94972 | C168: ES | E168: ['shopify_payments'] | F168: 1 | G168: 0 | H168: 0 | I168: 0.21 | J168: EUR | K168: 0.21 | L168: 0.86 | M168: 4.95 | N168: 4.09 | O168: REVER returns | P168: 0 | Q168: 0.21
A169: 202601 | B169: AS-94948 | C169: DE | E169: ['paypal'] | F169: 1 | G169: 0 | H169: 0 | I169: 0.19 | J169: EUR | K169: 0 | L169: 0 | M169: 0 | N169: 0 | O169: REVER returns | P169: 0 | Q169: 0
A170: 202601 | B170: AS-92287 | C170: FR | E170: ['shopify_payments'] | F170: 1 | G170: 0 | H170: 0 | I170: 0.2 | J170: EUR | K170: 0.2 | L170: -229.38 | M170: -1376.3 | N170: -1146.92 | O170: Claim, Return, REVER returns | P170: 0 | Q170: 0.2
A171: 202601 | B171: AS-92324 | C171: ES | E171: ['shopify_payments'] | F171: 0 | G171: 0 | H171: 0 | I171: 0.21 | J171: EUR | K171: 0.21 | L171: -7.79 | M171: -44.91 | N171: -37.12 | P171: 0 | Q171: 0.21
A172: 202601 | B172: AS-94997 | C172: ES | E172: ['shopify_payments'] | F172: 0 | G172: 0 | H172: 0 | I172: 0.21 | J172: EUR | K172: 0.21 | L172: 6.58 | M172: 37.9 | N172: 31.32 | P172: 0 | Q172: 0.21
A173: 202601 | B173: AS-94999 | C173: DE | E173: ['paypal'] | F173: 0 | G173: 0 | H173: 0 | I173: 0.19 | J173: EUR | K173: 0.19 | L173: 18.82 | M173: 117.9 | N173: 99.08 | P173: 0 | Q173: 0.19
A174: 202601 | B174: AS-95003 | C174: IT | E174: ['paypal'] | F174: 0 | G174: 0 | H174: 0 | I174: 0.22 | J174: EUR | K174: 0.22 | L174: 11.43 | M174: 63.36 | N174: 51.93 | P174: 0 | Q174: 0.22
A175: 202601 | B175: AS-95007 | C175: DE | E175: ['shopify_payments'] | F175: 0 | G175: 0 | H175: 0 | I175: 0.19 | J175: EUR | K175: 0.19 | L175: 6.04 | M175: 37.85 | N175: 31.81 | P175: 0 | Q175: 0.19
A176: 202601 | B176: AS-95008 | C176: DE | E176: ['shopify_payments'] | F176: 0 | G176: 0 | H176: 0 | I176: 0.19 | J176: EUR | K176: 0.19 | L176: 10.51 | M176: 65.85 | N176: 55.34 | P176: 0 | Q176: 0.19
A177: 202601 | B177: AS-95009 | C177: ES | E177: ['shopify_payments'] | F177: 0 | G177: 0 | H177: 0 | I177: 0.21 | J177: EUR | K177: 0.21 | L177: 6.58 | M177: 37.9 | N177: 31.32 | P177: 0 | Q177: 0.21
A178: 202601 | B178: AS-95010 | C178: FR | E178: ['shopify_payments'] | F178: 0 | G178: 0 | H178: 0 | I178: 0.2 | J178: EUR | K178: 0.2 | L178: 7.48 | M178: 44.85 | N178: 37.37 | P178: 0 | Q178: 0.2
A179: 202601 | B179: AS-95011 | C179: FR | E179: ['shopify_payments'] | F179: 0 | G179: 0 | H179: 0 | I179: 0.2 | J179: EUR | K179: 0.2 | L179: 16.66 | M179: 99.95 | N179: 83.29 | P179: 0 | Q179: 0.2
A180: 202601 | B180: AS-95012 | C180: IT | E180: ['shopify_payments'] | F180: 0 | G180: 0 | H180: 0 | I180: 0.22 | J180: EUR | K180: 0.22 | L180: 22.06 | M180: 122.31 | N180: 100.25 | P180: 0 | Q180: 0.22
A181: 202601 | B181: AS-95013 | C181: ES | E181: ['shopify_payments'] | F181: 0 | G181: 0 | H181: 0 | I181: 0.21 | J181: EUR | K181: 0.21 | L181: 11.44 | M181: 65.9 | N181: 54.46 | P181: 0 | Q181: 0.21
A182: 202601 | B182: AS-95015 | C182: ES | E182: ['shopify_payments'] | F182: 0 | G182: 0 | H182: 0 | I182: 0.21 | J182: EUR | K182: 0.21 | L182: 11.7 | M182: 67.41 | N182: 55.71 | P182: 0 | Q182: 0.21
... A211: 202601 | B211: AS-95050 | C211: FR | E211: ['shopify_payments'] | F211: 0 | G211: 0 | H211: 0 | I211: 0.2 | J211: EUR | K211: 0.2 | L211: 6.32 | M211: 37.9 | N211: 31.58 | P211: 0 | Q211: 0.2
A212: 202601 | B212: AS-95052 | C212: ES | E212: ['shopify_payments'] | F212: 0 | G212: 0 | H212: 0 | I212: 0.07 | J212: EUR | K212: 0.07 | L212: 4.45 | M212: 67.95 | N212: 63.5 | O212: Canarias | P212: 0 | Q212: 0.07
A213: 202601 | B213: AS-95053 | C213: DE | E213: ['paypal'] | F213: 0 | G213: 0 | H213: 0 | I213: 0.19 | J213: EUR | K213: 0.19 | L213: 9.4 | M213: 58.86 | N213: 49.46 | P213: 0 | Q213: 0.19
A214: 202601 | B214: AS-95054 | C214: ES | E214: ['shopify_payments'] | F214: 0 | G214: 0 | H214: 0 | I214: 0.21 | J214: EUR | K214: 0.21 | L214: 9.81 | M214: 56.51 | N214: 46.7 | P214: 0 | Q214: 0.21
A215: 202601 | B215: AS-95055 | C215: FR | E215: [] | F215: 0 | G215: 1 | H215: 0 | I215: 0.2 | J215: EUR | K215: 0 | L215: 4.67 | M215: 26.92 | N215: 22.25 | O215: Hannun | P215: 0 | Q215: 0.21
A216: 202601 | B216: AS-95056 | C216: IT | E216: [] | F216: 0 | G216: 1 | H216: 0 | I216: 0.22 | J216: EUR | K216: 0 | L216: 10.41 | M216: 59.96 | N216: 49.55 | O216: Hannun | P216: 0 | Q216: 0.21
A217: 202601 | B217: AS-95061 | C217: ES | E217: ['shopify_payments'] | F217: 0 | G217: 0 | H217: 0 | I217: 0.21 | J217: EUR | K217: 0.21 | L217: 14.74 | M217: 84.95 | N217: 70.21 | P217: 0 | Q217: 0.21
A218: 202601 | B218: AS-95062 | C218: ES | E218: ['paypal'] | F218: 0 | G218: 0 | H218: 0 | I218: 0.21 | J218: EUR | K218: 0.21 | L218: 23.59 | M218: 135.9 | N218: 112.31 | P218: 0 | Q218: 0.21
A219: 202601 | B219: AS-95063 | C219: DE | E219: ['paypal'] | F219: 0 | G219: 0 | H219: 0 | I219: 0.19 | J219: EUR | K219: 0.19 | L219: 6.05 | M219: 37.9 | N219: 31.85 | P219: 0 | Q219: 0.19
A220: 202601 | B220: AS-95064 | C220: DE | E220: ['shopify_payments'] | F220: 0 | G220: 0 | H220: 0 | I220: 0.19 | J220: EUR | K220: 0.19 | L220: 3.98 | M220: 24.9 | N220: 20.92 | P220: 0 | Q220: 0.19
A221: 202601 | B221: AS-95065 | C221: BE | E221: ['paypal'] | F221: 0 | G221: 0 | H221: 0 | I221: 0.21 | J221: EUR | K221: 0.21 | L221: 14.74 | M221: 84.95 | N221: 70.21 | P221: 0 | Q221: 0.21
A222: 202601 | B222: AS-95066 | C222: ES | E222: ['shopify_payments'] | F222: 0 | G222: 0 | H222: 0 | I222: 0.21 | J222: EUR | K222: 0.21 | L222: 13 | M222: 74.9 | N222: 61.9 | P222: 0 | Q222: 0.21
A223: 202601 | B223: AS-95067 | C223: DE | E223: ['paypal'] | F223: 0 | G223: 0 | H223: 0 | I223: 0.19 | J223: EUR | K223: 0.19 | L223: 5.09 | M223: 31.9 | N223: 26.81 | P223: 0 | Q223: 0.19
A224: 202601 | B224: AS-95068 | C224: IT | E224: ['shopify_payments'] | F224: 0 | G224: 0 | H224: 0 | I224: 0.22 | J224: EUR | K224: 0.22 | L224: 5.75 | M224: 31.9 | N224: 26.15 | P224: 0 | Q224: 0.22
A225: 202601 | B225: AS-95071 | C225: IT | E225: ['shopify_payments'] | F225: 0 | G225: 0 | H225: 0 | I225: 0.22 | J225: EUR | K225: 0.22 | L225: 4.49 | M225: 24.9 | N225: 20.41 | P225: 0 | Q225: 0.22
A226: 202601 | B226: AS-95072 | C226: DE | E226: ['paypal'] | F226: 0 | G226: 0 | H226: 0 | I226: 0.19 | J226: EUR | K226: 0.19 | L226: 9.47 | M226: 59.31 | N226: 49.84 | P226: 0 | Q226: 0.19
A227: 202601 | B227: AS-95073 | C227: ES | E227: ['paypal'] | F227: 0 | G227: 0 | H227: 0 | I227: 0.21 | J227: EUR | K227: 0.21 | L227: 68.07 | M227: 392.18 | N227: 324.11 | P227: 0 | Q227: 0.21
A228: 202601 | B228: AS-95075 | C228: ES | E228: ['shopify_payments'] | F228: 0 | G228: 0 | H228: 0 | I228: 0.21 | J228: EUR | K228: 0.21 | L228: 4.32 | M228: 24.9 | N228: 20.58 | P228: 0 | Q228: 0.21
... A244: 202601 | B244: AS-95097 | C244: IT | E244: ['paypal'] | F244: 0 | G244: 0 | H244: 0 | I244: 0.22 | J244: EUR | K244: 0.22 | L244: 15.07 | M244: 83.57 | N244: 68.5 | P244: 0 | Q244: 0.22
A245: 202601 | B245: AS-95006 | C245: DE | E245: ['shopify_payments'] | F245: 0 | G245: 0 | H245: 0 | I245: 0.19 | J245: EUR | K245: 0 | L245: 0 | M245: 0 | N245: 0 | O245: cancel-Wrong product, customer-edit | P245: 0 | Q245: 0
A246: 202601 | B246: AS-95014 | C246: DE | E246: ['shopify_payments'] | F246: 1 | G246: 0 | H246: 0 | I246: 0.19 | J246: EUR | K246: 0 | L246: 0 | M246: 0 | N246: 0 | O246: REVER returns | P246: 0 | Q246: 0
...

Sheet Paypal_Payouts
B1: Hora | C1: Zona horaria | D1: Nombre | E1: Tipo | F1: Estado | G1: Divisa | H1: Bruto | I1: Tarifa | J1: Neto | K1: Correo electrónico del remitente | L1: Correo electrónico del destinatario | M1: Id. de transacción | N1: Dirección de envío | O1: Estado de la dirección | P1: Nombre de artículo | Q1: Id. de artículo | R1: Importe de envío y manipulación | S1: Importe del seguro | T1: Impuesto de ventas | U1: Nombre de la opción 1 | V1: Valor de la opción 1 | W1: Nombre de la opción 2 | X1: Valor de la opción 2 | Y1: Id. de referencia de trans. | Z1: Número de factura | AA1: Número personalizado | AB1: Cantidad | AC1: Id. del recibo | AD1: Saldo | AE1: Línea de dirección 1 | AF1: Línea de dirección 2/Distrito/Barrio | AG1: Población | AH1: Estado/Provincia/Región/Condado/Territorio/Prefectura/República | AI1: Código postal | AJ1: País | AK1: Número de teléfono de contacto | AL1: Asunto | AM1: Nota | AN1: Código de país | AO1: Repercusiones en el saldo | AP1: Número de pedido | AQ1: pedido_id2 | AR1: pedido_id3 | AS1: pedido_id4
A2: 01/01/2026 | B2: 03:34:17 | C2: CET | D2: Siemone Schönitz | E2: Pago con Pago exprés | F2: Completado | G2: EUR | H2: 37.9 | I2: -1.45 | J2: 36.45 | K2: siemone.schoenitz@gmx.de | L2: info@artestaposters.com | M2: 65N51228E9959580X | N2: Siemone, Schönitz, Königsberger Straße 18, Uslar, 37170, Alemania | O2: Confirmada | P2: Scandi Japandi Houseplant 3 - Póster / Sin marco / 50x70 | R2: 4.95 | T2: 0 | Z2: rlpPq43qcJ2G529gz0Y3hQ17R | AA2: {"shop_id":751927347,"session_id":"rlpPq43qcJ2G529gz0Y3hQ17R"} | AB2: 1 | AD2: 5366.52 | AE2: Königsberger Straße 18 | AG2: Uslar | AI2: 37170 | AJ2: Alemania | AK2: +49 17631633932 | AL2: Scandi Japandi Houseplant 3 - Póster / Sin marco / 50x70 | AN2: DE | AO2: Crédito | AP2: =IFERROR(VLOOKUP(M2,Shopify_Transactions!V:BB,5,0),"Not_Found") -> AS-94795 | AQ2: =IFERROR(VLOOKUP(M2,Shopify_Transactions!X:BB,3,0),"Not_Found") -> Not_Found | AR2: =IFERROR(VLOOKUP(Z2,Shopify_Transactions!W:Z,4,0),"Not_Found") -> AS-94795 | AS2: =IF(AP2<>"Not_Found",AP2,IF(AQ2<>"Not_Found",AQ2,AR2)) -> AS-94795
A3: 01/01/2026 | B3: 07:42:46 | C3: CET | D3: Domenika Kusch | E3: Pago con Pago exprés | F3: Completado | G3: EUR | H3: 25.9 | I3: -1.1 | J3: 24.8 | K3: Domenika.Kusch@gmail.com | L3: info@artestaposters.com | M3: 1VY57255J0900715E | N3: Domenika, Kusch, Wolfshagen 8, Hamburg, 20535, Alemania | O3: Confirmada | P3: Colgador para póster de 60cm de madera y color negro | R3: 4.95 | T3: 0 | Z3: rKvBqDngbj2fMmeChnhphX247 | AA3: {"shop_id":751927347,"session_id":"rKvBqDngbj2fMmeChnhphX247"} | AB3: 1 | AD3: 5391.32 | AE3: Wolfshagen 8 | AG3: Hamburg | AI3: 20535 | AJ3: Alemania | AK3: +49 017693197672 | AL3: Colgador para póster de 60cm de madera y color negro | AN3: DE | AO3: Crédito | AP3: =IFERROR(VLOOKUP(M3,Shopify_Transactions!V:BB,5,0),"Not_Found") -> AS-94796 | AQ3: =IFERROR(VLOOKUP(M3,Shopify_Transactions!X:BB,3,0),"Not_Found") -> Not_Found | AR3: =IFERROR(VLOOKUP(Z3,Shopify_Transactions!W:Z,4,0),"Not_Found") -> AS-94796 | AS3: =IF(AP3<>"Not_Found",AP3,IF(AQ3<>"Not_Found",AQ3,AR3)) -> AS-94796
A4: 01/01/2026 | B4: 10:25:19 | C4: CET | D4: Eva Pischke | E4: Pago con Pago exprés | F4: Completado | G4: EUR | H4: 17.9 | I4: -0.87 | J4: 17.03 | K4: ep@stephanpischke.de | L4: info@artestaposters.com | M4: 26P35561C8773781H | N4: Eva Maria Pischke, Ackerstraße 5, Meerbusch, 40670, Alemania | O4: Confirmada | P4: Le petit dejeuner , Made in France - Póster / Sin marco / 20x30 | R4: 4.95 | T4: 0 | Z4: rEL1tkaxNS15hEpziAVQ7TSg1 | AA4: {"shop_id":751927347,"session_id":"rEL1tkaxNS15hEpziAVQ7TSg1"} | AB4: 1 | AD4: 5408.35 | AE4: Ackerstraße 5 | AG4: Meerbusch | AI4: 40670 | AJ4: Alemania | AK4: +49 1732875027 | AL4: Le petit dejeuner , Made in France - Póster / Sin marco / 20x30 | AN4: DE | AO4: Crédito | AP4: =IFERROR(VLOOKUP(M4,Shopify_Transactions!V:BB,5,0),"Not_Found") -> AS-94799 | AQ4: =IFERROR(VLOOKUP(M4,Shopify_Transactions!X:BB,3,0),"Not_Found") -> Not_Found | AR4: =IFERROR(VLOOKUP(Z4,Shopify_Transactions!W:Z,4,0),"Not_Found") -> AS-94799 | AS4: =IF(AP4<>"Not_Found",AP4,IF(AQ4<>"Not_Found",AQ4,AR4)) -> AS-94799
A5: 01/01/2026 | B5: 13:22:53 | C5: CET | D5: Sabrina Mißlinger | E5: Pago con Pago exprés | F5: Completado | G5: EUR | H5: 85.7 | I5: -2.84 | J5: 82.86 | K5: sabrina.he@gmx.de | L5: info@artestaposters.com | M5: 7BG53258A10745635 | N5: Sabrina Mißlinger, Birnbaumstr. 4, Furth, 84095, Alemania | O5: Confirmada | P5: Toy Captain America - Póster / Sin marco / 20x30, Marco roble 20x30cm - No, Toy Superman - Póster / Sin marco / 20x30 | R5: 0 | T5: 0 | Z5: rR0zuzQi9MH5yyb1PWtioXgmN | AA5: {"shop_id":751927347,"session_id":"rR0zuzQi9MH5yyb1PWtioXgmN"} | AB5: 6 | AD5: 5491.21 | AE5: Birnbaumstr. 4 | AG5: Furth | AI5: 84095 | AJ5: Alemania | AK5: +49 74037387 | AL5: Marco roble 20x30cm - No | AN5: DE | AO5: Crédito | AP5: =IFERROR(VLOOKUP(M5,Shopify_Transactions!V:BB,5,0),"Not_Found") -> AS-94806 | AQ5: =IFERROR(VLOOKUP(M5,Shopify_Transactions!X:BB,3,0),"Not_Found") -> Not_Found | AR5: =IFERROR(VLOOKUP(Z5,Shopify_Transactions!W:Z,4,0),"Not_Found") -> AS-94806 | AS5: =IF(AP5<>"Not_Found",AP5,IF(AQ5<>"Not_Found",AQ5,AR5)) -> AS-94806
A6: 01/01/2026 | B6: 14:46:22 | C6: CET | D6: andrea cabiola | E6: Pago con Pago exprés | F6: Completado | G6: EUR | H6: 39.9 | I6: -1.51 | J6: 38.39 | K6: andrea.cabiola@gmail.com | L6: info@artestaposters.com | M6: 1EU604669L4931209 | N6: Andrea Cabiola, Q.re Dott. Emanuele Piazza, 30, 30, Marostica, Vicenza, 36063, Italia | O6: Confirmada | P6: The cat - Lienzo / Sin marco / 30x40 | R6: 4.95 | T6: 0 | Z6: rynSFLdhtLslg1aIBHooTqXjO | AA6: {"shop_id":751927347,"session_id":"rynSFLdhtLslg1aIBHooTqXjO"} | AB6: 1 | AD6: 5529.6 | AE6: Q.re Dott. Emanuele Piazza, 30, 30 | AG6: Marostica | AH6: Vicenza | AI6: 36063 | AJ6: Italia | AK6: +39 3337464714 | AL6: The cat - Lienzo / Sin marco / 30x40 | AN6: IT | AO6: Crédito | AP6: =IFERROR(VLOOKUP(M6,Shopify_Transactions!V:BB,5,0),"Not_Found") -> AS-94808 | AQ6: =IFERROR(VLOOKUP(M6,Shopify_Transactions!X:BB,3,0),"Not_Found") -> Not_Found | AR6: =IFERROR(VLOOKUP(Z6,Shopify_Transactions!W:Z,4,0),"Not_Found") -> AS-94808 | AS6: =IF(AP6<>"Not_Found",AP6,IF(AQ6<>"Not_Found",AQ6,AR6)) -> AS-94808
A7: 01/01/2026 | B7: 15:25:06 | C7: CET | D7: sarah kregehr | E7: Pago con Pago exprés | F7: Completado | G7: EUR | H7: 37.9 | I7: -1.45 | J7: 36.45 | K7: sarah.kregehr@gmx.net | L7: info@artestaposters.com | M7: 7KG57170CV926344H | N7: Sarah Kregehr, Zastrowstr. 42, Kiel, 24114, Alemania | O7: Confirmada | P7: Sun Setting on the Seine (Special Edition) - Claude Monet - Póster / Sin marco / 50x70 | R7: 4.95 | T7: 0 | Z7: rRwVmycpJ7H781oQa99ieQMsr | AA7: {"shop_id":751927347,"session_id":"rRwVmycpJ7H781oQa99ieQMsr"} | AB7: 1 | AD7: 5566.05 | AE7: Zastrowstr. 42 | AG7: Kiel | AI7: 24114 | AJ7: Alemania | AK7: +49 4512802668576 | AL7: Sun Setting on the Seine (Special Edition) - Claude Monet - Póster / Sin marco / 50x70 | AN7: DE | AO7: Crédito | AP7: =IFERROR(VLOOKUP(M7,Shopify_Transactions!V:BB,5,0),"Not_Found") -> AS-94809 | AQ7: =IFERROR(VLOOKUP(M7,Shopify_Transactions!X:BB,3,0),"Not_Found") -> Not_Found | AR7: =IFERROR(VLOOKUP(Z7,Shopify_Transactions!W:Z,4,0),"Not_Found") -> AS-94809 | AS7: =IF(AP7<>"Not_Found",AP7,IF(AQ7<>"Not_Found",AQ7,AR7)) -> AS-94809
A8: 01/01/2026 | B8: 15:51:19 | C8: CET | D8: Simone Pirozzi | E8: Pago con Pago exprés | F8: Completado | G8: EUR | H8: 44.85 | I8: -1.65 | J8: 43.2 | K8: simo.pirozzi@gmail.com | L8: info@artestaposters.com | M8: 8P573960AN1045724 | N8: Simone, Pirozzi, via IX Maggio traversa Alessandro Volta 17, Castello di Cisterna, Napoli, 80030, Italia | O8: Confirmada | P8: Ginspiration No2 - Póster / Sin marco / 30x40, Floral Campbells - Póster / Sin marco / 30x40 | R8: 4.95 | T8: 0 | Z8: rMjyZN6D6I9sEL7Hto5VLZ5p9 | AA8: {"shop_id":751927347,"session_id":"rMjyZN6D6I9sEL7Hto5VLZ5p9"} | AB8: 2 | AD8: 5609.25 | AE8: via IX Maggio traversa Alessandro Volta 17 | AG8: Castello di Cisterna | AH8: Napoli | AI8: 80030 | AJ8: Italia | AK8: +39 3337957318 | AL8: Floral Campbells - Póster / Sin marco / 30x40 | AN8: IT | AO8: Crédito | AP8: =IFERROR(VLOOKUP(M8,Shopify_Transactions!V:BB,5,0),"Not_Found") -> AS-94811 | AQ8: =IFERROR(VLOOKUP(M8,Shopify_Transactions!X:BB,3,0),"Not_Found") -> Not_Found | AR8: =IFERROR(VLOOKUP(Z8,Shopify_Transactions!W:Z,4,0),"Not_Found") -> AS-94811 | AS8: =IF(AP8<>"Not_Found",AP8,IF(AQ8<>"Not_Found",AQ8,AR8)) -> AS-94811
A9: 01/01/2026 | B9: 17:10:30 | C9: CET | D9: Theresa Litzba | E9: Pago con Pago exprés | F9: Completado | G9: EUR | H9: 63.9 | I9: -2.2 | J9: 61.7 | K9: theresa.litzba@googlemail.com | L9: info@artestaposters.com | M9: 2LR05026NW557840J | N9: Theresa Litzba, Marienstraße 2e, Köln, 50825, Alemania | O9: Confirmada | P9: Surf Down - Póster / Madera negro / 40x50 | R9: 4.95 | T9: 0 | Z9: r8Xc0vge7019LIXhiXhNAzetf | AA9: {"shop_id":751927347,"session_id":"r8Xc0vge7019LIXhiXhNAzetf"} | AB9: 1 | AD9: 5670.95 | AE9: Marienstraße 2e | AG9: Köln | AI9: 50825 | AJ9: Alemania | AK9: +49 15227402303 | AL9: Surf Down - Póster / Madera negro / 40x50 | AN9: DE | AO9: Crédito | AP9: =IFERROR(VLOOKUP(M9,Shopify_Transactions!V:BB,5,0),"Not_Found") -> AS-94816 | AQ9: =IFERROR(VLOOKUP(M9,Shopify_Transactions!X:BB,3,0),"Not_Found") -> Not_Found | AR9: =IFERROR(VLOOKUP(Z9,Shopify_Transactions!W:Z,4,0),"Not_Found") -> AS-94816 | AS9: =IF(AP9<>"Not_Found",AP9,IF(AQ9<>"Not_Found",AQ9,AR9)) -> AS-94816
A10: 01/01/2026 | B10: 17:56:27 | C10: CET | D10: Tommy Heberle | E10: Pago con Pago exprés | F10: Completado | G10: EUR | H10: 110.57 | I10: -3.56 | J10: 107.01 | K10: tommy.heberle@gmail.com | L10: info@artestaposters.com | M10: 8C034025P1221142N | N10: Tommy, Heberle, Josef-Schofer-Straße 2, Karlsruhe, 76187, Alemania | O10: Confirmada | P10: Valencia, Spain - Póster / Sin marco / 70x100, Southern Spain V - Póster / Sin marco / 50x70, Tapas - Spain - Póster / Sin marco / 70x100 | R10: 0 | T10: 0 | Z10: rFJvk30JREFXcl6eEbUWsLkXp | AA10: {"shop_id":751927347,"session_id":"rFJvk30JREFXcl6eEbUWsLkXp"} | AB10: 3 | AD10: 5777.96 | AE10: Josef-Schofer-Straße 2 | AG10: Karlsruhe | AI10: 76187 | AJ10: Alemania | AK10: +49 15170890719 | AL10: Valencia, Spain - Póster / Sin marco / 70x100 | AN10: DE | AO10: Crédito | AP10: =IFERROR(VLOOKUP(M10,Shopify_Transactions!V:BB,5,0),"Not_Found") -> AS-94820 | AQ10: =IFERROR(VLOOKUP(M10,Shopify_Transactions!X:BB,3,0),"Not_Found") -> Not_Found | AR10: =IFERROR(VLOOKUP(Z10,Shopify_Transactions!W:Z,4,0),"Not_Found") -> AS-94820 | AS10: =IF(AP10<>"Not_Found",AP10,IF(AQ10<>"Not_Found",AQ10,AR10)) -> AS-94820
A11: 01/01/2026 | B11: 18:09:37 | C11: CET | D11: Raquel Jofre | E11: Pago con Pago exprés | F11: Completado | G11: EUR | H11: 58.95 | I11: -2.06 | J11: 56.89 | K11: rjofreh25@gmail.com | L11: info@artestaposters.com | M11: 2HE95554T0540935T | N11: Raquel Jofre Hombrado, Carrer de Teresa de Calcuta 21, SÚRIA, BARCELONA, 08260, España | O11: Confirmada | P11: Movement of Vaulted Chambers Exhibition - Paul Klee - Póster / Madera negro / 40x50 | R11: 0 | T11: 0 | Z11: ruDxI3uIiZwfoIlaEeyx7b0H7 | AA11: {"shop_id":751927347,"session_id":"ruDxI3uIiZwfoIlaEeyx7b0H7"} | AB11: 1 | AD11: 5834.85 | AE11: Carrer de Teresa de Calcuta 21 | AG11: SÚRIA | AH11: BARCELONA | AI11: 8260 | AJ11: España | AK11: +34 680762886 | AL11: Movement of Vaulted Chambers Exhibition - Paul Klee - Póster / Madera negro / 40x50 | AN11: ES | AO11: Crédito | AP11: =IFERROR(VLOOKUP(M11,Shopify_Transactions!V:BB,5,0),"Not_Found") -> AS-94821 | AQ11: =IFERROR(VLOOKUP(M11,Shopify_Transactions!X:BB,3,0),"Not_Found") -> Not_Found | AR11: =IFERROR(VLOOKUP(Z11,Shopify_Transactions!W:Z,4,0),"Not_Found") -> AS-94821 | AS11: =IF(AP11<>"Not_Found",AP11,IF(AQ11<>"Not_Found",AQ11,AR11)) -> AS-94821
A12: 01/01/2026 | B12: 18:12:36 | C12: CET | D12: Arne Lummerzheim | E12: Pago con Pago exprés | F12: Completado | G12: EUR | H12: 67.95 | I12: -2.32 | J12: 65.63 | K12: alu100@web.de | L12: info@artestaposters.com | M12: 8KA47748T9168140F | N12: Arne Lummerzheim, Parkstr. 26, Berlin, 13585, Alemania | O12: Confirmada | P12: Black Montmartre - Paris Step by Step - Póster / Madera negro / 50x70 | R12: 0 | T12: 0 | Z12: rG4TUudLGNFxxBFzCn9g0yuPn | AA12: {"shop_id":751927347,"session_id":"rG4TUudLGNFxxBFzCn9g0yuPn"} | AB12: 1 | AD12: 5900.48 | AE12: Parkstr. 26 | AG12: Berlin | AI12: 13585 | AJ12: Alemania | AK12: +49 015222571986 | AL12: Black Montmartre - Paris Step by Step - Póster / Madera negro / 50x70 | AN12: DE | AO12: Crédito | AP12: =IFERROR(VLOOKUP(M12,Shopify_Transactions!V:BB,5,0),"Not_Found") -> AS-94822 | AQ12: =IFERROR(VLOOKUP(M12,Shopify_Transactions!X:BB,3,0),"Not_Found") -> Not_Found | AR12: =IFERROR(VLOOKUP(Z12,Shopify_Transactions!W:Z,4,0),"Not_Found") -> AS-94822 | AS12: =IF(AP12<>"Not_Found",AP12,IF(AQ12<>"Not_Found",AQ12,AR12)) -> AS-94822
A13: 01/01/2026 | B13: 19:36:42 | C13: CET | D13: Niko Simak | E13: Pago con Pago exprés | F13: Completado | G13: EUR | H13: 182.85 | I13: -5.65 | J13: 177.2 | K13: niko.simak@t-online.de | L13: info@artestaposters.com | M13: 9SP93479742422154 | N13: Niko Simak, Am Gries 7, Erding, 85435, Alemania | O13: Confirmada | P13: Botanical, Fleurs et plantes -Ginkgo biloba leaf - Póster / Madera roble natural / 60x90, Exposition de linogravure, Ginkgo leaves - Póster / Madera roble natural / 60x90, Pablo Picasso Animals Drawings the elephant - Póster / Sin marco / 20x30 | R13: 0 | T13: 0 | Z13: rzPm2b27wgLuQh7pFm4XtuJcq | AA13: {"shop_id":751927347,"session_id":"rzPm2b27wgLuQh7pFm4XtuJcq"} | AB13: 3 | AD13: 6077.68 | AE13: Am Gries 7 | AG13: Erding | AI13: 85435 | AJ13: Alemania | AK13: +49 17663656458 | AL13: Exposition de linogravure, Ginkgo leaves - Póster / Madera roble natural / 60x90 | AN13: DE | AO13: Crédito | AP13: =IFERROR(VLOOKUP(M13,Shopify_Transactions!V:BB,5,0),"Not_Found") -> AS-94831 | AQ13: =IFERROR(VLOOKUP(M13,Shopify_Transactions!X:BB,3,0),"Not_Found") -> Not_Found | AR13: =IFERROR(VLOOKUP(Z13,Shopify_Transactions!W:Z,4,0),"Not_Found") -> AS-94831 | AS13: =IF(AP13<>"Not_Found",AP13,IF(AQ13<>"Not_Found",AQ13,AR13)) -> AS-94831
A14: 01/01/2026 | B14: 20:54:56 | C14: CET | D14: Carlo Lancini | E14: Pago con Pago exprés | F14: Completado | G14: EUR | H14: 79.9 | I14: -2.67 | J14: 77.23 | K14: carlolancini@tiscali.it | L14: info@artestaposters.com | M14: 4F210044PU032664W | N14: Carlo Lancini, Via Francesco Petrarca 8, Stezzano, Bergamo, 24040, Italia | O14: Confirmada | P14: Winter morning - Póster / Sin marco / 60x90, Chirping And Chilling (At Night) - Póster / Sin marco / 60x90 | R14: 0 | T14: 0 | Z14: rxZgU1TOGAExn1C9mOmxBbVeR | AA14: {"shop_id":751927347,"session_id":"rxZgU1TOGAExn1C9mOmxBbVeR"} | AB14: 2 | AD14: 6154.91 | AE14: Via Francesco Petrarca 8 | AG14: Stezzano | AH14: Bergamo | AI14: 24040 | AJ14: Italia | AK14: +39 0354379421 | AL14: Winter morning - Póster / Sin marco / 60x90 | AN14: IT | AO14: Crédito | AP14: =IFERROR(VLOOKUP(M14,Shopify_Transactions!V:BB,5,0),"Not_Found") -> AS-94835 | AQ14: =IFERROR(VLOOKUP(M14,Shopify_Transactions!X:BB,3,0),"Not_Found") -> Not_Found | AR14: =IFERROR(VLOOKUP(Z14,Shopify_Transactions!W:Z,4,0),"Not_Found") -> AS-94835 | AS14: =IF(AP14<>"Not_Found",AP14,IF(AQ14<>"Not_Found",AQ14,AR14)) -> AS-94835
A15: 01/01/2026 | B15: 21:42:06 | C15: CET | D15: EURIDICE LAZALDE GUTIERREZ | E15: Pago con Pago exprés | F15: Completado | G15: EUR | H15: 67.95 | I15: -2.32 | J15: 65.63 | K15: euridice.lazalde.gtz@gmail.com | L15: info@artestaposters.com | M15: 6C912892W3965535M | N15: Euridice LAZALDE Gutierrez, Viale Umbria 1, Bastia Umbra, Perugia, 06083, Italia | O15: Confirmada | P15: Mexico - Póster / Madera roble oscuro / 50x70 | R15: 0 | T15: 0 | Z15: r6B3qrX1uRteuXK2YCKzrIfBI | AA15: {"shop_id":751927347,"session_id":"r6B3qrX1uRteuXK2YCKzrIfBI"} | AB15: 1 | AD15: 6220.54 | AE15: Viale Umbria 1 | AG15: Bastia Umbra | AH15: Perugia | AI15: 6083 | AJ15: Italia | AK15: +39 3885820350 | AL15: Mexico - Póster / Madera roble oscuro / 50x70 | AN15: IT | AO15: Crédito | AP15: =IFERROR(VLOOKUP(M15,Shopify_Transactions!V:BB,5,0),"Not_Found") -> AS-94839 | AQ15: =IFERROR(VLOOKUP(M15,Shopify_Transactions!X:BB,3,0),"Not_Found") -> Not_Found | AR15: =IFERROR(VLOOKUP(Z15,Shopify_Transactions!W:Z,4,0),"Not_Found") -> AS-94839 | AS15: =IF(AP15<>"Not_Found",AP15,IF(AQ15<>"Not_Found",AQ15,AR15)) -> AS-94839
A16: 01/01/2026 | B16: 21:44:39 | C16: CET | D16: rolf clostermann | E16: Pago con Pago exprés | F16: Completado | G16: EUR | H16: 114.95 | I16: -3.68 | J16: 111.27 | K16: leslie.clostermann@gmail.com | L16: info@artestaposters.com | M16: 8HR26733VV295503E | N16: Leslie Clostermann, Gabainstr. 6, Wesel, 46483, Alemania | O16: Confirmada | P16: Mid Century Blue II - Lienzo / Madera negro / 50x70 | R16: 0 | T16: 0 | Z16: rH6WAmFf83ZbXZf2icWvwM9oM | AA16: {"shop_id":751927347,"session_id":"rH6WAmFf83ZbXZf2icWvwM9oM"} | AB16: 1 | AD16: 6331.81 | AE16: Gabainstr. 6 | AG16: Wesel | AI16: 46483 | AJ16: Alemania | AK16: +49 028599010125 | AL16: Mid Century Blue II - Lienzo / Madera negro / 50x70 | AN16: DE | AO16: Crédito | AP16: =IFERROR(VLOOKUP(M16,Shopify_Transactions!V:BB,5,0),"Not_Found") -> AS-94840 | AQ16: =IFERROR(VLOOKUP(M16,Shopify_Transactions!X:BB,3,0),"Not_Found") -> Not_Found | AR16: =IFERROR(VLOOKUP(Z16,Shopify_Transactions!W:Z,4,0),"Not_Found") -> AS-94840 | AS16: =IF(AP16<>"Not_Found",AP16,IF(AQ16<>"Not_Found",AQ16,AR16)) -> AS-94840
A17: 01/01/2026 | B17: 22:09:51 | C17: CET | D17: Reni Ahlborn | E17: Pago con Pago exprés | F17: Completado | G17: EUR | H17: 71.91 | I17: -2.44 | J17: 69.47 | K17: irene.ahlborn@web.de | L17: info@artestaposters.com | M17: 0BC33688L92679619 | N17: Irene Schwab-Ahlborn, Moorweg 45a, Schenefeld, 22869, Alemania | O17: Confirmada | P17: Pablo Picasso The Three Dancers Sktech poster - Póster / Sin marco / 60x90, Picasso Ladies of Avignon sketch Poster - Póster / Sin marco / 60x90 | R17: 0 | T17: 0 | Z17: r29RRtLUvXL6Tz39L5TWtgNnA | AA17: {"shop_id":751927347,"session_id":"r29RRtLUvXL6Tz39L5TWtgNnA"} | AB17: 2 | AD17: 6401.28 | AE17: Moorweg 45a | AG17: Schenefeld | AI17: 22869 | AJ17: Alemania | AK17: +49 15752834664 | AL17: Picasso Ladies of Avignon sketch Poster - Póster / Sin marco / 60x90 | AN17: DE | AO17: Crédito | AP17: =IFERROR(VLOOKUP(M17,Shopify_Transactions!V:BB,5,0),"Not_Found") -> AS-94842 | AQ17: =IFERROR(VLOOKUP(M17,Shopify_Transactions!X:BB,3,0),"Not_Found") -> Not_Found | AR17: =IFERROR(VLOOKUP(Z17,Shopify_Transactions!W:Z,4,0),"Not_Found") -> AS-94842 | AS17: =IF(AP17<>"Not_Found",AP17,IF(AQ17<>"Not_Found",AQ17,AR17)) -> AS-94842
A18: 01/01/2026 | B18: 22:23:43 | C18: CET | D18: Doreen Epstein | E18: Pago con Pago exprés | F18: Completado | G18: EUR | H18: 84.95 | I18: -2.81 | J18: 82.14 | K18: doreen.epstein@yahoo.de | L18: info@artestaposters.com | M18: 2FT21109V73915801 | N18: Doreen Epstein, Bürschgartenstraße 13, Wiesbaden, 65193, Alemania | O18: Confirmada | P18: La vie en France, St Tropez - Póster / Madera roble natural / 60x90 | R18: 0 | T18: 0 | Z18: rnDbfCSBaL9MVyHPi73lToJBJ | AA18: {"shop_id":751927347,"session_id":"rnDbfCSBaL9MVyHPi73lToJBJ"} | AB18: 1 | AD18: 6483.42 | AE18: Bürschgartenstraße 13 | AG18: Wiesbaden | AI18: 65193 | AJ18: Alemania | AK18: +49 17670067582 | AL18: La vie en France, St Tropez - Póster / Madera roble natural / 60x90 | AN18: DE | AO18: Crédito | AP18: =IFERROR(VLOOKUP(M18,Shopify_Transactions!V:BB,5,0),"Not_Found") -> AS-94843 | AQ18: =IFERROR(VLOOKUP(M18,Shopify_Transactions!X:BB,3,0),"Not_Found") -> Not_Found | AR18: =IFERROR(VLOOKUP(Z18,Shopify_Transactions!W:Z,4,0),"Not_Found") -> AS-94843 | AS18: =IF(AP18<>"Not_Found",AP18,IF(AQ18<>"Not_Found",AQ18,AR18)) -> AS-94843
A19: 01/01/2026 | B19: 23:40:36 | C19: CET | D19: Carolin Weihrauch | E19: Pago con Pago exprés | F19: Completado | G19: EUR | H19: 37.9 | I19: -1.45 | J19: 36.45 | K19: carolin-weihrauch@gmx.de | L19: info@artestaposters.com | M19: 2K825256CU025401D | N19: Carolin Weihrauch, Giselherstraße 13, Weinheim, 69469, Alemania | O19: Confirmada | P19: Maddies Mood - jotadejai - Póster / Sin marco / 50x70 | R19: 4.95 | T19: 0 | Z19: rbTKDXCCwJiLkypzQK0aXfiSm | AA19: {"shop_id":751927347,"session_id":"rbTKDXCCwJiLkypzQK0aXfiSm"} | AB19: 1 | AD19: 6519.87 | AE19: Giselherstraße 13 | AG19: Weinheim | AI19: 69469 | AJ19: Alemania | AK19: +49 17630426806 | AL19: Maddies Mood - jotadejai - Póster / Sin marco / 50x70 | AN19: DE | AO19: Crédito | AP19: =IFERROR(VLOOKUP(M19,Shopify_Transactions!V:BB,5,0),"Not_Found") -> AS-94847 | AQ19: =IFERROR(VLOOKUP(M19,Shopify_Transactions!X:BB,3,0),"Not_Found") -> Not_Found | AR19: =IFERROR(VLOOKUP(Z19,Shopify_Transactions!W:Z,4,0),"Not_Found") -> AS-94847 | AS19: =IF(AP19<>"Not_Found",AP19,IF(AQ19<>"Not_Found",AQ19,AR19)) -> AS-94847
A20: 02/01/2026 | B20: 03:06:04 | C20: CET | D20: Judith Heuer | E20: Pago con Pago exprés | F20: Completado | G20: EUR | H20: 24.9 | I20: -1.07 | J20: 23.83 | K20: juditheuer@web.de | L20: info@artestaposters.com | M20: 0H471785HL184274D | N20: Judith, Heuer, Bollerstaudenstrasse 6, Freiburg, 79111, Alemania | O20: Confirmada | P20: Linocut Tree - Alisa Galitsyna - Póster / Sin marco / 30x40 | R20: 4.95 | T20: 0 | Z20: r4vSAwDFqAFODjgyeQwb7YqUE | AA20: {"shop_id":751927347,"session_id":"r4vSAwDFqAFODjgyeQwb7YqUE"} | AB20: 1 | AD20: 6543.7 | AE20: Bollerstaudenstrasse 6 | AG20: Freiburg | AI20: 79111 | AJ20: Alemania | AK20: +49 7617070086 | AL20: Linocut Tree - Alisa Galitsyna - Póster / Sin marco / 30x40 | AN20: DE | AO20: Crédito | AP20: =IFERROR(VLOOKUP(M20,Shopify_Transactions!V:BB,5,0),"Not_Found") -> AS-94852 | AQ20: =IFERROR(VLOOKUP(M20,Shopify_Transactions!X:BB,3,0),"Not_Found") -> Not_Found | AR20: =IFERROR(VLOOKUP(Z20,Shopify_Transactions!W:Z,4,0),"Not_Found") -> AS-94852 | AS20: =IF(AP20<>"Not_Found",AP20,IF(AQ20<>"Not_Found",AQ20,AR20)) -> AS-94852
A21: 02/01/2026 | B21: 09:20:38 | C21: CET | D21: Antonella D'Agostino | E21: Reembolso de pago | F21: Completado | G21: EUR | H21: -42.5 | I21: 0 | J21: -42.5 | K21: info@artestaposters.com | L21: adagostino79@gmail.com | M21: 70D38532X6560444C | O21: No confirmada | P21: Dream Big - Póster / Madera negro / 60x90 | T21: 0 | Y21: 2FT67700GT9707127 | Z21: rPCOnHayv4pz9ocWKOiTL2ERc | AA21: {"shop_id":751927347,"session_id":"zG2XibzylGeidS5KCCVD0pczx"} | AB21: 1 | AD21: 6501.2 | AK21: +39 05321914250 | AL21: Dream Big - Póster / Madera negro / 60x90 | AO21: Cargo | AP21: =IFERROR(VLOOKUP(M21,Shopify_Transactions!V:BB,5,0),"Not_Found") -> AS-93059 | AQ21: =IFERROR(VLOOKUP(M21,Shopify_Transactions!X:BB,3,0),"Not_Found") -> AS-93059 | AR21: =IFERROR(VLOOKUP(Z21,Shopify_Transactions!W:Z,4,0),"Not_Found") -> AS-93059 | AS21: =IF(AP21<>"Not_Found",AP21,IF(AQ21<>"Not_Found",AQ21,AR21)) -> AS-93059
A22: 02/01/2026 | B22: 09:34:33 | C22: CET | D22: Rolf Bernau | E22: Pago con Pago exprés | F22: Completado | G22: EUR | H22: 63.9 | I22: -2.2 | J22: 61.7 | K22: Rolf.Bernau@alice.de | L22: info@artestaposters.com | M22: 9V1082071N1257400 | N22: Herr Rolf Bernau, Freimuthstr. 8b, Falkensee, 14612, Alemania | O22: Confirmada | P22: Gustav Klimt Garden Cat Print - Póster / Madera azul / 40x50 | R22: 4.95 | T22: 0 | Z22: rLI3K6gh3jmkEQgW96GQK41mA | AA22: {"shop_id":751927347,"session_id":"rLI3K6gh3jmkEQgW96GQK41mA"} | AB22: 1 | AD22: 6562.9 | AE22: Freimuthstr. 8b | AG22: Falkensee | AI22: 14612 | AJ22: Alemania | AK22: +49 01703436160 | AL22: Gustav Klimt Garden Cat Print - Póster / Madera azul / 40x50 | AN22: DE | AO22: Crédito | AP22: =IFERROR(VLOOKUP(M22,Shopify_Transactions!V:BB,5,0),"Not_Found") -> AS-94856 | AQ22: =IFERROR(VLOOKUP(M22,Shopify_Transactions!X:BB,3,0),"Not_Found") -> Not_Found | AR22: =IFERROR(VLOOKUP(Z22,Shopify_Transactions!W:Z,4,0),"Not_Found") -> AS-94856 | AS22: =IF(AP22<>"Not_Found",AP22,IF(AQ22<>"Not_Found",AQ22,AR22)) -> AS-94856
A23: 02/01/2026 | B23: 10:27:29 | C23: CET | D23: Rainer Plehwe | E23: Pago con Pago exprés | F23: Completado | G23: EUR | H23: 101.9 | I23: -3.31 | J23: 98.59 | K23: rainer.plehwe@freenet.de | L23: info@artestaposters.com | M23: 2WY88087XH197154R | N23: Plehwe Rainer, Deelacker 5, Schuby, 24850, Alemania | O23: Confirmada | P23: Pablo Picasso Animals Drawings the cat Esquisse D’un Félin - Póster / Madera blanco / 30x40, Pablo Picasso Animals Drawings the elephant - Póster / Madera blanco / 40x50 | R23: 0 | T23: 0 | Z23: r9OZ8HZ6ZOhzXVio74XH3RfqF | AA23: {"shop_id":751927347,"session_id":"r9OZ8HZ6ZOhzXVio74XH3RfqF"} | AB23: 2 | AD23: 6661.49 | AE23: Deelacker 5 | AG23: Schuby | AI23: 24850 | AJ23: Alemania | AK23: +49 15140190935 | AL23: Pablo Picasso Animals Drawings the elephant - Póster / Madera blanco / 40x50 | AN23: DE | AO23: Crédito | AP23: =IFERROR(VLOOKUP(M23,Shopify_Transactions!V:BB,5,0),"Not_Found") -> AS-94860 | AQ23: =IFERROR(VLOOKUP(M23,Shopify_Transactions!X:BB,3,0),"Not_Found") -> Not_Found | AR23: =IFERROR(VLOOKUP(Z23,Shopify_Transactions!W:Z,4,0),"Not_Found") -> AS-94860 | AS23: =IF(AP23<>"Not_Found",AP23,IF(AQ23<>"Not_Found",AQ23,AR23)) -> AS-94860
A24: 02/01/2026 | B24: 11:44:44 | C24: CET | E24: Retención del saldo disponible | F24: Completado | G24: EUR | H24: -2037.96 | I24: 0 | J24: -2037.96 | K24: info@artestaposters.com | M24: 479232030Y9989809 | AD24: 4623.53 | AO24: Cargo | AP24: =IFERROR(VLOOKUP(M24,Shopify_Transactions!V:BB,5,0),"Not_Found") -> Not_Found | AQ24: =IFERROR(VLOOKUP(M24,Shopify_Transactions!X:BB,3,0),"Not_Found") -> Not_Found | AR24: =IFERROR(VLOOKUP(Z24,Shopify_Transactions!W:Z,4,0),"Not_Found") -> Not_Found | AS24: =IF(AP24<>"Not_Found",AP24,IF(AQ24<>"Not_Found",AQ24,AR24)) -> Not_Found
A25: 02/01/2026 | B25: 11:44:53 | C25: CET | D25: Anna Carolline Da Cruz Farath | E25: Pago con Pago en serie | F25: Completado | G25: EUR | H25: -5.4 | I25: -0.11 | J25: -5.51 | K25: info@artestaposters.com | L25: galaxyeyes.shop@gmail.com | M25: 5HA55916NW8671213 | O25: No confirmada | Y25: 479232030Y9989809 | AA25: item_1767350658_1 | AD25: 4618.02 | AL25: Has recibido un pago | AM25: Te hemos enviado un pago por PayPal. | AO25: Cargo | AP25: =IFERROR(VLOOKUP(M25,Shopify_Transactions!V:BB,5,0),"Not_Found") -> Not_Found | AQ25: =IFERROR(VLOOKUP(M25,Shopify_Transactions!X:BB,3,0),"Not_Found") -> Not_Found | AR25: =IFERROR(VLOOKUP(Z25,Shopify_Transactions!W:Z,4,0),"Not_Found") -> Not_Found | AS25: =IF(AP25<>"Not_Found",AP25,IF(AQ25<>"Not_Found",AQ25,AR25)) -> Not_Found
A26: 02/01/2026 | B26: 11:44:53 | C26: CET | D26: PayPal | E26: Cancelación de retención de cuenta general | F26: Completado | G26: EUR | H26: 5.51 | I26: 0 | J26: 5.51 | L26: info@artestaposters.com | M26: 1CE1268435728604Y | Y26: 479232030Y9989809 | AD26: 4623.53 | AL26: Has recibido un pago | AO26: Crédito | AP26: =IFERROR(VLOOKUP(M26,Shopify_Transactions!V:BB,5,0),"Not_Found") -> Not_Found | AQ26: =IFERROR(VLOOKUP(M26,Shopify_Transactions!X:BB,3,0),"Not_Found") -> Not_Found | AR26: =IFERROR(VLOOKUP(Z26,Shopify_Transactions!W:Z,4,0),"Not_Found") -> Not_Found | AS26: =IF(AP26<>"Not_Found",AP26,IF(AQ26<>"Not_Found",AQ26,AR26)) -> Not_Found
A27: 02/01/2026 | B27: 11:44:53 | C27: CET | D27: Cordula Schaefer | E27: Pago con Pago en serie | F27: Completado | G27: EUR | H27: -6 | I27: -0.12 | J27: -6.12 | K27: info@artestaposters.com | L27: cordula.schaefer@gmx.net | M27: 7R100435TV757994D | O27: No confirmada | Y27: 479232030Y9989809 | AA27: item_1767350658_4 | AD27: 4617.41 | AL27: Has recibido un pago | AM27: Te hemos enviado un pago por PayPal. | AO27: Cargo | AP27: =IFERROR(VLOOKUP(M27,Shopify_Transactions!V:BB,5,0),"Not_Found") -> Not_Found | AQ27: =IFERROR(VLOOKUP(M27,Shopify_Transactions!X:BB,3,0),"Not_Found") -> Not_Found | AR27: =IFERROR(VLOOKUP(Z27,Shopify_Transactions!W:Z,4,0),"Not_Found") -> Not_Found | AS27: =IF(AP27<>"Not_Found",AP27,IF(AQ27<>"Not_Found",AQ27,AR27)) -> Not_Found
A28: 02/01/2026 | B28: 11:44:53 | C28: CET | D28: PayPal | E28: Cancelación de retención de cuenta general | F28: Completado | G28: EUR | H28: 6.12 | I28: 0 | J28: 6.12 | L28: info@artestaposters.com | M28: 04J78733D2957040J | Y28: 479232030Y9989809 | AD28: 4623.53 | AL28: Has recibido un pago | AO28: Crédito | AP28: =IFERROR(VLOOKUP(M28,Shopify_Transactions!V:BB,5,0),"Not_Found") -> Not_Found | AQ28: =IFERROR(VLOOKUP(M28,Shopify_Transactions!X:BB,3,0),"Not_Found") -> Not_Found | AR28: =IFERROR(VLOOKUP(Z28,Shopify_Transactions!W:Z,4,0),"Not_Found") -> Not_Found | AS28: =IF(AP28<>"Not_Found",AP28,IF(AQ28<>"Not_Found",AQ28,AR28)) -> Not_Found
A29: 02/01/2026 | B29: 11:44:53 | C29: CET | D29: Dana Shek | E29: Pago con Pago en serie | F29: Completado | G29: EUR | H29: -128.25 | I29: -2.57 | J29: -130.82 | K29: info@artestaposters.com | L29: dana.shek@gmail.com | M29: 5AH16117AS090991Y | O29: No confirmada | Y29: 479232030Y9989809 | AA29: item_1767350658_5 | AD29: 4492.71 | AL29: Has recibido un pago | AM29: Te hemos enviado un pago por PayPal. | AO29: Cargo | AP29: =IFERROR(VLOOKUP(M29,Shopify_Transactions!V:BB,5,0),"Not_Found") -> Not_Found | AQ29: =IFERROR(VLOOKUP(M29,Shopify_Transactions!X:BB,3,0),"Not_Found") -> Not_Found | AR29: =IFERROR(VLOOKUP(Z29,Shopify_Transactions!W:Z,4,0),"Not_Found") -> Not_Found | AS29: =IF(AP29<>"Not_Found",AP29,IF(AQ29<>"Not_Found",AQ29,AR29)) -> Not_Found
A30: 02/01/2026 | B30: 11:44:53 | C30: CET | D30: PayPal | E30: Cancelación de retención de cuenta general | F30: Completado | G30: EUR | H30: 130.82 | I30: 0 | J30: 130.82 | L30: info@artestaposters.com | M30: 1YL56527LA047635X | Y30: 479232030Y9989809 | AD30: 4623.53 | AL30: Has recibido un pago | AO30: Crédito | AP30: =IFERROR(VLOOKUP(M30,Shopify_Transactions!V:BB,5,0),"Not_Found") -> Not_Found | AQ30: =IFERROR(VLOOKUP(M30,Shopify_Transactions!X:BB,3,0),"Not_Found") -> Not_Found | AR30: =IFERROR(VLOOKUP(Z30,Shopify_Transactions!W:Z,4,0),"Not_Found") -> Not_Found | AS30: =IF(AP30<>"Not_Found",AP30,IF(AQ30<>"Not_Found",AQ30,AR30)) -> Not_Found
A31: 02/01/2026 | B31: 11:44:53 | C31: CET | D31: Wan Alvin Mak | E31: Pago con Pago en serie | F31: Completado | G31: EUR | H31: -34.2 | I31: -0.68 | J31: -34.88 | K31: info@artestaposters.com | L31: alvinmak74@gmail.com | M31: 7T226696B7863140L | O31: No confirmada | Y31: 479232030Y9989809 | AA31: item_1767350658_0 | AD31: 4588.65 | AL31: Has recibido un pago | AM31: Te hemos enviado un pago por PayPal. | AO31: Cargo | AP31: =IFERROR(VLOOKUP(M31,Shopify_Transactions!V:BB,5,0),"Not_Found") -> Not_Found | AQ31: =IFERROR(VLOOKUP(M31,Shopify_Transactions!X:BB,3,0),"Not_Found") -> Not_Found | AR31: =IFERROR(VLOOKUP(Z31,Shopify_Transactions!W:Z,4,0),"Not_Found") -> Not_Found | AS31: =IF(AP31<>"Not_Found",AP31,IF(AQ31<>"Not_Found",AQ31,AR31)) -> Not_Found
A32: 02/01/2026 | B32: 11:44:53 | C32: CET | D32: PayPal | E32: Cancelación de retención de cuenta general | F32: Completado | G32: EUR | H32: 34.88 | I32: 0 | J32: 34.88 | L32: info@artestaposters.com | M32: 80E036948J721470W | Y32: 479232030Y9989809 | AD32: 4623.53 | AL32: Has recibido un pago | AO32: Crédito | AP32: =IFERROR(VLOOKUP(M32,Shopify_Transactions!V:BB,5,0),"Not_Found") -> Not_Found | AQ32: =IFERROR(VLOOKUP(M32,Shopify_Transactions!X:BB,3,0),"Not_Found") -> Not_Found | AR32: =IFERROR(VLOOKUP(Z32,Shopify_Transactions!W:Z,4,0),"Not_Found") -> Not_Found | AS32: =IF(AP32<>"Not_Found",AP32,IF(AQ32<>"Not_Found",AQ32,AR32)) -> Not_Found
A33: 02/01/2026 | B33: 11:44:53 | C33: CET | D33: Bruno Morphet | E33: Pago con Pago en serie | F33: Completado | G33: EUR | H33: -28.5 | I33: -0.57 | J33: -29.07 | K33: info@artestaposters.com | L33: Bruno.Morphet@gmail.com | M33: 2G741075DW400002W | O33: No confirmada | Y33: 479232030Y9989809 | AA33: item_1767350658_3 | AD33: 4594.46 | AL33: Has recibido un pago | AM33: Te hemos enviado un pago por PayPal. | AO33: Cargo | AP33: =IFERROR(VLOOKUP(M33,Shopify_Transactions!V:BB,5,0),"Not_Found") -> Not_Found | AQ33: =IFERROR(VLOOKUP(M33,Shopify_Transactions!X:BB,3,0),"Not_Found") -> Not_Found | AR33: =IFERROR(VLOOKUP(Z33,Shopify_Transactions!W:Z,4,0),"Not_Found") -> Not_Found | AS33: =IF(AP33<>"Not_Found",AP33,IF(AQ33<>"Not_Found",AQ33,AR33)) -> Not_Found
A34: 02/01/2026 | B34: 11:44:53 | C34: CET | D34: PayPal | E34: Cancelación de retención de cuenta general | F34: Completado | G34: EUR | H34: 29.07 | I34: 0 | J34: 29.07 | L34: info@artestaposters.com | M34: 56V55145H52000300 | Y34: 479232030Y9989809 | AD34: 4623.53 | AL34: Has recibido un pago | AO34: Crédito | AP34: =IFERROR(VLOOKUP(M34,Shopify_Transactions!V:BB,5,0),"Not_Found") -> Not_Found | AQ34: =IFERROR(VLOOKUP(M34,Shopify_Transactions!X:BB,3,0),"Not_Found") -> Not_Found | AR34: =IFERROR(VLOOKUP(Z34,Shopify_Transactions!W:Z,4,0),"Not_Found") -> Not_Found | AS34: =IF(AP34<>"Not_Found",AP34,IF(AQ34<>"Not_Found",AQ34,AR34)) -> Not_Found
A35: 02/01/2026 | B35: 11:44:54 | C35: CET | D35: Artem Pozdniakov | E35: Pago con Pago en serie | F35: Completado | G35: EUR | H35: -18.9 | I35: -0.38 | J35: -19.28 | K35: info@artestaposters.com | L35: brain360@yandex.kz | M35: 9RR734633M188032T | O35: No confirmada | Y35: 479232030Y9989809 | AA35: item_1767350658_2 | AD35: 4604.25 | AL35: Has recibido un pago | AM35: Te hemos enviado un pago por PayPal. | AO35: Cargo | AP35: =IFERROR(VLOOKUP(M35,Shopify_Transactions!V:BB,5,0),"Not_Found") -> Not_Found | AQ35: =IFERROR(VLOOKUP(M35,Shopify_Transactions!X:BB,3,0),"Not_Found") -> Not_Found | AR35: =IFERROR(VLOOKUP(Z35,Shopify_Transactions!W:Z,4,0),"Not_Found") -> Not_Found | AS35: =IF(AP35<>"Not_Found",AP35,IF(AQ35<>"Not_Found",AQ35,AR35)) -> Not_Found
A36: 02/01/2026 | B36: 11:44:54 | C36: CET | D36: PayPal | E36: Cancelación de retención de cuenta general | F36: Completado | G36: EUR | H36: 19.28 | I36: 0 | J36: 19.28 | L36: info@artestaposters.com | M36: 9E319528RK662944F | Y36: 479232030Y9989809 | AD36: 4623.53 | AL36: Has recibido un pago | AO36: Crédito | AP36: =IFERROR(VLOOKUP(M36,Shopify_Transactions!V:BB,5,0),"Not_Found") -> Not_Found | AQ36: =IFERROR(VLOOKUP(M36,Shopify_Transactions!X:BB,3,0),"Not_Found") -> Not_Found | AR36: =IFERROR(VLOOKUP(Z36,Shopify_Transactions!W:Z,4,0),"Not_Found") -> Not_Found | AS36: =IF(AP36<>"Not_Found",AP36,IF(AQ36<>"Not_Found",AQ36,AR36)) -> Not_Found
A37: 02/01/2026 | B37: 11:44:55 | C37: CET | D37: Gal Design | E37: Pago con Pago en serie | F37: Completado | G37: EUR | H37: -145.35 | I37: -2.91 | J37: -148.26 | K37: info@artestaposters.com | L37: Gal.pittel@gmail.com | M37: 9M926396KT904862V | O37: No confirmada | Y37: 479232030Y9989809 | AA37: item_1767350658_9 | AD37: 4475.27 | AL37: Has recibido un pago | AM37: Te hemos enviado un pago por PayPal. | AO37: Cargo | AP37: =IFERROR(VLOOKUP(M37,Shopify_Transactions!V:BB,5,0),"Not_Found") -> Not_Found | AQ37: =IFERROR(VLOOKUP(M37,Shopify_Transactions!X:BB,3,0),"Not_Found") -> Not_Found | AR37: =IFERROR(VLOOKUP(Z37,Shopify_Transactions!W:Z,4,0),"Not_Found") -> Not_Found | AS37: =IF(AP37<>"Not_Found",AP37,IF(AQ37<>"Not_Found",AQ37,AR37)) -> Not_Found
A38: 02/01/2026 | B38: 11:44:55 | C38: CET | D38: PayPal | E38: Cancelación de retención de cuenta general | F38: Completado | G38: EUR | H38: 148.26 | I38: 0 | J38: 148.26 | L38: info@artestaposters.com | M38: 8C888240FV214483B | Y38: 479232030Y9989809 | AD38: 4623.53 | AL38: Has recibido un pago | AO38: Crédito | AP38: =IFERROR(VLOOKUP(M38,Shopify_Transactions!V:BB,5,0),"Not_Found") -> Not_Found | AQ38: =IFERROR(VLOOKUP(M38,Shopify_Transactions!X:BB,3,0),"Not_Found") -> Not_Found | AR38: =IFERROR(VLOOKUP(Z38,Shopify_Transactions!W:Z,4,0),"Not_Found") -> Not_Found | AS38: =IF(AP38<>"Not_Found",AP38,IF(AQ38<>"Not_Found",AQ38,AR38)) -> Not_Found
A39: 02/01/2026 | B39: 11:44:55 | C39: CET | D39: Katherine Stinchcomb-Smit | E39: Pago con Pago en serie | F39: Completado | G39: EUR | H39: -171 | I39: -3.42 | J39: -174.42 | K39: info@artestaposters.com | L39: katherine@creativenomadsdesign.com | M39: 041116387L360802H | O39: No confirmada | Y39: 479232030Y9989809 | AA39: item_1767350658_24 | AD39: 4449.11 | AL39: Has recibido un pago | AM39: Te hemos enviado un pago por PayPal. | AO39: Cargo | AP39: =IFERROR(VLOOKUP(M39,Shopify_Transactions!V:BB,5,0),"Not_Found") -> Not_Found | AQ39: =IFERROR(VLOOKUP(M39,Shopify_Transactions!X:BB,3,0),"Not_Found") -> Not_Found | AR39: =IFERROR(VLOOKUP(Z39,Shopify_Transactions!W:Z,4,0),"Not_Found") -> Not_Found | AS39: =IF(AP39<>"Not_Found",AP39,IF(AQ39<>"Not_Found",AQ39,AR39)) -> Not_Found
A40: 02/01/2026 | B40: 11:44:55 | C40: CET | D40: PayPal | E40: Cancelación de retención de cuenta general | F40: Completado | G40: EUR | H40: 174.42 | I40: 0 | J40: 174.42 | L40: info@artestaposters.com | M40: 8V210166GD155800M | Y40: 479232030Y9989809 | AD40: 4623.53 | AL40: Has recibido un pago | AO40: Crédito | AP40: =IFERROR(VLOOKUP(M40,Shopify_Transactions!V:BB,5,0),"Not_Found") -> Not_Found | AQ40: =IFERROR(VLOOKUP(M40,Shopify_Transactions!X:BB,3,0),"Not_Found") -> Not_Found | AR40: =IFERROR(VLOOKUP(Z40,Shopify_Transactions!W:Z,4,0),"Not_Found") -> Not_Found | AS40: =IF(AP40<>"Not_Found",AP40,IF(AQ40<>"Not_Found",AQ40,AR40)) -> Not_Found
A41: 02/01/2026 | B41: 11:44:55 | C41: CET | D41: Sophia Novosel | E41: Pago con Pago en serie | F41: Completado | G41: EUR | H41: -117 | I41: -2.34 | J41: -119.34 | K41: info@artestaposters.com | L41: novoselsophia@gmail.com | M41: 7W181086Y15483836 | O41: No confirmada | Y41: 479232030Y9989809 | AA41: item_1767350658_23 | AD41: 4504.19 | AL41: Has recibido un pago | AM41: Te hemos enviado un pago por PayPal. | AO41: Cargo | AP41: =IFERROR(VLOOKUP(M41,Shopify_Transactions!V:BB,5,0),"Not_Found") -> Not_Found | AQ41: =IFERROR(VLOOKUP(M41,Shopify_Transactions!X:BB,3,0),"Not_Found") -> Not_Found | AR41: =IFERROR(VLOOKUP(Z41,Shopify_Transactions!W:Z,4,0),"Not_Found") -> Not_Found | AS41: =IF(AP41<>"Not_Found",AP41,IF(AQ41<>"Not_Found",AQ41,AR41)) -> Not_Found
A42: 02/01/2026 | B42: 11:44:55 | C42: CET | D42: PayPal | E42: Cancelación de retención de cuenta general | F42: Completado | G42: EUR | H42: 119.34 | I42: 0 | J42: 119.34 | L42: info@artestaposters.com | M42: 6HB68053C3276632D | Y42: 479232030Y9989809 | AD42: 4623.53 | AL42: Has recibido un pago | AO42: Crédito | AP42: =IFERROR(VLOOKUP(M42,Shopify_Transactions!V:BB,5,0),"Not_Found") -> Not_Found | AQ42: =IFERROR(VLOOKUP(M42,Shopify_Transactions!X:BB,3,0),"Not_Found") -> Not_Found | AR42: =IFERROR(VLOOKUP(Z42,Shopify_Transactions!W:Z,4,0),"Not_Found") -> Not_Found | AS42: =IF(AP42<>"Not_Found",AP42,IF(AQ42<>"Not_Found",AQ42,AR42)) -> Not_Found
A43: 02/01/2026 | B43: 11:44:56 | C43: CET | D43: Fernando Lopez Ojea | E43: Pago con Pago en serie | F43: Completado | G43: EUR | H43: -109.65 | I43: -2.19 | J43: -111.84 | K43: info@artestaposters.com | L43: infodikhotomy@gmail.com | M43: 2BJ85352AN0993510 | O43: No confirmada | Y43: 479232030Y9989809 | AA43: item_1767350658_7 | AD43: 4511.69 | AL43: Has recibido un pago | AM43: Te hemos enviado un pago por PayPal. | AO43: Cargo | AP43: =IFERROR(VLOOKUP(M43,Shopify_Transactions!V:BB,5,0),"Not_Found") -> Not_Found | AQ43: =IFERROR(VLOOKUP(M43,Shopify_Transactions!X:BB,3,0),"Not_Found") -> Not_Found | AR43: =IFERROR(VLOOKUP(Z43,Shopify_Transactions!W:Z,4,0),"Not_Found") -> Not_Found | AS43: =IF(AP43<>"Not_Found",AP43,IF(AQ43<>"Not_Found",AQ43,AR43)) -> Not_Found
A44: 02/01/2026 | B44: 11:44:56 | C44: CET | D44: PayPal | E44: Cancelación de retención de cuenta general | F44: Completado | G44: EUR | H44: 111.84 | I44: 0 | J44: 111.84 | L44: info@artestaposters.com | M44: 6JG26630RK9941014 | Y44: 479232030Y9989809 | AD44: 4623.53 | AL44: Has recibido un pago | AO44: Crédito | AP44: =IFERROR(VLOOKUP(M44,Shopify_Transactions!V:BB,5,0),"Not_Found") -> Not_Found | AQ44: =IFERROR(VLOOKUP(M44,Shopify_Transactions!X:BB,3,0),"Not_Found") -> Not_Found | AR44: =IFERROR(VLOOKUP(Z44,Shopify_Transactions!W:Z,4,0),"Not_Found") -> Not_Found | AS44: =IF(AP44<>"Not_Found",AP44,IF(AQ44<>"Not_Found",AQ44,AR44)) -> Not_Found
A45: 02/01/2026 | B45: 11:44:56 | C45: CET | D45: Florent Bodart | E45: Pago con Pago en serie | F45: Completado | G45: EUR | H45: -147 | I45: -2.94 | J45: -149.94 | K45: info@artestaposters.com | L45: bodartflorent@gmail.com | M45: 6V384060VM781510R | O45: No confirmada | Y45: 479232030Y9989809 | AA45: item_1767350658_8 | AD45: 4473.59 | AL45: Has recibido un pago | AM45: Te hemos enviado un pago por PayPal. | AO45: Cargo | AP45: =IFERROR(VLOOKUP(M45,Shopify_Transactions!V:BB,5,0),"Not_Found") -> Not_Found | AQ45: =IFERROR(VLOOKUP(M45,Shopify_Transactions!X:BB,3,0),"Not_Found") -> Not_Found | AR45: =IFERROR(VLOOKUP(Z45,Shopify_Transactions!W:Z,4,0),"Not_Found") -> Not_Found | AS45: =IF(AP45<>"Not_Found",AP45,IF(AQ45<>"Not_Found",AQ45,AR45)) -> Not_Found
A46: 02/01/2026 | B46: 11:44:56 | C46: CET | D46: PayPal | E46: Cancelación de retención de cuenta general | F46: Completado | G46: EUR | H46: 149.94 | I46: 0 | J46: 149.94 | L46: info@artestaposters.com | M46: 5T631820S5656864E | Y46: 479232030Y9989809 | AD46: 4623.53 | AL46: Has recibido un pago | AO46: Crédito | AP46: =IFERROR(VLOOKUP(M46,Shopify_Transactions!V:BB,5,0),"Not_Found") -> Not_Found | AQ46: =IFERROR(VLOOKUP(M46,Shopify_Transactions!X:BB,3,0),"Not_Found") -> Not_Found | AR46: =IFERROR(VLOOKUP(Z46,Shopify_Transactions!W:Z,4,0),"Not_Found") -> Not_Found | AS46: =IF(AP46<>"Not_Found",AP46,IF(AQ46<>"Not_Found",AQ46,AR46)) -> Not_Found
A47: 02/01/2026 | B47: 11:44:56 | C47: CET | D47: Ninhol Design Ltda | E47: Pago con Pago en serie | F47: Pendiente | G47: EUR | H47: -12 | I47: -0.24 | J47: -12.24 | K47: info@artestaposters.com | L47: contact@ninhol.com | M47: 74W91794SB698501E | O47: No confirmada | Y47: 479232030Y9989809 | AA47: item_1767350658_11 | AD47: 4611.29 | AL47: Has recibido un pago | AM47: Te hemos enviado un pago por PayPal. | AO47: Cargo | AP47: =IFERROR(VLOOKUP(M47,Shopify_Transactions!V:BB,5,0),"Not_Found") -> Not_Found | AQ47: =IFERROR(VLOOKUP(M47,Shopify_Transactions!X:BB,3,0),"Not_Found") -> Not_Found | AR47: =IFERROR(VLOOKUP(Z47,Shopify_Transactions!W:Z,4,0),"Not_Found") -> Not_Found | AS47: =IF(AP47<>"Not_Found",AP47,IF(AQ47<>"Not_Found",AQ47,AR47)) -> Not_Found
A48: 02/01/2026 | B48: 11:44:56 | C48: CET | D48: PayPal | E48: Cancelación de retención de cuenta general | F48: Completado | G48: EUR | H48: 12.24 | I48: 0 | J48: 12.24 | L48: info@artestaposters.com | M48: 69619364S6276625R | Y48: 479232030Y9989809 | AD48: 4623.53 | AL48: Has recibido un pago | AO48: Crédito | AP48: =IFERROR(VLOOKUP(M48,Shopify_Transactions!V:BB,5,0),"Not_Found") -> Not_Found | AQ48: =IFERROR(VLOOKUP(M48,Shopify_Transactions!X:BB,3,0),"Not_Found") -> Not_Found | AR48: =IFERROR(VLOOKUP(Z48,Shopify_Transactions!W:Z,4,0),"Not_Found") -> Not_Found | AS48: =IF(AP48<>"Not_Found",AP48,IF(AQ48<>"Not_Found",AQ48,AR48)) -> Not_Found
A49: 02/01/2026 | B49: 11:44:57 | C49: CET | D49: Desirée Feldmann | E49: Pago con Pago en serie | F49: Completado | G49: EUR | H49: -18.9 | I49: -0.38 | J49: -19.28 | K49: info@artestaposters.com | L49: desiree.feldmann@gmail.com | M49: 7EY0641945452321R | O49: No confirmada | Y49: 479232030Y9989809 | AA49: item_1767350658_6 | AD49: 4604.25 | AL49: Has recibido un pago | AM49: Te hemos enviado un pago por PayPal. | AO49: Cargo | AP49: =IFERROR(VLOOKUP(M49,Shopify_Transactions!V:BB,5,0),"Not_Found") -> Not_Found | AQ49: =IFERROR(VLOOKUP(M49,Shopify_Transactions!X:BB,3,0),"Not_Found") -> Not_Found | AR49: =IFERROR(VLOOKUP(Z49,Shopify_Transactions!W:Z,4,0),"Not_Found") -> Not_Found | AS49: =IF(AP49<>"Not_Found",AP49,IF(AQ49<>"Not_Found",AQ49,AR49)) -> Not_Found
A50: 02/01/2026 | B50: 11:44:57 | C50: CET | D50: PayPal | E50: Cancelación de retención de cuenta general | F50: Completado | G50: EUR | H50: 19.28 | I50: 0 | J50: 19.28 | L50: info@artestaposters.com | M50: 7TW673482Y819932E | Y50: 479232030Y9989809 | AD50: 4623.53 | AL50: Has recibido un pago | AO50: Crédito | AP50: =IFERROR(VLOOKUP(M50,Shopify_Transactions!V:BB,5,0),"Not_Found") -> Not_Found | AQ50: =IFERROR(VLOOKUP(M50,Shopify_Transactions!X:BB,3,0),"Not_Found") -> Not_Found | AR50: =IFERROR(VLOOKUP(Z50,Shopify_Transactions!W:Z,4,0),"Not_Found") -> Not_Found | AS50: =IF(AP50<>"Not_Found",AP50,IF(AQ50<>"Not_Found",AQ50,AR50)) -> Not_Found
A51: 02/01/2026 | B51: 11:44:57 | C51: CET | D51: Sarah Manovski | E51: Pago con Pago en serie | F51: Completado | G51: EUR | H51: -99 | I51: -1.98 | J51: -100.98 | K51: info@artestaposters.com | L51: sarahmanovski@gmail.com | M51: 749286172V964113N | O51: No confirmada | Y51: 479232030Y9989809 | AA51: item_1767350658_21 | AD51: 4522.55 | AL51: Has recibido un pago | AM51: Te hemos enviado un pago por PayPal. | AO51: Cargo | AP51: =IFERROR(VLOOKUP(M51,Shopify_Transactions!V:BB,5,0),"Not_Found") -> Not_Found | AQ51: =IFERROR(VLOOKUP(M51,Shopify_Transactions!X:BB,3,0),"Not_Found") -> Not_Found | AR51: =IFERROR(VLOOKUP(Z51,Shopify_Transactions!W:Z,4,0),"Not_Found") -> Not_Found | AS51: =IF(AP51<>"Not_Found",AP51,IF(AQ51<>"Not_Found",AQ51,AR51)) -> Not_Found
A52: 02/01/2026 | B52: 11:44:57 | C52: CET | D52: PayPal | E52: Cancelación de retención de cuenta general | F52: Completado | G52: EUR | H52: 100.98 | I52: 0 | J52: 100.98 | L52: info@artestaposters.com | M52: 75M68578GP037132M | Y52: 479232030Y9989809 | AD52: 4623.53 | AL52: Has recibido un pago | AO52: Crédito | AP52: =IFERROR(VLOOKUP(M52,Shopify_Transactions!V:BB,5,0),"Not_Found") -> Not_Found | AQ52: =IFERROR(VLOOKUP(M52,Shopify_Transactions!X:BB,3,0),"Not_Found") -> Not_Found | AR52: =IFERROR(VLOOKUP(Z52,Shopify_Transactions!W:Z,4,0),"Not_Found") -> Not_Found | AS52: =IF(AP52<>"Not_Found",AP52,IF(AQ52<>"Not_Found",AQ52,AR52)) -> Not_Found
A53: 02/01/2026 | B53: 11:44:57 | C53: CET | D53: nicola squirrell | E53: Pago con Pago en serie | F53: Completado | G53: EUR | H53: -9 | I53: -0.18 | J53: -9.18 | K53: info@artestaposters.com | L53: squirrell@rocketmail.com | M53: 7SR56301B5769334R | O53: No confirmada | Y53: 479232030Y9989809 | AA53: item_1767350658_19 | AD53: 4614.35 | AL53: Has recibido un pago | AM53: Te hemos enviado un pago por PayPal. | AO53: Cargo | AP53: =IFERROR(VLOOKUP(M53,Shopify_Transactions!V:BB,5,0),"Not_Found") -> Not_Found | AQ53: =IFERROR(VLOOKUP(M53,Shopify_Transactions!X:BB,3,0),"Not_Found") -> Not_Found | AR53: =IFERROR(VLOOKUP(Z53,Shopify_Transactions!W:Z,4,0),"Not_Found") -> Not_Found | AS53: =IF(AP53<>"Not_Found",AP53,IF(AQ53<>"Not_Found",AQ53,AR53)) -> Not_Found
A54: 02/01/2026 | B54: 11:44:57 | C54: CET | D54: PayPal | E54: Cancelación de retención de cuenta general | F54: Completado | G54: EUR | H54: 9.18 | I54: 0 | J54: 9.18 | L54: info@artestaposters.com | M54: 3WE00816KF3543517 | Y54: 479232030Y9989809 | AD54: 4623.53 | AL54: Has recibido un pago | AO54: Crédito | AP54: =IFERROR(VLOOKUP(M54,Shopify_Transactions!V:BB,5,0),"Not_Found") -> Not_Found | AQ54: =IFERROR(VLOOKUP(M54,Shopify_Transactions!X:BB,3,0),"Not_Found") -> Not_Found | AR54: =IFERROR(VLOOKUP(Z54,Shopify_Transactions!W:Z,4,0),"Not_Found") -> Not_Found | AS54: =IF(AP54<>"Not_Found",AP54,IF(AQ54<>"Not_Found",AQ54,AR54)) -> Not_Found
A55: 02/01/2026 | B55: 11:44:57 | C55: CET | D55: Rafael da Silva Gomes | E55: Pago con Pago en serie | F55: Completado | G55: EUR | H55: -89.1 | I55: -1.78 | J55: -90.88 | K55: info@artestaposters.com | L55: rafazyz@gmail.com | M55: 4YP320904N130431W | O55: No confirmada | Y55: 479232030Y9989809 | AA55: item_1767350658_20 | AD55: 4532.65 | AL55: Has recibido un pago | AM55: Te hemos enviado un pago por PayPal. | AO55: Cargo | AP55: =IFERROR(VLOOKUP(M55,Shopify_Transactions!V:BB,5,0),"Not_Found") -> Not_Found | AQ55: =IFERROR(VLOOKUP(M55,Shopify_Transactions!X:BB,3,0),"Not_Found") -> Not_Found | AR55: =IFERROR(VLOOKUP(Z55,Shopify_Transactions!W:Z,4,0),"Not_Found") -> Not_Found | AS55: =IF(AP55<>"Not_Found",AP55,IF(AQ55<>"Not_Found",AQ55,AR55)) -> Not_Found
A56: 02/01/2026 | B56: 11:44:57 | C56: CET | D56: PayPal | E56: Cancelación de retención de cuenta general | F56: Completado | G56: EUR | H56: 90.88 | I56: 0 | J56: 90.88 | L56: info@artestaposters.com | M56: 17067585YH265771X | Y56: 479232030Y9989809 | AD56: 4623.53 | AL56: Has recibido un pago | AO56: Crédito | AP56: =IFERROR(VLOOKUP(M56,Shopify_Transactions!V:BB,5,0),"Not_Found") -> Not_Found | AQ56: =IFERROR(VLOOKUP(M56,Shopify_Transactions!X:BB,3,0),"Not_Found") -> Not_Found | AR56: =IFERROR(VLOOKUP(Z56,Shopify_Transactions!W:Z,4,0),"Not_Found") -> Not_Found | AS56: =IF(AP56<>"Not_Found",AP56,IF(AQ56<>"Not_Found",AQ56,AR56)) -> Not_Found
A57: 02/01/2026 | B57: 11:44:58 | C57: CET | D57: Shatha Dafai | E57: Pago con Pago en serie | F57: Completado | G57: EUR | H57: -113.16 | I57: -2.26 | J57: -115.42 | K57: info@artestaposters.com | L57: shatha.dafai@gmail.com | M57: 2RD01551AF012961P | O57: No confirmada | Y57: 479232030Y9989809 | AA57: item_1767350658_22 | AD57: 4508.11 | AL57: Has recibido un pago | AM57: Te hemos enviado un pago por PayPal. | AO57: Cargo | AP57: =IFERROR(VLOOKUP(M57,Shopify_Transactions!V:BB,5,0),"Not_Found") -> Not_Found | AQ57: =IFERROR(VLOOKUP(M57,Shopify_Transactions!X:BB,3,0),"Not_Found") -> Not_Found | AR57: =IFERROR(VLOOKUP(Z57,Shopify_Transactions!W:Z,4,0),"Not_Found") -> Not_Found | AS57: =IF(AP57<>"Not_Found",AP57,IF(AQ57<>"Not_Found",AQ57,AR57)) -> Not_Found
A58: 02/01/2026 | B58: 11:44:58 | C58: CET | D58: PayPal | E58: Cancelación de retención de cuenta general | F58: Completado | G58: EUR | H58: 115.42 | I58: 0 | J58: 115.42 | L58: info@artestaposters.com | M58: 9N261434WB6816349 | Y58: 479232030Y9989809 | AD58: 4623.53 | AL58: Has recibido un pago | AO58: Crédito | AP58: =IFERROR(VLOOKUP(M58,Shopify_Transactions!V:BB,5,0),"Not_Found") -> Not_Found | AQ58: =IFERROR(VLOOKUP(M58,Shopify_Transactions!X:BB,3,0),"Not_Found") -> Not_Found | AR58: =IFERROR(VLOOKUP(Z58,Shopify_Transactions!W:Z,4,0),"Not_Found") -> Not_Found | AS58: =IF(AP58<>"Not_Found",AP58,IF(AQ58<>"Not_Found",AQ58,AR58)) -> Not_Found
A59: 02/01/2026 | B59: 11:44:58 | C59: CET | D59: Jack Cope | E59: Pago con Pago en serie | F59: Completado | G59: EUR | H59: -468 | I59: -9.36 | J59: -477.36 | K59: info@artestaposters.com | L59: jackcope1995@hotmail.com | M59: 8HP678642C467725L | O59: No confirmada | Y59: 479232030Y9989809 | AA59: item_1767350658_10 | AD59: 4146.17 | AL59: Has recibido un pago | AM59: Te hemos enviado un pago por PayPal. | AO59: Cargo | AP59: =IFERROR(VLOOKUP(M59,Shopify_Transactions!V:BB,5,0),"Not_Found") -> Not_Found | AQ59: =IFERROR(VLOOKUP(M59,Shopify_Transactions!X:BB,3,0),"Not_Found") -> Not_Found | AR59: =IFERROR(VLOOKUP(Z59,Shopify_Transactions!W:Z,4,0),"Not_Found") -> Not_Found | AS59: =IF(AP59<>"Not_Found",AP59,IF(AQ59<>"Not_Found",AQ59,AR59)) -> Not_Found
A60: 02/01/2026 | B60: 11:44:58 | C60: CET | D60: PayPal | E60: Cancelación de retención de cuenta general | F60: Completado | G60: EUR | H60: 477.36 | I60: 0 | J60: 477.36 | L60: info@artestaposters.com | M60: 64U94486XU3836319 | Y60: 479232030Y9989809 | AD60: 4623.53 | AL60: Has recibido un pago | AO60: Crédito | AP60: =IFERROR(VLOOKUP(M60,Shopify_Transactions!V:BB,5,0),"Not_Found") -> Not_Found | AQ60: =IFERROR(VLOOKUP(M60,Shopify_Transactions!X:BB,3,0),"Not_Found") -> Not_Found | AR60: =IFERROR(VLOOKUP(Z60,Shopify_Transactions!W:Z,4,0),"Not_Found") -> Not_Found | AS60: =IF(AP60<>"Not_Found",AP60,IF(AQ60<>"Not_Found",AQ60,AR60)) -> Not_Found
A61: 02/01/2026 | B61: 11:44:58 | C61: CET | D61: Extra | E61: Pago con Pago en serie | F61: Completado | G61: EUR | H61: -8.64 | I61: -0.17 | J61: -8.81 | K61: info@artestaposters.com | L61: 1coldmain@gmail.com | M61: 2TX41624NE194234P | O61: No confirmada | Y61: 479232030Y9989809 | AA61: item_1767350658_13 | AD61: 4614.72 | AL61: Has recibido un pago | AM61: Te hemos enviado un pago por PayPal. | AO61: Cargo | AP61: =IFERROR(VLOOKUP(M61,Shopify_Transactions!V:BB,5,0),"Not_Found") -> Not_Found | AQ61: =IFERROR(VLOOKUP(M61,Shopify_Transactions!X:BB,3,0),"Not_Found") -> Not_Found | AR61: =IFERROR(VLOOKUP(Z61,Shopify_Transactions!W:Z,4,0),"Not_Found") -> Not_Found | AS61: =IF(AP61<>"Not_Found",AP61,IF(AQ61<>"Not_Found",AQ61,AR61)) -> Not_Found
A62: 02/01/2026 | B62: 11:44:58 | C62: CET | D62: PayPal | E62: Cancelación de retención de cuenta general | F62: Completado | G62: EUR | H62: 8.81 | I62: 0 | J62: 8.81 | L62: info@artestaposters.com | M62: 5V5722267D630084L | Y62: 479232030Y9989809 | AD62: 4623.53 | AL62: Has recibido un pago | AO62: Crédito | AP62: =IFERROR(VLOOKUP(M62,Shopify_Transactions!V:BB,5,0),"Not_Found") -> Not_Found | AQ62: =IFERROR(VLOOKUP(M62,Shopify_Transactions!X:BB,3,0),"Not_Found") -> Not_Found | AR62: =IFERROR(VLOOKUP(Z62,Shopify_Transactions!W:Z,4,0),"Not_Found") -> Not_Found | AS62: =IF(AP62<>"Not_Found",AP62,IF(AQ62<>"Not_Found",AQ62,AR62)) -> Not_Found
A63: 02/01/2026 | B63: 11:44:58 | C63: CET | D63: Veronika Boulová | E63: Pago con Pago en serie | F63: Completado | G63: EUR | H63: -3 | I63: -0.06 | J63: -3.06 | K63: info@artestaposters.com | L63: veronika.boulova@seznam.cz | M63: 746259136Y0127518 | O63: No confirmada | Y63: 479232030Y9989809 | AA63: item_1767350658_26 | AD63: 4620.47 | AL63: Has recibido un pago | AM63: Te hemos enviado un pago por PayPal. | AO63: Cargo | AP63: =IFERROR(VLOOKUP(M63,Shopify_Transactions!V:BB,5,0),"Not_Found") -> Not_Found | AQ63: =IFERROR(VLOOKUP(M63,Shopify_Transactions!X:BB,3,0),"Not_Found") -> Not_Found | AR63: =IFERROR(VLOOKUP(Z63,Shopify_Transactions!W:Z,4,0),"Not_Found") -> Not_Found | AS63: =IF(AP63<>"Not_Found",AP63,IF(AQ63<>"Not_Found",AQ63,AR63)) -> Not_Found
A64: 02/01/2026 | B64: 11:44:58 | C64: CET | D64: PayPal | E64: Cancelación de retención de cuenta general | F64: Completado | G64: EUR | H64: 3.06 | I64: 0 | J64: 3.06 | L64: info@artestaposters.com | M64: 5Y2205589T767422S | Y64: 479232030Y9989809 | AD64: 4623.53 | AL64: Has recibido un pago | AO64: Crédito | AP64: =IFERROR(VLOOKUP(M64,Shopify_Transactions!V:BB,5,0),"Not_Found") -> Not_Found | AQ64: =IFERROR(VLOOKUP(M64,Shopify_Transactions!X:BB,3,0),"Not_Found") -> Not_Found | AR64: =IFERROR(VLOOKUP(Z64,Shopify_Transactions!W:Z,4,0),"Not_Found") -> Not_Found | AS64: =IF(AP64<>"Not_Found",AP64,IF(AQ64<>"Not_Found",AQ64,AR64)) -> Not_Found
A65: 02/01/2026 | B65: 11:44:58 | C65: CET | D65: Juan Fonrodona | E65: Pago con Pago en serie | F65: Completado | G65: EUR | H65: -8.1 | I65: -0.16 | J65: -8.26 | K65: info@artestaposters.com | L65: juanpafond@gmail.com | M65: 6KS34292H69282629 | O65: No confirmada | Y65: 479232030Y9989809 | AA65: item_1767350658_12 | AD65: 4615.27 | AL65: Has recibido un pago | AM65: Te hemos enviado un pago por PayPal. | AO65: Cargo | AP65: =IFERROR(VLOOKUP(M65,Shopify_Transactions!V:BB,5,0),"Not_Found") -> Not_Found | AQ65: =IFERROR(VLOOKUP(M65,Shopify_Transactions!X:BB,3,0),"Not_Found") -> Not_Found | AR65: =IFERROR(VLOOKUP(Z65,Shopify_Transactions!W:Z,4,0),"Not_Found") -> Not_Found | AS65: =IF(AP65<>"Not_Found",AP65,IF(AQ65<>"Not_Found",AQ65,AR65)) -> Not_Found
A66: 02/01/2026 | B66: 11:44:58 | C66: CET | D66: PayPal | E66: Cancelación de retención de cuenta general | F66: Completado | G66: EUR | H66: 8.26 | I66: 0 | J66: 8.26 | L66: info@artestaposters.com | M66: 04663473Y2461750K | Y66: 479232030Y9989809 | AD66: 4623.53 | AL66: Has recibido un pago | AO66: Crédito | AP66: =IFERROR(VLOOKUP(M66,Shopify_Transactions!V:BB,5,0),"Not_Found") -> Not_Found | AQ66: =IFERROR(VLOOKUP(M66,Shopify_Transactions!X:BB,3,0),"Not_Found") -> Not_Found | AR66: =IFERROR(VLOOKUP(Z66,Shopify_Transactions!W:Z,4,0),"Not_Found") -> Not_Found | AS66: =IF(AP66<>"Not_Found",AP66,IF(AQ66<>"Not_Found",AQ66,AR66)) -> Not_Found
A67: 02/01/2026 | B67: 11:44:58 | C67: CET | D67: muthiman@gmx.de | E67: Pago con Pago en serie | F67: No reclamado | G67: EUR | H67: -6 | I67: -0.12 | J67: -6.12 | K67: info@artestaposters.com | L67: muthiman@gmx.de | M67: 5WB0734275482572A | Y67: 479232030Y9989809 | AA67: item_1767350658_17 | AD67: 4617.41 | AL67: Has recibido un pago | AM67: Te hemos enviado un pago por PayPal. | AO67: Cargo | AP67: =IFERROR(VLOOKUP(M67,Shopify_Transactions!V:BB,5,0),"Not_Found") -> Not_Found | AQ67: =IFERROR(VLOOKUP(M67,Shopify_Transactions!X:BB,3,0),"Not_Found") -> Not_Found | AR67: =IFERROR(VLOOKUP(Z67,Shopify_Transactions!W:Z,4,0),"Not_Found") -> Not_Found | AS67: =IF(AP67<>"Not_Found",AP67,IF(AQ67<>"Not_Found",AQ67,AR67)) -> Not_Found
A68: 02/01/2026 | B68: 11:44:58 | C68: CET | D68: PayPal | E68: Cancelación de retención de cuenta general | F68: Completado | G68: EUR | H68: 6.12 | I68: 0 | J68: 6.12 | L68: info@artestaposters.com | M68: 6UC71546G0131474T | Y68: 479232030Y9989809 | AD68: 4623.53 | AL68: Has recibido un pago | AO68: Crédito | AP68: =IFERROR(VLOOKUP(M68,Shopify_Transactions!V:BB,5,0),"Not_Found") -> Not_Found | AQ68: =IFERROR(VLOOKUP(M68,Shopify_Transactions!X:BB,3,0),"Not_Found") -> Not_Found | AR68: =IFERROR(VLOOKUP(Z68,Shopify_Transactions!W:Z,4,0),"Not_Found") -> Not_Found | AS68: =IF(AP68<>"Not_Found",AP68,IF(AQ68<>"Not_Found",AQ68,AR68)) -> Not_Found
A69: 02/01/2026 | B69: 11:44:58 | C69: CET | D69: Lucy Wisada | E69: Pago con Pago en serie | F69: Completado | G69: EUR | H69: -12 | I69: -0.24 | J69: -12.24 | K69: info@artestaposters.com | L69: lucy.wisada@hotmail.co.uk | M69: 2E234177EJ235571M | O69: No confirmada | Y69: 479232030Y9989809 | AA69: item_1767350658_15 | AD69: 4611.29 | AL69: Has recibido un pago | AM69: Te hemos enviado un pago por PayPal. | AO69: Cargo | AP69: =IFERROR(VLOOKUP(M69,Shopify_Transactions!V:BB,5,0),"Not_Found") -> Not_Found | AQ69: =IFERROR(VLOOKUP(M69,Shopify_Transactions!X:BB,3,0),"Not_Found") -> Not_Found | AR69: =IFERROR(VLOOKUP(Z69,Shopify_Transactions!W:Z,4,0),"Not_Found") -> Not_Found | AS69: =IF(AP69<>"Not_Found",AP69,IF(AQ69<>"Not_Found",AQ69,AR69)) -> Not_Found
A70: 02/01/2026 | B70: 11:44:58 | C70: CET | D70: PayPal | E70: Cancelación de retención de cuenta general | F70: Completado | G70: EUR | H70: 12.24 | I70: 0 | J70: 12.24 | L70: info@artestaposters.com | M70: 9D246591YB2358358 | Y70: 479232030Y9989809 | AD70: 4623.53 | AL70: Has recibido un pago | AO70: Crédito | AP70: =IFERROR(VLOOKUP(M70,Shopify_Transactions!V:BB,5,0),"Not_Found") -> Not_Found | AQ70: =IFERROR(VLOOKUP(M70,Shopify_Transactions!X:BB,3,0),"Not_Found") -> Not_Found | AR70: =IFERROR(VLOOKUP(Z70,Shopify_Transactions!W:Z,4,0),"Not_Found") -> Not_Found | AS70: =IF(AP70<>"Not_Found",AP70,IF(AQ70<>"Not_Found",AQ70,AR70)) -> Not_Found
A71: 02/01/2026 | B71: 11:44:59 | C71: CET | D71: Kris Favreau | E71: Pago con Pago en serie | F71: Completado | G71: EUR | H71: -136.8 | I71: -2.74 | J71: -139.54 | K71: info@artestaposters.com | L71: Futurlux@gmail.com | M71: 07365446D1086110M | O71: No confirmada | Y71: 479232030Y9989809 | AA71: item_1767350658_18 | AD71: 4483.99 | AL71: Has recibido un pago | AM71: Te hemos enviado un pago por PayPal. | AO71: Cargo | AP71: =IFERROR(VLOOKUP(M71,Shopify_Transactions!V:BB,5,0),"Not_Found") -> Not_Found | AQ71: =IFERROR(VLOOKUP(M71,Shopify_Transactions!X:BB,3,0),"Not_Found") -> Not_Found | AR71: =IFERROR(VLOOKUP(Z71,Shopify_Transactions!W:Z,4,0),"Not_Found") -> Not_Found | AS71: =IF(AP71<>"Not_Found",AP71,IF(AQ71<>"Not_Found",AQ71,AR71)) -> Not_Found
A72: 02/01/2026 | B72: 11:44:59 | C72: CET | D72: PayPal | E72: Cancelación de retención de cuenta general | F72: Completado | G72: EUR | H72: 139.54 | I72: 0 | J72: 139.54 | L72: info@artestaposters.com | M72: 4M340448GW699200H | Y72: 479232030Y9989809 | AD72: 4623.53 | AL72: Has recibido un pago | AO72: Crédito | AP72: =IFERROR(VLOOKUP(M72,Shopify_Transactions!V:BB,5,0),"Not_Found") -> Not_Found | AQ72: =IFERROR(VLOOKUP(M72,Shopify_Transactions!X:BB,3,0),"Not_Found") -> Not_Found | AR72: =IFERROR(VLOOKUP(Z72,Shopify_Transactions!W:Z,4,0),"Not_Found") -> Not_Found | AS72: =IF(AP72<>"Not_Found",AP72,IF(AQ72<>"Not_Found",AQ72,AR72)) -> Not_Found
A73: 02/01/2026 | B73: 11:44:59 | C73: CET | D73: Ludivine Josephine | E73: Pago con Pago en serie | F73: Completado | G73: EUR | H73: -15 | I73: -0.3 | J73: -15.3 | K73: info@artestaposters.com | L73: kanzilue@gmail.com | M73: 0L210004GU163253D | O73: No confirmada | Y73: 479232030Y9989809 | AA73: item_1767350658_16 | AD73: 4608.23 | AL73: Has recibido un pago | AM73: Te hemos enviado un pago por PayPal. | AO73: Cargo | AP73: =IFERROR(VLOOKUP(M73,Shopify_Transactions!V:BB,5,0),"Not_Found") -> Not_Found | AQ73: =IFERROR(VLOOKUP(M73,Shopify_Transactions!X:BB,3,0),"Not_Found") -> Not_Found | AR73: =IFERROR(VLOOKUP(Z73,Shopify_Transactions!W:Z,4,0),"Not_Found") -> Not_Found | AS73: =IF(AP73<>"Not_Found",AP73,IF(AQ73<>"Not_Found",AQ73,AR73)) -> Not_Found
A74: 02/01/2026 | B74: 11:44:59 | C74: CET | D74: PayPal | E74: Cancelación de retención de cuenta general | F74: Completado | G74: EUR | H74: 15.3 | I74: 0 | J74: 15.3 | L74: info@artestaposters.com | M74: 1DB74760AN139141B | Y74: 479232030Y9989809 | AD74: 4623.53 | AL74: Has recibido un pago | AO74: Crédito | AP74: =IFERROR(VLOOKUP(M74,Shopify_Transactions!V:BB,5,0),"Not_Found") -> Not_Found | AQ74: =IFERROR(VLOOKUP(M74,Shopify_Transactions!X:BB,3,0),"Not_Found") -> Not_Found | AR74: =IFERROR(VLOOKUP(Z74,Shopify_Transactions!W:Z,4,0),"Not_Found") -> Not_Found | AS74: =IF(AP74<>"Not_Found",AP74,IF(AQ74<>"Not_Found",AQ74,AR74)) -> Not_Found
A75: 02/01/2026 | B75: 11:44:59 | C75: CET | D75: Studio 324 | E75: Pago con Pago en serie | F75: Completado | G75: EUR | H75: -51 | I75: -1.02 | J75: -52.02 | K75: info@artestaposters.com | L75: studio324info@gmail.com | M75: 93E85481XP5697051 | O75: No confirmada | Y75: 479232030Y9989809 | AA75: item_1767350658_14 | AD75: 4571.51 | AL75: Has recibido un pago | AM75: Te hemos enviado un pago por PayPal. | AO75: Cargo | AP75: =IFERROR(VLOOKUP(M75,Shopify_Transactions!V:BB,5,0),"Not_Found") -> Not_Found | AQ75: =IFERROR(VLOOKUP(M75,Shopify_Transactions!X:BB,3,0),"Not_Found") -> Not_Found | AR75: =IFERROR(VLOOKUP(Z75,Shopify_Transactions!W:Z,4,0),"Not_Found") -> Not_Found | AS75: =IF(AP75<>"Not_Found",AP75,IF(AQ75<>"Not_Found",AQ75,AR75)) -> Not_Found
A76: 02/01/2026 | B76: 11:44:59 | C76: CET | D76: PayPal | E76: Cancelación de retención de cuenta general | F76: Completado | G76: EUR | H76: 52.02 | I76: 0 | J76: 52.02 | L76: info@artestaposters.com | M76: 7ME69720N1344303T | Y76: 479232030Y9989809 | AD76: 4623.53 | AL76: Has recibido un pago | AO76: Crédito | AP76: =IFERROR(VLOOKUP(M76,Shopify_Transactions!V:BB,5,0),"Not_Found") -> Not_Found | AQ76: =IFERROR(VLOOKUP(M76,Shopify_Transactions!X:BB,3,0),"Not_Found") -> Not_Found | AR76: =IFERROR(VLOOKUP(Z76,Shopify_Transactions!W:Z,4,0),"Not_Found") -> Not_Found | AS76: =IF(AP76<>"Not_Found",AP76,IF(AQ76<>"Not_Found",AQ76,AR76)) -> Not_Found
A77: 02/01/2026 | B77: 11:45:02 | C77: CET | D77: sudevi sen | E77: Pago con Pago en serie | F77: Completado | G77: EUR | H77: -37.05 | I77: -0.74 | J77: -37.79 | K77: info@artestaposters.com | L77: sudevi.sen@gmail.com | M77: 1R404280BF411625X | O77: No confirmada | Y77: 479232030Y9989809 | AA77: item_1767350658_25 | AD77: 4585.74 | AL77: Has recibido un pago | AM77: Te hemos enviado un pago por PayPal. | AO77: Cargo | AP77: =IFERROR(VLOOKUP(M77,Shopify_Transactions!V:BB,5,0),"Not_Found") -> Not_Found | AQ77: =IFERROR(VLOOKUP(M77,Shopify_Transactions!X:BB,3,0),"Not_Found") -> Not_Found | AR77: =IFERROR(VLOOKUP(Z77,Shopify_Transactions!W:Z,4,0),"Not_Found") -> Not_Found | AS77: =IF(AP77<>"Not_Found",AP77,IF(AQ77<>"Not_Found",AQ77,AR77)) -> Not_Found
A78: 02/01/2026 | B78: 11:45:02 | C78: CET | D78: PayPal | E78: Cancelación de retención de cuenta general | F78: Completado | G78: EUR | H78: 37.79 | I78: 0 | J78: 37.79 | L78: info@artestaposters.com | M78: 5L319827LB516545M | Y78: 479232030Y9989809 | AD78: 4623.53 | AL78: Has recibido un pago | AO78: Crédito | AP78: =IFERROR(VLOOKUP(M78,Shopify_Transactions!V:BB,5,0),"Not_Found") -> Not_Found | AQ78: =IFERROR(VLOOKUP(M78,Shopify_Transactions!X:BB,3,0),"Not_Found") -> Not_Found | AR78: =IFERROR(VLOOKUP(Z78,Shopify_Transactions!W:Z,4,0),"Not_Found") -> Not_Found | AS78: =IF(AP78<>"Not_Found",AP78,IF(AQ78<>"Not_Found",AQ78,AR78)) -> Not_Found
A79: 02/01/2026 | B79: 12:34:49 | C79: CET | D79: Tilman Wegerhoff | E79: Pago con Pago exprés | F79: Completado | G79: EUR | H79: 47.9 | I79: -1.74 | J79: 46.16 | K79: twegerhoff@gmx.de | L79: info@artestaposters.com | M79: 31P07222T17634456 | N79: Tilman Wegerhoff, Hasselbeckstraße 55, Düsseldorf, 40625, Alemania | O79: Confirmada | P79: Le Chat Noir - Théophile Alexandre Steinlen - Póster / Madera negro / 30x40 | R79: 4.95 | T79: 0 | Z79: rH0wsLY87Piyy4ZOw6paI4Ekk | AA79: {"shop_id":751927347,"session_id":"rH0wsLY87Piyy4ZOw6paI4Ekk"} | AB79: 1 | AD79: 4669.69 | AE79: Hasselbeckstraße 55 | AG79: Düsseldorf | AI79: 40625 | AJ79: Alemania | AK79: +49 21122980098 | AL79: Le Chat Noir - Théophile Alexandre Steinlen - Póster / Madera negro / 30x40 | AN79: DE | AO79: Crédito | AP79: =IFERROR(VLOOKUP(M79,Shopify_Transactions!V:BB,5,0),"Not_Found") -> AS-94870 | AQ79: =IFERROR(VLOOKUP(M79,Shopify_Transactions!X:BB,3,0),"Not_Found") -> Not_Found | AR79: =IFERROR(VLOOKUP(Z79,Shopify_Transactions!W:Z,4,0),"Not_Found") -> AS-94870 | AS79: =IF(AP79<>"Not_Found",AP79,IF(AQ79<>"Not_Found",AQ79,AR79)) -> AS-94870
A80: 02/01/2026 | B80: 13:29:38 | C80: CET | D80: Lenka Köhler | E80: Pago con Pago exprés | F80: Completado | G80: EUR | H80: 31.9 | I80: -1.28 | J80: 30.62 | K80: lenka.nb23@gmail.com | L80: info@artestaposters.com | M80: 0SG88862M20909424 | N80: Lenka Köhler, Jaro Schmied-Straße 1/15, Korneuburg, 2100, Austria | O80: Confirmada | P80: I am starting to forget your face - Póster / Sin marco / 40x50 | R80: 4.95 | T80: 0 | Z80: r6uc3PjuK2KY0DcgPhXp1Imra | AA80: {"shop_id":751927347,"session_id":"r6uc3PjuK2KY0DcgPhXp1Imra"} | AB80: 1 | AD80: 4700.31 | AE80: Jaro Schmied-Straße 1/15 | AG80: Korneuburg | AI80: 2100 | AJ80: Austria | AK80: +43 6707714874 | AL80: I am starting to forget your face - Póster / Sin marco / 40x50 | AN80: AT | AO80: Crédito | AP80: =IFERROR(VLOOKUP(M80,Shopify_Transactions!V:BB,5,0),"Not_Found") -> AS-94873 | AQ80: =IFERROR(VLOOKUP(M80,Shopify_Transactions!X:BB,3,0),"Not_Found") -> Not_Found | AR80: =IFERROR(VLOOKUP(Z80,Shopify_Transactions!W:Z,4,0),"Not_Found") -> AS-94873 | AS80: =IF(AP80<>"Not_Found",AP80,IF(AQ80<>"Not_Found",AQ80,AR80)) -> AS-94873
A81: 02/01/2026 | B81: 13:56:19 | C81: CET | D81: Gabriele Vitale | E81: Pago con Pago exprés | F81: Completado | G81: EUR | H81: 64.95 | I81: -2.23 | J81: 62.72 | K81: gabrivitale70@gmail.com | L81: info@artestaposters.com | M81: 2LM55236V0071992B | N81: Gabriele Vitale, Via XXIV Maggio, 44, Rogeno, Lecco, 23849, Italia | O81: Confirmada | P81: We ride until dawn - Lienzo / Sin marco / 50x70 | R81: 0 | T81: 0 | Z81: rMI1wJsckQgokBOAlrAWKqmPS | AA81: {"shop_id":751927347,"session_id":"rMI1wJsckQgokBOAlrAWKqmPS"} | AB81: 1 | AD81: 4763.03 | AE81: Via XXIV Maggio, 44 | AG81: Rogeno | AH81: Lecco | AI81: 23849 | AJ81: Italia | AK81: +39 3331399080 | AL81: We ride until dawn - Lienzo / Sin marco / 50x70 | AN81: IT | AO81: Crédito | AP81: =IFERROR(VLOOKUP(M81,Shopify_Transactions!V:BB,5,0),"Not_Found") -> AS-94878 | AQ81: =IFERROR(VLOOKUP(M81,Shopify_Transactions!X:BB,3,0),"Not_Found") -> Not_Found | AR81: =IFERROR(VLOOKUP(Z81,Shopify_Transactions!W:Z,4,0),"Not_Found") -> AS-94878 | AS81: =IF(AP81<>"Not_Found",AP81,IF(AQ81<>"Not_Found",AQ81,AR81)) -> AS-94878
A82: 02/01/2026 | B82: 15:00:02 | C82: CET | D82: Louisa Heinzl | E82: Pago con Pago exprés | F82: Completado | G82: EUR | H82: 140.75 | I82: -4.43 | J82: 136.32 | K82: louisa.heinzl@gmx.de | L82: info@artestaposters.com | M82: 2BC65606AH721811D | N82: Louisa Heinzl, Pflügerstraße 63, Berlin, 12047, Alemania | O82: Confirmada | R82: 0 | T82: 0 | Z82: rNuYvcS9uQv7qp5PkA13MFrKI | AA82: {"shop_id":751927347,"session_id":"rNuYvcS9uQv7qp5PkA13MFrKI"} | AB82: 5 | AD82: 4899.35 | AE82: Pflügerstraße 63 | AG82: Berlin | AI82: 12047 | AJ82: Alemania | AK82: +49 1714859277 | AL82: Stripes linocut Nº5 - Terracotta - Póster / Madera roble natural / 40x50 | AN82: DE | AO82: Crédito | AP82: =IFERROR(VLOOKUP(M82,Shopify_Transactions!V:BB,5,0),"Not_Found") -> AS-94885 | AQ82: =IFERROR(VLOOKUP(M82,Shopify_Transactions!X:BB,3,0),"Not_Found") -> Not_Found | AR82: =IFERROR(VLOOKUP(Z82,Shopify_Transactions!W:Z,4,0),"Not_Found") -> AS-94885 | AS82: =IF(AP82<>"Not_Found",AP82,IF(AQ82<>"Not_Found",AQ82,AR82)) -> AS-94885
A83: 02/01/2026 | B83: 16:07:51 | C83: CET | D83: Werner Huber | E83: Pago con Pago exprés | F83: Completado | G83: EUR | H83: 24.9 | I83: -1.07 | J83: 23.83 | K83: angela.huber73@gmx.de | L83: info@artestaposters.com | M83: 5FJ12282HW147423X | N83: Werner, Huber, Keplerstr. 11, Aschheim, 85609, Alemania | O83: Confirmada | P83: Lotus Flowers (Special Edition) - Ogawa Kazumasa - Póster / Sin marco / 30x40 | R83: 4.95 | T83: 0 | Z83: reLa8i8BB1CEJyVTqDfyD9Hw2 | AA83: {"shop_id":751927347,"session_id":"reLa8i8BB1CEJyVTqDfyD9Hw2"} | AB83: 1 | AD83: 4923.18 | AE83: Keplerstr. 11 | AG83: Aschheim | AI83: 85609 | AJ83: Alemania | AK83: +49 08990468363 | AL83: Lotus Flowers (Special Edition) - Ogawa Kazumasa - Póster / Sin marco / 30x40 | AN83: DE | AO83: Crédito | AP83: =IFERROR(VLOOKUP(M83,Shopify_Transactions!V:BB,5,0),"Not_Found") -> AS-94889 | AQ83: =IFERROR(VLOOKUP(M83,Shopify_Transactions!X:BB,3,0),"Not_Found") -> Not_Found | AR83: =IFERROR(VLOOKUP(Z83,Shopify_Transactions!W:Z,4,0),"Not_Found") -> AS-94889 | AS83: =IF(AP83<>"Not_Found",AP83,IF(AQ83<>"Not_Found",AQ83,AR83)) -> AS-94889
A84: 02/01/2026 | B84: 16:30:54 | C84: CET | D84: Alexander Wäschenbach | E84: Pago con Pago exprés | F84: Completado | G84: EUR | H84: 206.91 | I84: -6.35 | J84: 200.56 | K84: a.waeschenbach@googlemail.com | L84: info@artestaposters.com | M84: 8N7957107L455913Y | N84: Alexander Wäschenbach, Holsteiner Weg 9e, Paderborn, 33102, Alemania | O84: Confirmada | P84: Bauhaus Venus yellow circle - Lienzo / Madera roble natural / 50x70, Bauhaus Black and White Exhibition Poster 1923 - Lienzo / Madera roble natural / 50x70 | R84: 0 | T84: 0 | Z84: r5lD1tOljW727n2xqlcYX4zQJ | AA84: {"shop_id":751927347,"session_id":"r5lD1tOljW727n2xqlcYX4zQJ"} | AB84: 2 | AD84: 5123.74 | AE84: Holsteiner Weg 9e | AG84: Paderborn | AI84: 33102 | AJ84: Alemania | AK84: +49 15117681631 | AL84: Bauhaus Black and White Exhibition Poster 1923 - Lienzo / Madera roble natural / 50x70 | AN84: DE | AO84: Crédito | AP84: =IFERROR(VLOOKUP(M84,Shopify_Transactions!V:BB,5,0),"Not_Found") -> AS-94891 | AQ84: =IFERROR(VLOOKUP(M84,Shopify_Transactions!X:BB,3,0),"Not_Found") -> Not_Found | AR84: =IFERROR(VLOOKUP(Z84,Shopify_Transactions!W:Z,4,0),"Not_Found") -> AS-94891 | AS84: =IF(AP84<>"Not_Found",AP84,IF(AQ84<>"Not_Found",AQ84,AR84)) -> AS-94891
A85: 02/01/2026 | B85: 16:43:59 | C85: CET | D85: Ana Rubio | E85: Pago con Pago exprés | F85: Completado | G85: EUR | H85: 89.9 | I85: -2.96 | J85: 86.94 | K85: aperez93.apr@gmail.com | L85: info@artestaposters.com | M85: 81J336877R6561446 | N85: Ana Clara Pérez Rubio, Calle de la Cepa, 4, portal 1, 2°D, Tomares, Sevilla, 41940, España | O85: Confirmada | P85: Save water drink gin - Póster / Madera negro / 20x30, PimentA&sup3 - Studio - Lienzo / Madera roble natural / 30x40 | R85: 0 | T85: 0 | Z85: rutHyvtLQ2gvCcgLPjRvB8KDz | AA85: {"shop_id":751927347,"session_id":"rutHyvtLQ2gvCcgLPjRvB8KDz"} | AB85: 2 | AD85: 5210.68 | AE85: Calle de la Cepa, 4, portal 1, 2°D | AG85: Tomares | AH85: Sevilla | AI85: 41940 | AJ85: España | AK85: +34 654845594 | AL85: Save water drink gin - Póster / Madera negro / 20x30 | AN85: ES | AO85: Crédito | AP85: =IFERROR(VLOOKUP(M85,Shopify_Transactions!V:BB,5,0),"Not_Found") -> AS-94892 | AQ85: =IFERROR(VLOOKUP(M85,Shopify_Transactions!X:BB,3,0),"Not_Found") -> Not_Found | AR85: =IFERROR(VLOOKUP(Z85,Shopify_Transactions!W:Z,4,0),"Not_Found") -> AS-94892 | AS85: =IF(AP85<>"Not_Found",AP85,IF(AQ85<>"Not_Found",AQ85,AR85)) -> AS-94892
A86: 02/01/2026 | B86: 18:29:48 | C86: CET | D86: Stefan Leuthmetzer | E86: Pago con Pago exprés | F86: Completado | G86: EUR | H86: 97.11 | I86: -3.17 | J86: 93.94 | K86: steve.leuthmetzer@web.de | L86: info@artestaposters.com | M86: 0UE16469GN9970209 | N86: Stefan Leuthmetzer, Fourlanigasse 33, Theresienfeld, 2604, Austria | O86: Confirmada | P86: Lemon - Athene Fritsch - Póster / Madera roble natural / 30x40, A thousand birds - Lienzo / Sin marco / 50x70 | R86: 0 | T86: 0 | Z86: r0wVV6nw7SaC6w038nlVgSknr | AA86: {"shop_id":751927347,"session_id":"r0wVV6nw7SaC6w038nlVgSknr"} | AB86: 2 | AD86: 5304.62 | AE86: Fourlanigasse 33 | AG86: Theresienfeld | AI86: 2604 | AJ86: Austria | AK86: +43 6647850413 | AL86: A thousand birds - Lienzo / Sin marco / 50x70 | AN86: AT | AO86: Crédito | AP86: =IFERROR(VLOOKUP(M86,Shopify_Transactions!V:BB,5,0),"Not_Found") -> AS-94902 | AQ86: =IFERROR(VLOOKUP(M86,Shopify_Transactions!X:BB,3,0),"Not_Found") -> Not_Found | AR86: =IFERROR(VLOOKUP(Z86,Shopify_Transactions!W:Z,4,0),"Not_Found") -> AS-94902 | AS86: =IF(AP86<>"Not_Found",AP86,IF(AQ86<>"Not_Found",AQ86,AR86)) -> AS-94902
A87: 02/01/2026 | B87: 21:01:31 | C87: CET | D87: Francesca Volta | E87: Pago con Pago exprés | F87: Completado | G87: EUR | H87: 51.57 | I87: -1.85 | J87: 49.72 | K87: francesca.volta@gmail.com | L87: info@artestaposters.com | M87: 1DS041384X621404D | N87: Francesca Volta, Via Giuseppe Manfredi 77, Piacenza, Piacenza, 29122, Italia | O87: Confirmada | P87: Hands - Walk with me - Póster / Sin marco / 20x30, Cheers To You - Arty Guava - Póster / Sin marco / 20x30, Maddies Mood - jotadejai - Póster / Sin marco / 20x30, Holiday in a glass 1 - Póster / Sin marco / 20x30 | R87: 4.95 | T87: 0 | Z87: rjiEbAwEonWmIFxbF8kszG77E | AA87: {"shop_id":751927347,"session_id":"rjiEbAwEonWmIFxbF8kszG77E"} | AB87: 4 | AD87: 5354.34 | AE87: Via Giuseppe Manfredi 77 | AG87: Piacenza | AH87: Piacenza | AI87: 29122 | AJ87: Italia | AK87: +39 3334387687 | AL87: Hands - Walk with me - Póster / Sin marco / 20x30 | AN87: IT | AO87: Crédito | AP87: =IFERROR(VLOOKUP(M87,Shopify_Transactions!V:BB,5,0),"Not_Found") -> AS-94914 | AQ87: =IFERROR(VLOOKUP(M87,Shopify_Transactions!X:BB,3,0),"Not_Found") -> Not_Found | AR87: =IFERROR(VLOOKUP(Z87,Shopify_Transactions!W:Z,4,0),"Not_Found") -> AS-94914 | AS87: =IF(AP87<>"Not_Found",AP87,IF(AQ87<>"Not_Found",AQ87,AR87)) -> AS-94914
A88: 02/01/2026 | B88: 21:31:20 | C88: CET | D88: Matthias Burkhardt | E88: Pago con Pago exprés | F88: Completado | G88: EUR | H88: 37.9 | I88: -1.45 | J88: 36.45 | K88: matthias0577@googlemail.com | L88: info@artestaposters.com | M88: 6FS01087VG082243S | N88: Matthias Burkhardt, Lochhamer Str. 75, Gräfelfing, 82166, Alemania | O88: Confirmada | P88: Gustav Klimt Garden Cat Print - Póster / Sin marco / 50x70 | R88: 4.95 | T88: 0 | Z88: ret27jTOqzWh6UHL8EJQFwbJS | AA88: {"shop_id":751927347,"session_id":"ret27jTOqzWh6UHL8EJQFwbJS"} | AB88: 1 | AD88: 5390.79 | AE88: Lochhamer Str. 75 | AG88: Gräfelfing | AI88: 82166 | AJ88: Alemania | AK88: +49 1744180292 | AL88: Gustav Klimt Garden Cat Print - Póster / Sin marco / 50x70 | AN88: DE | AO88: Crédito | AP88: =IFERROR(VLOOKUP(M88,Shopify_Transactions!V:BB,5,0),"Not_Found") -> AS-94918 | AQ88: =IFERROR(VLOOKUP(M88,Shopify_Transactions!X:BB,3,0),"Not_Found") -> Not_Found | AR88: =IFERROR(VLOOKUP(Z88,Shopify_Transactions!W:Z,4,0),"Not_Found") -> AS-94918 | AS88: =IF(AP88<>"Not_Found",AP88,IF(AQ88<>"Not_Found",AQ88,AR88)) -> AS-94918
A89: 02/01/2026 | B89: 21:41:06 | C89: CET | D89: Andrea Walther | E89: Pago con Pago exprés | F89: Completado | G89: EUR | H89: 31.9 | I89: -1.28 | J89: 30.62 | K89: AndreaWalther1@gmx.de | L89: info@artestaposters.com | M89: 8SA56231RB1621238 | N89: Andrea, Walther, Spinnereistraße 32, markkleeberg, 04416, Alemania | O89: Confirmada | P89: Le marche fermier - cantaloup - Póster / Sin marco / 40x50 | R89: 4.95 | T89: 0 | Z89: rdHLmlMu6WBOS3BsLHagTqGHD | AA89: {"shop_id":751927347,"session_id":"rdHLmlMu6WBOS3BsLHagTqGHD"} | AB89: 1 | AD89: 5421.41 | AE89: Spinnereistraße 32 | AG89: markkleeberg | AI89: 4416 | AJ89: Alemania | AK89: +49 3413502996 | AL89: Le marche fermier - cantaloup - Póster / Sin marco / 40x50 | AN89: DE | AO89: Crédito | AP89: =IFERROR(VLOOKUP(M89,Shopify_Transactions!V:BB,5,0),"Not_Found") -> AS-94919 | AQ89: =IFERROR(VLOOKUP(M89,Shopify_Transactions!X:BB,3,0),"Not_Found") -> Not_Found | AR89: =IFERROR(VLOOKUP(Z89,Shopify_Transactions!W:Z,4,0),"Not_Found") -> AS-94919 | AS89: =IF(AP89<>"Not_Found",AP89,IF(AQ89<>"Not_Found",AQ89,AR89)) -> AS-94919
A90: 02/01/2026 | B90: 21:41:38 | C90: CET | D90: Laura SEVERAC | E90: Pago con Pago exprés | F90: Completado | G90: EUR | H90: 99.95 | I90: -3.25 | J90: 96.7 | K90: severac.laura.ima@gmail.com | L90: info@artestaposters.com | M90: 8MB87525WC1135818 | N90: Laura Severac, 7 RUE DU PUITS CLOS, ST RUSTICE, 31620, Francia | O90: Confirmada | P90: Nighthawks (Special Edition) - Edward Hopper - Póster / Madera negro / 70x100 | R90: 0 | T90: 0 | Z90: rvahAGHchv7jM7kfe8FvpMqR5 | AA90: {"shop_id":751927347,"session_id":"rvahAGHchv7jM7kfe8FvpMqR5"} | AB90: 1 | AD90: 5518.11 | AE90: 7 RUE DU PUITS CLOS | AG90: ST RUSTICE | AI90: 31620 | AJ90: Francia | AK90: +33 609385932 | AL90: Nighthawks (Special Edition) - Edward Hopper - Póster / Madera negro / 70x100 | AN90: FR | AO90: Crédito | AP90: =IFERROR(VLOOKUP(M90,Shopify_Transactions!V:BB,5,0),"Not_Found") -> AS-94920 | AQ90: =IFERROR(VLOOKUP(M90,Shopify_Transactions!X:BB,3,0),"Not_Found") -> Not_Found | AR90: =IFERROR(VLOOKUP(Z90,Shopify_Transactions!W:Z,4,0),"Not_Found") -> AS-94920 | AS90: =IF(AP90<>"Not_Found",AP90,IF(AQ90<>"Not_Found",AQ90,AR90)) -> AS-94920
A91: 02/01/2026 | B91: 22:46:03 | C91: CET | D91: AMADOR ZORRILLA LOPEZ | E91: Pago con Pago exprés | F91: Completado | G91: EUR | H91: 98.85 | I91: -3.22 | J91: 95.63 | K91: amadorzorrilla@hotmail.com | L91: info@artestaposters.com | M91: 5CE80692BF644000W | N91: KARMAYNOA SL, calle juan trejo 1 bajo, TARIFA, Cádiz, 11380, España | O91: Confirmada | P91: Chirping And Chilling (At Night) - Póster / Sin marco / 50x70, Watercolor Landscape N 21 - Póster / Sin marco / 50x70, Sunlight - Póster / Sin marco / 50x70 | R91: 0 | T91: 0 | Z91: r39nQjLuTX8JH9qKsvxADnyTd | AA91: {"shop_id":751927347,"session_id":"r39nQjLuTX8JH9qKsvxADnyTd"} | AB91: 3 | AD91: 5613.74 | AE91: calle juan trejo 1 bajo | AG91: TARIFA | AH91: Cádiz | AI91: 11380 | AJ91: España | AK91: +34 630756640 | AL91: Sunlight - Póster / Sin marco / 50x70 | AN91: ES | AO91: Crédito | AP91: =IFERROR(VLOOKUP(M91,Shopify_Transactions!V:BB,5,0),"Not_Found") -> AS-94927 | AQ91: =IFERROR(VLOOKUP(M91,Shopify_Transactions!X:BB,3,0),"Not_Found") -> Not_Found | AR91: =IFERROR(VLOOKUP(Z91,Shopify_Transactions!W:Z,4,0),"Not_Found") -> AS-94927 | AS91: =IF(AP91<>"Not_Found",AP91,IF(AQ91<>"Not_Found",AQ91,AR91)) -> AS-94927
A92: 02/01/2026 | B92: 23:00:31 | C92: CET | D92: Lina Gombert | E92: Pago con Pago exprés | F92: Completado | G92: EUR | H92: 65.9 | I92: -2.26 | J92: 63.64 | K92: lina.gombert@gmx.de | L92: info@artestaposters.com | M92: 10U482918R585952L | N92: Gombert, Lina, Meißnerstr. 2b, Hamburg, 20259, Alemania | O92: Confirmada | P92: Yayoi Kusama End Of The Fields exhibition poster - Póster / Sin marco / 50x70, RETRO GRAPHIC NO.1 - The Art Concept - Póster / Sin marco / 50x70 | R92: 0 | T92: 0 | Z92: rwaUHxsw4H2gswnHjel35VyAP | AA92: {"shop_id":751927347,"session_id":"rwaUHxsw4H2gswnHjel35VyAP"} | AB92: 2 | AD92: 5677.38 | AE92: Meißnerstr. 2b | AG92: Hamburg | AI92: 20259 | AJ92: Alemania | AK92: +49 17662760172 | AL92: RETRO GRAPHIC NO.1 - The Art Concept - Póster / Sin marco / 50x70 | AN92: DE | AO92: Crédito | AP92: =IFERROR(VLOOKUP(M92,Shopify_Transactions!V:BB,5,0),"Not_Found") -> AS-94930 | AQ92: =IFERROR(VLOOKUP(M92,Shopify_Transactions!X:BB,3,0),"Not_Found") -> Not_Found | AR92: =IFERROR(VLOOKUP(Z92,Shopify_Transactions!W:Z,4,0),"Not_Found") -> AS-94930 | AS92: =IF(AP92<>"Not_Found",AP92,IF(AQ92<>"Not_Found",AQ92,AR92)) -> AS-94930
A93: 03/01/2026 | B93: 00:46:01 | C93: CET | D93: JUAN ATERO GOMEZ | E93: Pago con Pago exprés | F93: Completado | G93: EUR | H93: 84.95 | I93: -2.81 | J93: 82.14 | K93: juan.atero.g@gmail.com | L93: info@artestaposters.com | M93: 13G125280N556394C | N93: JUAN ATERO CLINICA U. NAVARRA (Entrega L a V de 8 a 14h), Calle del Marquesado de Santa Marta 1, Madrid, Madrid, 28027, España | O93: Confirmada | P93: Madrid - Póster / Madera blanco / 60x90 | R93: 0 | T93: 0 | Z93: rTHJBsWfcgUCM3H7WQUKSznVr | AA93: {"shop_id":751927347,"session_id":"rTHJBsWfcgUCM3H7WQUKSznVr"} | AB93: 1 | AD93: 5759.52 | AE93: Calle del Marquesado de Santa Marta 1 | AG93: Madrid | AH93: Madrid | AI93: 28027 | AJ93: España | AK93: +34 627529132 | AL93: Madrid - Póster / Madera blanco / 60x90 | AN93: ES | AO93: Crédito | AP93: =IFERROR(VLOOKUP(M93,Shopify_Transactions!V:BB,5,0),"Not_Found") -> AS-94935 | AQ93: =IFERROR(VLOOKUP(M93,Shopify_Transactions!X:BB,3,0),"Not_Found") -> Not_Found | AR93: =IFERROR(VLOOKUP(Z93,Shopify_Transactions!W:Z,4,0),"Not_Found") -> AS-94935 | AS93: =IF(AP93<>"Not_Found",AP93,IF(AQ93<>"Not_Found",AQ93,AR93)) -> AS-94935
A94: 03/01/2026 | B94: 04:05:06 | C94: CET | D94: Mirko Laux | E94: Pago con Pago exprés | F94: Completado | G94: EUR | H94: 229.37 | I94: -7 | J94: 222.37 | K94: mirko.laux@gmx.de | L94: info@artestaposters.com | M94: 4GP295169T9239300 | N94: Mirko Umberto Laux, Kleyerstr. 1, Appartement 203, Frankfurt, 60326, Alemania | O94: Confirmada | R94: 0 | T94: 0 | Z94: rq6P4MvWp1qKLDWYHvS7lVSfw | AA94: {"shop_id":751927347,"session_id":"rq6P4MvWp1qKLDWYHvS7lVSfw"} | AB94: 3 | AD94: 5981.89 | AE94: Kleyerstr. 1, Appartement 203 | AG94: Frankfurt | AI94: 60326 | AJ94: Alemania | AK94: +49 01726782566 | AL94: Peonies and Canary Exhibition - Katsushika Hokusai - Póster / Madera roble natural / 60x90 | AN94: DE | AO94: Crédito | AP94: =IFERROR(VLOOKUP(M94,Shopify_Transactions!V:BB,5,0),"Not_Found") -> AS-94936 | AQ94: =IFERROR(VLOOKUP(M94,Shopify_Transactions!X:BB,3,0),"Not_Found") -> Not_Found | AR94: =IFERROR(VLOOKUP(Z94,Shopify_Transactions!W:Z,4,0),"Not_Found") -> AS-94936 | AS94: =IF(AP94<>"Not_Found",AP94,IF(AQ94<>"Not_Found",AQ94,AR94)) -> AS-94936
A95: 03/01/2026 | B95: 13:21:43 | C95: CET | D95: Johanna Hornung | E95: Pago con Pago exprés | F95: Completado | G95: EUR | H95: 72.85 | I95: -2.46 | J95: 70.39 | K95: johanna.hornung@gmx.net | L95: info@artestaposters.com | M95: 6S5127504P879684R | N95: Johanna Hornung, Lembekstr. 5b, Hamburg, 22529, Alemania | O95: Confirmada | P95: Minimal Abstract Fuschia Colorfield Painting 01 - Póster / Sin marco / 50x70, Do Epic Shit - Póster / Sin marco / 30x40, Maddies Mood - jotadejai - Póster / Sin marco / 30x40 | R95: 0 | T95: 0 | Z95: r6RYzp8QxgTepTqDi7jgfOWYq | AA95: {"shop_id":751927347,"session_id":"r6RYzp8QxgTepTqDi7jgfOWYq"} | AB95: 3 | AD95: 6052.28 | AE95: Lembekstr. 5b | AG95: Hamburg | AI95: 22529 | AJ95: Alemania | AK95: +49 1704835227 | AL95: Do Epic Shit - Póster / Sin marco / 30x40 | AN95: DE | AO95: Crédito | AP95: =IFERROR(VLOOKUP(M95,Shopify_Transactions!V:BB,5,0),"Not_Found") -> AS-94948 | AQ95: =IFERROR(VLOOKUP(M95,Shopify_Transactions!X:BB,3,0),"Not_Found") -> Not_Found | AR95: =IFERROR(VLOOKUP(Z95,Shopify_Transactions!W:Z,4,0),"Not_Found") -> AS-94948 | AS95: =IF(AP95<>"Not_Found",AP95,IF(AQ95<>"Not_Found",AQ95,AR95)) -> AS-94948
A96: 03/01/2026 | B96: 14:04:43 | C96: CET | D96: Charlotte KREBS | E96: Pago con Pago exprés | F96: Completado | G96: EUR | H96: 99.95 | I96: -3.25 | J96: 96.7 | K96: charlottekrebs@gmail.com | L96: info@artestaposters.com | M96: 6UM06312TP540590E | N96: Charlotte Krebs, 14 Rue Jean-Macé, Paris, 75011, Francia | O96: Confirmada | P96: Bauhaus Exhibition Poster 1923 - Póster / Madera roble natural / 70x100 | R96: 0 | T96: 0 | Z96: ruzP7ZTqiwdrDOYxc9UKxshqz | AA96: {"shop_id":751927347,"session_id":"ruzP7ZTqiwdrDOYxc9UKxshqz"} | AB96: 1 | AD96: 6148.98 | AE96: 14 Rue Jean-Macé | AG96: Paris | AI96: 75011 | AJ96: Francia | AK96: +33 607757797 | AL96: Bauhaus Exhibition Poster 1923 - Póster / Madera roble natural / 70x100 | AN96: FR | AO96: Crédito | AP96: =IFERROR(VLOOKUP(M96,Shopify_Transactions!V:BB,5,0),"Not_Found") -> AS-94950 | AQ96: =IFERROR(VLOOKUP(M96,Shopify_Transactions!X:BB,3,0),"Not_Found") -> Not_Found | AR96: =IFERROR(VLOOKUP(Z96,Shopify_Transactions!W:Z,4,0),"Not_Found") -> AS-94950 | AS96: =IF(AP96<>"Not_Found",AP96,IF(AQ96<>"Not_Found",AQ96,AR96)) -> AS-94950
A97: 03/01/2026 | B97: 14:19:17 | C97: CET | D97: Tanja Rolli | E97: Pago con Pago exprés | F97: Completado | G97: EUR | H97: 44.46 | I97: -1.64 | J97: 42.82 | K97: rollita@me.com | L97: info@artestaposters.com | M97: 8X621545ES520023G | N97: Tanja Rolli, Kinzigstr. 1, Hambrücken, 76707, Alemania | O97: Confirmada | P97: Pablo Picasso Animals Drawings the elephant - Póster / Sin marco / 40x50, Colgador para póster de 40cm de madera y color roble | R97: 4.95 | T97: 0 | Z97: rySrSkHOKe3niSjHIt9t8QmkL | AA97: {"shop_id":751927347,"session_id":"rySrSkHOKe3niSjHIt9t8QmkL"} | AB97: 2 | AD97: 6191.8 | AE97: Kinzigstr. 1 | AG97: Hambrücken | AI97: 76707 | AJ97: Alemania | AK97: +49 15734288022 | AL97: Pablo Picasso Animals Drawings the elephant - Póster / Sin marco / 40x50 | AN97: DE | AO97: Crédito | AP97: =IFERROR(VLOOKUP(M97,Shopify_Transactions!V:BB,5,0),"Not_Found") -> AS-94951 | AQ97: =IFERROR(VLOOKUP(M97,Shopify_Transactions!X:BB,3,0),"Not_Found") -> Not_Found | AR97: =IFERROR(VLOOKUP(Z97,Shopify_Transactions!W:Z,4,0),"Not_Found") -> AS-94951 | AS97: =IF(AP97<>"Not_Found",AP97,IF(AQ97<>"Not_Found",AQ97,AR97)) -> AS-94951
A98: 03/01/2026 | B98: 14:19:54 | C98: CET | D98: Sylvie Penalva | E98: Pago con Pago exprés | F98: Completado | G98: EUR | H98: 17.9 | I98: -0.87 | J98: 17.03 | K98: sylvie.penalva@outlook.fr | L98: info@artestaposters.com | M98: 3H020591E9627515X | N98: Sylvie, Penalva, 25 RUE DE LA PIERRE BLEUE, DIETWILLER, 68440, Francia | O98: Confirmada | P98: Five in the Bed - Sharyn Bursic - Póster / Sin marco / 20x30 | R98: 4.95 | T98: 0 | Z98: rfCjPSSIlm5l367PxVy7X0dhJ | AA98: {"shop_id":751927347,"session_id":"rfCjPSSIlm5l367PxVy7X0dhJ"} | AB98: 1 | AD98: 6208.83 | AE98: 25 RUE DE LA PIERRE BLEUE | AG98: DIETWILLER | AI98: 68440 | AJ98: Francia | AK98: +33 656724234 | AL98: Five in the Bed - Sharyn Bursic - Póster / Sin marco / 20x30 | AN98: FR | AO98: Crédito | AP98: =IFERROR(VLOOKUP(M98,Shopify_Transactions!V:BB,5,0),"Not_Found") -> AS-94952 | AQ98: =IFERROR(VLOOKUP(M98,Shopify_Transactions!X:BB,3,0),"Not_Found") -> Not_Found | AR98: =IFERROR(VLOOKUP(Z98,Shopify_Transactions!W:Z,4,0),"Not_Found") -> AS-94952 | AS98: =IF(AP98<>"Not_Found",AP98,IF(AQ98<>"Not_Found",AQ98,AR98)) -> AS-94952
A99: 03/01/2026 | B99: 14:25:39 | C99: CET | D99: Robert Walz | E99: Pago con Pago exprés | F99: Completado | G99: EUR | H99: 179.91 | I99: -5.57 | J99: 174.34 | K99: robertwalz@gmx.de | L99: info@artestaposters.com | M99: 6EN75623SE162971H | N99: Robert Walz, 2, Hösbach, 63768, Alemania | O99: Confirmada | P99: Pablo Picasso Animals Drawings Dove La colombe de paix - Lienzo / Sin marco / 70x100, Pablo Picasso Animals Drawings the elephant - Lienzo / Sin marco / 70x100 | R99: 0 | T99: 0 | Z99: ruhrd8qtxm5cmUEuewthdTPxc | AA99: {"shop_id":751927347,"session_id":"ruhrd8qtxm5cmUEuewthdTPxc"} | AB99: 2 | AD99: 6383.17 | AE99: 2 | AG99: Hösbach | AI99: 63768 | AJ99: Alemania | AK99: +49 060214941612 | AL99: Pablo Picasso Animals Drawings the elephant - Lienzo / Sin marco / 70x100 | AN99: DE | AO99: Crédito | AP99: =IFERROR(VLOOKUP(M99,Shopify_Transactions!V:BB,5,0),"Not_Found") -> AS-94954 | AQ99: =IFERROR(VLOOKUP(M99,Shopify_Transactions!X:BB,3,0),"Not_Found") -> Not_Found | AR99: =IFERROR(VLOOKUP(Z99,Shopify_Transactions!W:Z,4,0),"Not_Found") -> AS-94954 | AS99: =IF(AP99<>"Not_Found",AP99,IF(AQ99<>"Not_Found",AQ99,AR99)) -> AS-94954
A100: 03/01/2026 | B100: 15:49:58 | C100: CET | D100: Elisa Zulian | E100: Pago con Pago exprés | F100: Completado | G100: EUR | H100: 49.9 | I100: -1.8 | J100: 48.1 | K100: elisa.zulian@gmail.com | L100: info@artestaposters.com | M100: 9TP050217H447571G | N100: Giuliana Manfrellotti, Via Raffaele Cadorna 19/c, Torino, Turín, 10136, Italia | O100: Confirmada | P100: Maddies Mood - jotadejai - Póster / Sin marco / 70x100 | R100: 4.95 | T100: 0 | Z100: rZP46XzrMGjZXKqJWxXBq6F33 | AA100: {"shop_id":751927347,"session_id":"rZP46XzrMGjZXKqJWxXBq6F33"} | AB100: 1 | AD100: 6431.27 | AE100: Via Raffaele Cadorna 19/c | AG100: Torino | AH100: Turín | AI100: 10136 | AJ100: Italia | AK100: +39 3343532593 | AL100: Maddies Mood - jotadejai - Póster / Sin marco / 70x100 | AN100: IT | AO100: Crédito | AP100: =IFERROR(VLOOKUP(M100,Shopify_Transactions!V:BB,5,0),"Not_Found") -> AS-94964 | AQ100: =IFERROR(VLOOKUP(M100,Shopify_Transactions!X:BB,3,0),"Not_Found") -> Not_Found | AR100: =IFERROR(VLOOKUP(Z100,Shopify_Transactions!W:Z,4,0),"Not_Found") -> AS-94964 | AS100: =IF(AP100<>"Not_Found",AP100,IF(AQ100<>"Not_Found",AQ100,AR100)) -> AS-94964
...

Sheet Shopify_Transactions
A1: order_name | B1: order_month_yyyymm | C1: payment_gateway_names | D1: tags | E1: shipping_country_code | F1: shipping_state_code | G1: standard_rate | H1: tax_rate | I1: payment_currency | J1: imp_tax | K1: imp_gross | L1: imp_net | M1: gateway_filter | N1: order_id | O1: transaction_id | P1: gateway | Q1: kind | R1: status | S1: processed_at | T1: amount | U1: currency | V1: authorization_code | W1: payment_id | X1: gateway_transaction_id | Y1: receipt_json | Z1: Pedido
A2: AS-95859 | B2: 202601 | C2: ["shopify_payments"] | E2: AT | G2: 0.2 | H2: 0.2 | I2: EUR | J2: 6.32 | K2: 37.9 | L2: 31.58 | M2: shopify_payments | N2: gid://shopify/Order/7426608431442 | O2: gid://shopify/OrderTransaction/8599963369810 | P2: shopify_payments | Q2: SALE | R2: SUCCESS | S2: 2026-01-13T18:10:18Z | T2: 37.9 | U2: EUR | V2: py_3SpC2oIkWweOM9jA0M9Sd6qA | W2: ryRAmJLD1ZVCPmmkRasoWYlsz | X2: pi_3SpC2oIkWweOM9jA02NWFee1 | Y2: "{\"id\":\"pi_3SpC2oIkWweOM9jA02NWFee1\",\"object\":\"payment_intent\",\"amount\":3790,\"amount_capturable\":0,\"amount_received\":3790,\"canceled_at\":null,\"cancellation_reason\":null,\"capture_method\":\"automatic\",\"charges\":{\"object\":\"list\",\"data\":[{\"id\":\"py_3SpC2oIkWweOM9jA0M9Sd6qA\",\"object\":\"charge\",\"amount\":3790,\"application_fee\":\"fee_1SpC5KIkWweOM9jASFaEo78M\",\"balance_transaction\":\"txn_3SpC2oIkWweOM9jA09HrGYAx\",\"captured\":true,\"created\":1768327974,\"currency\":\"eur\",\"failure_code\":null,\"failure_message\":null,\"fraud_details\":{},\"livemode\":true,\"metadata\":{\"payments_extension_type\":\"klarna\",\"payments_extension\":\"true\",\"shop_id\":\"751927347\",\"reconciliation_flow\":\"payments_api\",\"payment_id\":\"ryRAmJLD1ZVCPmmkRasoWYlsz\"},\"outcome\":{\"advice_code\":null,\"network_advice_code\":null,\"network_decline_code\":null,\"network_status\":\"approved_by_network\",\"reason\":null,\"risk_level\":\"not_assessed\",\"seller_message\":\"Payment complete.\",\"type\":\"authorized\"},\"paid\":true,\"payment_intent\":\"pi_3SpC2oIkWweOM9jA02NWFee1\",\"payment_method\":\"pm_1SpC2oIkWweOM9jA2EYptUeA\",\"payment_method_details\":{\"klarna\":{\"payer_details\":{\"address\":{\"country\":\"AT\"}},\"payment_method_category\":\"pay_now\",\"preferred_locale\":\"de-AT\"},\"type\":\"klarna\"},\"refunded\":false,\"source\":null,\"status\":\"succeeded\"}],\"has_more\":false,\"total_count\":1,\"url\":\"\\/v1\\/charges?payment_intent=pi_3SpC2oIkWweOM9jA02NWFee1\"},\"latest_charge\":\"py_3SpC2oIkWweOM9jA0M9Sd6qA\",\"confirmation_method\":\"automatic\",\"created\":1768327818,\"currency\":\"eur\",\"customer\":null,\"last_payment_error\":null,\"livemode\":true,\"metadata\":{\"payments_extension_type\":\"klarna\",\"payments_extension\":\"true\",\"shop_id\":\"751927347\",\"reconciliation_flow\":\"payments_api\",\"payment_id\":\"ryRAmJLD1ZVCPmmkRasoWYlsz\"},\"next_action\":null,\"payment_method\":\"pm_1SpC2oIkWweOM9jA2EYptUeA\",\"payment_method_types\":[\"klarna\"],\"source\":null,\"status\":\"succeeded\"}" | Z2: =+A2 -> AS-95859
A3: AS-95104 | B3: 202601 | C3: ["shopify_payments"] | E3: DE | G3: 0.19 | H3: 0.19 | I3: EUR | J3: 8.77 | K3: 54.9 | L3: 46.13 | M3: shopify_payments | N3: gid://shopify/Order/7400359297362 | O3: gid://shopify/OrderTransaction/8464260399442 | P3: shopify_payments | Q3: SALE | R3: FAILURE | S3: 2025-12-08T10:56:03Z | T3: 299.95 | U3: EUR | W3: rlbbRIqxd8gUU8YFKiAIBOirS | X3: pi_3Sc26pIkWweOM9jA2jq2XrrO | Y3: "{\"id\":\"pi_3Sc26pIkWweOM9jA2jq2XrrO\",\"object\":\"payment_intent\",\"amount\":29995,\"amount_capturable\":0,\"amount_received\":0,\"canceled_at\":null,\"cancellation_reason\":null,\"capture_method\":\"automatic\",\"latest_charge\":null,\"confirmation_method\":\"manual\",\"created\":1765191363,\"currency\":\"eur\",\"customer\":null,\"last_payment_error\":null,\"livemode\":true,\"metadata\":{\"payment_id\":\"rlbbRIqxd8gUU8YFKiAIBOirS\",\"payments_extension\":\"true\",\"payments_extension_type\":\"card\",\"reconciliation_flow\":\"payments_api\",\"shop_id\":\"751927347\"},\"next_action\":{\"redirect_to_url\":{\"return_url\":\"https:\\/\\/artestastore.com\\/payment_providers\\/stripe\\/card\\/redirect\\/complete?session_id=rlbbRIqxd8gUU8YFKiAIBOirS\",\"url\":\"https:\\/\\/hooks.stripe.com\\/3d_secure_2\\/hosted?merchant=acct_1DdFjfIkWweOM9jA\\u0026payment_intent=pi_3Sc26pIkWweOM9jA2jq2XrrO\\u0026payment_intent_client_secret=pi_3Sc26pIkWweOM9jA2jq2XrrO_secret_ef4S0PGR9zevFMntKoouiqU0H\\u0026publishable_key=pk_live_xwMOVE2fmfvPMkkSA3diVqSq\\u0026source=payatt_3Sc26pIkWweOM9jA2A6pOFn0\\u0026stripe_account=acct_1DdFjfIkWweOM9jA\"},\"type\":\"redirect_to_url\"},\"payment_method\":\"pm_1Sc26pIkWweOM9jA9F5CtScT\",\"payment_method_types\":[\"card\"],\"source\":null,\"status\":\"requires_action\"}" | Z3: =+A3 -> AS-95104
A4: AS-95104 | B4: 202601 | C4: ["shopify_payments"] | E4: DE | G4: 0.19 | H4: 0.19 | I4: EUR | J4: 8.77 | K4: 54.9 | L4: 46.13 | M4: shopify_payments | N4: gid://shopify/Order/7400359297362 | O4: gid://shopify/OrderTransaction/8577337262418 | P4: shopify_payments | Q4: SALE | R4: SUCCESS | S4: 2026-01-05T06:24:45Z | T4: 54.9 | U4: EUR | V4: py_3Sm7DdIkWweOM9jA2V1yK6Z5 | W4: rP0NRLxBDWnejnIkCERZUXsx6 | X4: py_3Sm7DdIkWweOM9jA2V1yK6Z5 | Y4: "{\"id\":\"py_3Sm7DdIkWweOM9jA2V1yK6Z5\",\"object\":\"charge\",\"amount\":5490,\"application_fee\":\"fee_1Sm7EwIkWweOM9jANfClgved\",\"balance_transaction\":\"txn_3Sm7DdIkWweOM9jA2UlNKmRt\",\"captured\":true,\"created\":1767594366,\"currency\":\"eur\",\"failure_code\":null,\"failure_message\":null,\"fraud_details\":{},\"livemode\":true,\"metadata\":{\"payments_extension_type\":\"klarna\",\"reconciliation_flow\":\"payments_api\",\"shop_id\":\"751927347\",\"payments_extension\":\"true\",\"payment_id\":\"rP0NRLxBDWnejnIkCERZUXsx6\"},\"outcome\":{\"advice_code\":null,\"network_advice_code\":null,\"network_decline_code\":null,\"network_status\":\"approved_by_network\",\"reason\":null,\"risk_level\":\"not_assessed\",\"seller_message\":\"Payment complete.\",\"type\":\"authorized\"},\"paid\":true,\"payment_intent\":\"pi_3Sm7DdIkWweOM9jA20Gsbkf6\",\"payment_method\":\"pm_1Sm7DdIkWweOM9jAaGOpLufk\",\"payment_method_details\":{\"klarna\":{\"payer_details\":{\"address\":{\"country\":\"DE\"}},\"payment_method_category\":\"pay_later\",\"preferred_locale\":\"de-DE\"},\"type\":\"klarna\"},\"refunded\":false,\"source\":null,\"status\":\"succeeded\"}" | Z4: =+A4 -> AS-95104
A5: AS-95870 | B5: 202601 | C5: ["shopify_payments"] | E5: DE | G5: 0.19 | H5: 0.19 | I5: EUR | J5: 10.52 | K5: 65.9 | L5: 55.38 | M5: shopify_payments | N5: gid://shopify/Order/7426812576082 | O5: gid://shopify/OrderTransaction/8600215552338 | P5: shopify_payments | Q5: SALE | R5: SUCCESS | S5: 2026-01-13T20:03:19Z | T5: 65.9 | U5: EUR | V5: py_3SpDoCIkWweOM9jA1lSznUf1 | W5: rz5DDrJfvXuxGAl6nxxD9lbx2 | X5: pi_3SpDoCIkWweOM9jA1ILkq7VU | Y5: "{\"id\":\"pi_3SpDoCIkWweOM9jA1ILkq7VU\",\"object\":\"payment_intent\",\"amount\":6590,\"amount_capturable\":0,\"amount_received\":6590,\"canceled_at\":null,\"cancellation_reason\":null,\"capture_method\":\"automatic\",\"charges\":{\"object\":\"list\",\"data\":[{\"id\":\"py_3SpDoCIkWweOM9jA1lSznUf1\",\"object\":\"charge\",\"amount\":6590,\"application_fee\":\"fee_1SpDpLIkWweOM9jANuw67Ln2\",\"balance_transaction\":\"txn_3SpDoCIkWweOM9jA18LvrbSn\",\"captured\":true,\"created\":1768334671,\"currency\":\"eur\",\"failure_code\":null,\"failure_message\":null,\"fraud_details\":{},\"livemode\":true,\"metadata\":{\"payments_extension_type\":\"klarna\",\"reconciliation_flow\":\"payments_api\",\"shop_id\":\"751927347\",\"payments_extension\":\"true\",\"payment_id\":\"rz5DDrJfvXuxGAl6nxxD9lbx2\"},\"outcome\":{\"advice_code\":null,\"network_advice_code\":null,\"network_decline_code\":null,\"network_status\":\"approved_by_network\",\"reason\":null,\"risk_level\":\"not_assessed\",\"seller_message\":\"Payment complete.\",\"type\":\"authorized\"},\"paid\":true,\"payment_intent\":\"pi_3SpDoCIkWweOM9jA1ILkq7VU\",\"payment_method\":\"pm_1SpDoCIkWweOM9jAc50ynxkb\",\"payment_method_details\":{\"klarna\":{\"payer_details\":{\"address\":{\"country\":\"DE\"}},\"payment_method_category\":\"pay_later\",\"preferred_locale\":\"de-DE\"},\"type\":\"klarna\"},\"refunded\":false,\"source\":null,\"status\":\"succeeded\"}],\"has_more\":false,\"total_count\":1,\"url\":\"\\/v1\\/charges?payment_intent=pi_3SpDoCIkWweOM9jA1ILkq7VU\"},\"latest_charge\":\"py_3SpDoCIkWweOM9jA1lSznUf1\",\"confirmation_method\":\"automatic\",\"created\":1768334600,\"currency\":\"eur\",\"customer\":null,\"last_payment_error\":null,\"livemode\":true,\"metadata\":{\"payments_extension_type\":\"klarna\",\"reconciliation_flow\":\"payments_api\",\"shop_id\":\"751927347\",\"payments_extension\":\"true\",\"payment_id\":\"rz5DDrJfvXuxGAl6nxxD9lbx2\"},\"next_action\":null,\"payment_method\":\"pm_1SpDoCIkWweOM9jAc50ynxkb\",\"payment_method_types\":[\"klarna\"],\"source\":null,\"status\":\"succeeded\"}" | Z5: =+A5 -> AS-95870
A6: AS-96440 | B6: 202601 | C6: [] | D6: Claim, GLS, Logistics | E6: ES | G6: 0.21 | H6: 0 | I6: EUR | J6: 0 | K6: 0 | L6: 0 | M6: other | Z6: =+A6 -> AS-96440
A7: AS-97072 | B7: 202601 | C7: ["paypal"] | E7: ES | G7: 0.21 | H7: 0.21 | I7: EUR | J7: 5.54 | K7: 31.9 | L7: 26.36 | M7: paypal | N7: gid://shopify/Order/7512292786514 | O7: gid://shopify/OrderTransaction/8645461967186 | P7: paypal | Q7: SALE | R7: SUCCESS | S7: 2026-01-29T16:18:09Z | T7: 31.9 | U7: EUR | V7: 55640617UJ7564455 | W7: rZQbrRB8s7nRHZCXqEkYieip9 | X7: 8W553953PB392601G | Y7: "{\"id\":\"8W553953PB392601G\",\"intent\":\"CAPTURE\",\"status\":\"COMPLETED\",\"payment_source\":{\"paypal\":{\"email_address\":\"nitrozgz@yahoo.es\",\"account_id\":\"BKYNYCZVLJPSU\",\"account_status\":\"VERIFIED\",\"name\":{\"given_name\":\"DANIEL\",\"surname\":\"DUCHA MORALES\"},\"phone_number\":{\"national_number\":\"667631874\"},\"address\":{\"address_line_1\":\"Calle Jacinto Benavente n\u00ba 1-3-5 Portal 4 2\u00baC\",\"admin_area_2\":\"ZARAGOZA\",\"admin_area_1\":\"Zaragoza\",\"postal_code\":\"50006\",\"country_code\":\"ES\"}}},\"purchase_units\":[{\"reference_id\":\"default\",\"amount\":{\"currency_code\":\"EUR\",\"value\":\"31.90\",\"breakdown\":{\"item_total\":{\"currency_code\":\"EUR\",\"value\":\"26.95\"},\"shipping\":{\"currency_code\":\"EUR\",\"value\":\"4.95\"},\"handling\":{\"currency_code\":\"EUR\",\"value\":\"0.00\"},\"tax_total\":{\"currency_code\":\"EUR\",\"value\":\"0.00\"},\"insurance\":{\"currency_code\":\"EUR\",\"value\":\"0.00\"},\"shipping_discount\":{\"currency_code\":\"EUR\",\"value\":\"0.00\"},\"discount\":{\"currency_code\":\"EUR\",\"value\":\"0.0\"}}},\"payee\":{\"email_address\":\"info@artestaposters.com\",\"merchant_id\":\"CZQCEKGVW6QGG\",\"display_data\":{\"brand_name\":\"Artesta\"}},\"payment_instruction\":{\"disbursement_mode\":\"INSTANT\"},\"description\":\"Zaragoza Skyline multicolor - P\u00f3ster \\/ Sin marco \\/ 40x50\",\"custom_id\":\"{\\\"shop_id\\\":751927347,\\\"session_id\\\":\\\"rZQbrRB8s7nRHZCXqEkYieip9\\\"}\",\"invoice_id\":\"rZQbrRB8s7nRHZCXqEkYieip9\",\"soft_descriptor\":\"PAYPAL *ARTESTASTOR AR\",\"items\":[{\"name\":\"Zaragoza Skyline multicolor - P\u00f3ster \\/ Sin marco \\/ 40x50\",\"unit_amount\":{\"currency_code\":\"EUR\",\"value\":\"26.95\"},\"tax\":{\"currency_code\":\"EUR\",\"value\":\"0.00\"},\"quantity\":\"1\"}],\"shipping\":{\"name\":{\"full_name\":\"DANIEL DUCHA MORALES\"},\"address\":{\"address_line_1\":\"Calle Jacinto Benavente n\u00ba 1-3-5 Portal 4 2\u00baC\",\"admin_area_2\":\"ZARAGOZA\",\"admin_area_1\":\"Zaragoza\",\"postal_code\":\"50006\",\"country_code\":\"ES\"}},\"payments\":{\"captures\":[{\"id\":\"55640617UJ7564455\",\"status\":\"COMPLETED\",\"amount\":{\"currency_code\":\"EUR\",\"value\":\"31.90\"},\"final_capture\":true,\"disbursement_mode\":\"INSTANT\",\"seller_protection\":{\"status\":\"ELIGIBLE\",\"dispute_categories\":[\"ITEM_NOT_RECEIVED\",\"UNAUTHORIZED_TRANSACTION\"]},\"seller_receivable_breakdown\":{\"gross_amount\":{\"currency_code\":\"EUR\",\"value\":\"31.90\"},\"paypal_fee\":{\"currency_code\":\"EUR\",\"value\":\"1.28\"},\"net_amount\":{\"currency_code\":\"EUR\",\"value\":\"30.62\"}},\"invoice_id\":\"rZQbrRB8s7nRHZCXqEkYieip9\",\"custom_id\":\"{\\\"shop_id\\\":751927347,\\\"session_id\\\":\\\"rZQbrRB8s7nRHZCXqEkYieip9\\\"}\",\"links\":[{\"href\":\"https:\\/\\/api.paypal.com\\/v2\\/payments\\/captures\\/55640617UJ7564455\",\"rel\":\"self\",\"method\":\"GET\"},{\"href\":\"https:\\/\\/api.paypal.com\\/v2\\/payments\\/captures\\/55640617UJ7564455\\/refund\",\"rel\":\"refund\",\"method\":\"POST\"},{\"href\":\"https:\\/\\/api.paypal.com\\/v2\\/checkout\\/orders\\/8W553953PB392601G\",\"rel\":\"up\",\"method\":\"GET\"}],\"create_time\":\"2026-01-29T16:18:11Z\",\"update_time\":\"2026-01-29T16:18:11Z\"}]}}],\"payer\":{\"name\":{\"given_name\":\"DANIEL\",\"surname\":\"DUCHA MORALES\"},\"email_address\":\"nitrozgz@yahoo.es\",\"payer_id\":\"BKYNYCZVLJPSU\",\"phone\":{\"phone_number\":{\"national_number\":\"667631874\"}},\"address\":{\"address_line_1\":\"Calle Jacinto Benavente n\u00ba 1-3-5 Portal 4 2\u00baC\",\"admin_area_2\":\"ZARAGOZA\",\"admin_area_1\":\"Zaragoza\",\"postal_code\":\"50006\",\"country_code\":\"ES\"}},\"create_time\":\"2026-01-29T16:17:10Z\",\"update_time\":\"2026-01-29T16:18:11Z\",\"links\":[{\"href\":\"https:\\/\\/api.paypal.com\\/v2\\/checkout\\/orders\\/8W553953PB392601G\",\"rel\":\"self\",\"method\":\"GET\"}]}" | Z7: =+A7 -> AS-97072
A8: AS-96103 | B8: 202601 | C8: ["shopify_payments"] | E8: DE | G8: 0.19 | H8: 0.19 | I8: EUR | J8: 10.52 | K8: 65.9 | L8: 55.38 | M8: shopify_payments | N8: gid://shopify/Order/7434288398674 | O8: gid://shopify/OrderTransaction/8609051345234 | P8: shopify_payments | Q8: SALE | R8: SUCCESS | S8: 2026-01-16T22:20:46Z | T8: 65.9 | U8: EUR | V8: ch_3SqLNrIkWweOM9jA08SO0GcL | W8: rZ553QeSuZwnCGCCwfN8ggSIL | X8: pi_3SqLNrIkWweOM9jA0uPcI8xF | Y8: "{\"id\":\"pi_3SqLNrIkWweOM9jA0uPcI8xF\",\"object\":\"payment_intent\",\"amount\":6590,\"amount_capturable\":0,\"amount_received\":6590,\"canceled_at\":null,\"cancellation_reason\":null,\"capture_method\":\"automatic\",\"latest_charge\":{\"id\":\"ch_3SqLNrIkWweOM9jA08SO0GcL\",\"object\":\"charge\",\"amount\":6590,\"application_fee\":\"fee_1SqLNuIkWweOM9jAIB8Vlyah\",\"balance_transaction\":\"txn_3SqLNrIkWweOM9jA0LoF07rP\",\"captured\":true,\"created\":1768602048,\"currency\":\"eur\",\"failure_code\":null,\"failure_message\":null,\"fraud_details\":{},\"livemode\":true,\"metadata\":{\"payment_id\":\"rZ553QeSuZwnCGCCwfN8ggSIL\",\"payments_extension\":\"true\",\"payments_extension_type\":\"card\",\"reconciliation_flow\":\"payments_api\",\"shop_id\":\"751927347\"},\"outcome\":{\"advice_code\":null,\"network_advice_code\":null,\"network_decline_code\":null,\"network_status\":\"approved_by_network\",\"reason\":null,\"risk_level\":\"normal\",\"seller_message\":\"Payment complete.\",\"type\":\"authorized\"},\"paid\":true,\"payment_intent\":\"pi_3SqLNrIkWweOM9jA0uPcI8xF\",\"payment_method\":\"pm_1SqLNrIkWweOM9jAcLlyg9lG\",\"payment_method_details\":{\"card\":{\"amount_authorized\":6590,\"authorization_code\":\"788093\",\"brand\":\"visa\",\"checks\":{\"address_line1_check\":\"unavailable\",\"address_postal_code_check\":\"unavailable\",\"cvc_check\":\"pass\"},\"country\":\"DE\",\"description\":\"Visa Classic\",\"ds_transaction_id\":null,\"exp_month\":9,\"exp_year\":2029,\"extended_authorization\":{\"status\":\"disabled\"},\"fingerprint\":\"N60PgAxbAE3qSJii\",\"funding\":\"debit\",\"iin\":\"422174\",\"incremental_authorization\":{\"status\":\"unavailable\"},\"installments\":null,\"issuer\":\"DEUTSCHE KREDITBANK AG\",\"last4\":\"9322\",\"mandate\":null,\"moto\":false,\"multicapture\":{\"status\":\"unavailable\"},\"network\":\"visa\",\"network_token\":{\"used\":false},\"network_transaction_id\":\"486016804489767\",\"overcapture\":{\"maximum_amount_capturable\":6590,\"status\":\"unavailable\"},\"payment_account_reference\":\"V0010014622085532210347728013\",\"regulated_status\":\"unregulated\",\"three_d_secure\":null,\"wallet\":null},\"type\":\"card\"},\"refunded\":false,\"source\":null,\"status\":\"succeeded\",\"mit_params\":{\"network_transaction_id\":\"486016804489767\"}},\"confirmation_method\":\"manual\",\"created\":1768602047,\"currency\":\"eur\",\"customer\":null,\"last_payment_error\":null,\"livemode\":true,\"metadata\":{\"payment_id\":\"rZ553QeSuZwnCGCCwfN8ggSIL\",\"payments_extension\":\"true\",\"payments_extension_type\":\"card\",\"reconciliation_flow\":\"payments_api\",\"shop_id\":\"751927347\"},\"next_action\":null,\"payment_method\":\"pm_1SqLNrIkWweOM9jAcLlyg9lG\",\"payment_method_types\":[\"card\"],\"source\":null,\"status\":\"succeeded\"}" | Z8: =+A8 -> AS-96103
A9: AS-95949 | B9: 202601 | C9: ["shopify_payments"] | E9: FR | G9: 0.2 | H9: 0.2 | I9: EUR | J9: 6.32 | K9: 37.9 | L9: 31.58 | M9: shopify_payments | N9: gid://shopify/Order/7428838555986 | O9: gid://shopify/OrderTransaction/8602891977042 | P9: shopify_payments | Q9: SALE | R9: SUCCESS | S9: 2026-01-14T20:23:34Z | T9: 37.9 | U9: EUR | V9: ch_3SpabLIkWweOM9jA1DgKtiCj | W9: rg1vvCNXrFJ2MY9cMZBIHKsfn | X9: pi_3SpabLIkWweOM9jA1L3OXCg5 | Y9: "{\"id\":\"pi_3SpabLIkWweOM9jA1L3OXCg5\",\"object\":\"payment_intent\",\"amount\":3790,\"amount_capturable\":0,\"amount_received\":3790,\"canceled_at\":null,\"cancellation_reason\":null,\"capture_method\":\"automatic\",\"latest_charge\":{\"id\":\"ch_3SpabLIkWweOM9jA1DgKtiCj\",\"object\":\"charge\",\"amount\":3790,\"application_fee\":\"fee_1SpabPIkWweOM9jA5uL4kJPs\",\"balance_transaction\":\"txn_3SpabLIkWweOM9jA1XVqMNr9\",\"captured\":true,\"created\":1768422218,\"currency\":\"eur\",\"failure_code\":null,\"failure_message\":null,\"fraud_details\":{},\"livemode\":true,\"metadata\":{\"payment_id\":\"rg1vvCNXrFJ2MY9cMZBIHKsfn\",\"payments_extension\":\"true\",\"payments_extension_type\":\"card\",\"reconciliation_flow\":\"payments_api\",\"shop_id\":\"751927347\"},\"outcome\":{\"advice_code\":null,\"network_advice_code\":null,\"network_decline_code\":null,\"network_status\":\"approved_by_network\",\"reason\":null,\"risk_level\":\"normal\",\"seller_message\":\"Payment complete.\",\"type\":\"authorized\"},\"paid\":true,\"payment_intent\":\"pi_3SpabLIkWweOM9jA1L3OXCg5\",\"payment_method\":\"pm_1SpabLIkWweOM9jApgy1lBRK\",\"payment_method_details\":{\"card\":{\"amount_authorized\":3790,\"authorization_code\":\"150946\",\"brand\":\"mastercard\",\"checks\":{\"address_line1_check\":\"unavailable\",\"address_postal_code_check\":\"unavailable\",\"cvc_check\":null},\"country\":\"FR\",\"description\":\"MasterCard Standard Card Immediate Debit\",\"ds_transaction_id\":null,\"exp_month\":1,\"exp_year\":2026,\"extended_authorization\":{\"status\":\"disabled\"},\"fingerprint\":\"OtBnGCwF1cqGIWG1\",\"funding\":\"debit\",\"iin\":\"513770\",\"incremental_authorization\":{\"status\":\"unavailable\"},\"installments\":null,\"issuer\":\"CREDIT AGRICOLE S.A.\",\"last4\":\"0791\",\"mandate\":null,\"moto\":false,\"multicapture\":{\"status\":\"unavailable\"},\"network\":\"mastercard\",\"network_token\":{\"used\":false},\"network_transaction_id\":\"TCSX8A18H0114\",\"overcapture\":{\"maximum_amount_capturable\":3790,\"status\":\"unavailable\"},\"payment_account_reference\":\"5001DHXU638Q0QGHTIOAB7UI4QWJ7\",\"regulated_status\":\"unregulated\",\"three_d_secure\":{\"authentication_flow\":\"frictionless\",\"electronic_commerce_indicator\":\"06\",\"exemption_indicator\":null,\"result\":\"exempted\",\"result_reason\":null,\"transaction_id\":\"74d6f95e-93b3-43e9-9c11-1d088d9838b7\",\"version\":\"2.2.0\"},\"wallet\":null},\"type\":\"card\"},\"refunded\":false,\"source\":null,\"status\":\"succeeded\",\"mit_params\":{\"network_transaction_id\":\"TCSX8A18H0114\"}},\"confirmation_method\":\"manual\",\"created\":1768422215,\"currency\":\"eur\",\"customer\":null,\"last_payment_error\":null,\"livemode\":true,\"metadata\":{\"payment_id\":\"rg1vvCNXrFJ2MY9cMZBIHKsfn\",\"payments_extension\":\"true\",\"payments_extension_type\":\"card\",\"reconciliation_flow\":\"payments_api\",\"shop_id\":\"751927347\"},\"next_action\":null,\"payment_method\":\"pm_1SpabLIkWweOM9jApgy1lBRK\",\"payment_method_types\":[\"card\"],\"source\":null,\"status\":\"succeeded\"}" | Z9: =+A9 -> AS-95949
A10: AS-96340 | B10: 202601 | C10: ["paypal"] | E10: DE | G10: 0.19 | H10: 0.19 | I10: EUR | J10: 6.05 | K10: 37.9 | L10: 31.85 | M10: paypal | N10: gid://shopify/Order/7442393956690 | O10: gid://shopify/OrderTransaction/8618773184850 | P10: paypal | Q10: SALE | R10: SUCCESS | S10: 2026-01-19T18:03:10Z | T10: 37.9 | U10: EUR | V10: 7H828225CB117980W | W10: rwLsMer5rnSNuxrw4PYuAw85p | X10: 6G172405MA5913831 | Y10: "{\"id\":\"6G172405MA5913831\",\"intent\":\"CAPTURE\",\"status\":\"COMPLETED\",\"payment_source\":{\"paypal\":{\"email_address\":\"romyseitz@yahoo.com\",\"account_id\":\"4B2BMB7PUW7HW\",\"account_status\":\"UNVERIFIED\",\"name\":{\"given_name\":\"Romy\",\"surname\":\"Seitz\"},\"phone_number\":{\"national_number\":\"4915255623629\"},\"address\":{\"address_line_1\":\"Heinrich-Nicolaus-Stra\u00dfe 9B\",\"admin_area_2\":\"Dachau\",\"postal_code\":\"85221\",\"country_code\":\"DE\"}}},\"purchase_units\":[{\"reference_id\":\"default\",\"amount\":{\"currency_code\":\"EUR\",\"value\":\"37.90\",\"breakdown\":{\"item_total\":{\"currency_code\":\"EUR\",\"value\":\"32.95\"},\"shipping\":{\"currency_code\":\"EUR\",\"value\":\"4.95\"},\"handling\":{\"currency_code\":\"EUR\",\"value\":\"0.00\"},\"tax_total\":{\"currency_code\":\"EUR\",\"value\":\"0.00\"},\"insurance\":{\"currency_code\":\"EUR\",\"value\":\"0.00\"},\"shipping_discount\":{\"currency_code\":\"EUR\",\"value\":\"0.00\"},\"discount\":{\"currency_code\":\"EUR\",\"value\":\"0.0\"}}},\"payee\":{\"email_address\":\"info@artestaposters.com\",\"merchant_id\":\"CZQCEKGVW6QGG\",\"display_data\":{\"brand_name\":\"Artesta\"}},\"payment_instruction\":{\"disbursement_mode\":\"INSTANT\"},\"description\":\"The Lady in Red (Special Edition) - Egon Schiele - P\u00f3ster \\/ Sin marco \\/ 50x70\",\"custom_id\":\"{\\\"shop_id\\\":751927347,\\\"session_id\\\":\\\"rwLsMer5rnSNuxrw4PYuAw85p\\\"}\",\"invoice_id\":\"rwLsMer5rnSNuxrw4PYuAw85p\",\"items\":[{\"name\":\"The Lady in Red (Special Edition) - Egon Schiele - P\u00f3ster \\/ Sin marco \\/ 50x70\",\"unit_amount\":{\"currency_code\":\"EUR\",\"value\":\"32.95\"},\"tax\":{\"currency_code\":\"EUR\",\"value\":\"0.00\"},\"quantity\":\"1\"}],\"shipping\":{\"name\":{\"full_name\":\"Romy Seitz\"},\"address\":{\"address_line_1\":\"Heinrich-Nicolaus-Stra\u00dfe 9B\",\"admin_area_2\":\"Dachau\",\"postal_code\":\"85221\",\"country_code\":\"DE\"}},\"supplementary_data\":{\"tax_nexus\":[]},\"payments\":{\"captures\":[{\"id\":\"7H828225CB117980W\",\"status\":\"COMPLETED\",\"amount\":{\"currency_code\":\"EUR\",\"value\":\"37.90\"},\"final_capture\":true,\"disbursement_mode\":\"INSTANT\",\"seller_protection\":{\"status\":\"ELIGIBLE\",\"dispute_categories\":[\"ITEM_NOT_RECEIVED\",\"UNAUTHORIZED_TRANSACTION\"]},\"seller_receivable_breakdown\":{\"gross_amount\":{\"currency_code\":\"EUR\",\"value\":\"37.90\"},\"paypal_fee\":{\"currency_code\":\"EUR\",\"value\":\"1.45\"},\"net_amount\":{\"currency_code\":\"EUR\",\"value\":\"36.45\"}},\"invoice_id\":\"rwLsMer5rnSNuxrw4PYuAw85p\",\"custom_id\":\"{\\\"shop_id\\\":751927347,\\\"session_id\\\":\\\"rwLsMer5rnSNuxrw4PYuAw85p\\\"}\",\"links\":[{\"href\":\"https:\\/\\/api.paypal.com\\/v2\\/payments\\/captures\\/7H828225CB117980W\",\"rel\":\"self\",\"method\":\"GET\"},{\"href\":\"https:\\/\\/api.paypal.com\\/v2\\/payments\\/captures\\/7H828225CB117980W\\/refund\",\"rel\":\"refund\",\"method\":\"POST\"},{\"href\":\"https:\\/\\/api.paypal.com\\/v2\\/checkout\\/orders\\/6G172405MA5913831\",\"rel\":\"up\",\"method\":\"GET\"}],\"create_time\":\"2026-01-19T18:03:12Z\",\"update_time\":\"2026-01-19T18:03:12Z\"}]}}],\"payer\":{\"name\":{\"given_name\":\"Romy\",\"surname\":\"Seitz\"},\"email_address\":\"romyseitz@yahoo.com\",\"payer_id\":\"4B2BMB7PUW7HW\",\"phone\":{\"phone_number\":{\"national_number\":\"4915255623629\"}},\"address\":{\"address_line_1\":\"Heinrich-Nicolaus-Stra\u00dfe 9B\",\"admin_area_2\":\"Dachau\",\"postal_code\":\"85221\",\"country_code\":\"DE\"}},\"create_time\":\"2026-01-19T18:02:46Z\",\"update_time\":\"2026-01-19T18:03:12Z\",\"links\":[{\"href\":\"https:\\/\\/api.paypal.com\\/v2\\/checkout\\/orders\\/6G172405MA5913831\",\"rel\":\"self\",\"method\":\"GET\"}]}" | Z10: =+A10 -> AS-96340
A11: AS-97191 | B11: 202601 | C11: ["shopify_payments"] | E11: ES | G11: 0.21 | H11: 0.21 | I11: EUR | J11: 20.46 | K11: 117.9 | L11: 97.44 | M11: shopify_payments | N11: gid://shopify/Order/7515447787858 | O11: gid://shopify/OrderTransaction/8649801498962 | P11: shopify_payments | Q11: SALE | R11: SUCCESS | S11: 2026-01-31T11:44:31Z | T11: 117.9 | U11: EUR | V11: ch_3SvcbMIkWweOM9jA1dBMaWec | W11: rdrngfRMebWUdHqT5JxYkmzuB | X11: pi_3SvcbMIkWweOM9jA1hQMHRzx | Y11: "{\"id\":\"pi_3SvcbMIkWweOM9jA1hQMHRzx\",\"object\":\"payment_intent\",\"amount\":11790,\"amount_capturable\":0,\"amount_received\":11790,\"canceled_at\":null,\"cancellation_reason\":null,\"capture_method\":\"automatic\",\"latest_charge\":{\"id\":\"ch_3SvcbMIkWweOM9jA1dBMaWec\",\"object\":\"charge\",\"amount\":11790,\"application_fee\":\"fee_1SvcbOIkWweOM9jAqbxsfOuX\",\"balance_transaction\":\"txn_3SvcbMIkWweOM9jA1DRRnoxf\",\"captured\":true,\"created\":1769859873,\"currency\":\"eur\",\"failure_code\":null,\"failure_message\":null,\"fraud_details\":{},\"livemode\":true,\"metadata\":{\"payment_id\":\"rdrngfRMebWUdHqT5JxYkmzuB\",\"payments_extension\":\"true\",\"payments_extension_type\":\"card\",\"reconciliation_flow\":\"payments_api\",\"shop_id\":\"751927347\"},\"outcome\":{\"advice_code\":null,\"network_advice_code\":null,\"network_decline_code\":null,\"network_status\":\"approved_by_network\",\"reason\":null,\"risk_level\":\"normal\",\"seller_message\":\"Payment complete.\",\"type\":\"authorized\"},\"paid\":true,\"payment_intent\":\"pi_3SvcbMIkWweOM9jA1hQMHRzx\",\"payment_method\":\"pm_1SvcbMIkWweOM9jA9h1953ff\",\"payment_method_details\":{\"card\":{\"amount_authorized\":11790,\"authorization_code\":\"560565\",\"brand\":\"mastercard\",\"checks\":{\"address_line1_check\":\"unavailable\",\"address_postal_code_check\":\"unavailable\",\"cvc_check\":\"pass\"},\"country\":\"ES\",\"description\":\"MasterCard Prepaid Card (Non-US)\",\"ds_transaction_id\":null,\"exp_month\":10,\"exp_year\":2029,\"extended_authorization\":{\"status\":\"disabled\"},\"fingerprint\":\"3xv2AaspkeGcNkiC\",\"funding\":\"prepaid\",\"iin\":\"527027\",\"incremental_authorization\":{\"status\":\"unavailable\"},\"installments\":null,\"issuer\":\"SERVIRED, SOCIEDAD ESPANOLA DE\",\"last4\":\"5498\",\"mandate\":null,\"moto\":false,\"multicapture\":{\"status\":\"unavailable\"},\"network\":\"mastercard\",\"network_token\":{\"used\":false},\"network_transaction_id\":\"MRGNFSOLF0131\",\"overcapture\":{\"maximum_amount_capturable\":11790,\"status\":\"unavailable\"},\"payment_account_reference\":\"5001ELJU4GHL3KNGPSUZJX6GKMISC\",\"regulated_status\":\"unregulated\",\"three_d_secure\":null,\"wallet\":null},\"type\":\"card\"},\"refunded\":false,\"source\":null,\"status\":\"succeeded\",\"mit_params\":{\"network_transaction_id\":\"MRGNFSOLF0131\"}},\"confirmation_method\":\"manual\",\"created\":1769859872,\"currency\":\"eur\",\"customer\":null,\"last_payment_error\":null,\"livemode\":true,\"metadata\":{\"payment_id\":\"rdrngfRMebWUdHqT5JxYkmzuB\",\"payments_extension\":\"true\",\"payments_extension_type\":\"card\",\"reconciliation_flow\":\"payments_api\",\"shop_id\":\"751927347\"},\"next_action\":null,\"payment_method\":\"pm_1SvcbMIkWweOM9jA9h1953ff\",\"payment_method_types\":[\"card\"],\"source\":null,\"status\":\"succeeded\"}" | Z11: =+A11 -> AS-97191
A12: AS-96810 | B12: 202601 | C12: [] | D12: Claim, Logistics, UPS | E12: AT | G12: 0.2 | H12: 0 | I12: EUR | J12: 0 | K12: 0 | L12: 0 | M12: other | Z12: =+A12 -> AS-96810
A13: AS-95079 | B13: 202601 | C13: ["paypal"] | E13: DE | G13: 0.19 | H13: 0.19 | I13: EUR | J13: 6.05 | K13: 37.9 | L13: 31.85 | M13: paypal | N13: gid://shopify/Order/7399884751186 | O13: gid://shopify/OrderTransaction/8576724599122 | P13: paypal | Q13: SALE | R13: SUCCESS | S13: 2026-01-04T20:12:48Z | T13: 37.9 | U13: EUR | V13: 60C664959K135250N | W13: rkq40FCAKXNAmfxvzl2vqMVmc | X13: 4MH648067B047702C | Y13: "{\"id\":\"4MH648067B047702C\",\"intent\":\"CAPTURE\",\"status\":\"COMPLETED\",\"payment_source\":{\"paypal\":{\"email_address\":\"smiedl7@aol.com\",\"account_id\":\"5F95P9KSLYCSC\",\"account_status\":\"VERIFIED\",\"name\":{\"given_name\":\"Sabine\",\"surname\":\"Miedl\"},\"phone_number\":{\"national_number\":\"1796959484\"},\"address\":{\"address_line_1\":\"Perhamerstr. 72\",\"admin_area_2\":\"M\u00fcnchen\",\"postal_code\":\"80687\",\"country_code\":\"DE\"}}},\"purchase_units\":[{\"reference_id\":\"default\",\"amount\":{\"currency_code\":\"EUR\",\"value\":\"37.90\",\"breakdown\":{\"item_total\":{\"currency_code\":\"EUR\",\"value\":\"32.95\"},\"shipping\":{\"currency_code\":\"EUR\",\"value\":\"4.95\"},\"handling\":{\"currency_code\":\"EUR\",\"value\":\"0.00\"},\"tax_total\":{\"currency_code\":\"EUR\",\"value\":\"0.00\"},\"insurance\":{\"currency_code\":\"EUR\",\"value\":\"0.00\"},\"shipping_discount\":{\"currency_code\":\"EUR\",\"value\":\"0.00\"},\"discount\":{\"currency_code\":\"EUR\",\"value\":\"0.0\"}}},\"payee\":{\"email_address\":\"info@artestaposters.com\",\"merchant_id\":\"CZQCEKGVW6QGG\",\"display_data\":{\"brand_name\":\"Artesta\"}},\"payment_instruction\":{\"disbursement_mode\":\"INSTANT\"},\"description\":\"Vespa - P\u00f3ster \\/ Sin marco \\/ 50x70\",\"custom_id\":\"{\\\"shop_id\\\":751927347,\\\"session_id\\\":\\\"rkq40FCAKXNAmfxvzl2vqMVmc\\\"}\",\"invoice_id\":\"rkq40FCAKXNAmfxvzl2vqMVmc\",\"items\":[{\"name\":\"Vespa - P\u00f3ster \\/ Sin marco \\/ 50x70\",\"unit_amount\":{\"currency_code\":\"EUR\",\"value\":\"32.95\"},\"tax\":{\"currency_code\":\"EUR\",\"value\":\"0.00\"},\"quantity\":\"1\"}],\"shipping\":{\"name\":{\"full_name\":\"Sabine Miedl\"},\"address\":{\"address_line_1\":\"Perhamerstrasse 72 \",\"admin_area_2\":\"M\u00fcnchen\",\"postal_code\":\"80687\",\"country_code\":\"DE\"}},\"supplementary_data\":{\"tax_nexus\":[]},\"payments\":{\"captures\":[{\"id\":\"60C664959K135250N\",\"status\":\"COMPLETED\",\"amount\":{\"currency_code\":\"EUR\",\"value\":\"37.90\"},\"final_capture\":true,\"disbursement_mode\":\"INSTANT\",\"seller_protection\":{\"status\":\"ELIGIBLE\",\"dispute_categories\":[\"ITEM_NOT_RECEIVED\",\"UNAUTHORIZED_TRANSACTION\"]},\"seller_receivable_breakdown\":{\"gross_amount\":{\"currency_code\":\"EUR\",\"value\":\"37.90\"},\"paypal_fee\":{\"currency_code\":\"EUR\",\"value\":\"1.45\"},\"net_amount\":{\"currency_code\":\"EUR\",\"value\":\"36.45\"}},\"invoice_id\":\"rkq40FCAKXNAmfxvzl2vqMVmc\",\"custom_id\":\"{\\\"shop_id\\\":751927347,\\\"session_id\\\":\\\"rkq40FCAKXNAmfxvzl2vqMVmc\\\"}\",\"links\":[{\"href\":\"https:\\/\\/api.paypal.com\\/v2\\/payments\\/captures\\/60C664959K135250N\",\"rel\":\"self\",\"method\":\"GET\"},{\"href\":\"https:\\/\\/api.paypal.com\\/v2\\/payments\\/captures\\/60C664959K135250N\\/refund\",\"rel\":\"refund\",\"method\":\"POST\"},{\"href\":\"https:\\/\\/api.paypal.com\\/v2\\/checkout\\/orders\\/4MH648067B047702C\",\"rel\":\"up\",\"method\":\"GET\"}],\"create_time\":\"2026-01-04T20:12:50Z\",\"update_time\":\"2026-01-04T20:12:50Z\"}]}}],\"payer\":{\"name\":{\"given_name\":\"Sabine\",\"surname\":\"Miedl\"},\"email_address\":\"smiedl7@aol.com\",\"payer_id\":\"5F95P9KSLYCSC\",\"phone\":{\"phone_number\":{\"national_number\":\"1796959484\"}},\"address\":{\"address_line_1\":\"Perhamerstr. 72\",\"admin_area_2\":\"M\u00fcnchen\",\"postal_code\":\"80687\",\"country_code\":\"DE\"}},\"create_time\":\"2026-01-04T20:11:13Z\",\"update_time\":\"2026-01-04T20:12:50Z\",\"links\":[{\"href\":\"https:\\/\\/api.paypal.com\\/v2\\/checkout\\/orders\\/4MH648067B047702C\",\"rel\":\"self\",\"method\":\"GET\"}]}" | Z13: =+A13 -> AS-95079
A14: AS-95722 | B14: 202601 | C14: ["shopify_payments"] | E14: FR | G14: 0.2 | H14: 0.2 | I14: EUR | J14: 41.95 | K14: 251.69 | L14: 209.74 | M14: shopify_payments | N14: gid://shopify/Order/7421871554898 | O14: gid://shopify/OrderTransaction/8595321520466 | P14: shopify_payments | Q14: SALE | R14: SUCCESS | S14: 2026-01-11T22:28:29Z | T14: 251.69 | U14: EUR | V14: ch_3SoX7ZIkWweOM9jA0UcqPX93 | W14: rwQmTEYPf73qdRavi4yZIQQyO | X14: pi_3SoX7ZIkWweOM9jA00ggJpzK | Y14: "{\"id\":\"pi_3SoX7ZIkWweOM9jA00ggJpzK\",\"object\":\"payment_intent\",\"amount\":25169,\"amount_capturable\":0,\"amount_received\":25169,\"canceled_at\":null,\"cancellation_reason\":null,\"capture_method\":\"automatic\",\"latest_charge\":{\"id\":\"ch_3SoX7ZIkWweOM9jA0UcqPX93\",\"object\":\"charge\",\"amount\":25169,\"application_fee\":\"fee_1SoX8EIkWweOM9jAX0lfC4TS\",\"balance_transaction\":\"txn_3SoX7ZIkWweOM9jA0if0WlPY\",\"captured\":true,\"created\":1768170549,\"currency\":\"eur\",\"failure_code\":null,\"failure_message\":null,\"fraud_details\":{},\"livemode\":true,\"metadata\":{\"payment_id\":\"rwQmTEYPf73qdRavi4yZIQQyO\",\"payments_extension\":\"true\",\"payments_extension_type\":\"card\",\"reconciliation_flow\":\"payments_api\",\"shop_id\":\"751927347\"},\"outcome\":{\"advice_code\":null,\"network_advice_code\":null,\"network_decline_code\":null,\"network_status\":\"approved_by_network\",\"reason\":null,\"risk_level\":\"normal\",\"seller_message\":\"Payment complete.\",\"type\":\"authorized\"},\"paid\":true,\"payment_intent\":\"pi_3SoX7ZIkWweOM9jA00ggJpzK\",\"payment_method\":\"pm_1SoX7ZIkWweOM9jApraDoOX7\",\"payment_method_details\":{\"card\":{\"amount_authorized\":25169,\"authorization_code\":\"444067\",\"brand\":\"visa\",\"checks\":{\"address_line1_check\":\"unavailable\",\"address_postal_code_check\":\"unavailable\",\"cvc_check\":null},\"country\":\"FR\",\"description\":\"Visa Business\",\"ds_transaction_id\":null,\"exp_month\":12,\"exp_year\":2028,\"extended_authorization\":{\"status\":\"disabled\"},\"fingerprint\":\"79vinjVlRmZqMu34\",\"funding\":\"debit\",\"iin\":\"497208\",\"incremental_authorization\":{\"status\":\"unavailable\"},\"installments\":null,\"issuer\":\"LE CREDIT LYONNAIS\",\"last4\":\"8021\",\"mandate\":null,\"moto\":false,\"multicapture\":{\"status\":\"unavailable\"},\"network\":\"visa\",\"network_token\":{\"used\":true},\"network_transaction_id\":\"486011809496078\",\"overcapture\":{\"maximum_amount_capturable\":25169,\"status\":\"unavailable\"},\"payment_account_reference\":null,\"regulated_status\":\"unregulated\",\"three_d_secure\":{\"authentication_flow\":\"challenge\",\"electronic_commerce_indicator\":\"05\",\"exemption_indicator\":null,\"result\":\"authenticated\",\"result_reason\":null,\"transaction_id\":\"5940b178-ad16-44ae-995e-a9fdafb333ac\",\"version\":\"2.2.0\"},\"wallet\":null},\"type\":\"card\"},\"refunded\":false,\"source\":null,\"status\":\"succeeded\",\"mit_params\":{\"network_transaction_id\":\"486011809496078\"}},\"confirmation_method\":\"manual\",\"created\":1768170509,\"currency\":\"eur\",\"customer\":null,\"last_payment_error\":null,\"livemode\":true,\"metadata\":{\"payment_id\":\"rwQmTEYPf73qdRavi4yZIQQyO\",\"payments_extension\":\"true\",\"payments_extension_type\":\"card\",\"reconciliation_flow\":\"payments_api\",\"shop_id\":\"751927347\"},\"next_action\":null,\"payment_method\":\"pm_1SoX7ZIkWweOM9jApraDoOX7\",\"payment_method_types\":[\"card\"],\"source\":null,\"status\":\"succeeded\"}" | Z14: =+A14 -> AS-95722
A15: AS-96356 | B15: 202601 | C15: ["shopify_payments"] | E15: IT | G15: 0.22 | H15: 0.22 | I15: EUR | J15: 12.05 | K15: 66.85 | L15: 54.8 | M15: shopify_payments | N15: gid://shopify/Order/7442918441298 | O15: gid://shopify/OrderTransaction/8619360059730 | P15: shopify_payments | Q15: SALE | R15: SUCCESS | S15: 2026-01-19T21:17:26Z | T15: 66.85 | U15: EUR | V15: ch_3SrPpDIkWweOM9jA2CXASlRH | W15: r1al0qkLEXnWJACmP2rTF4W3h | X15: pi_3SrPpDIkWweOM9jA21GSXs7L | Y15: "{\"id\":\"pi_3SrPpDIkWweOM9jA21GSXs7L\",\"object\":\"payment_intent\",\"amount\":6685,\"amount_capturable\":0,\"amount_received\":6685,\"canceled_at\":null,\"cancellation_reason\":null,\"capture_method\":\"automatic\",\"latest_charge\":{\"id\":\"ch_3SrPpDIkWweOM9jA2CXASlRH\",\"object\":\"charge\",\"amount\":6685,\"application_fee\":\"fee_1SrPpEIkWweOM9jA3qt95CK7\",\"balance_transaction\":\"txn_3SrPpDIkWweOM9jA2NYMrlKl\",\"captured\":true,\"created\":1768857448,\"currency\":\"eur\",\"failure_code\":null,\"failure_message\":null,\"fraud_details\":{},\"livemode\":true,\"metadata\":{\"payment_id\":\"r1al0qkLEXnWJACmP2rTF4W3h\",\"payments_extension\":\"true\",\"payments_extension_type\":\"card\",\"reconciliation_flow\":\"payments_api\",\"shop_id\":\"751927347\"},\"outcome\":{\"advice_code\":null,\"network_advice_code\":null,\"network_decline_code\":null,\"network_status\":\"approved_by_network\",\"reason\":null,\"risk_level\":\"normal\",\"seller_message\":\"Payment complete.\",\"type\":\"authorized\"},\"paid\":true,\"payment_intent\":\"pi_3SrPpDIkWweOM9jA21GSXs7L\",\"payment_method\":\"pm_1SrPpDIkWweOM9jA4FqMZYW7\",\"payment_method_details\":{\"card\":{\"amount_authorized\":6685,\"authorization_code\":\"H69016\",\"brand\":\"mastercard\",\"checks\":{\"address_line1_check\":\"unavailable\",\"address_postal_code_check\":\"unavailable\",\"cvc_check\":null},\"country\":\"IT\",\"description\":\"Prepaid Unembossed MasterCard Card (Non-US)\",\"ds_transaction_id\":null,\"exp_month\":4,\"exp_year\":2026,\"extended_authorization\":{\"status\":\"disabled\"},\"fingerprint\":\"Uy1aJUtknBzPwffp\",\"funding\":\"prepaid\",\"iin\":\"526430\",\"incremental_authorization\":{\"status\":\"unavailable\"},\"installments\":null,\"issuer\":\"UNICREDIT SPA\",\"last4\":\"7221\",\"mandate\":null,\"moto\":false,\"multicapture\":{\"status\":\"unavailable\"},\"network\":\"mastercard\",\"network_token\":{\"used\":false},\"network_transaction_id\":\"SURYQFTHU0119\",\"overcapture\":{\"maximum_amount_capturable\":6685,\"status\":\"unavailable\"},\"payment_account_reference\":\"5001F00J9O4X215QKAEDYCNTO6BGY\",\"regulated_status\":\"unregulated\",\"three_d_secure\":null,\"wallet\":null},\"type\":\"card\"},\"refunded\":false,\"source\":null,\"status\":\"succeeded\",\"mit_params\":{\"network_transaction_id\":\"SURYQFTHU0119\"}},\"confirmation_method\":\"manual\",\"created\":1768857447,\"currency\":\"eur\",\"customer\":null,\"last_payment_error\":null,\"livemode\":true,\"metadata\":{\"payment_id\":\"r1al0qkLEXnWJACmP2rTF4W3h\",\"payments_extension\":\"true\",\"payments_extension_type\":\"card\",\"reconciliation_flow\":\"payments_api\",\"shop_id\":\"751927347\"},\"next_action\":null,\"payment_method\":\"pm_1SrPpDIkWweOM9jA4FqMZYW7\",\"payment_method_types\":[\"card\"],\"source\":null,\"status\":\"succeeded\"}" | Z15: =+A15 -> AS-96356
A16: AS-95520 | B16: 202601 | C16: ["shopify_payments"] | E16: ES | G16: 0.21 | H16: 0.21 | I16: EUR | J16: 26.54 | K16: 152.91 | L16: 126.37 | M16: shopify_payments | N16: gid://shopify/Order/7418086981970 | O16: gid://shopify/OrderTransaction/8590926250322 | P16: shopify_payments | Q16: SALE | R16: SUCCESS | S16: 2026-01-10T07:05:27Z | T16: 152.91 | U16: EUR | V16: ch_3SnwEmIkWweOM9jA126NsO3i | W16: rNfvkk6o6SjtwYNgVUdlr9wVQ | X16: pi_3SnwEmIkWweOM9jA1tFJfR0f | Y16: "{\"id\":\"pi_3SnwEmIkWweOM9jA1tFJfR0f\",\"object\":\"payment_intent\",\"amount\":15291,\"amount_capturable\":0,\"amount_received\":15291,\"canceled_at\":null,\"cancellation_reason\":null,\"capture_method\":\"automatic\",\"latest_charge\":{\"id\":\"ch_3SnwEmIkWweOM9jA126NsO3i\",\"object\":\"charge\",\"amount\":15291,\"application_fee\":\"fee_1SnwEoIkWweOM9jA5wUq2dFj\",\"balance_transaction\":\"txn_3SnwEmIkWweOM9jA1ZQGDjCl\",\"captured\":true,\"created\":1768028729,\"currency\":\"eur\",\"failure_code\":null,\"failure_message\":null,\"fraud_details\":{},\"livemode\":true,\"metadata\":{\"payment_id\":\"rNfvkk6o6SjtwYNgVUdlr9wVQ\",\"payments_extension\":\"true\",\"payments_extension_type\":\"card\",\"reconciliation_flow\":\"payments_api\",\"shop_id\":\"751927347\"},\"outcome\":{\"advice_code\":null,\"network_advice_code\":null,\"network_decline_code\":null,\"network_status\":\"approved_by_network\",\"reason\":null,\"risk_level\":\"normal\",\"seller_message\":\"Payment complete.\",\"type\":\"authorized\"},\"paid\":true,\"payment_intent\":\"pi_3SnwEmIkWweOM9jA1tFJfR0f\",\"payment_method\":\"pm_1SnwEmIkWweOM9jArRUmhN4k\",\"payment_method_details\":{\"card\":{\"amount_authorized\":15291,\"authorization_code\":\"130044\",\"brand\":\"mastercard\",\"checks\":{\"address_line1_check\":\"unavailable\",\"address_postal_code_check\":\"unavailable\",\"cvc_check\":\"pass\"},\"country\":\"ES\",\"description\":\"MasterCard Credit Card (mixed BIN)\",\"ds_transaction_id\":null,\"exp_month\":6,\"exp_year\":2031,\"extended_authorization\":{\"status\":\"disabled\"},\"fingerprint\":\"Xk4OL8tAiqfNyZ0w\",\"funding\":\"credit\",\"iin\":\"541541\",\"incremental_authorization\":{\"status\":\"unavailable\"},\"installments\":null,\"issuer\":\"BANCO SANTANDER S.A.\",\"last4\":\"3591\",\"mandate\":null,\"moto\":false,\"multicapture\":{\"status\":\"unavailable\"},\"network\":\"mastercard\",\"network_token\":{\"used\":false},\"network_transaction_id\":\"MCCMLVWM30110\",\"overcapture\":{\"maximum_amount_capturable\":15291,\"status\":\"unavailable\"},\"payment_account_reference\":\"50013CXX43ED7O2L8R9P17BS0FHDI\",\"regulated_status\":\"unregulated\",\"three_d_secure\":null,\"wallet\":null},\"type\":\"card\"},\"refunded\":false,\"source\":null,\"status\":\"succeeded\",\"mit_params\":{\"network_transaction_id\":\"MCCMLVWM30110\"}},\"confirmation_method\":\"manual\",\"created\":1768028728,\"currency\":\"eur\",\"customer\":null,\"last_payment_error\":null,\"livemode\":true,\"metadata\":{\"payment_id\":\"rNfvkk6o6SjtwYNgVUdlr9wVQ\",\"payments_extension\":\"true\",\"payments_extension_type\":\"card\",\"reconciliation_flow\":\"payments_api\",\"shop_id\":\"751927347\"},\"next_action\":null,\"payment_method\":\"pm_1SnwEmIkWweOM9jArRUmhN4k\",\"payment_method_types\":[\"card\"],\"source\":null,\"status\":\"succeeded\"}" | Z16: =+A16 -> AS-95520
A17: AS-95338 | B17: 202601 | C17: ["shopify_payments"] | E17: FR | G17: 0.2 | H17: 0.2 | I17: EUR | J17: 9.81 | K17: 58.85 | L17: 49.04 | M17: shopify_payments | N17: gid://shopify/Order/7413272281426 | O17: gid://shopify/OrderTransaction/8585168290130 | P17: shopify_payments | Q17: SALE | R17: SUCCESS | S17: 2026-01-07T22:50:26Z | T17: 58.85 | U17: EUR | V17: ch_3Sn5YcIkWweOM9jA10YALbJy | W17: rdmehMoHGcUWyJZluAmAdaKbR | X17: pi_3Sn5YcIkWweOM9jA1qgX7dvY | Y17: "{\"id\":\"pi_3Sn5YcIkWweOM9jA1qgX7dvY\",\"object\":\"payment_intent\",\"amount\":5885,\"amount_capturable\":0,\"amount_received\":5885,\"canceled_at\":null,\"cancellation_reason\":null,\"capture_method\":\"automatic\",\"latest_charge\":{\"id\":\"ch_3Sn5YcIkWweOM9jA10YALbJy\",\"object\":\"charge\",\"amount\":5885,\"application_fee\":\"fee_1Sn5YeIkWweOM9jAV34ddOsu\",\"balance_transaction\":\"txn_3Sn5YcIkWweOM9jA1vLz2bFd\",\"captured\":true,\"created\":1767826228,\"currency\":\"eur\",\"failure_code\":null,\"failure_message\":null,\"fraud_details\":{},\"livemode\":true,\"metadata\":{\"payment_id\":\"rdmehMoHGcUWyJZluAmAdaKbR\",\"payments_extension\":\"true\",\"payments_extension_type\":\"card\",\"reconciliation_flow\":\"payments_api\",\"shop_id\":\"751927347\"},\"outcome\":{\"advice_code\":null,\"network_advice_code\":null,\"network_decline_code\":null,\"network_status\":\"approved_by_network\",\"reason\":null,\"risk_level\":\"normal\",\"seller_message\":\"Payment complete.\",\"type\":\"authorized\"},\"paid\":true,\"payment_intent\":\"pi_3Sn5YcIkWweOM9jA1qgX7dvY\",\"payment_method\":\"pm_1Sn5YcIkWweOM9jAOsIKaft9\",\"payment_method_details\":{\"card\":{\"amount_authorized\":5885,\"authorization_code\":\"112001\",\"brand\":\"visa\",\"checks\":{\"address_line1_check\":\"fail\",\"address_postal_code_check\":\"fail\",\"cvc_check\":\"pass\"},\"country\":\"FR\",\"description\":\"Visa Gold\",\"ds_transaction_id\":null,\"exp_month\":3,\"exp_year\":2028,\"extended_authorization\":{\"status\":\"disabled\"},\"fingerprint\":\"NuNYX6SS7RxfkSWu\",\"funding\":\"debit\",\"iin\":\"463344\",\"incremental_authorization\":{\"status\":\"unavailable\"},\"installments\":null,\"issuer\":\"BPCE\",\"last4\":\"5308\",\"mandate\":null,\"moto\":false,\"multicapture\":{\"status\":\"unavailable\"},\"network\":\"visa\",\"network_token\":{\"used\":false},\"network_transaction_id\":\"486007822284527\",\"overcapture\":{\"maximum_amount_capturable\":5885,\"status\":\"unavailable\"},\"payment_account_reference\":\"V001AACC327012023053042756560\",\"regulated_status\":\"unregulated\",\"three_d_secure\":{\"authentication_flow\":\"frictionless\",\"electronic_commerce_indicator\":\"07\",\"exemption_indicator\":null,\"result\":\"exempted\",\"result_reason\":null,\"transaction_id\":\"b506c16d-bc5c-46ec-84a8-305c8e93d765\",\"version\":\"2.2.0\"},\"wallet\":null},\"type\":\"card\"},\"refunded\":false,\"source\":null,\"status\":\"succeeded\",\"mit_params\":{\"network_transaction_id\":\"486007822284527\"}},\"confirmation_method\":\"manual\",\"created\":1767826226,\"currency\":\"eur\",\"customer\":null,\"last_payment_error\":null,\"livemode\":true,\"metadata\":{\"payment_id\":\"rdmehMoHGcUWyJZluAmAdaKbR\",\"payments_extension\":\"true\",\"payments_extension_type\":\"card\",\"reconciliation_flow\":\"payments_api\",\"shop_id\":\"751927347\"},\"next_action\":null,\"payment_method\":\"pm_1Sn5YcIkWweOM9jAOsIKaft9\",\"payment_method_types\":[\"card\"],\"source\":null,\"status\":\"succeeded\"}" | Z17: =+A17 -> AS-95338
A18: AS-95578 | B18: 202601 | C18: ["shopify_payments"] | E18: DE | G18: 0.19 | H18: 0.19 | I18: EUR | J18: 14.64 | K18: 91.71 | L18: 77.07 | M18: shopify_payments | N18: gid://shopify/Order/7419339997522 | O18: gid://shopify/OrderTransaction/8592424665426 | P18: shopify_payments | Q18: SALE | R18: SUCCESS | S18: 2026-01-10T17:58:25Z | T18: 91.71 | U18: EUR | V18: py_3So6QfIkWweOM9jA1cHK9NXv | W18: rEGEL1XRLzjpWbv52OJQ5ADTx | X18: py_3So6QfIkWweOM9jA1cHK9NXv | Y18: "{\"id\":\"py_3So6QfIkWweOM9jA1cHK9NXv\",\"object\":\"charge\",\"amount\":9171,\"application_fee\":\"fee_1So6R0IkWweOM9jAX9mp87DP\",\"balance_transaction\":\"txn_3So6QfIkWweOM9jA1O1TuNmi\",\"captured\":true,\"created\":1768067926,\"currency\":\"eur\",\"failure_code\":null,\"failure_message\":null,\"fraud_details\":{},\"livemode\":true,\"metadata\":{\"payments_extension_type\":\"klarna\",\"payments_extension\":\"true\",\"shop_id\":\"751927347\",\"reconciliation_flow\":\"payments_api\",\"payment_id\":\"rEGEL1XRLzjpWbv52OJQ5ADTx\"},\"outcome\":{\"advice_code\":null,\"network_advice_code\":null,\"network_decline_code\":null,\"network_status\":\"approved_by_network\",\"reason\":null,\"risk_level\":\"not_assessed\",\"seller_message\":\"Payment complete.\",\"type\":\"authorized\"},\"paid\":true,\"payment_intent\":\"pi_3So6QfIkWweOM9jA161oURZB\",\"payment_method\":\"pm_1So6QfIkWweOM9jAEgZdkAjF\",\"payment_method_details\":{\"klarna\":{\"payer_details\":{\"address\":{\"country\":\"DE\"}},\"payment_method_category\":\"pay_later\",\"preferred_locale\":\"de-DE\"},\"type\":\"klarna\"},\"refunded\":false,\"source\":null,\"status\":\"succeeded\"}" | Z18: =+A18 -> AS-95578
A19: AS-95339 | B19: 202601 | C19: ["shopify_payments"] | E19: FR | G19: 0.2 | H19: 0.2 | I19: EUR | J19: 76.71 | K19: 460.26 | L19: 383.55 | M19: shopify_payments | N19: gid://shopify/Order/7413276049746 | O19: gid://shopify/OrderTransaction/8585168748882 | P19: shopify_payments | Q19: SALE | R19: SUCCESS | S19: 2026-01-07T22:51:01Z | T19: 460.26 | U19: EUR | V19: py_3Sn5ZBIkWweOM9jA0PMWIcg8 | W19: rZvmzhfPYKzqDB2cKLoI8jui6 | X19: py_3Sn5ZBIkWweOM9jA0PMWIcg8 | Y19: "{\"id\":\"py_3Sn5ZBIkWweOM9jA0PMWIcg8\",\"object\":\"charge\",\"amount\":46026,\"application_fee\":\"fee_1Sn5cwIkWweOM9jA0xax3Rsb\",\"balance_transaction\":\"txn_3Sn5ZBIkWweOM9jA0o0vbReA\",\"captured\":true,\"created\":1767826494,\"currency\":\"eur\",\"failure_code\":null,\"failure_message\":null,\"fraud_details\":{},\"livemode\":true,\"metadata\":{\"payments_extension_type\":\"klarna\",\"payments_extension\":\"true\",\"shop_id\":\"751927347\",\"reconciliation_flow\":\"payments_api\",\"payment_id\":\"rZvmzhfPYKzqDB2cKLoI8jui6\"},\"outcome\":{\"advice_code\":null,\"network_advice_code\":null,\"network_decline_code\":null,\"network_status\":\"approved_by_network\",\"reason\":null,\"risk_level\":\"not_assessed\",\"seller_message\":\"Payment complete.\",\"type\":\"authorized\"},\"paid\":true,\"payment_intent\":\"pi_3Sn5ZBIkWweOM9jA0W94oUre\",\"payment_method\":\"pm_1Sn5ZBIkWweOM9jA9KHaL1us\",\"payment_method_details\":{\"klarna\":{\"payer_details\":{\"address\":{\"country\":\"FR\"}},\"payment_method_category\":\"pay_in_installments\",\"preferred_locale\":\"fr-FR\"},\"type\":\"klarna\"},\"refunded\":false,\"source\":null,\"status\":\"succeeded\"}" | Z19: =+A19 -> AS-95339
A20: AS-96425 | B20: 202601 | C20: ["shopify_payments"] | E20: ES | G20: 0.21 | H20: 0.21 | I20: EUR | J20: 9.35 | K20: 53.9 | L20: 44.55 | M20: shopify_payments | N20: gid://shopify/Order/7444796768594 | O20: gid://shopify/OrderTransaction/8621926089042 | P20: shopify_payments | Q20: SALE | R20: SUCCESS | S20: 2026-01-20T23:06:06Z | T20: 53.9 | U20: EUR | V20: ch_3SrnzvIkWweOM9jA2o2Fd9Ms | W20: r0JL4gRiE4ixRFhK4oaqYZMwl | X20: pi_3SrnzvIkWweOM9jA23m58vDS | Y20: "{\"id\":\"pi_3SrnzvIkWweOM9jA23m58vDS\",\"object\":\"payment_intent\",\"amount\":5390,\"amount_capturable\":0,\"amount_received\":5390,\"canceled_at\":null,\"cancellation_reason\":null,\"capture_method\":\"automatic\",\"latest_charge\":{\"id\":\"ch_3SrnzvIkWweOM9jA2o2Fd9Ms\",\"object\":\"charge\",\"amount\":5390,\"application_fee\":\"fee_1SrnzwIkWweOM9jAzNqCFQss\",\"balance_transaction\":\"txn_3SrnzvIkWweOM9jA2QxEXDnB\",\"captured\":true,\"created\":1768950368,\"currency\":\"eur\",\"failure_code\":null,\"failure_message\":null,\"fraud_details\":{},\"livemode\":true,\"metadata\":{\"payment_id\":\"r0JL4gRiE4ixRFhK4oaqYZMwl\",\"payments_extension\":\"true\",\"payments_extension_type\":\"card\",\"reconciliation_flow\":\"payments_api\",\"shop_id\":\"751927347\"},\"outcome\":{\"advice_code\":null,\"network_advice_code\":null,\"network_decline_code\":null,\"network_status\":\"approved_by_network\",\"reason\":null,\"risk_level\":\"normal\",\"seller_message\":\"Payment complete.\",\"type\":\"authorized\"},\"paid\":true,\"payment_intent\":\"pi_3SrnzvIkWweOM9jA23m58vDS\",\"payment_method\":\"pm_1SrnzvIkWweOM9jAGNVDF70x\",\"payment_method_details\":{\"card\":{\"amount_authorized\":5390,\"authorization_code\":\"022927\",\"brand\":\"mastercard\",\"checks\":{\"address_line1_check\":null,\"address_postal_code_check\":null,\"cvc_check\":null},\"country\":\"ES\",\"description\":\"MasterCard New World Immediate Debit\",\"ds_transaction_id\":null,\"exp_month\":3,\"exp_year\":2028,\"extended_authorization\":{\"status\":\"disabled\"},\"fingerprint\":\"QN0PJH5wf7QrGAcg\",\"funding\":\"debit\",\"iin\":\"515896\",\"incremental_authorization\":{\"status\":\"unavailable\"},\"installments\":null,\"issuer\":\"BANCO SABADELL S.A.\",\"last4\":\"0000\",\"mandate\":null,\"moto\":false,\"multicapture\":{\"status\":\"unavailable\"},\"network\":\"mastercard\",\"network_token\":{\"used\":false},\"network_transaction_id\":\"TNWR8O5940120\",\"overcapture\":{\"maximum_amount_capturable\":5390,\"status\":\"unavailable\"},\"payment_account_reference\":\"50012H7RG2D9JJGVMWQ0ELU72GYVQ\",\"regulated_status\":\"unregulated\",\"three_d_secure\":null,\"wallet\":{\"apple_pay\":{\"type\":\"apple_pay\"},\"dynamic_last4\":\"6242\",\"type\":\"apple_pay\"}},\"type\":\"card\"},\"refunded\":false,\"source\":null,\"status\":\"succeeded\",\"mit_params\":{\"network_transaction_id\":\"TNWR8O5940120\"}},\"confirmation_method\":\"manual\",\"created\":1768950367,\"currency\":\"eur\",\"customer\":null,\"last_payment_error\":null,\"livemode\":true,\"metadata\":{\"payment_id\":\"r0JL4gRiE4ixRFhK4oaqYZMwl\",\"payments_extension\":\"true\",\"payments_extension_type\":\"card\",\"reconciliation_flow\":\"payments_api\",\"shop_id\":\"751927347\"},\"next_action\":null,\"payment_method\":\"pm_1SrnzvIkWweOM9jAGNVDF70x\",\"payment_method_types\":[\"card\"],\"source\":null,\"status\":\"succeeded\"}" | Z20: =+A20 -> AS-96425
A21: AS-96815 | B21: 202601 | C21: ["shopify_payments"] | E21: FR | G21: 0.2 | H21: 0.2 | I21: EUR | J21: 47.21 | K21: 283.23 | L21: 236.02 | M21: shopify_payments | N21: gid://shopify/Order/7495581958482 | O21: gid://shopify/OrderTransaction/8635358347602 | P21: shopify_payments | Q21: SALE | R21: FAILURE | S21: 2026-01-26T09:42:59Z | T21: 283.23 | U21: EUR | V21: ch_3StmK0IkWweOM9jA1agh7ZDV | W21: rxR7O83c0IVhDSzZBfpTSHZqU | X21: pi_3StmK0IkWweOM9jA1jCMm6W3 | Y21: "{\"id\":\"pi_3StmK0IkWweOM9jA1jCMm6W3\",\"object\":\"payment_intent\",\"amount\":28323,\"amount_capturable\":0,\"amount_received\":0,\"canceled_at\":null,\"cancellation_reason\":null,\"capture_method\":\"automatic\",\"latest_charge\":{\"id\":\"ch_3StmK0IkWweOM9jA1agh7ZDV\",\"object\":\"charge\",\"amount\":28323,\"application_fee\":null,\"balance_transaction\":null,\"captured\":false,\"created\":1769420582,\"currency\":\"eur\",\"failure_code\":\"card_declined\",\"failure_message\":\"Your card has insufficient funds.\",\"fraud_details\":{},\"livemode\":true,\"metadata\":{\"payment_id\":\"rxR7O83c0IVhDSzZBfpTSHZqU\",\"payments_extension\":\"true\",\"payments_extension_type\":\"card\",\"reconciliation_flow\":\"payments_api\",\"shop_id\":\"751927347\"},\"outcome\":{\"advice_code\":\"try_again_later\",\"network_advice_code\":\"02\",\"network_decline_code\":\"51\",\"network_status\":\"declined_by_network\",\"reason\":\"insufficient_funds\",\"risk_level\":\"normal\",\"seller_message\":\"The bank returned the decline code `insufficient_funds`.\",\"type\":\"issuer_declined\"},\"paid\":false,\"payment_intent\":\"pi_3StmK0IkWweOM9jA1jCMm6W3\",\"payment_method\":\"pm_1StmK0IkWweOM9jAWIuDWwmf\",\"payment_method_details\":{\"card\":{\"amount_authorized\":null,\"authorization_code\":null,\"brand\":\"visa\",\"checks\":{\"address_line1_check\":\"fail\",\"address_postal_code_check\":\"pass\",\"cvc_check\":\"pass\"},\"country\":\"FR\",\"description\":\"Visa Classic\",\"ds_transaction_id\":null,\"exp_month\":5,\"exp_year\":2028,\"extended_authorization\":{\"status\":\"disabled\"},\"fingerprint\":\"l4RhahC6bvbHioSF\",\"funding\":\"debit\",\"iin\":\"497355\",\"incremental_authorization\":{\"status\":\"unavailable\"},\"installments\":null,\"issuer\":\"SOCIETE GENERALE S.A.\",\"last4\":\"4655\",\"mandate\":null,\"moto\":false,\"multicapture\":{\"status\":\"unavailable\"},\"network\":\"visa\",\"network_token\":{\"used\":false},\"network_transaction_id\":\"486026349827322\",\"overcapture\":{\"maximum_amount_capturable\":28323,\"status\":\"unavailable\"},\"payment_account_reference\":\"V001AAG0000368400610000000000\",\"regulated_status\":\"unregulated\",\"three_d_secure\":null,\"wallet\":null},\"type\":\"card\"},\"refunded\":false,\"source\":null,\"status\":\"failed\",\"mit_params\":{\"network_transaction_id\":\"486026349827322\"}},\"confirmation_method\":\"manual\",\"created\":1769420580,\"currency\":\"eur\",\"customer\":null,\"last_payment_error\":{\"advice_code\":\"try_again_later\",\"charge\":\"ch_3StmK0IkWweOM9jA1agh7ZDV\",\"code\":\"card_declined\",\"decline_code\":\"insufficient_funds\",\"doc_url\":\"https:\\/\\/stripe.com\\/docs\\/error-codes\\/card-declined\",\"message\":\"Your card has insufficient funds.\",\"network_advice_code\":\"02\",\"network_decline_code\":\"51\",\"payment_method\":{\"id\":\"pm_1StmK0IkWweOM9jAWIuDWwmf\",\"object\":\"payment_method\",\"card\":{\"brand\":\"visa\",\"checks\":{\"address_line1_check\":\"fail\",\"address_postal_code_check\":\"pass\",\"cvc_check\":\"pass\"},\"country\":\"FR\",\"description\":\"Visa Classic\",\"display_brand\":\"visa\",\"exp_month\":5,\"exp_year\":2028,\"fingerprint\":\"l4RhahC6bvbHioSF\",\"funding\":\"debit\",\"generated_from\":null,\"iin\":\"497355\",\"issuer\":\"SOCIETE GENERALE S.A.\",\"last4\":\"4655\",\"network_token\":null,\"networks\":{\"available\":[\"visa\"],\"preferred\":null},\"payment_account_reference\":null,\"regulated_status\":\"unregulated\",\"three_d_secure_usage\":{\"supported\":true},\"wallet\":null},\"created\":1769420580,\"livemode\":true,\"metadata\":{},\"type\":\"card\"},\"type\":\"card_error\"},\"livemode\":true,\"metadata\":{\"payment_id\":\"rxR7O83c0IVhDSzZBfpTSHZqU\",\"payments_extension\":\"true\",\"payments_extension_type\":\"card\",\"reconciliation_flow\":\"payments_api\",\"shop_id\":\"751927347\"},\"next_action\":null,\"payment_method\":null,\"payment_method_types\":[\"card\"],\"source\":null,\"status\":\"requires_payment_method\"}" | Z21: =+A21 -> AS-96815
A22: AS-96815 | B22: 202601 | C22: ["shopify_payments"] | E22: FR | G22: 0.2 | H22: 0.2 | I22: EUR | J22: 47.21 | K22: 283.23 | L22: 236.02 | M22: shopify_payments | N22: gid://shopify/Order/7495581958482 | O22: gid://shopify/OrderTransaction/8635361263954 | P22: shopify_payments | Q22: SALE | R22: SUCCESS | S22: 2026-01-26T09:44:26Z | T22: 283.23 | U22: EUR | V22: ch_3StmLPIkWweOM9jA23pZq7H7 | W22: rasLLMLvcfsy8i3O0E9Y0ZmJN | X22: pi_3StmLPIkWweOM9jA2VNKx01m | Y22: "{\"id\":\"pi_3StmLPIkWweOM9jA2VNKx01m\",\"object\":\"payment_intent\",\"amount\":28323,\"amount_capturable\":0,\"amount_received\":28323,\"canceled_at\":null,\"cancellation_reason\":null,\"capture_method\":\"automatic\",\"latest_charge\":{\"id\":\"ch_3StmLPIkWweOM9jA23pZq7H7\",\"object\":\"charge\",\"amount\":28323,\"application_fee\":\"fee_1StmLrIkWweOM9jAhpvcLp71\",\"balance_transaction\":\"txn_3StmLPIkWweOM9jA2PemZHAq\",\"captured\":true,\"created\":1769420695,\"currency\":\"eur\",\"failure_code\":null,\"failure_message\":null,\"fraud_details\":{},\"livemode\":true,\"metadata\":{\"payment_id\":\"rasLLMLvcfsy8i3O0E9Y0ZmJN\",\"payments_extension\":\"true\",\"payments_extension_type\":\"card\",\"reconciliation_flow\":\"payments_api\",\"shop_id\":\"751927347\"},\"outcome\":{\"advice_code\":null,\"network_advice_code\":null,\"network_decline_code\":null,\"network_status\":\"approved_by_network\",\"reason\":null,\"risk_level\":\"normal\",\"seller_message\":\"Payment complete.\",\"type\":\"authorized\"},\"paid\":true,\"payment_intent\":\"pi_3StmLPIkWweOM9jA2VNKx01m\",\"payment_method\":\"pm_1StmLPIkWweOM9jAblt65oVH\",\"payment_method_details\":{\"card\":{\"amount_authorized\":28323,\"authorization_code\":\"298254\",\"brand\":\"visa\",\"checks\":{\"address_line1_check\":\"fail\",\"address_postal_code_check\":\"pass\",\"cvc_check\":\"pass\"},\"country\":\"FR\",\"description\":\"Visa Classic\",\"ds_transaction_id\":null,\"exp_month\":5,\"exp_year\":2028,\"extended_authorization\":{\"status\":\"disabled\"},\"fingerprint\":\"l4RhahC6bvbHioSF\",\"funding\":\"debit\",\"iin\":\"497355\",\"incremental_authorization\":{\"status\":\"unavailable\"},\"installments\":null,\"issuer\":\"SOCIETE GENERALE S.A.\",\"last4\":\"4655\",\"mandate\":null,\"moto\":false,\"multicapture\":{\"status\":\"unavailable\"},\"network\":\"visa\",\"network_token\":{\"used\":false},\"network_transaction_id\":\"486026350958523\",\"overcapture\":{\"maximum_amount_capturable\":28323,\"status\":\"unavailable\"},\"payment_account_reference\":\"V001AAG0000368400610000000000\",\"regulated_status\":\"unregulated\",\"three_d_secure\":{\"authentication_flow\":\"challenge\",\"electronic_commerce_indicator\":\"05\",\"exemption_indicator\":null,\"result\":\"authenticated\",\"result_reason\":null,\"transaction_id\":\"be7a8286-b7d5-42a5-96f2-1af5404d0b30\",\"version\":\"2.2.0\"},\"wallet\":null},\"type\":\"card\"},\"refunded\":false,\"source\":null,\"status\":\"succeeded\",\"mit_params\":{\"network_transaction_id\":\"486026350958523\"}},\"confirmation_method\":\"manual\",\"created\":1769420667,\"currency\":\"eur\",\"customer\":null,\"last_payment_error\":null,\"livemode\":true,\"metadata\":{\"payment_id\":\"rasLLMLvcfsy8i3O0E9Y0ZmJN\",\"payments_extension\":\"true\",\"payments_extension_type\":\"card\",\"reconciliation_flow\":\"payments_api\",\"shop_id\":\"751927347\"},\"next_action\":null,\"payment_method\":\"pm_1StmLPIkWweOM9jAblt65oVH\",\"payment_method_types\":[\"card\"],\"source\":null,\"status\":\"succeeded\"}" | Z22: =+A22 -> AS-96815
A23: AS-96146 | B23: 202601 | C23: ["paypal"] | E23: IT | G23: 0.22 | H23: 0.22 | I23: EUR | J23: 13.75 | K23: 76.23 | L23: 62.48 | M23: paypal | N23: gid://shopify/Order/7436385747282 | O23: gid://shopify/OrderTransaction/8611523789138 | P23: paypal | Q23: SALE | R23: SUCCESS | S23: 2026-01-17T14:00:55Z | T23: 76.23 | U23: EUR | V23: 0DV43619KL6524647 | W23: rnRUoYSRY9CdMGq3cXpamWsL1 | X23: 1CJ96774E1766125B | Y23: "{\"id\":\"1CJ96774E1766125B\",\"intent\":\"CAPTURE\",\"status\":\"COMPLETED\",\"payment_source\":{\"paypal\":{\"email_address\":\"chiara.giorgetti@alice.it\",\"account_id\":\"EBXWQKMLLYMGN\",\"account_status\":\"VERIFIED\",\"name\":{\"given_name\":\"Chiara\",\"surname\":\"Giorgetti\"},\"phone_number\":{\"national_number\":\"393384247353\"},\"address\":{\"address_line_1\":\"Via pascoli\",\"address_line_2\":\"19\",\"admin_area_2\":\"Sesto Fiorentino\",\"admin_area_1\":\"FI\",\"postal_code\":\"50019\",\"country_code\":\"IT\"}}},\"purchase_units\":[{\"reference_id\":\"default\",\"amount\":{\"currency_code\":\"EUR\",\"value\":\"76.23\",\"breakdown\":{\"item_total\":{\"currency_code\":\"EUR\",\"value\":\"84.70\"},\"shipping\":{\"currency_code\":\"EUR\",\"value\":\"0.00\"},\"handling\":{\"currency_code\":\"EUR\",\"value\":\"0.00\"},\"tax_total\":{\"currency_code\":\"EUR\",\"value\":\"0.00\"},\"insurance\":{\"currency_code\":\"EUR\",\"value\":\"0.00\"},\"shipping_discount\":{\"currency_code\":\"EUR\",\"value\":\"0.00\"},\"discount\":{\"currency_code\":\"EUR\",\"value\":\"8.47\"}}},\"payee\":{\"email_address\":\"info@artestaposters.com\",\"merchant_id\":\"CZQCEKGVW6QGG\",\"display_data\":{\"brand_name\":\"Artesta\"}},\"payment_instruction\":{\"disbursement_mode\":\"INSTANT\"},\"description\":\"Mont Blanc 2 - P\u00f3ster \\/ Sin marco \\/ 20x30\",\"custom_id\":\"{\\\"shop_id\\\":751927347,\\\"session_id\\\":\\\"rnRUoYSRY9CdMGq3cXpamWsL1\\\"}\",\"invoice_id\":\"rnRUoYSRY9CdMGq3cXpamWsL1\",\"soft_descriptor\":\"PAYPAL *ARTESTASTOR AR\",\"items\":[{\"name\":\"Mont Blanc 2 - P\u00f3ster \\/ Sin marco \\/ 20x30\",\"unit_amount\":{\"currency_code\":\"EUR\",\"value\":\"12.95\"},\"tax\":{\"currency_code\":\"EUR\",\"value\":\"0.00\"},\"quantity\":\"1\"},{\"name\":\"Forest - P\u00f3ster \\/ Sin marco \\/ 20x30\",\"unit_amount\":{\"currency_code\":\"EUR\",\"value\":\"12.95\"},\"tax\":{\"currency_code\":\"EUR\",\"value\":\"0.00\"},\"quantity\":\"1\"},{\"name\":\"Ens\u014d (on white background) - P\u00f3ster \\/ Sin marco \\/ 30x40\",\"unit_amount\":{\"currency_code\":\"EUR\",\"value\":\"19.95\"},\"tax\":{\"currency_code\":\"EUR\",\"value\":\"0.00\"},\"quantity\":\"1\"},{\"name\":\"Natureye - P\u00f3ster \\/ Sin marco \\/ 20x30\",\"unit_amount\":{\"currency_code\":\"EUR\",\"value\":\"12.95\"},\"tax\":{\"currency_code\":\"EUR\",\"value\":\"0.00\"},\"quantity\":\"1\"},{\"name\":\"Pretty coffee cups - P\u00f3ster \\/ Sin marco \\/ 20x30\",\"unit_amount\":{\"currency_code\":\"EUR\",\"value\":\"12.95\"},\"tax\":{\"currency_code\":\"EUR\",\"value\":\"0.00\"},\"quantity\":\"1\"},{\"name\":\"Surf Hut - P\u00f3ster \\/ Sin marco \\/ 20x30\",\"unit_amount\":{\"currency_code\":\"EUR\",\"value\":\"12.95\"},\"tax\":{\"currency_code\":\"EUR\",\"value\":\"0.00\"},\"quantity\":\"1\"}],\"shipping\":{\"name\":{\"full_name\":\"Chiara Giorgetti\"},\"address\":{\"address_line_1\":\"Via Giovanni Pascoli 19\",\"admin_area_2\":\"Sesto Fiorentino\",\"admin_area_1\":\"Firenze\",\"postal_code\":\"50019\",\"country_code\":\"IT\"}},\"supplementary_data\":{\"tax_nexus\":[]},\"payments\":{\"captures\":[{\"id\":\"0DV43619KL6524647\",\"status\":\"COMPLETED\",\"amount\":{\"currency_code\":\"EUR\",\"value\":\"76.23\"},\"final_capture\":true,\"disbursement_mode\":\"INSTANT\",\"seller_protection\":{\"status\":\"ELIGIBLE\",\"dispute_categories\":[\"ITEM_NOT_RECEIVED\",\"UNAUTHORIZED_TRANSACTION\"]},\"seller_receivable_breakdown\":{\"gross_amount\":{\"currency_code\":\"EUR\",\"value\":\"76.23\"},\"paypal_fee\":{\"currency_code\":\"EUR\",\"value\":\"2.56\"},\"net_amount\":{\"currency_code\":\"EUR\",\"value\":\"73.67\"}},\"invoice_id\":\"rnRUoYSRY9CdMGq3cXpamWsL1\",\"custom_id\":\"{\\\"shop_id\\\":751927347,\\\"session_id\\\":\\\"rnRUoYSRY9CdMGq3cXpamWsL1\\\"}\",\"links\":[{\"href\":\"https:\\/\\/api.paypal.com\\/v2\\/payments\\/captures\\/0DV43619KL6524647\",\"rel\":\"self\",\"method\":\"GET\"},{\"href\":\"https:\\/\\/api.paypal.com\\/v2\\/payments\\/captures\\/0DV43619KL6524647\\/refund\",\"rel\":\"refund\",\"method\":\"POST\"},{\"href\":\"https:\\/\\/api.paypal.com\\/v2\\/checkout\\/orders\\/1CJ96774E1766125B\",\"rel\":\"up\",\"method\":\"GET\"}],\"create_time\":\"2026-01-17T14:00:57Z\",\"update_time\":\"2026-01-17T14:00:57Z\"}]}}],\"payer\":{\"name\":{\"given_name\":\"Chiara\",\"surname\":\"Giorgetti\"},\"email_address\":\"chiara.giorgetti@alice.it\",\"payer_id\":\"EBXWQKMLLYMGN\",\"phone\":{\"phone_number\":{\"national_number\":\"393384247353\"}},\"address\":{\"address_line_1\":\"Via pascoli\",\"address_line_2\":\"19\",\"admin_area_2\":\"Sesto Fiorentino\",\"admin_area_1\":\"FI\",\"postal_code\":\"50019\",\"country_code\":\"IT\"}},\"create_time\":\"2026-01-17T14:00:16Z\",\"update_time\":\"2026-01-17T14:00:57Z\",\"links\":[{\"href\":\"https:\\/\\/api.paypal.com\\/v2\\/checkout\\/orders\\/1CJ96774E1766125B\",\"rel\":\"self\",\"method\":\"GET\"}]}" | Z23: =+A23 -> AS-96146
A24: AS-96280 | B24: 202601 | C24: ["shopify_payments"] | E24: ES | G24: 0.21 | H24: 0.21 | I24: EUR | J24: 21.23 | K24: 122.31 | L24: 101.08 | M24: shopify_payments | N24: gid://shopify/Order/7439884058962 | O24: gid://shopify/OrderTransaction/8615705018706 | P24: shopify_payments | Q24: SALE | R24: SUCCESS | S24: 2026-01-18T19:20:04Z | T24: 122.31 | U24: EUR | V24: ch_3Sr1W5IkWweOM9jA0ApbUO5g | W24: rTjzZjO1YIQi5PagTrLKR1kM7 | X24: pi_3Sr1W5IkWweOM9jA0pygEHfw | Y24: "{\"id\":\"pi_3Sr1W5IkWweOM9jA0pygEHfw\",\"object\":\"payment_intent\",\"amount\":12231,\"amount_capturable\":0,\"amount_received\":12231,\"canceled_at\":null,\"cancellation_reason\":null,\"capture_method\":\"automatic\",\"latest_charge\":{\"id\":\"ch_3Sr1W5IkWweOM9jA0ApbUO5g\",\"object\":\"charge\",\"amount\":12231,\"application_fee\":\"fee_1Sr1W6IkWweOM9jAq1j7zTG9\",\"balance_transaction\":\"txn_3Sr1W5IkWweOM9jA0iUwDgp1\",\"captured\":true,\"created\":1768764005,\"currency\":\"eur\",\"failure_code\":null,\"failure_message\":null,\"fraud_details\":{},\"livemode\":true,\"metadata\":{\"payment_id\":\"rTjzZjO1YIQi5PagTrLKR1kM7\",\"payments_extension\":\"true\",\"payments_extension_type\":\"card\",\"reconciliation_flow\":\"payments_api\",\"shop_id\":\"751927347\"},\"outcome\":{\"advice_code\":null,\"network_advice_code\":null,\"network_decline_code\":null,\"network_status\":\"approved_by_network\",\"reason\":null,\"risk_level\":\"normal\",\"seller_message\":\"Payment complete.\",\"type\":\"authorized\"},\"paid\":true,\"payment_intent\":\"pi_3Sr1W5IkWweOM9jA0pygEHfw\",\"payment_method\":\"pm_1Sr1W5IkWweOM9jAk1FiRkaj\",\"payment_method_details\":{\"card\":{\"amount_authorized\":12231,\"authorization_code\":\"920580\",\"brand\":\"visa\",\"checks\":{\"address_line1_check\":null,\"address_postal_code_check\":null,\"cvc_check\":null},\"country\":\"ES\",\"description\":\"Visa Platinum\",\"ds_transaction_id\":null,\"exp_month\":12,\"exp_year\":2031,\"extended_authorization\":{\"status\":\"disabled\"},\"fingerprint\":\"knVUtbiLohd5zynD\",\"funding\":\"credit\",\"iin\":\"482066\",\"incremental_authorization\":{\"status\":\"unavailable\"},\"installments\":null,\"issuer\":\"Sociedad Conjunta para la emision y gestion de medios de pago, e.f.c., s.a.\",\"last4\":\"0000\",\"mandate\":null,\"moto\":false,\"multicapture\":{\"status\":\"unavailable\"},\"network\":\"visa\",\"network_token\":{\"used\":false},\"network_transaction_id\":\"486018696056455\",\"overcapture\":{\"maximum_amount_capturable\":12231,\"status\":\"unavailable\"},\"payment_account_reference\":\"V0010013025204665368412850193\",\"regulated_status\":\"unregulated\",\"three_d_secure\":null,\"wallet\":{\"apple_pay\":{\"type\":\"apple_pay\"},\"dynamic_last4\":\"2692\",\"type\":\"apple_pay\"}},\"type\":\"card\"},\"refunded\":false,\"source\":null,\"status\":\"succeeded\",\"mit_params\":{\"network_transaction_id\":\"486018696056455\"}},\"confirmation_method\":\"manual\",\"created\":1768764005,\"currency\":\"eur\",\"customer\":null,\"last_payment_error\":null,\"livemode\":true,\"metadata\":{\"payment_id\":\"rTjzZjO1YIQi5PagTrLKR1kM7\",\"payments_extension\":\"true\",\"payments_extension_type\":\"card\",\"reconciliation_flow\":\"payments_api\",\"shop_id\":\"751927347\"},\"next_action\":null,\"payment_method\":\"pm_1Sr1W5IkWweOM9jAk1FiRkaj\",\"payment_method_types\":[\"card\"],\"source\":null,\"status\":\"succeeded\"}" | Z24: =+A24 -> AS-96280
... A26: AS-94938 | B26: 202601 | C26: ["shopify_payments"] | E26: FR | G26: 0.2 | H26: 0.2 | I26: EUR | J26: 6.32 | K26: 37.9 | L26: 31.58 | M26: shopify_payments | N26: gid://shopify/Order/7396723360082 | O26: gid://shopify/OrderTransaction/8572533702994 | P26: shopify_payments | Q26: SALE | R26: SUCCESS | S26: 2026-01-03T08:17:40Z | T26: 37.9 | U26: EUR | V26: ch_3SlQ1pIkWweOM9jA1lwz5Wn6 | W26: rqxXIma9iSpMmlE4BqLfz6Nty | X26: pi_3SlQ1pIkWweOM9jA1ywSWfvU | Y26: "{\"id\":\"pi_3SlQ1pIkWweOM9jA1ywSWfvU\",\"object\":\"payment_intent\",\"amount\":3790,\"amount_capturable\":0,\"amount_received\":3790,\"canceled_at\":null,\"cancellation_reason\":null,\"capture_method\":\"automatic\",\"latest_charge\":{\"id\":\"ch_3SlQ1pIkWweOM9jA1lwz5Wn6\",\"object\":\"charge\",\"amount\":3790,\"application_fee\":\"fee_1SlQ1qIkWweOM9jAzjejVLZJ\",\"balance_transaction\":\"txn_3SlQ1pIkWweOM9jA1r4qjK5j\",\"captured\":true,\"created\":1767428261,\"currency\":\"eur\",\"failure_code\":null,\"failure_message\":null,\"fraud_details\":{},\"livemode\":true,\"metadata\":{\"payment_id\":\"rqxXIma9iSpMmlE4BqLfz6Nty\",\"payments_extension\":\"true\",\"payments_extension_type\":\"card\",\"reconciliation_flow\":\"payments_api\",\"shop_id\":\"751927347\"},\"outcome\":{\"advice_code\":null,\"network_advice_code\":null,\"network_decline_code\":null,\"network_status\":\"approved_by_network\",\"reason\":null,\"risk_level\":\"normal\",\"seller_message\":\"Payment complete.\",\"type\":\"authorized\"},\"paid\":true,\"payment_intent\":\"pi_3SlQ1pIkWweOM9jA1ywSWfvU\",\"payment_method\":\"pm_1SlQ1pIkWweOM9jAeU7ftz9P\",\"payment_method_details\":{\"card\":{\"amount_authorized\":3790,\"authorization_code\":\"069564\",\"brand\":\"visa\",\"checks\":{\"address_line1_check\":null,\"address_postal_code_check\":null,\"cvc_check\":null},\"country\":\"FR\",\"description\":\"Visa Platinum\",\"ds_transaction_id\":null,\"exp_month\":5,\"exp_year\":2030,\"extended_authorization\":{\"status\":\"disabled\"},\"fingerprint\":\"J5wxQCbXxyJNB6cy\",\"funding\":\"debit\",\"iin\":\"455844\",\"incremental_authorization\":{\"status\":\"unavailable\"},\"installments\":null,\"issuer\":\"La Banque Postale\",\"last4\":\"0000\",\"mandate\":null,\"moto\":false,\"multicapture\":{\"status\":\"unavailable\"},\"network\":\"visa\",\"network_token\":{\"used\":false},\"network_transaction_id\":\"486003298616636\",\"overcapture\":{\"maximum_amount_capturable\":3790,\"status\":\"unavailable\"},\"payment_account_reference\":\"V001AADBP30000393530170000000\",\"regulated_status\":\"unregulated\",\"three_d_secure\":null,\"wallet\":{\"apple_pay\":{\"type\":\"apple_pay\"},\"dynamic_last4\":\"8827\",\"type\":\"apple_pay\"}},\"type\":\"card\"},\"refunded\":false,\"source\":null,\"status\":\"succeeded\",\"mit_params\":{\"network_transaction_id\":\"486003298616636\"}},\"confirmation_method\":\"manual\",\"created\":1767428261,\"currency\":\"eur\",\"customer\":null,\"last_payment_error\":null,\"livemode\":true,\"metadata\":{\"payment_id\":\"rqxXIma9iSpMmlE4BqLfz6Nty\",\"payments_extension\":\"true\",\"payments_extension_type\":\"card\",\"reconciliation_flow\":\"payments_api\",\"shop_id\":\"751927347\"},\"next_action\":null,\"payment_method\":\"pm_1SlQ1pIkWweOM9jAeU7ftz9P\",\"payment_method_types\":[\"card\"],\"source\":null,\"status\":\"succeeded\"}" | Z26: =+A26 -> AS-94938
A27: AS-96378 | B27: 202601 | C27: [] | D27: Claim, Logistics, UPS | E27: AT | G27: 0.2 | H27: 0 | I27: EUR | J27: 0 | K27: 0 | L27: 0 | M27: other | Z27: =+A27 -> AS-96378
A28: AS-95893 | B28: 202601 | C28: ["shopify_payments"] | E28: FR | G28: 0.2 | H28: 0.2 | I28: EUR | J28: 4.15 | K28: 24.9 | L28: 20.75 | M28: shopify_payments | N28: gid://shopify/Order/7427571253586 | O28: gid://shopify/OrderTransaction/8601149866322 | P28: shopify_payments | Q28: SALE | R28: SUCCESS | S28: 2026-01-14T08:52:43Z | T28: 24.9 | U28: EUR | V28: ch_3SpPomIkWweOM9jA0XVS93vK | W28: rdqGuhPvM7fRlW8I7WPirdyV3 | X28: pi_3SpPomIkWweOM9jA0EmOJLS8 | Y28: "{\"id\":\"pi_3SpPomIkWweOM9jA0EmOJLS8\",\"object\":\"payment_intent\",\"amount\":2490,\"amount_capturable\":0,\"amount_received\":2490,\"canceled_at\":null,\"cancellation_reason\":null,\"capture_method\":\"automatic\",\"latest_charge\":{\"id\":\"ch_3SpPomIkWweOM9jA0XVS93vK\",\"object\":\"charge\",\"amount\":2490,\"application_fee\":\"fee_1SpPopIkWweOM9jAcvH88HhB\",\"balance_transaction\":\"txn_3SpPomIkWweOM9jA0rtHAOSB\",\"captured\":true,\"created\":1768380766,\"currency\":\"eur\",\"failure_code\":null,\"failure_message\":null,\"fraud_details\":{},\"livemode\":true,\"metadata\":{\"payment_id\":\"rdqGuhPvM7fRlW8I7WPirdyV3\",\"payments_extension\":\"true\",\"payments_extension_type\":\"card\",\"reconciliation_flow\":\"payments_api\",\"shop_id\":\"751927347\"},\"outcome\":{\"advice_code\":null,\"network_advice_code\":null,\"network_decline_code\":null,\"network_status\":\"approved_by_network\",\"reason\":null,\"risk_level\":\"normal\",\"seller_message\":\"Payment complete.\",\"type\":\"authorized\"},\"paid\":true,\"payment_intent\":\"pi_3SpPomIkWweOM9jA0EmOJLS8\",\"payment_method\":\"pm_1SpPomIkWweOM9jAE5lh3BW2\",\"payment_method_details\":{\"card\":{\"amount_authorized\":2490,\"authorization_code\":\"639841\",\"brand\":\"mastercard\",\"checks\":{\"address_line1_check\":\"unavailable\",\"address_postal_code_check\":\"unavailable\",\"cvc_check\":\"pass\"},\"country\":\"FR\",\"description\":\"MasterCard Standard Card Immediate Debit\",\"ds_transaction_id\":null,\"exp_month\":9,\"exp_year\":2029,\"extended_authorization\":{\"status\":\"disabled\"},\"fingerprint\":\"VziFz7cSh1ltbV9k\",\"funding\":\"debit\",\"iin\":\"513770\",\"incremental_authorization\":{\"status\":\"unavailable\"},\"installments\":null,\"issuer\":\"CREDIT AGRICOLE S.A.\",\"last4\":\"2307\",\"mandate\":null,\"moto\":false,\"multicapture\":{\"status\":\"unavailable\"},\"network\":\"mastercard\",\"network_token\":{\"used\":false},\"network_transaction_id\":\"TCSEXG6PF0114\",\"overcapture\":{\"maximum_amount_capturable\":2490,\"status\":\"unavailable\"},\"payment_account_reference\":\"50014A1AI0E5IV0QG3BLT88KIQ14Y\",\"regulated_status\":\"unregulated\",\"three_d_secure\":{\"authentication_flow\":\"frictionless\",\"electronic_commerce_indicator\":\"06\",\"exemption_indicator\":null,\"result\":\"exempted\",\"result_reason\":null,\"transaction_id\":\"b3ac608b-8cad-4599-86a0-eeab408222f7\",\"version\":\"2.2.0\"},\"wallet\":null},\"type\":\"card\"},\"refunded\":false,\"source\":null,\"status\":\"succeeded\",\"mit_params\":{\"network_transaction_id\":\"TCSEXG6PF0114\"}},\"confirmation_method\":\"manual\",\"created\":1768380764,\"currency\":\"eur\",\"customer\":null,\"last_payment_error\":null,\"livemode\":true,\"metadata\":{\"payment_id\":\"rdqGuhPvM7fRlW8I7WPirdyV3\",\"payments_extension\":\"true\",\"payments_extension_type\":\"card\",\"reconciliation_flow\":\"payments_api\",\"shop_id\":\"751927347\"},\"next_action\":null,\"payment_method\":\"pm_1SpPomIkWweOM9jAE5lh3BW2\",\"payment_method_types\":[\"card\"],\"source\":null,\"status\":\"succeeded\"}" | Z28: =+A28 -> AS-95893
A29: AS-95688 | B29: 202601 | C29: [] | D29: Hannun | E29: ES | G29: 0.21 | H29: 0 | I29: EUR | J29: 3.32 | K29: 19.15 | L29: 15.83 | M29: other | Z29: =+A29 -> AS-95688
A30: AS-96573 | B30: 202601 | C30: ["shopify_payments"] | E30: ES | G30: 0.21 | H30: 0.21 | I30: EUR | J30: 10.23 | K30: 58.95 | L30: 48.72 | M30: shopify_payments | N30: gid://shopify/Order/7489115717970 | O30: gid://shopify/OrderTransaction/8627298140498 | P30: shopify_payments | Q30: SALE | R30: FAILURE | S30: 2026-01-23T08:46:39Z | T30: 58.95 | U30: EUR | V30: ch_3Ssg0qIkWweOM9jA2M83Mn8J | W30: ri5uVzCSQy66ymDlvbXwzcJPm | X30: pi_3Ssg0qIkWweOM9jA2179yyPC | Y30: "{\"id\":\"pi_3Ssg0qIkWweOM9jA2179yyPC\",\"object\":\"payment_intent\",\"amount\":5895,\"amount_capturable\":0,\"amount_received\":0,\"canceled_at\":null,\"cancellation_reason\":null,\"capture_method\":\"automatic\",\"latest_charge\":{\"id\":\"ch_3Ssg0qIkWweOM9jA2M83Mn8J\",\"object\":\"charge\",\"amount\":5895,\"application_fee\":null,\"balance_transaction\":null,\"captured\":false,\"created\":1769158052,\"currency\":\"eur\",\"failure_code\":\"card_declined\",\"failure_message\":\"Your card was declined.\",\"fraud_details\":{},\"livemode\":true,\"metadata\":{\"payment_id\":\"ri5uVzCSQy66ymDlvbXwzcJPm\",\"payments_extension\":\"true\",\"payments_extension_type\":\"card\",\"reconciliation_flow\":\"payments_api\",\"shop_id\":\"751927347\"},\"outcome\":{\"advice_code\":\"do_not_try_again\",\"network_advice_code\":\"03\",\"network_decline_code\":\"83\",\"network_status\":\"declined_by_network\",\"reason\":\"do_not_honor\",\"risk_level\":\"normal\",\"seller_message\":\"The bank returned the decline code `do_not_honor`.\",\"type\":\"issuer_declined\"},\"paid\":false,\"payment_intent\":\"pi_3Ssg0qIkWweOM9jA2179yyPC\",\"payment_method\":\"pm_1Ssg0qIkWweOM9jAFcQif5WM\",\"payment_method_details\":{\"card\":{\"amount_authorized\":null,\"authorization_code\":null,\"brand\":\"mastercard\",\"checks\":{\"address_line1_check\":\"unavailable\",\"address_postal_code_check\":\"unavailable\",\"cvc_check\":null},\"country\":\"ES\",\"description\":\"MasterCard New World Immediate Debit\",\"ds_transaction_id\":null,\"exp_month\":4,\"exp_year\":2030,\"extended_authorization\":{\"status\":\"disabled\"},\"fingerprint\":\"qVy2tfLcXMiwPjeF\",\"funding\":\"debit\",\"iin\":\"540205\",\"incremental_authorization\":{\"status\":\"unavailable\"},\"installments\":null,\"issuer\":\"BANCO SABADELL S.A.\",\"last4\":\"1016\",\"mandate\":null,\"moto\":false,\"multicapture\":{\"status\":\"unavailable\"},\"network\":\"mastercard\",\"network_token\":{\"used\":false},\"network_transaction_id\":\"TNWUVTO1L0123\",\"overcapture\":{\"maximum_amount_capturable\":5895,\"status\":\"unavailable\"},\"payment_account_reference\":\"50015INGHZU30WE8RJT9ATRV41XSI\",\"regulated_status\":\"unregulated\",\"three_d_secure\":{\"authentication_flow\":\"challenge\",\"electronic_commerce_indicator\":\"02\",\"exemption_indicator\":null,\"result\":\"authenticated\",\"result_reason\":null,\"transaction_id\":\"e37468f7-2885-471b-90b5-c10bbad05b17\",\"version\":\"2.2.0\"},\"wallet\":null},\"type\":\"card\"},\"refunded\":false,\"source\":null,\"status\":\"failed\",\"mit_params\":{\"network_transaction_id\":\"TNWUVTO1L0123\"}},\"confirmation_method\":\"manual\",\"created\":1769158000,\"currency\":\"eur\",\"customer\":null,\"last_payment_error\":{\"advice_code\":\"do_not_try_again\",\"charge\":\"ch_3Ssg0qIkWweOM9jA2M83Mn8J\",\"code\":\"card_declined\",\"decline_code\":\"do_not_honor\",\"doc_url\":\"https:\\/\\/stripe.com\\/docs\\/error-codes\\/card-declined\",\"message\":\"Your card was declined.\",\"network_advice_code\":\"03\",\"network_decline_code\":\"83\",\"payment_method\":{\"id\":\"pm_1Ssg0qIkWweOM9jAFcQif5WM\",\"object\":\"payment_method\",\"card\":{\"brand\":\"mastercard\",\"checks\":{\"address_line1_check\":\"unavailable\",\"address_postal_code_check\":\"unavailable\",\"cvc_check\":null},\"country\":\"ES\",\"description\":\"MasterCard New World Immediate Debit\",\"display_brand\":\"mastercard\",\"exp_month\":4,\"exp_year\":2030,\"fingerprint\":\"qVy2tfLcXMiwPjeF\",\"funding\":\"debit\",\"generated_from\":null,\"iin\":\"540205\",\"issuer\":\"BANCO SABADELL S.A.\",\"last4\":\"1016\",\"network_token\":null,\"networks\":{\"available\":[\"mastercard\"],\"preferred\":null},\"payment_account_reference\":null,\"regulated_status\":\"unregulated\",\"three_d_secure_usage\":{\"supported\":true},\"wallet\":null},\"created\":1769158000,\"livemode\":true,\"metadata\":{},\"type\":\"card\"},\"type\":\"card_error\"},\"livemode\":true,\"metadata\":{\"payment_id\":\"ri5uVzCSQy66ymDlvbXwzcJPm\",\"payments_extension\":\"true\",\"payments_extension_type\":\"card\",\"reconciliation_flow\":\"payments_api\",\"shop_id\":\"751927347\"},\"next_action\":null,\"payment_method\":null,\"payment_method_types\":[\"card\"],\"source\":null,\"status\":\"requires_payment_method\"}" | Z30: =+A30 -> AS-96573
A31: AS-96573 | B31: 202601 | C31: ["shopify_payments"] | E31: ES | G31: 0.21 | H31: 0.21 | I31: EUR | J31: 10.23 | K31: 58.95 | L31: 48.72 | M31: shopify_payments | N31: gid://shopify/Order/7489115717970 | O31: gid://shopify/OrderTransaction/8627302760786 | P31: shopify_payments | Q31: SALE | R31: SUCCESS | S31: 2026-01-23T08:49:16Z | T31: 58.95 | U31: EUR | V31: ch_3Ssg3NIkWweOM9jA1Oqptpcf | W31: r2GSelaM79zl15DNCcqeooxr8 | X31: pi_3Ssg3NIkWweOM9jA119OhF3Y | Y31: "{\"id\":\"pi_3Ssg3NIkWweOM9jA119OhF3Y\",\"object\":\"payment_intent\",\"amount\":5895,\"amount_capturable\":0,\"amount_received\":5895,\"canceled_at\":null,\"cancellation_reason\":null,\"capture_method\":\"automatic\",\"latest_charge\":{\"id\":\"ch_3Ssg3NIkWweOM9jA1Oqptpcf\",\"object\":\"charge\",\"amount\":5895,\"application_fee\":\"fee_1Ssg3PIkWweOM9jAm6HiIDpD\",\"balance_transaction\":\"txn_3Ssg3NIkWweOM9jA1qlBv7E3\",\"captured\":true,\"created\":1769158158,\"currency\":\"eur\",\"failure_code\":null,\"failure_message\":null,\"fraud_details\":{},\"livemode\":true,\"metadata\":{\"payment_id\":\"r2GSelaM79zl15DNCcqeooxr8\",\"payments_extension\":\"true\",\"payments_extension_type\":\"card\",\"reconciliation_flow\":\"payments_api\",\"shop_id\":\"751927347\"},\"outcome\":{\"advice_code\":null,\"network_advice_code\":null,\"network_decline_code\":null,\"network_status\":\"approved_by_network\",\"reason\":null,\"risk_level\":\"normal\",\"seller_message\":\"Payment complete.\",\"type\":\"authorized\"},\"paid\":true,\"payment_intent\":\"pi_3Ssg3NIkWweOM9jA119OhF3Y\",\"payment_method\":\"pm_1Ssg3NIkWweOM9jASD9m248g\",\"payment_method_details\":{\"card\":{\"amount_authorized\":5895,\"authorization_code\":\"477829\",\"brand\":\"mastercard\",\"checks\":{\"address_line1_check\":\"unavailable\",\"address_postal_code_check\":\"unavailable\",\"cvc_check\":null},\"country\":\"ES\",\"description\":\"MasterCard New World Immediate Debit\",\"ds_transaction_id\":null,\"exp_month\":4,\"exp_year\":2031,\"extended_authorization\":{\"status\":\"disabled\"},\"fingerprint\":\"30GOJyqJUFeTPvUn\",\"funding\":\"debit\",\"iin\":\"540205\",\"incremental_authorization\":{\"status\":\"unavailable\"},\"installments\":null,\"issuer\":\"BANCO SABADELL S.A.\",\"last4\":\"1024\",\"mandate\":null,\"moto\":false,\"multicapture\":{\"status\":\"unavailable\"},\"network\":\"mastercard\",\"network_token\":{\"used\":false},\"network_transaction_id\":\"TNWWNDA2K0123\",\"overcapture\":{\"maximum_amount_capturable\":5895,\"status\":\"unavailable\"},\"payment_account_reference\":\"50019I3HY0WIJSH5WMONN1497LH06\",\"regulated_status\":\"unregulated\",\"three_d_secure\":null,\"wallet\":null},\"type\":\"card\"},\"refunded\":false,\"source\":null,\"status\":\"succeeded\",\"mit_params\":{\"network_transaction_id\":\"TNWWNDA2K0123\"}},\"confirmation_method\":\"manual\",\"created\":1769158157,\"currency\":\"eur\",\"customer\":null,\"last_payment_error\":null,\"livemode\":true,\"metadata\":{\"payment_id\":\"r2GSelaM79zl15DNCcqeooxr8\",\"payments_extension\":\"true\",\"payments_extension_type\":\"card\",\"reconciliation_flow\":\"payments_api\",\"shop_id\":\"751927347\"},\"next_action\":null,\"payment_method\":\"pm_1Ssg3NIkWweOM9jASD9m248g\",\"payment_method_types\":[\"card\"],\"source\":null,\"status\":\"succeeded\"}" | Z31: =+A31 -> AS-96573
